{
  "type": "Feature",
  "properties": {
    "addr:full":"16-565 Old Volcano Rd Keaau HI 96749",
    "addr:housenumber":"16-565",
    "addr:postcode":"96749",
    "addr:street":"Old Volcano Rd",
    "iso:country":"US",
    "sg:address":"16-565 Old Volcano Rd",
    "sg:city":"Keaau",
    "sg:classifiers":[
        {
            "category":"Restaurant",
            "type":"Food & Drink"
        }
    ],
    "sg:menulink":"http://www.allmenus.com/hi/keaau-mountain-view/202807-mcdonalds/menu/",
    "sg:postcode":"96749",
    "sg:province":"HI",
    "sg:tags":[
        "burger",
        "american"
    ],
    "wof:name":"McDonald's",
    "wof:placetype":"venue"
},
  "geometry": {"coordinates":[-155.03921299999999,19.622371],"type":"Point"}
}