{
  "type": "Feature",
  "properties": {
    "addr:full":"439 Kalihi St Honolulu HI 96819",
    "addr:housenumber":"439",
    "addr:postcode":"96819",
    "addr:street":"Kalihi St",
    "iso:country":"US",
    "sg:address":"439 Kalihi St",
    "sg:city":"Honolulu",
    "sg:classifiers":[
        {
            "category":"Wholesale",
            "subcategory":"Poultry",
            "type":"Manufacturing & Wholesale Goods"
        }
    ],
    "sg:phone":"+1 808 841 7695",
    "sg:postcode":"96819",
    "sg:province":"HI",
    "sg:tags":[
        "eggs"
    ],
    "wof:name":"Associated Producers Corp",
    "wof:placetype":"venue"
},
  "geometry": {"coordinates":[-157.880537,21.325738],"type":"Point"}
}