{
  "type": "Feature",
  "properties": {
    "iso:country":"US",
    "sg:address":"1510 Evelyn Ln",
    "sg:city":"Honolulu",
    "sg:classifiers":[
        {
            "category":"Social Services",
            "type":"Services"
        }
    ],
    "sg:phone":"+1 808 945 7710",
    "sg:postcode":"96822",
    "sg:province":"HI",
    "sg:tags":[
        "referral"
    ],
    "wof:name":"Government - Palau Med",
    "wof:placetype":"venue"
},
  "geometry": {"coordinates":[-157.828273,21.300014],"type":"Point"}
}