{
  "type": "Feature",
  "properties": {
    "iso:country":"US",
    "sg:address":"1066 Mamalahoa Hwy",
    "sg:city":"Kamuela",
    "sg:classifiers":[
        {
            "category":"Shopping",
            "subcategory":"Clothing, Apparel, & Fashions",
            "type":"Retail Goods"
        }
    ],
    "sg:phone":"+1 808 881 8206",
    "sg:postcode":"96743",
    "sg:province":"HI",
    "wof:name":"Coconut Girl Clothing Co",
    "wof:placetype":"venue"
},
  "geometry": {"coordinates":[-155.66504900000001,20.023663],"type":"Point"}
}