{
  "type": "Feature",
  "properties": {
    "iso:country":"US",
    "sg:address":"712 Farrington Hwy",
    "sg:city":"Waipahu",
    "sg:classifiers":[
        {
            "category":"Banks & Credit Unions",
            "subcategory":"Bank",
            "type":"Services"
        }
    ],
    "sg:phone":"+1 808 671 1731",
    "sg:postcode":"96797",
    "sg:province":"HI",
    "sg:tags":[
        "state",
        "commercial"
    ],
    "wof:name":"Bank Of Hawaii",
    "wof:placetype":"venue"
},
  "geometry": {"coordinates":[-158.006519,21.383668],"type":"Point"}
}