{
  "type": "Feature",
  "properties": {
    "addr:full":"670 Worchester Ave Honolulu HI 96818",
    "addr:housenumber":"670",
    "addr:postcode":"96818",
    "addr:street":"Worchester Ave",
    "iso:country":"US",
    "sg:address":"670 Worchester Ave",
    "sg:city":"Honolulu",
    "sg:classifiers":[
        {
            "category":"Government",
            "subcategory":"Office",
            "type":"Public Place"
        }
    ],
    "sg:phone":"+1 808 422 1622",
    "sg:postcode":"96818",
    "sg:province":"HI",
    "sg:tags":[
        "transportation"
    ],
    "wof:name":"FAA Admnstration Hawaii-Hickam",
    "wof:placetype":"venue"
},
  "geometry": {"coordinates":[-157.92937900000001,21.317944],"type":"Point"}
}