{
  "type": "Feature",
  "properties": {
    "addr:full":"1560 Kanunu St Honolulu HI 96814",
    "addr:housenumber":"1560",
    "addr:postcode":"96814",
    "addr:street":"Kanunu St",
    "iso:country":"US",
    "sg:address":"1560 Kanunu St",
    "sg:city":"Honolulu",
    "sg:classifiers":[
        {
            "category":"Food & Beverages",
            "subcategory":"Specialty",
            "type":"Retail Goods"
        }
    ],
    "sg:phone":"+1 808 955 5266",
    "sg:postcode":"96814",
    "sg:province":"HI",
    "sg:tags":[
        "health",
        "diet"
    ],
    "wof:name":"Camstar Office",
    "wof:placetype":"venue"
},
  "geometry": {"coordinates":[-157.84103200000001,21.295437],"type":"Point"}
}