{
  "type": "Feature",
  "properties": {
    "iso:country":"US",
    "sg:address":"1349 Miloiki St",
    "sg:city":"Honolulu",
    "sg:classifiers":[
        {
            "category":"Communications",
            "subcategory":"Film & Video Production",
            "type":"Services"
        }
    ],
    "sg:phone":"+1 808 396 8998",
    "sg:postcode":"96825",
    "sg:province":"HI",
    "sg:tags":[
        "taping"
    ],
    "sg:website":"www.cocopalmpictures.com",
    "wof:name":"Coco Palm Pictures",
    "wof:placetype":"venue"
},
  "geometry": {"coordinates":[-157.682523,21.308106],"type":"Point"}
}