{
  "type": "Feature",
  "properties": {
    "iso:country":"US",
    "sg:address":"111 Holua Rd",
    "sg:city":"Kailua Kona",
    "sg:classifiers":[
        {
            "category":"Organizations",
            "subcategory":"Religious Organization",
            "type":"Services"
        }
    ],
    "sg:phone":"+1 808 322 0808",
    "sg:postcode":"96740",
    "sg:province":"HI",
    "sg:tags":[
        "house",
        "retreat"
    ],
    "wof:name":"Paradise Point",
    "wof:placetype":"venue"
},
  "geometry": {"coordinates":[-155.96314699999999,19.563943],"type":"Point"}
}