{
  "type": "Feature",
  "properties": {
    "iso:country":"US",
    "sg:address":"1255 Waiua Pl",
    "sg:city":"Aiea",
    "sg:classifiers":[
        {
            "category":"Building & Trades",
            "subcategory":"Construction",
            "type":"Services"
        }
    ],
    "sg:phone":"+1 808 487 1041",
    "sg:postcode":"96701",
    "sg:province":"HI",
    "sg:tags":[
        "contractor"
    ],
    "wof:name":"Quality Design Build",
    "wof:placetype":"venue"
},
  "geometry": {"coordinates":[-157.90094300000001,21.375149],"type":"Point"}
}