{
  "type": "Feature",
  "properties": {
    "iso:country":"US",
    "sg:address":"1151 Hoike Way",
    "sg:city":"Kapolei",
    "sg:classifiers":[
        {
            "category":"Wholesale",
            "subcategory":"Machinery & Supplies",
            "type":"Manufacturing & Wholesale Goods"
        }
    ],
    "sg:phone":"+1 808 478 3560",
    "sg:postcode":"96707",
    "sg:province":"HI",
    "sg:tags":[
        "industrial",
        "retail"
    ],
    "wof:name":"Industrial Supply Co LLC",
    "wof:placetype":"venue"
},
  "geometry": {"coordinates":[-158.086645,21.366298],"type":"Point"}
}