{
  "type": "Feature",
  "properties": {
    "iso:country":"US",
    "sg:address":"2046 S King St",
    "sg:city":"Honolulu",
    "sg:classifiers":[
        {
            "category":"Real Estate",
            "subcategory":"Architect",
            "type":"Services"
        }
    ],
    "sg:phone":"+1 808 949 4080",
    "sg:postcode":"96826",
    "sg:province":"HI",
    "wof:name":"PMT Architecture Inc",
    "wof:placetype":"venue"
},
  "geometry": {"coordinates":[-157.82996199999999,21.2949],"type":"Point"}
}