{
  "type": "Feature",
  "properties": {
    "addr:full":"647 N Kainalu Dr Kailua HI 96734",
    "addr:housenumber":"647",
    "addr:postcode":"96734",
    "addr:street":"N Kainalu Dr",
    "iso:country":"US",
    "sg:address":"647 N Kainalu Dr",
    "sg:city":"Kailua",
    "sg:classifiers":[
        {
            "category":"Building & Trades",
            "subcategory":"Construction",
            "type":"Services"
        }
    ],
    "sg:phone":"+1 808 261 7919",
    "sg:postcode":"96734",
    "sg:province":"HI",
    "sg:tags":[
        "house"
    ],
    "wof:name":"Mark Librie Gen Bldr",
    "wof:placetype":"venue"
},
  "geometry": {"coordinates":[-157.748099,21.411385],"type":"Point"}
}