{
  "type": "Feature",
  "properties": {
    "iso:country":"US",
    "sg:address":"50 E Puainako St",
    "sg:city":"Hilo",
    "sg:classifiers":[
        {
            "category":"Personal",
            "subcategory":"Beauty Salon",
            "type":"Services"
        }
    ],
    "sg:phone":"+1 808 981 5459",
    "sg:postcode":"96720",
    "sg:province":"HI",
    "wof:name":"Lani's Beauty Salon",
    "wof:placetype":"venue"
},
  "geometry": {"coordinates":[-155.067137,19.694949],"type":"Point"}
}