{
  "type": "Feature",
  "properties": {
    "iso:country":"US",
    "sg:address":"2143 Eluwene St",
    "sg:city":"Honolulu",
    "sg:classifiers":[
        {
            "category":"Building & Trades",
            "subcategory":"Construction",
            "type":"Services"
        }
    ],
    "sg:phone":"+1 808 847 6265",
    "sg:postcode":"96819",
    "sg:province":"HI",
    "sg:tags":[
        "roofing",
        "contractor"
    ],
    "wof:name":"R S Toyama Roofing Svc",
    "wof:placetype":"venue"
},
  "geometry": {"coordinates":[-157.883062,21.33067],"type":"Point"}
}