{
  "type": "Feature",
  "properties": {
    "iso:country":"US",
    "sg:address":"87-1978 Farrington Hwy",
    "sg:city":"Waianae",
    "sg:classifiers":[
        {
            "category":"Restaurant",
            "type":"Food & Drink"
        }
    ],
    "sg:menulink":"http://www.allmenus.com/hi/waianae/198256-kfc---kentucky-fried-chicken/menu/",
    "sg:phone":"+1 808 668 1030",
    "sg:postcode":"96792",
    "sg:province":"HI",
    "sg:tags":[
        "american",
        "chicken"
    ],
    "wof:name":"KFC - Kentucky Fried Chicken",
    "wof:placetype":"venue"
},
  "geometry": {"coordinates":[-158.152512,21.388718],"type":"Point"}
}