{
  "type": "Feature",
  "properties": {
    "iso:country":"US",
    "sg:address":"209 Lilipuna Rd",
    "sg:city":"Kaneohe",
    "sg:classifiers":[
        {
            "category":"Professional",
            "subcategory":"Business Services",
            "type":"Services"
        }
    ],
    "sg:phone":"+1 808 247 5339",
    "sg:postcode":"96744",
    "sg:province":"HI",
    "sg:tags":[
        "translator",
        "interpreter"
    ],
    "wof:name":"Korean-English Interpreter",
    "wof:placetype":"venue"
},
  "geometry": {"coordinates":[-157.80143799999999,21.422832],"type":"Point"}
}