{
  "type": "Feature",
  "properties": {
    "iso:country":"US",
    "sg:address":"999 Bishop St",
    "sg:city":"Honolulu",
    "sg:classifiers":[
        {
            "category":"Professional",
            "subcategory":"Lawyer & Legal Services",
            "type":"Services"
        }
    ],
    "sg:phone":"+1 808 523 0303",
    "sg:postcode":"96813",
    "sg:province":"HI",
    "wof:name":"Ganley Paul Attorney At Law",
    "wof:placetype":"venue"
},
  "geometry": {"coordinates":[-157.86222900000001,21.307997],"type":"Point"}
}