{
  "type": "Feature",
  "properties": {
    "iso:country":"US",
    "sg:address":"2256 Komo Mai Dr",
    "sg:city":"Pearl City",
    "sg:classifiers":[
        {
            "category":"Organizations",
            "subcategory":"Labor Organization",
            "type":"Services"
        }
    ],
    "sg:phone":"+1 808 455 9329",
    "sg:postcode":"96782",
    "sg:province":"HI",
    "wof:name":"Teamsters Local",
    "wof:placetype":"venue"
},
  "geometry": {"coordinates":[-157.954756,21.428332],"type":"Point"}
}