{
  "type": "Feature",
  "properties": {
    "iso:country":"US",
    "sg:address":"1760 Nalani St",
    "sg:city":"Honolulu",
    "sg:classifiers":[
        {
            "category":"Organizations",
            "subcategory":"Religious Organization",
            "type":"Services"
        }
    ],
    "sg:phone":"+1 808 845 2812",
    "sg:postcode":"96819",
    "sg:province":"HI",
    "wof:name":"Ka Hale Hoano Hou O Ke Akua",
    "wof:placetype":"venue"
},
  "geometry": {"coordinates":[-157.869011,21.340448],"type":"Point"}
}