{
  "type": "Feature",
  "properties": {
    "addr:full":"32 Ulili St Kaunakakai HI 96720",
    "addr:housenumber":"32",
    "addr:postcode":"96720",
    "addr:street":"Ulili St",
    "iso:country":"US",
    "sg:address":"32 Ulili St",
    "sg:city":"Kaunakakai",
    "sg:classifiers":[
        {
            "category":"Utilities",
            "subcategory":"Electric",
            "type":"Services"
        }
    ],
    "sg:phone":"+1 808 553 3234",
    "sg:postcode":"96720",
    "sg:province":"HI",
    "sg:tags":[
        "company"
    ],
    "wof:name":"Maui Electric Co LTD",
    "wof:placetype":"venue"
},
  "geometry": {"coordinates":[-155.09653299999999,19.716803],"type":"Point"}
}