{
  "type": "Feature",
  "properties": {
    "addr:full":"1199 Auina Rd Pahoa HI 96778",
    "addr:housenumber":"1199",
    "addr:postcode":"96778",
    "addr:street":"Auina Rd",
    "iso:country":"US",
    "sg:address":"1199 Auina Rd",
    "sg:city":"Pahoa",
    "sg:classifiers":[
        {
            "category":"Farming",
            "subcategory":"Nursery",
            "type":"Manufacturing & Wholesale Goods"
        }
    ],
    "sg:phone":"+1 808 965 8498",
    "sg:postcode":"96778",
    "sg:province":"HI",
    "sg:tags":[
        "ornamental"
    ],
    "wof:name":"Puna Makai Nursery Inc",
    "wof:placetype":"venue"
},
  "geometry": {"coordinates":[-154.94486000000001,19.51694],"type":"Point"}
}