{
  "type": "Feature",
  "properties": {
    "iso:country":"US",
    "sg:address":"307 Farrington Hwy",
    "sg:city":"Waipahu",
    "sg:classifiers":[
        {
            "category":"Bars & Pubs",
            "type":"Food & Drink"
        }
    ],
    "sg:phone":"+1 808 677 6888",
    "sg:postcode":"96797",
    "sg:province":"HI",
    "sg:tags":[
        "lounge",
        "cocktail"
    ],
    "wof:name":"Club Best Friend",
    "wof:placetype":"venue"
},
  "geometry": {"coordinates":[-158.018743,21.380031],"type":"Point"}
}