{
  "type": "Feature",
  "properties": {
    "addr:full":"5873 Walua Rd Kailua Kona HI 96740",
    "addr:housenumber":"5873",
    "addr:postcode":"96740",
    "addr:street":"Walua Rd",
    "iso:country":"US",
    "sg:address":"5873 Walua Rd",
    "sg:city":"Kailua Kona",
    "sg:classifiers":[
        {
            "category":"Real Estate",
            "subcategory":"Real Estate Agent",
            "type":"Services"
        }
    ],
    "sg:phone":"+1 808 329 2374",
    "sg:postcode":"96740",
    "sg:province":"HI",
    "wof:name":"Kona Mansions V Condominium",
    "wof:placetype":"venue"
},
  "geometry": {"coordinates":[-155.986062,19.629349],"type":"Point"}
}