{
  "type": "Feature",
  "properties": {
    "iso:country":"US",
    "sg:address":"129 Mikiola Dr",
    "sg:city":"Kaneohe",
    "sg:classifiers":[
        {
            "category":"Real Estate",
            "subcategory":"Real Estate Agent",
            "type":"Services"
        }
    ],
    "sg:phone":"+1 808 235 1890",
    "sg:postcode":"96744",
    "sg:province":"HI",
    "sg:tags":[
        "management"
    ],
    "wof:name":"R & R Of Hawaii Inc",
    "wof:placetype":"venue"
},
  "geometry": {"coordinates":[-157.77357900000001,21.409341],"type":"Point"}
}