{
  "type": "Feature",
  "properties": {
    "addr:full":"2371 Jennie St Honolulu HI 96819",
    "addr:housenumber":"2371",
    "addr:postcode":"96819",
    "addr:street":"Jennie St",
    "iso:country":"US",
    "sg:address":"2371 Jennie St",
    "sg:city":"Honolulu",
    "sg:classifiers":[
        {
            "category":"Professional",
            "subcategory":"Accounting & Tax Preparation",
            "type":"Services"
        }
    ],
    "sg:phone":"+1 808 847 4974",
    "sg:postcode":"96819",
    "sg:province":"HI",
    "sg:tags":[
        "return"
    ],
    "wof:name":"Less Tax Inc",
    "wof:placetype":"venue"
},
  "geometry": {"coordinates":[-157.86222599999999,21.34811],"type":"Point"}
}