{
  "type": "Feature",
  "properties": {
    "iso:country":"US",
    "sg:address":"1085 Puhau St",
    "sg:city":"Hilo",
    "sg:classifiers":[
        {
            "category":"Building & Trades",
            "subcategory":"Construction",
            "type":"Services"
        }
    ],
    "sg:phone":"+1 808 959 4627",
    "sg:postcode":"96720",
    "sg:province":"HI",
    "sg:tags":[
        "hanging",
        "contractor"
    ],
    "wof:name":"Jesses Painting",
    "wof:placetype":"venue"
},
  "geometry": {"coordinates":[-155.104724,19.677609],"type":"Point"}
}