{
  "type": "Feature",
  "properties": {
    "addr:full":"3300 Kuhio Hwy Lihue HI 96766",
    "addr:housenumber":"3300",
    "addr:postcode":"96766",
    "addr:street":"Kuhio Hwy",
    "iso:country":"US",
    "sg:address":"3300 Kuhio Hwy",
    "sg:city":"Lihue",
    "sg:classifiers":[
        {
            "category":"Shopping",
            "subcategory":"Department Store",
            "type":"Retail Goods"
        }
    ],
    "sg:phone":"+1 808 246 1599",
    "sg:postcode":"96766",
    "sg:province":"HI",
    "sg:tags":[
        "discount"
    ],
    "wof:name":"Wal-Mart",
    "wof:placetype":"venue"
},
  "geometry": {"coordinates":[-159.367279,21.982391],"type":"Point"}
}