{
  "type": "Feature",
  "properties": {
    "iso:country":"US",
    "sg:address":"1481 S King St",
    "sg:city":"Honolulu",
    "sg:classifiers":[
        {
            "category":"Travel",
            "subcategory":"Travel Agent",
            "type":"Entertainment"
        }
    ],
    "sg:phone":"+1 808 951 8448",
    "sg:postcode":"96814",
    "sg:province":"HI",
    "sg:tags":[
        "agency"
    ],
    "wof:name":"Hawaii Hana Tour and Travel",
    "wof:placetype":"venue"
},
  "geometry": {"coordinates":[-157.840135,21.29837],"type":"Point"}
}