{
  "type": "Feature",
  "properties": {
    "addr:full":"437 6th St Lanai City HI 96763",
    "addr:housenumber":"437",
    "addr:postcode":"96763",
    "addr:street":"6Th St",
    "iso:country":"US",
    "sg:address":"437 6th St",
    "sg:city":"Lanai City",
    "sg:classifiers":[
        {
            "category":"Freight",
            "type":"Transportation"
        }
    ],
    "sg:phone":"+1 808 565 7438",
    "sg:postcode":"96763",
    "sg:province":"HI",
    "sg:tags":[
        "delivery"
    ],
    "wof:name":"Mj Express",
    "wof:placetype":"venue"
},
  "geometry": {"coordinates":[-156.92276699999999,20.830293],"type":"Point"}
}