{
  "type": "Feature",
  "properties": {
    "iso:country":"US",
    "sg:address":"1085 Moanalua Rd",
    "sg:city":"Aiea",
    "sg:classifiers":[
        {
            "category":"Health Services",
            "subcategory":"Optometrist",
            "type":"Services"
        }
    ],
    "sg:phone":"+1 808 486 2666",
    "sg:postcode":"96701",
    "sg:province":"HI",
    "wof:name":"Au & Lau",
    "wof:placetype":"venue"
},
  "geometry": {"coordinates":[-157.93802299999999,21.384347],"type":"Point"}
}