{
  "type": "Feature",
  "properties": {
    "iso:country":"US",
    "sg:address":"693 Farrington Hwy",
    "sg:city":"Waipahu",
    "sg:classifiers":[
        {
            "category":"Restaurant",
            "type":"Food & Drink"
        }
    ],
    "sg:phone":"+1 808 677 1866",
    "sg:postcode":"96797",
    "sg:province":"HI",
    "sg:tags":[
        "eating"
    ],
    "wof:name":"Jesses Bakery Inc",
    "wof:placetype":"venue"
},
  "geometry": {"coordinates":[-158.007182,21.383385],"type":"Point"}
}