{
  "type": "Feature",
  "properties": {
    "iso:country":"US",
    "sg:address":"815 Gulick Ave",
    "sg:city":"Honolulu",
    "sg:classifiers":[
        {
            "category":"Wholesale",
            "subcategory":"Groceries",
            "type":"Manufacturing & Wholesale Goods"
        },
        {
            "category":"Wholesale",
            "subcategory":"Durable Goods & Equipment",
            "type":"Manufacturing & Wholesale Goods"
        }
    ],
    "sg:phone":"+1 808 848 0300",
    "sg:postcode":"96819",
    "sg:province":"HI",
    "sg:tags":[
        "importer"
    ],
    "wof:name":"Oriental Food Distributor",
    "wof:placetype":"venue"
},
  "geometry": {"coordinates":[-157.88009,21.332694],"type":"Point"}
}