{
  "type": "Feature",
  "properties": {
    "iso:country":"US",
    "sg:address":"117 Kahinani Way",
    "sg:city":"Kaneohe",
    "sg:classifiers":[
        {
            "category":"Building & Trades",
            "subcategory":"Landscaping Services",
            "type":"Services"
        }
    ],
    "sg:phone":"+1 808 247 3109",
    "sg:postcode":"96744",
    "sg:province":"HI",
    "sg:tags":[
        "designer",
        "landscape"
    ],
    "wof:name":"Mechler Corp",
    "wof:placetype":"venue"
},
  "geometry": {"coordinates":[-157.77147099999999,21.408042],"type":"Point"}
}