{
  "type": "Feature",
  "properties": {
    "iso:country":"US",
    "sg:address":"4270 Kilauea Rd",
    "sg:city":"Kilauea",
    "sg:classifiers":[
        {
            "category":"Food & Beverages",
            "subcategory":"Meat & Fish",
            "type":"Retail Goods"
        }
    ],
    "sg:phone":"+1 808 828 6244",
    "sg:postcode":"96754",
    "sg:province":"HI",
    "sg:tags":[
        "seafood"
    ],
    "wof:name":"Kilauea Fish Market",
    "wof:placetype":"venue"
},
  "geometry": {"coordinates":[-159.40812500000001,22.211025],"type":"Point"}
}