{
  "type": "Feature",
  "properties": {
    "iso:country":"US",
    "sg:address":"164 N King St",
    "sg:city":"Honolulu",
    "sg:classifiers":[
        {
            "category":"Restaurant",
            "type":"Food & Drink"
        }
    ],
    "sg:phone":"+1 808 599 1866",
    "sg:postcode":"96817",
    "sg:province":"HI",
    "wof:name":"Saigon Restaurant Vietnamese",
    "wof:placetype":"venue"
},
  "geometry": {"coordinates":[-157.86402100000001,21.312686],"type":"Point"}
}