{
  "type": "Feature",
  "properties": {
    "iso:country":"US",
    "sg:address":"2760 Waiwai Loop",
    "sg:city":"Honolulu",
    "sg:classifiers":[
        {
            "category":"Autos & Motor Vehicles",
            "subcategory":"Auto Supplies",
            "type":"Retail Goods"
        }
    ],
    "sg:phone":"+1 808 836 0331",
    "sg:postcode":"96819",
    "sg:province":"HI",
    "sg:tags":[
        "automobile",
        "parts"
    ],
    "wof:name":"Carquest Auto Parts",
    "wof:placetype":"venue"
},
  "geometry": {"coordinates":[-157.90051,21.332568],"type":"Point"}
}