{
  "type": "Feature",
  "properties": {
    "addr:full":"1124 7th Ave Honolulu HI 96816",
    "addr:housenumber":"1124",
    "addr:postcode":"96816",
    "addr:street":"7Th Ave",
    "iso:country":"US",
    "sg:address":"1124 7th Ave",
    "sg:city":"Honolulu",
    "sg:classifiers":[
        {
            "category":"Education",
            "subcategory":"School",
            "type":"Public Place"
        }
    ],
    "sg:phone":"+1 808 734 8979",
    "sg:postcode":"96816",
    "sg:province":"HI",
    "wof:name":"St Patrick's School",
    "wof:placetype":"venue"
},
  "geometry": {"coordinates":[-157.804891,21.285252],"type":"Point"}
}