{
  "type": "Feature",
  "properties": {
    "iso:country":"US",
    "sg:address":"1609 Iwi Way",
    "sg:city":"Honolulu",
    "sg:classifiers":[
        {
            "category":"Communications",
            "subcategory":"Film & Video Production",
            "type":"Services"
        }
    ],
    "sg:phone":"+1 808 732 2590",
    "sg:postcode":"96816",
    "sg:province":"HI",
    "sg:tags":[
        "motion"
    ],
    "wof:name":"Camera One",
    "wof:placetype":"venue"
},
  "geometry": {"coordinates":[-157.791359,21.287954],"type":"Point"}
}