{
  "type": "Feature",
  "properties": {
    "iso:country":"US",
    "sg:address":"500 N Nimitz Hwy",
    "sg:city":"Honolulu",
    "sg:classifiers":[
        {
            "category":"Shopping",
            "type":"Retail Goods"
        }
    ],
    "sg:phone":"+1 808 524 3059",
    "sg:postcode":"96817",
    "sg:province":"HI",
    "sg:tags":[
        "telephone",
        "cellular"
    ],
    "wof:name":"Hawaiian Wireless Express",
    "wof:placetype":"venue"
},
  "geometry": {"coordinates":[-157.87074899999999,21.313648],"type":"Point"}
}