{
  "type": "Feature",
  "properties": {
    "iso:country":"US",
    "sg:address":"2668 Haili Rd",
    "sg:city":"Honolulu",
    "sg:classifiers":[
        {
            "category":"Real Estate",
            "subcategory":"Surveying",
            "type":"Services"
        }
    ],
    "sg:phone":"+1 808 537 6666",
    "sg:postcode":"96813",
    "sg:province":"HI",
    "sg:tags":[
        "surveyor"
    ],
    "wof:name":"Akira Ishida",
    "wof:placetype":"venue"
},
  "geometry": {"coordinates":[-157.843412,21.323967],"type":"Point"}
}