{
  "type": "Feature",
  "properties": {
    "iso:country":"US",
    "sg:address":"33 N Holokai Rd",
    "sg:city":"Haiku",
    "sg:classifiers":[
        {
            "category":"Travel",
            "subcategory":"Travel Agent",
            "type":"Entertainment"
        }
    ],
    "sg:phone":"+1 808 572 8478",
    "sg:postcode":"96708",
    "sg:province":"HI",
    "sg:tags":[
        "agency",
        "bureau"
    ],
    "wof:name":"Leilani's Tours",
    "wof:placetype":"venue"
},
  "geometry": {"coordinates":[-156.26879,20.923929],"type":"Point"}
}