{
  "type": "Feature",
  "properties": {
    "iso:country":"US",
    "sg:address":"33 S King St",
    "sg:city":"Honolulu",
    "sg:classifiers":[
        {
            "category":"Professional",
            "subcategory":"Lawyer & Legal Services",
            "type":"Services"
        }
    ],
    "sg:phone":"+1 808 545 2525",
    "sg:postcode":"96813",
    "sg:province":"HI",
    "wof:name":"Donald Low",
    "wof:placetype":"venue"
},
  "geometry": {"coordinates":[-157.86295100000001,21.310464],"type":"Point"}
}