{
  "type": "Feature",
  "properties": {
    "iso:country":"US",
    "sg:address":"1442 Ulupii St",
    "sg:city":"Kailua",
    "sg:classifiers":[
        {
            "category":"Building & Trades",
            "subcategory":"Construction",
            "type":"Services"
        }
    ],
    "sg:phone":"+1 808 262 2676",
    "sg:postcode":"96734",
    "sg:province":"HI",
    "sg:tags":[
        "contractor"
    ],
    "wof:name":"Mac Shannon Masonry",
    "wof:placetype":"venue"
},
  "geometry": {"coordinates":[-157.75230400000001,21.377807],"type":"Point"}
}