{
  "type": "Feature",
  "properties": {
    "iso:country":"US",
    "sg:address":"1248 Kinoole St",
    "sg:city":"Hilo",
    "sg:classifiers":[
        {
            "category":"Health Services",
            "subcategory":"Doctor",
            "type":"Services"
        }
    ],
    "sg:phone":"+1 808 935 6888",
    "sg:postcode":"96720",
    "sg:province":"HI",
    "sg:tags":[
        "medical"
    ],
    "wof:name":"Alan C Desilva MD Inc",
    "wof:placetype":"venue"
},
  "geometry": {"coordinates":[-155.07848200000001,19.708581],"type":"Point"}
}