{
  "type": "Feature",
  "properties": {
    "iso:country":"US",
    "sg:address":"29 Hekaha St",
    "sg:city":"Aiea",
    "sg:classifiers":[
        {
            "category":"Shopping",
            "subcategory":"Used Merchandise",
            "type":"Retail Goods"
        }
    ],
    "sg:phone":"+1 808 488 9885",
    "sg:postcode":"96701",
    "sg:province":"HI",
    "sg:tags":[
        "pawnbroker"
    ],
    "wof:name":"Leeward Gold Exchange",
    "wof:placetype":"venue"
},
  "geometry": {"coordinates":[-157.95153400000001,21.384524],"type":"Point"}
}