{
  "type": "Feature",
  "properties": {
    "addr:full":"2301 Kalakaua Ave Honolulu HI 96815",
    "addr:housenumber":"2301",
    "addr:postcode":"96815",
    "addr:street":"Kalakaua Ave",
    "iso:country":"US",
    "sg:address":"2301 Kalakaua Ave",
    "sg:city":"Honolulu",
    "sg:classifiers":[
        {
            "category":"Shopping",
            "subcategory":"Clothing, Apparel, & Fashions",
            "type":"Retail Goods"
        }
    ],
    "sg:phone":"+1 808 923 0693",
    "sg:postcode":"96815",
    "sg:province":"HI",
    "sg:tags":[
        "item",
        "boutique"
    ],
    "wof:name":"Palm Tree House Inc",
    "wof:placetype":"venue"
},
  "geometry": {"coordinates":[-157.82606999999999,21.276543],"type":"Point"}
}