{
  "type": "Feature",
  "properties": {
    "iso:country":"US",
    "sg:address":"480 Kenolio Rd",
    "sg:city":"Kihei",
    "sg:classifiers":[
        {
            "category":"Professional",
            "subcategory":"Business Services",
            "type":"Services"
        }
    ],
    "sg:phone":"+1 808 875 6383",
    "sg:postcode":"96753",
    "sg:province":"HI",
    "wof:name":"Ice Sculptures By Darren Ho",
    "wof:placetype":"venue"
},
  "geometry": {"coordinates":[-156.45756800000001,20.774265],"type":"Point"}
}