{
  "type": "Feature",
  "properties": {
    "addr:full":"740 Hui Kelu St Kaneohe HI 96744",
    "addr:housenumber":"740",
    "addr:postcode":"96744",
    "addr:street":"Hui Kelu St",
    "iso:country":"US",
    "sg:address":"740 Hui Kelu St",
    "sg:city":"Kaneohe",
    "sg:classifiers":[
        {
            "category":"Professional",
            "subcategory":"Management & Consulting",
            "type":"Services"
        }
    ],
    "sg:phone":"+1 808 239 2301",
    "sg:postcode":"96744",
    "sg:province":"HI",
    "wof:name":"Tom Haynes Commucations",
    "wof:placetype":"venue"
},
  "geometry": {"coordinates":[-157.83527900000001,21.434731],"type":"Point"}
}