{
  "type": "Feature",
  "properties": {
    "addr:full":"1032 Mamalahoa Hwy Kamuela HI 96743",
    "addr:housenumber":"1032",
    "addr:postcode":"96743",
    "addr:street":"Mamalahoa Hwy Kamuela",
    "iso:country":"US",
    "sg:address":"1032 Mamalahoa Hwy",
    "sg:city":"Kamuela",
    "sg:classifiers":[
        {
            "category":"Social Services",
            "type":"Services"
        }
    ],
    "sg:phone":"+1 808 885 0086",
    "sg:postcode":"96743",
    "sg:province":"HI",
    "sg:tags":[
        "organization",
        "welfare"
    ],
    "wof:name":"Family Support Svc",
    "wof:placetype":"venue"
},
  "geometry": {"coordinates":[-155.663005,20.02444],"type":"Point"}
}