{
  "type": "Feature",
  "properties": {
    "addr:full":"818 Sheridan St Honolulu HI 96814",
    "addr:housenumber":"818",
    "addr:postcode":"96814",
    "addr:street":"Sheridan St",
    "iso:country":"US",
    "sg:address":"818 Sheridan St",
    "sg:city":"Honolulu",
    "sg:classifiers":[
        {
            "category":"Retail",
            "subcategory":"Laundry & Dry Cleaning",
            "type":"Services"
        },
        {
            "category":"Shopping",
            "subcategory":"Clothing, Apparel, & Fashions",
            "type":"Retail Goods"
        }
    ],
    "sg:phone":"+1 808 949 6858",
    "sg:postcode":"96814",
    "sg:province":"HI",
    "sg:tags":[
        "alteration"
    ],
    "wof:name":"Sook Hi's Alteration",
    "wof:placetype":"venue"
},
  "geometry": {"coordinates":[-157.84167099999999,21.29741],"type":"Point"}
}