{
  "type": "Feature",
  "properties": {
    "iso:country":"US",
    "sg:address":"414 Mokauea St",
    "sg:city":"Honolulu",
    "sg:classifiers":[
        {
            "category":"Food & Beverages",
            "subcategory":"Liquor & Beverages",
            "type":"Retail Goods"
        }
    ],
    "sg:phone":"+1 808 848 0940",
    "sg:postcode":"96819",
    "sg:province":"HI",
    "wof:name":"Mokauea Mart",
    "wof:placetype":"venue"
},
  "geometry": {"coordinates":[-157.882194,21.32735],"type":"Point"}
}