{
  "type": "Feature",
  "properties": {
    "iso:country":"US",
    "sg:address":"202 Kailua Rd",
    "sg:city":"Kailua",
    "sg:classifiers":[
        {
            "category":"Professional",
            "subcategory":"Business Services",
            "type":"Services"
        }
    ],
    "sg:phone":"+1 808 263 3195",
    "sg:postcode":"96734",
    "sg:province":"HI",
    "sg:tags":[
        "trade",
        "contractor"
    ],
    "wof:name":"J&S Enterprises",
    "wof:placetype":"venue"
},
  "geometry": {"coordinates":[-157.73288500000001,21.394727],"type":"Point"}
}