{
  "type": "Feature",
  "properties": {
    "iso:country":"US",
    "sg:address":"3288 Moanalua Rd",
    "sg:city":"Honolulu",
    "sg:classifiers":[
        {
            "category":"Restaurant",
            "type":"Food & Drink"
        }
    ],
    "sg:phone":"+1 808 833 8968",
    "sg:postcode":"96819",
    "sg:province":"HI",
    "sg:tags":[
        "eating"
    ],
    "wof:name":"Paradise Isle Espresso Co",
    "wof:placetype":"venue"
},
  "geometry": {"coordinates":[-157.90042700000001,21.361464],"type":"Point"}
}