{
  "type": "Feature",
  "properties": {
    "iso:country":"US",
    "sg:address":"129 Lahainaluna Rd",
    "sg:city":"Lahaina",
    "sg:classifiers":[
        {
            "category":"Restaurant",
            "type":"Food & Drink"
        }
    ],
    "sg:phone":"+1 808 667 5683",
    "sg:postcode":"96761",
    "sg:province":"HI",
    "sg:tags":[
        "delicatessen",
        "eating",
        "grocery"
    ],
    "wof:name":"Mr Sub Sandwiches",
    "wof:placetype":"venue"
},
  "geometry": {"coordinates":[-156.682164,20.878609],"type":"Point"}
}