{
  "type": "Feature",
  "properties": {
    "iso:country":"US",
    "sg:address":"1529 Hoomahie Loop",
    "sg:city":"Pearl City",
    "sg:classifiers":[
        {
            "category":"Professional",
            "subcategory":"Management & Consulting",
            "type":"Services"
        }
    ],
    "sg:phone":"+1 808 455 1489",
    "sg:postcode":"96782",
    "sg:province":"HI",
    "wof:name":"Jsm Consulting",
    "wof:placetype":"venue"
},
  "geometry": {"coordinates":[-157.95555400000001,21.399784],"type":"Point"}
}