{
  "type": "Feature",
  "properties": {
    "iso:country":"US",
    "sg:address":"45-480 Kaneohe Bay Dr",
    "sg:city":"Kaneohe",
    "sg:classifiers":[
        {
            "category":"Coffee & Tea",
            "type":"Food & Drink"
        }
    ],
    "sg:menulink":"http://www.allmenus.com/hi/koolaupoko/108578-starbucks-coffee/menu/",
    "sg:phone":"+1 808 234 6900",
    "sg:postcode":"96744",
    "sg:province":"HI",
    "sg:tags":[
        "american"
    ],
    "wof:name":"Starbucks Coffee",
    "wof:placetype":"venue"
},
  "geometry": {"coordinates":[-157.79804300000001,21.401594],"type":"Point"}
}