{
  "type": "Feature",
  "properties": {
    "addr:full":"36 Makaweo Ave Wahiawa HI 96786",
    "addr:housenumber":"36",
    "addr:postcode":"96786",
    "addr:street":"Makaweo Ave",
    "iso:country":"US",
    "sg:address":"36 Makaweo Ave",
    "sg:city":"Wahiawa",
    "sg:classifiers":[
        {
            "category":"Building & Trades",
            "subcategory":"Construction",
            "type":"Services"
        }
    ],
    "sg:phone":"+1 808 622 4977",
    "sg:postcode":"96786",
    "sg:province":"HI",
    "sg:tags":[
        "house"
    ],
    "wof:name":"Shige Higa Builders Inc",
    "wof:placetype":"venue"
},
  "geometry": {"coordinates":[-158.016559,21.501907],"type":"Point"}
}