{
  "type": "Feature",
  "properties": {
    "iso:country":"US",
    "sg:address":"1279 Kawaihae Rd",
    "sg:city":"Kamuela",
    "sg:classifiers":[
        {
            "category":"Professional",
            "subcategory":"Engineering",
            "type":"Services"
        }
    ],
    "sg:phone":"+1 808 885 7270",
    "sg:postcode":"96743",
    "sg:province":"HI",
    "sg:tags":[
        "general",
        "contractor"
    ],
    "wof:name":"M Luce Contracting Inc",
    "wof:placetype":"venue"
},
  "geometry": {"coordinates":[-155.69908799999999,20.02667],"type":"Point"}
}