{
  "type": "Feature",
  "properties": {
    "addr:full":"801 S Beretania St Honolulu HI 96813",
    "addr:housenumber":"801",
    "addr:postcode":"96813",
    "addr:street":"S Beretania St",
    "iso:country":"US",
    "sg:address":"801 S Beretania St",
    "sg:city":"Honolulu",
    "sg:classifiers":[
        {
            "category":"Food & Beverages",
            "subcategory":"Groceries & Convenience Stores",
            "type":"Retail Goods"
        }
    ],
    "sg:phone":"+1 808 523 0820",
    "sg:postcode":"96813",
    "sg:province":"HI",
    "sg:tags":[
        "product",
        "snack"
    ],
    "wof:name":"HPD Snack Shop",
    "wof:placetype":"venue"
},
  "geometry": {"coordinates":[-157.84943999999999,21.303834],"type":"Point"}
}