{
  "type": "Feature",
  "properties": {
    "iso:country":"US",
    "sg:address":"537 Ulune St",
    "sg:city":"Aiea",
    "sg:classifiers":[
        {
            "category":"Retail",
            "subcategory":"Repair Shop",
            "type":"Services"
        }
    ],
    "sg:phone":"+1 808 488 1376",
    "sg:postcode":"96701",
    "sg:province":"HI",
    "sg:tags":[
        "equipment"
    ],
    "wof:name":"Independent Equipment Svcs LLC",
    "wof:placetype":"venue"
},
  "geometry": {"coordinates":[-157.92174800000001,21.376198],"type":"Point"}
}