{
  "type": "Feature",
  "properties": {
    "iso:country":"US",
    "sg:address":"266 Kaelepulu Dr",
    "sg:city":"Kailua",
    "sg:classifiers":[
        {
            "category":"Recreation",
            "type":"Entertainment"
        }
    ],
    "sg:phone":"+1 808 262 8161",
    "sg:postcode":"96734",
    "sg:province":"HI",
    "sg:tags":[
        "course",
        "golf"
    ],
    "wof:name":"Mid-Pacific Country Club",
    "wof:placetype":"venue"
},
  "geometry": {"coordinates":[-157.71899400000001,21.39159],"type":"Point"}
}