{
  "type": "Feature",
  "properties": {
    "iso:country":"US",
    "sg:address":"837 4th Ave",
    "sg:city":"Honolulu",
    "sg:classifiers":[
        {
            "category":"Retail",
            "subcategory":"Repair Shop",
            "type":"Services"
        }
    ],
    "sg:phone":"+1 808 737 1196",
    "sg:postcode":"96816",
    "sg:province":"HI",
    "sg:tags":[
        "sporting"
    ],
    "wof:name":"Precision Golfcraft",
    "wof:placetype":"venue"
},
  "geometry": {"coordinates":[-157.812712,21.281471],"type":"Point"}
}