{
  "type": "Feature",
  "properties": {
    "iso:country":"US",
    "sg:address":"4286 Rice St",
    "sg:city":"Lihue",
    "sg:classifiers":[
        {
            "category":"Real Estate",
            "subcategory":"Developer",
            "type":"Services"
        }
    ],
    "sg:phone":"+1 808 245 7929",
    "sg:postcode":"96766",
    "sg:province":"HI",
    "sg:tags":[
        "subdivider"
    ],
    "wof:name":"Kauai Sea Breeze Realty Inc",
    "wof:placetype":"venue"
},
  "geometry": {"coordinates":[-159.36519999999999,21.97264],"type":"Point"}
}