{
  "type": "Feature",
  "properties": {
    "iso:country":"US",
    "sg:address":"922 Kamehameha Hwy",
    "sg:city":"Pearl City",
    "sg:classifiers":[
        {
            "category":"Autos & Motor Vehicles",
            "subcategory":"Fuel & Gas Station",
            "type":"Retail Goods"
        }
    ],
    "sg:phone":"+1 808 453 1469",
    "sg:postcode":"96782",
    "sg:province":"HI",
    "sg:tags":[
        "oil"
    ],
    "wof:name":"TESORO Gas Express",
    "wof:placetype":"venue"
},
  "geometry": {"coordinates":[-157.972497,21.39473],"type":"Point"}
}