{
  "type": "Feature",
  "properties": {
    "addr:full":"1744 Paula Dr Honolulu HI 96816",
    "addr:housenumber":"1744",
    "addr:postcode":"96816",
    "addr:street":"Paula Dr",
    "iso:country":"US",
    "sg:address":"1744 Paula Dr",
    "sg:city":"Honolulu",
    "sg:classifiers":[
        {
            "category":"Shopping",
            "subcategory":"Used Merchandise",
            "type":"Retail Goods"
        }
    ],
    "sg:phone":"+1 808 732 3884",
    "sg:postcode":"96816",
    "sg:province":"HI",
    "sg:tags":[
        "antique",
        "store"
    ],
    "wof:name":"Anchor House Antiques",
    "wof:placetype":"venue"
},
  "geometry": {"coordinates":[-157.78820099999999,21.289537],"type":"Point"}
}