{
  "type": "Feature",
  "properties": {
    "iso:country":"US",
    "sg:address":"680 Iwilei Rd",
    "sg:city":"Honolulu",
    "sg:classifiers":[
        {
            "category":"Government",
            "subcategory":"Office",
            "type":"Public Place"
        }
    ],
    "sg:phone":"+1 808 587 5580",
    "sg:postcode":"96817",
    "sg:province":"HI",
    "sg:tags":[
        "state",
        "program"
    ],
    "sg:website":"www.doe.k12.hi.us",
    "wof:name":"Education Dept",
    "wof:placetype":"venue"
},
  "geometry": {"coordinates":[-157.86953500000001,21.316097],"type":"Point"}
}