{
  "type": "Feature",
  "properties": {
    "iso:country":"US",
    "sg:address":"55 Kaahumanu Ave",
    "sg:city":"Kahului",
    "sg:classifiers":[
        {
            "category":"Food & Beverages",
            "subcategory":"Groceries & Convenience Stores",
            "type":"Retail Goods"
        }
    ],
    "sg:phone":"+1 808 877 3308",
    "sg:postcode":"96732",
    "sg:province":"HI",
    "sg:tags":[
        "grocer"
    ],
    "wof:name":"Ah Fook's Super Market",
    "wof:placetype":"venue"
},
  "geometry": {"coordinates":[-156.47019499999999,20.890153],"type":"Point"}
}