{
  "type": "Feature",
  "properties": {
    "addr:full":"2881 Milo Hae Loop Koloa HI 96756",
    "addr:housenumber":"2881",
    "addr:postcode":"96756",
    "addr:street":"Milo Hae Loop",
    "iso:country":"US",
    "sg:address":"2881 Milo Hae Loop",
    "sg:city":"Koloa",
    "sg:classifiers":[
        {
            "category":"Building & Trades",
            "subcategory":"Landscaping Services",
            "type":"Services"
        }
    ],
    "sg:phone":"+1 808 742 9027",
    "sg:postcode":"96756",
    "sg:province":"HI",
    "sg:tags":[
        "landscape",
        "contractor"
    ],
    "wof:name":"SGS Landscape Maintenance Co",
    "wof:placetype":"venue"
},
  "geometry": {"coordinates":[-159.462245,21.886576],"type":"Point"}
}