{
  "type": "Feature",
  "properties": {
    "iso:country":"US",
    "sg:address":"5315 Lower Honoapiilani Rd",
    "sg:city":"Lahaina",
    "sg:classifiers":[
        {
            "category":"Travel",
            "subcategory":"Hotels & Motels",
            "type":"Entertainment"
        }
    ],
    "sg:phone":"+1 808 442 3700",
    "sg:postcode":"96761",
    "sg:province":"HI",
    "wof:name":"Fish & Poi",
    "wof:placetype":"venue"
},
  "geometry": {"coordinates":[-156.666481,20.99272],"type":"Point"}
}