{
  "type": "Feature",
  "properties": {
    "iso:country":"US",
    "sg:address":"517 Paheehee Pl",
    "sg:city":"Waianae",
    "sg:classifiers":[
        {
            "category":"Building & Trades",
            "subcategory":"Equipment Rental",
            "type":"Services"
        }
    ],
    "sg:phone":"+1 808 696 8560",
    "sg:postcode":"96792",
    "sg:province":"HI",
    "wof:name":"Pony Parties By Ziggy",
    "wof:placetype":"venue"
},
  "geometry": {"coordinates":[-158.16377900000001,21.449307],"type":"Point"}
}