{
  "type": "Feature",
  "properties": {
    "iso:country":"US",
    "sg:address":"2780 Mokoi St",
    "sg:city":"Lihue",
    "sg:classifiers":[
        {
            "category":"Building & Trades",
            "subcategory":"Construction",
            "type":"Services"
        }
    ],
    "sg:phone":"+1 808 245 2465",
    "sg:postcode":"96766",
    "sg:province":"HI",
    "sg:tags":[
        "house"
    ],
    "wof:name":"Nyles Muramoto Construction",
    "wof:placetype":"venue"
},
  "geometry": {"coordinates":[-159.36218099999999,21.964862],"type":"Point"}
}