{
  "type": "Feature",
  "properties": {
    "addr:full":"770 Mapunapuna St Honolulu HI 96819",
    "addr:housenumber":"770",
    "addr:postcode":"96819",
    "addr:street":"Mapunapuna St",
    "iso:country":"US",
    "sg:address":"770 Mapunapuna St",
    "sg:city":"Honolulu",
    "sg:classifiers":[
        {
            "category":"Autos & Motor Vehicles",
            "subcategory":"Auto Supplies",
            "type":"Retail Goods"
        }
    ],
    "sg:phone":"+1 808 836 2939",
    "sg:postcode":"96819",
    "sg:province":"HI",
    "sg:tags":[
        "equipment",
        "air",
        "conditioning",
        "automobile"
    ],
    "wof:name":"A-1 AUTO AC Specialists",
    "wof:placetype":"venue"
},
  "geometry": {"coordinates":[-157.90016,21.340416],"type":"Point"}
}