{
  "type": "Feature",
  "properties": {
    "iso:country":"US",
    "sg:address":"1048 Kamehameha Hwy",
    "sg:city":"Kaneohe",
    "sg:classifiers":[
        {
            "category":"Health Services",
            "subcategory":"Doctor",
            "type":"Services"
        }
    ],
    "sg:phone":"+1 808 235 6801",
    "sg:postcode":"96744",
    "sg:province":"HI",
    "sg:tags":[
        "dentist"
    ],
    "sg:website":"www.drwall.net",
    "wof:name":"Windward Orthodontics",
    "wof:placetype":"venue"
},
  "geometry": {"coordinates":[-157.80085700000001,21.415235],"type":"Point"}
}