{
  "type": "Feature",
  "properties": {
    "iso:country":"US",
    "sg:address":"581 Dillingham Blvd",
    "sg:city":"Honolulu",
    "sg:classifiers":[
        {
            "category":"Restaurant",
            "type":"Food & Drink"
        }
    ],
    "sg:phone":"+1 808 847 2563",
    "sg:postcode":"96817",
    "sg:province":"HI",
    "sg:tags":[
        "caterer"
    ],
    "wof:name":"Nicky BBQ & Okazu",
    "wof:placetype":"venue"
},
  "geometry": {"coordinates":[-157.865038,21.318324],"type":"Point"}
}