{
  "type": "Feature",
  "properties": {
    "iso:country":"US",
    "sg:address":"1127 Kamehameha Hwy",
    "sg:city":"Kaneohe",
    "sg:classifiers":[
        {
            "category":"Shopping",
            "subcategory":"Bicycles & Sporting Goods",
            "type":"Retail Goods"
        }
    ],
    "sg:phone":"+1 808 235 4140",
    "sg:postcode":"96744",
    "sg:province":"HI",
    "sg:tags":[
        "athletic",
        "apparel",
        "sport",
        "team"
    ],
    "wof:name":"S T Sports Inc",
    "wof:placetype":"venue"
},
  "geometry": {"coordinates":[-157.80130199999999,21.416723],"type":"Point"}
}