{
  "type": "Feature",
  "properties": {
    "iso:country":"US",
    "sg:address":"1578 Oili Loop",
    "sg:city":"Honolulu",
    "sg:classifiers":[
        {
            "category":"Professional",
            "subcategory":"Management & Consulting",
            "type":"Services"
        }
    ],
    "sg:phone":"+1 808 941 9296",
    "sg:postcode":"96816",
    "sg:province":"HI",
    "sg:tags":[
        "business"
    ],
    "wof:name":"Compucare Consulting Service",
    "wof:placetype":"venue"
},
  "geometry": {"coordinates":[-157.78348399999999,21.287699],"type":"Point"}
}