{
  "type": "Feature",
  "properties": {
    "addr:full":"3050 Monsarrat Ave Honolulu HI 96815",
    "addr:postcode":"3050;96815",
    "addr:street":"Monsarrat Ave",
    "iso:country":"US",
    "sg:address":"3050 Monsarrat Ave",
    "sg:city":"Honolulu",
    "sg:classifiers":[
        {
            "category":"Shopping",
            "subcategory":"Clothing, Apparel, & Fashions",
            "type":"Retail Goods"
        }
    ],
    "sg:phone":"+1 808 922 1050",
    "sg:postcode":"96815",
    "sg:province":"HI",
    "wof:name":"Glorias Bridal Service Inc",
    "wof:placetype":"venue"
},
  "geometry": {"coordinates":[-157.81410500000001,21.269144],"type":"Point"}
}