{
  "type": "Feature",
  "properties": {
    "iso:country":"US",
    "sg:address":"1631 Liholiho St",
    "sg:city":"Honolulu",
    "sg:classifiers":[
        {
            "category":"Shopping",
            "subcategory":"Computers & Home Electronics",
            "type":"Retail Goods"
        }
    ],
    "sg:phone":"+1 808 949 2558",
    "sg:postcode":"96822",
    "sg:province":"HI",
    "sg:tags":[
        "radio",
        "television",
        "electronic",
        "store"
    ],
    "wof:name":"Shilla Electronics",
    "wof:placetype":"venue"
},
  "geometry": {"coordinates":[-157.83693299999999,21.307572],"type":"Point"}
}