{
  "type": "Feature",
  "properties": {
    "addr:full":"24 Makaala St Hilo HI 96720",
    "addr:housenumber":"24",
    "addr:postcode":"96720",
    "addr:street":"Makaala St",
    "iso:country":"US",
    "sg:address":"24 Makaala St",
    "sg:city":"Hilo",
    "sg:classifiers":[
        {
            "category":"Home & Garden",
            "subcategory":"Carpets & Floor Coverings",
            "type":"Retail Goods"
        }
    ],
    "sg:phone":"+1 808 934 9142",
    "sg:postcode":"96720",
    "sg:province":"HI",
    "sg:tags":[
        "material"
    ],
    "wof:name":"Warehouse Direct",
    "wof:placetype":"venue"
},
  "geometry": {"coordinates":[-155.06775099999999,19.704001],"type":"Point"}
}