{
  "type": "Feature",
  "properties": {
    "iso:country":"US",
    "sg:address":"590 Farrington Hwy",
    "sg:city":"Kapolei",
    "sg:classifiers":[
        {
            "category":"Travel",
            "subcategory":"Travel Agent",
            "type":"Entertainment"
        }
    ],
    "sg:phone":"+1 808 672 8844",
    "sg:postcode":"96707",
    "sg:province":"HI",
    "sg:tags":[
        "agency",
        "bureau"
    ],
    "wof:name":"Mor's Travel",
    "wof:placetype":"venue"
},
  "geometry": {"coordinates":[-158.123063,21.34601],"type":"Point"}
}