{
  "type": "Feature",
  "properties": {
    "addr:full":"2309 Aumakua St Pearl City HI 96782",
    "addr:housenumber":"2309",
    "addr:postcode":"96782",
    "addr:street":"Aumakua St",
    "iso:country":"US",
    "sg:address":"2309 Aumakua St",
    "sg:city":"Pearl City",
    "sg:classifiers":[
        {
            "category":"Building & Trades",
            "subcategory":"Construction",
            "type":"Services"
        }
    ],
    "sg:phone":"+1 808 455 5681",
    "sg:postcode":"96782",
    "sg:province":"HI",
    "sg:tags":[
        "roofing",
        "contractor"
    ],
    "wof:name":"Guarantee Roofing Co Inc",
    "wof:placetype":"venue"
},
  "geometry": {"coordinates":[-157.953791,21.422622],"type":"Point"}
}