{
  "type": "Feature",
  "properties": {
    "iso:country":"US",
    "sg:address":"2821 Kamanaiki St",
    "sg:city":"Honolulu",
    "sg:classifiers":[
        {
            "category":"Arts & Performance",
            "subcategory":"Theater",
            "type":"Entertainment"
        }
    ],
    "sg:phone":"+1 808 841 0161",
    "sg:postcode":"96819",
    "sg:province":"HI",
    "sg:tags":[
        "group"
    ],
    "wof:name":"Nite Beat Mobile Disco",
    "wof:placetype":"venue"
},
  "geometry": {"coordinates":[-157.85775100000001,21.34805],"type":"Point"}
}