{
  "type": "Feature",
  "properties": {
    "addr:full":"511 Waipaipai St Kaneohe HI 96744",
    "addr:housenumber":"511",
    "addr:postcode":"96744",
    "addr:street":"Waipaipai St",
    "iso:country":"US",
    "sg:address":"511 Waipaipai St",
    "sg:city":"Kaneohe",
    "sg:classifiers":[
        {
            "category":"Professional",
            "subcategory":"Accounting & Tax Preparation",
            "type":"Services"
        }
    ],
    "sg:phone":"+1 808 239 9418",
    "sg:postcode":"96744",
    "sg:province":"HI",
    "wof:name":"Tiaras of Hawaii",
    "wof:placetype":"venue"
},
  "geometry": {"coordinates":[-157.84147400000001,21.442942],"type":"Point"}
}