{
  "type": "Feature",
  "properties": {
    "iso:country":"US",
    "sg:address":"1823 Halekoa Dr",
    "sg:city":"Honolulu",
    "sg:classifiers":[
        {
            "category":"Professional",
            "subcategory":"Computer Services",
            "type":"Services"
        }
    ],
    "sg:phone":"+1 808 834 6159",
    "sg:postcode":"96821",
    "sg:province":"HI",
    "sg:tags":[
        "datum"
    ],
    "wof:name":"Michael Kometani",
    "wof:placetype":"venue"
},
  "geometry": {"coordinates":[-157.78001399999999,21.285242],"type":"Point"}
}