{
  "type": "Feature",
  "properties": {
    "addr:full":"950 Robello Ln Honolulu HI 96817",
    "addr:housenumber":"950",
    "addr:postcode":"96817",
    "addr:street":"Robello Ln",
    "iso:country":"US",
    "sg:address":"950 Robello Ln",
    "sg:city":"Honolulu",
    "sg:classifiers":[
        {
            "category":"Manufacturing",
            "subcategory":"Metals",
            "type":"Manufacturing & Wholesale Goods"
        }
    ],
    "sg:phone":"+1 808 841 6143",
    "sg:postcode":"96817",
    "sg:province":"HI",
    "sg:tags":[
        "work"
    ],
    "wof:name":"Ali'i Fire Protection Co LTD",
    "wof:placetype":"venue"
},
  "geometry": {"coordinates":[-157.86730299999999,21.320174],"type":"Point"}
}