{
  "type": "Feature",
  "properties": {
    "iso:country":"US",
    "sg:address":"315 Makaala St",
    "sg:city":"Hilo",
    "sg:classifiers":[
        {
            "category":"Shopping",
            "type":"Retail Goods"
        }
    ],
    "sg:phone":"+1 808 933 1730",
    "sg:postcode":"96720",
    "sg:province":"HI",
    "sg:tags":[
        "telephone",
        "cellular",
        "accessory"
    ],
    "wof:name":"T-Mobile USA Inc",
    "wof:placetype":"venue"
},
  "geometry": {"coordinates":[-155.06759500000001,19.700863],"type":"Point"}
}