{
  "type": "Feature",
  "properties": {
    "iso:country":"US",
    "sg:address":"2104 S King St",
    "sg:city":"Honolulu",
    "sg:classifiers":[
        {
            "category":"Health Services",
            "subcategory":"Doctor",
            "type":"Services"
        }
    ],
    "sg:phone":"+1 808 949 6608",
    "sg:postcode":"96826",
    "sg:province":"HI",
    "sg:tags":[
        "dentist"
    ],
    "wof:name":"Kometani & Associates",
    "wof:placetype":"venue"
},
  "geometry": {"coordinates":[-157.828868,21.294517],"type":"Point"}
}