{
  "type": "Feature",
  "properties": {
    "addr:full":"1932 Liliha St Honolulu HI 96817",
    "addr:housenumber":"1932",
    "addr:postcode":"96817",
    "addr:street":"Liliha St",
    "iso:country":"US",
    "sg:address":"1932 Liliha St",
    "sg:city":"Honolulu",
    "sg:classifiers":[
        {
            "category":"Professional",
            "subcategory":"Business Services",
            "type":"Services"
        }
    ],
    "sg:phone":"+1 808 537 1666",
    "sg:postcode":"96817",
    "sg:province":"HI",
    "sg:tags":[
        "drafting"
    ],
    "wof:name":"Lum's Drafting Svc",
    "wof:placetype":"venue"
},
  "geometry": {"coordinates":[-157.854997,21.325604],"type":"Point"}
}