{
  "type": "Feature",
  "properties": {
    "iso:country":"US",
    "sg:address":"444 Hobron Ln",
    "sg:city":"Honolulu",
    "sg:classifiers":[
        {
            "category":"Bars & Pubs",
            "type":"Food & Drink"
        }
    ],
    "sg:phone":"+1 808 951 0008",
    "sg:postcode":"96815",
    "sg:province":"HI",
    "sg:tags":[
        "lounge",
        "cocktail"
    ],
    "wof:name":"Club Michaelangelo",
    "wof:placetype":"venue"
},
  "geometry": {"coordinates":[-157.83573100000001,21.28681],"type":"Point"}
}