{
  "type": "Feature",
  "properties": {
    "iso:country":"US",
    "sg:address":"639 Kaulukanu St",
    "sg:city":"Waimanalo",
    "sg:classifiers":[
        {
            "category":"Building & Trades",
            "subcategory":"Landscaping Services",
            "type":"Services"
        }
    ],
    "sg:phone":"+1 808 396 6595",
    "sg:postcode":"96795",
    "sg:province":"HI",
    "sg:tags":[
        "landscape",
        "contractor"
    ],
    "sg:website":"www.mulkernlandscaping.com",
    "wof:name":"Kevin J Mulkern Landscaping",
    "wof:placetype":"venue"
},
  "geometry": {"coordinates":[-157.725966,21.337397],"type":"Point"}
}