{
  "type": "Feature",
  "properties": {
    "iso:country":"US",
    "sg:address":"1174 Honokahua St",
    "sg:city":"Honolulu",
    "sg:classifiers":[
        {
            "category":"Banks & Credit Unions",
            "subcategory":"Bank",
            "type":"Services"
        }
    ],
    "sg:phone":"+1 808 395 5781",
    "sg:postcode":"96825",
    "sg:province":"HI",
    "sg:tags":[
        "loan",
        "broker"
    ],
    "wof:name":"Hawaii Mortgage Brokers Corp",
    "wof:placetype":"venue"
},
  "geometry": {"coordinates":[-157.670647,21.299357],"type":"Point"}
}