{
  "type": "Feature",
  "properties": {
    "addr:full":"2804 E Manoa Rd Honolulu HI 96822",
    "addr:housenumber":"2804",
    "addr:postcode":"96822",
    "addr:street":"E Manoa Rd",
    "iso:country":"US",
    "sg:address":"2804 E Manoa Rd",
    "sg:city":"Honolulu",
    "sg:classifiers":[
        {
            "category":"Education",
            "subcategory":"Special Training",
            "type":"Public Place"
        },
        {
            "category":"Organizations",
            "subcategory":"Professional Association",
            "type":"Services"
        }
    ],
    "sg:phone":"+1 808 988 2602",
    "sg:postcode":"96822",
    "sg:province":"HI",
    "sg:tags":[
        "c",
        "language",
        "school",
        "community",
        "assoc",
        "child"
    ],
    "wof:name":"Manoa Japanese Language School",
    "wof:placetype":"venue"
},
  "geometry": {"coordinates":[-157.81071600000001,21.30962],"type":"Point"}
}