{
  "type": "Feature",
  "properties": {
    "addr:full":"1000 Uluohia St Kapolei HI 96707",
    "addr:housenumber":"1000",
    "addr:postcode":"96707",
    "addr:street":"Uluohia St",
    "iso:country":"US",
    "sg:address":"1000 Uluohia St",
    "sg:city":"Kapolei",
    "sg:classifiers":[
        {
            "category":"Government",
            "subcategory":"Office",
            "type":"Public Place"
        }
    ],
    "sg:phone":"+1 808 692 5561",
    "sg:postcode":"96707",
    "sg:province":"HI",
    "sg:tags":[
        "dept",
        "recreation",
        "parks"
    ],
    "wof:name":"Parks & Recreation Dept",
    "wof:placetype":"venue"
},
  "geometry": {"coordinates":[-158.08300500000001,21.331211],"type":"Point"}
}