{
  "type": "Feature",
  "properties": {
    "iso:country":"US",
    "sg:address":"1922 Wilhelmina Rise",
    "sg:city":"Honolulu",
    "sg:classifiers":[
        {
            "category":"Real Estate",
            "subcategory":"Architect",
            "type":"Services"
        }
    ],
    "sg:phone":"+1 808 737 9683",
    "sg:postcode":"96816",
    "sg:province":"HI",
    "sg:tags":[
        "architectural"
    ],
    "wof:name":"Nick H Huddleston AIA",
    "wof:placetype":"venue"
},
  "geometry": {"coordinates":[-157.791077,21.293568],"type":"Point"}
}