{
  "type": "Feature",
  "properties": {
    "iso:country":"US",
    "sg:address":"1638 Kalakaua Ave",
    "sg:city":"Honolulu",
    "sg:classifiers":[
        {
            "category":"Wholesale",
            "subcategory":"Construction Materials",
            "type":"Manufacturing & Wholesale Goods"
        },
        {
            "category":"Manufacturing",
            "subcategory":"Metals",
            "type":"Manufacturing & Wholesale Goods"
        }
    ],
    "sg:phone":"+1 808 955 2522",
    "sg:postcode":"96826",
    "sg:province":"HI",
    "sg:tags":[
        "steel",
        "fabricated",
        "joist"
    ],
    "wof:name":"Hambro Hawaii Inc",
    "wof:placetype":"venue"
},
  "geometry": {"coordinates":[-157.83670499999999,21.293418],"type":"Point"}
}