{
  "type": "Feature",
  "properties": {
    "iso:country":"US",
    "sg:address":"2463 S Kihei Rd",
    "sg:city":"Kihei",
    "sg:classifiers":[
        {
            "category":"Food & Beverages",
            "subcategory":"Bakery",
            "type":"Retail Goods"
        }
    ],
    "sg:phone":"+1 808 879 5177",
    "sg:postcode":"96753",
    "sg:province":"HI",
    "sg:tags":[
        "baker",
        "eating"
    ],
    "wof:name":"Cinnamon Roll Fair Hawaii",
    "wof:placetype":"venue"
},
  "geometry": {"coordinates":[-156.44661600000001,20.718932],"type":"Point"}
}