{
  "type": "Feature",
  "properties": {
    "addr:full":"537 Ahui St Honolulu HI 96813",
    "addr:housenumber":"537",
    "addr:postcode":"96813",
    "addr:street":"Ahui St",
    "iso:country":"US",
    "sg:address":"537 Ahui St",
    "sg:city":"Honolulu",
    "sg:classifiers":[
        {
            "category":"Retail",
            "subcategory":"Auto Repair",
            "type":"Services"
        },
        {
            "category":"Wholesale",
            "subcategory":"Auto Parts",
            "type":"Manufacturing & Wholesale Goods"
        }
    ],
    "sg:phone":"+1 808 593 0100",
    "sg:postcode":"96813",
    "sg:province":"HI",
    "sg:tags":[
        "transmission",
        "supply"
    ],
    "wof:name":"Trans-Parts Express",
    "wof:placetype":"venue"
},
  "geometry": {"coordinates":[-157.85689199999999,21.297671],"type":"Point"}
}