{
  "type": "Feature",
  "properties": {
    "addr:full":"155 Hamakua Dr Kailua HI 96734",
    "addr:housenumber":"155",
    "addr:postcode":"96734",
    "addr:street":"Hamakua Dr",
    "iso:country":"US",
    "sg:address":"155 Hamakua Dr",
    "sg:city":"Kailua",
    "sg:classifiers":[
        {
            "category":"Building & Trades",
            "subcategory":"Plumbing",
            "type":"Services"
        }
    ],
    "sg:phone":"+1 808 262 4772",
    "sg:postcode":"96734",
    "sg:province":"HI",
    "sg:tags":[
        "conditioning",
        "air",
        "system",
        "contractor"
    ],
    "wof:name":"Regal Service Co",
    "wof:placetype":"venue"
},
  "geometry": {"coordinates":[-157.74007700000001,21.389831],"type":"Point"}
}