{
  "type": "Feature",
  "properties": {
    "addr:full":"241 Waiahole Valley Rd Kaneohe HI 96744",
    "addr:housenumber":"241",
    "addr:postcode":"96744",
    "addr:street":"Waiahole Valley Rd",
    "iso:country":"US",
    "sg:address":"241 Waiahole Valley Rd",
    "sg:city":"Kaneohe",
    "sg:classifiers":[
        {
            "category":"Recreation",
            "type":"Entertainment"
        }
    ],
    "sg:phone":"+1 808 239 9110",
    "sg:postcode":"96744",
    "sg:province":"HI",
    "wof:name":"Nautilus Hawaii",
    "wof:placetype":"venue"
},
  "geometry": {"coordinates":[-157.85316399999999,21.482589],"type":"Point"}
}