{
  "type": "Feature",
  "properties": {
    "iso:country":"US",
    "sg:address":"802 Front St",
    "sg:city":"Lahaina",
    "sg:classifiers":[
        {
            "category":"Shopping",
            "type":"Retail Goods"
        }
    ],
    "sg:phone":"+1 808 667 4030",
    "sg:postcode":"96761",
    "sg:province":"HI",
    "sg:tags":[
        "art",
        "gallery",
        "dealer"
    ],
    "sg:website":"www.sargentsfineart.com",
    "wof:name":"Sargent's Fine Art",
    "wof:placetype":"venue"
},
  "geometry": {"coordinates":[-156.683187,20.879218],"type":"Point"}
}