{
  "type": "Feature",
  "properties": {
    "iso:country":"US",
    "sg:address":"109 Holomua St",
    "sg:city":"Hilo",
    "sg:classifiers":[
        {
            "category":"Retail",
            "subcategory":"Auto Repair",
            "type":"Services"
        }
    ],
    "sg:phone":"+1 808 969 7855",
    "sg:postcode":"96720",
    "sg:province":"HI",
    "sg:tags":[
        "repairing",
        "automobile",
        "general"
    ],
    "wof:name":"Shawnz Muffler & Brake",
    "wof:placetype":"venue"
},
  "geometry": {"coordinates":[-155.066112,19.701915],"type":"Point"}
}