{
  "type": "Feature",
  "properties": {
    "iso:country":"US",
    "sg:address":"505 Wanaao Rd",
    "sg:city":"Kailua",
    "sg:classifiers":[
        {
            "category":"Education",
            "subcategory":"Special Training",
            "type":"Public Place"
        }
    ],
    "sg:phone":"+1 808 956 7985",
    "sg:postcode":"96734",
    "sg:province":"HI",
    "sg:tags":[
        "professor"
    ],
    "wof:name":"James L Brewbaker PHD",
    "wof:placetype":"venue"
},
  "geometry": {"coordinates":[-157.72995499999999,21.388294],"type":"Point"}
}