{
  "type": "Feature",
  "properties": {
    "iso:country":"US",
    "sg:address":"54 Westervelt St",
    "sg:city":"Wahiawa",
    "sg:classifiers":[
        {
            "category":"Organizations",
            "subcategory":"Religious Organization",
            "type":"Services"
        }
    ],
    "sg:phone":"+1 808 621 9164",
    "sg:postcode":"96786",
    "sg:province":"HI",
    "sg:tags":[
        "church"
    ],
    "wof:name":"Christian Central Oahu Church",
    "wof:placetype":"venue"
},
  "geometry": {"coordinates":[-158.02782400000001,21.498195],"type":"Point"}
}