{
  "type": "Feature",
  "properties": {
    "addr:full":"650 Iwilei Rd Honolulu HI 96817",
    "addr:housenumber":"650",
    "addr:postcode":"96817",
    "addr:street":"Iwilei Rd",
    "iso:country":"US",
    "sg:address":"650 Iwilei Rd",
    "sg:city":"Honolulu",
    "sg:classifiers":[
        {
            "category":"Shopping",
            "subcategory":"Used Merchandise",
            "type":"Retail Goods"
        },
        {
            "category":"Wholesale",
            "subcategory":"Furniture",
            "type":"Manufacturing & Wholesale Goods"
        }
    ],
    "sg:phone":"+1 808 538 0422",
    "sg:postcode":"96817",
    "sg:province":"HI",
    "sg:tags":[
        "antique"
    ],
    "wof:name":"China Bazaar",
    "wof:placetype":"venue"
},
  "geometry": {"coordinates":[-157.86893800000001,21.315966],"type":"Point"}
}