{
  "type": "Feature",
  "properties": {
    "addr:full":"501 Sumner St Honolulu HI 96817",
    "addr:housenumber":"501",
    "addr:postcode":"96817",
    "addr:street":"Sumner St",
    "iso:country":"US",
    "sg:address":"501 Sumner St",
    "sg:city":"Honolulu",
    "sg:classifiers":[
        {
            "category":"Manufacturing",
            "subcategory":"Printing",
            "type":"Manufacturing & Wholesale Goods"
        }
    ],
    "sg:phone":"+1 808 533 2967",
    "sg:postcode":"96817",
    "sg:province":"HI",
    "sg:tags":[
        "commercial"
    ],
    "wof:name":"PIP Printing",
    "wof:placetype":"venue"
},
  "geometry": {"coordinates":[-157.868596,21.318077],"type":"Point"}
}