{
  "type": "Feature",
  "properties": {
    "iso:country":"US",
    "sg:address":"4449 Kolohala St",
    "sg:city":"Honolulu",
    "sg:classifiers":[
        {
            "category":"Building & Trades",
            "subcategory":"Construction",
            "type":"Services"
        }
    ],
    "sg:phone":"+1 808 371 1808",
    "sg:postcode":"96816",
    "sg:province":"HI",
    "sg:tags":[
        "general",
        "contractor"
    ],
    "wof:name":"808 Development LLC",
    "wof:placetype":"venue"
},
  "geometry": {"coordinates":[-157.78925100000001,21.263183],"type":"Point"}
}