{
  "type": "Feature",
  "properties": {
    "addr:full":"76 N King St Honolulu HI 96817",
    "addr:housenumber":"76",
    "addr:postcode":"96817",
    "addr:street":"N King St",
    "iso:country":"US",
    "sg:address":"76 N King St",
    "sg:city":"Honolulu",
    "sg:classifiers":[
        {
            "category":"Travel",
            "subcategory":"Travel Agent",
            "type":"Entertainment"
        }
    ],
    "sg:phone":"+1 808 538 7938",
    "sg:postcode":"96817",
    "sg:province":"HI",
    "sg:tags":[
        "tours",
        "promoter"
    ],
    "wof:name":"C & H Intl",
    "wof:placetype":"venue"
},
  "geometry": {"coordinates":[-157.863482,21.3117],"type":"Point"}
}