{
  "type": "Feature",
  "properties": {
    "iso:country":"US",
    "sg:address":"2353 Kalakaua Ave",
    "sg:city":"Honolulu",
    "sg:classifiers":[
        {
            "category":"Wholesale",
            "subcategory":"Apparel",
            "type":"Manufacturing & Wholesale Goods"
        }
    ],
    "sg:phone":"+1 808 926 4146",
    "sg:postcode":"96815",
    "sg:province":"HI",
    "sg:tags":[
        "clothing"
    ],
    "wof:name":"G S L Enterprises Inc",
    "wof:placetype":"venue"
},
  "geometry": {"coordinates":[-157.82705799999999,21.277367],"type":"Point"}
}