{
  "type": "Feature",
  "properties": {
    "iso:country":"US",
    "sg:address":"461 Awiki St",
    "sg:city":"Mililani",
    "sg:classifiers":[
        {
            "category":"Shopping",
            "subcategory":"Clothing, Apparel, & Fashions",
            "type":"Retail Goods"
        }
    ],
    "sg:phone":"+1 808 623 7552",
    "sg:postcode":"96789",
    "sg:province":"HI",
    "sg:tags":[
        "family"
    ],
    "wof:name":"Sst Shope",
    "wof:placetype":"venue"
},
  "geometry": {"coordinates":[-158.02440300000001,21.445677],"type":"Point"}
}