{
  "type": "Feature",
  "properties": {
    "addr:full":"530 Kaahele St Aiea HI 96701",
    "addr:housenumber":"530",
    "addr:postcode":"96701",
    "addr:street":"Kaahele St",
    "iso:country":"US",
    "sg:address":"530 Kaahele St",
    "sg:city":"Aiea",
    "sg:classifiers":[
        {
            "category":"Organizations",
            "subcategory":"Religious Organization",
            "type":"Services"
        }
    ],
    "sg:phone":"+1 808 487 0497",
    "sg:postcode":"96701",
    "sg:province":"HI",
    "sg:tags":[
        "church"
    ],
    "wof:name":"Church Of Jesus Christ Of Lds",
    "wof:placetype":"venue"
},
  "geometry": {"coordinates":[-157.944761,21.397487],"type":"Point"}
}