{
  "type": "Feature",
  "properties": {
    "iso:country":"US",
    "sg:address":"165 Kuanalio Pl",
    "sg:city":"Mililani",
    "sg:classifiers":[
        {
            "category":"Professional",
            "subcategory":"Engineering",
            "type":"Services"
        }
    ],
    "sg:phone":"+1 808 454 0555",
    "sg:postcode":"96789",
    "sg:province":"HI",
    "sg:tags":[
        "repair",
        "installation",
        "contractor",
        "boiler",
        "ship",
        "welding"
    ],
    "wof:name":"Jmi Contractors",
    "wof:placetype":"venue"
},
  "geometry": {"coordinates":[-158.024101,21.440061],"type":"Point"}
}