{
  "type": "Feature",
  "properties": {
    "addr:full":"5188 Kikala Rd Kalaheo HI 96741",
    "addr:housenumber":"5188",
    "addr:postcode":"96741",
    "addr:street":"Kikala Rd",
    "iso:country":"US",
    "sg:address":"5188 Kikala Rd",
    "sg:city":"Kalaheo",
    "sg:classifiers":[
        {
            "category":"Professional",
            "subcategory":"Business Services",
            "type":"Services"
        }
    ],
    "sg:phone":"+1 808 332 0142",
    "sg:postcode":"96741",
    "sg:province":"HI",
    "sg:tags":[
        "training",
        "combat",
        "air"
    ],
    "wof:name":"Ukulele Air",
    "wof:placetype":"venue"
},
  "geometry": {"coordinates":[-159.51946799999999,21.939984],"type":"Point"}
}