{
  "type": "Feature",
  "properties": {
    "iso:country":"US",
    "sg:address":"2800 Woodlawn Dr",
    "sg:city":"Honolulu",
    "sg:classifiers":[
        {
            "category":"Utilities",
            "subcategory":"Telephone",
            "type":"Services"
        },
        {
            "category":"Professional",
            "subcategory":"Computer Services",
            "type":"Services"
        }
    ],
    "sg:phone":"+1 808 539 3631",
    "sg:postcode":"96822",
    "sg:province":"HI",
    "sg:tags":[
        "consulting",
        "dev",
        "communications",
        "internet",
        "home",
        "page"
    ],
    "sg:website":"www.guide.net",
    "wof:name":"Guide Net Inc",
    "wof:placetype":"venue"
},
  "geometry": {"coordinates":[-157.80744899999999,21.309085],"type":"Point"}
}