{
  "type": "Feature",
  "properties": {
    "iso:country":"US",
    "sg:address":"1080 Ukuwai St",
    "sg:city":"Mililani",
    "sg:classifiers":[
        {
            "category":"Organizations",
            "subcategory":"Religious Organization",
            "type":"Services"
        }
    ],
    "sg:phone":"+1 808 626 8798",
    "sg:postcode":"96789",
    "sg:province":"HI",
    "sg:tags":[
        "church"
    ],
    "wof:name":"Cornerstone Fellowship",
    "wof:placetype":"venue"
},
  "geometry": {"coordinates":[-158.001913,21.468534],"type":"Point"}
}