{
  "type": "Feature",
  "properties": {
    "iso:country":"US",
    "sg:address":"4425 Paiaha St",
    "sg:city":"Kailua Kona",
    "sg:classifiers":[
        {
            "category":"Farming",
            "subcategory":"Aquatic Farm",
            "type":"Manufacturing & Wholesale Goods"
        }
    ],
    "sg:phone":"+1 808 325 7022",
    "sg:postcode":"96740",
    "sg:province":"HI",
    "wof:name":"Hawaii Koi Farm",
    "wof:placetype":"venue"
},
  "geometry": {"coordinates":[-155.99918600000001,19.714321],"type":"Point"}
}