{
  "type": "Feature",
  "properties": {
    "iso:country":"US",
    "sg:address":"4315 Ulumalu Pl",
    "sg:city":"Haiku",
    "sg:classifiers":[
        {
            "category":"Professional",
            "subcategory":"Accounting & Tax Preparation",
            "type":"Services"
        }
    ],
    "sg:phone":"+1 808 572 4117",
    "sg:postcode":"96708",
    "sg:province":"HI",
    "sg:tags":[
        "bookkeeping",
        "general"
    ],
    "wof:name":"Kay Jackson Bookkeeping Svc",
    "wof:placetype":"venue"
},
  "geometry": {"coordinates":[-156.28414100000001,20.908383],"type":"Point"}
}