{
  "type": "Feature",
  "properties": {
    "addr:full":"3975 Lower Honoapiilani Rd Lahaina HI 96761",
    "addr:housenumber":"3975",
    "addr:postcode":"96761",
    "addr:street":"Lower Honoapiilani Rd",
    "iso:country":"US",
    "sg:address":"3975 Lower Honoapiilani Rd",
    "sg:city":"Lahaina",
    "sg:classifiers":[
        {
            "category":"Building & Trades",
            "subcategory":"Construction",
            "type":"Services"
        }
    ],
    "sg:phone":"+1 808 669 1092",
    "sg:postcode":"96761",
    "sg:province":"HI",
    "sg:tags":[
        "house"
    ],
    "wof:name":"Scott Reinke Development",
    "wof:placetype":"venue"
},
  "geometry": {"coordinates":[-156.68270799999999,20.963384],"type":"Point"}
}