{
  "type": "Feature",
  "properties": {
    "addr:full":"33 Lono Ave Kahului HI 96732",
    "addr:housenumber":"33",
    "addr:postcode":"96732",
    "addr:street":"Lono Ave",
    "iso:country":"US",
    "sg:address":"33 Lono Ave",
    "sg:city":"Kahului",
    "sg:classifiers":[
        {
            "category":"Banks & Credit Unions",
            "subcategory":"Bank",
            "type":"Services"
        }
    ],
    "sg:phone":"+1 808 893 0995",
    "sg:postcode":"96732",
    "sg:province":"HI",
    "sg:tags":[
        "loan",
        "real estate"
    ],
    "sg:website":"www.charterfunding.com",
    "wof:name":"Charter Funding",
    "wof:placetype":"venue"
},
  "geometry": {"coordinates":[-156.46976799999999,20.889554],"type":"Point"}
}