{
  "type": "Feature",
  "properties": {
    "addr:full":"2136 W Vineyard St Wailuku HI 96793",
    "addr:housenumber":"2136",
    "addr:postcode":"96793",
    "addr:street":"W Vineyard St",
    "iso:country":"US",
    "sg:address":"2136 W Vineyard St",
    "sg:city":"Wailuku",
    "sg:classifiers":[
        {
            "category":"Professional",
            "type":"Services"
        }
    ],
    "sg:phone":"+1 808 242 8429",
    "sg:postcode":"96793",
    "sg:province":"HI",
    "sg:tags":[
        "establishment"
    ],
    "wof:name":"Kealiiloa",
    "wof:placetype":"venue"
},
  "geometry": {"coordinates":[-156.51087100000001,20.890241],"type":"Point"}
}