{
  "type": "Feature",
  "properties": {
    "addr:full":"1778 Ala Moana Blvd Honolulu HI 96815",
    "addr:housenumber":"1778",
    "addr:postcode":"96815",
    "addr:street":"Ala Moana Blvd",
    "iso:country":"US",
    "sg:address":"1778 Ala Moana Blvd",
    "sg:city":"Honolulu",
    "sg:classifiers":[
        {
            "category":"Banks & Credit Unions",
            "subcategory":"Financial Services",
            "type":"Services"
        }
    ],
    "sg:phone":"+1 808 942 0635",
    "sg:postcode":"96815",
    "sg:province":"HI",
    "sg:tags":[
        "investor"
    ],
    "wof:name":"Whimar Investments LLC",
    "wof:placetype":"venue"
},
  "geometry": {"coordinates":[-157.83809199999999,21.28498],"type":"Point"}
}