{
  "type": "Feature",
  "properties": {
    "iso:country":"US",
    "sg:address":"820 Lumiauau St",
    "sg:city":"Waipahu",
    "sg:classifiers":[
        {
            "category":"Recreation",
            "type":"Entertainment"
        }
    ],
    "sg:phone":"+1 808 678 9110",
    "sg:postcode":"96797",
    "sg:province":"HI",
    "sg:tags":[
        "club",
        "travel"
    ],
    "wof:name":"Chameleon Travel Club Cha Inc",
    "wof:placetype":"venue"
},
  "geometry": {"coordinates":[-158.000114,21.405302],"type":"Point"}
}