{
  "type": "Feature",
  "properties": {
    "iso:country":"US",
    "sg:address":"344 Kalihi St",
    "sg:city":"Honolulu",
    "sg:classifiers":[
        {
            "category":"Retail",
            "subcategory":"Auto Repair",
            "type":"Services"
        }
    ],
    "sg:phone":"+1 808 845 6826",
    "sg:postcode":"96819",
    "sg:province":"HI",
    "sg:tags":[
        "brake",
        "relining",
        "vehicle"
    ],
    "wof:name":"Industrial Brake Supply Co",
    "wof:placetype":"venue"
},
  "geometry": {"coordinates":[-157.881663,21.324796],"type":"Point"}
}