{
  "type": "Feature",
  "properties": {
    "iso:country":"US",
    "sg:address":"1155 Wilder Ave",
    "sg:city":"Honolulu",
    "sg:classifiers":[
        {
            "category":"Real Estate",
            "subcategory":"Real Estate Operator",
            "type":"Services"
        }
    ],
    "sg:phone":"+1 808 533 1155",
    "sg:postcode":"96822",
    "sg:province":"HI",
    "sg:tags":[
        "apartment"
    ],
    "wof:name":"Makiki Station Apartments",
    "wof:placetype":"venue"
},
  "geometry": {"coordinates":[-157.84045499999999,21.30676],"type":"Point"}
}