{
  "type": "Feature",
  "properties": {
    "iso:country":"US",
    "sg:address":"3079 Manu Hope Pl",
    "sg:city":"Kihei",
    "sg:classifiers":[
        {
            "category":"Professional",
            "type":"Services"
        }
    ],
    "sg:phone":"+1 808 874 5121",
    "sg:postcode":"96753",
    "sg:province":"HI",
    "wof:name":"Naturally Maui Inc",
    "wof:placetype":"venue"
},
  "geometry": {"coordinates":[-156.44607199999999,20.704845],"type":"Point"}
}