{
  "type": "Feature",
  "properties": {
    "addr:full":"2079 Kaahumanu St Pearl City HI 96701",
    "addr:housenumber":"2079",
    "addr:postcode":"96701",
    "addr:street":"Kaahumanu St",
    "iso:country":"US",
    "sg:address":"2079 Kaahumanu St",
    "sg:city":"Pearl City",
    "sg:classifiers":[
        {
            "category":"Health Services",
            "subcategory":"Doctor",
            "type":"Services"
        }
    ],
    "sg:phone":"+1 808 456 8662",
    "sg:postcode":"96701",
    "sg:province":"HI",
    "sg:tags":[
        "dentist"
    ],
    "wof:name":"Tracy N Tanji DDS",
    "wof:placetype":"venue"
},
  "geometry": {"coordinates":[-157.943085,21.411633],"type":"Point"}
}