{
  "type": "Feature",
  "properties": {
    "iso:country":"US",
    "sg:address":"945 Kapahulu Ave",
    "sg:city":"Honolulu",
    "sg:classifiers":[
        {
            "category":"Personal",
            "subcategory":"Barber",
            "type":"Services"
        }
    ],
    "sg:phone":"+1 808 735 1116",
    "sg:postcode":"96816",
    "sg:province":"HI",
    "sg:tags":[
        "shop"
    ],
    "wof:name":"Choi's Hairstyling & Barber",
    "wof:placetype":"venue"
},
  "geometry": {"coordinates":[-157.81332699999999,21.285497],"type":"Point"}
}