{
  "type": "Feature",
  "properties": {
    "iso:country":"US",
    "sg:address":"166 Kamehameha Ave",
    "sg:city":"Hilo",
    "sg:classifiers":[
        {
            "category":"Professional",
            "subcategory":"Lawyer & Legal Services",
            "type":"Services"
        }
    ],
    "sg:phone":"+1 808 935 6462",
    "sg:postcode":"96720",
    "sg:province":"HI",
    "sg:tags":[
        "attorney"
    ],
    "wof:name":"Curtis Narimatsu",
    "wof:placetype":"venue"
},
  "geometry": {"coordinates":[-155.08676399999999,19.726425],"type":"Point"}
}