{
  "type": "Feature",
  "properties": {
    "iso:country":"US",
    "sg:address":"2960 Aheahe St",
    "sg:city":"Lihue",
    "sg:classifiers":[
        {
            "category":"Communications",
            "subcategory":"Film & Video Production",
            "type":"Services"
        }
    ],
    "sg:phone":"+1 808 246 3499",
    "sg:postcode":"96766",
    "sg:province":"HI",
    "sg:tags":[
        "motion",
        "picture"
    ],
    "wof:name":"Up Close Video Productions",
    "wof:placetype":"venue"
},
  "geometry": {"coordinates":[-159.36819,21.968804],"type":"Point"}
}