{
  "type": "Feature",
  "properties": {
    "iso:country":"US",
    "sg:address":"22 Alaloa St",
    "sg:city":"Kaneohe",
    "sg:classifiers":[
        {
            "category":"Organizations",
            "subcategory":"Religious Organization",
            "type":"Services"
        }
    ],
    "sg:phone":"+1 808 235 4200",
    "sg:postcode":"96744",
    "sg:province":"HI",
    "sg:tags":[
        "church"
    ],
    "wof:name":"Ekalesia Foundation Of Jesus",
    "wof:placetype":"venue"
},
  "geometry": {"coordinates":[-157.806059,21.417334],"type":"Point"}
}