{
  "type": "Feature",
  "properties": {
    "addr:full":"737 Lower Main St Wailuku HI 96793",
    "addr:housenumber":"737",
    "addr:postcode":"96793",
    "addr:street":"Lower Main St",
    "iso:country":"US",
    "sg:address":"737 Lower Main St",
    "sg:city":"Wailuku",
    "sg:classifiers":[
        {
            "category":"Restaurant",
            "type":"Food & Drink"
        }
    ],
    "sg:phone":"+1 808 242 1900",
    "sg:postcode":"96793",
    "sg:province":"HI",
    "sg:tags":[
        "eating"
    ],
    "wof:name":"Subway",
    "wof:placetype":"venue"
},
  "geometry": {"coordinates":[-156.490002,20.904653],"type":"Point"}
}