{
  "type": "Feature",
  "properties": {
    "iso:country":"US",
    "sg:address":"1230 Waiua Pl",
    "sg:city":"Aiea",
    "sg:classifiers":[
        {
            "category":"Wholesale",
            "subcategory":"Hardware",
            "type":"Manufacturing & Wholesale Goods"
        }
    ],
    "sg:phone":"+1 808 486 5551",
    "sg:postcode":"96701",
    "sg:province":"HI",
    "sg:tags":[
        "beverage",
        "dispensing"
    ],
    "sg:website":"www.cicoenterprise.com",
    "wof:name":"Cico Enterprise LTD",
    "wof:placetype":"venue"
},
  "geometry": {"coordinates":[-157.905418,21.373683],"type":"Point"}
}