{
  "type": "Feature",
  "properties": {
    "addr:full":"735 California Ave Wahiawa HI 96786",
    "addr:housenumber":"735",
    "addr:postcode":"96786",
    "addr:street":"California Ave",
    "iso:country":"US",
    "sg:address":"735 California Ave",
    "sg:city":"Wahiawa",
    "sg:classifiers":[
        {
            "category":"Health Services",
            "subcategory":"Health Practitioner",
            "type":"Services"
        }
    ],
    "sg:phone":"+1 808 628 9988",
    "sg:postcode":"96786",
    "sg:province":"HI",
    "wof:name":"First Physical & Functional",
    "wof:placetype":"venue"
},
  "geometry": {"coordinates":[-158.02726200000001,21.496878],"type":"Point"}
}