{
  "type": "Feature",
  "properties": {
    "iso:country":"US",
    "sg:address":"140 Hoohana St",
    "sg:city":"Kahului",
    "sg:classifiers":[
        {
            "category":"Food & Beverages",
            "subcategory":"Specialty",
            "type":"Retail Goods"
        }
    ],
    "sg:phone":"+1 808 871 4122",
    "sg:postcode":"96732",
    "sg:province":"HI",
    "sg:tags":[
        "water",
        "bulk",
        "company"
    ],
    "wof:name":"Water Store",
    "wof:placetype":"venue"
},
  "geometry": {"coordinates":[-156.46408700000001,20.888388],"type":"Point"}
}