{
  "type": "Feature",
  "properties": {
    "addr:full":"421 Alakawa St Honolulu HI 96817",
    "addr:housenumber":"421",
    "addr:postcode":"96817",
    "addr:street":"Alakawa St",
    "iso:country":"US",
    "sg:address":"421 Alakawa St",
    "sg:city":"Honolulu",
    "sg:classifiers":[
        {
            "category":"Home & Garden",
            "subcategory":"Building Materials",
            "type":"Retail Goods"
        }
    ],
    "sg:phone":"+1 808 521 7355",
    "sg:postcode":"96817",
    "sg:province":"HI",
    "sg:website":"www.homedepot.com",
    "wof:name":"Home Depot",
    "wof:placetype":"venue"
},
  "geometry": {"coordinates":[-157.87376,21.31765],"type":"Point"}
}