{
  "type": "Feature",
  "properties": {
    "iso:country":"US",
    "sg:address":"994 Kuhio Hwy",
    "sg:city":"Kapaa",
    "sg:classifiers":[
        {
            "category":"Autos & Motor Vehicles",
            "subcategory":"Fuel & Gas Station",
            "type":"Retail Goods"
        }
    ],
    "sg:phone":"+1 808 822 5318",
    "sg:postcode":"96746",
    "sg:province":"HI",
    "sg:tags":[
        "station"
    ],
    "wof:name":"Leonards Kapaa Service",
    "wof:placetype":"venue"
},
  "geometry": {"coordinates":[-159.31923,22.066088],"type":"Point"}
}