{
  "type": "Feature",
  "properties": {
    "iso:country":"US",
    "sg:address":"110 Ahamaka Rd",
    "sg:city":"Wahiawa",
    "sg:classifiers":[
        {
            "category":"Social Services",
            "subcategory":"Child Care",
            "type":"Services"
        }
    ],
    "sg:phone":"+1 808 621 0193",
    "sg:postcode":"96786",
    "sg:province":"HI",
    "sg:tags":[
        "day"
    ],
    "wof:name":"Cleo McNeil",
    "wof:placetype":"venue"
},
  "geometry": {"coordinates":[-158.01666,21.532454],"type":"Point"}
}