{
  "type": "Feature",
  "properties": {
    "addr:full":"666 Kalanianaole Ave Hilo HI 96720",
    "addr:housenumber":"666",
    "addr:postcode":"96720",
    "addr:street":"Kalanianaole Ave",
    "iso:country":"US",
    "sg:address":"666 Kalanianaole Ave",
    "sg:city":"Hilo",
    "sg:classifiers":[
        {
            "category":"Wholesale",
            "subcategory":"Petroleum",
            "type":"Manufacturing & Wholesale Goods"
        }
    ],
    "sg:phone":"+1 808 961 3634",
    "sg:postcode":"96720",
    "sg:province":"HI",
    "sg:tags":[
        "bulk",
        "station"
    ],
    "wof:name":"Chevron",
    "wof:placetype":"venue"
},
  "geometry": {"coordinates":[-155.05462499999999,19.72725],"type":"Point"}
}