{
  "type": "Feature",
  "properties": {
    "iso:country":"US",
    "sg:address":"465 Kapahulu Ave",
    "sg:city":"Honolulu",
    "sg:classifiers":[
        {
            "category":"Retail",
            "subcategory":"Auto Repair",
            "type":"Services"
        }
    ],
    "sg:phone":"+1 808 737 6937",
    "sg:postcode":"96815",
    "sg:province":"HI",
    "sg:tags":[
        "automobile",
        "electric"
    ],
    "wof:name":"Ecologics",
    "wof:placetype":"venue"
},
  "geometry": {"coordinates":[-157.81538699999999,21.27532],"type":"Point"}
}