{
  "type": "Feature",
  "properties": {
    "iso:country":"US",
    "sg:address":"1311 Kapiolani Blvd",
    "sg:city":"Honolulu",
    "sg:classifiers":[
        {
            "category":"Professional",
            "subcategory":"Advertising",
            "type":"Services"
        }
    ],
    "sg:phone":"+1 808 599 7777",
    "sg:postcode":"96814",
    "sg:province":"HI",
    "sg:tags":[
        "counselor"
    ],
    "wof:name":"NBC Inc",
    "wof:placetype":"venue"
},
  "geometry": {"coordinates":[-157.84601499999999,21.294597],"type":"Point"}
}