{
  "type": "Feature",
  "properties": {
    "iso:country":"US",
    "sg:address":"46 Puamana Pl",
    "sg:city":"Lahaina",
    "sg:classifiers":[
        {
            "category":"Professional",
            "subcategory":"Computer Services",
            "type":"Services"
        }
    ],
    "sg:phone":"+1 808 669 7602",
    "sg:postcode":"96761",
    "sg:province":"HI",
    "sg:tags":[
        "consulting"
    ],
    "wof:name":"Pactech Hawaii",
    "wof:placetype":"venue"
},
  "geometry": {"coordinates":[-156.677209,20.98336],"type":"Point"}
}