{
  "type": "Feature",
  "properties": {
    "iso:country":"US",
    "sg:address":"3083 Akahi St",
    "sg:city":"Lihue",
    "sg:classifiers":[
        {
            "category":"Government",
            "subcategory":"Police Station",
            "type":"Public Place"
        }
    ],
    "sg:phone":"+1 808 632 7950",
    "sg:postcode":"96766",
    "sg:province":"HI",
    "sg:tags":[
        "state"
    ],
    "wof:name":"Sheriff Division",
    "wof:placetype":"venue"
},
  "geometry": {"coordinates":[-159.36752300000001,21.97772],"type":"Point"}
}