{
  "type": "Feature",
  "properties": {
    "iso:country":"US",
    "sg:address":"1420 Konia St",
    "sg:city":"Honolulu",
    "sg:classifiers":[
        {
            "category":"Building & Trades",
            "subcategory":"Electrical",
            "type":"Services"
        }
    ],
    "sg:phone":"+1 808 351 2437",
    "sg:postcode":"96817",
    "sg:province":"HI",
    "sg:tags":[
        "electrical",
        "contractor"
    ],
    "wof:name":"Freds Electrical Service",
    "wof:placetype":"venue"
},
  "geometry": {"coordinates":[-157.864316,21.334043],"type":"Point"}
}