{
  "type": "Feature",
  "properties": {
    "iso:country":"US",
    "sg:address":"583 Mililani Pl",
    "sg:city":"Kihei",
    "sg:classifiers":[
        {
            "category":"Retail",
            "subcategory":"Repair Shop",
            "type":"Services"
        }
    ],
    "sg:phone":"+1 808 877 3750",
    "sg:postcode":"96753",
    "sg:province":"HI",
    "sg:tags":[
        "plumbing",
        "drain",
        "cleaning",
        "sewer"
    ],
    "wof:name":"Kahului Rooter Svc",
    "wof:placetype":"venue"
},
  "geometry": {"coordinates":[-156.42808600000001,20.703483],"type":"Point"}
}