{
  "type": "Feature",
  "properties": {
    "iso:country":"US",
    "sg:address":"10 Halawai Dr",
    "sg:city":"Lahaina",
    "sg:classifiers":[
        {
            "category":"Retail",
            "subcategory":"Auto Rental",
            "type":"Services"
        }
    ],
    "sg:phone":"+1 808 661 4588",
    "sg:postcode":"96761",
    "sg:province":"HI",
    "sg:tags":[
        "passenger",
        "car"
    ],
    "wof:name":"Avis Rent A Car Systems Inc",
    "wof:placetype":"venue"
},
  "geometry": {"coordinates":[-156.688468,20.942267],"type":"Point"}
}