{
  "type": "Feature",
  "properties": {
    "iso:country":"US",
    "sg:address":"3148 Oihana St",
    "sg:city":"Lihue",
    "sg:classifiers":[
        {
            "category":"Retail",
            "subcategory":"Auto Repair",
            "type":"Services"
        },
        {
            "category":"Manufacturing",
            "subcategory":"Motor Vehicles & Parts",
            "type":"Manufacturing & Wholesale Goods"
        }
    ],
    "sg:phone":"+1 808 245 5264",
    "sg:postcode":"96766",
    "sg:province":"HI",
    "sg:tags":[
        "body",
        "automobile",
        "painting",
        "suppl",
        "mfg"
    ],
    "wof:name":"Kauai Body and Paint",
    "wof:placetype":"venue"
},
  "geometry": {"coordinates":[-159.356707,21.970027],"type":"Point"}
}