{
  "type": "Feature",
  "properties": {
    "addr:full":"26 Hoolai St Kailua HI 96734",
    "addr:housenumber":"26",
    "addr:postcode":"96734",
    "addr:street":"Hoolai St",
    "iso:country":"US",
    "sg:address":"26 Hoolai St",
    "sg:city":"Kailua",
    "sg:classifiers":[
        {
            "category":"Cinema",
            "subcategory":"Movie Rental",
            "type":"Entertainment"
        }
    ],
    "sg:phone":"+1 808 261 0500",
    "sg:postcode":"96734",
    "sg:province":"HI",
    "sg:tags":[
        "leasing",
        "video",
        "disc",
        "tape"
    ],
    "sg:website":"www.blockbuster.com",
    "wof:name":"Blockbuster Video",
    "wof:placetype":"venue"
},
  "geometry": {"coordinates":[-157.745081,21.395016],"type":"Point"}
}