{
  "type": "Feature",
  "properties": {
    "addr:full":"723 Kamehameha Hwy Kaneohe HI 96744",
    "addr:housenumber":"723",
    "addr:postcode":"96744",
    "addr:street":"Kamehameha Hwy",
    "iso:country":"US",
    "sg:address":"723 Kamehameha Hwy",
    "sg:city":"Kaneohe",
    "sg:classifiers":[
        {
            "category":"Food & Beverages",
            "subcategory":"Liquor & Beverages",
            "type":"Retail Goods"
        }
    ],
    "sg:phone":"+1 808 239 8348",
    "sg:postcode":"96744",
    "sg:province":"HI",
    "wof:name":"Country Market",
    "wof:placetype":"venue"
},
  "geometry": {"coordinates":[-157.79921100000001,21.409345],"type":"Point"}
}