{
  "type": "Feature",
  "properties": {
    "iso:country":"US",
    "sg:address":"1646 Kapiolani Blvd",
    "sg:city":"Honolulu",
    "sg:classifiers":[
        {
            "category":"Restaurant",
            "type":"Food & Drink"
        }
    ],
    "sg:menulink":"http://www.allmenus.com/hi/honolulu/83568-papa-johns-pizza/menu/",
    "sg:phone":"+1 808 592 7272",
    "sg:postcode":"96814",
    "sg:province":"HI",
    "sg:tags":[
        "american",
        "pizza"
    ],
    "wof:name":"Papa John's Pizza",
    "wof:placetype":"venue"
},
  "geometry": {"coordinates":[-157.83858900000001,21.292063],"type":"Point"}
}