{
  "type": "Feature",
  "properties": {
    "addr:full":"4776 Kanalani St Kailua Kona HI 96740",
    "addr:housenumber":"4776",
    "addr:postcode":"96740",
    "addr:street":"Kanalani St",
    "iso:country":"US",
    "sg:address":"4776 Kanalani St",
    "sg:city":"Kailua Kona",
    "sg:classifiers":[
        {
            "category":"Professional",
            "subcategory":"Art Services",
            "type":"Services"
        },
        {
            "category":"Manufacturing",
            "subcategory":"Printing",
            "type":"Manufacturing & Wholesale Goods"
        }
    ],
    "sg:phone":"+1 808 329 3367",
    "sg:postcode":"96740",
    "sg:province":"HI",
    "sg:tags":[
        "shop",
        "silk",
        "for",
        "screen",
        "tee",
        "t",
        "print",
        "retail"
    ],
    "wof:name":"C G Tee's",
    "wof:placetype":"venue"
},
  "geometry": {"coordinates":[-156.020081,19.686719],"type":"Point"}
}