{
  "type": "Feature",
  "properties": {
    "iso:country":"US",
    "sg:address":"3054 Ala Poha Pl",
    "sg:city":"Honolulu",
    "sg:classifiers":[
        {
            "category":"Arts & Performance",
            "subcategory":"Theater",
            "type":"Entertainment"
        }
    ],
    "sg:phone":"+1 808 839 7311",
    "sg:postcode":"96818",
    "sg:province":"HI",
    "sg:tags":[
        "theatrical"
    ],
    "wof:name":"Augie Rey Entertainment I",
    "wof:placetype":"venue"
},
  "geometry": {"coordinates":[-157.902445,21.349079],"type":"Point"}
}