{
  "type": "Feature",
  "properties": {
    "addr:full":"4333 Ulumalu Pl Haiku HI 96708",
    "addr:housenumber":"4333",
    "addr:postcode":"96708",
    "addr:street":"Ulumalu Pl",
    "iso:country":"US",
    "sg:address":"4333 Ulumalu Pl",
    "sg:city":"Haiku",
    "sg:classifiers":[
        {
            "category":"Retail",
            "subcategory":"Repair Shop",
            "type":"Services"
        }
    ],
    "sg:phone":"+1 808 572 9255",
    "sg:postcode":"96708",
    "sg:province":"HI",
    "sg:tags":[
        "appliance"
    ],
    "wof:name":"Haiku & Makawao Refrig & Appl",
    "wof:placetype":"venue"
},
  "geometry": {"coordinates":[-156.284145,20.908383],"type":"Point"}
}