{
  "type": "Feature",
  "properties": {
    "iso:country":"US",
    "sg:address":"590 N King St",
    "sg:city":"Honolulu",
    "sg:classifiers":[
        {
            "category":"Restaurant",
            "type":"Food & Drink"
        }
    ],
    "sg:phone":"+1 808 845 5360",
    "sg:postcode":"96817",
    "sg:province":"HI",
    "wof:name":"Linh's Cafe & Restaurant",
    "wof:placetype":"venue"
},
  "geometry": {"coordinates":[-157.865893,21.320169],"type":"Point"}
}