{
  "type": "Feature",
  "properties": {
    "addr:full":"864 S Beretania St Honolulu HI 96813",
    "addr:housenumber":"864",
    "addr:postcode":"96813",
    "addr:street":"S Beretania St",
    "iso:country":"US",
    "sg:address":"864 S Beretania St",
    "sg:city":"Honolulu",
    "sg:classifiers":[
        {
            "category":"Wholesale",
            "subcategory":"Computers",
            "type":"Manufacturing & Wholesale Goods"
        }
    ],
    "sg:phone":"+1 808 537 9971",
    "sg:postcode":"96813",
    "sg:province":"HI",
    "sg:tags":[
        "wholesaler"
    ],
    "wof:name":"Advanced Abacus Associates",
    "wof:placetype":"venue"
},
  "geometry": {"coordinates":[-157.85028,21.304243],"type":"Point"}
}