{
  "type": "Feature",
  "properties": {
    "addr:full":"370 Kawaihae St Honolulu HI 96825",
    "addr:housenumber":"370",
    "addr:postcode":"96825",
    "addr:street":"Kawaihae St",
    "iso:country":"US",
    "sg:address":"370 Kawaihae St",
    "sg:city":"Honolulu",
    "sg:classifiers":[
        {
            "category":"Building & Trades",
            "subcategory":"Construction",
            "type":"Services"
        }
    ],
    "sg:phone":"+1 808 394 5471",
    "sg:postcode":"96825",
    "sg:province":"HI",
    "sg:tags":[
        "general",
        "contractor"
    ],
    "wof:name":"K R M Construction",
    "wof:placetype":"venue"
},
  "geometry": {"coordinates":[-157.71824599999999,21.290493],"type":"Point"}
}