{
  "type": "Feature",
  "properties": {
    "iso:country":"US",
    "sg:address":"1012 Anaunau St",
    "sg:city":"Ewa Beach",
    "sg:classifiers":[
        {
            "category":"Travel",
            "subcategory":"Travel Agent",
            "type":"Entertainment"
        }
    ],
    "sg:phone":"+1 808 681 0633",
    "sg:postcode":"96706",
    "sg:province":"HI",
    "sg:tags":[
        "operator",
        "tour"
    ],
    "wof:name":"Jj Tour Service",
    "wof:placetype":"venue"
},
  "geometry": {"coordinates":[-158.02606800000001,21.355534],"type":"Point"}
}