{
  "type": "Feature",
  "properties": {
    "iso:country":"US",
    "sg:address":"513 Pohue St",
    "sg:city":"Aiea",
    "sg:classifiers":[
        {
            "category":"Building & Trades",
            "subcategory":"Construction",
            "type":"Services"
        }
    ],
    "sg:phone":"+1 808 488 5161",
    "sg:postcode":"96701",
    "sg:province":"HI",
    "sg:tags":[
        "hanging",
        "wallpaper",
        "contractor"
    ],
    "wof:name":"Ken's Wallpapering",
    "wof:placetype":"venue"
},
  "geometry": {"coordinates":[-157.920986,21.375254],"type":"Point"}
}