{
  "type": "Feature",
  "properties": {
    "iso:country":"US",
    "sg:address":"500 Ala Moana Blvd",
    "sg:city":"Honolulu",
    "sg:classifiers":[
        {
            "category":"Banks & Credit Unions",
            "subcategory":"Bank",
            "type":"Services"
        }
    ],
    "sg:phone":"+1 808 543 6300",
    "sg:postcode":"96813",
    "sg:province":"HI",
    "sg:tags":[
        "loan",
        "real estate"
    ],
    "wof:name":"Ameriquest",
    "wof:placetype":"venue"
},
  "geometry": {"coordinates":[-157.86317500000001,21.300985],"type":"Point"}
}