{
  "type": "Feature",
  "properties": {
    "iso:country":"US",
    "sg:address":"1785 S King St",
    "sg:city":"Honolulu",
    "sg:classifiers":[
        {
            "category":"Professional",
            "subcategory":"Business Services",
            "type":"Services"
        }
    ],
    "sg:phone":"+1 808 946 5863",
    "sg:postcode":"96826",
    "sg:province":"HI",
    "sg:tags":[
        "auctioneer"
    ],
    "wof:name":"Since Hawaii",
    "wof:placetype":"venue"
},
  "geometry": {"coordinates":[-157.833191,21.295906],"type":"Point"}
}