{
  "type": "Feature",
  "properties": {
    "iso:country":"US",
    "sg:address":"801 Aumakiki Loop",
    "sg:city":"Aiea",
    "sg:classifiers":[
        {
            "category":"Building & Trades",
            "subcategory":"Construction",
            "type":"Services"
        }
    ],
    "sg:phone":"+1 808 486 5052",
    "sg:postcode":"96701",
    "sg:province":"HI",
    "sg:tags":[
        "resurfacing",
        "laying",
        "refinishing",
        "floor"
    ],
    "wof:name":"Premium Flooring",
    "wof:placetype":"venue"
},
  "geometry": {"coordinates":[-157.91247200000001,21.377872],"type":"Point"}
}