{
  "type": "Feature",
  "properties": {
    "iso:country":"US",
    "sg:address":"647 Luakini St",
    "sg:city":"Lahaina",
    "sg:classifiers":[
        {
            "category":"Real Estate",
            "subcategory":"Real Estate Operator",
            "type":"Services"
        }
    ],
    "sg:phone":"+1 808 661 3487",
    "sg:postcode":"96761",
    "sg:province":"HI",
    "sg:tags":[
        "apartment"
    ],
    "wof:name":"Liberty Apartment",
    "wof:placetype":"venue"
},
  "geometry": {"coordinates":[-156.67884000000001,20.874905],"type":"Point"}
}