{
  "type": "Feature",
  "properties": {
    "iso:country":"US",
    "sg:address":"1034 Waiolina St",
    "sg:city":"Waipahu",
    "sg:classifiers":[
        {
            "category":"Manufacturing",
            "subcategory":"Wood Products",
            "type":"Manufacturing & Wholesale Goods"
        }
    ],
    "sg:phone":"+1 808 671 8473",
    "sg:postcode":"96797",
    "sg:province":"HI",
    "sg:tags":[
        "mfg"
    ],
    "wof:name":"Stanford Bronze Works",
    "wof:placetype":"venue"
},
  "geometry": {"coordinates":[-158.00313199999999,21.419065],"type":"Point"}
}