{
  "type": "Feature",
  "properties": {
    "addr:full":"101 Ala Moana Blvd Honolulu HI 96813",
    "addr:housenumber":"101",
    "addr:postcode":"96813",
    "addr:street":"Ala Moana Blvd",
    "iso:country":"US",
    "sg:address":"101 Ala Moana Blvd",
    "sg:city":"Honolulu",
    "sg:classifiers":[
        {
            "category":"Shopping",
            "subcategory":"Beauty & Cosmetics",
            "type":"Retail Goods"
        }
    ],
    "sg:phone":"+1 808 528 5449",
    "sg:postcode":"96813",
    "sg:province":"HI",
    "sg:tags":[
        "outlet",
        "perfume"
    ],
    "wof:name":"Perfumania Store 200",
    "wof:placetype":"venue"
},
  "geometry": {"coordinates":[-157.864248,21.307731],"type":"Point"}
}