{
  "type": "Feature",
  "properties": {
    "iso:country":"US",
    "sg:address":"700 Richards St",
    "sg:city":"Honolulu",
    "sg:classifiers":[
        {
            "category":"Building & Trades",
            "subcategory":"Construction",
            "type":"Services"
        }
    ],
    "sg:phone":"+1 808 537 9916",
    "sg:postcode":"96813",
    "sg:province":"HI",
    "sg:tags":[
        "tile",
        "dealer",
        "contractor"
    ],
    "wof:name":"Fischer Tile & Marble Hawa LLC",
    "wof:placetype":"venue"
},
  "geometry": {"coordinates":[-157.86155400000001,21.306214],"type":"Point"}
}