{
  "type": "Feature",
  "properties": {
    "iso:country":"US",
    "sg:address":"101 Kooku Pl",
    "sg:city":"Kailua",
    "sg:classifiers":[
        {
            "category":"Professional",
            "subcategory":"Business Services",
            "type":"Services"
        }
    ],
    "sg:phone":"+1 808 262 0429",
    "sg:postcode":"96734",
    "sg:province":"HI",
    "wof:name":"Sam Failla",
    "wof:placetype":"venue"
},
  "geometry": {"coordinates":[-157.73925800000001,21.363709],"type":"Point"}
}