{
  "type": "Feature",
  "properties": {
    "iso:country":"US",
    "sg:address":"1104 Pensacola St",
    "sg:city":"Honolulu",
    "sg:classifiers":[
        {
            "category":"Restaurant",
            "type":"Food & Drink"
        }
    ],
    "sg:phone":"+1 808 521 7307",
    "sg:postcode":"96814",
    "sg:province":"HI",
    "wof:name":"Taka 2",
    "wof:placetype":"venue"
},
  "geometry": {"coordinates":[-157.84538000000001,21.301536],"type":"Point"}
}