{
  "type": "Feature",
  "properties": {
    "iso:country":"US",
    "sg:address":"1338 Akalani Loop",
    "sg:city":"Kailua",
    "sg:classifiers":[
        {
            "category":"Education",
            "subcategory":"Vocational School",
            "type":"Public Place"
        }
    ],
    "sg:phone":"+1 808 261 8636",
    "sg:postcode":"96734",
    "sg:province":"HI",
    "wof:name":"Amy K Uemoto",
    "wof:placetype":"venue"
},
  "geometry": {"coordinates":[-157.733418,21.371854],"type":"Point"}
}