{
  "type": "Feature",
  "properties": {
    "iso:country":"US",
    "sg:address":"1449 Gregory St",
    "sg:city":"Honolulu",
    "sg:classifiers":[
        {
            "category":"Wholesale",
            "subcategory":"Electrical",
            "type":"Manufacturing & Wholesale Goods"
        }
    ],
    "sg:phone":"+1 808 537 7432",
    "sg:postcode":"96817",
    "sg:province":"HI",
    "sg:tags":[
        "control",
        "lighting"
    ],
    "wof:name":"Control Systems LLC",
    "wof:placetype":"venue"
},
  "geometry": {"coordinates":[-157.86801500000001,21.332552],"type":"Point"}
}