{
  "type": "Feature",
  "properties": {
    "addr:full":"3045 Monsarrat Ave Honolulu HI 96815",
    "addr:housenumber":"3045",
    "addr:postcode":"96815",
    "addr:street":"Monsarrat Ave",
    "iso:country":"US",
    "sg:address":"3045 Monsarrat Ave",
    "sg:city":"Honolulu",
    "sg:classifiers":[
        {
            "category":"Restaurant",
            "type":"Food & Drink"
        }
    ],
    "sg:phone":"+1 808 732 0058",
    "sg:postcode":"96815",
    "sg:province":"HI",
    "wof:name":"Aloha Sushi",
    "wof:placetype":"venue"
},
  "geometry": {"coordinates":[-157.81365500000001,21.268987],"type":"Point"}
}