{
  "type": "Feature",
  "properties": {
    "iso:country":"US",
    "sg:address":"5545 Mamalahoa Hwy",
    "sg:city":"Naalehu",
    "sg:classifiers":[
        {
            "category":"Education",
            "subcategory":"School",
            "type":"Public Place"
        }
    ],
    "sg:phone":"+1 808 939 2413",
    "sg:postcode":"96772",
    "sg:province":"HI",
    "wof:name":"Naalehu School",
    "wof:placetype":"venue"
},
  "geometry": {"coordinates":[-155.579341,19.062291],"type":"Point"}
}