{
  "type": "Feature",
  "properties": {
    "iso:country":"US",
    "sg:address":"1 Aloha Tower Dr",
    "sg:city":"Honolulu",
    "sg:classifiers":[
        {
            "category":"Retail",
            "subcategory":"Photofinishing",
            "type":"Services"
        }
    ],
    "sg:phone":"+1 808 537 6677",
    "sg:postcode":"96813",
    "sg:province":"HI",
    "sg:tags":[
        "photo",
        "finishing"
    ],
    "wof:name":"Hawaii 1-100 Photo Svc Inc",
    "wof:placetype":"venue"
},
  "geometry": {"coordinates":[-157.86456699999999,21.306433],"type":"Point"}
}