{
  "type": "Feature",
  "properties": {
    "iso:country":"US",
    "sg:address":"205 Leoku St",
    "sg:city":"Waipahu",
    "sg:classifiers":[
        {
            "category":"Insurance",
            "subcategory":"Title Insurance",
            "type":"Services"
        },
        {
            "category":"Banks & Credit Unions",
            "subcategory":"Bank",
            "type":"Services"
        }
    ],
    "sg:phone":"+1 808 678 6620",
    "sg:postcode":"96797",
    "sg:province":"HI",
    "sg:tags":[
        "carrier",
        "escrow"
    ],
    "sg:website":"www.tghawaii.com",
    "wof:name":"Title Guaranty Escrow Svc Inc",
    "wof:placetype":"venue"
},
  "geometry": {"coordinates":[-158.02422000000001,21.379545],"type":"Point"}
}