{
  "type": "Feature",
  "properties": {
    "iso:country":"US",
    "sg:address":"611 Kapahulu Ave",
    "sg:city":"Honolulu",
    "sg:classifiers":[
        {
            "category":"Restaurant",
            "type":"Food & Drink"
        }
    ],
    "sg:menulink":"http://www.allmenus.com/hi/honolulu/83572-papa-johns-pizza/menu/",
    "sg:phone":"+1 808 733 7272",
    "sg:postcode":"96815",
    "sg:province":"HI",
    "sg:tags":[
        "american",
        "pizza"
    ],
    "wof:name":"Papa John's Pizza",
    "wof:placetype":"venue"
},
  "geometry": {"coordinates":[-157.81358299999999,21.278657],"type":"Point"}
}