{
  "type": "Feature",
  "properties": {
    "addr:full":"1150 N Nimitz Hwy Honolulu HI 96817",
    "addr:housenumber":"1150",
    "addr:postcode":"96817",
    "addr:street":"N Nimitz Hwy",
    "iso:country":"US",
    "sg:address":"1150 N Nimitz Hwy",
    "sg:city":"Honolulu",
    "sg:classifiers":[
        {
            "category":"Building & Trades",
            "subcategory":"Construction",
            "type":"Services"
        }
    ],
    "sg:phone":"+1 808 521 1605",
    "sg:postcode":"96817",
    "sg:province":"HI",
    "sg:tags":[
        "house",
        "builder",
        "operative"
    ],
    "wof:name":"Lais Kiawe",
    "wof:placetype":"venue"
},
  "geometry": {"coordinates":[-157.875708,21.317931],"type":"Point"}
}