{
  "type": "Feature",
  "properties": {
    "addr:full":"2455 Niumalu Rd Lihue HI 96766",
    "addr:housenumber":"2455",
    "addr:postcode":"96766",
    "addr:street":"Niumalu Rd",
    "iso:country":"US",
    "sg:address":"2455 Niumalu Rd",
    "sg:city":"Lihue",
    "sg:classifiers":[
        {
            "category":"Travel",
            "subcategory":"Hotels & Motels",
            "type":"Entertainment"
        }
    ],
    "sg:phone":"+1 808 245 2923",
    "sg:postcode":"96766",
    "sg:province":"HI",
    "wof:name":"Motel Frances",
    "wof:placetype":"venue"
},
  "geometry": {"coordinates":[-159.36261999999999,21.95185],"type":"Point"}
}