{
  "type": "Feature",
  "properties": {
    "iso:country":"US",
    "sg:address":"2299 Kuhio Ave",
    "sg:city":"Honolulu",
    "sg:classifiers":[
        {
            "category":"Shopping",
            "subcategory":"Jewelry",
            "type":"Retail Goods"
        }
    ],
    "sg:phone":"+1 808 922 4013",
    "sg:postcode":"96815",
    "sg:province":"HI",
    "sg:tags":[
        "jeweler"
    ],
    "wof:name":"DSH Enterprise",
    "wof:placetype":"venue"
},
  "geometry": {"coordinates":[-157.82705799999999,21.280215],"type":"Point"}
}