{
  "type": "Feature",
  "properties": {
    "iso:country":"US",
    "sg:address":"2615 S King St",
    "sg:city":"Honolulu",
    "sg:classifiers":[
        {
            "category":"Personal",
            "subcategory":"Beauty Salon",
            "type":"Services"
        }
    ],
    "sg:phone":"+1 808 942 3411",
    "sg:postcode":"96826",
    "sg:province":"HI",
    "sg:tags":[
        "shop"
    ],
    "wof:name":"Pearl Fujiwara",
    "wof:placetype":"venue"
},
  "geometry": {"coordinates":[-157.82127700000001,21.291498],"type":"Point"}
}