{
  "type": "Feature",
  "properties": {
    "addr:full":"20 Hauoli St Wailuku HI 96793",
    "addr:housenumber":"20",
    "addr:postcode":"96793",
    "addr:street":"Hauoli St",
    "iso:country":"US",
    "sg:address":"20 Hauoli St",
    "sg:city":"Wailuku",
    "sg:classifiers":[
        {
            "category":"Recreation",
            "type":"Entertainment"
        }
    ],
    "sg:phone":"+1 808 242 2906",
    "sg:postcode":"96793",
    "sg:province":"HI",
    "sg:tags":[
        "diving",
        "instruction"
    ],
    "wof:name":"J & B Svc",
    "wof:placetype":"venue"
},
  "geometry": {"coordinates":[-156.510233,20.793054],"type":"Point"}
}