{
  "type": "Feature",
  "properties": {
    "iso:country":"US",
    "sg:address":"687 Wainee St",
    "sg:city":"Lahaina",
    "sg:classifiers":[
        {
            "category":"Shopping",
            "subcategory":"Bicycles & Sporting Goods",
            "type":"Retail Goods"
        }
    ],
    "sg:phone":"+1 808 661 1637",
    "sg:postcode":"96761",
    "sg:province":"HI",
    "sg:tags":[
        "equipment",
        "skateboard"
    ],
    "wof:name":"Lahaina Skate Co LLC",
    "wof:placetype":"venue"
},
  "geometry": {"coordinates":[-156.678777,20.876905],"type":"Point"}
}