{
  "type": "Feature",
  "properties": {
    "iso:country":"US",
    "sg:address":"119 Kuaie Pl",
    "sg:city":"Mililani",
    "sg:classifiers":[
        {
            "category":"Professional",
            "type":"Services"
        }
    ],
    "sg:phone":"+1 808 623 0182",
    "sg:postcode":"96789",
    "sg:province":"HI",
    "wof:name":"Sung Co",
    "wof:placetype":"venue"
},
  "geometry": {"coordinates":[-158.00117800000001,21.449631],"type":"Point"}
}