{
  "type": "Feature",
  "properties": {
    "iso:country":"US",
    "sg:address":"416 Kamehameha Hwy",
    "sg:city":"Kaneohe",
    "sg:classifiers":[
        {
            "category":"Organizations",
            "subcategory":"Religious Organization",
            "type":"Services"
        }
    ],
    "sg:phone":"+1 808 235 1044",
    "sg:postcode":"96744",
    "sg:province":"HI",
    "sg:tags":[
        "church"
    ],
    "sg:website":"www.windwardworship.com",
    "wof:name":"Windward Worship Ctr",
    "wof:placetype":"venue"
},
  "geometry": {"coordinates":[-157.83262099999999,21.457887],"type":"Point"}
}