{
  "type": "Feature",
  "properties": {
    "iso:country":"US",
    "sg:address":"254 Waimakua Dr",
    "sg:city":"Mililani",
    "sg:classifiers":[
        {
            "category":"Retail",
            "subcategory":"Repair Shop",
            "type":"Services"
        }
    ],
    "sg:phone":"+1 808 686 9355",
    "sg:postcode":"96789",
    "sg:province":"HI",
    "sg:tags":[
        "welding"
    ],
    "wof:name":"K & B Fabraications Inc",
    "wof:placetype":"venue"
},
  "geometry": {"coordinates":[-158.01139699999999,21.464526],"type":"Point"}
}