{
  "type": "Feature",
  "properties": {
    "addr:full":"850 Noelani St Pearl City HI 96782",
    "addr:housenumber":"850",
    "addr:postcode":"96782",
    "addr:street":"Noelani St",
    "iso:country":"US",
    "sg:address":"850 Noelani St",
    "sg:city":"Pearl City",
    "sg:classifiers":[
        {
            "category":"Personal",
            "subcategory":"Beauty Salon",
            "type":"Services"
        }
    ],
    "sg:phone":"+1 808 781 2127",
    "sg:postcode":"96782",
    "sg:province":"HI",
    "sg:tags":[
        "supply"
    ],
    "wof:name":"Margartts Prpose By Dsign Slon",
    "wof:placetype":"venue"
},
  "geometry": {"coordinates":[-157.96104399999999,21.395865],"type":"Point"}
}