{
  "type": "Feature",
  "properties": {
    "addr:full":"3750 Wailea Alanui Dr Kihei HI 96753",
    "addr:housenumber":"3750",
    "addr:postcode":"96753",
    "addr:street":"Wailea Alanui Dr",
    "iso:country":"US",
    "sg:address":"3750 Wailea Alanui Dr",
    "sg:city":"Kihei",
    "sg:classifiers":[
        {
            "category":"Food & Beverages",
            "subcategory":"Dairy",
            "type":"Retail Goods"
        },
        {
            "category":"Restaurant",
            "type":"Food & Drink"
        }
    ],
    "sg:phone":"+1 808 879 1711",
    "sg:postcode":"96753",
    "sg:province":"HI",
    "sg:tags":[
        "product",
        "parlor",
        "ice",
        "cream"
    ],
    "wof:name":"Lappert's Ice Cream",
    "wof:placetype":"venue"
},
  "geometry": {"coordinates":[-156.439267,20.686522],"type":"Point"}
}