{
  "type": "Feature",
  "properties": {
    "iso:country":"US",
    "sg:address":"3542 Mamane St",
    "sg:city":"Honokaa",
    "sg:classifiers":[
        {
            "category":"Cinema",
            "subcategory":"Movie Rental",
            "type":"Entertainment"
        }
    ],
    "sg:phone":"+1 808 775 9777",
    "sg:postcode":"96727",
    "sg:province":"HI",
    "sg:tags":[
        "leasing",
        "video",
        "disc",
        "tape"
    ],
    "wof:name":"Cousins Brother's Video",
    "wof:placetype":"venue"
},
  "geometry": {"coordinates":[-155.46665999999999,20.078659],"type":"Point"}
}