{
  "type": "Feature",
  "properties": {
    "iso:country":"US",
    "sg:address":"390 Jade St",
    "sg:city":"Waianae",
    "sg:classifiers":[
        {
            "category":"Health Services",
            "subcategory":"Nursing And Care Facility",
            "type":"Services"
        }
    ],
    "sg:phone":"+1 808 695 9508",
    "sg:postcode":"96792",
    "sg:province":"HI",
    "sg:tags":[
        "home",
        "skilled",
        "convalescent"
    ],
    "sg:website":"www.lihshawaii.com",
    "wof:name":"Leeward Integrated Health Svcs",
    "wof:placetype":"venue"
},
  "geometry": {"coordinates":[-158.208618,21.467492],"type":"Point"}
}