{
  "type": "Feature",
  "properties": {
    "addr:full":"6135 Hana Hwy Haiku HI 96708",
    "addr:housenumber":"6135",
    "addr:postcode":"96708",
    "addr:street":"Hana Hwy",
    "iso:country":"US",
    "sg:address":"6135 Hana Hwy",
    "sg:city":"Haiku",
    "sg:classifiers":[
        {
            "category":"Organizations",
            "subcategory":"Community Association",
            "type":"Services"
        }
    ],
    "sg:phone":"+1 808 572 0741",
    "sg:postcode":"96708",
    "sg:province":"HI",
    "sg:tags":[
        "fraternal"
    ],
    "wof:name":"Honopou Lodge",
    "wof:placetype":"venue"
},
  "geometry": {"coordinates":[-156.26021600000001,20.91396],"type":"Point"}
}