{
  "type": "Feature",
  "properties": {
    "iso:country":"US",
    "sg:address":"2411 S Kihei Rd",
    "sg:city":"Kihei",
    "sg:classifiers":[
        {
            "category":"Food & Beverages",
            "subcategory":"Specialty",
            "type":"Retail Goods"
        }
    ],
    "sg:phone":"+1 808 875 4356",
    "sg:postcode":"96753",
    "sg:province":"HI",
    "sg:tags":[
        "health",
        "diet"
    ],
    "wof:name":"Hawaiian Moons Natural Foods",
    "wof:placetype":"venue"
},
  "geometry": {"coordinates":[-156.446348,20.717624],"type":"Point"}
}