{
  "type": "Feature",
  "properties": {
    "addr:full":"153 Wailupe Cir Honolulu HI 96821",
    "addr:housenumber":"153",
    "addr:postcode":"96821",
    "addr:street":"Wailupe Cir",
    "iso:country":"US",
    "sg:address":"153 Wailupe Cir",
    "sg:city":"Honolulu",
    "sg:classifiers":[
        {
            "category":"Real Estate",
            "subcategory":"Architect",
            "type":"Services"
        }
    ],
    "sg:phone":"+1 808 373 2176",
    "sg:postcode":"96821",
    "sg:province":"HI",
    "wof:name":"Raymond L Cote III",
    "wof:placetype":"venue"
},
  "geometry": {"coordinates":[-157.758724,21.275704],"type":"Point"}
}