{
  "type": "Feature",
  "properties": {
    "iso:country":"US",
    "sg:address":"5518 Kaiwi St",
    "sg:city":"Kailua Kona",
    "sg:classifiers":[
        {
            "category":"Home & Garden",
            "subcategory":"Building Materials",
            "type":"Retail Goods"
        }
    ],
    "sg:phone":"+1 808 329 5110",
    "sg:postcode":"96740",
    "sg:province":"HI",
    "wof:name":"John Wagner Associates Inc",
    "wof:placetype":"venue"
},
  "geometry": {"coordinates":[-156.000563,19.646552],"type":"Point"}
}