{
  "type": "Feature",
  "properties": {
    "addr:full":"424 Dairy Rd Kahului HI 96732",
    "addr:housenumber":"424",
    "addr:postcode":"96732",
    "addr:street":"Dairy Rd",
    "iso:country":"US",
    "sg:address":"424 Dairy Rd",
    "sg:city":"Kahului",
    "sg:classifiers":[
        {
            "category":"Shopping",
            "subcategory":"Department Store",
            "type":"Retail Goods"
        }
    ],
    "sg:phone":"+1 808 871 8553",
    "sg:postcode":"96732",
    "sg:province":"HI",
    "sg:website":"www.mykmart.com",
    "wof:name":"Kmart",
    "wof:placetype":"venue"
},
  "geometry": {"coordinates":[-156.45308299999999,20.884806],"type":"Point"}
}