{
  "type": "Feature",
  "properties": {
    "addr:full":"1787 Wili Pa Loop Wailuku HI 96793",
    "addr:housenumber":"1787",
    "addr:postcode":"96793",
    "addr:street":"Wili Pa Loop",
    "iso:country":"US",
    "sg:address":"1787 Wili Pa Loop",
    "sg:city":"Wailuku",
    "sg:classifiers":[
        {
            "category":"Real Estate",
            "subcategory":"Real Estate Agent",
            "type":"Services"
        }
    ],
    "sg:phone":"+1 808 242 4970",
    "sg:postcode":"96793",
    "sg:province":"HI",
    "wof:name":"Pale Kaiko Hale Pa'i",
    "wof:placetype":"venue"
},
  "geometry": {"coordinates":[-156.50403700000001,20.895722],"type":"Point"}
}