{
  "type": "Feature",
  "properties": {
    "addr:full":"328 N Market St Wailuku HI 96793",
    "addr:housenumber":"328",
    "addr:postcode":"96793",
    "addr:street":"N Market St",
    "iso:country":"US",
    "sg:address":"328 N Market St",
    "sg:city":"Wailuku",
    "sg:classifiers":[
        {
            "category":"Wholesale",
            "subcategory":"Non-durable Goods",
            "type":"Manufacturing & Wholesale Goods"
        },
        {
            "category":"Professional",
            "subcategory":"Advertising",
            "type":"Services"
        }
    ],
    "sg:phone":"+1 808 243 9326",
    "sg:postcode":"96793",
    "sg:province":"HI",
    "sg:tags":[
        "agency",
        "operates"
    ],
    "wof:name":"Sills Creative Consulting",
    "wof:placetype":"venue"
},
  "geometry": {"coordinates":[-156.50698600000001,20.895394],"type":"Point"}
}