{
  "type": "Feature",
  "properties": {
    "iso:country":"US",
    "sg:address":"5669 Alii Dr",
    "sg:city":"Kailua Kona",
    "sg:classifiers":[
        {
            "category":"Shopping",
            "subcategory":"Clothing, Apparel, & Fashions",
            "type":"Retail Goods"
        }
    ],
    "sg:phone":"+1 808 331 1330",
    "sg:postcode":"96740",
    "sg:province":"HI",
    "sg:tags":[
        "item",
        "boutique"
    ],
    "wof:name":"Mermaids By The Sea",
    "wof:placetype":"venue"
},
  "geometry": {"coordinates":[-155.99546000000001,19.640162],"type":"Point"}
}