{
  "type": "Feature",
  "properties": {
    "iso:country":"US",
    "sg:address":"871 Hualalai Rd",
    "sg:city":"Kailua Kona",
    "sg:classifiers":[
        {
            "category":"Banks & Credit Unions",
            "subcategory":"Bank",
            "type":"Services"
        }
    ],
    "sg:phone":"+1 808 329 6579",
    "sg:postcode":"96740",
    "sg:province":"HI",
    "sg:tags":[
        "broker",
        "mortgage"
    ],
    "wof:name":"Allstar Mortgage",
    "wof:placetype":"venue"
},
  "geometry": {"coordinates":[-155.95649599999999,19.620031],"type":"Point"}
}