{
  "type": "Feature",
  "properties": {
    "addr:full":"1345 S Beretania St Honolulu HI 96814",
    "addr:housenumber":"1345",
    "addr:postcode":"96814",
    "addr:street":"S Beretania St",
    "iso:country":"US",
    "sg:address":"1345 S Beretania St",
    "sg:city":"Honolulu",
    "sg:classifiers":[
        {
            "category":"Insurance",
            "subcategory":"Insurance Agent",
            "type":"Services"
        }
    ],
    "sg:phone":"+1 808 593 8221",
    "sg:postcode":"96814",
    "sg:province":"HI",
    "wof:name":"John P Huey Insurance",
    "wof:placetype":"venue"
},
  "geometry": {"coordinates":[-157.843234,21.301588],"type":"Point"}
}