{
  "type": "Feature",
  "properties": {
    "addr:full":"478 Honomakau Rd Kapaau HI 96755",
    "addr:housenumber":"478",
    "addr:postcode":"96755",
    "addr:street":"Honomakau Rd",
    "iso:country":"US",
    "sg:address":"478 Honomakau Rd",
    "sg:city":"Kapaau",
    "sg:classifiers":[
        {
            "category":"Wholesale",
            "subcategory":"Plants",
            "type":"Manufacturing & Wholesale Goods"
        }
    ],
    "sg:phone":"+1 808 889 5323",
    "sg:postcode":"96755",
    "sg:province":"HI",
    "sg:tags":[
        "nursery",
        "tree"
    ],
    "wof:name":"Hawaii Palm Co",
    "wof:placetype":"venue"
},
  "geometry": {"coordinates":[-155.81658400000001,20.243118],"type":"Point"}
}