{
  "type": "Feature",
  "properties": {
    "iso:country":"US",
    "sg:address":"42 Puaole St",
    "sg:city":"Paia",
    "sg:classifiers":[
        {
            "category":"Personal",
            "subcategory":"Beauty Salon",
            "type":"Services"
        }
    ],
    "sg:phone":"+1 808 579 8823",
    "sg:postcode":"96779",
    "sg:province":"HI",
    "wof:name":"Peter Of Paia",
    "wof:placetype":"venue"
},
  "geometry": {"coordinates":[-156.37428,20.902625],"type":"Point"}
}