{
  "type": "Feature",
  "properties": {
    "iso:country":"US",
    "sg:address":"1425 Liliha St",
    "sg:city":"Honolulu",
    "sg:classifiers":[
        {
            "category":"Travel",
            "subcategory":"Travel Agent",
            "type":"Entertainment"
        }
    ],
    "sg:phone":"+1 808 524 8600",
    "sg:postcode":"96817",
    "sg:province":"HI",
    "sg:tags":[
        "agency",
        "bureau"
    ],
    "wof:name":"Asia Air Way Tours & Travel",
    "wof:placetype":"venue"
},
  "geometry": {"coordinates":[-157.861593,21.320236],"type":"Point"}
}