{
  "type": "Feature",
  "properties": {
    "addr:full":"831 Pohukaina St Honolulu HI 96813",
    "addr:housenumber":"831",
    "addr:postcode":"96813",
    "addr:street":"Pohukaina St",
    "iso:country":"US",
    "sg:address":"831 Pohukaina St",
    "sg:city":"Honolulu",
    "sg:classifiers":[
        {
            "category":"Manufacturing",
            "subcategory":"Tools & Machinery",
            "type":"Manufacturing & Wholesale Goods"
        }
    ],
    "sg:phone":"+1 808 591 2225",
    "sg:postcode":"96813",
    "sg:province":"HI",
    "sg:tags":[
        "car",
        "wash"
    ],
    "wof:name":"Tsunami Express Wash",
    "wof:placetype":"venue"
},
  "geometry": {"coordinates":[-157.85705300000001,21.296599],"type":"Point"}
}