{
  "type": "Feature",
  "properties": {
    "iso:country":"US",
    "sg:address":"1068 Ka Uka Blvd",
    "sg:city":"Waipahu",
    "sg:classifiers":[
        {
            "category":"Restaurant",
            "type":"Food & Drink"
        }
    ],
    "sg:phone":"+1 808 677 7744",
    "sg:postcode":"96797",
    "sg:province":"HI",
    "sg:tags":[
        "caterer"
    ],
    "sg:website":"www.acateredexperience.com",
    "wof:name":"A Catered Experience",
    "wof:placetype":"venue"
},
  "geometry": {"coordinates":[-158.00368599999999,21.420888],"type":"Point"}
}