{
  "type": "Feature",
  "properties": {
    "iso:country":"US",
    "sg:address":"7266 Mamalahoa Hwy",
    "sg:city":"Kealakekua",
    "sg:classifiers":[
        {
            "category":"Health Services",
            "subcategory":"Doctor",
            "type":"Services"
        }
    ],
    "sg:phone":"+1 808 322 3434",
    "sg:postcode":"96750",
    "sg:province":"HI",
    "sg:tags":[
        "physician",
        "surgeon"
    ],
    "wof:name":"Sira Santad INC",
    "wof:placetype":"venue"
},
  "geometry": {"coordinates":[-155.929428,19.543811],"type":"Point"}
}