{
  "type": "Feature",
  "properties": {
    "iso:country":"US",
    "sg:address":"740 Halekauwila St",
    "sg:city":"Honolulu",
    "sg:classifiers":[
        {
            "category":"Wholesale",
            "subcategory":"Motor Vehicles",
            "type":"Manufacturing & Wholesale Goods"
        }
    ],
    "sg:phone":"+1 808 591 3075",
    "sg:postcode":"96813",
    "sg:province":"HI",
    "sg:tags":[
        "automobile",
        "truck",
        "broker"
    ],
    "wof:name":"Subaru Of Hawaii",
    "wof:placetype":"venue"
},
  "geometry": {"coordinates":[-157.85731799999999,21.299146],"type":"Point"}
}