{
  "type": "Feature",
  "properties": {
    "iso:country":"US",
    "sg:address":"745 Fort Street Ml",
    "sg:city":"Honolulu",
    "sg:classifiers":[
        {
            "category":"Wholesale",
            "subcategory":"Apparel",
            "type":"Manufacturing & Wholesale Goods"
        }
    ],
    "sg:phone":"+1 808 561 5606",
    "sg:postcode":"96813",
    "sg:province":"HI",
    "sg:tags":[
        "export",
        "sportswear"
    ],
    "wof:name":"Lance and Company Inc",
    "wof:placetype":"venue"
},
  "geometry": {"coordinates":[-157.863764,21.308151],"type":"Point"}
}