{
  "type": "Feature",
  "properties": {
    "iso:country":"US",
    "sg:address":"53 Amala Pl",
    "sg:city":"Kahului",
    "sg:classifiers":[
        {
            "category":"Manufacturing",
            "subcategory":"Metals",
            "type":"Manufacturing & Wholesale Goods"
        }
    ],
    "sg:phone":"+1 808 871 0962",
    "sg:postcode":"96732",
    "sg:province":"HI",
    "sg:tags":[
        "sling"
    ],
    "wof:name":"Maui Crane Svc LLC",
    "wof:placetype":"venue"
},
  "geometry": {"coordinates":[-156.46266800000001,20.895734],"type":"Point"}
}