{
  "type": "Feature",
  "properties": {
    "addr:full":"841 Bishop St Honolulu HI 96813",
    "addr:housenumber":"841",
    "addr:postcode":"96813",
    "addr:street":"Bishop St",
    "iso:country":"US",
    "sg:address":"841 Bishop St",
    "sg:city":"Honolulu",
    "sg:classifiers":[
        {
            "category":"Banks & Credit Unions",
            "subcategory":"Bank",
            "type":"Services"
        }
    ],
    "sg:phone":"+1 808 531 6636",
    "sg:postcode":"96813",
    "sg:province":"HI",
    "sg:tags":[
        "broker",
        "mortgage"
    ],
    "wof:name":"Premier Federal Mortgage Inc",
    "wof:placetype":"venue"
},
  "geometry": {"coordinates":[-157.86240799999999,21.307771],"type":"Point"}
}