{
  "type": "Feature",
  "properties": {
    "iso:country":"US",
    "sg:address":"328 Cooke St",
    "sg:city":"Honolulu",
    "sg:classifiers":[
        {
            "category":"Professional",
            "subcategory":"Business Services",
            "type":"Services"
        }
    ],
    "sg:phone":"+1 808 589 1922",
    "sg:postcode":"96813",
    "sg:province":"HI",
    "sg:tags":[
        "merchandising"
    ],
    "wof:name":"Sae Hak Enterprises Inc",
    "wof:placetype":"venue"
},
  "geometry": {"coordinates":[-157.86025000000001,21.297185],"type":"Point"}
}