{
  "type": "Feature",
  "properties": {
    "iso:country":"US",
    "sg:address":"1001 Ipo Pl",
    "sg:city":"Honolulu",
    "sg:classifiers":[
        {
            "category":"Professional",
            "subcategory":"Management & Consulting",
            "type":"Services"
        }
    ],
    "sg:phone":"+1 808 791 1680",
    "sg:postcode":"96816",
    "sg:province":"HI",
    "sg:tags":[
        "business"
    ],
    "wof:name":"Sh Consulting LLC",
    "wof:placetype":"venue"
},
  "geometry": {"coordinates":[-157.79011499999999,21.275149],"type":"Point"}
}