{
  "type": "Feature",
  "properties": {
    "iso:country":"US",
    "sg:address":"300 Saratoga Rd",
    "sg:city":"Honolulu",
    "sg:classifiers":[
        {
            "category":"Government",
            "subcategory":"Post Office",
            "type":"Public Place"
        }
    ],
    "sg:phone":"+1 808 000 1111",
    "sg:postcode":"96815",
    "sg:province":"HI",
    "wof:name":"US Post Office",
    "wof:placetype":"venue"
},
  "geometry": {"coordinates":[-157.83155500000001,21.281037],"type":"Point"}
}