{
  "type": "Feature",
  "properties": {
    "iso:country":"US",
    "sg:address":"1380 Lusitana St",
    "sg:city":"Honolulu",
    "sg:classifiers":[
        {
            "category":"Health Services",
            "subcategory":"Doctor",
            "type":"Services"
        }
    ],
    "sg:phone":"+1 808 524 0066",
    "sg:postcode":"96813",
    "sg:province":"HI",
    "sg:tags":[
        "physician",
        "surgeon",
        "medical"
    ],
    "wof:name":"Medical Specialty Associates",
    "wof:placetype":"venue"
},
  "geometry": {"coordinates":[-157.85279399999999,21.308206],"type":"Point"}
}