{
  "type": "Feature",
  "properties": {
    "iso:country":"US",
    "sg:address":"928 Lower Main St",
    "sg:city":"Wailuku",
    "sg:classifiers":[
        {
            "category":"Retail",
            "subcategory":"Auto Repair",
            "type":"Services"
        }
    ],
    "sg:phone":"+1 808 242 6555",
    "sg:postcode":"96793",
    "sg:province":"HI",
    "sg:tags":[
        "body"
    ],
    "wof:name":"Maui Magic Auto Body LLC",
    "wof:placetype":"venue"
},
  "geometry": {"coordinates":[-156.489282,20.899368],"type":"Point"}
}