{
  "type": "Feature",
  "properties": {
    "iso:country":"US",
    "sg:address":"3412 Kahikolu Way",
    "sg:city":"Honolulu",
    "sg:classifiers":[
        {
            "category":"Professional",
            "subcategory":"Secretarial Services",
            "type":"Services"
        }
    ],
    "sg:phone":"+1 808 833 2242",
    "sg:postcode":"96818",
    "sg:province":"HI",
    "sg:tags":[
        "reporting"
    ],
    "wof:name":"Steno LLC",
    "wof:placetype":"venue"
},
  "geometry": {"coordinates":[-157.91464500000001,21.344649],"type":"Point"}
}