{
  "type": "Feature",
  "properties": {
    "iso:country":"US",
    "sg:address":"200 Keolalani St",
    "sg:city":"Makawao",
    "sg:classifiers":[
        {
            "category":"Recreation",
            "type":"Entertainment"
        }
    ],
    "sg:phone":"+1 808 572 0550",
    "sg:postcode":"96768",
    "sg:province":"HI",
    "sg:tags":[
        "tours",
        "sightseeing"
    ],
    "wof:name":"Hana Cassette Guide",
    "wof:placetype":"venue"
},
  "geometry": {"coordinates":[-156.35486399999999,20.841563],"type":"Point"}
}