{
  "type": "Feature",
  "properties": {
    "iso:country":"US",
    "sg:address":"765 Hooluu St",
    "sg:city":"Pearl City",
    "sg:classifiers":[
        {
            "category":"Building & Trades",
            "subcategory":"Construction",
            "type":"Services"
        }
    ],
    "sg:phone":"+1 808 671 0410",
    "sg:postcode":"96782",
    "sg:province":"HI",
    "sg:tags":[
        "pumping",
        "contractor"
    ],
    "wof:name":"A 1 Grease Trap Man",
    "wof:placetype":"venue"
},
  "geometry": {"coordinates":[-157.961039,21.402684],"type":"Point"}
}