{
  "type": "Feature",
  "properties": {
    "iso:country":"US",
    "sg:address":"5355 Papai St",
    "sg:city":"Honolulu",
    "sg:classifiers":[
        {
            "category":"Professional",
            "subcategory":"Computer Services",
            "type":"Services"
        }
    ],
    "sg:phone":"+1 808 373 1714",
    "sg:postcode":"96821",
    "sg:province":"HI",
    "sg:tags":[
        "related"
    ],
    "wof:name":"CC Enterprise",
    "wof:placetype":"venue"
},
  "geometry": {"coordinates":[-157.74807799999999,21.279903],"type":"Point"}
}