{
  "type": "Feature",
  "properties": {
    "addr:full":"270 Kuulei Rd Kailua HI 96734",
    "addr:housenumber":"270",
    "addr:postcode":"96734",
    "addr:street":"Kuulei Rd",
    "iso:country":"US",
    "sg:address":"270 Kuulei Rd",
    "sg:city":"Kailua",
    "sg:classifiers":[
        {
            "category":"Building & Trades",
            "subcategory":"Cleaning & Sanitation",
            "type":"Services"
        }
    ],
    "sg:phone":"+1 808 262 2200",
    "sg:postcode":"96734",
    "sg:province":"HI",
    "sg:tags":[
        "janitor"
    ],
    "wof:name":"Nook & Cranny",
    "wof:placetype":"venue"
},
  "geometry": {"coordinates":[-157.74068600000001,21.396314],"type":"Point"}
}