{
  "type": "Feature",
  "properties": {
    "addr:full":"1068 Kaaholo St Waipahu HI 96797",
    "addr:housenumber":"1068",
    "addr:postcode":"96797",
    "addr:street":"Kaaholo St",
    "iso:country":"US",
    "sg:address":"1068 Kaaholo St",
    "sg:city":"Waipahu",
    "sg:classifiers":[
        {
            "category":"Food & Beverages",
            "subcategory":"Specialty",
            "type":"Retail Goods"
        }
    ],
    "sg:phone":"+1 808 678 1992",
    "sg:postcode":"96797",
    "sg:province":"HI",
    "sg:tags":[
        "health",
        "diet"
    ],
    "wof:name":"Matol Botanical Intl LTD",
    "wof:placetype":"venue"
},
  "geometry": {"coordinates":[-158.02417800000001,21.396887],"type":"Point"}
}