{
  "type": "Feature",
  "properties": {
    "iso:country":"US",
    "sg:address":"413 Naulu Pl",
    "sg:city":"Kailua Kona",
    "sg:classifiers":[
        {
            "category":"Professional",
            "subcategory":"Computer Services",
            "type":"Services"
        }
    ],
    "sg:phone":"+1 808 355 8337",
    "sg:postcode":"96740",
    "sg:province":"HI",
    "sg:tags":[
        "datum"
    ],
    "wof:name":"Nueworld",
    "wof:placetype":"venue"
},
  "geometry": {"coordinates":[-155.99537100000001,19.67407],"type":"Point"}
}