{
  "type": "Feature",
  "properties": {
    "iso:country":"US",
    "sg:address":"930 Mc Cully St",
    "sg:city":"Honolulu",
    "sg:classifiers":[
        {
            "category":"Food & Beverages",
            "subcategory":"Specialty",
            "type":"Retail Goods"
        }
    ],
    "sg:phone":"+1 808 955 0660",
    "sg:postcode":"96826",
    "sg:province":"HI",
    "sg:tags":[
        "health",
        "diet"
    ],
    "wof:name":"Suplinx",
    "wof:placetype":"venue"
},
  "geometry": {"coordinates":[-157.830129,21.294878],"type":"Point"}
}