{
  "type": "Feature",
  "properties": {
    "addr:full":"2736 Peter St Honolulu HI 96816",
    "addr:housenumber":"2736",
    "addr:postcode":"96816",
    "addr:street":"Peter St",
    "iso:country":"US",
    "sg:address":"2736 Peter St",
    "sg:city":"Honolulu",
    "sg:classifiers":[
        {
            "category":"Professional",
            "subcategory":"Business Services",
            "type":"Services"
        }
    ],
    "sg:phone":"+1 808 734 7055",
    "sg:postcode":"96816",
    "sg:province":"HI",
    "wof:name":"Best/Fx Inc",
    "wof:placetype":"venue"
},
  "geometry": {"coordinates":[-157.79902000000001,21.302908],"type":"Point"}
}