{
  "type": "Feature",
  "properties": {
    "iso:country":"US",
    "sg:address":"1038 Kikowaena Pl",
    "sg:city":"Honolulu",
    "sg:classifiers":[
        {
            "category":"Wholesale",
            "subcategory":"Drugs",
            "type":"Manufacturing & Wholesale Goods"
        }
    ],
    "sg:phone":"+1 808 839 0242",
    "sg:postcode":"96819",
    "sg:province":"HI",
    "sg:tags":[
        "cosmetic"
    ],
    "wof:name":"Hawaiian Tropic Suncare Prods",
    "wof:placetype":"venue"
},
  "geometry": {"coordinates":[-157.89363900000001,21.343427],"type":"Point"}
}