{
  "type": "Feature",
  "properties": {
    "addr:full":"834 Leomana Way Waipahu HI 96797",
    "addr:housenumber":"834",
    "addr:postcode":"96797",
    "addr:street":"Leomana Way",
    "iso:country":"US",
    "sg:address":"834 Leomana Way",
    "sg:city":"Waipahu",
    "sg:classifiers":[
        {
            "category":"Education",
            "subcategory":"Special Training",
            "type":"Public Place"
        }
    ],
    "sg:phone":"+1 808 680 9544",
    "sg:postcode":"96797",
    "sg:province":"HI",
    "wof:name":"Kim Marilyn Liu Music Studio",
    "wof:placetype":"venue"
},
  "geometry": {"coordinates":[-157.997218,21.408996],"type":"Point"}
}