{
  "type": "Feature",
  "properties": {
    "iso:country":"US",
    "sg:address":"377 Keahole St",
    "sg:city":"Honolulu",
    "sg:classifiers":[
        {
            "category":"Restaurant",
            "type":"Food & Drink"
        }
    ],
    "sg:phone":"+1 808 396 1919",
    "sg:postcode":"96825",
    "sg:province":"HI",
    "sg:tags":[
        "eating"
    ],
    "wof:name":"Shack Sports Bar & Grill",
    "wof:placetype":"venue"
},
  "geometry": {"coordinates":[-157.70769200000001,21.285752],"type":"Point"}
}