{
  "type": "Feature",
  "properties": {
    "iso:country":"US",
    "sg:address":"2827 Umalu Pl",
    "sg:city":"Kihei",
    "sg:classifiers":[
        {
            "category":"Building & Trades",
            "subcategory":"Construction",
            "type":"Services"
        }
    ],
    "sg:phone":"+1 808 874 3566",
    "sg:postcode":"96753",
    "sg:province":"HI",
    "sg:tags":[
        "repairing",
        "remodeling",
        "contractor"
    ],
    "wof:name":"Barrera Randall General Contr",
    "wof:placetype":"venue"
},
  "geometry": {"coordinates":[-156.436949,20.709248],"type":"Point"}
}