{
  "type": "Feature",
  "properties": {
    "addr:full":"1026 Lowell Pl Honolulu HI 96817",
    "addr:housenumber":"1026",
    "addr:postcode":"96817",
    "addr:street":"Lowell Pl",
    "iso:country":"US",
    "sg:address":"1026 Lowell Pl",
    "sg:city":"Honolulu",
    "sg:classifiers":[
        {
            "category":"Building & Trades",
            "subcategory":"Plumbing",
            "type":"Services"
        }
    ],
    "sg:phone":"+1 808 845 1547",
    "sg:postcode":"96817",
    "sg:province":"HI",
    "sg:tags":[
        "contractor"
    ],
    "wof:name":"Neals Plumbing",
    "wof:placetype":"venue"
},
  "geometry": {"coordinates":[-157.864574,21.32824],"type":"Point"}
}