{
  "type": "Feature",
  "properties": {
    "addr:full":"6765 Kuakini Hwy Kailua Kona HI 96740",
    "addr:housenumber":"6765",
    "addr:postcode":"96740",
    "addr:street":"Kuakini Hwy",
    "iso:country":"US",
    "sg:address":"6765 Kuakini Hwy",
    "sg:city":"Kailua Kona",
    "sg:classifiers":[
        {
            "category":"Real Estate",
            "subcategory":"Architect",
            "type":"Services"
        }
    ],
    "sg:phone":"+1 808 322 0000",
    "sg:postcode":"96740",
    "sg:province":"HI",
    "wof:name":"Robert Nespor & Assoc",
    "wof:placetype":"venue"
},
  "geometry": {"coordinates":[-155.95326900000001,19.584286],"type":"Point"}
}