{
  "type": "Feature",
  "properties": {
    "iso:country":"US",
    "sg:address":"41 Laimana St",
    "sg:city":"Hilo",
    "sg:classifiers":[
        {
            "category":"Shopping",
            "type":"Retail Goods"
        }
    ],
    "sg:phone":"+1 808 969 3100",
    "sg:postcode":"96720",
    "sg:province":"HI",
    "sg:tags":[
        "surgical",
        "orthopedic",
        "appliance",
        "merchandise",
        "mfg"
    ],
    "wof:name":"Big Island Orthopedic Services",
    "wof:placetype":"venue"
},
  "geometry": {"coordinates":[-155.09445099999999,19.721846],"type":"Point"}
}