{
  "type": "Feature",
  "properties": {
    "iso:country":"US",
    "sg:address":"5663 Palani Rd",
    "sg:city":"Kailua Kona",
    "sg:classifiers":[
        {
            "category":"Shopping",
            "subcategory":"Optical Goods",
            "type":"Retail Goods"
        },
        {
            "category":"Wholesale",
            "subcategory":"Durable Goods & Equipment",
            "type":"Manufacturing & Wholesale Goods"
        }
    ],
    "sg:phone":"+1 808 329 9227",
    "sg:postcode":"96740",
    "sg:province":"HI",
    "sg:tags":[
        "sun",
        "goggles",
        "sunglasses"
    ],
    "wof:name":"Kona Coast Sunglasses Co",
    "wof:placetype":"venue"
},
  "geometry": {"coordinates":[-155.99310600000001,19.647206],"type":"Point"}
}