{
  "type": "Feature",
  "properties": {
    "iso:country":"US",
    "sg:address":"419 Waiakamilo Rd",
    "sg:city":"Honolulu",
    "sg:classifiers":[
        {
            "category":"Shopping",
            "subcategory":"Florist",
            "type":"Retail Goods"
        }
    ],
    "sg:phone":"+1 808 847 0494",
    "sg:postcode":"96817",
    "sg:province":"HI",
    "wof:name":"Nita's Flower Market",
    "wof:placetype":"venue"
},
  "geometry": {"coordinates":[-157.87708799999999,21.322762],"type":"Point"}
}