{
  "type": "Feature",
  "properties": {
    "addr:full":"59 Kamehameha Hwy Haleiwa HI 96712",
    "addr:housenumber":"59",
    "addr:postcode":"96712",
    "addr:street":"Kamehameha Hwy",
    "iso:country":"US",
    "sg:address":"59 Kamehameha Hwy",
    "sg:city":"Haleiwa",
    "sg:classifiers":[
        {
            "category":"Retail",
            "subcategory":"Laundry & Dry Cleaning",
            "type":"Services"
        }
    ],
    "sg:phone":"+1 808 486 6444",
    "sg:postcode":"96712",
    "sg:province":"HI",
    "wof:name":"Ocean Chem-Dry Carpet Cleaning",
    "wof:placetype":"venue"
},
  "geometry": {"coordinates":[-158.10298,21.591875],"type":"Point"}
}