{
  "type": "Feature",
  "properties": {
    "addr:full":"2430 Oka St Kilauea HI 96754",
    "addr:housenumber":"2430",
    "addr:postcode":"96754",
    "addr:street":"Oka St",
    "iso:country":"US",
    "sg:address":"2430 Oka St",
    "sg:city":"Kilauea",
    "sg:classifiers":[
        {
            "category":"Restaurant",
            "type":"Food & Drink"
        }
    ],
    "sg:phone":"+1 808 634 5328",
    "sg:postcode":"96754",
    "sg:province":"HI",
    "wof:name":"Starvin Marvin's Kilauea Deli",
    "wof:placetype":"venue"
},
  "geometry": {"coordinates":[-159.40661,22.20997],"type":"Point"}
}