{
  "type": "Feature",
  "properties": {
    "addr:full":"91-775 Papipi Rd Ewa Beach HI 96706",
    "addr:housenumber":"91-775",
    "addr:postcode":"96706",
    "addr:street":"Papipi Rd",
    "iso:country":"US",
    "sg:address":"91-775 Papipi Rd",
    "sg:city":"Ewa Beach",
    "sg:classifiers":[
        {
            "category":"Restaurant",
            "type":"Food & Drink"
        }
    ],
    "sg:menulink":"http://www.allmenus.com/hi/ewa/63958-dominos-pizza/menu/",
    "sg:phone":"+1 808 689 8323",
    "sg:postcode":"96706",
    "sg:province":"HI",
    "sg:tags":[
        "american",
        "wing",
        "pizza"
    ],
    "wof:name":"Domino's Pizza",
    "wof:placetype":"venue"
},
  "geometry": {"coordinates":[-158.013406,21.316086],"type":"Point"}
}