{
  "type": "Feature",
  "properties": {
    "iso:country":"US",
    "sg:address":"546 Akaawa St",
    "sg:city":"Kapolei",
    "sg:classifiers":[
        {
            "category":"Building & Trades",
            "subcategory":"Construction",
            "type":"Services"
        }
    ],
    "sg:phone":"+1 808 672 3465",
    "sg:postcode":"96707",
    "sg:province":"HI",
    "sg:tags":[
        "contractor"
    ],
    "wof:name":"Island Pacific Interiors",
    "wof:placetype":"venue"
},
  "geometry": {"coordinates":[-158.08355299999999,21.34046],"type":"Point"}
}