{
  "type": "Feature",
  "properties": {
    "addr:full":"708 Hui Alala St Kaneohe HI 96744",
    "addr:housenumber":"708",
    "addr:postcode":"96744",
    "addr:street":"Hui Alala St",
    "iso:country":"US",
    "sg:address":"708 Hui Alala St",
    "sg:city":"Kaneohe",
    "sg:classifiers":[
        {
            "category":"Banks & Credit Unions",
            "subcategory":"Bank",
            "type":"Services"
        }
    ],
    "sg:phone":"+1 808 239 5911",
    "sg:postcode":"96744",
    "sg:province":"HI",
    "sg:tags":[
        "broker",
        "mortgage"
    ],
    "wof:name":"Evelyn Takara",
    "wof:placetype":"venue"
},
  "geometry": {"coordinates":[-157.837197,21.437583],"type":"Point"}
}