{
  "type": "Feature",
  "properties": {
    "iso:country":"US",
    "sg:address":"1475 N King St",
    "sg:city":"Honolulu",
    "sg:classifiers":[
        {
            "category":"Professional",
            "subcategory":"Business Services",
            "type":"Services"
        }
    ],
    "sg:phone":"+1 808 842 0933",
    "sg:postcode":"96817",
    "sg:province":"HI",
    "wof:name":"Surge Ahead",
    "wof:placetype":"venue"
},
  "geometry": {"coordinates":[-157.872478,21.329079],"type":"Point"}
}