{
  "type": "Feature",
  "properties": {
    "iso:country":"US",
    "sg:address":"1126 12th Ave",
    "sg:city":"Honolulu",
    "sg:classifiers":[
        {
            "category":"Retail",
            "subcategory":"Repair Shop",
            "type":"Services"
        }
    ],
    "sg:phone":"+1 808 737 0389",
    "sg:postcode":"96816",
    "sg:province":"HI",
    "sg:tags":[
        "jewelry"
    ],
    "wof:name":"Kilikina",
    "wof:placetype":"venue"
},
  "geometry": {"coordinates":[-157.799115,21.28226],"type":"Point"}
}