{
  "type": "Feature",
  "properties": {
    "iso:country":"US",
    "sg:address":"1100 Kamokila Blvd",
    "sg:city":"Kapolei",
    "sg:classifiers":[
        {
            "category":"Government",
            "subcategory":"Police Station",
            "type":"Public Place"
        }
    ],
    "sg:phone":"+1 808 692 4238",
    "sg:postcode":"96707",
    "sg:province":"HI",
    "sg:tags":[
        "department",
        "protection"
    ],
    "wof:name":"Honolulu Police Dept",
    "wof:placetype":"venue"
},
  "geometry": {"coordinates":[-158.08063000000001,21.335433],"type":"Point"}
}