{
  "type": "Feature",
  "properties": {
    "iso:country":"US",
    "sg:address":"100 Kaukahi St",
    "sg:city":"Kihei",
    "sg:classifiers":[
        {
            "category":"Restaurant",
            "type":"Food & Drink"
        }
    ],
    "sg:phone":"+1 808 879 4060",
    "sg:postcode":"96753",
    "sg:province":"HI",
    "wof:name":"Fairway Restaurant Inc",
    "wof:placetype":"venue"
},
  "geometry": {"coordinates":[-156.43657999999999,20.676189],"type":"Point"}
}