{
  "type": "Feature",
  "properties": {
    "iso:country":"US",
    "sg:address":"2895 Kalakaua Ave",
    "sg:city":"Honolulu",
    "sg:classifiers":[
        {
            "category":"Real Estate",
            "subcategory":"Real Estate Agent",
            "type":"Services"
        }
    ],
    "sg:phone":"+1 808 924 8555",
    "sg:postcode":"96815",
    "sg:province":"HI",
    "wof:name":"Prestige Properties",
    "wof:placetype":"venue"
},
  "geometry": {"coordinates":[-157.82044999999999,21.262299],"type":"Point"}
}