{
  "type": "Feature",
  "properties": {
    "addr:full":"5751 Kini Loop Kailua Kona HI 96740",
    "addr:housenumber":"5751",
    "addr:postcode":"96740",
    "addr:street":"Kini Loop",
    "iso:country":"US",
    "sg:address":"5751 Kini Loop",
    "sg:city":"Kailua Kona",
    "sg:classifiers":[
        {
            "category":"Professional",
            "subcategory":"Engineering",
            "type":"Services"
        }
    ],
    "sg:phone":"+1 808 334 0322",
    "sg:postcode":"96740",
    "sg:province":"HI",
    "wof:name":"Witcher Engineering",
    "wof:placetype":"venue"
},
  "geometry": {"coordinates":[-155.97861900000001,19.638809],"type":"Point"}
}