{
  "type": "Feature",
  "properties": {
    "iso:country":"US",
    "sg:address":"125 Uaoa Loop",
    "sg:city":"Haiku",
    "sg:phone":"+1 808 572 7293",
    "sg:postcode":"96708",
    "sg:province":"HI",
    "sg:tags":[
        "farm",
        "field",
        "crop"
    ],
    "wof:name":"Windward Tropicals Inc",
    "wof:placetype":"venue"
},
  "geometry": {"coordinates":[-156.28032899999999,20.923517],"type":"Point"}
}