{
  "type": "Feature",
  "properties": {
    "addr:full":"1005 Moanalua Rd Aiea HI 96701",
    "addr:housenumber":"1005",
    "addr:postcode":"96701",
    "addr:street":"Moanalua Rd",
    "iso:country":"US",
    "sg:address":"1005 Moanalua Rd",
    "sg:city":"Aiea",
    "sg:classifiers":[
        {
            "category":"Food & Beverages",
            "subcategory":"Bakery",
            "type":"Retail Goods"
        }
    ],
    "sg:phone":"+1 808 483 0492",
    "sg:postcode":"96701",
    "sg:province":"HI",
    "sg:tags":[
        "cookie",
        "cracker"
    ],
    "wof:name":"Cookie Corner",
    "wof:placetype":"venue"
},
  "geometry": {"coordinates":[-157.94079500000001,21.385893],"type":"Point"}
}