{
  "type": "Feature",
  "properties": {
    "iso:country":"US",
    "sg:address":"404 Paui Pl",
    "sg:city":"Honolulu",
    "sg:classifiers":[
        {
            "category":"Restaurant",
            "type":"Food & Drink"
        }
    ],
    "sg:phone":"+1 808 531 8609",
    "sg:postcode":"96817",
    "sg:province":"HI",
    "sg:tags":[
        "eating"
    ],
    "wof:name":"Ongies",
    "wof:placetype":"venue"
},
  "geometry": {"coordinates":[-157.85635400000001,21.323426],"type":"Point"}
}