{
  "type": "Feature",
  "properties": {
    "addr:full":"2801 Lai Rd Honolulu HI 96816",
    "addr:housenumber":"2801",
    "addr:postcode":"96816",
    "addr:street":"Lai Rd",
    "iso:country":"US",
    "sg:address":"2801 Lai Rd",
    "sg:city":"Honolulu",
    "sg:classifiers":[
        {
            "category":"Wholesale",
            "subcategory":"Plants",
            "type":"Manufacturing & Wholesale Goods"
        }
    ],
    "sg:phone":"+1 808 732 5614",
    "sg:postcode":"96816",
    "sg:province":"HI",
    "sg:tags":[
        "supply"
    ],
    "wof:name":"Harold Narahara",
    "wof:placetype":"venue"
},
  "geometry": {"coordinates":[-157.78675000000001,21.308509],"type":"Point"}
}