{
  "type": "Feature",
  "properties": {
    "addr:full":"264 Kaiulani Ave Honolulu HI 96815",
    "addr:postcode":"96815",
    "addr:street":"Kaiulani Ave",
    "iso:country":"US",
    "sg:address":"264 Kaiulani Ave",
    "sg:city":"Honolulu",
    "sg:classifiers":[
        {
            "category":"Shopping",
            "subcategory":"Department Store",
            "type":"Retail Goods"
        }
    ],
    "sg:phone":"+1 808 923 3050",
    "sg:postcode":"96815",
    "sg:province":"HI",
    "wof:name":"Wal-Mart",
    "wof:placetype":"venue"
},
  "geometry": {"coordinates":[-157.82266899999999,21.278684],"type":"Point"}
}