{
  "type": "Feature",
  "properties": {
    "iso:country":"US",
    "sg:address":"737 Fort Weaver Rd",
    "sg:city":"Ewa Beach",
    "sg:classifiers":[
        {
            "category":"Real Estate",
            "subcategory":"Real Estate Operator",
            "type":"Services"
        }
    ],
    "sg:phone":"+1 808 689 8887",
    "sg:postcode":"96706",
    "sg:province":"HI",
    "sg:tags":[
        "building",
        "apartment"
    ],
    "wof:name":"G & F Apartments",
    "wof:placetype":"venue"
},
  "geometry": {"coordinates":[-158.01145600000001,21.314288],"type":"Point"}
}