{
  "type": "Feature",
  "properties": {
    "addr:full":"689 Kakoi St Honolulu HI 96819",
    "addr:housenumber":"689",
    "addr:postcode":"96819",
    "addr:street":"Kakoi St",
    "iso:country":"US",
    "sg:address":"689 Kakoi St",
    "sg:city":"Honolulu",
    "sg:classifiers":[
        {
            "category":"Retail",
            "subcategory":"Repair Shop",
            "type":"Services"
        }
    ],
    "sg:phone":"+1 808 836 3881",
    "sg:postcode":"96819",
    "sg:province":"HI",
    "sg:tags":[
        "appliance",
        "household",
        "electrical"
    ],
    "wof:name":"TNT Services Inc",
    "wof:placetype":"venue"
},
  "geometry": {"coordinates":[-157.89587299999999,21.337214],"type":"Point"}
}