{
  "type": "Feature",
  "properties": {
    "iso:country":"US",
    "sg:address":"4515 Amakihi Rd",
    "sg:city":"Kekaha",
    "sg:classifiers":[
        {
            "category":"Retail",
            "subcategory":"Repair Shop",
            "type":"Services"
        }
    ],
    "sg:phone":"+1 808 639 4149",
    "sg:postcode":"96752",
    "sg:province":"HI",
    "sg:tags":[
        "plumbing",
        "drain",
        "cleaning",
        "sewer"
    ],
    "wof:name":"Pete's Service & Repair",
    "wof:placetype":"venue"
},
  "geometry": {"coordinates":[-159.71932200000001,21.968987],"type":"Point"}
}