{
  "type": "Feature",
  "properties": {
    "iso:country":"US",
    "sg:address":"2074 Young St",
    "sg:city":"Honolulu",
    "sg:classifiers":[
        {
            "category":"Personal",
            "subcategory":"Beauty Salon",
            "type":"Services"
        }
    ],
    "sg:phone":"+1 808 949 6598",
    "sg:postcode":"96826",
    "sg:province":"HI",
    "sg:tags":[
        "shop"
    ],
    "wof:name":"Bev Lyns Beauty Salon",
    "wof:placetype":"venue"
},
  "geometry": {"coordinates":[-157.82899699999999,21.295535],"type":"Point"}
}