{
  "type": "Feature",
  "properties": {
    "addr:full":"933 Keaahala Pl Kaneohe HI 96744",
    "addr:housenumber":"933",
    "addr:postcode":"96744",
    "addr:street":"Keaahala Pl",
    "iso:country":"US",
    "sg:address":"933 Keaahala Pl",
    "sg:city":"Kaneohe",
    "sg:classifiers":[
        {
            "category":"Building & Trades",
            "subcategory":"Construction",
            "type":"Services"
        }
    ],
    "sg:phone":"+1 808 247 1699",
    "sg:postcode":"96744",
    "sg:province":"HI",
    "sg:tags":[
        "contractor"
    ],
    "wof:name":"Convenient Home Builders",
    "wof:placetype":"venue"
},
  "geometry": {"coordinates":[-157.80334199999999,21.413328],"type":"Point"}
}