{
  "type": "Feature",
  "properties": {
    "addr:full":"905 Waipahu St Waipahu HI 96797",
    "addr:housenumber":"905",
    "addr:postcode":"96797",
    "addr:street":"Waipahu St",
    "iso:country":"US",
    "sg:address":"905 Waipahu St",
    "sg:city":"Waipahu",
    "sg:classifiers":[
        {
            "category":"Social Services",
            "subcategory":"Child Care",
            "type":"Services"
        }
    ],
    "sg:phone":"+1 808 677 7333",
    "sg:postcode":"96797",
    "sg:province":"HI",
    "wof:name":"Refuge Christian Daycare Ctr",
    "wof:placetype":"venue"
},
  "geometry": {"coordinates":[-158.00550000000001,21.387188],"type":"Point"}
}