{
  "type": "Feature",
  "properties": {
    "iso:country":"US",
    "sg:address":"1976 Kaumana Dr",
    "sg:city":"Hilo",
    "sg:classifiers":[
        {
            "category":"Shopping",
            "subcategory":"Discount & Variety Stores",
            "type":"Retail Goods"
        }
    ],
    "sg:phone":"+1 808 969 9208",
    "sg:postcode":"96720",
    "sg:province":"HI",
    "sg:tags":[
        "merchandise",
        "general"
    ],
    "wof:name":"All Things Store",
    "wof:placetype":"venue"
},
  "geometry": {"coordinates":[-155.14136999999999,19.68543],"type":"Point"}
}