{
  "type": "Feature",
  "properties": {
    "iso:country":"US",
    "sg:address":"3593 Mamane St",
    "sg:city":"Honokaa",
    "sg:classifiers":[
        {
            "category":"Shopping",
            "subcategory":"Gifts & Souvenirs",
            "type":"Retail Goods"
        },
        {
            "category":"Shopping",
            "subcategory":"Clothing, Apparel, & Fashions",
            "type":"Retail Goods"
        }
    ],
    "sg:phone":"+1 808 775 1016",
    "sg:postcode":"96727",
    "sg:province":"HI",
    "wof:name":"Maya's Clothing & Gifts",
    "wof:placetype":"venue"
},
  "geometry": {"coordinates":[-155.46692200000001,20.078612],"type":"Point"}
}