{
  "type": "Feature",
  "properties": {
    "addr:full":"2239 Waikolu Way Honolulu HI 96815",
    "addr:housenumber":"2239",
    "addr:postcode":"96815",
    "addr:street":"Waikolu Way",
    "iso:country":"US",
    "sg:address":"2239 Waikolu Way",
    "sg:city":"Honolulu",
    "sg:classifiers":[
        {
            "category":"Travel",
            "subcategory":"Travel Agent",
            "type":"Entertainment"
        }
    ],
    "sg:phone":"+1 808 924 1889",
    "sg:postcode":"96815",
    "sg:province":"HI",
    "sg:tags":[
        "agency",
        "bureau"
    ],
    "wof:name":"Trans Pacific Tours",
    "wof:placetype":"venue"
},
  "geometry": {"coordinates":[-157.827631,21.279802],"type":"Point"}
}