{
  "type": "Feature",
  "properties": {
    "iso:country":"US",
    "sg:address":"3253 N Nimitz Hwy",
    "sg:city":"Honolulu",
    "sg:classifiers":[
        {
            "category":"Real Estate",
            "subcategory":"Real Estate Operator",
            "type":"Services"
        }
    ],
    "sg:phone":"+1 808 836 8889",
    "sg:postcode":"96819",
    "sg:province":"HI",
    "sg:tags":[
        "apartment",
        "dwelling",
        "except"
    ],
    "wof:name":"Grace Business Dev Corp",
    "wof:placetype":"venue"
},
  "geometry": {"coordinates":[-157.91414700000001,21.336811],"type":"Point"}
}