{
  "type": "Feature",
  "properties": {
    "iso:country":"US",
    "sg:address":"1779 Hooikaika Pl",
    "sg:city":"Pearl City",
    "sg:classifiers":[
        {
            "category":"Professional",
            "subcategory":"Management & Consulting",
            "type":"Services"
        }
    ],
    "sg:phone":"+1 808 455 8323",
    "sg:postcode":"96782",
    "sg:province":"HI",
    "sg:tags":[
        "business"
    ],
    "wof:name":"Jed Assoiciates Inc",
    "wof:placetype":"venue"
},
  "geometry": {"coordinates":[-157.95424700000001,21.405408],"type":"Point"}
}