{
  "type": "Feature",
  "properties": {
    "iso:country":"US",
    "sg:address":"572 Kailua Rd",
    "sg:city":"Kailua",
    "sg:classifiers":[
        {
            "category":"Shopping",
            "subcategory":"Hobbies, Toys, & Games",
            "type":"Retail Goods"
        }
    ],
    "sg:phone":"+1 808 262 4315",
    "sg:postcode":"96734",
    "sg:province":"HI",
    "sg:tags":[
        "equipment",
        "ceramic",
        "supply"
    ],
    "wof:name":"Kailua Dental Ceramics",
    "wof:placetype":"venue"
},
  "geometry": {"coordinates":[-157.74248499999999,21.394221],"type":"Point"}
}