{
  "type": "Feature",
  "properties": {
    "addr:full":"532 California Ave Wahiawa HI 96786",
    "addr:housenumber":"532",
    "addr:postcode":"96786",
    "addr:street":"California Ave",
    "iso:country":"US",
    "sg:address":"532 California Ave",
    "sg:city":"Wahiawa",
    "sg:classifiers":[
        {
            "category":"Shopping",
            "subcategory":"Used Merchandise",
            "type":"Retail Goods"
        }
    ],
    "sg:phone":"+1 808 628 9220",
    "sg:postcode":"96786",
    "sg:province":"HI",
    "sg:tags":[
        "antique"
    ],
    "wof:name":"Trash From The Past",
    "wof:placetype":"venue"
},
  "geometry": {"coordinates":[-158.029561,21.496109],"type":"Point"}
}