{
  "type": "Feature",
  "properties": {
    "iso:country":"US",
    "sg:address":"486 Kuanana St",
    "sg:city":"Paia",
    "sg:classifiers":[
        {
            "category":"Building & Trades",
            "subcategory":"Construction",
            "type":"Services"
        }
    ],
    "sg:phone":"+1 808 250 9763",
    "sg:postcode":"96779",
    "sg:province":"HI",
    "sg:tags":[
        "contract"
    ],
    "wof:name":"Basey Custom Wood & Land LLC",
    "wof:placetype":"venue"
},
  "geometry": {"coordinates":[-156.37460100000001,20.903454],"type":"Point"}
}