{
  "type": "Feature",
  "properties": {
    "iso:country":"US",
    "sg:address":"6898 Palekana Rd",
    "sg:city":"Holualoa",
    "sg:classifiers":[
        {
            "category":"Wholesale",
            "subcategory":"Groceries",
            "type":"Manufacturing & Wholesale Goods"
        }
    ],
    "sg:phone":"+1 808 322 3579",
    "sg:postcode":"96725",
    "sg:province":"HI",
    "wof:name":"Cohala Coast & Protea",
    "wof:placetype":"venue"
},
  "geometry": {"coordinates":[-155.93533400000001,19.563961],"type":"Point"}
}