{
  "type": "Feature",
  "properties": {
    "addr:full":"4211 Waialae Ave Honolulu HI 96816",
    "addr:housenumber":"4211",
    "addr:postcode":"96816",
    "addr:street":"Waialae Ave",
    "iso:country":"US",
    "sg:address":"4211 Waialae Ave",
    "sg:city":"Honolulu",
    "sg:classifiers":[
        {
            "category":"Restaurant",
            "type":"Food & Drink"
        }
    ],
    "sg:phone":"+1 808 735 9788",
    "sg:postcode":"96816",
    "sg:province":"HI",
    "wof:name":"Pizza Hut",
    "wof:placetype":"venue"
},
  "geometry": {"coordinates":[-157.78477100000001,21.278289],"type":"Point"}
}