{
  "type": "Feature",
  "properties": {
    "iso:country":"US",
    "sg:address":"61 S Papa Ave",
    "sg:city":"Kahului",
    "sg:classifiers":[
        {
            "category":"Organizations",
            "subcategory":"Religious Organization",
            "type":"Services"
        }
    ],
    "sg:phone":"+1 808 877 7232",
    "sg:postcode":"96732",
    "sg:province":"HI",
    "wof:name":"Ka-Pule-Lima",
    "wof:placetype":"venue"
},
  "geometry": {"coordinates":[-156.48440199999999,20.886537],"type":"Point"}
}