{
  "type": "Feature",
  "properties": {
    "iso:country":"US",
    "sg:address":"221 Kipapa Dr",
    "sg:city":"Mililani",
    "sg:classifiers":[
        {
            "category":"Restaurant",
            "type":"Food & Drink"
        }
    ],
    "sg:phone":"+1 808 623 4447",
    "sg:postcode":"96789",
    "sg:province":"HI",
    "wof:name":"Ba-Le Sandwich Shop",
    "wof:placetype":"venue"
},
  "geometry": {"coordinates":[-158.01588000000001,21.458431],"type":"Point"}
}