{
  "type": "Feature",
  "properties": {
    "iso:country":"US",
    "sg:address":"1453 Ala Napunani St",
    "sg:city":"Honolulu",
    "sg:classifiers":[
        {
            "category":"Shopping",
            "type":"Retail Goods"
        }
    ],
    "sg:phone":"+1 808 833 1309",
    "sg:postcode":"96818",
    "sg:province":"HI",
    "sg:tags":[
        "decoration",
        "ornament",
        "christmas"
    ],
    "wof:name":"Kris Kringles Den Inc",
    "wof:placetype":"venue"
},
  "geometry": {"coordinates":[-157.899551,21.353683],"type":"Point"}
}