{
  "type": "Feature",
  "properties": {
    "iso:country":"US",
    "sg:address":"223 Kalani St",
    "sg:city":"Kailua Kona",
    "sg:classifiers":[
        {
            "category":"Organizations",
            "subcategory":"Religious Organization",
            "type":"Services"
        }
    ],
    "sg:phone":"+1 808 326 2330",
    "sg:postcode":"96740",
    "sg:province":"HI",
    "sg:tags":[
        "church"
    ],
    "wof:name":"Salvation Army",
    "wof:placetype":"venue"
},
  "geometry": {"coordinates":[-155.98755600000001,19.641873],"type":"Point"}
}