{
  "type": "Feature",
  "properties": {
    "iso:country":"US",
    "sg:address":"1276 Lower Main St",
    "sg:city":"Wailuku",
    "sg:classifiers":[
        {
            "category":"Retail",
            "subcategory":"Auto Repair",
            "type":"Services"
        }
    ],
    "sg:phone":"+1 808 244 4770",
    "sg:postcode":"96793",
    "sg:province":"HI",
    "sg:tags":[
        "body",
        "automotive",
        "reupholster"
    ],
    "wof:name":"Maui Auto Top & Upholstery",
    "wof:placetype":"venue"
},
  "geometry": {"coordinates":[-156.495341,20.899231],"type":"Point"}
}