{
  "type": "Feature",
  "properties": {
    "addr:full":"4211 Waialae Ave Honolulu HI 96816",
    "addr:housenumber":"4211",
    "addr:postcode":"96816",
    "addr:street":"Waialae Ave",
    "iso:country":"US",
    "sg:address":"4211 Waialae Ave",
    "sg:city":"Honolulu",
    "sg:classifiers":[
        {
            "category":"Real Estate",
            "subcategory":"Real Estate Operator",
            "type":"Services"
        }
    ],
    "sg:phone":"+1 808 732 7736",
    "sg:postcode":"96816",
    "sg:province":"HI",
    "sg:tags":[
        "mall",
        "shopping",
        "center"
    ],
    "wof:name":"MMI Realty Svc Inc",
    "wof:placetype":"venue"
},
  "geometry": {"coordinates":[-157.78477100000001,21.278289],"type":"Point"}
}