{
  "type": "Feature",
  "properties": {
    "iso:country":"US",
    "sg:address":"755 Upena St",
    "sg:city":"Waianae",
    "sg:classifiers":[
        {
            "category":"Shopping",
            "subcategory":"Bicycles & Sporting Goods",
            "type":"Retail Goods"
        }
    ],
    "sg:phone":"+1 808 696 6954",
    "sg:postcode":"96792",
    "sg:province":"HI",
    "sg:tags":[
        "equipment",
        "exercise"
    ],
    "wof:name":"Country Power Inc",
    "wof:placetype":"venue"
},
  "geometry": {"coordinates":[-158.21883299999999,21.472455],"type":"Point"}
}