{
  "type": "Feature",
  "properties": {
    "addr:full":"32 Kainehe St Kailua HI 96734",
    "addr:housenumber":"32",
    "addr:postcode":"96734",
    "addr:street":"Kainehe St",
    "iso:country":"US",
    "sg:address":"32 Kainehe St",
    "sg:city":"Kailua",
    "sg:classifiers":[
        {
            "category":"Building & Trades",
            "subcategory":"Construction",
            "type":"Services"
        }
    ],
    "sg:phone":"+1 808 262 5401",
    "sg:postcode":"96734",
    "sg:province":"HI",
    "sg:tags":[
        "fence",
        "contractor"
    ],
    "wof:name":"Kailua Fencing",
    "wof:placetype":"venue"
},
  "geometry": {"coordinates":[-157.74579499999999,21.394463],"type":"Point"}
}