{
  "type": "Feature",
  "properties": {
    "iso:country":"US",
    "sg:address":"611 Middle St",
    "sg:city":"Honolulu",
    "sg:classifiers":[
        {
            "category":"Retail",
            "subcategory":"Auto Repair",
            "type":"Services"
        }
    ],
    "sg:phone":"+1 808 845 4500",
    "sg:postcode":"96819",
    "sg:province":"HI",
    "sg:tags":[
        "automotive",
        "towing"
    ],
    "wof:name":"Stoneridge Recoveries LLC",
    "wof:placetype":"venue"
},
  "geometry": {"coordinates":[-157.88862800000001,21.334241],"type":"Point"}
}