{
  "type": "Feature",
  "properties": {
    "iso:country":"US",
    "sg:address":"470 Goodale Ave",
    "sg:city":"Waialua",
    "sg:classifiers":[
        {
            "category":"Personal",
            "subcategory":"Beauty Salon",
            "type":"Services"
        }
    ],
    "sg:phone":"+1 808 637 4744",
    "sg:postcode":"96791",
    "sg:province":"HI",
    "wof:name":"May's Beauty Shop",
    "wof:placetype":"venue"
},
  "geometry": {"coordinates":[-158.12255999999999,21.566686],"type":"Point"}
}