{
  "type": "Feature",
  "properties": {
    "iso:country":"US",
    "sg:address":"96 Central Ave",
    "sg:city":"Wailuku",
    "sg:classifiers":[
        {
            "category":"Shopping",
            "subcategory":"Photographic Equipment",
            "type":"Retail Goods"
        }
    ],
    "sg:phone":"+1 808 877 7022",
    "sg:postcode":"96793",
    "sg:province":"HI",
    "sg:tags":[
        "carpentry",
        "contractor"
    ],
    "wof:name":"Editions-Maui Inc Limited",
    "wof:placetype":"venue"
},
  "geometry": {"coordinates":[-156.50317799999999,20.893638],"type":"Point"}
}