{
  "type": "Feature",
  "properties": {
    "iso:country":"US",
    "sg:address":"1425 Keolu Dr",
    "sg:city":"Kailua",
    "sg:classifiers":[
        {
            "category":"Organizations",
            "subcategory":"Religious Organization",
            "type":"Services"
        }
    ],
    "sg:phone":"+1 808 262 7979",
    "sg:postcode":"96734",
    "sg:province":"HI",
    "wof:name":"Keolumana Untd Methdst Church",
    "wof:placetype":"venue"
},
  "geometry": {"coordinates":[-157.734599,21.371521],"type":"Point"}
}