{
  "type": "Feature",
  "properties": {
    "iso:country":"US",
    "sg:address":"1520 Liliha St",
    "sg:city":"Honolulu",
    "sg:classifiers":[
        {
            "category":"Professional",
            "subcategory":"Accounting & Tax Preparation",
            "type":"Services"
        }
    ],
    "sg:phone":"+1 808 522 0765",
    "sg:postcode":"96817",
    "sg:province":"HI",
    "wof:name":"Yonemitsu & Co CPA Inc",
    "wof:placetype":"venue"
},
  "geometry": {"coordinates":[-157.860365,21.32138],"type":"Point"}
}