{
  "type": "Feature",
  "properties": {
    "iso:country":"US",
    "sg:address":"4370 Kukui Grove St",
    "sg:city":"Lihue",
    "sg:classifiers":[
        {
            "category":"Shopping",
            "type":"Retail Goods"
        }
    ],
    "sg:phone":"+1 808 246 6717",
    "sg:postcode":"96766",
    "sg:province":"HI",
    "sg:tags":[
        "hearing",
        "equipment",
        "supply",
        "impaired"
    ],
    "wof:name":"Better Hearing Of Hawaii LLC",
    "wof:placetype":"venue"
},
  "geometry": {"coordinates":[-159.37670700000001,21.970876],"type":"Point"}
}