{
  "type": "Feature",
  "properties": {
    "iso:country":"US",
    "sg:address":"4480 Hokua Rd",
    "sg:city":"Kalaheo",
    "sg:classifiers":[
        {
            "category":"Social Services",
            "subcategory":"Child Care",
            "type":"Services"
        }
    ],
    "sg:phone":"+1 808 332 5550",
    "sg:postcode":"96741",
    "sg:province":"HI",
    "sg:tags":[
        "kindergarten",
        "academic",
        "school"
    ],
    "wof:name":"Kalaheo Missionary Preschool",
    "wof:placetype":"venue"
},
  "geometry": {"coordinates":[-159.52266299999999,21.924375],"type":"Point"}
}