{
  "type": "Feature",
  "properties": {
    "addr:full":"319 Wyllie St Honolulu HI 96817",
    "addr:housenumber":"319",
    "addr:postcode":"96817",
    "addr:street":"Wyllie St",
    "iso:country":"US",
    "sg:address":"319 Wyllie St",
    "sg:city":"Honolulu",
    "sg:classifiers":[
        {
            "category":"Education",
            "subcategory":"Special Training",
            "type":"Public Place"
        }
    ],
    "sg:phone":"+1 808 595 3131",
    "sg:postcode":"96817",
    "sg:province":"HI",
    "sg:tags":[
        "tutoring"
    ],
    "wof:name":"Kumon USA",
    "wof:placetype":"venue"
},
  "geometry": {"coordinates":[-157.847264,21.328903],"type":"Point"}
}