{
  "type": "Feature",
  "properties": {
    "addr:full":"2957 Kalakaua Ave Honolulu HI 96815",
    "addr:housenumber":"2957",
    "addr:postcode":"96815",
    "addr:street":"Kalakaua Ave",
    "iso:country":"US",
    "sg:address":"2957 Kalakaua Ave",
    "sg:city":"Honolulu",
    "sg:classifiers":[
        {
            "category":"Professional",
            "subcategory":"Management & Consulting",
            "type":"Services"
        }
    ],
    "sg:phone":"+1 808 440 4251",
    "sg:postcode":"96815",
    "sg:province":"HI",
    "sg:tags":[
        "field",
        "grant",
        "reader"
    ],
    "wof:name":"Rosemary Wolfe",
    "wof:placetype":"venue"
},
  "geometry": {"coordinates":[-157.81995000000001,21.261044],"type":"Point"}
}