{
  "type": "Feature",
  "properties": {
    "addr:full":"1773 Eames St Wahiawa HI 96786",
    "addr:housenumber":"1773",
    "addr:postcode":"96786",
    "addr:street":"Eames St",
    "iso:country":"US",
    "sg:address":"1773 Eames St",
    "sg:city":"Wahiawa",
    "sg:classifiers":[
        {
            "category":"Education",
            "subcategory":"Special Training",
            "type":"Public Place"
        }
    ],
    "sg:phone":"+1 808 621 9015",
    "sg:postcode":"96786",
    "sg:province":"HI",
    "wof:name":"People First LLC",
    "wof:placetype":"venue"
},
  "geometry": {"coordinates":[-158.00847099999999,21.504697],"type":"Point"}
}