{
  "type": "Feature",
  "properties": {
    "iso:country":"US",
    "sg:address":"1270 Kaeleku St",
    "sg:city":"Honolulu",
    "sg:classifiers":[
        {
            "category":"Real Estate",
            "subcategory":"Real Estate Agent",
            "type":"Services"
        }
    ],
    "sg:phone":"+1 808 387 6821",
    "sg:postcode":"96825",
    "sg:province":"HI",
    "wof:name":"Prime Sites",
    "wof:placetype":"venue"
},
  "geometry": {"coordinates":[-157.67103299999999,21.305549],"type":"Point"}
}