{
  "type": "Feature",
  "properties": {
    "iso:country":"US",
    "sg:address":"2139 Fort Weaver Rd",
    "sg:city":"Ewa Beach",
    "sg:classifiers":[
        {
            "category":"Health Services",
            "subcategory":"Doctor",
            "type":"Services"
        }
    ],
    "sg:phone":"+1 808 676 5331",
    "sg:postcode":"96706",
    "sg:province":"HI",
    "sg:tags":[
        "occupational",
        "therapy",
        "physical"
    ],
    "wof:name":"Work Star Occptional Hlth Svcs",
    "wof:placetype":"venue"
},
  "geometry": {"coordinates":[-158.02632199999999,21.36867],"type":"Point"}
}