{
  "type": "Feature",
  "properties": {
    "iso:country":"US",
    "sg:address":"743 Waiakamilo Rd",
    "sg:city":"Honolulu",
    "sg:classifiers":[
        {
            "category":"Food & Beverages",
            "subcategory":"Candy",
            "type":"Retail Goods"
        }
    ],
    "sg:phone":"+1 808 841 1272",
    "sg:postcode":"96817",
    "sg:province":"HI",
    "wof:name":"Sumis Sweets",
    "wof:placetype":"venue"
},
  "geometry": {"coordinates":[-157.873223,21.326742],"type":"Point"}
}