{
  "type": "Feature",
  "properties": {
    "iso:country":"US",
    "sg:address":"1111 Bishop St",
    "sg:city":"Honolulu",
    "sg:classifiers":[
        {
            "category":"Shopping",
            "type":"Retail Goods"
        }
    ],
    "sg:phone":"+1 808 531 6251",
    "sg:postcode":"96813",
    "sg:province":"HI",
    "sg:tags":[
        "supply",
        "stamp",
        "except",
        "dealer",
        "mail",
        "coin",
        "order"
    ],
    "sg:website":"www.hisc.net",
    "wof:name":"Hawaiian Islands Stamp & Coin",
    "wof:placetype":"venue"
},
  "geometry": {"coordinates":[-157.85980599999999,21.309631],"type":"Point"}
}