{
  "type": "Feature",
  "properties": {
    "iso:country":"US",
    "sg:address":"5071 Hana Hwy",
    "sg:city":"Haiku",
    "sg:classifiers":[
        {
            "category":"Professional",
            "type":"Services"
        }
    ],
    "sg:phone":"+1 808 572 2113",
    "sg:postcode":"96708",
    "sg:province":"HI",
    "sg:tags":[
        "writer"
    ],
    "wof:name":"Martini Frederic H Inc",
    "wof:placetype":"venue"
},
  "geometry": {"coordinates":[-156.27166600000001,20.922284],"type":"Point"}
}