{
  "type": "Feature",
  "properties": {
    "iso:country":"US",
    "sg:address":"330 Kamani St",
    "sg:city":"Honolulu",
    "sg:classifiers":[
        {
            "category":"Wholesale",
            "subcategory":"Hardware",
            "type":"Manufacturing & Wholesale Goods"
        },
        {
            "category":"Home & Garden",
            "subcategory":"Home Furnishings",
            "type":"Retail Goods"
        }
    ],
    "sg:phone":"+1 808 592 0233",
    "sg:postcode":"96813",
    "sg:province":"HI",
    "sg:tags":[
        "plumbing",
        "fixture",
        "specialty",
        "supply"
    ],
    "sg:website":"www.fiddlers.net",
    "wof:name":"Fiddler's",
    "wof:placetype":"venue"
},
  "geometry": {"coordinates":[-157.856379,21.297178],"type":"Point"}
}