{
  "type": "Feature",
  "properties": {
    "addr:full":"2680 Woodlawn Dr Honolulu HI 96822",
    "addr:housenumber":"2680",
    "addr:postcode":"96822",
    "addr:street":"Woodlawn Dr",
    "iso:country":"US",
    "sg:address":"2680 Woodlawn Dr",
    "sg:city":"Honolulu",
    "sg:classifiers":[
        {
            "category":"Professional",
            "subcategory":"Research",
            "type":"Services"
        }
    ],
    "sg:phone":"+1 808 956 8312",
    "sg:postcode":"96822",
    "sg:province":"HI",
    "sg:tags":[
        "organization",
        "commercial",
        "noncommercial"
    ],
    "wof:name":"Institute For Astronomy",
    "wof:placetype":"venue"
},
  "geometry": {"coordinates":[-157.81171699999999,21.306671],"type":"Point"}
}