{
  "type": "Feature",
  "properties": {
    "iso:country":"US",
    "sg:address":"358 Papa Pl",
    "sg:city":"Kahului",
    "sg:classifiers":[
        {
            "category":"Professional",
            "subcategory":"Management & Consulting",
            "type":"Services"
        }
    ],
    "sg:phone":"+1 808 877 4142",
    "sg:postcode":"96732",
    "sg:province":"HI",
    "sg:tags":[
        "marketing",
        "program"
    ],
    "wof:name":"Third Wave Business Svc",
    "wof:placetype":"venue"
},
  "geometry": {"coordinates":[-156.45459399999999,20.885223],"type":"Point"}
}