{
  "type": "Feature",
  "properties": {
    "iso:country":"US",
    "sg:address":"631 18th Ave",
    "sg:city":"Honolulu",
    "sg:classifiers":[
        {
            "category":"Education",
            "subcategory":"School",
            "type":"Public Place"
        }
    ],
    "sg:phone":"+1 808 733 4800",
    "sg:postcode":"96816",
    "sg:province":"HI",
    "sg:tags":[
        "high",
        "junior"
    ],
    "wof:name":"Kaimuki Intermediate School",
    "wof:placetype":"venue"
},
  "geometry": {"coordinates":[-157.79743199999999,21.270406],"type":"Point"}
}