{
  "type": "Feature",
  "properties": {
    "iso:country":"US",
    "sg:address":"202 N Kamehameha Hwy",
    "sg:city":"Wahiawa",
    "sg:classifiers":[
        {
            "category":"Food & Beverages",
            "subcategory":"Groceries & Convenience Stores",
            "type":"Retail Goods"
        }
    ],
    "sg:phone":"+1 808 621 6711",
    "sg:postcode":"96786",
    "sg:province":"HI",
    "wof:name":"7-Eleven",
    "wof:placetype":"venue"
},
  "geometry": {"coordinates":[-158.02932799999999,21.500533],"type":"Point"}
}