{
  "type": "Feature",
  "properties": {
    "addr:full":"747 Queen St Honolulu HI 96813",
    "addr:housenumber":"747",
    "addr:postcode":"96813",
    "addr:street":"Queen St",
    "iso:country":"US",
    "sg:address":"747 Queen St",
    "sg:city":"Honolulu",
    "sg:classifiers":[
        {
            "category":"Organizations",
            "subcategory":"Community Association",
            "type":"Services"
        }
    ],
    "sg:phone":"+1 808 591 0712",
    "sg:postcode":"96813",
    "sg:province":"HI",
    "sg:tags":[
        "club"
    ],
    "wof:name":"Club Queenbee",
    "wof:placetype":"venue"
},
  "geometry": {"coordinates":[-157.85508200000001,21.298385],"type":"Point"}
}