{
  "type": "Feature",
  "properties": {
    "iso:country":"US",
    "sg:address":"2979 Kalakaua Ave",
    "sg:city":"Honolulu",
    "sg:classifiers":[
        {
            "category":"Retail",
            "subcategory":"Repair Shop",
            "type":"Services"
        }
    ],
    "sg:phone":"+1 808 922 1196",
    "sg:postcode":"96815",
    "sg:province":"HI",
    "wof:name":"Golf Club Repair & Fiiting",
    "wof:placetype":"venue"
},
  "geometry": {"coordinates":[-157.82024000000001,21.261514],"type":"Point"}
}