{
  "type": "Feature",
  "properties": {
    "iso:country":"US",
    "sg:address":"1913 Young St",
    "sg:city":"Honolulu",
    "sg:classifiers":[
        {
            "category":"Autos & Motor Vehicles",
            "subcategory":"Auto Supplies",
            "type":"Retail Goods"
        }
    ],
    "sg:phone":"+1 808 941 5776",
    "sg:postcode":"96826",
    "sg:province":"HI",
    "sg:tags":[
        "automobile",
        "stereo",
        "radio"
    ],
    "wof:name":"Island Sound",
    "wof:placetype":"venue"
},
  "geometry": {"coordinates":[-157.830072,21.295734],"type":"Point"}
}