{
  "type": "Feature",
  "properties": {
    "addr:full":"288 Kilauea Ave Hilo HI 96720",
    "addr:housenumber":"288",
    "addr:postcode":"96720",
    "addr:street":"Kilauea Ave",
    "iso:country":"US",
    "sg:address":"288 Kilauea Ave",
    "sg:city":"Hilo",
    "sg:classifiers":[
        {
            "category":"Health Services",
            "subcategory":"Doctor",
            "type":"Services"
        }
    ],
    "sg:phone":"+1 808 961 4722",
    "sg:postcode":"96720",
    "sg:province":"HI",
    "sg:tags":[
        "physician",
        "surgeon"
    ],
    "wof:name":"Yvonne Conner MD",
    "wof:placetype":"venue"
},
  "geometry": {"coordinates":[-155.08459500000001,19.721276],"type":"Point"}
}