{
  "type": "Feature",
  "properties": {
    "iso:country":"US",
    "sg:address":"4374 Kukui Grove St",
    "sg:city":"Lihue",
    "sg:classifiers":[
        {
            "category":"Health Services",
            "subcategory":"Doctor",
            "type":"Services"
        }
    ],
    "sg:phone":"+1 808 246 0663",
    "sg:postcode":"96766",
    "sg:province":"HI",
    "sg:tags":[
        "physician",
        "surgeon",
        "medical"
    ],
    "wof:name":"Ke Ala Pono Recovery Center",
    "wof:placetype":"venue"
},
  "geometry": {"coordinates":[-159.37674000000001,21.970905],"type":"Point"}
}