{
  "type": "Feature",
  "properties": {
    "iso:country":"US",
    "sg:address":"340 Ukee St",
    "sg:city":"Waipahu",
    "sg:classifiers":[
        {
            "category":"Retail",
            "subcategory":"Repair Shop",
            "type":"Services"
        }
    ],
    "sg:phone":"+1 808 671 2122",
    "sg:postcode":"96797",
    "sg:province":"HI",
    "wof:name":"Mililani TV Repair",
    "wof:placetype":"venue"
},
  "geometry": {"coordinates":[-158.000743,21.424547],"type":"Point"}
}