{
  "type": "Feature",
  "properties": {
    "iso:country":"US",
    "sg:address":"31 Lilipuna Pl",
    "sg:city":"Kaneohe",
    "sg:classifiers":[
        {
            "category":"Building & Trades",
            "subcategory":"Plumbing",
            "type":"Services"
        }
    ],
    "sg:phone":"+1 808 247 1955",
    "sg:postcode":"96744",
    "sg:province":"HI",
    "sg:tags":[
        "plumbing",
        "contractor"
    ],
    "wof:name":"Suburban Plumbing",
    "wof:placetype":"venue"
},
  "geometry": {"coordinates":[-157.79165499999999,21.420573],"type":"Point"}
}