{
  "type": "Feature",
  "properties": {
    "iso:country":"US",
    "sg:address":"459 Patterson Rd",
    "sg:city":"Honolulu",
    "sg:classifiers":[
        {
            "category":"Organizations",
            "subcategory":"Community Association",
            "type":"Services"
        }
    ],
    "sg:phone":"+1 808 433 0141",
    "sg:postcode":"96819",
    "sg:province":"HI",
    "wof:name":"United Sttes Vtrans Initiative",
    "wof:placetype":"venue"
},
  "geometry": {"coordinates":[-157.888792,21.361079],"type":"Point"}
}