{
  "type": "Feature",
  "properties": {
    "iso:country":"US",
    "sg:address":"4888 Bougainville Dr",
    "sg:city":"Honolulu",
    "sg:classifiers":[
        {
            "category":"Government",
            "subcategory":"Office",
            "type":"Public Place"
        }
    ],
    "sg:phone":"+1 808 421 3444",
    "sg:postcode":"96818",
    "sg:province":"HI",
    "sg:tags":[
        "general"
    ],
    "wof:name":"Pearl Harbor Distribution Ctr",
    "wof:placetype":"venue"
},
  "geometry": {"coordinates":[-157.92933300000001,21.342899],"type":"Point"}
}