{
  "type": "Feature",
  "properties": {
    "iso:country":"US",
    "sg:address":"1281 Kawaihae Rd",
    "sg:city":"Kamuela",
    "sg:classifiers":[
        {
            "category":"Real Estate",
            "subcategory":"Architect",
            "type":"Services"
        }
    ],
    "sg:phone":"+1 808 887 0277",
    "sg:postcode":"96743",
    "sg:province":"HI",
    "sg:tags":[
        "building",
        "designer"
    ],
    "wof:name":"RCS Design",
    "wof:placetype":"venue"
},
  "geometry": {"coordinates":[-155.699082,20.026671],"type":"Point"}
}