{
  "type": "Feature",
  "properties": {
    "iso:country":"US",
    "sg:address":"100 Kaahumanu Ave",
    "sg:city":"Kahului",
    "sg:classifiers":[
        {
            "category":"Travel",
            "subcategory":"Hotels & Motels",
            "type":"Entertainment"
        }
    ],
    "sg:phone":"+1 808 877 3311",
    "sg:postcode":"96732",
    "sg:province":"HI",
    "sg:website":"www.sand-seaside.com",
    "wof:name":"Maui Seaside Hotel",
    "wof:placetype":"venue"
},
  "geometry": {"coordinates":[-156.47011900000001,20.890262],"type":"Point"}
}