{
  "type": "Feature",
  "properties": {
    "iso:country":"US",
    "sg:address":"411 Hobron Ln",
    "sg:city":"Honolulu",
    "sg:classifiers":[
        {
            "category":"Autos & Motor Vehicles",
            "subcategory":"Auto Supplies",
            "type":"Retail Goods"
        }
    ],
    "sg:phone":"+1 808 941 5070",
    "sg:postcode":"96815",
    "sg:province":"HI",
    "sg:tags":[
        "automobile",
        "alarm"
    ],
    "wof:name":"Steel Mate",
    "wof:placetype":"venue"
},
  "geometry": {"coordinates":[-157.83516900000001,21.286323],"type":"Point"}
}