{
  "type": "Feature",
  "properties": {
    "iso:country":"US",
    "sg:address":"167 Kamehameha Hwy",
    "sg:city":"Haleiwa",
    "sg:classifiers":[
        {
            "category":"Sports & Exercise",
            "subcategory":"Gym",
            "type":"Entertainment"
        }
    ],
    "sg:phone":"+1 808 637 2711",
    "sg:postcode":"96712",
    "sg:province":"HI",
    "sg:tags":[
        "club",
        "health",
        "studio",
        "gymnasium"
    ],
    "wof:name":"Curves For Women",
    "wof:placetype":"venue"
},
  "geometry": {"coordinates":[-158.030438,21.682551],"type":"Point"}
}