{
  "type": "Feature",
  "properties": {
    "addr:full":"3375 Koapaka St Honolulu HI 96819",
    "addr:postcode":"96819",
    "addr:street":"Koapaka St",
    "iso:country":"US",
    "sg:address":"3375 Koapaka St",
    "sg:city":"Honolulu",
    "sg:classifiers":[
        {
            "category":"Wholesale",
            "subcategory":"Machinery & Supplies",
            "type":"Manufacturing & Wholesale Goods"
        }
    ],
    "sg:phone":"+1 808 836 6978",
    "sg:postcode":"96819",
    "sg:province":"HI",
    "sg:tags":[
        "equipment",
        "transportation"
    ],
    "wof:name":"Saic",
    "wof:placetype":"venue"
},
  "geometry": {"coordinates":[-157.91583600000001,21.336026],"type":"Point"}
}