{
  "type": "Feature",
  "properties": {
    "iso:country":"US",
    "sg:address":"2025 Aaniu Loop",
    "sg:city":"Pearl City",
    "sg:classifiers":[
        {
            "category":"Professional",
            "type":"Services"
        }
    ],
    "sg:phone":"+1 808 455 5100",
    "sg:postcode":"96782",
    "sg:province":"HI",
    "wof:name":"Hawaii Master Crafters",
    "wof:placetype":"venue"
},
  "geometry": {"coordinates":[-157.96485899999999,21.418151],"type":"Point"}
}