{
  "type": "Feature",
  "properties": {
    "addr:full":"425 Puako Beach Dr Kamuela HI 96743",
    "addr:housenumber":"425",
    "addr:postcode":"96743",
    "addr:street":"Puako Beach Dr",
    "iso:country":"US",
    "sg:address":"425 Puako Beach Dr",
    "sg:city":"Kamuela",
    "sg:classifiers":[
        {
            "category":"Shopping",
            "type":"Retail Goods"
        }
    ],
    "sg:phone":"+1 808 886 4020",
    "sg:postcode":"96743",
    "sg:province":"HI",
    "sg:tags":[
        "sell",
        "equipment",
        "rent",
        "solution"
    ],
    "wof:name":"Business Works of Hawaii Inc",
    "wof:placetype":"venue"
},
  "geometry": {"coordinates":[-155.83040099999999,19.973181],"type":"Point"}
}