{
  "type": "Feature",
  "properties": {
    "iso:country":"US",
    "sg:address":"410 Koauka Loop",
    "sg:city":"Aiea",
    "sg:classifiers":[
        {
            "category":"Real Estate",
            "subcategory":"Real Estate Operator",
            "type":"Services"
        }
    ],
    "sg:phone":"+1 808 488 3452",
    "sg:postcode":"96701",
    "sg:province":"HI",
    "sg:tags":[
        "condominium"
    ],
    "wof:name":"Pearl Two Condominium",
    "wof:placetype":"venue"
},
  "geometry": {"coordinates":[-157.93606500000001,21.385704],"type":"Point"}
}