{
  "type": "Feature",
  "properties": {
    "iso:country":"US",
    "sg:address":"1111 Fort Street Mall",
    "sg:city":"Honolulu",
    "sg:classifiers":[
        {
            "category":"Restaurant",
            "type":"Food & Drink"
        }
    ],
    "sg:menulink":"http://www.allmenus.com/hi/honolulu/92302-l--l-drive-inn/menu/",
    "sg:phone":"+1 808 521 8891",
    "sg:postcode":"96813",
    "sg:province":"HI",
    "sg:tags":[
        "barbecue",
        "american",
        "hawaiian"
    ],
    "wof:name":"L & L Drive Inn",
    "wof:placetype":"venue"
},
  "geometry": {"coordinates":[-157.860829,21.309959],"type":"Point"}
}