{
  "type": "Feature",
  "properties": {
    "iso:country":"US",
    "sg:address":"3660 Waialae Ave",
    "sg:city":"Honolulu",
    "sg:classifiers":[
        {
            "category":"Real Estate",
            "subcategory":"Real Estate Agent",
            "type":"Services"
        }
    ],
    "sg:phone":"+1 808 735 1545",
    "sg:postcode":"96816",
    "sg:province":"HI",
    "wof:name":"Heaman Properties",
    "wof:placetype":"venue"
},
  "geometry": {"coordinates":[-157.79691199999999,21.281658],"type":"Point"}
}