{
  "type": "Feature",
  "properties": {
    "iso:country":"US",
    "sg:address":"5511 Luhia St",
    "sg:city":"Kailua Kona",
    "sg:classifiers":[
        {
            "category":"Home & Garden",
            "subcategory":"Building Materials",
            "type":"Retail Goods"
        }
    ],
    "sg:phone":"+1 808 334 4200",
    "sg:postcode":"96740",
    "sg:province":"HI",
    "sg:tags":[
        "supply"
    ],
    "wof:name":"Hawaii Planning",
    "wof:placetype":"venue"
},
  "geometry": {"coordinates":[-155.997896,19.646902],"type":"Point"}
}