{
  "type": "Feature",
  "properties": {
    "iso:country":"US",
    "sg:address":"1142 Bethel St",
    "sg:city":"Honolulu",
    "sg:classifiers":[
        {
            "category":"Shopping",
            "type":"Retail Goods"
        }
    ],
    "sg:phone":"+1 808 546 8000",
    "sg:postcode":"96813",
    "sg:province":"HI",
    "sg:tags":[
        "art",
        "gallery",
        "dealer"
    ],
    "wof:name":"Details Gallery",
    "wof:placetype":"venue"
},
  "geometry": {"coordinates":[-157.86045100000001,21.311323],"type":"Point"}
}