{
  "type": "Feature",
  "properties": {
    "iso:country":"US",
    "sg:address":"423 Kalamauka Rd",
    "sg:city":"Holualoa",
    "sg:classifiers":[
        {
            "category":"Professional",
            "type":"Services"
        }
    ],
    "sg:phone":"+1 808 322 7127",
    "sg:postcode":"96725",
    "sg:province":"HI",
    "wof:name":"Acc Dean Williams",
    "wof:placetype":"venue"
},
  "geometry": {"coordinates":[-155.95376899999999,19.606978],"type":"Point"}
}