{
  "type": "Feature",
  "properties": {
    "iso:country":"US",
    "sg:address":"283 Lalo St",
    "sg:city":"Kahului",
    "sg:classifiers":[
        {
            "category":"Professional",
            "subcategory":"Advertising",
            "type":"Services"
        }
    ],
    "sg:phone":"+1 808 877 2020",
    "sg:postcode":"96732",
    "sg:province":"HI",
    "sg:tags":[
        "counselor"
    ],
    "wof:name":"Advertising Services & Prdctn",
    "wof:placetype":"venue"
},
  "geometry": {"coordinates":[-156.458474,20.88324],"type":"Point"}
}