{
  "type": "Feature",
  "properties": {
    "iso:country":"US",
    "sg:address":"3616 Kawaihae Rd",
    "sg:city":"Kamuela",
    "sg:classifiers":[
        {
            "category":"Recreation",
            "type":"Entertainment"
        }
    ],
    "sg:phone":"+1 808 882 1544",
    "sg:postcode":"96743",
    "sg:province":"HI",
    "sg:tags":[
        "diving",
        "instruction"
    ],
    "sg:website":"www.maunakeadivers.com",
    "wof:name":"Mauna Kea Divers Inc",
    "wof:placetype":"venue"
},
  "geometry": {"coordinates":[-155.809259,20.022229],"type":"Point"}
}