{
  "type": "Feature",
  "properties": {
    "iso:country":"US",
    "sg:address":"757 Nanihoku Way",
    "sg:city":"Kaneohe",
    "sg:classifiers":[
        {
            "category":"Building & Trades",
            "subcategory":"Pest Control",
            "type":"Services"
        }
    ],
    "sg:phone":"+1 808 235 2030",
    "sg:postcode":"96744",
    "sg:province":"HI",
    "wof:name":"Residential Pest Control Inc",
    "wof:placetype":"venue"
},
  "geometry": {"coordinates":[-157.79435799999999,21.412544],"type":"Point"}
}