{
  "type": "Feature",
  "properties": {
    "addr:full":"4489 Sierra Dr Honolulu HI 96816",
    "addr:housenumber":"4489",
    "addr:postcode":"96816",
    "addr:street":"Sierra Dr",
    "iso:country":"US",
    "sg:address":"4489 Sierra Dr",
    "sg:city":"Honolulu",
    "sg:classifiers":[
        {
            "category":"Professional",
            "subcategory":"Art Services",
            "type":"Services"
        }
    ],
    "sg:phone":"+1 808 778 7855",
    "sg:postcode":"96816",
    "sg:province":"HI",
    "sg:tags":[
        "contracting",
        "graphic",
        "design",
        "software"
    ],
    "wof:name":"Studio 3511",
    "wof:placetype":"venue"
},
  "geometry": {"coordinates":[-157.79145600000001,21.291897],"type":"Point"}
}