{
  "type": "Feature",
  "properties": {
    "iso:country":"US",
    "sg:address":"1458 Ulupuni St",
    "sg:city":"Kailua",
    "sg:classifiers":[
        {
            "category":"Manufacturing",
            "subcategory":"Tools & Machinery",
            "type":"Manufacturing & Wholesale Goods"
        }
    ],
    "sg:phone":"+1 808 262 7039",
    "sg:postcode":"96734",
    "sg:province":"HI",
    "sg:tags":[
        "contractor"
    ],
    "wof:name":"Comeaux's Equipment Rentals",
    "wof:placetype":"venue"
},
  "geometry": {"coordinates":[-157.75501499999999,21.378832],"type":"Point"}
}