{
  "type": "Feature",
  "properties": {
    "iso:country":"US",
    "sg:address":"375 W Kuiaha Rd",
    "sg:city":"Haiku",
    "sg:classifiers":[
        {
            "category":"Home & Garden",
            "subcategory":"Home Furnishings",
            "type":"Retail Goods"
        }
    ],
    "sg:phone":"+1 808 575 2179",
    "sg:postcode":"96708",
    "sg:province":"HI",
    "sg:tags":[
        "equipment",
        "bath",
        "supply"
    ],
    "wof:name":"Fabricated Marble Of Hawaii",
    "wof:placetype":"venue"
},
  "geometry": {"coordinates":[-156.31047799999999,20.921354],"type":"Point"}
}