{
  "type": "Feature",
  "properties": {
    "iso:country":"US",
    "sg:address":"2028 Dillingham Blvd",
    "sg:city":"Honolulu",
    "sg:classifiers":[
        {
            "category":"Food & Beverages",
            "subcategory":"Groceries & Convenience Stores",
            "type":"Retail Goods"
        }
    ],
    "sg:phone":"+1 808 847 8092",
    "sg:postcode":"96819",
    "sg:province":"HI",
    "wof:name":"Meg's Mini Mart",
    "wof:placetype":"venue"
},
  "geometry": {"coordinates":[-157.881744,21.328874],"type":"Point"}
}