{
  "type": "Feature",
  "properties": {
    "iso:country":"US",
    "sg:address":"546 Kaimu Loop",
    "sg:city":"Aiea",
    "sg:classifiers":[
        {
            "category":"Home & Garden",
            "subcategory":"Household Appliances",
            "type":"Retail Goods"
        }
    ],
    "sg:phone":"+1 808 488 6142",
    "sg:postcode":"96701",
    "sg:province":"HI",
    "wof:name":"Bosch Kitchen Ctr",
    "wof:placetype":"venue"
},
  "geometry": {"coordinates":[-157.93482599999999,21.383261],"type":"Point"}
}