{
  "type": "Feature",
  "properties": {
    "addr:full":"1163 S Beretania St Honolulu HI 96814",
    "addr:housenumber":"1163",
    "addr:postcode":"96814",
    "addr:street":"S Beretania St",
    "iso:country":"US",
    "sg:address":"1163 S Beretania St",
    "sg:city":"Honolulu",
    "sg:classifiers":[
        {
            "category":"Banks & Credit Unions",
            "subcategory":"Investment Brokerage",
            "type":"Services"
        }
    ],
    "sg:phone":"+1 808 527 8888",
    "sg:postcode":"96814",
    "sg:province":"HI",
    "sg:tags":[
        "advisory",
        "financial"
    ],
    "wof:name":"Transamerica Financial Advisor",
    "wof:placetype":"venue"
},
  "geometry": {"coordinates":[-157.845032,21.302239],"type":"Point"}
}