{
  "type": "Feature",
  "properties": {
    "addr:full":"586 Kanoelehua Ave Hilo HI 96720",
    "addr:housenumber":"586",
    "addr:postcode":"96720",
    "addr:street":"Kanoelehua Ave",
    "iso:country":"US",
    "sg:address":"586 Kanoelehua Ave",
    "sg:city":"Hilo",
    "sg:classifiers":[
        {
            "category":"Professional",
            "subcategory":"Lawyer & Legal Services",
            "type":"Services"
        }
    ],
    "sg:phone":"+1 808 969 3302",
    "sg:postcode":"96720",
    "sg:province":"HI",
    "sg:tags":[
        "attorney"
    ],
    "wof:name":"Ian L Mattoch Law Offices",
    "wof:placetype":"venue"
},
  "geometry": {"coordinates":[-155.064391,19.712066],"type":"Point"}
}