{
  "type": "Feature",
  "properties": {
    "addr:full":"357 Waiale Rd Wailuku HI 96793",
    "addr:housenumber":"357",
    "addr:postcode":"96793",
    "addr:street":"Waiale Rd",
    "iso:country":"US",
    "sg:address":"357 Waiale Rd",
    "sg:city":"Wailuku",
    "sg:classifiers":[
        {
            "category":"Organizations",
            "subcategory":"Religious Organization",
            "type":"Services"
        }
    ],
    "sg:phone":"+1 808 244 7329",
    "sg:postcode":"96793",
    "sg:province":"HI",
    "wof:name":"Kupaianaha Church",
    "wof:placetype":"venue"
},
  "geometry": {"coordinates":[-156.501676,20.886304],"type":"Point"}
}