{
  "type": "Feature",
  "properties": {
    "iso:country":"US",
    "sg:address":"3468 Mamane St",
    "sg:city":"Honokaa",
    "sg:classifiers":[
        {
            "category":"Personal",
            "subcategory":"Beauty Salon",
            "type":"Services"
        }
    ],
    "sg:phone":"+1 808 775 1101",
    "sg:postcode":"96727",
    "sg:province":"HI",
    "wof:name":"Beauty By Island Girlz",
    "wof:placetype":"venue"
},
  "geometry": {"coordinates":[-155.46561199999999,20.078221],"type":"Point"}
}