{
  "type": "Feature",
  "properties": {
    "addr:full":"126 N King St Honolulu HI 96817",
    "addr:housenumber":"126",
    "addr:postcode":"96817",
    "addr:street":"N King St",
    "iso:country":"US",
    "sg:address":"126 N King St",
    "sg:city":"Honolulu",
    "sg:classifiers":[
        {
            "category":"Wholesale",
            "subcategory":"Jewelry",
            "type":"Manufacturing & Wholesale Goods"
        }
    ],
    "sg:phone":"+1 808 536 8828",
    "sg:postcode":"96817",
    "sg:province":"HI",
    "sg:tags":[
        "jeweler"
    ],
    "wof:name":"Golden Star",
    "wof:placetype":"venue"
},
  "geometry": {"coordinates":[-157.86383499999999,21.312003],"type":"Point"}
}