{
  "type": "Feature",
  "properties": {
    "iso:country":"US",
    "sg:address":"1942 Farrington Hwy",
    "sg:city":"Waianae",
    "sg:classifiers":[
        {
            "category":"Food & Beverages",
            "subcategory":"Groceries & Convenience Stores",
            "type":"Retail Goods"
        }
    ],
    "sg:phone":"+1 808 664 2188",
    "sg:postcode":"96792",
    "sg:province":"HI",
    "wof:name":"Nanakuli Food Mart",
    "wof:placetype":"venue"
},
  "geometry": {"coordinates":[-158.15365499999999,21.389159],"type":"Point"}
}