{
  "type": "Feature",
  "properties": {
    "iso:country":"US",
    "sg:address":"470 N Nimitz Hwy",
    "sg:city":"Honolulu",
    "sg:classifiers":[
        {
            "category":"Organizations",
            "subcategory":"Community Association",
            "type":"Services"
        }
    ],
    "sg:phone":"+1 808 531 2635",
    "sg:postcode":"96817",
    "sg:province":"HI",
    "sg:tags":[
        "club"
    ],
    "wof:name":"Waterfront Club Mikado",
    "wof:placetype":"venue"
},
  "geometry": {"coordinates":[-157.867898,21.314669],"type":"Point"}
}