{
  "type": "Feature",
  "properties": {
    "addr:full":"5546 Kaiwi St Kailua Kona HI 96740",
    "addr:housenumber":"5546",
    "addr:postcode":"96740",
    "addr:street":"Kaiwi St",
    "iso:country":"US",
    "sg:address":"5546 Kaiwi St",
    "sg:city":"Kailua Kona",
    "sg:classifiers":[
        {
            "category":"Retail",
            "subcategory":"Auto Repair",
            "type":"Services"
        }
    ],
    "sg:phone":"+1 808 327 9878",
    "sg:postcode":"96740",
    "sg:province":"HI",
    "sg:tags":[
        "repairing",
        "automobile",
        "general"
    ],
    "wof:name":"Automotive Engineering Kona",
    "wof:placetype":"venue"
},
  "geometry": {"coordinates":[-156.00104099999999,19.642899],"type":"Point"}
}