{
  "type": "Feature",
  "properties": {
    "iso:country":"US",
    "sg:address":"1620 N School St",
    "sg:city":"Honolulu",
    "sg:classifiers":[
        {
            "category":"Shopping",
            "subcategory":"Computers & Home Electronics",
            "type":"Retail Goods"
        }
    ],
    "sg:phone":"+1 808 845 7570",
    "sg:postcode":"96817",
    "sg:province":"HI",
    "sg:tags":[
        "equipment",
        "electronic",
        "supply"
    ],
    "wof:name":"Radio Shack",
    "wof:placetype":"venue"
},
  "geometry": {"coordinates":[-157.86914300000001,21.335749],"type":"Point"}
}