{
  "type": "Feature",
  "properties": {
    "iso:country":"US",
    "sg:address":"1354 Waihona St",
    "sg:city":"Pearl City",
    "sg:classifiers":[
        {
            "category":"Autos & Motor Vehicles",
            "subcategory":"Auto Supplies",
            "type":"Retail Goods"
        },
        {
            "category":"Retail",
            "subcategory":"Auto Repair",
            "type":"Services"
        }
    ],
    "sg:phone":"+1 808 455 9332",
    "sg:postcode":"96782",
    "sg:province":"HI",
    "sg:tags":[
        "repairing",
        "automobile",
        "general"
    ],
    "sg:website":"www.islandautoair.com",
    "wof:name":"Island Auto Air Inc",
    "wof:placetype":"venue"
},
  "geometry": {"coordinates":[-157.971575,21.412868],"type":"Point"}
}