{
  "type": "Feature",
  "properties": {
    "addr:full":"216 Farrington Hwy Waipahu HI 96797",
    "addr:housenumber":"216",
    "addr:postcode":"96797",
    "addr:street":"Farrington Hwy",
    "iso:country":"US",
    "sg:address":"216 Farrington Hwy",
    "sg:city":"Waipahu",
    "sg:classifiers":[
        {
            "category":"Restaurant",
            "type":"Food & Drink"
        }
    ],
    "sg:phone":"+1 808 678 8058",
    "sg:postcode":"96797",
    "sg:province":"HI",
    "sg:tags":[
        "barbecue"
    ],
    "wof:name":"Gina's Barbecue II",
    "wof:placetype":"venue"
},
  "geometry": {"coordinates":[-158.01993899999999,21.379627],"type":"Point"}
}