{
  "type": "Feature",
  "properties": {
    "addr:full":"1088 Bishop St Honolulu HI 96813",
    "addr:housenumber":"1088",
    "addr:postcode":"96813",
    "addr:street":"Bishop St",
    "iso:country":"US",
    "sg:address":"1088 Bishop St",
    "sg:city":"Honolulu",
    "sg:classifiers":[
        {
            "category":"Real Estate",
            "subcategory":"Developer",
            "type":"Services"
        }
    ],
    "sg:phone":"+1 808 521 0382",
    "sg:postcode":"96813",
    "sg:province":"HI",
    "wof:name":"Upland Investments LTD",
    "wof:placetype":"venue"
},
  "geometry": {"coordinates":[-157.861548,21.308484],"type":"Point"}
}