{
  "type": "Feature",
  "properties": {
    "iso:country":"US",
    "sg:address":"741 Kanoelehua Ave",
    "sg:city":"Hilo",
    "sg:classifiers":[
        {
            "category":"Retail",
            "subcategory":"Auto Repair",
            "type":"Services"
        }
    ],
    "sg:phone":"+1 808 935 1406",
    "sg:postcode":"96720",
    "sg:province":"HI",
    "sg:tags":[
        "repairing",
        "automobile",
        "general"
    ],
    "wof:name":"Hawaii Auto Repair",
    "wof:placetype":"venue"
},
  "geometry": {"coordinates":[-155.064245,19.708474],"type":"Point"}
}