{
  "type": "Feature",
  "properties": {
    "iso:country":"US",
    "sg:address":"3959 Kaumualii Hwy",
    "sg:city":"Hanapepe",
    "sg:classifiers":[
        {
            "category":"Restaurant",
            "type":"Food & Drink"
        }
    ],
    "sg:phone":"+1 808 335 0020",
    "sg:postcode":"96756",
    "sg:province":"HI",
    "wof:name":"Carving Stone Ohana Bar & Grll",
    "wof:placetype":"venue"
},
  "geometry": {"coordinates":[-159.49574999999999,21.923578],"type":"Point"}
}