{
  "type": "Feature",
  "properties": {
    "iso:country":"US",
    "sg:address":"824 Moloalo St",
    "sg:city":"Waipahu",
    "sg:classifiers":[
        {
            "category":"Health Services",
            "subcategory":"Optometrist",
            "type":"Services"
        }
    ],
    "sg:phone":"+1 808 677 0734",
    "sg:postcode":"96797",
    "sg:province":"HI",
    "wof:name":"Fujisaki James S Dr",
    "wof:placetype":"venue"
},
  "geometry": {"coordinates":[-158.003657,21.384417],"type":"Point"}
}