{
  "type": "Feature",
  "properties": {
    "iso:country":"US",
    "sg:address":"1102 S Kihei Rd",
    "sg:city":"Kihei",
    "sg:classifiers":[
        {
            "category":"Organizations",
            "subcategory":"Religious Organization",
            "type":"Services"
        }
    ],
    "sg:phone":"+1 808 875 4644",
    "sg:postcode":"96753",
    "sg:province":"HI",
    "sg:tags":[
        "church"
    ],
    "wof:name":"Circle-Love Christian Family",
    "wof:placetype":"venue"
},
  "geometry": {"coordinates":[-156.45671300000001,20.754769],"type":"Point"}
}