{
  "type": "Feature",
  "properties": {
    "addr:full":"1517 Makiki St Honolulu HI 96822",
    "addr:housenumber":"1517",
    "addr:postcode":"96822",
    "addr:street":"Makiki St",
    "iso:country":"US",
    "sg:address":"1517 Makiki St",
    "sg:city":"Honolulu",
    "sg:classifiers":[
        {
            "category":"Organizations",
            "subcategory":"Community Association",
            "type":"Services"
        }
    ],
    "sg:phone":"+1 808 946 1308",
    "sg:postcode":"96822",
    "sg:province":"HI",
    "sg:tags":[
        "owner",
        "condominium"
    ],
    "wof:name":"Makiki Park Place",
    "wof:placetype":"venue"
},
  "geometry": {"coordinates":[-157.834993,21.303641],"type":"Point"}
}