{
  "type": "Feature",
  "properties": {
    "iso:country":"US",
    "sg:address":"1352 Liliha St",
    "sg:city":"Honolulu",
    "sg:classifiers":[
        {
            "category":"Organizations",
            "subcategory":"Membership Organization",
            "type":"Services"
        }
    ],
    "sg:phone":"+1 808 522 1302",
    "sg:postcode":"96817",
    "sg:province":"HI",
    "wof:name":"Face Action For Cmnty Equity",
    "wof:placetype":"venue"
},
  "geometry": {"coordinates":[-157.862787,21.319497],"type":"Point"}
}