{
  "type": "Feature",
  "properties": {
    "addr:full":"487 Lehua St Honokaa HI 96727",
    "addr:housenumber":"487",
    "addr:postcode":"96727",
    "addr:street":"Lehua St",
    "iso:country":"US",
    "sg:address":"487 Lehua St",
    "sg:city":"Honokaa",
    "sg:classifiers":[
        {
            "category":"Retail",
            "subcategory":"Auto Repair",
            "type":"Services"
        }
    ],
    "sg:phone":"+1 808 775 0220",
    "sg:postcode":"96727",
    "sg:province":"HI",
    "sg:tags":[
        "body"
    ],
    "wof:name":"Nobrigas Auto Body & Repair",
    "wof:placetype":"venue"
},
  "geometry": {"coordinates":[-155.46864400000001,20.082389],"type":"Point"}
}