{
  "type": "Feature",
  "properties": {
    "addr:full":"4336 Palanehe Pl Kailua Kona HI 96740",
    "addr:housenumber":"4336",
    "addr:postcode":"96740",
    "addr:street":"Palanehe Pl",
    "iso:country":"US",
    "sg:address":"4336 Palanehe Pl",
    "sg:city":"Kailua Kona",
    "sg:classifiers":[
        {
            "category":"Professional",
            "type":"Services"
        }
    ],
    "sg:phone":"+1 808 325 3474",
    "sg:postcode":"96740",
    "sg:province":"HI",
    "sg:tags":[
        "establishment"
    ],
    "wof:name":"Adventure Islands Incentives",
    "wof:placetype":"venue"
},
  "geometry": {"coordinates":[-156.01522800000001,19.722654],"type":"Point"}
}