{
  "type": "Feature",
  "properties": {
    "addr:full":"6823 Makenawai St Kailua Kona HI 96740",
    "addr:housenumber":"6823",
    "addr:postcode":"96740",
    "addr:street":"Makenawai St",
    "iso:country":"US",
    "sg:address":"6823 Makenawai St",
    "sg:city":"Kailua Kona",
    "sg:classifiers":[
        {
            "category":"Building & Trades",
            "subcategory":"Construction",
            "type":"Services"
        }
    ],
    "sg:phone":"+1 808 324 1161",
    "sg:postcode":"96740",
    "sg:province":"HI",
    "sg:tags":[
        "mater",
        "contractor"
    ],
    "wof:name":"Engel Insulation",
    "wof:placetype":"venue"
},
  "geometry": {"coordinates":[-155.95018300000001,19.585474],"type":"Point"}
}