{
  "type": "Feature",
  "properties": {
    "iso:country":"US",
    "sg:address":"7394 Mamalahoa Hwy",
    "sg:city":"Kealakekua",
    "sg:classifiers":[
        {
            "category":"Real Estate",
            "subcategory":"Real Estate Agent",
            "type":"Services"
        }
    ],
    "sg:phone":"+1 808 322 3677",
    "sg:postcode":"96750",
    "sg:province":"HI",
    "wof:name":"Real Estate Concern-Hawaii",
    "wof:placetype":"venue"
},
  "geometry": {"coordinates":[-155.92884699999999,19.539509],"type":"Point"}
}