{
  "type": "Feature",
  "properties": {
    "addr:full":"935 Dillingham Blvd Honolulu HI 96817",
    "addr:housenumber":"935",
    "addr:postcode":"96817",
    "addr:street":"Dillingham Blvd",
    "iso:country":"US",
    "sg:address":"935 Dillingham Blvd",
    "sg:city":"Honolulu",
    "sg:classifiers":[
        {
            "category":"Shopping",
            "type":"Retail Goods"
        },
        {
            "category":"Retail",
            "subcategory":"Repair Shop",
            "type":"Services"
        }
    ],
    "sg:phone":"+1 808 842 0678",
    "sg:postcode":"96817",
    "sg:province":"HI",
    "sg:tags":[
        "machine",
        "equipment",
        "copying"
    ],
    "wof:name":"Aloha Copy Systems",
    "wof:placetype":"venue"
},
  "geometry": {"coordinates":[-157.872693,21.321723],"type":"Point"}
}