{
  "type": "Feature",
  "properties": {
    "iso:country":"US",
    "sg:address":"730 Iliaina St",
    "sg:city":"Kailua",
    "sg:classifiers":[
        {
            "category":"Education",
            "subcategory":"School",
            "type":"Public Place"
        }
    ],
    "sg:phone":"+1 808 254 7955",
    "sg:postcode":"96734",
    "sg:province":"HI",
    "sg:tags":[
        "secondary"
    ],
    "sg:website":"www.winsa.k12.hi.us",
    "wof:name":"Windward School For Adults",
    "wof:placetype":"venue"
},
  "geometry": {"coordinates":[-157.756236,21.409452],"type":"Point"}
}