{
  "type": "Feature",
  "properties": {
    "addr:full":"930 N King St Honolulu HI 96817",
    "addr:housenumber":"930",
    "addr:postcode":"96817",
    "addr:street":"N King St",
    "iso:country":"US",
    "sg:address":"930 N King St",
    "sg:city":"Honolulu",
    "sg:classifiers":[
        {
            "category":"Food & Beverages",
            "subcategory":"Groceries & Convenience Stores",
            "type":"Retail Goods"
        }
    ],
    "sg:phone":"+1 808 841 2722",
    "sg:postcode":"96817",
    "sg:province":"HI",
    "sg:tags":[
        "grocer",
        "market"
    ],
    "wof:name":"Family Market",
    "wof:placetype":"venue"
},
  "geometry": {"coordinates":[-157.867931,21.323196],"type":"Point"}
}