{
  "type": "Feature",
  "properties": {
    "iso:country":"US",
    "sg:address":"138 Kuwale Rd",
    "sg:city":"Waianae",
    "sg:classifiers":[
        {
            "category":"Building & Trades",
            "subcategory":"Construction",
            "type":"Services"
        }
    ],
    "sg:phone":"+1 808 696 7553",
    "sg:postcode":"96792",
    "sg:province":"HI",
    "sg:tags":[
        "roofing",
        "contractor"
    ],
    "wof:name":"Leeward Roofing & Gen Contg",
    "wof:placetype":"venue"
},
  "geometry": {"coordinates":[-158.152715,21.456466],"type":"Point"}
}