{
  "type": "Feature",
  "properties": {
    "iso:country":"US",
    "sg:address":"1224 N School St",
    "sg:city":"Honolulu",
    "sg:classifiers":[
        {
            "category":"Personal",
            "subcategory":"Barber",
            "type":"Services"
        }
    ],
    "sg:phone":"+1 808 841 5534",
    "sg:postcode":"96817",
    "sg:province":"HI",
    "sg:tags":[
        "shop"
    ],
    "wof:name":"Mary's Barber Shop",
    "wof:placetype":"venue"
},
  "geometry": {"coordinates":[-157.86514500000001,21.330705],"type":"Point"}
}