{
  "type": "Feature",
  "properties": {
    "iso:country":"US",
    "sg:address":"208 Kahuhipa St",
    "sg:city":"Kaneohe",
    "sg:classifiers":[
        {
            "category":"Wholesale",
            "subcategory":"Non-durable Goods",
            "type":"Manufacturing & Wholesale Goods"
        }
    ],
    "sg:phone":"+1 808 247 8797",
    "sg:postcode":"96744",
    "sg:province":"HI",
    "sg:tags":[
        "advertising"
    ],
    "sg:website":"www.apphawaii.com",
    "wof:name":"APP Hawaii",
    "wof:placetype":"venue"
},
  "geometry": {"coordinates":[-157.808593,21.41425],"type":"Point"}
}