{
  "type": "Feature",
  "properties": {
    "iso:country":"US",
    "sg:address":"179 Kilauea Ave",
    "sg:city":"Hilo",
    "sg:classifiers":[
        {
            "category":"Retail",
            "subcategory":"Portrait Studio",
            "type":"Services"
        }
    ],
    "sg:phone":"+1 808 961 9923",
    "sg:postcode":"96720",
    "sg:province":"HI",
    "sg:tags":[
        "photographer"
    ],
    "wof:name":"Kilauea Gallery & Studio",
    "wof:placetype":"venue"
},
  "geometry": {"coordinates":[-155.08604600000001,19.72264],"type":"Point"}
}