{
  "type": "Feature",
  "properties": {
    "iso:country":"US",
    "sg:address":"3810 Maunaloa Ave",
    "sg:city":"Honolulu",
    "sg:classifiers":[
        {
            "category":"Health Services",
            "subcategory":"Health Practitioner",
            "type":"Services"
        }
    ],
    "sg:phone":"+1 808 732 7717",
    "sg:postcode":"96816",
    "sg:province":"HI",
    "wof:name":"Ward Laurence K Dr North Dako",
    "wof:placetype":"venue"
},
  "geometry": {"coordinates":[-157.798202,21.274266],"type":"Point"}
}