{
  "type": "Feature",
  "properties": {
    "iso:country":"US",
    "sg:address":"1130 Anuanu St",
    "sg:city":"Mililani",
    "sg:classifiers":[
        {
            "category":"Building & Trades",
            "subcategory":"Electrical",
            "type":"Services"
        }
    ],
    "sg:phone":"+1 808 630 2393",
    "sg:postcode":"96789",
    "sg:province":"HI",
    "sg:tags":[
        "electrical",
        "contractor"
    ],
    "wof:name":"C E O of Hawaii",
    "wof:placetype":"venue"
},
  "geometry": {"coordinates":[-157.988743,21.483382],"type":"Point"}
}