{
  "type": "Feature",
  "properties": {
    "iso:country":"US",
    "sg:address":"1249 Meheula Pkwy",
    "sg:city":"Mililani",
    "sg:classifiers":[
        {
            "category":"Wholesale",
            "subcategory":"Apparel",
            "type":"Manufacturing & Wholesale Goods"
        }
    ],
    "sg:phone":"+1 808 623 5112",
    "sg:postcode":"96789",
    "sg:province":"HI",
    "sg:tags":[
        "sportswear"
    ],
    "wof:name":"Ever Blue Casuals",
    "wof:placetype":"venue"
},
  "geometry": {"coordinates":[-158.007576,21.455167],"type":"Point"}
}