{
  "type": "Feature",
  "properties": {
    "addr:full":"709 Ahua St Honolulu HI 96819",
    "addr:housenumber":"709",
    "addr:postcode":"96819",
    "addr:street":"Ahua St",
    "iso:country":"US",
    "sg:address":"709 Ahua St",
    "sg:city":"Honolulu",
    "sg:classifiers":[
        {
            "category":"Professional",
            "subcategory":"Printing & Photocopies",
            "type":"Services"
        },
        {
            "category":"Manufacturing",
            "subcategory":"Printing",
            "type":"Manufacturing & Wholesale Goods"
        }
    ],
    "sg:phone":"+1 808 592 6555",
    "sg:postcode":"96819",
    "sg:province":"HI",
    "sg:tags":[
        "publishing",
        "copying",
        "duplicating"
    ],
    "wof:name":"New Tech Imaging",
    "wof:placetype":"venue"
},
  "geometry": {"coordinates":[-157.896895,21.339192],"type":"Point"}
}