{
  "type": "Feature",
  "properties": {
    "addr:full":"238 Sand Island Access Rd Honolulu HI 96819",
    "addr:housenumber":"238",
    "addr:postcode":"96819",
    "addr:street":"Sand Island Access Rd",
    "iso:country":"US",
    "sg:address":"238 Sand Island Access Rd",
    "sg:city":"Honolulu",
    "sg:classifiers":[
        {
            "category":"Building & Trades",
            "subcategory":"Electrical",
            "type":"Services"
        }
    ],
    "sg:phone":"+1 808 847 1792",
    "sg:postcode":"96819",
    "sg:province":"HI",
    "sg:tags":[
        "electric",
        "contractor"
    ],
    "wof:name":"Chet's Electric Repair",
    "wof:placetype":"venue"
},
  "geometry": {"coordinates":[-157.88963000000001,21.325355],"type":"Point"}
}