{
  "type": "Feature",
  "properties": {
    "iso:country":"US",
    "sg:address":"600 Kailua Rd",
    "sg:city":"Kailua",
    "sg:classifiers":[
        {
            "category":"Restaurant",
            "type":"Food & Drink"
        }
    ],
    "sg:phone":"+1 808 262 3337",
    "sg:postcode":"96734",
    "sg:province":"HI",
    "sg:tags":[
        "eating"
    ],
    "wof:name":"Pepper's Place",
    "wof:placetype":"venue"
},
  "geometry": {"coordinates":[-157.743393,21.394595],"type":"Point"}
}