{
  "type": "Feature",
  "properties": {
    "iso:country":"US",
    "sg:address":"42 Waianuenue Ave",
    "sg:city":"Hilo",
    "sg:classifiers":[
        {
            "category":"Personal",
            "subcategory":"Beauty Salon",
            "type":"Services"
        }
    ],
    "sg:phone":"+1 808 961 5858",
    "sg:postcode":"96720",
    "sg:province":"HI",
    "sg:tags":[
        "shop"
    ],
    "wof:name":"Studio 58",
    "wof:placetype":"venue"
},
  "geometry": {"coordinates":[-155.087245,19.726462],"type":"Point"}
}