{
  "type": "Feature",
  "properties": {
    "iso:country":"US",
    "sg:address":"205 Nui Village Rd",
    "sg:city":"Ookala",
    "sg:classifiers":[
        {
            "category":"Retail",
            "subcategory":"Repair Shop",
            "type":"Services"
        }
    ],
    "sg:phone":"+1 808 962 6689",
    "sg:postcode":"96774",
    "sg:province":"HI",
    "sg:tags":[
        "repairing",
        "lawn",
        "mower"
    ],
    "wof:name":"Labrie's Small Engine Repair",
    "wof:placetype":"venue"
},
  "geometry": {"coordinates":[-155.27303000000001,20.01022],"type":"Point"}
}