{
  "type": "Feature",
  "properties": {
    "addr:full":"5095 Napilihau St Lahaina HI 96761",
    "addr:housenumber":"5095",
    "addr:postcode":"96761",
    "addr:street":"Napilihau St",
    "iso:country":"US",
    "sg:address":"5095 Napilihau St",
    "sg:city":"Lahaina",
    "sg:classifiers":[
        {
            "category":"Recreation",
            "type":"Entertainment"
        }
    ],
    "sg:phone":"+1 808 669 4708",
    "sg:postcode":"96761",
    "sg:province":"HI",
    "wof:name":"Ironwood Ranch Riding STA",
    "wof:placetype":"venue"
},
  "geometry": {"coordinates":[-156.67121299999999,20.990135],"type":"Point"}
}