{
  "type": "Feature",
  "properties": {
    "iso:country":"US",
    "sg:address":"1620 Alaneo St",
    "sg:city":"Honolulu",
    "sg:classifiers":[
        {
            "category":"Professional",
            "subcategory":"Lawyer & Legal Services",
            "type":"Services"
        }
    ],
    "sg:phone":"+1 808 550 4661",
    "sg:postcode":"96817",
    "sg:province":"HI",
    "wof:name":"Lee Lenore H Law Office of",
    "wof:placetype":"venue"
},
  "geometry": {"coordinates":[-157.859872,21.326088],"type":"Point"}
}