{
  "type": "Feature",
  "properties": {
    "iso:country":"US",
    "sg:address":"113 Krukowski Rd",
    "sg:city":"Honolulu",
    "sg:classifiers":[
        {
            "category":"Building & Trades",
            "subcategory":"Construction",
            "type":"Services"
        }
    ],
    "sg:phone":"+1 808 834 2110",
    "sg:postcode":"96859",
    "sg:province":"HI",
    "sg:tags":[
        "nonresidential"
    ],
    "wof:name":"J A Jones Construction Company",
    "wof:placetype":"venue"
},
  "geometry": {"coordinates":[-157.89396600000001,21.356482],"type":"Point"}
}