{
  "type": "Feature",
  "properties": {
    "iso:country":"US",
    "sg:address":"790 Lumiaina St",
    "sg:city":"Waipahu",
    "sg:classifiers":[
        {
            "category":"Organizations",
            "subcategory":"Labor Organization",
            "type":"Services"
        }
    ],
    "sg:phone":"+1 808 677 2963",
    "sg:postcode":"96797",
    "sg:province":"HI",
    "sg:tags":[
        "clothes"
    ],
    "wof:name":"Local Fever",
    "wof:placetype":"venue"
},
  "geometry": {"coordinates":[-158.006113,21.400364],"type":"Point"}
}