{
  "type": "Feature",
  "properties": {
    "addr:full":"2328 Kaululaau St Honolulu HI 96813",
    "addr:housenumber":"2328",
    "addr:postcode":"96813",
    "addr:street":"Kaululaau St",
    "iso:country":"US",
    "sg:address":"2328 Kaululaau St",
    "sg:city":"Honolulu",
    "sg:classifiers":[
        {
            "category":"Manufacturing",
            "subcategory":"Printing",
            "type":"Manufacturing & Wholesale Goods"
        }
    ],
    "sg:phone":"+1 808 373 4297",
    "sg:postcode":"96813",
    "sg:province":"HI",
    "sg:tags":[
        "lithographic",
        "commercial"
    ],
    "wof:name":"Gerards Printing",
    "wof:placetype":"venue"
},
  "geometry": {"coordinates":[-157.836513,21.318785],"type":"Point"}
}