{
  "type": "Feature",
  "properties": {
    "iso:country":"US",
    "sg:address":"545 Hihimanu St",
    "sg:city":"Waimanalo",
    "sg:classifiers":[
        {
            "category":"Real Estate",
            "subcategory":"Real Estate Operator",
            "type":"Services"
        }
    ],
    "sg:phone":"+1 808 259 5649",
    "sg:postcode":"96795",
    "sg:province":"HI",
    "sg:tags":[
        "apartment"
    ],
    "wof:name":"Waimanalo Apartments",
    "wof:placetype":"venue"
},
  "geometry": {"coordinates":[-157.722407,21.344465],"type":"Point"}
}