{
  "type": "Feature",
  "properties": {
    "iso:country":"US",
    "sg:address":"765 Amana St",
    "sg:city":"Honolulu",
    "sg:classifiers":[
        {
            "category":"Wholesale",
            "subcategory":"Electrical",
            "type":"Manufacturing & Wholesale Goods"
        }
    ],
    "sg:phone":"+1 808 732 5552",
    "sg:postcode":"96814",
    "sg:province":"HI",
    "sg:tags":[
        "alarm",
        "burglar",
        "system"
    ],
    "wof:name":"Elite Security Systems",
    "wof:placetype":"venue"
},
  "geometry": {"coordinates":[-157.84028900000001,21.29398],"type":"Point"}
}