{
  "type": "Feature",
  "properties": {
    "iso:country":"US",
    "sg:address":"5799 Mamalahoa Hwy",
    "sg:city":"Holualoa",
    "sg:classifiers":[
        {
            "category":"Restaurant",
            "type":"Food & Drink"
        }
    ],
    "sg:phone":"+1 808 324 1495",
    "sg:postcode":"96725",
    "sg:province":"HI",
    "sg:tags":[
        "eating"
    ],
    "wof:name":"Lani Tiare Coffee",
    "wof:placetype":"venue"
},
  "geometry": {"coordinates":[-155.94869,19.6291],"type":"Point"}
}