{
  "type": "Feature",
  "properties": {
    "iso:country":"US",
    "sg:address":"207 Muliwai Ave",
    "sg:city":"Wahiawa",
    "sg:classifiers":[
        {
            "category":"Organizations",
            "subcategory":"Religious Organization",
            "type":"Services"
        }
    ],
    "sg:phone":"+1 808 621 6667",
    "sg:postcode":"96786",
    "sg:province":"HI",
    "wof:name":"Konko Mission Of Wahiawa",
    "wof:placetype":"venue"
},
  "geometry": {"coordinates":[-158.02547300000001,21.494272],"type":"Point"}
}