{
  "type": "Feature",
  "properties": {
    "iso:country":"US",
    "sg:address":"1964 10th Ave",
    "sg:city":"Honolulu",
    "sg:classifiers":[
        {
            "category":"Wholesale",
            "subcategory":"Apparel",
            "type":"Manufacturing & Wholesale Goods"
        }
    ],
    "sg:phone":"+1 808 732 7813",
    "sg:postcode":"96816",
    "sg:province":"HI",
    "sg:tags":[
        "clothing"
    ],
    "wof:name":"Soljah",
    "wof:placetype":"venue"
},
  "geometry": {"coordinates":[-157.79370900000001,21.297353],"type":"Point"}
}