{
  "type": "Feature",
  "properties": {
    "addr:full":"1926 S King St Honolulu HI 96826",
    "addr:housenumber":"1926",
    "addr:postcode":"96826",
    "addr:street":"S King St",
    "iso:country":"US",
    "sg:address":"1926 S King St",
    "sg:city":"Honolulu",
    "sg:classifiers":[
        {
            "category":"Real Estate",
            "subcategory":"Real Estate Agent",
            "type":"Services"
        }
    ],
    "sg:phone":"+1 808 955 7575",
    "sg:postcode":"96826",
    "sg:province":"HI",
    "wof:name":"Real Estate Systems Inc",
    "wof:placetype":"venue"
},
  "geometry": {"coordinates":[-157.83029300000001,21.295022],"type":"Point"}
}