{
  "type": "Feature",
  "properties": {
    "iso:country":"US",
    "sg:address":"5563 Kaiwi St",
    "sg:city":"Kailua Kona",
    "sg:classifiers":[
        {
            "category":"Shopping",
            "subcategory":"Used Merchandise",
            "type":"Retail Goods"
        }
    ],
    "sg:phone":"+1 808 331 8788",
    "sg:postcode":"96740",
    "sg:province":"HI",
    "sg:tags":[
        "antique"
    ],
    "wof:name":"Robert Teasley Collections",
    "wof:placetype":"venue"
},
  "geometry": {"coordinates":[-156.000925,19.643036],"type":"Point"}
}