{
  "type": "Feature",
  "properties": {
    "iso:country":"US",
    "sg:address":"1036 Maunakea St",
    "sg:city":"Honolulu",
    "sg:classifiers":[
        {
            "category":"Food & Beverages",
            "subcategory":"Groceries & Convenience Stores",
            "type":"Retail Goods"
        }
    ],
    "sg:phone":"+1 808 523 5464",
    "sg:postcode":"96817",
    "sg:province":"HI",
    "sg:tags":[
        "chinese",
        "market"
    ],
    "wof:name":"Wing Loy Market",
    "wof:placetype":"venue"
},
  "geometry": {"coordinates":[-157.86362700000001,21.311807],"type":"Point"}
}