{
  "type": "Feature",
  "properties": {
    "iso:country":"US",
    "sg:address":"1394 Kalaniiki St",
    "sg:city":"Honolulu",
    "sg:classifiers":[
        {
            "category":"Organizations",
            "subcategory":"Religious Organization",
            "type":"Services"
        }
    ],
    "sg:phone":"+1 808 373 7783",
    "sg:postcode":"96821",
    "sg:province":"HI",
    "wof:name":"New Song Christian Fellowship",
    "wof:placetype":"venue"
},
  "geometry": {"coordinates":[-157.77234999999999,21.281716],"type":"Point"}
}