{
  "type": "Feature",
  "properties": {
    "addr:full":"601 N Kukui St Honolulu HI 96817",
    "addr:housenumber":"601",
    "addr:postcode":"96817",
    "addr:street":"N Kukui St",
    "iso:country":"US",
    "sg:address":"601 N Kukui St",
    "sg:city":"Honolulu",
    "sg:classifiers":[
        {
            "category":"Professional",
            "subcategory":"Computer Services",
            "type":"Services"
        }
    ],
    "sg:phone":"+1 808 395 3006",
    "sg:postcode":"96817",
    "sg:province":"HI",
    "sg:tags":[
        "programming"
    ],
    "wof:name":"Bruckmans",
    "wof:placetype":"venue"
},
  "geometry": {"coordinates":[-157.86472499999999,21.321057],"type":"Point"}
}