{
  "type": "Feature",
  "properties": {
    "iso:country":"US",
    "sg:address":"303 Liliuokalani Ave",
    "sg:city":"Honolulu",
    "sg:classifiers":[
        {
            "category":"Retail",
            "subcategory":"Repair Shop",
            "type":"Services"
        }
    ],
    "sg:phone":"+1 808 924 2605",
    "sg:postcode":"96815",
    "sg:province":"HI",
    "sg:tags":[
        "lock",
        "locksmith"
    ],
    "wof:name":"Gold's Locksmith Co",
    "wof:placetype":"venue"
},
  "geometry": {"coordinates":[-157.82094000000001,21.27667],"type":"Point"}
}