{
  "type": "Feature",
  "properties": {
    "addr:full":"500 Ala Moana Blvd Honolulu HI 96813",
    "addr:housenumber":"500",
    "addr:postcode":"96813",
    "addr:street":"Ala Moana Blvd",
    "iso:country":"US",
    "sg:address":"500 Ala Moana Blvd",
    "sg:city":"Honolulu",
    "sg:classifiers":[
        {
            "category":"Manufacturing",
            "subcategory":"Furniture",
            "type":"Manufacturing & Wholesale Goods"
        }
    ],
    "sg:phone":"+1 808 521 7086",
    "sg:postcode":"96813",
    "sg:province":"HI",
    "sg:tags":[
        "household",
        "metal",
        "mfg"
    ],
    "wof:name":"D & L McKay Associates",
    "wof:placetype":"venue"
},
  "geometry": {"coordinates":[-157.86317500000001,21.300985],"type":"Point"}
}