{
  "type": "Feature",
  "properties": {
    "iso:country":"US",
    "sg:address":"71 Lopaka Pl",
    "sg:city":"Kula",
    "sg:classifiers":[
        {
            "category":"Professional",
            "subcategory":"Computer Services",
            "type":"Services"
        }
    ],
    "sg:phone":"+1 808 878 3035",
    "sg:postcode":"96790",
    "sg:province":"HI",
    "sg:tags":[
        "related"
    ],
    "wof:name":"Stephen Lock Computer Conslt",
    "wof:placetype":"venue"
},
  "geometry": {"coordinates":[-156.324657,20.793676],"type":"Point"}
}