{
  "type": "Feature",
  "properties": {
    "iso:country":"US",
    "sg:address":"310 Hoauna St",
    "sg:city":"Kaneohe",
    "sg:classifiers":[
        {
            "category":"Food & Beverages",
            "subcategory":"Bakery",
            "type":"Retail Goods"
        }
    ],
    "sg:phone":"+1 808 247 6106",
    "sg:postcode":"96744",
    "sg:province":"HI",
    "wof:name":"Bread of Life Inc",
    "wof:placetype":"venue"
},
  "geometry": {"coordinates":[-157.81319500000001,21.419062],"type":"Point"}
}