{
  "type": "Feature",
  "properties": {
    "addr:full":"61 Koaha Way Aiea HI 96701",
    "addr:housenumber":"61",
    "addr:postcode":"96701",
    "addr:street":"Koaha Way",
    "iso:country":"US",
    "sg:address":"61 Koaha Way",
    "sg:city":"Aiea",
    "sg:classifiers":[
        {
            "category":"Manufacturing",
            "subcategory":"Furniture",
            "type":"Manufacturing & Wholesale Goods"
        }
    ],
    "sg:phone":"+1 808 236 1449",
    "sg:postcode":"96701",
    "sg:province":"HI",
    "sg:tags":[
        "drapery",
        "mfg"
    ],
    "wof:name":"Vertical Junkies Clothing Co",
    "wof:placetype":"venue"
},
  "geometry": {"coordinates":[-157.89872,21.37802],"type":"Point"}
}