{
  "type": "Feature",
  "properties": {
    "addr:full":"629 Kailua Rd Kailua HI 96734",
    "addr:housenumber":"629",
    "addr:postcode":"96734",
    "addr:street":"Kailua Rd",
    "iso:country":"US",
    "sg:address":"629 Kailua Rd",
    "sg:city":"Kailua",
    "sg:classifiers":[
        {
            "category":"Shopping",
            "type":"Retail Goods"
        }
    ],
    "sg:phone":"+1 808 261 8131",
    "sg:postcode":"96734",
    "sg:province":"HI",
    "sg:tags":[
        "art",
        "gallery",
        "dealer"
    ],
    "wof:name":"Island Treasures",
    "wof:placetype":"venue"
},
  "geometry": {"coordinates":[-157.741761,21.393841],"type":"Point"}
}