{
  "type": "Feature",
  "properties": {
    "addr:full":"2134 Saint Louis Dr Honolulu HI 96816",
    "addr:housenumber":"2134",
    "addr:postcode":"96816",
    "addr:street":"Saint Louis Dr",
    "iso:country":"US",
    "sg:address":"2134 Saint Louis Dr",
    "sg:city":"Honolulu",
    "sg:classifiers":[
        {
            "category":"Wholesale",
            "subcategory":"Non-durable Goods",
            "type":"Manufacturing & Wholesale Goods"
        }
    ],
    "sg:phone":"+1 808 734 2282",
    "sg:postcode":"96816",
    "sg:province":"HI",
    "wof:name":"Crofton Group",
    "wof:placetype":"venue"
},
  "geometry": {"coordinates":[-157.802313,21.300797],"type":"Point"}
}