{
  "type": "Feature",
  "properties": {
    "iso:country":"US",
    "sg:address":"830 Mapunapuna St",
    "sg:city":"Honolulu",
    "sg:classifiers":[
        {
            "category":"Professional",
            "type":"Services"
        }
    ],
    "sg:phone":"+1 808 836 7672",
    "sg:postcode":"96819",
    "sg:province":"HI",
    "sg:tags":[
        "establishment"
    ],
    "wof:name":"H K Enterprises Inc",
    "wof:placetype":"venue"
},
  "geometry": {"coordinates":[-157.89941200000001,21.342047],"type":"Point"}
}