{
  "type": "Feature",
  "properties": {
    "iso:country":"US",
    "sg:address":"848 Ala Lilikoi St",
    "sg:city":"Honolulu",
    "sg:classifiers":[
        {
            "category":"Autos & Motor Vehicles",
            "subcategory":"Auto Supplies",
            "type":"Retail Goods"
        }
    ],
    "sg:phone":"+1 808 833 6626",
    "sg:postcode":"96818",
    "sg:province":"HI",
    "sg:tags":[
        "automobile",
        "parts"
    ],
    "wof:name":"Salt Lake Auto Parts Inc",
    "wof:placetype":"venue"
},
  "geometry": {"coordinates":[-157.913084,21.344877],"type":"Point"}
}