{
  "type": "Feature",
  "properties": {
    "iso:country":"US",
    "sg:address":"371 Makapipipi St",
    "sg:city":"Mililani",
    "sg:classifiers":[
        {
            "category":"Building & Trades",
            "subcategory":"Construction",
            "type":"Services"
        }
    ],
    "sg:phone":"+1 808 623 7326",
    "sg:postcode":"96789",
    "sg:province":"HI",
    "sg:tags":[
        "excavation",
        "contractor"
    ],
    "wof:name":"Mahelu Bobcats Inc",
    "wof:placetype":"venue"
},
  "geometry": {"coordinates":[-158.01713699999999,21.428743],"type":"Point"}
}