{
  "type": "Feature",
  "properties": {
    "iso:country":"US",
    "sg:address":"1206 S King St",
    "sg:city":"Honolulu",
    "sg:classifiers":[
        {
            "category":"Restaurant",
            "type":"Food & Drink"
        }
    ],
    "sg:phone":"+1 808 591 9276",
    "sg:postcode":"96814",
    "sg:province":"HI",
    "sg:tags":[
        "independent",
        "family"
    ],
    "wof:name":"Wisteria The",
    "wof:placetype":"venue"
},
  "geometry": {"coordinates":[-157.84342799999999,21.299689],"type":"Point"}
}