{
  "type": "Feature",
  "properties": {
    "iso:country":"US",
    "sg:address":"915 Lehua Ave",
    "sg:city":"Pearl City",
    "sg:classifiers":[
        {
            "category":"Personal",
            "subcategory":"Beauty Salon",
            "type":"Services"
        }
    ],
    "sg:phone":"+1 808 456 0022",
    "sg:postcode":"96782",
    "sg:province":"HI",
    "wof:name":"Suki's Barber Shop",
    "wof:placetype":"venue"
},
  "geometry": {"coordinates":[-157.971056,21.391816],"type":"Point"}
}