{
  "type": "Feature",
  "properties": {
    "addr:full":"4350 Halupa St Honolulu HI 96818",
    "addr:housenumber":"4350",
    "addr:postcode":"96818",
    "addr:street":"Halupa St",
    "iso:country":"US",
    "sg:address":"4350 Halupa St",
    "sg:city":"Honolulu",
    "sg:classifiers":[
        {
            "category":"Professional",
            "subcategory":"Business Services",
            "type":"Services"
        }
    ],
    "sg:phone":"+1 808 423 1916",
    "sg:postcode":"96818",
    "sg:province":"HI",
    "sg:tags":[
        "interior",
        "consultant",
        "design",
        "decorator"
    ],
    "wof:name":"Interior Design Svc",
    "wof:placetype":"venue"
},
  "geometry": {"coordinates":[-157.91953699999999,21.364643],"type":"Point"}
}