{
  "type": "Feature",
  "properties": {
    "iso:country":"US",
    "sg:address":"1005 Moanalua Rd",
    "sg:city":"Aiea",
    "sg:classifiers":[
        {
            "category":"Real Estate",
            "subcategory":"Real Estate Operator",
            "type":"Services"
        }
    ],
    "sg:phone":"+1 808 488 0981",
    "sg:postcode":"96701",
    "sg:province":"HI",
    "sg:tags":[
        "mall",
        "shopping",
        "center"
    ],
    "wof:name":"MMI Realty Svc",
    "wof:placetype":"venue"
},
  "geometry": {"coordinates":[-157.94079500000001,21.385893],"type":"Point"}
}