{
  "type": "Feature",
  "properties": {
    "iso:country":"US",
    "sg:address":"1258 Kaahumanu St",
    "sg:city":"Pearl City",
    "sg:classifiers":[
        {
            "category":"Insurance",
            "subcategory":"Insurance Agent",
            "type":"Services"
        }
    ],
    "sg:phone":"+1 808 533 2444",
    "sg:postcode":"96782",
    "sg:province":"HI",
    "wof:name":"AIG Hawaii",
    "wof:placetype":"venue"
},
  "geometry": {"coordinates":[-157.954227,21.387617],"type":"Point"}
}