{
  "type": "Feature",
  "properties": {
    "iso:country":"US",
    "sg:address":"326 Lala Pl",
    "sg:city":"Kailua",
    "sg:classifiers":[
        {
            "category":"Professional",
            "subcategory":"Business Services",
            "type":"Services"
        }
    ],
    "sg:phone":"+1 808 262 0730",
    "sg:postcode":"96734",
    "sg:province":"HI",
    "sg:tags":[
        "arbitration"
    ],
    "wof:name":"Mediation Center-Windward",
    "wof:placetype":"venue"
},
  "geometry": {"coordinates":[-157.714203,21.381938],"type":"Point"}
}