{
  "type": "Feature",
  "properties": {
    "iso:country":"US",
    "sg:address":"335 Merchant St",
    "sg:city":"Honolulu",
    "sg:classifiers":[
        {
            "category":"Food & Beverages",
            "subcategory":"Groceries & Convenience Stores",
            "type":"Retail Goods"
        }
    ],
    "sg:phone":"+1 808 599 8979",
    "sg:postcode":"96813",
    "sg:province":"HI",
    "wof:name":"Les's Snack Shop",
    "wof:placetype":"venue"
},
  "geometry": {"coordinates":[-157.860196,21.306217],"type":"Point"}
}