{
  "type": "Feature",
  "properties": {
    "addr:full":"634 Kalihi St Honolulu HI 96819",
    "addr:housenumber":"634",
    "addr:postcode":"96819",
    "addr:street":"Kalihi St",
    "iso:country":"US",
    "sg:address":"634 Kalihi St",
    "sg:city":"Honolulu",
    "sg:classifiers":[
        {
            "category":"Health Services",
            "subcategory":"Doctor",
            "type":"Services"
        }
    ],
    "sg:phone":"+1 808 847 1888",
    "sg:postcode":"96819",
    "sg:province":"HI",
    "sg:tags":[
        "dentist"
    ],
    "wof:name":"Ylarde Roland J B DDS",
    "wof:placetype":"venue"
},
  "geometry": {"coordinates":[-157.87866399999999,21.32787],"type":"Point"}
}