{
  "type": "Feature",
  "properties": {
    "iso:country":"US",
    "sg:address":"961 Kawaiahao St",
    "sg:city":"Honolulu",
    "sg:classifiers":[
        {
            "category":"Building & Trades",
            "subcategory":"Cleaning & Sanitation",
            "type":"Services"
        }
    ],
    "sg:phone":"+1 808 593 1211",
    "sg:postcode":"96814",
    "sg:province":"HI",
    "sg:tags":[
        "interior",
        "window",
        "b",
        "exterior"
    ],
    "wof:name":"Clear Visions",
    "wof:placetype":"venue"
},
  "geometry": {"coordinates":[-157.85301799999999,21.297032],"type":"Point"}
}