{
  "type": "Feature",
  "properties": {
    "iso:country":"US",
    "sg:address":"1141 Union Mall",
    "sg:city":"Honolulu",
    "sg:classifiers":[
        {
            "category":"Personal",
            "subcategory":"Beauty Salon",
            "type":"Services"
        }
    ],
    "sg:phone":"+1 808 537 5773",
    "sg:postcode":"96813",
    "sg:province":"HI",
    "sg:tags":[
        "shop"
    ],
    "wof:name":"Lorraine's Beauty Salons",
    "wof:placetype":"venue"
},
  "geometry": {"coordinates":[-157.86002099999999,21.309832],"type":"Point"}
}