{
  "type": "Feature",
  "properties": {
    "iso:country":"US",
    "sg:address":"611 Cooke St",
    "sg:city":"Honolulu",
    "sg:classifiers":[
        {
            "category":"Social Services",
            "subcategory":"Child Care",
            "type":"Services"
        }
    ],
    "sg:phone":"+1 808 791 3647",
    "sg:postcode":"96813",
    "sg:province":"HI",
    "wof:name":"Ohana Doggie Day Care & Spa",
    "wof:placetype":"venue"
},
  "geometry": {"coordinates":[-157.85657800000001,21.300184],"type":"Point"}
}