{
  "type": "Feature",
  "properties": {
    "iso:country":"US",
    "sg:address":"620 California Ave",
    "sg:city":"Wahiawa",
    "sg:classifiers":[
        {
            "category":"Shopping",
            "subcategory":"Gifts & Souvenirs",
            "type":"Retail Goods"
        }
    ],
    "sg:phone":"+1 808 931 6278",
    "sg:postcode":"96786",
    "sg:province":"HI",
    "sg:tags":[
        "shop"
    ],
    "wof:name":"B-Mart",
    "wof:placetype":"venue"
},
  "geometry": {"coordinates":[-158.02856299999999,21.496519],"type":"Point"}
}