{
  "type": "Feature",
  "properties": {
    "iso:country":"US",
    "sg:address":"162 N King St",
    "sg:city":"Honolulu",
    "sg:classifiers":[
        {
            "category":"Retail",
            "subcategory":"Repair Shop",
            "type":"Services"
        }
    ],
    "sg:phone":"+1 808 533 6405",
    "sg:postcode":"96817",
    "sg:province":"HI",
    "wof:name":"Quang Watch Repair",
    "wof:placetype":"venue"
},
  "geometry": {"coordinates":[-157.864034,21.312715],"type":"Point"}
}