{
  "type": "Feature",
  "properties": {
    "addr:full":"3599 Waialae Ave Honolulu HI 96816",
    "addr:housenumber":"3599",
    "addr:postcode":"96816",
    "addr:street":"Waialae Ave",
    "iso:country":"US",
    "sg:address":"3599 Waialae Ave",
    "sg:city":"Honolulu",
    "sg:classifiers":[
        {
            "category":"Banks & Credit Unions",
            "subcategory":"Bank",
            "type":"Services"
        }
    ],
    "sg:phone":"+1 808 943 4570",
    "sg:postcode":"96816",
    "sg:province":"HI",
    "wof:name":"First Hawaiian Bank",
    "wof:placetype":"venue"
},
  "geometry": {"coordinates":[-157.799139,21.282811],"type":"Point"}
}