{
  "type": "Feature",
  "properties": {
    "addr:full":"508 Atkinson Dr Honolulu HI 96814",
    "addr:housenumber":"508",
    "addr:postcode":"96814",
    "addr:street":"Atkinson Dr",
    "iso:country":"US",
    "sg:address":"508 Atkinson Dr",
    "sg:city":"Honolulu",
    "sg:classifiers":[
        {
            "category":"Shopping",
            "subcategory":"Optical Goods",
            "type":"Retail Goods"
        }
    ],
    "sg:phone":"+1 808 949 7288",
    "sg:postcode":"96814",
    "sg:province":"HI",
    "sg:tags":[
        "optician"
    ],
    "wof:name":"Eyeglass Shop The",
    "wof:placetype":"venue"
},
  "geometry": {"coordinates":[-157.83801700000001,21.29028],"type":"Point"}
}