{
  "type": "Feature",
  "properties": {
    "iso:country":"US",
    "sg:address":"192 Pili Mua St",
    "sg:city":"Keaau",
    "sg:classifiers":[
        {
            "category":"Social Services",
            "type":"Services"
        }
    ],
    "sg:phone":"+1 808 930 0400",
    "sg:postcode":"96749",
    "sg:province":"HI",
    "sg:tags":[
        "youth",
        "organization",
        "center"
    ],
    "wof:name":"Bay Clinic Pulama Project",
    "wof:placetype":"venue"
},
  "geometry": {"coordinates":[-155.039965,19.620686],"type":"Point"}
}