{
  "type": "Feature",
  "properties": {
    "iso:country":"US",
    "sg:address":"3052 Peleke St",
    "sg:city":"Lihue",
    "sg:classifiers":[
        {
            "category":"Retail",
            "subcategory":"Repair Shop",
            "type":"Services"
        }
    ],
    "sg:phone":"+1 808 245 9340",
    "sg:postcode":"96766",
    "sg:province":"HI",
    "sg:tags":[
        "welding"
    ],
    "wof:name":"Kauai Welding Inc",
    "wof:placetype":"venue"
},
  "geometry": {"coordinates":[-159.3553,21.96717],"type":"Point"}
}