{
  "type": "Feature",
  "properties": {
    "addr:full":"515 Ukee St Waipahu HI 96797",
    "addr:housenumber":"515",
    "addr:postcode":"96797",
    "addr:street":"Ukee St",
    "iso:country":"US",
    "sg:address":"515 Ukee St",
    "sg:city":"Waipahu",
    "sg:classifiers":[
        {
            "category":"Shopping",
            "subcategory":"Computers & Home Electronics",
            "type":"Retail Goods"
        }
    ],
    "sg:phone":"+1 808 677 5700",
    "sg:postcode":"96797",
    "sg:province":"HI",
    "sg:tags":[
        "professional",
        "audio",
        "rental",
        "sales",
        "equipment"
    ],
    "wof:name":"Leo Nani Incorporated",
    "wof:placetype":"venue"
},
  "geometry": {"coordinates":[-158.00488899999999,21.420438],"type":"Point"}
}