{
  "type": "Feature",
  "properties": {
    "iso:country":"US",
    "sg:address":"1350 Waianuenue Ave",
    "sg:city":"Hilo",
    "sg:classifiers":[
        {
            "category":"Organizations",
            "subcategory":"Religious Organization",
            "type":"Services"
        }
    ],
    "sg:phone":"+1 808 935 5914",
    "sg:postcode":"96720",
    "sg:province":"HI",
    "sg:tags":[
        "church"
    ],
    "wof:name":"First United Protestant Church",
    "wof:placetype":"venue"
},
  "geometry": {"coordinates":[-155.11861200000001,19.716968],"type":"Point"}
}