{
  "type": "Feature",
  "properties": {
    "iso:country":"US",
    "sg:address":"6224 Mamalahoa Hwy",
    "sg:city":"Captain Cook",
    "sg:classifiers":[
        {
            "category":"Real Estate",
            "subcategory":"Real Estate Agent",
            "type":"Services"
        }
    ],
    "sg:phone":"+1 808 323 9789",
    "sg:postcode":"96704",
    "sg:province":"HI",
    "sg:website":"www.kefferhawaii.com",
    "wof:name":"Keffer Properties",
    "wof:placetype":"venue"
},
  "geometry": {"coordinates":[-155.91423599999999,19.491872],"type":"Point"}
}