{
  "type": "Feature",
  "properties": {
    "addr:full":"385 Hukilike St Kahului HI 96732",
    "addr:housenumber":"385",
    "addr:postcode":"96732",
    "addr:street":"Hukilike St",
    "iso:country":"US",
    "sg:address":"385 Hukilike St",
    "sg:city":"Kahului",
    "sg:classifiers":[
        {
            "category":"Wholesale",
            "subcategory":"Petroleum",
            "type":"Manufacturing & Wholesale Goods"
        },
        {
            "category":"Mining & Drilling",
            "type":"Manufacturing & Wholesale Goods"
        }
    ],
    "sg:phone":"+1 808 270 2802",
    "sg:postcode":"96732",
    "sg:province":"HI",
    "sg:tags":[
        "bulk",
        "field",
        "oil",
        "gasoline"
    ],
    "wof:name":"Hawaii Fueling Network",
    "wof:placetype":"venue"
},
  "geometry": {"coordinates":[-156.45898199999999,20.88332],"type":"Point"}
}