{
  "type": "Feature",
  "properties": {
    "iso:country":"US",
    "sg:address":"1357 S Beretania St",
    "sg:city":"Honolulu",
    "sg:classifiers":[
        {
            "category":"Retail",
            "subcategory":"Laundry & Dry Cleaning",
            "type":"Services"
        }
    ],
    "sg:phone":"+1 808 593 0457",
    "sg:postcode":"96814",
    "sg:province":"HI",
    "sg:tags":[
        "drycleaning",
        "plant"
    ],
    "wof:name":"Abe Cleaners",
    "wof:placetype":"venue"
},
  "geometry": {"coordinates":[-157.83965499999999,21.300217],"type":"Point"}
}