{
  "type": "Feature",
  "properties": {
    "iso:country":"US",
    "sg:address":"250 Kamehameha Hwy",
    "sg:city":"Haleiwa",
    "sg:classifiers":[
        {
            "category":"Shopping",
            "subcategory":"Jewelry",
            "type":"Retail Goods"
        }
    ],
    "sg:phone":"+1 808 637 6609",
    "sg:postcode":"96712",
    "sg:province":"HI",
    "sg:tags":[
        "merchandise",
        "jeweler"
    ],
    "wof:name":"Jungle Gems",
    "wof:placetype":"venue"
},
  "geometry": {"coordinates":[-158.07068100000001,21.631967],"type":"Point"}
}