{
  "type": "Feature",
  "properties": {
    "iso:country":"US",
    "sg:address":"1095 Dillingham Blvd",
    "sg:city":"Honolulu",
    "sg:classifiers":[
        {
            "category":"Retail",
            "subcategory":"Auto Repair",
            "type":"Services"
        }
    ],
    "sg:phone":"+1 808 841 9077",
    "sg:postcode":"96817",
    "sg:province":"HI",
    "sg:tags":[
        "glass",
        "coating",
        "tinting"
    ],
    "wof:name":"Special-T-Tinting Mobile Elect",
    "wof:placetype":"venue"
},
  "geometry": {"coordinates":[-157.87038100000001,21.320332],"type":"Point"}
}