{
  "type": "Feature",
  "properties": {
    "iso:country":"US",
    "sg:address":"633 Keneke St",
    "sg:city":"Kaneohe",
    "sg:classifiers":[
        {
            "category":"Education",
            "subcategory":"School",
            "type":"Public Place"
        }
    ],
    "sg:phone":"+1 808 233 2900",
    "sg:postcode":"96744",
    "sg:province":"HI",
    "sg:website":"www.koolaubc.org",
    "wof:name":"Koolau Baptist Church",
    "wof:placetype":"venue"
},
  "geometry": {"coordinates":[-157.8058,21.404905],"type":"Point"}
}