{
  "type": "Feature",
  "properties": {
    "iso:country":"US",
    "sg:address":"3050 Kiele Ave",
    "sg:city":"Honolulu",
    "sg:classifiers":[
        {
            "category":"Wholesale",
            "subcategory":"Machinery & Supplies",
            "type":"Manufacturing & Wholesale Goods"
        }
    ],
    "sg:phone":"+1 808 396 8248",
    "sg:postcode":"96815",
    "sg:province":"HI",
    "sg:tags":[
        "instrument",
        "surveying"
    ],
    "wof:name":"Folk Enterprises Inc",
    "wof:placetype":"venue"
},
  "geometry": {"coordinates":[-157.818667,21.25997],"type":"Point"}
}