{
  "type": "Feature",
  "properties": {
    "addr:full":"315 Hookahi St Wailuku HI 96793",
    "addr:housenumber":"315",
    "addr:postcode":"96793",
    "addr:street":"Hookahi St",
    "iso:country":"US",
    "sg:address":"315 Hookahi St",
    "sg:city":"Wailuku",
    "sg:classifiers":[
        {
            "category":"Bars & Pubs",
            "type":"Food & Drink"
        }
    ],
    "sg:phone":"+1 808 244 5656",
    "sg:postcode":"96793",
    "sg:province":"HI",
    "sg:tags":[
        "drinking"
    ],
    "wof:name":"Little Saigon",
    "wof:placetype":"venue"
},
  "geometry": {"coordinates":[-156.48588699999999,20.904639],"type":"Point"}
}