{
  "type": "Feature",
  "properties": {
    "iso:country":"US",
    "sg:address":"1050 Queen St",
    "sg:city":"Honolulu",
    "sg:classifiers":[
        {
            "category":"Organizations",
            "subcategory":"Labor Organization",
            "type":"Services"
        }
    ],
    "sg:phone":"+1 808 597 1315",
    "sg:postcode":"96814",
    "sg:province":"HI",
    "wof:name":"Professional Flight Attendants",
    "wof:placetype":"venue"
},
  "geometry": {"coordinates":[-157.85212300000001,21.295096],"type":"Point"}
}