{
  "type": "Feature",
  "properties": {
    "iso:country":"US",
    "sg:address":"45 Ala Hoku Pl",
    "sg:city":"Lahaina",
    "sg:classifiers":[
        {
            "category":"Building & Trades",
            "subcategory":"Construction",
            "type":"Services"
        }
    ],
    "sg:phone":"+1 808 669 6636",
    "sg:postcode":"96761",
    "sg:province":"HI",
    "sg:tags":[
        "maintenance",
        "contractor"
    ],
    "wof:name":"Kauvaka's Ground Maintenance",
    "wof:placetype":"venue"
},
  "geometry": {"coordinates":[-156.677086,20.969262],"type":"Point"}
}