{
  "type": "Feature",
  "properties": {
    "addr:full":"2983 Aukele St Lihue HI 96766",
    "addr:housenumber":"2983",
    "addr:postcode":"96766",
    "addr:street":"Aukele St",
    "iso:country":"US",
    "sg:address":"2983 Aukele St",
    "sg:city":"Lihue",
    "sg:classifiers":[
        {
            "category":"Retail",
            "subcategory":"Auto Rental",
            "type":"Services"
        }
    ],
    "sg:phone":"+1 808 246 6000",
    "sg:postcode":"96766",
    "sg:province":"HI",
    "sg:tags":[
        "automobile",
        "leasing"
    ],
    "wof:name":"Island Cars",
    "wof:placetype":"venue"
},
  "geometry": {"coordinates":[-159.356618,21.967887],"type":"Point"}
}