{
  "type": "Feature",
  "properties": {
    "iso:country":"US",
    "sg:address":"928 Fort Weaver Rd",
    "sg:city":"Ewa Beach",
    "sg:classifiers":[
        {
            "category":"Organizations",
            "subcategory":"Religious Organization",
            "type":"Services"
        }
    ],
    "sg:phone":"+1 808 689 6297",
    "sg:postcode":"96706",
    "sg:province":"HI",
    "sg:tags":[
        "church"
    ],
    "sg:website":"www.calvarychapel.org",
    "wof:name":"Calvary Chapel West Oahu",
    "wof:placetype":"venue"
},
  "geometry": {"coordinates":[-158.01356699999999,21.317802],"type":"Point"}
}