{
  "type": "Feature",
  "properties": {
    "iso:country":"US",
    "sg:address":"1170 Farrington Hwy",
    "sg:city":"Waianae",
    "sg:classifiers":[
        {
            "category":"Retail",
            "subcategory":"Self-service Laundry",
            "type":"Services"
        }
    ],
    "sg:phone":"+1 808 695 8307",
    "sg:postcode":"96792",
    "sg:province":"HI",
    "wof:name":"Wash Spot Makaha",
    "wof:placetype":"venue"
},
  "geometry": {"coordinates":[-158.207832,21.460819],"type":"Point"}
}