{
  "type": "Feature",
  "properties": {
    "iso:country":"US",
    "sg:address":"380 Hookahi St",
    "sg:city":"Wailuku",
    "sg:classifiers":[
        {
            "category":"Shopping",
            "type":"Retail Goods"
        }
    ],
    "sg:phone":"+1 808 242 4117",
    "sg:postcode":"96793",
    "sg:province":"HI",
    "sg:tags":[
        "equipment",
        "supply"
    ],
    "wof:name":"American Restaurant Supply",
    "wof:placetype":"venue"
},
  "geometry": {"coordinates":[-156.48868899999999,20.907988],"type":"Point"}
}