{
  "type": "Feature",
  "properties": {
    "iso:country":"US",
    "sg:address":"2441 Date St",
    "sg:city":"Honolulu",
    "sg:classifiers":[
        {
            "category":"Food & Beverages",
            "subcategory":"Groceries & Convenience Stores",
            "type":"Retail Goods"
        }
    ],
    "sg:phone":"+1 808 942 2234",
    "sg:postcode":"96826",
    "sg:province":"HI",
    "wof:name":"Date Street Grocery",
    "wof:placetype":"venue"
},
  "geometry": {"coordinates":[-157.82407000000001,21.287817],"type":"Point"}
}