{
  "type": "Feature",
  "properties": {
    "addr:full":"156 Mokauea St Honolulu HI 96819",
    "addr:housenumber":"156",
    "addr:postcode":"96819",
    "addr:street":"Mokauea St",
    "iso:country":"US",
    "sg:address":"156 Mokauea St",
    "sg:city":"Honolulu",
    "sg:classifiers":[
        {
            "category":"Building & Trades",
            "subcategory":"Construction",
            "type":"Services"
        },
        {
            "category":"Building & Trades",
            "subcategory":"Plumbing",
            "type":"Services"
        }
    ],
    "sg:phone":"+1 808 841 6041",
    "sg:postcode":"96819",
    "sg:province":"HI",
    "sg:tags":[
        "sheet",
        "work",
        "metal",
        "contractor"
    ],
    "wof:name":"T I Sheetmetal Shop",
    "wof:placetype":"venue"
},
  "geometry": {"coordinates":[-157.886932,21.322455],"type":"Point"}
}