{
  "type": "Feature",
  "properties": {
    "iso:country":"US",
    "sg:address":"5622 Alapa St",
    "sg:city":"Kailua Kona",
    "sg:classifiers":[
        {
            "category":"Retail",
            "subcategory":"Repair Shop",
            "type":"Services"
        }
    ],
    "sg:phone":"+1 808 329 1800",
    "sg:postcode":"96740",
    "sg:province":"HI",
    "sg:tags":[
        "lock",
        "locksmith"
    ],
    "wof:name":"Trouble Call",
    "wof:placetype":"venue"
},
  "geometry": {"coordinates":[-155.99945500000001,19.646091],"type":"Point"}
}