{
  "type": "Feature",
  "properties": {
    "iso:country":"US",
    "sg:address":"2881 S Kihei Rd",
    "sg:city":"Kihei",
    "sg:classifiers":[
        {
            "category":"Travel",
            "subcategory":"Hotels & Motels",
            "type":"Entertainment"
        }
    ],
    "sg:phone":"+1 808 879 6321",
    "sg:postcode":"96753",
    "sg:province":"HI",
    "sg:tags":[
        "operation",
        "real estate"
    ],
    "wof:name":"Maui Hill Resort",
    "wof:placetype":"venue"
},
  "geometry": {"coordinates":[-156.44764799999999,20.707953],"type":"Point"}
}