{
  "type": "Feature",
  "properties": {
    "addr:full":"1047 Kuhaulua St Waipahu HI 96797",
    "addr:housenumber":"1047",
    "addr:postcode":"96797",
    "addr:street":"Kuhaulua St",
    "iso:country":"US",
    "sg:address":"1047 Kuhaulua St",
    "sg:city":"Waipahu",
    "sg:classifiers":[
        {
            "category":"Social Services",
            "subcategory":"Adult Care",
            "type":"Services"
        }
    ],
    "sg:phone":"+1 808 671 9434",
    "sg:postcode":"96797",
    "sg:province":"HI",
    "sg:tags":[
        "residential"
    ],
    "wof:name":"Classic Res Care Hm",
    "wof:placetype":"venue"
},
  "geometry": {"coordinates":[-158.010019,21.39488],"type":"Point"}
}