{
  "type": "Feature",
  "properties": {
    "iso:country":"US",
    "sg:address":"233 Keawe St",
    "sg:city":"Honolulu",
    "sg:classifiers":[
        {
            "category":"Professional",
            "subcategory":"Research",
            "type":"Services"
        }
    ],
    "sg:phone":"+1 808 521 2437",
    "sg:postcode":"96813",
    "sg:province":"HI",
    "sg:tags":[
        "foundation",
        "philanthropic"
    ],
    "sg:website":"www.lifefoundation.org",
    "wof:name":"Life Foundation",
    "wof:placetype":"venue"
},
  "geometry": {"coordinates":[-157.86308099999999,21.297414],"type":"Point"}
}