{
  "type": "Feature",
  "properties": {
    "iso:country":"US",
    "sg:address":"941 Kau'olu Pl",
    "sg:city":"Waipahu",
    "sg:classifiers":[
        {
            "category":"Communications",
            "subcategory":"Film & Video Production",
            "type":"Services"
        }
    ],
    "sg:phone":"+1 808 677 4127",
    "sg:postcode":"96797",
    "sg:province":"HI",
    "wof:name":"Video Eye",
    "wof:placetype":"venue"
},
  "geometry": {"coordinates":[-158.00297499999999,21.387149],"type":"Point"}
}