{
  "type": "Feature",
  "properties": {
    "iso:country":"US",
    "sg:address":"3975 Kiani St",
    "sg:city":"Lawai",
    "sg:classifiers":[
        {
            "category":"Building & Trades",
            "subcategory":"Construction",
            "type":"Services"
        }
    ],
    "sg:phone":"+1 808 332 8320",
    "sg:postcode":"96756",
    "sg:province":"HI",
    "sg:tags":[
        "contractor"
    ],
    "wof:name":"Wesley Yorkman General Contr",
    "wof:placetype":"venue"
},
  "geometry": {"coordinates":[-159.50061600000001,21.914287],"type":"Point"}
}