{
  "type": "Feature",
  "properties": {
    "addr:full":"121 Dickenson St Lahaina HI 96761",
    "addr:housenumber":"121",
    "addr:postcode":"96761",
    "addr:street":"Dickenson St",
    "iso:country":"US",
    "sg:address":"121 Dickenson St",
    "sg:city":"Lahaina",
    "sg:classifiers":[
        {
            "category":"Food & Beverages",
            "subcategory":"Fruits & Vegetables",
            "type":"Retail Goods"
        }
    ],
    "sg:phone":"+1 808 667 7056",
    "sg:postcode":"96761",
    "sg:province":"HI",
    "sg:tags":[
        "fresh"
    ],
    "sg:website":"www.takehomemaui.com",
    "wof:name":"Take Home Maui Inc",
    "wof:placetype":"venue"
},
  "geometry": {"coordinates":[-156.680701,20.876746],"type":"Point"}
}