{
  "type": "Feature",
  "properties": {
    "addr:full":"1068 Limahana Pl Lahaina HI 96761",
    "addr:housenumber":"1068",
    "addr:postcode":"96761",
    "addr:street":"Limahana Pl",
    "iso:country":"US",
    "sg:address":"1068 Limahana Pl",
    "sg:city":"Lahaina",
    "sg:classifiers":[
        {
            "category":"Manufacturing",
            "subcategory":"Signs",
            "type":"Manufacturing & Wholesale Goods"
        }
    ],
    "sg:phone":"+1 808 661 0900",
    "sg:postcode":"96761",
    "sg:province":"HI",
    "sg:tags":[
        "specialty",
        "mfg"
    ],
    "wof:name":"Signs In A Day",
    "wof:placetype":"venue"
},
  "geometry": {"coordinates":[-156.682963,20.884691],"type":"Point"}
}