{
  "type": "Feature",
  "properties": {
    "iso:country":"US",
    "sg:address":"922 Makaala Dr",
    "sg:city":"Wailuku",
    "sg:classifiers":[
        {
            "category":"Personal",
            "type":"Services"
        }
    ],
    "sg:phone":"+1 808 244 5811",
    "sg:postcode":"96793",
    "sg:province":"HI",
    "wof:name":"Special Svcs & Accommodation",
    "wof:placetype":"venue"
},
  "geometry": {"coordinates":[-156.500227,20.910408],"type":"Point"}
}