{
  "type": "Feature",
  "properties": {
    "iso:country":"US",
    "sg:address":"2406 Apoepoe St",
    "sg:city":"Pearl City",
    "sg:classifiers":[
        {
            "category":"Retail",
            "subcategory":"Auto Repair",
            "type":"Services"
        }
    ],
    "sg:phone":"+1 808 456 7517",
    "sg:postcode":"96782",
    "sg:province":"HI",
    "sg:tags":[
        "general"
    ],
    "wof:name":"Otto Vw Haus",
    "wof:placetype":"venue"
},
  "geometry": {"coordinates":[-157.948958,21.430506],"type":"Point"}
}