{
  "type": "Feature",
  "properties": {
    "addr:full":"7062 Kuakini Hwy Keauhou HI 96740",
    "addr:housenumber":"7062",
    "addr:postcode":"96740",
    "addr:street":"Kuakini Hwy",
    "iso:country":"US",
    "sg:address":"7062 Kuakini Hwy",
    "sg:city":"Keauhou",
    "sg:classifiers":[
        {
            "category":"Retail",
            "subcategory":"Veterinary Services",
            "type":"Services"
        }
    ],
    "sg:phone":"+1 808 322 3469",
    "sg:postcode":"96740",
    "sg:province":"HI",
    "sg:tags":[
        "hospital",
        "animal"
    ],
    "wof:name":"Kona Coast Veterinary Hospital",
    "wof:placetype":"venue"
},
  "geometry": {"coordinates":[-155.94354999999999,19.56945],"type":"Point"}
}