{
  "type": "Feature",
  "properties": {
    "iso:country":"US",
    "sg:address":"850 Kamehameha Hwy",
    "sg:city":"Pearl City",
    "sg:classifiers":[
        {
            "category":"Food & Beverages",
            "subcategory":"Candy",
            "type":"Retail Goods"
        }
    ],
    "sg:phone":"+1 808 455 6601",
    "sg:postcode":"96782",
    "sg:province":"HI",
    "sg:tags":[
        "confectionery"
    ],
    "wof:name":"Sweetland",
    "wof:placetype":"venue"
},
  "geometry": {"coordinates":[-157.97010800000001,21.393903],"type":"Point"}
}