{
  "type": "Feature",
  "properties": {
    "iso:country":"US",
    "sg:address":"15 Kuahelani Ave",
    "sg:city":"Mililani",
    "sg:classifiers":[
        {
            "category":"Real Estate",
            "subcategory":"Real Estate Operator",
            "type":"Services"
        }
    ],
    "sg:phone":"+1 808 623 1627",
    "sg:postcode":"96789",
    "sg:province":"HI",
    "sg:tags":[
        "condominium"
    ],
    "wof:name":"Nahoa Condominium",
    "wof:placetype":"venue"
},
  "geometry": {"coordinates":[-158.01893100000001,21.446749],"type":"Point"}
}