{
  "type": "Feature",
  "properties": {
    "iso:country":"US",
    "sg:address":"1325 Kalihi St",
    "sg:city":"Honolulu",
    "sg:classifiers":[
        {
            "category":"Education",
            "subcategory":"Library",
            "type":"Public Place"
        }
    ],
    "sg:phone":"+1 808 832 3466",
    "sg:postcode":"96819",
    "sg:province":"HI",
    "wof:name":"Kalihi Palama Public Library",
    "wof:placetype":"venue"
},
  "geometry": {"coordinates":[-157.87191100000001,21.334051],"type":"Point"}
}