{
  "type": "Feature",
  "properties": {
    "addr:full":"1972 Kalakaua Ave Honolulu HI 96815",
    "addr:housenumber":"1972",
    "addr:postcode":"96815",
    "addr:street":"Kalakaua Ave",
    "iso:country":"US",
    "sg:address":"1972 Kalakaua Ave",
    "sg:city":"Honolulu",
    "sg:classifiers":[
        {
            "category":"Restaurant",
            "type":"Food & Drink"
        }
    ],
    "sg:phone":"+1 808 942 2121",
    "sg:postcode":"96815",
    "sg:province":"HI",
    "sg:tags":[
        "drinking",
        "eating"
    ],
    "sg:website":"www.tonyromas.com",
    "wof:name":"Tony Roma's",
    "wof:placetype":"venue"
},
  "geometry": {"coordinates":[-157.83239,21.284878],"type":"Point"}
}