{
  "type": "Feature",
  "properties": {
    "iso:country":"US",
    "sg:address":"1435 Auld Ln",
    "sg:city":"Honolulu",
    "sg:classifiers":[
        {
            "category":"Shopping",
            "subcategory":"Clothing, Apparel, & Fashions",
            "type":"Retail Goods"
        }
    ],
    "sg:phone":"+1 808 847 8759",
    "sg:postcode":"96817",
    "sg:province":"HI",
    "wof:name":"Lucky 8 Garment LLC",
    "wof:placetype":"venue"
},
  "geometry": {"coordinates":[-157.86631499999999,21.32599],"type":"Point"}
}