{
  "type": "Feature",
  "properties": {
    "iso:country":"US",
    "sg:address":"3750 Wailea Alanui Dr",
    "sg:city":"Kihei",
    "sg:classifiers":[
        {
            "category":"Restaurant",
            "type":"Food & Drink"
        }
    ],
    "sg:menulink":"http://www.allmenus.com/hi/kula/14374-ruths-chris-steak-house/menu/",
    "sg:phone":"+1 808 874 8880",
    "sg:postcode":"96753",
    "sg:province":"HI",
    "sg:tags":[
        "american",
        "steakhouse"
    ],
    "wof:name":"Ruth's Chris Steak House",
    "wof:placetype":"venue"
},
  "geometry": {"coordinates":[-156.44119900000001,20.691567],"type":"Point"}
}