{
  "type": "Feature",
  "properties": {
    "iso:country":"US",
    "sg:address":"49 Oneawa St",
    "sg:city":"Kailua",
    "sg:classifiers":[
        {
            "category":"Food & Beverages",
            "subcategory":"Liquor & Beverages",
            "type":"Retail Goods"
        }
    ],
    "sg:phone":"+1 808 261 2741",
    "sg:postcode":"96734",
    "sg:province":"HI",
    "sg:tags":[
        "alcoholic"
    ],
    "wof:name":"Oneawa Market",
    "wof:placetype":"venue"
},
  "geometry": {"coordinates":[-157.74418800000001,21.395215],"type":"Point"}
}