{
  "type": "Feature",
  "properties": {
    "addr:full":"1023 Pensacola St Honolulu HI 96814",
    "addr:housenumber":"1023",
    "addr:postcode":"96814",
    "addr:street":"Pensacola St",
    "iso:country":"US",
    "sg:address":"1023 Pensacola St",
    "sg:city":"Honolulu",
    "sg:classifiers":[
        {
            "category":"Real Estate",
            "subcategory":"Real Estate Agent",
            "type":"Services"
        }
    ],
    "sg:phone":"+1 808 596 8161",
    "sg:postcode":"96814",
    "sg:province":"HI",
    "wof:name":"Young's Ventures Inc",
    "wof:placetype":"venue"
},
  "geometry": {"coordinates":[-157.84542200000001,21.301113],"type":"Point"}
}