{
  "type": "Feature",
  "properties": {
    "iso:country":"US",
    "sg:address":"118 Kupuohi St",
    "sg:city":"Lahaina",
    "sg:classifiers":[
        {
            "category":"Building & Trades",
            "subcategory":"Electrical",
            "type":"Services"
        }
    ],
    "sg:phone":"+1 808 667 5054",
    "sg:postcode":"96761",
    "sg:province":"HI",
    "sg:tags":[
        "general",
        "electrical",
        "electric",
        "contractor"
    ],
    "wof:name":"Northwest Electric Inc",
    "wof:placetype":"venue"
},
  "geometry": {"coordinates":[-156.683233,20.886604],"type":"Point"}
}