{
  "type": "Feature",
  "properties": {
    "iso:country":"US",
    "sg:address":"150 Hoohana St",
    "sg:city":"Kamuela",
    "sg:classifiers":[
        {
            "category":"Real Estate",
            "subcategory":"Developer",
            "type":"Services"
        }
    ],
    "sg:phone":"+1 808 881 9500",
    "sg:postcode":"96743",
    "sg:province":"HI",
    "sg:website":"www.pauoabeach.com",
    "wof:name":"White Sand Beach",
    "wof:placetype":"venue"
},
  "geometry": {"coordinates":[-155.85270399999999,19.943364],"type":"Point"}
}