{
  "type": "Feature",
  "properties": {
    "addr:full":"2988 Ualena St Honolulu HI 96819",
    "addr:housenumber":"2988",
    "addr:postcode":"96819",
    "addr:street":"Ualena St",
    "iso:country":"US",
    "sg:address":"2988 Ualena St",
    "sg:city":"Honolulu",
    "sg:classifiers":[
        {
            "category":"Freight",
            "type":"Transportation"
        }
    ],
    "sg:phone":"+1 808 833 0988",
    "sg:postcode":"96819",
    "sg:province":"HI",
    "sg:tags":[
        "warehouse"
    ],
    "wof:name":"All American Taxi Truck",
    "wof:placetype":"venue"
},
  "geometry": {"coordinates":[-157.90211099999999,21.332956],"type":"Point"}
}