{
  "type": "Feature",
  "properties": {
    "iso:country":"US",
    "sg:address":"177 Kaukamana St",
    "sg:city":"Waianae",
    "sg:classifiers":[
        {
            "category":"Freight",
            "type":"Transportation"
        }
    ],
    "sg:phone":"+1 808 696 1605",
    "sg:postcode":"96792",
    "sg:province":"HI",
    "sg:tags":[
        "distance",
        "long",
        "trucking"
    ],
    "wof:name":"Sean Demello",
    "wof:placetype":"venue"
},
  "geometry": {"coordinates":[-158.17819,21.423952],"type":"Point"}
}