{
  "type": "Feature",
  "properties": {
    "iso:country":"US",
    "sg:address":"1124 Fort Street Ml",
    "sg:city":"Honolulu",
    "sg:classifiers":[
        {
            "category":"Professional",
            "subcategory":"Engineering",
            "type":"Services"
        }
    ],
    "sg:phone":"+1 808 792 2022",
    "sg:postcode":"96813",
    "sg:province":"HI",
    "sg:tags":[
        "design"
    ],
    "wof:name":"Bills Engineering Inc",
    "wof:placetype":"venue"
},
  "geometry": {"coordinates":[-157.861017,21.310059],"type":"Point"}
}