{
  "type": "Feature",
  "properties": {
    "addr:full":"1833 Kalakaua Ave Honolulu HI 96815",
    "addr:housenumber":"1833",
    "addr:postcode":"96815",
    "addr:street":"Kalakaua Ave",
    "iso:country":"US",
    "sg:address":"1833 Kalakaua Ave",
    "sg:city":"Honolulu",
    "sg:classifiers":[
        {
            "category":"Real Estate",
            "subcategory":"Real Estate Agent",
            "type":"Services"
        }
    ],
    "sg:phone":"+1 808 923 7666",
    "sg:postcode":"96815",
    "sg:province":"HI",
    "wof:name":"Earl Thacker LTD",
    "wof:placetype":"venue"
},
  "geometry": {"coordinates":[-157.834372,21.288059],"type":"Point"}
}