{
  "type": "Feature",
  "properties": {
    "iso:country":"US",
    "sg:address":"1040 Lunalilo St",
    "sg:city":"Honolulu",
    "sg:classifiers":[
        {
            "category":"Real Estate",
            "subcategory":"Real Estate Agent",
            "type":"Services"
        },
        {
            "category":"Real Estate",
            "subcategory":"Real Estate Operator",
            "type":"Services"
        }
    ],
    "sg:phone":"+1 808 536 8412",
    "sg:postcode":"96822",
    "sg:province":"HI",
    "sg:tags":[
        "condominium"
    ],
    "wof:name":"Continental Plaza",
    "wof:placetype":"venue"
},
  "geometry": {"coordinates":[-157.846858,21.30538],"type":"Point"}
}