{
  "type": "Feature",
  "properties": {
    "iso:country":"US",
    "sg:address":"119 Laimi Rd",
    "sg:city":"Honolulu",
    "sg:classifiers":[
        {
            "category":"Travel",
            "subcategory":"Travel Agent",
            "type":"Entertainment"
        }
    ],
    "sg:phone":"+1 808 595 6651",
    "sg:postcode":"96817",
    "sg:province":"HI",
    "sg:tags":[
        "operator",
        "tour"
    ],
    "wof:name":"Aloha Aina Eco Tours",
    "wof:placetype":"venue"
},
  "geometry": {"coordinates":[-157.83877899999999,21.332003],"type":"Point"}
}