{
  "type": "Feature",
  "properties": {
    "addr:full":"1168 Lunalilo Home Rd Honolulu HI 96825",
    "addr:housenumber":"1168",
    "addr:postcode":"96825",
    "addr:street":"Lunalilo Home Rd",
    "iso:country":"US",
    "sg:address":"1168 Lunalilo Home Rd",
    "sg:city":"Honolulu",
    "sg:classifiers":[
        {
            "category":"Professional",
            "subcategory":"Lawyer & Legal Services",
            "type":"Services"
        }
    ],
    "sg:phone":"+1 808 396 9252",
    "sg:postcode":"96825",
    "sg:province":"HI",
    "sg:tags":[
        "attorney"
    ],
    "wof:name":"Wesley H Ikeda",
    "wof:placetype":"venue"
},
  "geometry": {"coordinates":[-157.683864,21.307624],"type":"Point"}
}