{
  "type": "Feature",
  "properties": {
    "iso:country":"US",
    "sg:address":"582 N King St",
    "sg:city":"Honolulu",
    "sg:classifiers":[
        {
            "category":"Food & Beverages",
            "subcategory":"Groceries & Convenience Stores",
            "type":"Retail Goods"
        }
    ],
    "sg:phone":"+1 808 845 7283",
    "sg:postcode":"96817",
    "sg:province":"HI",
    "wof:name":"Fugi Market",
    "wof:placetype":"venue"
},
  "geometry": {"coordinates":[-157.86585099999999,21.320098],"type":"Point"}
}