{
  "type": "Feature",
  "properties": {
    "iso:country":"US",
    "sg:address":"24 Kamehameha Hwy",
    "sg:city":"Kaneohe",
    "sg:classifiers":[
        {
            "category":"Insurance",
            "subcategory":"Insurance Agent",
            "type":"Services"
        }
    ],
    "sg:phone":"+1 808 247 5250",
    "sg:postcode":"96744",
    "sg:province":"HI",
    "wof:name":"State Farm Insurance",
    "wof:placetype":"venue"
},
  "geometry": {"coordinates":[-157.78242700000001,21.376371],"type":"Point"}
}