{
  "type": "Feature",
  "properties": {
    "iso:country":"US",
    "sg:address":"145 N Kihei Rd",
    "sg:city":"Kihei",
    "sg:classifiers":[
        {
            "category":"Recreation",
            "type":"Entertainment"
        }
    ],
    "sg:phone":"+1 808 875 0596",
    "sg:postcode":"96753",
    "sg:province":"HI",
    "sg:tags":[
        "snorkeling"
    ],
    "wof:name":"Snorkel World",
    "wof:placetype":"venue"
},
  "geometry": {"coordinates":[-156.47828000000001,20.791889],"type":"Point"}
}