{
  "type": "Feature",
  "properties": {
    "addr:full":"1639 Papau St Kapaa HI 96746",
    "addr:housenumber":"1639",
    "addr:postcode":"96746",
    "addr:street":"Papau St",
    "iso:country":"US",
    "sg:address":"1639 Papau St",
    "sg:city":"Kapaa",
    "sg:classifiers":[
        {
            "category":"Building & Trades",
            "subcategory":"Electrical",
            "type":"Services"
        }
    ],
    "sg:phone":"+1 808 821 1548",
    "sg:postcode":"96746",
    "sg:province":"HI",
    "sg:tags":[
        "electrical",
        "electric",
        "contractor"
    ],
    "wof:name":"Balilea Electric",
    "wof:placetype":"venue"
},
  "geometry": {"coordinates":[-159.332178,22.095426],"type":"Point"}
}