{
  "type": "Feature",
  "properties": {
    "addr:full":"1499 W Kuiaha Rd Haiku HI 96708",
    "addr:housenumber":"1499",
    "addr:postcode":"96708",
    "addr:street":"W Kuiaha Rd",
    "iso:country":"US",
    "sg:address":"1499 W Kuiaha Rd",
    "sg:city":"Haiku",
    "sg:classifiers":[
        {
            "category":"Shopping",
            "type":"Retail Goods"
        }
    ],
    "sg:phone":"+1 808 575 2930",
    "sg:postcode":"96708",
    "sg:province":"HI",
    "sg:tags":[
        "merchandise"
    ],
    "wof:name":"Small Farm Equipment Inc",
    "wof:placetype":"venue"
},
  "geometry": {"coordinates":[-156.29969500000001,20.889618],"type":"Point"}
}