{
  "type": "Feature",
  "properties": {
    "addr:full":"316 Kamehameha Hwy Hauula HI 96717",
    "addr:housenumber":"316",
    "addr:postcode":"96717",
    "addr:street":"Kamehameha Hwy",
    "iso:country":"US",
    "sg:address":"316 Kamehameha Hwy",
    "sg:city":"Hauula",
    "sg:classifiers":[
        {
            "category":"Professional",
            "subcategory":"Engineering",
            "type":"Services"
        }
    ],
    "sg:phone":"+1 808 232 0464",
    "sg:postcode":"96717",
    "sg:province":"HI",
    "sg:tags":[
        "general",
        "contractor"
    ],
    "wof:name":"O-Vest Corp",
    "wof:placetype":"venue"
},
  "geometry": {"coordinates":[-157.91508200000001,21.619507],"type":"Point"}
}