{
  "type": "Feature",
  "properties": {
    "iso:country":"US",
    "sg:address":"658 Front St",
    "sg:city":"Lahaina",
    "sg:classifiers":[
        {
            "category":"Shopping",
            "subcategory":"Gifts & Souvenirs",
            "type":"Retail Goods"
        }
    ],
    "sg:phone":"+1 808 667 2840",
    "sg:postcode":"96761",
    "sg:province":"HI",
    "sg:tags":[
        "shop"
    ],
    "wof:name":"Tropical Gifts",
    "wof:placetype":"venue"
},
  "geometry": {"coordinates":[-156.68003899999999,20.875251],"type":"Point"}
}