{
  "type": "Feature",
  "properties": {
    "iso:country":"US",
    "sg:address":"336 Kikoo Pl",
    "sg:city":"Honolulu",
    "sg:classifiers":[
        {
            "category":"Wholesale",
            "subcategory":"Poultry",
            "type":"Manufacturing & Wholesale Goods"
        }
    ],
    "sg:phone":"+1 808 395 4607",
    "sg:postcode":"96825",
    "sg:province":"HI",
    "sg:tags":[
        "fresh",
        "seafood",
        "meat"
    ],
    "wof:name":"Midera Foods Inc",
    "wof:placetype":"venue"
},
  "geometry": {"coordinates":[-157.702315,21.280845],"type":"Point"}
}