{
  "type": "Feature",
  "properties": {
    "addr:full":"360 Peke Ln Waipahu HI 96797",
    "addr:housenumber":"360",
    "addr:postcode":"96797",
    "addr:street":"Peke Ln",
    "iso:country":"US",
    "sg:address":"360 Peke Ln",
    "sg:city":"Waipahu",
    "sg:classifiers":[
        {
            "category":"Wholesale",
            "subcategory":"Plants",
            "type":"Manufacturing & Wholesale Goods"
        }
    ],
    "sg:phone":"+1 808 671 0512",
    "sg:postcode":"96797",
    "sg:province":"HI",
    "sg:tags":[
        "florist"
    ],
    "wof:name":"Tgis Flowers",
    "wof:placetype":"venue"
},
  "geometry": {"coordinates":[-158.000214,21.392341],"type":"Point"}
}