{
  "type": "Feature",
  "properties": {
    "addr:full":"1200 Ala Moana Blvd Honolulu HI 96814",
    "addr:housenumber":"1200",
    "addr:postcode":"96814",
    "addr:street":"Ala Moana Blvd",
    "iso:country":"US",
    "sg:address":"1200 Ala Moana Blvd",
    "sg:city":"Honolulu",
    "sg:classifiers":[
        {
            "category":"Education",
            "subcategory":"Special Training",
            "type":"Public Place"
        },
        {
            "category":"Manufacturing",
            "subcategory":"Printing",
            "type":"Manufacturing & Wholesale Goods"
        }
    ],
    "sg:phone":"+1 808 593 4442",
    "sg:postcode":"96814",
    "sg:province":"HI",
    "sg:tags":[
        "management",
        "seminar",
        "time"
    ],
    "sg:website":"www.franklincovey.com",
    "wof:name":"Franklin Covey Co",
    "wof:placetype":"venue"
},
  "geometry": {"coordinates":[-157.848668,21.291408],"type":"Point"}
}