{
  "type": "Feature",
  "properties": {
    "iso:country":"US",
    "sg:address":"159 Namoku St",
    "sg:city":"Kaneohe",
    "sg:classifiers":[
        {
            "category":"Building & Trades",
            "subcategory":"Pest Control",
            "type":"Services"
        }
    ],
    "sg:phone":"+1 808 235 0916",
    "sg:postcode":"96744",
    "sg:province":"HI",
    "wof:name":"Breezes",
    "wof:placetype":"venue"
},
  "geometry": {"coordinates":[-157.785785,21.398022],"type":"Point"}
}