{
  "type": "Feature",
  "properties": {
    "iso:country":"US",
    "sg:address":"3121 Arizona Rd",
    "sg:city":"Honolulu",
    "sg:classifiers":[
        {
            "category":"Organizations",
            "subcategory":"Religious Organization",
            "type":"Services"
        }
    ],
    "sg:phone":"+1 808 423 9020",
    "sg:postcode":"96818",
    "sg:province":"HI",
    "wof:name":"Hawai-Philippine Baptst Church",
    "wof:placetype":"venue"
},
  "geometry": {"coordinates":[-157.908714,21.341783],"type":"Point"}
}