{
  "type": "Feature",
  "properties": {
    "iso:country":"US",
    "sg:address":"46 Merchant St",
    "sg:city":"Honolulu",
    "sg:classifiers":[
        {
            "category":"Arts & Performance",
            "subcategory":"Theater",
            "type":"Entertainment"
        }
    ],
    "sg:phone":"+1 808 536 4441",
    "sg:postcode":"96813",
    "sg:province":"HI",
    "sg:tags":[
        "theatrical"
    ],
    "wof:name":"KUMU Kahua Theatre",
    "wof:placetype":"venue"
},
  "geometry": {"coordinates":[-157.86282299999999,21.30894],"type":"Point"}
}