{
  "type": "Feature",
  "properties": {
    "iso:country":"US",
    "sg:address":"960 Prospect St",
    "sg:city":"Honolulu",
    "sg:classifiers":[
        {
            "category":"Education",
            "subcategory":"College",
            "type":"Public Place"
        }
    ],
    "sg:phone":"+1 808 956 5728",
    "sg:postcode":"96822",
    "sg:province":"HI",
    "wof:name":"Tammy L Vandevender",
    "wof:placetype":"venue"
},
  "geometry": {"coordinates":[-157.84521799999999,21.309186],"type":"Point"}
}