{
  "type": "Feature",
  "properties": {
    "addr:full":"5315 Mamalahoa Hwy Honaunau HI 96704",
    "addr:housenumber":"5315",
    "addr:postcode":"96704",
    "addr:street":"Mamalahoa Hwy",
    "iso:country":"US",
    "sg:address":"5315 Mamalahoa Hwy",
    "sg:city":"Honaunau",
    "sg:classifiers":[
        {
            "category":"Food & Beverages",
            "subcategory":"Specialty",
            "type":"Retail Goods"
        }
    ],
    "sg:phone":"+1 808 328 0322",
    "sg:postcode":"96704",
    "sg:province":"HI",
    "sg:tags":[
        "tea",
        "coffee"
    ],
    "wof:name":"Coffees 'n Epicurea",
    "wof:placetype":"venue"
},
  "geometry": {"coordinates":[-155.87984499999999,19.447488],"type":"Point"}
}