{
  "type": "Feature",
  "properties": {
    "iso:country":"US",
    "sg:address":"2211 Ala Wai Blvd",
    "sg:city":"Honolulu",
    "sg:classifiers":[
        {
            "category":"Home & Garden",
            "subcategory":"Building Materials",
            "type":"Retail Goods"
        }
    ],
    "sg:phone":"+1 808 926 8984",
    "sg:postcode":"96815",
    "sg:province":"HI",
    "sg:tags":[
        "roofing"
    ],
    "wof:name":"B T Reid & Assoc",
    "wof:placetype":"venue"
},
  "geometry": {"coordinates":[-157.82592700000001,21.281684],"type":"Point"}
}