{
  "type": "Feature",
  "properties": {
    "addr:full":"1425 Liliha St Honolulu HI 96817",
    "addr:housenumber":"1425",
    "addr:postcode":"96817",
    "addr:street":"Liliha St",
    "iso:country":"US",
    "sg:address":"1425 Liliha St",
    "sg:city":"Honolulu",
    "sg:classifiers":[
        {
            "category":"Banks & Credit Unions",
            "subcategory":"Bank",
            "type":"Services"
        }
    ],
    "sg:phone":"+1 808 526 0002",
    "sg:postcode":"96817",
    "sg:province":"HI",
    "wof:name":"American Savings Bank",
    "wof:placetype":"venue"
},
  "geometry": {"coordinates":[-157.861593,21.320236],"type":"Point"}
}