{
  "type": "Feature",
  "properties": {
    "iso:country":"US",
    "sg:address":"201 Merchant St",
    "sg:city":"Honolulu",
    "sg:classifiers":[
        {
            "category":"Professional",
            "subcategory":"Business Services",
            "type":"Services"
        }
    ],
    "sg:phone":"+1 808 521 6783",
    "sg:postcode":"96813",
    "sg:province":"HI",
    "sg:tags":[
        "recording",
        "studio"
    ],
    "wof:name":"Image Illuminations Intl",
    "wof:placetype":"venue"
},
  "geometry": {"coordinates":[-157.86066299999999,21.306805],"type":"Point"}
}