{
  "type": "Feature",
  "properties": {
    "addr:full":"901 Aalapapa Dr Kailua HI 96734",
    "addr:housenumber":"901",
    "addr:postcode":"96734",
    "addr:street":"Aalapapa Dr",
    "iso:country":"US",
    "sg:address":"901 Aalapapa Dr",
    "sg:city":"Kailua",
    "sg:classifiers":[
        {
            "category":"Building & Trades",
            "subcategory":"Construction",
            "type":"Services"
        }
    ],
    "sg:phone":"+1 808 262 2767",
    "sg:postcode":"96734",
    "sg:province":"HI",
    "sg:tags":[
        "contractor"
    ],
    "wof:name":"Intraspect Construction Svc",
    "wof:placetype":"venue"
},
  "geometry": {"coordinates":[-157.717726,21.391106],"type":"Point"}
}