{
  "type": "Feature",
  "properties": {
    "addr:full":"342 Ponohana Pl Aiea HI 96701",
    "addr:housenumber":"342",
    "addr:postcode":"96701",
    "addr:street":"Ponohana Pl",
    "iso:country":"US",
    "sg:address":"342 Ponohana Pl",
    "sg:city":"Aiea",
    "sg:classifiers":[
        {
            "category":"Building & Trades",
            "subcategory":"Construction",
            "type":"Services"
        }
    ],
    "sg:phone":"+1 808 484 5095",
    "sg:postcode":"96701",
    "sg:province":"HI",
    "sg:tags":[
        "nonresidential"
    ],
    "wof:name":"Keiwit Pacific Job 5843",
    "wof:placetype":"venue"
},
  "geometry": {"coordinates":[-157.94572400000001,21.390663],"type":"Point"}
}