{
  "type": "Feature",
  "properties": {
    "addr:full":"422 Papolohiwa St Mililani HI 96789",
    "addr:housenumber":"422",
    "addr:postcode":"96789",
    "addr:street":"Papolohiwa St",
    "iso:country":"US",
    "sg:address":"422 Papolohiwa St",
    "sg:city":"Mililani",
    "sg:classifiers":[
        {
            "category":"Retail",
            "subcategory":"Repair Shop",
            "type":"Services"
        }
    ],
    "sg:phone":"+1 808 623 3694",
    "sg:postcode":"96789",
    "sg:province":"HI",
    "sg:tags":[
        "appliance"
    ],
    "wof:name":"S & R Refrigeration",
    "wof:placetype":"venue"
},
  "geometry": {"coordinates":[-158.015422,21.432332],"type":"Point"}
}