{
  "type": "Feature",
  "properties": {
    "addr:full":"1772 Bettencourt Ln Kapaa HI 96746",
    "addr:housenumber":"1772",
    "addr:postcode":"96746",
    "addr:street":"Bettencourt Ln",
    "iso:country":"US",
    "sg:address":"1772 Bettencourt Ln",
    "sg:city":"Kapaa",
    "sg:classifiers":[
        {
            "category":"Recreation",
            "type":"Entertainment"
        }
    ],
    "sg:phone":"+1 808 822 5849",
    "sg:postcode":"96746",
    "sg:province":"HI",
    "wof:name":"Vic 4 Inc",
    "wof:placetype":"venue"
},
  "geometry": {"coordinates":[-159.35687300000001,22.097754],"type":"Point"}
}