{
  "type": "Feature",
  "properties": {
    "iso:country":"US",
    "sg:address":"626 Coral St",
    "sg:city":"Honolulu",
    "sg:classifiers":[
        {
            "category":"Professional",
            "type":"Services"
        }
    ],
    "sg:phone":"+1 808 523 1533",
    "sg:postcode":"96813",
    "sg:province":"HI",
    "sg:tags":[
        "establishment"
    ],
    "wof:name":"Kang's Market",
    "wof:placetype":"venue"
},
  "geometry": {"coordinates":[-157.85751999999999,21.300975],"type":"Point"}
}