{
  "type": "Feature",
  "properties": {
    "addr:full":"7409 Ainanani Pl Honolulu HI 96825",
    "addr:housenumber":"7409",
    "addr:postcode":"96825",
    "addr:street":"Ainanani Pl",
    "iso:country":"US",
    "sg:address":"7409 Ainanani Pl",
    "sg:city":"Honolulu",
    "sg:classifiers":[
        {
            "category":"Education",
            "subcategory":"Special Training",
            "type":"Public Place"
        }
    ],
    "sg:phone":"+1 808 395 8236",
    "sg:postcode":"96825",
    "sg:province":"HI",
    "wof:name":"Ishida-Ho Associates",
    "wof:placetype":"venue"
},
  "geometry": {"coordinates":[-157.67985100000001,21.295719],"type":"Point"}
}