{
  "type": "Feature",
  "properties": {
    "iso:country":"US",
    "sg:address":"127 Lahainaluna Rd",
    "sg:city":"Lahaina",
    "sg:classifiers":[
        {
            "category":"Restaurant",
            "type":"Food & Drink"
        }
    ],
    "sg:menulink":"http://www.allmenus.com/hi/lahaina/3312-david-pauls-lahaina-grill/menu/",
    "sg:phone":"+1 800 360 2606",
    "sg:postcode":"96761",
    "sg:province":"HI",
    "sg:tags":[
        "american",
        "hawaiian"
    ],
    "wof:name":"David Paul's Lahaina Grill",
    "wof:placetype":"venue"
},
  "geometry": {"coordinates":[-156.67946800000001,20.87546],"type":"Point"}
}