{
  "type": "Feature",
  "properties": {
    "addr:full":"1501 Geiger Rd Ewa Beach HI 96706",
    "addr:housenumber":"1501",
    "addr:postcode":"96706",
    "addr:street":"Geiger Rd",
    "iso:country":"US",
    "sg:address":"1501 Geiger Rd",
    "sg:city":"Ewa Beach",
    "sg:classifiers":[
        {
            "category":"Government",
            "subcategory":"Office",
            "type":"Public Place"
        }
    ],
    "sg:phone":"+1 808 681 3138",
    "sg:postcode":"96706",
    "sg:province":"HI",
    "sg:tags":[
        "village"
    ],
    "wof:name":"Honolulu City Honouliuli",
    "wof:placetype":"venue"
},
  "geometry": {"coordinates":[-158.03420299999999,21.32951],"type":"Point"}
}