{
  "type": "Feature",
  "properties": {
    "iso:country":"US",
    "sg:address":"3343 Kuhio Hwy",
    "sg:city":"Lihue",
    "sg:classifiers":[
        {
            "category":"Wholesale",
            "subcategory":"Seafood",
            "type":"Manufacturing & Wholesale Goods"
        }
    ],
    "sg:phone":"+1 808 245 9918",
    "sg:postcode":"96766",
    "sg:province":"HI",
    "sg:tags":[
        "fish"
    ],
    "wof:name":"Fish Express Ltd",
    "wof:placetype":"venue"
},
  "geometry": {"coordinates":[-159.36674099999999,21.984723],"type":"Point"}
}