{
  "type": "Feature",
  "properties": {
    "iso:country":"US",
    "sg:address":"711 Kapiolani Blvd",
    "sg:city":"Honolulu",
    "sg:classifiers":[
        {
            "category":"Insurance",
            "subcategory":"Life Insurance",
            "type":"Services"
        }
    ],
    "sg:phone":"+1 808 589 2834",
    "sg:postcode":"96813",
    "sg:province":"HI",
    "sg:tags":[
        "planner",
        "estate"
    ],
    "wof:name":"Estate Planners of America",
    "wof:placetype":"venue"
},
  "geometry": {"coordinates":[-157.85479100000001,21.301965],"type":"Point"}
}