{
  "type": "Feature",
  "properties": {
    "addr:full":"909 Kapahulu Ave Honolulu HI 96816",
    "addr:housenumber":"909",
    "addr:postcode":"96816",
    "addr:street":"Kapahulu Ave",
    "iso:country":"US",
    "sg:address":"909 Kapahulu Ave",
    "sg:city":"Honolulu",
    "sg:classifiers":[
        {
            "category":"Arts & Performance",
            "subcategory":"Theater",
            "type":"Entertainment"
        }
    ],
    "sg:phone":"+1 808 734 7771",
    "sg:postcode":"96816",
    "sg:province":"HI",
    "sg:tags":[
        "karaoke"
    ],
    "wof:name":"Karaoke Hut & Lounge",
    "wof:placetype":"venue"
},
  "geometry": {"coordinates":[-157.81353300000001,21.284637],"type":"Point"}
}