{
  "type": "Feature",
  "properties": {
    "iso:country":"US",
    "sg:address":"5074 Keikilani Cir",
    "sg:city":"Honolulu",
    "sg:classifiers":[
        {
            "category":"Personal",
            "subcategory":"Beauty Salon",
            "type":"Services"
        }
    ],
    "sg:phone":"+1 808 373 1043",
    "sg:postcode":"96821",
    "sg:province":"HI",
    "sg:tags":[
        "hair",
        "removal"
    ],
    "wof:name":"Electrology Clinic",
    "wof:placetype":"venue"
},
  "geometry": {"coordinates":[-157.759186,21.279098],"type":"Point"}
}