{
  "type": "Feature",
  "properties": {
    "addr:full":"6365 Kenika Pl Kailua Kona HI 96740",
    "addr:housenumber":"6365",
    "addr:postcode":"96740",
    "addr:street":"Kenika Pl",
    "iso:country":"US",
    "sg:address":"6365 Kenika Pl",
    "sg:city":"Kailua Kona",
    "sg:classifiers":[
        {
            "category":"Health Services",
            "subcategory":"Doctor",
            "type":"Services"
        }
    ],
    "sg:phone":"+1 808 329 7774",
    "sg:postcode":"96740",
    "sg:province":"HI",
    "sg:tags":[
        "physician",
        "surgeon"
    ],
    "wof:name":"Scott B Gladstone MD",
    "wof:placetype":"venue"
},
  "geometry": {"coordinates":[-155.966813,19.606657],"type":"Point"}
}