{
  "type": "Feature",
  "properties": {
    "iso:country":"US",
    "sg:address":"19 Kamehameha Hwy",
    "sg:city":"Aiea",
    "sg:classifiers":[
        {
            "category":"Shopping",
            "subcategory":"Bicycles & Sporting Goods",
            "type":"Retail Goods"
        }
    ],
    "sg:phone":"+1 808 487 3615",
    "sg:postcode":"96701",
    "sg:province":"HI",
    "wof:name":"Bike Shop Inc",
    "wof:placetype":"venue"
},
  "geometry": {"coordinates":[-157.94898900000001,21.384636],"type":"Point"}
}