{
  "type": "Feature",
  "properties": {
    "iso:country":"US",
    "sg:address":"830 W Hind Dr",
    "sg:city":"Honolulu",
    "sg:classifiers":[
        {
            "category":"Autos & Motor Vehicles",
            "subcategory":"Fuel & Gas Station",
            "type":"Retail Goods"
        }
    ],
    "sg:phone":"+1 808 395 2133",
    "sg:postcode":"96821",
    "sg:province":"HI",
    "sg:tags":[
        "station",
        "gasoline"
    ],
    "wof:name":"Hawaii Kai 76",
    "wof:placetype":"venue"
},
  "geometry": {"coordinates":[-157.755169,21.278314],"type":"Point"}
}