{
  "type": "Feature",
  "properties": {
    "addr:full":"2870 Government Beach Rd Pahoa HI 96778",
    "addr:housenumber":"2870",
    "addr:postcode":"96778",
    "addr:street":"Government Beach Rd",
    "iso:country":"US",
    "sg:address":"2870 Government Beach Rd",
    "sg:city":"Pahoa",
    "sg:classifiers":[
        {
            "category":"Building & Trades",
            "subcategory":"Electrical",
            "type":"Services"
        }
    ],
    "sg:phone":"+1 808 965 1115",
    "sg:postcode":"96778",
    "sg:province":"HI",
    "sg:tags":[
        "electric",
        "contractor"
    ],
    "wof:name":"Power Electric",
    "wof:placetype":"venue"
},
  "geometry": {"coordinates":[-154.88527099999999,19.557491],"type":"Point"}
}