{
  "type": "Feature",
  "properties": {
    "iso:country":"US",
    "sg:address":"1740 S King St",
    "sg:city":"Honolulu",
    "sg:classifiers":[
        {
            "category":"Personal",
            "subcategory":"Beauty Salon",
            "type":"Services"
        }
    ],
    "sg:phone":"+1 808 946 7088",
    "sg:postcode":"96826",
    "sg:province":"HI",
    "sg:tags":[
        "manicuring"
    ],
    "wof:name":"A Nail Salon",
    "wof:placetype":"venue"
},
  "geometry": {"coordinates":[-157.834304,21.296446],"type":"Point"}
}