{
  "type": "Feature",
  "properties": {
    "iso:country":"US",
    "sg:address":"3669 Baldwin Ave",
    "sg:city":"Makawao",
    "sg:classifiers":[
        {
            "category":"Restaurant",
            "type":"Food & Drink"
        }
    ],
    "sg:phone":"+1 808 573 9065",
    "sg:postcode":"96768",
    "sg:province":"HI",
    "sg:tags":[
        "eating"
    ],
    "wof:name":"Cafe OLei",
    "wof:placetype":"venue"
},
  "geometry": {"coordinates":[-156.31101799999999,20.854964],"type":"Point"}
}