{
  "type": "Feature",
  "properties": {
    "iso:country":"US",
    "sg:address":"225 N Nimitz Hwy",
    "sg:city":"Honolulu",
    "sg:classifiers":[
        {
            "category":"Wholesale",
            "subcategory":"Seafood",
            "type":"Manufacturing & Wholesale Goods"
        }
    ],
    "sg:phone":"+1 808 524 4847",
    "sg:postcode":"96817",
    "sg:province":"HI",
    "sg:website":"www.gvisfd.com",
    "wof:name":"Garden & Valley Isle Seafood",
    "wof:placetype":"venue"
},
  "geometry": {"coordinates":[-157.86554100000001,21.313486],"type":"Point"}
}