{
  "type": "Feature",
  "properties": {
    "iso:country":"US",
    "sg:address":"918 Hausten St",
    "sg:city":"Honolulu",
    "sg:classifiers":[
        {
            "category":"Health Services",
            "subcategory":"Clinic",
            "type":"Services"
        }
    ],
    "sg:phone":"+1 808 221 0939",
    "sg:postcode":"96826",
    "sg:province":"HI",
    "sg:tags":[
        "hypnotherapy"
    ],
    "wof:name":"Hypnosis Research/Learning Ctr",
    "wof:placetype":"venue"
},
  "geometry": {"coordinates":[-157.82495499999999,21.290021],"type":"Point"}
}