{
  "type": "Feature",
  "properties": {
    "iso:country":"US",
    "sg:address":"550 California Ave",
    "sg:city":"Wahiawa",
    "sg:classifiers":[
        {
            "category":"Arts & Performance",
            "subcategory":"Theater",
            "type":"Entertainment"
        }
    ],
    "sg:phone":"+1 808 622 2857",
    "sg:postcode":"96786",
    "sg:province":"HI",
    "sg:tags":[
        "group"
    ],
    "wof:name":"Club Love",
    "wof:placetype":"venue"
},
  "geometry": {"coordinates":[-158.029403,21.496167],"type":"Point"}
}