{
  "type": "Feature",
  "properties": {
    "iso:country":"US",
    "sg:address":"1610 Wonderview Pl",
    "sg:city":"Wahiawa",
    "sg:classifiers":[
        {
            "category":"Professional",
            "type":"Services"
        }
    ],
    "sg:phone":"+1 808 622 2121",
    "sg:postcode":"96786",
    "sg:province":"HI",
    "wof:name":"Jeanne C Ishikawa",
    "wof:placetype":"venue"
},
  "geometry": {"coordinates":[-158.01327499999999,21.507481],"type":"Point"}
}