{
  "type": "Feature",
  "properties": {
    "iso:country":"US",
    "sg:address":"868 Queen St",
    "sg:city":"Honolulu",
    "sg:classifiers":[
        {
            "category":"Freight",
            "type":"Transportation"
        }
    ],
    "sg:phone":"+1 808 596 7225",
    "sg:postcode":"96813",
    "sg:province":"HI",
    "sg:tags":[
        "commercial",
        "storage"
    ],
    "wof:name":"Storage Room",
    "wof:placetype":"venue"
},
  "geometry": {"coordinates":[-157.856201,21.299962],"type":"Point"}
}