{
  "type": "Feature",
  "properties": {
    "addr:full":"23 Makaweli St Honolulu HI 96825",
    "addr:housenumber":"23",
    "addr:postcode":"96825",
    "addr:street":"Makaweli St",
    "iso:country":"US",
    "sg:address":"23 Makaweli St",
    "sg:city":"Honolulu",
    "sg:classifiers":[
        {
            "category":"Travel",
            "subcategory":"Travel Agent",
            "type":"Entertainment"
        }
    ],
    "sg:phone":"+1 808 395 5283",
    "sg:postcode":"96825",
    "sg:province":"HI",
    "sg:tags":[
        "operator",
        "tour"
    ],
    "wof:name":"Ol Tours Hawaii",
    "wof:placetype":"venue"
},
  "geometry": {"coordinates":[-157.70675199999999,21.271314],"type":"Point"}
}