{
  "type": "Feature",
  "properties": {
    "iso:country":"US",
    "sg:address":"1821 Kaumualii Hwy",
    "sg:city":"Lihue",
    "sg:classifiers":[
        {
            "category":"Social Services",
            "subcategory":"Child Care",
            "type":"Services"
        }
    ],
    "sg:phone":"+1 808 245 1755",
    "sg:postcode":"96766",
    "sg:province":"HI",
    "sg:tags":[
        "kindergarten",
        "academic",
        "school"
    ],
    "wof:name":"Punana Leo O Kaua'i",
    "wof:placetype":"venue"
},
  "geometry": {"coordinates":[-159.397448,21.966151],"type":"Point"}
}