{
  "type": "Feature",
  "properties": {
    "iso:country":"US",
    "sg:address":"30 Hauoli St",
    "sg:city":"Wailuku",
    "sg:classifiers":[
        {
            "category":"Real Estate",
            "subcategory":"Real Estate Agent",
            "type":"Services"
        }
    ],
    "sg:phone":"+1 808 249 0488",
    "sg:postcode":"96793",
    "sg:province":"HI",
    "sg:website":"www.foxandfoxmauirealestate.com",
    "wof:name":"Fox & Fox Maui Real Estate",
    "wof:placetype":"venue"
},
  "geometry": {"coordinates":[-156.51058599999999,20.79306],"type":"Point"}
}