{
  "type": "Feature",
  "properties": {
    "addr:full":"4230 Waialae Ave Honolulu HI 96816",
    "addr:postcode":"4230;96816",
    "addr:street":"Waialae Ave",
    "iso:country":"US",
    "sg:address":"4230 Waialae Ave",
    "sg:city":"Honolulu",
    "sg:classifiers":[
        {
            "category":"Restaurant",
            "type":"Food & Drink"
        }
    ],
    "sg:phone":"+1 808 735 9595",
    "sg:postcode":"96816",
    "sg:province":"HI",
    "sg:tags":[
        "eating"
    ],
    "wof:name":"Tony Roma's",
    "wof:placetype":"venue"
},
  "geometry": {"coordinates":[-157.785213,21.278479],"type":"Point"}
}