{
  "type": "Feature",
  "properties": {
    "iso:country":"US",
    "sg:address":"2180 Kaululoa Pl",
    "sg:city":"Honolulu",
    "sg:classifiers":[
        {
            "category":"Wholesale",
            "subcategory":"Apparel",
            "type":"Manufacturing & Wholesale Goods"
        }
    ],
    "sg:phone":"+1 808 737 6995",
    "sg:postcode":"96816",
    "sg:province":"HI",
    "wof:name":"Joan M & Co Inc",
    "wof:placetype":"venue"
},
  "geometry": {"coordinates":[-157.79430300000001,21.302924],"type":"Point"}
}