{
  "type": "Feature",
  "properties": {
    "addr:full":"1544 Haleukana St Lihue HI 96766",
    "addr:housenumber":"1544",
    "addr:postcode":"96766",
    "addr:street":"Haleukana St",
    "iso:country":"US",
    "sg:address":"1544 Haleukana St",
    "sg:city":"Lihue",
    "sg:classifiers":[
        {
            "category":"Professional",
            "subcategory":"Art Services",
            "type":"Services"
        },
        {
            "category":"Manufacturing",
            "subcategory":"Printing",
            "type":"Manufacturing & Wholesale Goods"
        }
    ],
    "sg:phone":"+1 808 245 6551",
    "sg:postcode":"96766",
    "sg:province":"HI",
    "sg:tags":[
        "graphic",
        "commercial",
        "designer"
    ],
    "wof:name":"Summerfieldesigns",
    "wof:placetype":"venue"
},
  "geometry": {"coordinates":[-159.392855,21.959852],"type":"Point"}
}