{
  "type": "Feature",
  "properties": {
    "iso:country":"US",
    "sg:address":"1144 Kamehameha Hwy",
    "sg:city":"Kaneohe",
    "sg:classifiers":[
        {
            "category":"Health Services",
            "subcategory":"Clinic",
            "type":"Services"
        }
    ],
    "sg:phone":"+1 808 236 7663",
    "sg:postcode":"96744",
    "sg:province":"HI",
    "sg:tags":[
        "physician",
        "surgeon",
        "bureau",
        "information"
    ],
    "sg:website":"www.healthweb1.com",
    "wof:name":"Healthweb1.Com Of Hawaii",
    "wof:placetype":"venue"
},
  "geometry": {"coordinates":[-157.80140700000001,21.416595],"type":"Point"}
}