{
  "type": "Feature",
  "properties": {
    "iso:country":"US",
    "sg:address":"1151 12th Ave",
    "sg:city":"Honolulu",
    "sg:classifiers":[
        {
            "category":"Shopping",
            "type":"Retail Goods"
        },
        {
            "category":"Recreation",
            "type":"Entertainment"
        }
    ],
    "sg:phone":"+1 808 739 1655",
    "sg:postcode":"96816",
    "sg:province":"HI",
    "sg:tags":[
        "metaphysical",
        "supply"
    ],
    "sg:website":"www.prosperitycorner.com",
    "wof:name":"Prosperity Corner Inc",
    "wof:placetype":"venue"
},
  "geometry": {"coordinates":[-157.79921300000001,21.281804],"type":"Point"}
}