{
  "type": "Feature",
  "properties": {
    "iso:country":"US",
    "sg:address":"2243 Kalaunu St",
    "sg:city":"Honolulu",
    "sg:classifiers":[
        {
            "category":"Social Services",
            "type":"Services"
        }
    ],
    "sg:phone":"+1 808 848 0585",
    "sg:postcode":"96819",
    "sg:province":"HI",
    "sg:tags":[
        "organization",
        "welfare"
    ],
    "wof:name":"Kokua Kalihi Valley",
    "wof:placetype":"venue"
},
  "geometry": {"coordinates":[-157.86372900000001,21.349741],"type":"Point"}
}