{
  "type": "Feature",
  "properties": {
    "iso:country":"US",
    "sg:address":"1109 12th Ave",
    "sg:city":"Honolulu",
    "sg:classifiers":[
        {
            "category":"Personal",
            "subcategory":"Beauty Salon",
            "type":"Services"
        }
    ],
    "sg:phone":"+1 808 737 6360",
    "sg:postcode":"96816",
    "sg:province":"HI",
    "wof:name":"Wendy L Tom",
    "wof:placetype":"venue"
},
  "geometry": {"coordinates":[-157.798811,21.282476],"type":"Point"}
}