{
  "type": "Feature",
  "properties": {
    "iso:country":"US",
    "sg:address":"414 Keehuhiwa St",
    "sg:city":"Mililani",
    "sg:classifiers":[
        {
            "category":"Professional",
            "subcategory":"Business Services",
            "type":"Services"
        }
    ],
    "sg:phone":"+1 808 623 8668",
    "sg:postcode":"96789",
    "sg:province":"HI",
    "wof:name":"Anabets Interiors",
    "wof:placetype":"venue"
},
  "geometry": {"coordinates":[-158.015266,21.431247],"type":"Point"}
}