{
  "type": "Feature",
  "properties": {
    "iso:country":"US",
    "sg:address":"1557 Lehua St",
    "sg:city":"Honolulu",
    "sg:classifiers":[
        {
            "category":"Professional",
            "subcategory":"Business Services",
            "type":"Services"
        }
    ],
    "sg:phone":"+1 808 843 1611",
    "sg:postcode":"96819",
    "sg:province":"HI",
    "wof:name":"Oahu Appraisals LLC",
    "wof:placetype":"venue"
},
  "geometry": {"coordinates":[-157.86107100000001,21.344348],"type":"Point"}
}