{
  "type": "Feature",
  "properties": {
    "addr:full":"1214 Ala Aupaka Pl Honolulu HI 96818",
    "addr:housenumber":"1214",
    "addr:postcode":"96818",
    "addr:street":"Ala Aupaka Pl",
    "iso:country":"US",
    "sg:address":"1214 Ala Aupaka Pl",
    "sg:city":"Honolulu",
    "sg:classifiers":[
        {
            "category":"Building & Trades",
            "subcategory":"Construction",
            "type":"Services"
        }
    ],
    "sg:phone":"+1 808 833 9570",
    "sg:postcode":"96818",
    "sg:province":"HI",
    "sg:tags":[
        "housing"
    ],
    "wof:name":"Jon Clifft Construction Inc",
    "wof:placetype":"venue"
},
  "geometry": {"coordinates":[-157.91966199999999,21.352748],"type":"Point"}
}