{
  "type": "Feature",
  "properties": {
    "addr:full":"3285 Waapa Rd Lihue HI 96766",
    "addr:housenumber":"3285",
    "addr:postcode":"96766",
    "addr:street":"Waapa Rd",
    "iso:country":"US",
    "sg:address":"3285 Waapa Rd",
    "sg:city":"Lihue",
    "sg:classifiers":[
        {
            "category":"Home & Garden",
            "subcategory":"Carpets & Floor Coverings",
            "type":"Retail Goods"
        }
    ],
    "sg:phone":"+1 808 246 3700",
    "sg:postcode":"96766",
    "sg:province":"HI",
    "wof:name":"Hesse Flooring",
    "wof:placetype":"venue"
},
  "geometry": {"coordinates":[-159.35405,21.95799],"type":"Point"}
}