{
  "type": "Feature",
  "properties": {
    "addr:full":"2035 Kamehameha Ave Honolulu HI 96822",
    "addr:housenumber":"2035",
    "addr:postcode":"96822",
    "addr:street":"Kamehameha Ave",
    "iso:country":"US",
    "sg:address":"2035 Kamehameha Ave",
    "sg:city":"Honolulu",
    "sg:classifiers":[
        {
            "category":"Social Services",
            "type":"Services"
        }
    ],
    "sg:phone":"+1 808 943 8767",
    "sg:postcode":"96822",
    "sg:province":"HI",
    "wof:name":"Monoa Cottage",
    "wof:placetype":"venue"
},
  "geometry": {"coordinates":[-157.823521,21.306122],"type":"Point"}
}