{
  "type": "Feature",
  "properties": {
    "iso:country":"US",
    "sg:address":"3160 Ualena St",
    "sg:city":"Honolulu",
    "sg:classifiers":[
        {
            "category":"Wholesale",
            "subcategory":"Chemicals & Plastics",
            "type":"Manufacturing & Wholesale Goods"
        }
    ],
    "sg:phone":"+1 808 833 9088",
    "sg:postcode":"96819",
    "sg:province":"HI",
    "wof:name":"CSS Inc",
    "wof:placetype":"venue"
},
  "geometry": {"coordinates":[-157.91119,21.334107],"type":"Point"}
}