{
  "type": "Feature",
  "properties": {
    "addr:full":"2396 Hulemalu Rd Lihue HI 96766",
    "addr:housenumber":"2396",
    "addr:postcode":"96766",
    "addr:street":"Hulemalu Rd",
    "iso:country":"US",
    "sg:address":"2396 Hulemalu Rd",
    "sg:city":"Lihue",
    "sg:classifiers":[
        {
            "category":"Building & Trades",
            "subcategory":"Electrical",
            "type":"Services"
        }
    ],
    "sg:phone":"+1 808 246 2459",
    "sg:postcode":"96766",
    "sg:province":"HI",
    "sg:tags":[
        "electric",
        "contractor"
    ],
    "wof:name":"JDK Enterprises",
    "wof:placetype":"venue"
},
  "geometry": {"coordinates":[-159.36520200000001,21.949833],"type":"Point"}
}