{
  "type": "Feature",
  "properties": {
    "addr:full":"3149 Poipu Rd Koloa HI 96756",
    "addr:housenumber":"3149",
    "addr:postcode":"96756",
    "addr:street":"Poipu Rd",
    "iso:country":"US",
    "sg:address":"3149 Poipu Rd",
    "sg:city":"Koloa",
    "sg:classifiers":[
        {
            "category":"Retail",
            "subcategory":"Auto Repair",
            "type":"Services"
        }
    ],
    "sg:phone":"+1 808 639 3719",
    "sg:postcode":"96756",
    "sg:province":"HI",
    "sg:tags":[
        "body",
        "automobile",
        "painting"
    ],
    "wof:name":"C & J's Custom Auto Body",
    "wof:placetype":"venue"
},
  "geometry": {"coordinates":[-159.46586500000001,21.895218],"type":"Point"}
}