{
  "type": "Feature",
  "properties": {
    "addr:full":"690 Kakoi St Honolulu HI 96819",
    "addr:housenumber":"690",
    "addr:postcode":"96819",
    "addr:street":"Kakoi St",
    "iso:country":"US",
    "sg:address":"690 Kakoi St",
    "sg:city":"Honolulu",
    "sg:classifiers":[
        {
            "category":"Wholesale",
            "subcategory":"Machinery & Supplies",
            "type":"Manufacturing & Wholesale Goods"
        }
    ],
    "sg:phone":"+1 808 836 1941",
    "sg:postcode":"96819",
    "sg:province":"HI",
    "sg:tags":[
        "upholsterer"
    ],
    "wof:name":"Keyston Brothers",
    "wof:placetype":"venue"
},
  "geometry": {"coordinates":[-157.89602400000001,21.337243],"type":"Point"}
}