{
  "type": "Feature",
  "properties": {
    "iso:country":"US",
    "sg:address":"355 Hukilike St",
    "sg:city":"Kahului",
    "sg:classifiers":[
        {
            "category":"Personal",
            "subcategory":"Beauty Salon",
            "type":"Services"
        }
    ],
    "sg:phone":"+1 808 877 3993",
    "sg:postcode":"96732",
    "sg:province":"HI",
    "sg:tags":[
        "shop"
    ],
    "wof:name":"Trendsitions",
    "wof:placetype":"venue"
},
  "geometry": {"coordinates":[-156.45881199999999,20.882999],"type":"Point"}
}