{
  "type": "Feature",
  "properties": {
    "iso:country":"US",
    "sg:address":"105 Oneawa St",
    "sg:city":"Kailua",
    "sg:classifiers":[
        {
            "category":"Autos & Motor Vehicles",
            "subcategory":"Automobile Sales",
            "type":"Retail Goods"
        }
    ],
    "sg:phone":"+1 808 266 8000",
    "sg:postcode":"96734",
    "sg:province":"HI",
    "wof:name":"McKenna Mtrs Wndward Vlkswagen",
    "wof:placetype":"venue"
},
  "geometry": {"coordinates":[-157.744955,21.39591],"type":"Point"}
}