{
  "type": "Feature",
  "properties": {
    "iso:country":"US",
    "sg:address":"1887 Lalea Pl",
    "sg:city":"Honolulu",
    "sg:classifiers":[
        {
            "category":"Professional",
            "type":"Services"
        }
    ],
    "sg:phone":"+1 808 524 1966",
    "sg:postcode":"96821",
    "sg:province":"HI",
    "wof:name":"Creative Arts Center",
    "wof:placetype":"venue"
},
  "geometry": {"coordinates":[-157.76345000000001,21.28702],"type":"Point"}
}