{
  "type": "Feature",
  "properties": {
    "addr:full":"2850 Paa St Honolulu HI 96819",
    "addr:postcode":"2850;96819",
    "addr:street":"Paa St",
    "iso:country":"US",
    "sg:address":"2850 Paa St",
    "sg:city":"Honolulu",
    "sg:classifiers":[
        {
            "category":"Professional",
            "subcategory":"Employment Agencies",
            "type":"Services"
        }
    ],
    "sg:phone":"+1 808 836 1334",
    "sg:postcode":"96819",
    "sg:province":"HI",
    "sg:tags":[
        "help",
        "contractor"
    ],
    "wof:name":"Hawaii Temp",
    "wof:placetype":"venue"
},
  "geometry": {"coordinates":[-157.895894,21.345557],"type":"Point"}
}