{
  "type": "Feature",
  "properties": {
    "iso:country":"US",
    "sg:address":"261 Dairy Rd",
    "sg:city":"Wailuku",
    "sg:classifiers":[
        {
            "category":"Wholesale",
            "subcategory":"Scrap",
            "type":"Manufacturing & Wholesale Goods"
        }
    ],
    "sg:phone":"+1 808 385 1867",
    "sg:postcode":"96732",
    "sg:province":"HI",
    "sg:tags":[
        "recycling",
        "center"
    ],
    "wof:name":"Reynolds Recycling Inc",
    "wof:placetype":"venue"
},
  "geometry": {"coordinates":[-156.45631299999999,20.880709],"type":"Point"}
}