{
  "type": "Feature",
  "properties": {
    "addr:full":"204 Makee Rd Honolulu HI 96815",
    "addr:housenumber":"204",
    "addr:postcode":"96815",
    "addr:street":"Makee Rd",
    "iso:country":"US",
    "sg:address":"204 Makee Rd",
    "sg:city":"Honolulu",
    "sg:phone":"+1 808 924 8282",
    "sg:postcode":"96815",
    "sg:province":"HI",
    "sg:tags":[
        "equipment",
        "commercial",
        "furniture"
    ],
    "wof:name":"Makai Sales Ltd",
    "wof:placetype":"venue"
},
  "geometry": {"coordinates":[-157.82032799999999,21.272087],"type":"Point"}
}