{
  "type": "Feature",
  "properties": {
    "iso:country":"US",
    "sg:address":"856 Aalapapa Dr",
    "sg:city":"Kailua",
    "sg:classifiers":[
        {
            "category":"Professional",
            "type":"Services"
        }
    ],
    "sg:phone":"+1 808 262 4393",
    "sg:postcode":"96734",
    "sg:province":"HI",
    "wof:name":"Mallory Players",
    "wof:placetype":"venue"
},
  "geometry": {"coordinates":[-157.719089,21.393236],"type":"Point"}
}