{
  "type": "Feature",
  "properties": {
    "iso:country":"US",
    "sg:address":"1450 Ala Moana Blvd",
    "sg:city":"Honolulu",
    "sg:classifiers":[
        {
            "category":"Shopping",
            "subcategory":"Computers & Home Electronics",
            "type":"Retail Goods"
        }
    ],
    "sg:phone":"+1 808 983 7625",
    "sg:postcode":"96814",
    "sg:province":"HI",
    "sg:tags":[
        "equipment",
        "electronic",
        "supply"
    ],
    "sg:website":"www.radioshack.com",
    "wof:name":"Radio Shack",
    "wof:placetype":"venue"
},
  "geometry": {"coordinates":[-157.84143399999999,21.289059],"type":"Point"}
}