{
  "type": "Feature",
  "properties": {
    "iso:country":"US",
    "sg:address":"300 Ohukai Rd",
    "sg:city":"Kihei",
    "sg:classifiers":[
        {
            "category":"Personal",
            "subcategory":"Beauty Salon",
            "type":"Services"
        }
    ],
    "sg:phone":"+1 808 879 6909",
    "sg:postcode":"96753",
    "sg:province":"HI",
    "sg:tags":[
        "shop"
    ],
    "wof:name":"Silky Skin Laser Spa",
    "wof:placetype":"venue"
},
  "geometry": {"coordinates":[-156.454159,20.775451],"type":"Point"}
}