{
  "type": "Feature",
  "properties": {
    "addr:full":"660 Aipo St Honolulu HI 96825",
    "addr:housenumber":"660",
    "addr:postcode":"96825",
    "addr:street":"Aipo St",
    "iso:country":"US",
    "sg:address":"660 Aipo St",
    "sg:city":"Honolulu",
    "sg:classifiers":[
        {
            "category":"Building & Trades",
            "subcategory":"Construction",
            "type":"Services"
        }
    ],
    "sg:phone":"+1 808 841 2295",
    "sg:postcode":"96825",
    "sg:province":"HI",
    "sg:tags":[
        "general",
        "contractor"
    ],
    "wof:name":"J J S Construction Inc",
    "wof:placetype":"venue"
},
  "geometry": {"coordinates":[-157.69391899999999,21.291029],"type":"Point"}
}