{
  "type": "Feature",
  "properties": {
    "iso:country":"US",
    "sg:address":"1690 W Kuiaha Rd",
    "sg:city":"Haiku",
    "sg:classifiers":[
        {
            "category":"Building & Trades",
            "subcategory":"Construction",
            "type":"Services"
        }
    ],
    "sg:phone":"+1 808 572 0216",
    "sg:postcode":"96708",
    "sg:province":"HI",
    "sg:tags":[
        "contractor"
    ],
    "wof:name":"Ricos Ceramic Tile",
    "wof:placetype":"venue"
},
  "geometry": {"coordinates":[-156.30003099999999,20.888578],"type":"Point"}
}