{
  "type": "Feature",
  "properties": {
    "addr:full":"6915 Kokeanu Pl Kapaa HI 96746",
    "addr:housenumber":"6915",
    "addr:postcode":"96746",
    "addr:street":"Kokeanu Pl",
    "iso:country":"US",
    "sg:address":"6915 Kokeanu Pl",
    "sg:city":"Kapaa",
    "sg:classifiers":[
        {
            "category":"Real Estate",
            "subcategory":"Real Estate Agent",
            "type":"Services"
        }
    ],
    "sg:phone":"+1 808 822 3886",
    "sg:postcode":"96746",
    "sg:province":"HI",
    "sg:tags":[
        "inspection"
    ],
    "wof:name":"Home Masters",
    "wof:placetype":"venue"
},
  "geometry": {"coordinates":[-159.387169,22.058335],"type":"Point"}
}