{
  "type": "Feature",
  "properties": {
    "addr:full":"1350 S King St Honolulu HI 96814",
    "addr:housenumber":"1350",
    "addr:postcode":"96814",
    "addr:street":"S King St",
    "iso:country":"US",
    "sg:address":"1350 S King St",
    "sg:city":"Honolulu",
    "sg:classifiers":[
        {
            "category":"Professional",
            "subcategory":"Detective & Security Services",
            "type":"Services"
        }
    ],
    "sg:phone":"+1 808 593 1125",
    "sg:postcode":"96814",
    "sg:province":"HI",
    "sg:tags":[
        "alarm",
        "patrol",
        "guard",
        "system"
    ],
    "sg:website":"www.apisecurity.com",
    "wof:name":"API Security",
    "wof:placetype":"venue"
},
  "geometry": {"coordinates":[-157.841677,21.299071],"type":"Point"}
}