{
  "type": "Feature",
  "properties": {
    "addr:full":"240 Desha Ave Hilo HI 96720",
    "addr:housenumber":"240",
    "addr:postcode":"96720",
    "addr:street":"Desha Ave",
    "iso:country":"US",
    "sg:address":"240 Desha Ave",
    "sg:city":"Hilo",
    "sg:classifiers":[
        {
            "category":"Government",
            "subcategory":"Office",
            "type":"Public Place"
        }
    ],
    "sg:phone":"+1 808 935 1959",
    "sg:postcode":"96720",
    "sg:province":"HI",
    "sg:tags":[
        "educational",
        "program",
        "administrative"
    ],
    "wof:name":"Keaukaka School",
    "wof:placetype":"venue"
},
  "geometry": {"coordinates":[-155.04521500000001,19.728754],"type":"Point"}
}