{
  "type": "Feature",
  "properties": {
    "iso:country":"US",
    "sg:address":"32 Kinoole St",
    "sg:city":"Hilo",
    "sg:classifiers":[
        {
            "category":"Government",
            "subcategory":"Office",
            "type":"Public Place"
        }
    ],
    "sg:phone":"+1 808 969 9909",
    "sg:postcode":"96720",
    "sg:province":"HI",
    "wof:name":"Hakalau Forest National Refuge",
    "wof:placetype":"venue"
},
  "geometry": {"coordinates":[-155.08962099999999,19.725841],"type":"Point"}
}