{
  "type": "Feature",
  "properties": {
    "iso:country":"US",
    "sg:address":"26 Hoolai St",
    "sg:city":"Kailua",
    "sg:classifiers":[
        {
            "category":"Restaurant",
            "type":"Food & Drink"
        }
    ],
    "sg:menulink":"http://www.allmenus.com/hi/koolaupoko/92280-l--l-hawaiian-bbq/menu/",
    "sg:phone":"+1 808 262 1113",
    "sg:postcode":"96734",
    "sg:province":"HI",
    "sg:tags":[
        "barbecue",
        "american",
        "hawaiian"
    ],
    "wof:name":"L & L Hawaiian BBQ",
    "wof:placetype":"venue"
},
  "geometry": {"coordinates":[-157.74466899999999,21.394874],"type":"Point"}
}