{
  "type": "Feature",
  "properties": {
    "iso:country":"US",
    "sg:address":"1773 Ulu St",
    "sg:city":"Aiea",
    "sg:classifiers":[
        {
            "category":"Professional",
            "subcategory":"Business Services",
            "type":"Services"
        }
    ],
    "sg:phone":"+1 808 488 0531",
    "sg:postcode":"96701",
    "sg:province":"HI",
    "wof:name":"Real Isle Properties",
    "wof:placetype":"venue"
},
  "geometry": {"coordinates":[-157.945234,21.404593],"type":"Point"}
}