{
  "type": "Feature",
  "properties": {
    "iso:country":"US",
    "sg:address":"4473 Pahee St",
    "sg:city":"Lihue",
    "sg:classifiers":[
        {
            "category":"Professional",
            "subcategory":"Accounting & Tax Preparation",
            "type":"Services"
        }
    ],
    "sg:phone":"+1 808 246 9422",
    "sg:postcode":"96766",
    "sg:province":"HI",
    "sg:tags":[
        "accountant"
    ],
    "wof:name":"Oberg & Free",
    "wof:placetype":"venue"
},
  "geometry": {"coordinates":[-159.383184,21.970317],"type":"Point"}
}