{
  "type": "Feature",
  "properties": {
    "iso:country":"US",
    "sg:address":"355 Royal Hawaiian Ave",
    "sg:city":"Honolulu",
    "sg:classifiers":[
        {
            "category":"Shopping",
            "subcategory":"Shoes",
            "type":"Retail Goods"
        }
    ],
    "sg:phone":"+1 808 926 8836",
    "sg:postcode":"96815",
    "sg:province":"HI",
    "wof:name":"Cinderella Shoe Store",
    "wof:placetype":"venue"
},
  "geometry": {"coordinates":[-157.82772600000001,21.280727],"type":"Point"}
}