{
  "type": "Feature",
  "properties": {
    "iso:country":"US",
    "sg:address":"5 Sand Island Access Rd",
    "sg:city":"Honolulu",
    "sg:classifiers":[
        {
            "category":"Organizations",
            "subcategory":"Religious Organization",
            "type":"Services"
        }
    ],
    "sg:phone":"+1 808 841 8689",
    "sg:postcode":"96819",
    "sg:province":"HI",
    "sg:tags":[
        "church"
    ],
    "wof:name":"Mauga Olive Samoan Assembly",
    "wof:placetype":"venue"
},
  "geometry": {"coordinates":[-157.88908699999999,21.316561],"type":"Point"}
}