{
  "type": "Feature",
  "properties": {
    "iso:country":"US",
    "sg:address":"1038 Puaniu St",
    "sg:city":"Ewa Beach",
    "sg:classifiers":[
        {
            "category":"Retail",
            "subcategory":"Repair Shop",
            "type":"Services"
        }
    ],
    "sg:phone":"+1 808 683 5428",
    "sg:postcode":"96706",
    "sg:province":"HI",
    "wof:name":"Bolt-Konno Electronics",
    "wof:placetype":"venue"
},
  "geometry": {"coordinates":[-158.03260800000001,21.339441],"type":"Point"}
}