{
  "type": "Feature",
  "properties": {
    "iso:country":"US",
    "sg:address":"29 Hekaha St",
    "sg:city":"Aiea",
    "sg:classifiers":[
        {
            "category":"Real Estate",
            "subcategory":"Real Estate Agent",
            "type":"Services"
        }
    ],
    "sg:phone":"+1 808 488 1070",
    "sg:postcode":"96701",
    "sg:province":"HI",
    "wof:name":"Onishi Shirley Realtor LLC",
    "wof:placetype":"venue"
},
  "geometry": {"coordinates":[-157.95153400000001,21.384524],"type":"Point"}
}