{
  "type": "Feature",
  "properties": {
    "iso:country":"US",
    "sg:address":"33 S King St",
    "sg:city":"Honolulu",
    "sg:classifiers":[
        {
            "category":"Real Estate",
            "subcategory":"Real Estate Agent",
            "type":"Services"
        }
    ],
    "sg:phone":"+1 808 538 6887",
    "sg:postcode":"96813",
    "sg:province":"HI",
    "sg:tags":[
        "appraiser"
    ],
    "wof:name":"Second Opinion Hawaii Inc",
    "wof:placetype":"venue"
},
  "geometry": {"coordinates":[-157.86295100000001,21.310464],"type":"Point"}
}