{
  "type": "Feature",
  "properties": {
    "iso:country":"US",
    "sg:address":"546 Ilimano St",
    "sg:city":"Kailua",
    "sg:classifiers":[
        {
            "category":"Wholesale",
            "subcategory":"Groceries",
            "type":"Manufacturing & Wholesale Goods"
        }
    ],
    "sg:phone":"+1 808 262 7007",
    "sg:postcode":"96734",
    "sg:province":"HI",
    "sg:tags":[
        "food",
        "basket",
        "hawaiian",
        "gift"
    ],
    "wof:name":"Hungry Hawaiian Snack",
    "wof:placetype":"venue"
},
  "geometry": {"coordinates":[-157.75313800000001,21.415043],"type":"Point"}
}