{
  "type": "Feature",
  "properties": {
    "iso:country":"US",
    "sg:address":"653 Ialeleiaka Pl",
    "sg:city":"Mililani",
    "sg:classifiers":[
        {
            "category":"Retail",
            "subcategory":"Repair Shop",
            "type":"Services"
        },
        {
            "category":"Building & Trades",
            "subcategory":"Plumbing",
            "type":"Services"
        }
    ],
    "sg:phone":"+1 808 625 1373",
    "sg:postcode":"96789",
    "sg:province":"HI",
    "sg:tags":[
        "conditioning",
        "air",
        "refrigeration",
        "system",
        "contractor"
    ],
    "wof:name":"Yoshis Refrigeration & AC Svc",
    "wof:placetype":"venue"
},
  "geometry": {"coordinates":[-158.02656899999999,21.438806],"type":"Point"}
}