{
  "type": "Feature",
  "properties": {
    "iso:country":"US",
    "sg:address":"550 Halekauwila St",
    "sg:city":"Honolulu",
    "sg:classifiers":[
        {
            "category":"Real Estate",
            "subcategory":"Developer",
            "type":"Services"
        }
    ],
    "sg:phone":"+1 808 531 0998",
    "sg:postcode":"96813",
    "sg:province":"HI",
    "wof:name":"Essll Partners",
    "wof:placetype":"venue"
},
  "geometry": {"coordinates":[-157.86031800000001,21.302589],"type":"Point"}
}