{
  "type": "Feature",
  "properties": {
    "addr:full":"375 W Kuiaha Rd Haiku HI 96708",
    "addr:housenumber":"375",
    "addr:postcode":"96708",
    "addr:street":"W Kuiaha Rd",
    "iso:country":"US",
    "sg:address":"375 W Kuiaha Rd",
    "sg:city":"Haiku",
    "sg:classifiers":[
        {
            "category":"Manufacturing",
            "subcategory":"Toys & Sporting Goods",
            "type":"Manufacturing & Wholesale Goods"
        }
    ],
    "sg:phone":"+1 808 575 2495",
    "sg:postcode":"96708",
    "sg:province":"HI",
    "sg:tags":[
        "mfg"
    ],
    "wof:name":"Da Kine Hawaii Inc",
    "wof:placetype":"venue"
},
  "geometry": {"coordinates":[-156.31047799999999,20.921354],"type":"Point"}
}