{
  "type": "Feature",
  "properties": {
    "iso:country":"US",
    "sg:address":"7108 Kukii St",
    "sg:city":"Honolulu",
    "sg:classifiers":[
        {
            "category":"Shopping",
            "subcategory":"Bicycles & Sporting Goods",
            "type":"Retail Goods"
        }
    ],
    "sg:phone":"+1 808 396 9001",
    "sg:postcode":"96825",
    "sg:province":"HI",
    "wof:name":"Mikeys Scuba Repair Inc",
    "wof:placetype":"venue"
},
  "geometry": {"coordinates":[-157.691676,21.297134],"type":"Point"}
}