{
  "type": "Feature",
  "properties": {
    "addr:full":"2875 Ualena St Honolulu HI 96819",
    "addr:housenumber":"2875",
    "addr:postcode":"96819",
    "addr:street":"Ualena St",
    "iso:country":"US",
    "sg:address":"2875 Ualena St",
    "sg:city":"Honolulu",
    "sg:classifiers":[
        {
            "category":"Manufacturing",
            "subcategory":"Motor Vehicles & Parts",
            "type":"Manufacturing & Wholesale Goods"
        }
    ],
    "sg:phone":"+1 808 838 7754",
    "sg:postcode":"96819",
    "sg:province":"HI",
    "sg:tags":[
        "mfg"
    ],
    "wof:name":"Tdk Autobody & Paint",
    "wof:placetype":"venue"
},
  "geometry": {"coordinates":[-157.90571399999999,21.333141],"type":"Point"}
}