{
  "type": "Feature",
  "properties": {
    "iso:country":"US",
    "sg:address":"1247 Kaahumanu St",
    "sg:city":"Aiea",
    "sg:classifiers":[
        {
            "category":"Health Services",
            "subcategory":"Doctor",
            "type":"Services"
        }
    ],
    "sg:phone":"+1 808 487 2411",
    "sg:postcode":"96701",
    "sg:province":"HI",
    "wof:name":"Chang Allan S DDS Ms D",
    "wof:placetype":"venue"
},
  "geometry": {"coordinates":[-157.953833,21.388047],"type":"Point"}
}