{
  "type": "Feature",
  "properties": {
    "iso:country":"US",
    "sg:address":"218 Leleoi Pl",
    "sg:city":"Ewa Beach",
    "sg:classifiers":[
        {
            "category":"Banks & Credit Unions",
            "subcategory":"Bank",
            "type":"Services"
        }
    ],
    "sg:phone":"+1 808 722 0734",
    "sg:postcode":"96706",
    "sg:province":"HI",
    "sg:tags":[
        "broker",
        "mortgage"
    ],
    "wof:name":"Total Advantedge LLC",
    "wof:placetype":"venue"
},
  "geometry": {"coordinates":[-158.021872,21.340017],"type":"Point"}
}