{
  "type": "Feature",
  "properties": {
    "iso:country":"US",
    "sg:address":"1211 Mokulua Dr",
    "sg:city":"Kailua",
    "sg:classifiers":[
        {
            "category":"Food & Beverages",
            "subcategory":"Specialty",
            "type":"Retail Goods"
        }
    ],
    "sg:phone":"+1 808 263 3046",
    "sg:postcode":"96734",
    "sg:province":"HI",
    "sg:tags":[
        "specializing",
        "product",
        "health",
        "or"
    ],
    "wof:name":"Personal Prosperity Inc",
    "wof:placetype":"venue"
},
  "geometry": {"coordinates":[-157.712074,21.386824],"type":"Point"}
}