{
  "type": "Feature",
  "properties": {
    "iso:country":"US",
    "sg:address":"4321 Aalona St",
    "sg:city":"Kilauea",
    "sg:classifiers":[
        {
            "category":"Retail",
            "subcategory":"Repair Shop",
            "type":"Services"
        },
        {
            "category":"Autos & Motor Vehicles",
            "subcategory":"Motorcycle Sales",
            "type":"Retail Goods"
        }
    ],
    "sg:phone":"+1 808 828 1015",
    "sg:postcode":"96754",
    "sg:province":"HI",
    "sg:tags":[
        "scooter"
    ],
    "wof:name":"R & S Cycle",
    "wof:placetype":"venue"
},
  "geometry": {"coordinates":[-159.40922,22.207729],"type":"Point"}
}