{
  "type": "Feature",
  "properties": {
    "iso:country":"US",
    "sg:address":"250 Kamehameha Hwy",
    "sg:city":"Waialua",
    "sg:classifiers":[
        {
            "category":"Shopping",
            "subcategory":"Bicycles & Sporting Goods",
            "type":"Retail Goods"
        }
    ],
    "sg:phone":"+1 808 637 7797",
    "sg:postcode":"96712",
    "sg:province":"HI",
    "wof:name":"Barnfeild Progress",
    "wof:placetype":"venue"
},
  "geometry": {"coordinates":[-158.07068100000001,21.631967],"type":"Point"}
}