{
  "type": "Feature",
  "properties": {
    "addr:full":"1120 Maunakea St Honolulu HI 96817",
    "addr:housenumber":"1120",
    "addr:postcode":"96817",
    "addr:street":"Maunakea St",
    "iso:country":"US",
    "sg:address":"1120 Maunakea St",
    "sg:city":"Honolulu",
    "sg:classifiers":[
        {
            "category":"Food & Beverages",
            "subcategory":"Groceries & Convenience Stores",
            "type":"Retail Goods"
        }
    ],
    "sg:phone":"+1 808 545 4594",
    "sg:postcode":"96817",
    "sg:province":"HI",
    "sg:tags":[
        "market"
    ],
    "wof:name":"Adams Retail Store",
    "wof:placetype":"venue"
},
  "geometry": {"coordinates":[-157.86246800000001,21.312588],"type":"Point"}
}