{
  "type": "Feature",
  "properties": {
    "iso:country":"US",
    "sg:address":"1425 Liliha St",
    "sg:city":"Honolulu",
    "sg:classifiers":[
        {
            "category":"Restaurant",
            "type":"Food & Drink"
        }
    ],
    "sg:menulink":"http://www.allmenus.com/hi/honolulu/109805-subway/menu/",
    "sg:phone":"+1 808 526 4500",
    "sg:postcode":"96817",
    "sg:province":"HI",
    "sg:tags":[
        "american",
        "sandwich"
    ],
    "wof:name":"Subway",
    "wof:placetype":"venue"
},
  "geometry": {"coordinates":[-157.86121499999999,21.319795],"type":"Point"}
}