{
  "type": "Feature",
  "properties": {
    "iso:country":"US",
    "sg:address":"390 Pau Hana Rd",
    "sg:city":"Makawao",
    "sg:classifiers":[
        {
            "category":"Building & Trades",
            "subcategory":"Construction",
            "type":"Services"
        }
    ],
    "sg:phone":"+1 808 244 9679",
    "sg:postcode":"96768",
    "sg:province":"HI",
    "sg:tags":[
        "contractor"
    ],
    "wof:name":"Kinores Masonry",
    "wof:placetype":"venue"
},
  "geometry": {"coordinates":[-156.32509300000001,20.854256],"type":"Point"}
}