{
  "type": "Feature",
  "properties": {
    "iso:country":"US",
    "sg:address":"1109 Young St",
    "sg:city":"Honolulu",
    "sg:classifiers":[
        {
            "category":"Health Services",
            "subcategory":"Medical Lab",
            "type":"Services"
        }
    ],
    "sg:phone":"+1 808 592 0863",
    "sg:postcode":"96814",
    "sg:province":"HI",
    "sg:tags":[
        "laboratory"
    ],
    "wof:name":"Clinical Laboratories LLP",
    "wof:placetype":"venue"
},
  "geometry": {"coordinates":[-157.84440499999999,21.300903],"type":"Point"}
}