{
  "type": "Feature",
  "properties": {
    "iso:country":"US",
    "sg:address":"4520 Kukui St",
    "sg:city":"Kapaa",
    "sg:classifiers":[
        {
            "category":"Organizations",
            "subcategory":"Religious Organization",
            "type":"Services"
        }
    ],
    "sg:phone":"+1 808 823 6959",
    "sg:postcode":"96746",
    "sg:province":"HI",
    "sg:tags":[
        "meditation"
    ],
    "wof:name":"Crystal Academy",
    "wof:placetype":"venue"
},
  "geometry": {"coordinates":[-159.31903600000001,22.076129],"type":"Point"}
}