{
  "type": "Feature",
  "properties": {
    "addr:full":"333 Queen St Honolulu HI 96813",
    "addr:housenumber":"333",
    "addr:postcode":"96813",
    "addr:street":"Queen St",
    "iso:country":"US",
    "sg:address":"333 Queen St",
    "sg:city":"Honolulu",
    "sg:classifiers":[
        {
            "category":"Professional",
            "subcategory":"Accounting & Tax Preparation",
            "type":"Services"
        }
    ],
    "sg:phone":"+1 808 523 0471",
    "sg:postcode":"96813",
    "sg:province":"HI",
    "sg:tags":[
        "accountant",
        "public",
        "certified"
    ],
    "wof:name":"Ichishita Brian K CPA",
    "wof:placetype":"venue"
},
  "geometry": {"coordinates":[-157.861118,21.305616],"type":"Point"}
}