{
  "type": "Feature",
  "properties": {
    "iso:country":"US",
    "sg:address":"1039 Meheula Pkwy",
    "sg:city":"Mililani",
    "sg:classifiers":[
        {
            "category":"Communications",
            "subcategory":"Radio Station",
            "type":"Services"
        }
    ],
    "sg:phone":"+1 808 623 6646",
    "sg:postcode":"96789",
    "sg:province":"HI",
    "sg:tags":[
        "broadcast"
    ],
    "wof:name":"Oahu Hawaii Facility MGT Group",
    "wof:placetype":"venue"
},
  "geometry": {"coordinates":[-158.01232099999999,21.451101],"type":"Point"}
}