{
  "type": "Feature",
  "properties": {
    "addr:full":"174 Hanua St Kapolei HI 96707",
    "addr:housenumber":"174",
    "addr:postcode":"96707",
    "addr:street":"Hanua St",
    "iso:country":"US",
    "sg:address":"174 Hanua St",
    "sg:city":"Kapolei",
    "sg:classifiers":[
        {
            "category":"Government",
            "subcategory":"Office",
            "type":"Public Place"
        }
    ],
    "sg:phone":"+1 808 682 1359",
    "sg:postcode":"96707",
    "sg:province":"HI",
    "sg:tags":[
        "program",
        "economic",
        "general"
    ],
    "wof:name":"Covanta Facilities",
    "wof:placetype":"venue"
},
  "geometry": {"coordinates":[-158.102441,21.304128],"type":"Point"}
}