{
  "type": "Feature",
  "properties": {
    "iso:country":"US",
    "sg:address":"5620 Palani Rd",
    "sg:city":"Kailua Kona",
    "sg:classifiers":[
        {
            "category":"Organizations",
            "subcategory":"Community Association",
            "type":"Services"
        }
    ],
    "sg:phone":"+1 808 326 9335",
    "sg:postcode":"96740",
    "sg:province":"HI",
    "sg:tags":[
        "educational"
    ],
    "wof:name":"Pacific Rim Education Fndtn",
    "wof:placetype":"venue"
},
  "geometry": {"coordinates":[-155.991195,19.648583],"type":"Point"}
}