{
  "type": "Feature",
  "properties": {
    "iso:country":"US",
    "sg:address":"3750 Wailea Alanui Dr",
    "sg:city":"Kihei",
    "sg:classifiers":[
        {
            "category":"Personal",
            "subcategory":"Beauty Salon",
            "type":"Services"
        }
    ],
    "sg:phone":"+1 808 891 9448",
    "sg:postcode":"96753",
    "sg:province":"HI",
    "sg:tags":[
        "make",
        "studio"
    ],
    "wof:name":"Cos Bar At Wailea Inc",
    "wof:placetype":"venue"
},
  "geometry": {"coordinates":[-156.439267,20.686522],"type":"Point"}
}