{
  "type": "Feature",
  "properties": {
    "iso:country":"US",
    "sg:address":"598 Halekauwila St",
    "sg:city":"Honolulu",
    "sg:classifiers":[
        {
            "category":"Professional",
            "subcategory":"Accounting & Tax Preparation",
            "type":"Services"
        }
    ],
    "sg:phone":"+1 808 533 4244",
    "sg:postcode":"96813",
    "sg:province":"HI",
    "sg:tags":[
        "firm",
        "public",
        "certified"
    ],
    "wof:name":"Erwin Lee W CPA",
    "wof:placetype":"venue"
},
  "geometry": {"coordinates":[-157.86118999999999,21.303435],"type":"Point"}
}