{
  "type": "Feature",
  "properties": {
    "iso:country":"US",
    "sg:address":"284 Komohana St",
    "sg:city":"Kapolei",
    "sg:classifiers":[
        {
            "category":"Building & Trades",
            "subcategory":"Construction",
            "type":"Services"
        }
    ],
    "sg:phone":"+1 808 682 1465",
    "sg:postcode":"96707",
    "sg:province":"HI",
    "sg:tags":[
        "masonry",
        "drywall",
        "contractor"
    ],
    "wof:name":"Ono Construction Inc",
    "wof:placetype":"venue"
},
  "geometry": {"coordinates":[-158.09324599999999,21.308573],"type":"Point"}
}