{
  "type": "Feature",
  "properties": {
    "addr:full":"875 Waimanu St Honolulu HI 96813",
    "addr:housenumber":"875",
    "addr:postcode":"96813",
    "addr:street":"Waimanu St",
    "iso:country":"US",
    "sg:address":"875 Waimanu St",
    "sg:city":"Honolulu",
    "sg:classifiers":[
        {
            "category":"Shopping",
            "subcategory":"Hobbies, Toys, & Games",
            "type":"Retail Goods"
        }
    ],
    "sg:phone":"+1 808 261 7115",
    "sg:postcode":"96813",
    "sg:province":"HI",
    "wof:name":"Thinker Toys",
    "wof:placetype":"venue"
},
  "geometry": {"coordinates":[-157.854623,21.300029],"type":"Point"}
}