{
  "type": "Feature",
  "properties": {
    "iso:country":"US",
    "sg:address":"2747 Pali Hwy",
    "sg:city":"Honolulu",
    "sg:classifiers":[
        {
            "category":"Organizations",
            "subcategory":"Religious Organization",
            "type":"Services"
        }
    ],
    "sg:phone":"+1 808 595 3105",
    "sg:postcode":"96817",
    "sg:province":"HI",
    "wof:name":"St Stephen Church",
    "wof:placetype":"venue"
},
  "geometry": {"coordinates":[-157.841399,21.333788],"type":"Point"}
}