{
  "type": "Feature",
  "properties": {
    "addr:full":"5000 Kahala Ave Honolulu HI 96816",
    "addr:housenumber":"5000",
    "addr:postcode":"96816",
    "addr:street":"Kahala Ave",
    "iso:country":"US",
    "sg:address":"5000 Kahala Ave",
    "sg:city":"Honolulu",
    "sg:classifiers":[
        {
            "category":"Restaurant",
            "type":"Food & Drink"
        }
    ],
    "sg:menulink":"http://www.allmenus.com/hi/honolulu/3323-tokyo-tokyo/menu/",
    "sg:phone":"+1 808 739 8901",
    "sg:postcode":"96816",
    "sg:province":"HI",
    "sg:tags":[
        "japanese",
        "asian"
    ],
    "wof:name":"Tokyo-Tokyo",
    "wof:placetype":"venue"
},
  "geometry": {"coordinates":[-157.77416700000001,21.271954],"type":"Point"}
}