{
  "type": "Feature",
  "properties": {
    "iso:country":"US",
    "sg:address":"680 Ala Moana Blvd",
    "sg:city":"Honolulu",
    "sg:classifiers":[
        {
            "category":"Professional",
            "subcategory":"Engineering",
            "type":"Services"
        }
    ],
    "sg:phone":"+1 808 537 1141",
    "sg:postcode":"96813",
    "sg:province":"HI",
    "wof:name":"Nance Tom Water Resource Engrg",
    "wof:placetype":"venue"
},
  "geometry": {"coordinates":[-157.86194599999999,21.297866],"type":"Point"}
}