{
  "type": "Feature",
  "properties": {
    "iso:country":"US",
    "sg:address":"1857 S King St",
    "sg:city":"Honolulu",
    "sg:classifiers":[
        {
            "category":"Real Estate",
            "subcategory":"Real Estate Agent",
            "type":"Services"
        }
    ],
    "sg:phone":"+1 808 946 2757",
    "sg:postcode":"96826",
    "sg:province":"HI",
    "sg:tags":[
        "sales"
    ],
    "wof:name":"Realty Factors Inc",
    "wof:placetype":"venue"
},
  "geometry": {"coordinates":[-157.83223100000001,21.295573],"type":"Point"}
}