{
  "type": "Feature",
  "properties": {
    "iso:country":"US",
    "sg:address":"3801 Hanapepe Rd",
    "sg:city":"Hanapepe",
    "sg:classifiers":[
        {
            "category":"Shopping",
            "type":"Retail Goods"
        }
    ],
    "sg:phone":"+1 808 335 3223",
    "sg:postcode":"96716",
    "sg:province":"HI",
    "sg:tags":[
        "art",
        "gallery",
        "dealer"
    ],
    "wof:name":"Shaning Cierras Gallery",
    "wof:placetype":"venue"
},
  "geometry": {"coordinates":[-159.58959999999999,21.9099],"type":"Point"}
}