{
  "type": "Feature",
  "properties": {
    "iso:country":"US",
    "sg:address":"307 Farrington Hwy",
    "sg:city":"Waipahu",
    "sg:classifiers":[
        {
            "category":"Restaurant",
            "type":"Food & Drink"
        }
    ],
    "sg:phone":"+1 808 678 0744",
    "sg:postcode":"96797",
    "sg:province":"HI",
    "sg:tags":[
        "caterer"
    ],
    "wof:name":"Nana Conching's Chitcharon",
    "wof:placetype":"venue"
},
  "geometry": {"coordinates":[-158.018743,21.380031],"type":"Point"}
}