{
  "type": "Feature",
  "properties": {
    "addr:full":"1190 Hikikaulia St Mililani HI 96789",
    "addr:housenumber":"1190",
    "addr:postcode":"96789",
    "addr:street":"Hikikaulia St",
    "iso:country":"US",
    "sg:address":"1190 Hikikaulia St",
    "sg:city":"Mililani",
    "sg:classifiers":[
        {
            "category":"Organizations",
            "subcategory":"Religious Organization",
            "type":"Services"
        }
    ],
    "sg:phone":"+1 808 625 1040",
    "sg:postcode":"96789",
    "sg:province":"HI",
    "wof:name":"YMCA",
    "wof:placetype":"venue"
},
  "geometry": {"coordinates":[-158.00909899999999,21.450439],"type":"Point"}
}