{
  "type": "Feature",
  "properties": {
    "iso:country":"US",
    "sg:address":"76 Keaa St",
    "sg:city":"Hilo",
    "sg:classifiers":[
        {
            "category":"Professional",
            "type":"Services"
        }
    ],
    "sg:phone":"+1 808 935 7200",
    "sg:postcode":"96720",
    "sg:province":"HI",
    "sg:tags":[
        "establishment"
    ],
    "wof:name":"Pacific Image Co",
    "wof:placetype":"venue"
},
  "geometry": {"coordinates":[-155.05870999999999,19.723292],"type":"Point"}
}