{
  "type": "Feature",
  "properties": {
    "iso:country":"US",
    "sg:address":"2411 S Kihei Rd",
    "sg:city":"Kihei",
    "sg:classifiers":[
        {
            "category":"Recreation",
            "type":"Entertainment"
        }
    ],
    "sg:phone":"+1 808 879 7449",
    "sg:postcode":"96753",
    "sg:province":"HI",
    "wof:name":"Snorkel Bobs Kapahulu Inc",
    "wof:placetype":"venue"
},
  "geometry": {"coordinates":[-156.446348,20.717624],"type":"Point"}
}