{
  "type": "Feature",
  "properties": {
    "iso:country":"US",
    "sg:address":"4569 Ahuli Pl",
    "sg:city":"Honolulu",
    "sg:classifiers":[
        {
            "category":"Manufacturing",
            "subcategory":"Rubber & Plastics",
            "type":"Manufacturing & Wholesale Goods"
        }
    ],
    "sg:phone":"+1 808 734 3292",
    "sg:postcode":"96816",
    "sg:province":"HI",
    "sg:tags":[
        "work",
        "glove"
    ],
    "wof:name":"S & D Enterprises",
    "wof:placetype":"venue"
},
  "geometry": {"coordinates":[-157.78649799999999,21.274349],"type":"Point"}
}