{
  "type": "Feature",
  "properties": {
    "iso:country":"US",
    "sg:address":"300 Ohukai Rd",
    "sg:city":"Kihei",
    "sg:classifiers":[
        {
            "category":"Building & Trades",
            "subcategory":"Electrical",
            "type":"Services"
        }
    ],
    "sg:phone":"+1 808 879 3145",
    "sg:postcode":"96753",
    "sg:province":"HI",
    "sg:tags":[
        "electric",
        "contractor"
    ],
    "wof:name":"Island Electric Maui Inc",
    "wof:placetype":"venue"
},
  "geometry": {"coordinates":[-156.454159,20.775451],"type":"Point"}
}