{
  "type": "Feature",
  "properties": {
    "iso:country":"US",
    "sg:address":"1410 Koaha Pl",
    "sg:city":"Aiea",
    "sg:classifiers":[
        {
            "category":"Professional",
            "type":"Services"
        }
    ],
    "sg:phone":"+1 808 487 8600",
    "sg:postcode":"96701",
    "sg:province":"HI",
    "sg:tags":[
        "establishment"
    ],
    "wof:name":"Global Marketing Svc",
    "wof:placetype":"venue"
},
  "geometry": {"coordinates":[-157.898619,21.377011],"type":"Point"}
}