{
  "type": "Feature",
  "properties": {
    "iso:country":"US",
    "sg:address":"2033 N King St",
    "sg:city":"Honolulu",
    "sg:classifiers":[
        {
            "category":"Restaurant",
            "type":"Food & Drink"
        }
    ],
    "sg:phone":"+1 808 841 2771",
    "sg:postcode":"96819",
    "sg:province":"HI",
    "sg:tags":[
        "eating"
    ],
    "wof:name":"Ray S Cafe",
    "wof:placetype":"venue"
},
  "geometry": {"coordinates":[-157.87921399999999,21.333349],"type":"Point"}
}