{
  "type": "Feature",
  "properties": {
    "iso:country":"US",
    "sg:address":"1114 Lunahelu Pl",
    "sg:city":"Kailua",
    "sg:classifiers":[
        {
            "category":"Health Services",
            "subcategory":"Doctor",
            "type":"Services"
        }
    ],
    "sg:phone":"+1 808 375 9018",
    "sg:postcode":"96734",
    "sg:province":"HI",
    "sg:tags":[
        "dental",
        "hygiene"
    ],
    "wof:name":"Diane L Walls Ldh",
    "wof:placetype":"venue"
},
  "geometry": {"coordinates":[-157.76870500000001,21.36703],"type":"Point"}
}