{
  "type": "Feature",
  "properties": {
    "addr:full":"2222 Citron St Honolulu HI 96826",
    "addr:housenumber":"2222",
    "addr:postcode":"96826",
    "addr:street":"Citron St",
    "iso:country":"US",
    "sg:address":"2222 Citron St",
    "sg:city":"Honolulu",
    "sg:classifiers":[
        {
            "category":"Real Estate",
            "subcategory":"Real Estate Operator",
            "type":"Services"
        }
    ],
    "sg:phone":"+1 808 955 5111",
    "sg:postcode":"96826",
    "sg:province":"HI",
    "sg:tags":[
        "building",
        "residential",
        "commercial"
    ],
    "wof:name":"Kensho USA Inc",
    "wof:placetype":"venue"
},
  "geometry": {"coordinates":[-157.82710599999999,21.290684],"type":"Point"}
}