{
  "type": "Feature",
  "properties": {
    "iso:country":"US",
    "sg:address":"2002 Home Rule St",
    "sg:city":"Honolulu",
    "sg:classifiers":[
        {
            "category":"Professional",
            "subcategory":"Engineering",
            "type":"Services"
        }
    ],
    "sg:phone":"+1 808 841 8889",
    "sg:postcode":"96819",
    "sg:province":"HI",
    "sg:tags":[
        "general",
        "contractor"
    ],
    "wof:name":"57 Builders LTD",
    "wof:placetype":"venue"
},
  "geometry": {"coordinates":[-157.88532599999999,21.325554],"type":"Point"}
}