{
  "type": "Feature",
  "properties": {
    "iso:country":"US",
    "sg:address":"1247 Kailua Rd",
    "sg:city":"Kailua",
    "sg:classifiers":[
        {
            "category":"Home & Garden",
            "subcategory":"Building Materials",
            "type":"Retail Goods"
        }
    ],
    "sg:phone":"+1 808 262 7771",
    "sg:postcode":"96734",
    "sg:province":"HI",
    "wof:name":"Kellenes Stained Glass Studio",
    "wof:placetype":"venue"
},
  "geometry": {"coordinates":[-157.75336100000001,21.383747],"type":"Point"}
}