{
  "type": "Feature",
  "properties": {
    "addr:full":"500 Alakawa St Honolulu HI 96817",
    "addr:housenumber":"500",
    "addr:postcode":"96817",
    "addr:street":"Alakawa St",
    "iso:country":"US",
    "sg:address":"500 Alakawa St",
    "sg:city":"Honolulu",
    "sg:classifiers":[
        {
            "category":"Professional",
            "subcategory":"Testing Lab",
            "type":"Services"
        }
    ],
    "sg:phone":"+1 808 848 8866",
    "sg:postcode":"96817",
    "sg:province":"HI",
    "sg:tags":[
        "laboratory"
    ],
    "wof:name":"Brewer Environmental Svc",
    "wof:placetype":"venue"
},
  "geometry": {"coordinates":[-157.87427400000001,21.317565],"type":"Point"}
}