{
  "type": "Feature",
  "properties": {
    "iso:country":"US",
    "sg:address":"1445 Kehaulani Dr",
    "sg:city":"Kailua",
    "sg:classifiers":[
        {
            "category":"Personal",
            "type":"Services"
        }
    ],
    "sg:phone":"+1 808 261 1237",
    "sg:postcode":"96734",
    "sg:province":"HI",
    "sg:tags":[
        "consultant",
        "wedding"
    ],
    "wof:name":"Global Wedding",
    "wof:placetype":"venue"
},
  "geometry": {"coordinates":[-157.714134,21.384324],"type":"Point"}
}