{
  "type": "Feature",
  "properties": {
    "iso:country":"US",
    "sg:address":"3885 Akoni Pule Hwy",
    "sg:city":"Kapaau",
    "sg:classifiers":[
        {
            "category":"Manufacturing",
            "subcategory":"Metals",
            "type":"Manufacturing & Wholesale Goods"
        }
    ],
    "sg:phone":"+1 808 889 6884",
    "sg:postcode":"96755",
    "sg:province":"HI",
    "sg:tags":[
        "tool"
    ],
    "wof:name":"Innovative Tools Inc",
    "wof:placetype":"venue"
},
  "geometry": {"coordinates":[-155.781004,20.227322],"type":"Point"}
}