{
  "type": "Feature",
  "properties": {
    "iso:country":"US",
    "sg:address":"2222 Kamehameha Hwy",
    "sg:city":"Honolulu",
    "sg:classifiers":[
        {
            "category":"Manufacturing",
            "subcategory":"Printing",
            "type":"Manufacturing & Wholesale Goods"
        }
    ],
    "sg:phone":"+1 808 836 3775",
    "sg:postcode":"96819",
    "sg:province":"HI",
    "sg:tags":[
        "laser",
        "processing",
        "datum",
        "preparation",
        "computer",
        "w"
    ],
    "wof:name":"TNT Diversified Inc",
    "wof:placetype":"venue"
},
  "geometry": {"coordinates":[-157.887145,21.332502],"type":"Point"}
}