{
  "type": "Feature",
  "properties": {
    "iso:country":"US",
    "sg:address":"94-1201 Ka Uka Blvd",
    "sg:city":"Waipahu",
    "sg:classifiers":[
        {
            "category":"Restaurant",
            "type":"Food & Drink"
        }
    ],
    "sg:menulink":"http://www.allmenus.com/hi/ewa/104854-taco-del-mar/menu/",
    "sg:phone":"+1 808 671 1117",
    "sg:postcode":"96797",
    "sg:province":"HI",
    "sg:tags":[
        "mexican"
    ],
    "wof:name":"Taco Del Mar",
    "wof:placetype":"venue"
},
  "geometry": {"coordinates":[-158.001949,21.42626],"type":"Point"}
}