{
  "type": "Feature",
  "properties": {
    "iso:country":"US",
    "sg:address":"2865 Pali Hwy",
    "sg:city":"Honolulu",
    "sg:classifiers":[
        {
            "category":"Professional",
            "type":"Services"
        }
    ],
    "sg:phone":"+1 808 595 5396",
    "sg:postcode":"96817",
    "sg:province":"HI",
    "wof:name":"Northern Pacific Services",
    "wof:placetype":"venue"
},
  "geometry": {"coordinates":[-157.838337,21.336854],"type":"Point"}
}