{
  "type": "Feature",
  "properties": {
    "addr:full":"221 Kipapa Dr Mililani HI 96789",
    "addr:housenumber":"221",
    "addr:postcode":"96789",
    "addr:street":"Kipapa Dr",
    "iso:country":"US",
    "sg:address":"221 Kipapa Dr",
    "sg:city":"Mililani",
    "sg:classifiers":[
        {
            "category":"Autos & Motor Vehicles",
            "subcategory":"Auto Supplies",
            "type":"Retail Goods"
        }
    ],
    "sg:phone":"+1 808 623 2600",
    "sg:postcode":"96789",
    "sg:province":"HI",
    "sg:tags":[
        "automobile",
        "parts"
    ],
    "wof:name":"NAPA Auto Parts",
    "wof:placetype":"venue"
},
  "geometry": {"coordinates":[-158.01588000000001,21.458431],"type":"Point"}
}