{
  "type": "Feature",
  "properties": {
    "addr:full":"29 Hekaha St Aiea HI 96701",
    "addr:housenumber":"29",
    "addr:postcode":"96701",
    "addr:street":"Hekaha St",
    "iso:country":"US",
    "sg:address":"29 Hekaha St",
    "sg:city":"Aiea",
    "sg:classifiers":[
        {
            "category":"Wholesale",
            "subcategory":"Computers",
            "type":"Manufacturing & Wholesale Goods"
        },
        {
            "category":"Wholesale",
            "subcategory":"Office Equipment",
            "type":"Manufacturing & Wholesale Goods"
        }
    ],
    "sg:phone":"+1 808 486 1100",
    "sg:postcode":"96701",
    "sg:province":"HI",
    "sg:tags":[
        "register",
        "cash",
        "supply"
    ],
    "sg:website":"www.rsihawaii.biz",
    "wof:name":"Retail Solutions Inc",
    "wof:placetype":"venue"
},
  "geometry": {"coordinates":[-157.95153400000001,21.384524],"type":"Point"}
}