{
  "type": "Feature",
  "properties": {
    "iso:country":"US",
    "sg:address":"333 Uluniu St",
    "sg:city":"Kailua",
    "sg:classifiers":[
        {
            "category":"Building & Trades",
            "subcategory":"Plumbing",
            "type":"Services"
        }
    ],
    "sg:phone":"+1 808 262 2344",
    "sg:postcode":"96734",
    "sg:province":"HI",
    "sg:tags":[
        "boiler",
        "cleaning"
    ],
    "wof:name":"Doonwood Engineering",
    "wof:placetype":"venue"
},
  "geometry": {"coordinates":[-157.74170799999999,21.397298],"type":"Point"}
}