{
  "type": "Feature",
  "properties": {
    "iso:country":"US",
    "sg:address":"1365 Kulawai St",
    "sg:city":"Aiea",
    "sg:classifiers":[
        {
            "category":"Real Estate",
            "subcategory":"Real Estate Agent",
            "type":"Services"
        }
    ],
    "sg:phone":"+1 808 488 6051",
    "sg:postcode":"96701",
    "sg:province":"HI",
    "wof:name":"DSM Appraisal Co",
    "wof:placetype":"venue"
},
  "geometry": {"coordinates":[-157.913983,21.394692],"type":"Point"}
}