{
  "type": "Feature",
  "properties": {
    "addr:full":"925 16th Ave Honolulu HI 96816",
    "addr:housenumber":"925",
    "addr:postcode":"96816",
    "addr:street":"16Th Ave",
    "iso:country":"US",
    "sg:address":"925 16th Ave",
    "sg:city":"Honolulu",
    "sg:classifiers":[
        {
            "category":"Building & Trades",
            "subcategory":"Construction",
            "type":"Services"
        }
    ],
    "sg:phone":"+1 808 732 5258",
    "sg:postcode":"96816",
    "sg:province":"HI",
    "sg:tags":[
        "house"
    ],
    "wof:name":"Olympic Construction Company",
    "wof:placetype":"venue"
},
  "geometry": {"coordinates":[-157.796134,21.276697],"type":"Point"}
}