{
  "type": "Feature",
  "properties": {
    "addr:full":"3050 Hoolako St Lihue HI 96766",
    "addr:housenumber":"3050",
    "addr:postcode":"96766",
    "addr:street":"Hoolako St",
    "iso:country":"US",
    "sg:address":"3050 Hoolako St",
    "sg:city":"Lihue",
    "sg:classifiers":[
        {
            "category":"Retail",
            "subcategory":"Auto Rental",
            "type":"Services"
        }
    ],
    "sg:phone":"+1 808 245 7741",
    "sg:postcode":"96766",
    "sg:province":"HI",
    "sg:tags":[
        "company",
        "leasing",
        "franchising"
    ],
    "wof:name":"Thrifty Car Rental",
    "wof:placetype":"venue"
},
  "geometry": {"coordinates":[-159.35951499999999,21.969451],"type":"Point"}
}