{
  "type": "Feature",
  "properties": {
    "iso:country":"US",
    "sg:address":"3820 Old Pali Rd",
    "sg:city":"Honolulu",
    "sg:classifiers":[
        {
            "category":"Shopping",
            "subcategory":"Gifts & Souvenirs",
            "type":"Retail Goods"
        }
    ],
    "sg:phone":"+1 808 595 3951",
    "sg:postcode":"96817",
    "sg:province":"HI",
    "wof:name":"Hothouse Ceramics",
    "wof:placetype":"venue"
},
  "geometry": {"coordinates":[-157.82612700000001,21.346563],"type":"Point"}
}