{
  "type": "Feature",
  "properties": {
    "addr:full":"421 S Oahu St Kahului HI 96732",
    "addr:housenumber":"421",
    "addr:postcode":"96732",
    "addr:street":"S Oahu St",
    "iso:country":"US",
    "sg:address":"421 S Oahu St",
    "sg:city":"Kahului",
    "sg:classifiers":[
        {
            "category":"Retail",
            "subcategory":"Repair Shop",
            "type":"Services"
        }
    ],
    "sg:phone":"+1 808 871 4976",
    "sg:postcode":"96732",
    "sg:province":"HI",
    "wof:name":"Split Tees",
    "wof:placetype":"venue"
},
  "geometry": {"coordinates":[-156.46681000000001,20.879559],"type":"Point"}
}