{
  "type": "Feature",
  "properties": {
    "iso:country":"US",
    "sg:address":"2970 Kalihi St",
    "sg:city":"Honolulu",
    "sg:classifiers":[
        {
            "category":"Personal",
            "subcategory":"Beauty Salon",
            "type":"Services"
        }
    ],
    "sg:phone":"+1 808 841 0731",
    "sg:postcode":"96819",
    "sg:province":"HI",
    "sg:tags":[
        "shop"
    ],
    "wof:name":"JS Beauty Shop",
    "wof:placetype":"venue"
},
  "geometry": {"coordinates":[-157.85353900000001,21.359403],"type":"Point"}
}