{
  "type": "Feature",
  "properties": {
    "iso:country":"US",
    "sg:address":"1212 University Ave",
    "sg:city":"Honolulu",
    "sg:classifiers":[
        {
            "category":"Social Services",
            "type":"Services"
        }
    ],
    "sg:phone":"+1 808 942 7922",
    "sg:postcode":"96826",
    "sg:province":"HI",
    "sg:tags":[
        "organization",
        "welfare"
    ],
    "wof:name":"Pwa Coalition Hawaii",
    "wof:placetype":"venue"
},
  "geometry": {"coordinates":[-157.82131100000001,21.293315],"type":"Point"}
}