{
  "type": "Feature",
  "properties": {
    "iso:country":"US",
    "sg:address":"934 7th Ave",
    "sg:city":"Honolulu",
    "sg:classifiers":[
        {
            "category":"Professional",
            "type":"Services"
        }
    ],
    "sg:phone":"+1 808 739 0646",
    "sg:postcode":"96816",
    "sg:province":"HI",
    "sg:tags":[
        "arts",
        "artist"
    ],
    "sg:website":"www.junogalangstudio.com",
    "wof:name":"Juno Galang Studio",
    "wof:placetype":"venue"
},
  "geometry": {"coordinates":[-157.806815,21.28194],"type":"Point"}
}