{
  "type": "Feature",
  "properties": {
    "iso:country":"US",
    "sg:address":"1188 Bishop St",
    "sg:city":"Honolulu",
    "sg:classifiers":[
        {
            "category":"Health Services",
            "subcategory":"Clinic",
            "type":"Services"
        }
    ],
    "sg:phone":"+1 808 521 1900",
    "sg:postcode":"96813",
    "sg:province":"HI",
    "sg:tags":[
        "specialty",
        "outpatient"
    ],
    "wof:name":"Harve Ballesteros & Associates",
    "wof:placetype":"venue"
},
  "geometry": {"coordinates":[-157.85939099999999,21.310095],"type":"Point"}
}