{
  "type": "Feature",
  "properties": {
    "iso:country":"US",
    "sg:address":"227 Lewers St",
    "sg:city":"Honolulu",
    "sg:classifiers":[
        {
            "category":"Shopping",
            "subcategory":"Jewelry",
            "type":"Retail Goods"
        }
    ],
    "sg:phone":"+1 808 922 5906",
    "sg:postcode":"96815",
    "sg:province":"HI",
    "wof:name":"Guey-Long Jewelry",
    "wof:placetype":"venue"
},
  "geometry": {"coordinates":[-157.83044799999999,21.279499],"type":"Point"}
}