{
  "type": "Feature",
  "properties": {
    "addr:full":"2902 E Manoa Rd Honolulu HI 96822",
    "addr:housenumber":"2902",
    "addr:postcode":"96822",
    "addr:street":"E Manoa Rd",
    "iso:country":"US",
    "sg:address":"2902 E Manoa Rd",
    "sg:city":"Honolulu",
    "sg:classifiers":[
        {
            "category":"Coffee & Tea",
            "type":"Food & Drink"
        }
    ],
    "sg:menulink":"http://www.allmenus.com/hi/honolulu/108566-starbucks-coffee/menu/",
    "sg:phone":"+1 808 988 9295",
    "sg:postcode":"96822",
    "sg:province":"HI",
    "sg:tags":[
        "american"
    ],
    "wof:name":"Starbucks Coffee",
    "wof:placetype":"venue"
},
  "geometry": {"coordinates":[-157.810348,21.30994],"type":"Point"}
}