{
  "type": "Feature",
  "properties": {
    "iso:country":"US",
    "sg:address":"1680 Kapiolani Blvd",
    "sg:city":"Honolulu",
    "sg:classifiers":[
        {
            "category":"Recreation",
            "type":"Entertainment"
        }
    ],
    "sg:phone":"+1 808 946 1343",
    "sg:postcode":"96814",
    "sg:province":"HI",
    "sg:tags":[
        "parlor",
        "billiard",
        "video",
        "game",
        "arcade"
    ],
    "sg:website":"www.hawaiianbrians.com",
    "wof:name":"Hawaiian Brian's Billiards Pro",
    "wof:placetype":"venue"
},
  "geometry": {"coordinates":[-157.838888,21.291622],"type":"Point"}
}