{
  "type": "Feature",
  "properties": {
    "iso:country":"US",
    "sg:address":"36 Laenui Pl",
    "sg:city":"Paia",
    "sg:classifiers":[
        {
            "category":"Social Services",
            "subcategory":"Child Care",
            "type":"Services"
        }
    ],
    "sg:phone":"+1 808 661 0901",
    "sg:postcode":"96779",
    "sg:province":"HI",
    "sg:tags":[
        "day"
    ],
    "wof:name":"Fresh Start Maintenance",
    "wof:placetype":"venue"
},
  "geometry": {"coordinates":[-156.37497999999999,20.918645],"type":"Point"}
}