{
  "type": "Feature",
  "properties": {
    "iso:country":"US",
    "sg:address":"811 Alua St",
    "sg:city":"Wailuku",
    "sg:classifiers":[
        {
            "category":"Retail",
            "subcategory":"Laundry & Dry Cleaning",
            "type":"Services"
        }
    ],
    "sg:phone":"+1 808 244 8810",
    "sg:postcode":"96793",
    "sg:province":"HI",
    "sg:tags":[
        "supply",
        "launderer",
        "industrial",
        "linen"
    ],
    "wof:name":"Rainbow Industrial Laundry",
    "wof:placetype":"venue"
},
  "geometry": {"coordinates":[-156.48931099999999,20.906103],"type":"Point"}
}