{
  "type": "Feature",
  "properties": {
    "addr:full":"1850 Alaweo St Honolulu HI 96821",
    "addr:housenumber":"1850",
    "addr:postcode":"96821",
    "addr:street":"Alaweo St",
    "iso:country":"US",
    "sg:address":"1850 Alaweo St",
    "sg:city":"Honolulu",
    "sg:classifiers":[
        {
            "category":"Professional",
            "subcategory":"Business Services",
            "type":"Services"
        }
    ],
    "sg:phone":"+1 808 373 4443",
    "sg:postcode":"96821",
    "sg:province":"HI",
    "wof:name":"Windward Hawaiian Dog Fan",
    "wof:placetype":"venue"
},
  "geometry": {"coordinates":[-157.764455,21.286232],"type":"Point"}
}