{
  "type": "Feature",
  "properties": {
    "iso:country":"US",
    "sg:address":"757 Kawaiahao St",
    "sg:city":"Honolulu",
    "sg:classifiers":[
        {
            "category":"Retail",
            "subcategory":"Auto Repair",
            "type":"Services"
        }
    ],
    "sg:phone":"+1 808 589 1333",
    "sg:postcode":"96813",
    "sg:province":"HI",
    "sg:tags":[
        "general"
    ],
    "wof:name":"Bavarian Motor Experts",
    "wof:placetype":"venue"
},
  "geometry": {"coordinates":[-157.85428200000001,21.298652],"type":"Point"}
}