{
  "type": "Feature",
  "properties": {
    "addr:full":"975 Kapiolani Blvd Honolulu HI 96814",
    "addr:housenumber":"975",
    "addr:postcode":"96814",
    "addr:street":"Kapiolani Blvd",
    "iso:country":"US",
    "sg:address":"975 Kapiolani Blvd",
    "sg:city":"Honolulu",
    "sg:classifiers":[
        {
            "category":"Personal",
            "subcategory":"Beauty Salon",
            "type":"Services"
        }
    ],
    "sg:phone":"+1 808 593 1770",
    "sg:postcode":"96814",
    "sg:province":"HI",
    "wof:name":"Hair & Nails By Leona",
    "wof:placetype":"venue"
},
  "geometry": {"coordinates":[-157.852068,21.298069],"type":"Point"}
}