{
  "type": "Feature",
  "properties": {
    "addr:full":"1726 Kapiolani Blvd Honolulu HI 96814",
    "addr:housenumber":"1726",
    "addr:postcode":"96814",
    "addr:street":"Kapiolani Blvd",
    "iso:country":"US",
    "sg:address":"1726 Kapiolani Blvd",
    "sg:city":"Honolulu",
    "sg:classifiers":[
        {
            "category":"Personal",
            "subcategory":"Beauty Salon",
            "type":"Services"
        }
    ],
    "sg:phone":"+1 808 942 0033",
    "sg:postcode":"96814",
    "sg:province":"HI",
    "sg:tags":[
        "treatment",
        "skin"
    ],
    "wof:name":"Aquaria-An Aveda Concept Salon",
    "wof:placetype":"venue"
},
  "geometry": {"coordinates":[-157.83668900000001,21.290684],"type":"Point"}
}