{
  "type": "Feature",
  "properties": {
    "iso:country":"US",
    "sg:address":"1815 Alaweo St",
    "sg:city":"Honolulu",
    "sg:classifiers":[
        {
            "category":"Shopping",
            "subcategory":"Clothing, Apparel, & Fashions",
            "type":"Retail Goods"
        }
    ],
    "sg:phone":"+1 808 373 9435",
    "sg:postcode":"96821",
    "sg:province":"HI",
    "sg:tags":[
        "sportswear",
        "accessory"
    ],
    "wof:name":"Yumeiya",
    "wof:placetype":"venue"
},
  "geometry": {"coordinates":[-157.762945,21.285157],"type":"Point"}
}