{
  "type": "Feature",
  "properties": {
    "iso:country":"US",
    "sg:address":"830 Punchbowl St",
    "sg:city":"Honolulu",
    "sg:classifiers":[
        {
            "category":"Government",
            "subcategory":"Office",
            "type":"Public Place"
        }
    ],
    "sg:phone":"+1 808 586 8610",
    "sg:postcode":"96813",
    "sg:province":"HI",
    "sg:tags":[
        "state",
        "inspection",
        "labor"
    ],
    "wof:name":"Hawaii Labor Relations Board",
    "wof:placetype":"venue"
},
  "geometry": {"coordinates":[-157.86024900000001,21.304027],"type":"Point"}
}