{
  "type": "Feature",
  "properties": {
    "iso:country":"US",
    "sg:address":"1970 Judd Hillside Rd",
    "sg:city":"Honolulu",
    "sg:classifiers":[
        {
            "category":"Social Services",
            "type":"Services"
        }
    ],
    "sg:phone":"+1 808 973 5683",
    "sg:postcode":"96822",
    "sg:province":"HI",
    "sg:tags":[
        "organization",
        "welfare"
    ],
    "wof:name":"Ronald Mc Donald House",
    "wof:placetype":"venue"
},
  "geometry": {"coordinates":[-157.82638600000001,21.306882],"type":"Point"}
}