{
  "type": "Feature",
  "properties": {
    "addr:full":"6177 Alii Dr Kailua Kona HI 96740",
    "addr:housenumber":"6177",
    "addr:postcode":"96740",
    "addr:street":"Alii Dr",
    "iso:country":"US",
    "sg:address":"6177 Alii Dr",
    "sg:city":"Kailua Kona",
    "sg:classifiers":[
        {
            "category":"Professional",
            "subcategory":"Advertising",
            "type":"Services"
        }
    ],
    "sg:phone":"+1 808 989 2935",
    "sg:postcode":"96740",
    "sg:province":"HI",
    "sg:tags":[
        "web"
    ],
    "wof:name":"Big Island Web Development",
    "wof:placetype":"venue"
},
  "geometry": {"coordinates":[-155.984328,19.619668],"type":"Point"}
}