{
  "type": "Feature",
  "properties": {
    "addr:full":"944 Lunaawa Pl Kailua HI 96734",
    "addr:housenumber":"944",
    "addr:postcode":"96734",
    "addr:street":"Lunaawa Pl",
    "iso:country":"US",
    "sg:address":"944 Lunaawa Pl",
    "sg:city":"Kailua",
    "sg:classifiers":[
        {
            "category":"Retail",
            "subcategory":"Auto Repair",
            "type":"Services"
        }
    ],
    "sg:phone":"+1 808 261 5611",
    "sg:postcode":"96734",
    "sg:province":"HI",
    "sg:tags":[
        "electrical",
        "contractor"
    ],
    "wof:name":"Marks Wiring Service",
    "wof:placetype":"venue"
},
  "geometry": {"coordinates":[-157.76946000000001,21.36815],"type":"Point"}
}