{
  "type": "Feature",
  "properties": {
    "iso:country":"US",
    "sg:address":"1928 Home Rule St",
    "sg:city":"Honolulu",
    "sg:classifiers":[
        {
            "category":"Wholesale",
            "subcategory":"Meat",
            "type":"Manufacturing & Wholesale Goods"
        }
    ],
    "sg:phone":"+1 808 845 1711",
    "sg:postcode":"96819",
    "sg:province":"HI",
    "sg:tags":[
        "plant",
        "packing",
        "mfg"
    ],
    "wof:name":"AMOR Nino Foods Inc",
    "wof:placetype":"venue"
},
  "geometry": {"coordinates":[-157.88592399999999,21.32608],"type":"Point"}
}