{
  "type": "Feature",
  "properties": {
    "addr:full":"33 Lono Ave Kahului HI 96732",
    "addr:housenumber":"33",
    "addr:postcode":"96732",
    "addr:street":"Lono Ave",
    "iso:country":"US",
    "sg:address":"33 Lono Ave",
    "sg:city":"Kahului",
    "sg:classifiers":[
        {
            "category":"Health Services",
            "subcategory":"Doctor",
            "type":"Services"
        }
    ],
    "sg:phone":"+1 808 877 3605",
    "sg:postcode":"96732",
    "sg:province":"HI",
    "wof:name":"Theiss  Conrad Jr DMD Inc",
    "wof:placetype":"venue"
},
  "geometry": {"coordinates":[-156.46976799999999,20.889554],"type":"Point"}
}