{
  "type": "Feature",
  "properties": {
    "iso:country":"US",
    "sg:address":"1128 Nuuanu Ave",
    "sg:city":"Honolulu",
    "sg:classifiers":[
        {
            "category":"Shopping",
            "subcategory":"Photographic Equipment",
            "type":"Retail Goods"
        },
        {
            "category":"Professional",
            "subcategory":"Art Services",
            "type":"Services"
        }
    ],
    "sg:phone":"+1 808 537 9464",
    "sg:postcode":"96817",
    "sg:province":"HI",
    "sg:tags":[
        "photographer",
        "photography"
    ],
    "wof:name":"Schechter Photography",
    "wof:placetype":"venue"
},
  "geometry": {"coordinates":[-157.86174299999999,21.311289],"type":"Point"}
}