{
  "type": "Feature",
  "properties": {
    "iso:country":"US",
    "sg:address":"3531 Mahiole Pl",
    "sg:city":"Kamuela",
    "sg:classifiers":[
        {
            "category":"Banks & Credit Unions",
            "subcategory":"Investment Brokerage",
            "type":"Services"
        }
    ],
    "sg:phone":"+1 808 882 8001",
    "sg:postcode":"96743",
    "sg:province":"HI",
    "sg:tags":[
        "management"
    ],
    "wof:name":"Rothschild Investment Corp",
    "wof:placetype":"venue"
},
  "geometry": {"coordinates":[-155.81587500000001,20.006126],"type":"Point"}
}