{
  "type": "Feature",
  "properties": {
    "iso:country":"US",
    "sg:address":"3615 Akoni Pule Hwy",
    "sg:city":"Kapaau",
    "sg:classifiers":[
        {
            "category":"Restaurant",
            "type":"Food & Drink"
        }
    ],
    "sg:phone":"+1 808 889 0208",
    "sg:postcode":"96755",
    "sg:province":"HI",
    "wof:name":"Kohala Diner",
    "wof:placetype":"venue"
},
  "geometry": {"coordinates":[-155.78034400000001,20.227171],"type":"Point"}
}