{
  "type": "Feature",
  "properties": {
    "iso:country":"US",
    "sg:address":"5629 Kuakini Hwy",
    "sg:city":"Kailua Kona",
    "sg:classifiers":[
        {
            "category":"Restaurant",
            "type":"Food & Drink"
        }
    ],
    "sg:phone":"+1 808 326 1577",
    "sg:postcode":"96740",
    "sg:province":"HI",
    "wof:name":"Mahina Pizza",
    "wof:placetype":"venue"
},
  "geometry": {"coordinates":[-155.99807300000001,19.642574],"type":"Point"}
}