{
  "type": "Feature",
  "properties": {
    "iso:country":"US",
    "sg:address":"2710 Kaaha St",
    "sg:city":"Honolulu",
    "sg:classifiers":[
        {
            "category":"Social Services",
            "type":"Services"
        }
    ],
    "sg:phone":"+1 808 946 3696",
    "sg:postcode":"96826",
    "sg:province":"HI",
    "wof:name":"Wendy L Geary",
    "wof:placetype":"venue"
},
  "geometry": {"coordinates":[-157.821877,21.287814],"type":"Point"}
}