{
  "type": "Feature",
  "properties": {
    "iso:country":"US",
    "sg:address":"919 Kulakoa St",
    "sg:city":"Waianae",
    "sg:classifiers":[
        {
            "category":"Government",
            "subcategory":"Office",
            "type":"Public Place"
        }
    ],
    "sg:phone":"+1 808 655 7182",
    "sg:postcode":"96792",
    "sg:province":"HI",
    "sg:tags":[
        "specialist",
        "production"
    ],
    "wof:name":"Lipman Melita",
    "wof:placetype":"venue"
},
  "geometry": {"coordinates":[-158.168375,21.406015],"type":"Point"}
}