{
  "type": "Feature",
  "properties": {
    "iso:country":"US",
    "sg:address":"120 Sand Island Access Rd",
    "sg:city":"Honolulu",
    "sg:classifiers":[
        {
            "category":"Restaurant",
            "type":"Food & Drink"
        }
    ],
    "sg:menulink":"http://www.allmenus.com/hi/honolulu/124059-quiznos-sub/menu/",
    "sg:phone":"+1 808 847 5600",
    "sg:postcode":"96819",
    "sg:province":"HI",
    "sg:tags":[
        "wrap",
        "american",
        "sandwich"
    ],
    "wof:name":"Quiznos Sub",
    "wof:placetype":"venue"
},
  "geometry": {"coordinates":[-157.89133200000001,21.323959],"type":"Point"}
}