{
  "type": "Feature",
  "properties": {
    "iso:country":"US",
    "sg:address":"118 Puuowaa St",
    "sg:city":"Hauula",
    "sg:classifiers":[
        {
            "category":"Professional",
            "subcategory":"Computer Services",
            "type":"Services"
        }
    ],
    "sg:phone":"+1 808 293 0412",
    "sg:postcode":"96717",
    "sg:province":"HI",
    "sg:tags":[
        "repair"
    ],
    "wof:name":"Mac At Work",
    "wof:placetype":"venue"
},
  "geometry": {"coordinates":[-157.912982,21.613132],"type":"Point"}
}