{
  "type": "Feature",
  "properties": {
    "iso:country":"US",
    "sg:address":"23 S Vineyard Blvd",
    "sg:city":"Honolulu",
    "sg:classifiers":[
        {
            "category":"Travel",
            "subcategory":"Hotels & Motels",
            "type":"Entertainment"
        }
    ],
    "sg:phone":"+1 808 521 2383",
    "sg:postcode":"96813",
    "sg:province":"HI",
    "sg:tags":[
        "operation"
    ],
    "sg:website":"www.hawaiihomestay.com",
    "wof:name":"Hawaii Homestay",
    "wof:placetype":"venue"
},
  "geometry": {"coordinates":[-157.85693699999999,21.313168],"type":"Point"}
}