{
  "type": "Feature",
  "properties": {
    "addr:full":"3123 Oihana St Lihue HI 96766",
    "addr:housenumber":"3123",
    "addr:postcode":"96766",
    "addr:street":"Oihana St",
    "iso:country":"US",
    "sg:address":"3123 Oihana St",
    "sg:city":"Lihue",
    "sg:classifiers":[
        {
            "category":"Retail",
            "subcategory":"Repair Shop",
            "type":"Services"
        },
        {
            "category":"Building & Trades",
            "subcategory":"Plumbing",
            "type":"Services"
        }
    ],
    "sg:phone":"+1 808 245 2901",
    "sg:postcode":"96766",
    "sg:province":"HI",
    "sg:tags":[
        "system",
        "air",
        "refrigeration",
        "conditioning",
        "uni",
        "contractor"
    ],
    "wof:name":"Kauai Refrigeration Svc Inc",
    "wof:placetype":"venue"
},
  "geometry": {"coordinates":[-159.35663099999999,21.970441],"type":"Point"}
}