{
  "type": "Feature",
  "properties": {
    "iso:country":"US",
    "sg:address":"32 Pohaku St",
    "sg:city":"Hilo",
    "sg:classifiers":[
        {
            "category":"Shopping",
            "subcategory":"Discount & Variety Stores",
            "type":"Retail Goods"
        }
    ],
    "sg:phone":"+1 808 934 9130",
    "sg:postcode":"96720",
    "sg:province":"HI",
    "sg:tags":[
        "merchandise",
        "general"
    ],
    "wof:name":"Budget Car Sales",
    "wof:placetype":"venue"
},
  "geometry": {"coordinates":[-155.063425,19.70295],"type":"Point"}
}