{
  "type": "Feature",
  "properties": {
    "iso:country":"US",
    "sg:address":"25 Kaneohe Bay Dr",
    "sg:city":"Kailua",
    "sg:classifiers":[
        {
            "category":"Restaurant",
            "type":"Food & Drink"
        }
    ],
    "sg:phone":"+1 808 254 6681",
    "sg:postcode":"96734",
    "sg:province":"HI",
    "wof:name":"Subway Sandwiches & Salads",
    "wof:placetype":"venue"
},
  "geometry": {"coordinates":[-157.74949899999999,21.423086],"type":"Point"}
}