{
  "type": "Feature",
  "properties": {
    "addr:full":"400 Mahalani St Wailuku HI 96793",
    "addr:housenumber":"400",
    "addr:postcode":"96793",
    "addr:street":"Mahalani St",
    "iso:country":"US",
    "sg:address":"400 Mahalani St",
    "sg:city":"Wailuku",
    "sg:classifiers":[
        {
            "category":"Organizations",
            "subcategory":"Non-profit Organization",
            "type":"Services"
        }
    ],
    "sg:phone":"+1 808 244 5555",
    "sg:postcode":"96793",
    "sg:province":"HI",
    "sg:tags":[
        "human"
    ],
    "sg:website":"www.hospicemaui.org",
    "wof:name":"Hospice Maui",
    "wof:placetype":"venue"
},
  "geometry": {"coordinates":[-156.495645,20.884896],"type":"Point"}
}