{
  "type": "Feature",
  "properties": {
    "iso:country":"US",
    "sg:address":"1389 Kilikina St",
    "sg:city":"Hilo",
    "sg:classifiers":[
        {
            "category":"Building & Trades",
            "subcategory":"Construction",
            "type":"Services"
        }
    ],
    "sg:phone":"+1 808 961 2517",
    "sg:postcode":"96720",
    "sg:province":"HI",
    "sg:tags":[
        "home",
        "general",
        "family",
        "contractor"
    ],
    "wof:name":"Kenneth Waltjen Contracting",
    "wof:placetype":"venue"
},
  "geometry": {"coordinates":[-155.12535199999999,19.711869],"type":"Point"}
}