{
  "type": "Feature",
  "properties": {
    "iso:country":"US",
    "sg:address":"150 Kapahulu Ave",
    "sg:city":"Honolulu",
    "sg:classifiers":[
        {
            "category":"Shopping",
            "subcategory":"Gifts & Souvenirs",
            "type":"Retail Goods"
        }
    ],
    "sg:phone":"+1 808 926 5156",
    "sg:postcode":"96815",
    "sg:province":"HI",
    "sg:tags":[
        "shop"
    ],
    "wof:name":"Queen's Island Gifts",
    "wof:placetype":"venue"
},
  "geometry": {"coordinates":[-157.82061999999999,21.271857],"type":"Point"}
}