{
  "type": "Feature",
  "properties": {
    "iso:country":"US",
    "sg:address":"1196 Nanilihilihi St",
    "sg:city":"Waipahu",
    "sg:classifiers":[
        {
            "category":"Retail",
            "subcategory":"Repair Shop",
            "type":"Services"
        }
    ],
    "sg:phone":"+1 808 671 2328",
    "sg:postcode":"96797",
    "sg:province":"HI",
    "sg:tags":[
        "electrical"
    ],
    "wof:name":"Toms Electrical Repair",
    "wof:placetype":"venue"
},
  "geometry": {"coordinates":[-157.99526900000001,21.419456],"type":"Point"}
}