{
  "type": "Feature",
  "properties": {
    "iso:country":"US",
    "sg:address":"415 South St",
    "sg:city":"Honolulu",
    "sg:classifiers":[
        {
            "category":"Professional",
            "type":"Services"
        }
    ],
    "sg:phone":"+1 808 545 1213",
    "sg:postcode":"96813",
    "sg:province":"HI",
    "sg:tags":[
        "establishment"
    ],
    "wof:name":"Compass Concepts",
    "wof:placetype":"venue"
},
  "geometry": {"coordinates":[-157.86107100000001,21.30085],"type":"Point"}
}