{
  "type": "Feature",
  "properties": {
    "iso:country":"US",
    "sg:address":"616 Hoomau St",
    "sg:city":"Wailuku",
    "sg:classifiers":[
        {
            "category":"Wholesale",
            "subcategory":"Auto Parts",
            "type":"Manufacturing & Wholesale Goods"
        }
    ],
    "sg:phone":"+1 808 870 3883",
    "sg:postcode":"96793",
    "sg:province":"HI",
    "sg:tags":[
        "truck",
        "accessory"
    ],
    "wof:name":"Valley Isle Campertops",
    "wof:placetype":"venue"
},
  "geometry": {"coordinates":[-156.49613400000001,20.914451],"type":"Point"}
}