{
  "type": "Feature",
  "properties": {
    "iso:country":"US",
    "sg:address":"41 E Lipoa St",
    "sg:city":"Kihei",
    "sg:classifiers":[
        {
            "category":"Banks & Credit Unions",
            "subcategory":"Bank",
            "type":"Services"
        }
    ],
    "sg:phone":"+1 808 891 2580",
    "sg:postcode":"96753",
    "sg:province":"HI",
    "sg:tags":[
        "loan",
        "real estate"
    ],
    "wof:name":"Stanton Mortgage Inc",
    "wof:placetype":"venue"
},
  "geometry": {"coordinates":[-156.454049,20.74778],"type":"Point"}
}