{
  "type": "Feature",
  "properties": {
    "iso:country":"US",
    "sg:address":"900 Fort Street Ml",
    "sg:city":"Honolulu",
    "sg:classifiers":[
        {
            "category":"Professional",
            "subcategory":"Lawyer & Legal Services",
            "type":"Services"
        }
    ],
    "sg:phone":"+1 808 528 4274",
    "sg:postcode":"96813",
    "sg:province":"HI",
    "sg:tags":[
        "attorney"
    ],
    "wof:name":"Blake Goodman",
    "wof:placetype":"venue"
},
  "geometry": {"coordinates":[-157.862101,21.309186],"type":"Point"}
}