{
  "type": "Feature",
  "properties": {
    "iso:country":"US",
    "sg:address":"1515 Hoohulu St",
    "sg:city":"Pearl City",
    "sg:classifiers":[
        {
            "category":"Recreation",
            "type":"Entertainment"
        }
    ],
    "sg:phone":"+1 808 456 1021",
    "sg:postcode":"96782",
    "sg:province":"HI",
    "wof:name":"Tok S Kwon",
    "wof:placetype":"venue"
},
  "geometry": {"coordinates":[-157.95891900000001,21.402334],"type":"Point"}
}