{
  "type": "Feature",
  "properties": {
    "addr:full":"885 Farrington Hwy Waianae HI 96792",
    "addr:housenumber":"885",
    "addr:postcode":"96792",
    "addr:street":"Farrington Hwy",
    "iso:country":"US",
    "sg:address":"885 Farrington Hwy",
    "sg:city":"Waianae",
    "sg:classifiers":[
        {
            "category":"Health Services",
            "subcategory":"Health Practitioner",
            "type":"Services"
        }
    ],
    "sg:phone":"+1 808 696 4764",
    "sg:postcode":"96792",
    "sg:province":"HI",
    "sg:tags":[
        "therapist",
        "physical"
    ],
    "sg:website":"www.firstphysical.com",
    "wof:name":"First Physical & Functional",
    "wof:placetype":"venue"
},
  "geometry": {"coordinates":[-158.21299099999999,21.464098],"type":"Point"}
}