{
  "type": "Feature",
  "properties": {
    "addr:full":"1188 Bishop St Honolulu HI 96813",
    "addr:housenumber":"1188",
    "addr:postcode":"96813",
    "addr:street":"Bishop St",
    "iso:country":"US",
    "sg:address":"1188 Bishop St",
    "sg:city":"Honolulu",
    "sg:classifiers":[
        {
            "category":"Health Services",
            "subcategory":"Doctor",
            "type":"Services"
        }
    ],
    "sg:phone":"+1 808 528 4125",
    "sg:postcode":"96813",
    "sg:province":"HI",
    "sg:tags":[
        "medical"
    ],
    "wof:name":"The Wellness Doctor",
    "wof:placetype":"venue"
},
  "geometry": {"coordinates":[-157.85939099999999,21.310095],"type":"Point"}
}