{
  "type": "Feature",
  "properties": {
    "iso:country":"US",
    "sg:address":"590 Farrington Hwy",
    "sg:city":"Kapolei",
    "sg:classifiers":[
        {
            "category":"Restaurant",
            "type":"Food & Drink"
        }
    ],
    "sg:menulink":"http://www.allmenus.com/hi/ewa/124560-quiznos-sub/menu/",
    "sg:phone":"+1 808 674 8200",
    "sg:postcode":"96707",
    "sg:province":"HI",
    "sg:tags":[
        "wrap",
        "american",
        "sandwich"
    ],
    "wof:name":"Quiznos Sub",
    "wof:placetype":"venue"
},
  "geometry": {"coordinates":[-158.079781,21.337755],"type":"Point"}
}