{
  "type": "Feature",
  "properties": {
    "addr:full":"875 Kapiolani Blvd Honolulu HI 96813",
    "addr:housenumber":"875",
    "addr:postcode":"96813",
    "addr:street":"Kapiolani Blvd",
    "iso:country":"US",
    "sg:address":"875 Kapiolani Blvd",
    "sg:city":"Honolulu",
    "sg:classifiers":[
        {
            "category":"Restaurant",
            "type":"Food & Drink"
        }
    ],
    "sg:menulink":"http://www.allmenus.com/hi/honolulu/180332-jack-in-the-box/menu/",
    "sg:phone":"+1 808 593 8076",
    "sg:postcode":"96813",
    "sg:province":"HI",
    "sg:tags":[
        "burger",
        "american"
    ],
    "wof:name":"Jack in the Box",
    "wof:placetype":"venue"
},
  "geometry": {"coordinates":[-157.853061,21.299001],"type":"Point"}
}