{
  "type": "Feature",
  "properties": {
    "iso:country":"US",
    "sg:address":"2887 Koapaka St",
    "sg:city":"Honolulu",
    "sg:classifiers":[
        {
            "category":"Freight",
            "type":"Transportation"
        }
    ],
    "sg:phone":"+1 808 841 0131",
    "sg:postcode":"96819",
    "sg:province":"HI",
    "sg:tags":[
        "arrangement"
    ],
    "wof:name":"Aloha Freight Forwarders Inc",
    "wof:placetype":"venue"
},
  "geometry": {"coordinates":[-157.905136,21.334436],"type":"Point"}
}