{
  "type": "Feature",
  "properties": {
    "addr:full":"283 Lalo St Kahului HI 96732",
    "addr:housenumber":"283",
    "addr:postcode":"96732",
    "addr:street":"Lalo St",
    "iso:country":"US",
    "sg:address":"283 Lalo St",
    "sg:city":"Kahului",
    "sg:classifiers":[
        {
            "category":"Local Transit",
            "type":"Transportation"
        }
    ],
    "sg:phone":"+1 808 877 3552",
    "sg:postcode":"96732",
    "sg:province":"HI",
    "wof:name":"Maui Kanko Svc Inc",
    "wof:placetype":"venue"
},
  "geometry": {"coordinates":[-156.458474,20.88324],"type":"Point"}
}