{
  "type": "Feature",
  "properties": {
    "iso:country":"US",
    "sg:address":"5397 Mamalahoa Hwy",
    "sg:city":"Captain Cook",
    "sg:classifiers":[
        {
            "category":"Building & Trades",
            "subcategory":"Construction",
            "type":"Services"
        }
    ],
    "sg:phone":"+1 808 523 5963",
    "sg:postcode":"96704",
    "sg:province":"HI",
    "sg:tags":[
        "paving",
        "contractor"
    ],
    "wof:name":"Kolea Paving & Sealing",
    "wof:placetype":"venue"
},
  "geometry": {"coordinates":[-155.879785,19.451759],"type":"Point"}
}