{
  "type": "Feature",
  "properties": {
    "iso:country":"US",
    "sg:address":"305 Saratoga Rd",
    "sg:city":"Honolulu",
    "sg:classifiers":[
        {
            "category":"Travel",
            "subcategory":"Hotels & Motels",
            "type":"Entertainment"
        }
    ],
    "sg:phone":"+1 808 923 5211",
    "sg:postcode":"96815",
    "sg:province":"HI",
    "sg:tags":[
        "operation"
    ],
    "wof:name":"Aloha Punawai",
    "wof:placetype":"venue"
},
  "geometry": {"coordinates":[-157.83146600000001,21.280885],"type":"Point"}
}