{
  "type": "Feature",
  "properties": {
    "addr:full":"666 N Nimitz Hwy Honolulu HI 96817",
    "addr:housenumber":"666",
    "addr:postcode":"96817",
    "addr:street":"N Nimitz Hwy",
    "iso:country":"US",
    "sg:address":"666 N Nimitz Hwy",
    "sg:city":"Honolulu",
    "sg:classifiers":[
        {
            "category":"Restaurant",
            "type":"Food & Drink"
        }
    ],
    "sg:phone":"+1 808 532 9305",
    "sg:postcode":"96817",
    "sg:province":"HI",
    "sg:tags":[
        "kitchen"
    ],
    "wof:name":"Paradise Cruise Ltd",
    "wof:placetype":"venue"
},
  "geometry": {"coordinates":[-157.86873600000001,21.314304],"type":"Point"}
}