{
  "type": "Feature",
  "properties": {
    "addr:full":"2045 Kalakaua Ave Honolulu HI 96815",
    "addr:housenumber":"2045",
    "addr:postcode":"96815",
    "addr:street":"Kalakaua Ave",
    "iso:country":"US",
    "sg:address":"2045 Kalakaua Ave",
    "sg:city":"Honolulu",
    "sg:classifiers":[
        {
            "category":"Shopping",
            "subcategory":"Jewelry",
            "type":"Retail Goods"
        }
    ],
    "sg:phone":"+1 808 946 2181",
    "sg:postcode":"96815",
    "sg:province":"HI",
    "sg:tags":[
        "jeweler"
    ],
    "wof:name":"Ohana Gift & Jewelry Inc",
    "wof:placetype":"venue"
},
  "geometry": {"coordinates":[-157.83164099999999,21.283355],"type":"Point"}
}