{
  "type": "Feature",
  "properties": {
    "iso:country":"US",
    "sg:address":"1351 Hawaii Belt Rd",
    "sg:city":"Paauilo",
    "sg:classifiers":[
        {
            "category":"Manufacturing",
            "subcategory":"Lumber",
            "type":"Manufacturing & Wholesale Goods"
        }
    ],
    "sg:phone":"+1 808 776 9900",
    "sg:postcode":"96776",
    "sg:province":"HI",
    "sg:tags":[
        "forester"
    ],
    "wof:name":"Forest Solutions Inc",
    "wof:placetype":"venue"
},
  "geometry": {"coordinates":[-155.370947,20.040656],"type":"Point"}
}