{
  "type": "Feature",
  "properties": {
    "iso:country":"US",
    "sg:address":"3133 Waialae Ave",
    "sg:city":"Honolulu",
    "sg:classifiers":[
        {
            "category":"Shopping",
            "type":"Retail Goods"
        }
    ],
    "sg:phone":"+1 808 735 0065",
    "sg:postcode":"96816",
    "sg:province":"HI",
    "sg:tags":[
        "telephone",
        "cellular"
    ],
    "wof:name":"Honolulu Wireless",
    "wof:placetype":"venue"
},
  "geometry": {"coordinates":[-157.80931000000001,21.287941],"type":"Point"}
}