{
  "type": "Feature",
  "properties": {
    "iso:country":"US",
    "sg:address":"940 Queen St",
    "sg:city":"Honolulu",
    "sg:classifiers":[
        {
            "category":"Retail",
            "subcategory":"Auto Repair",
            "type":"Services"
        }
    ],
    "sg:phone":"+1 808 596 2300",
    "sg:postcode":"96814",
    "sg:province":"HI",
    "sg:tags":[
        "glass",
        "coating",
        "tinting"
    ],
    "wof:name":"Elite Glass Tinting",
    "wof:placetype":"venue"
},
  "geometry": {"coordinates":[-157.853184,21.296378],"type":"Point"}
}