{
  "type": "Feature",
  "properties": {
    "iso:country":"US",
    "sg:address":"405 Ena Rd",
    "sg:city":"Honolulu",
    "sg:classifiers":[
        {
            "category":"Food & Beverages",
            "subcategory":"Groceries & Convenience Stores",
            "type":"Retail Goods"
        }
    ],
    "sg:phone":"+1 808 942 4550",
    "sg:postcode":"96815",
    "sg:province":"HI",
    "wof:name":"ABC Discount Store",
    "wof:placetype":"venue"
},
  "geometry": {"coordinates":[-157.835095,21.286263],"type":"Point"}
}