{
  "type": "Feature",
  "properties": {
    "iso:country":"US",
    "sg:address":"872 2nd St",
    "sg:city":"Pearl City",
    "sg:classifiers":[
        {
            "category":"Organizations",
            "subcategory":"Religious Organization",
            "type":"Services"
        }
    ],
    "sg:phone":"+1 808 456 4176",
    "sg:postcode":"96782",
    "sg:province":"HI",
    "sg:tags":[
        "synagogue"
    ],
    "wof:name":"Thai Buddhist Temple of Hawaii",
    "wof:placetype":"venue"
},
  "geometry": {"coordinates":[-157.969211,21.390901],"type":"Point"}
}