{
  "type": "Feature",
  "properties": {
    "iso:country":"US",
    "sg:address":"1455 Kulawai St",
    "sg:city":"Aiea",
    "sg:classifiers":[
        {
            "category":"Freight",
            "type":"Transportation"
        }
    ],
    "sg:phone":"+1 808 306 6391",
    "sg:postcode":"96701",
    "sg:province":"HI",
    "wof:name":"Hawaii Car Hunters LLC",
    "wof:placetype":"venue"
},
  "geometry": {"coordinates":[-157.91602499999999,21.393794],"type":"Point"}
}