{
  "type": "Feature",
  "properties": {
    "iso:country":"US",
    "sg:address":"550 Maluniu Ave",
    "sg:city":"Kailua",
    "sg:classifiers":[
        {
            "category":"Wholesale",
            "subcategory":"Machinery & Supplies",
            "type":"Manufacturing & Wholesale Goods"
        }
    ],
    "sg:phone":"+1 808 381 4683",
    "sg:postcode":"96734",
    "sg:province":"HI",
    "sg:tags":[
        "car"
    ],
    "sg:website":"www.hawaiianislandshine.com",
    "wof:name":"Hawaiian Island Shine",
    "wof:placetype":"venue"
},
  "geometry": {"coordinates":[-157.74538699999999,21.404079],"type":"Point"}
}