{
  "type": "Feature",
  "properties": {
    "iso:country":"US",
    "sg:address":"66 Queen St",
    "sg:city":"Honolulu",
    "sg:classifiers":[
        {
            "category":"Wholesale",
            "subcategory":"Meat",
            "type":"Manufacturing & Wholesale Goods"
        }
    ],
    "sg:phone":"+1 808 529 9121",
    "sg:postcode":"96813",
    "sg:province":"HI",
    "sg:tags":[
        "food",
        "live",
        "processing"
    ],
    "wof:name":"Senoaqua Food Group",
    "wof:placetype":"venue"
},
  "geometry": {"coordinates":[-157.86354700000001,21.308379],"type":"Point"}
}