{
  "type": "Feature",
  "properties": {
    "iso:country":"US",
    "sg:address":"2749 S King St",
    "sg:city":"Honolulu",
    "sg:classifiers":[
        {
            "category":"Personal",
            "subcategory":"Beauty Salon",
            "type":"Services"
        }
    ],
    "sg:phone":"+1 808 941 2993",
    "sg:postcode":"96826",
    "sg:province":"HI",
    "sg:tags":[
        "shop"
    ],
    "wof:name":"Mei Young Salon",
    "wof:placetype":"venue"
},
  "geometry": {"coordinates":[-157.820875,21.291331],"type":"Point"}
}