{
  "type": "Feature",
  "properties": {
    "addr:full":"270 Hookahi St Wailuku HI 96793",
    "addr:housenumber":"270",
    "addr:postcode":"96793",
    "addr:street":"Hookahi St",
    "iso:country":"US",
    "sg:address":"270 Hookahi St",
    "sg:city":"Wailuku",
    "sg:classifiers":[
        {
            "category":"Health Services",
            "subcategory":"Hospital",
            "type":"Services"
        }
    ],
    "sg:phone":"+1 808 243 9733",
    "sg:postcode":"96793",
    "sg:province":"HI",
    "sg:tags":[
        "general"
    ],
    "wof:name":"Castle Medical Center",
    "wof:placetype":"venue"
},
  "geometry": {"coordinates":[-156.48598000000001,20.904941],"type":"Point"}
}