{
  "type": "Feature",
  "properties": {
    "iso:country":"US",
    "sg:address":"55 Makawao Ave",
    "sg:city":"Makawao",
    "sg:classifiers":[
        {
            "category":"Health Services",
            "subcategory":"Chiropractor",
            "type":"Services"
        }
    ],
    "sg:phone":"+1 808 572 0986",
    "sg:postcode":"96768",
    "sg:province":"HI",
    "wof:name":"Ryan Chiropractic Offices",
    "wof:placetype":"venue"
},
  "geometry": {"coordinates":[-156.33186000000001,20.835165],"type":"Point"}
}