{
  "type": "Feature",
  "properties": {
    "addr:full":"570 Kawainui St Kailua HI 96734",
    "addr:housenumber":"570",
    "addr:postcode":"96734",
    "addr:street":"Kawainui St",
    "iso:country":"US",
    "sg:address":"570 Kawainui St",
    "sg:city":"Kailua",
    "sg:classifiers":[
        {
            "category":"Building & Trades",
            "subcategory":"Plumbing",
            "type":"Services"
        }
    ],
    "sg:phone":"+1 808 261 4700",
    "sg:postcode":"96734",
    "sg:province":"HI",
    "sg:tags":[
        "plumbing",
        "contractor"
    ],
    "wof:name":"Banzai Plumbing",
    "wof:placetype":"venue"
},
  "geometry": {"coordinates":[-157.746691,21.396679],"type":"Point"}
}