{
  "type": "Feature",
  "properties": {
    "iso:country":"US",
    "sg:address":"4051 Kuhio Hwy",
    "sg:city":"Lihue",
    "sg:classifiers":[
        {
            "category":"Taxi",
            "type":"Transportation"
        }
    ],
    "sg:phone":"+1 808 245 4970",
    "sg:postcode":"96766",
    "sg:province":"HI",
    "sg:tags":[
        "taxicab"
    ],
    "wof:name":"Kimo's Transportation Hawaii",
    "wof:placetype":"venue"
},
  "geometry": {"coordinates":[-159.35809,21.993109],"type":"Point"}
}