{
  "type": "Feature",
  "properties": {
    "iso:country":"US",
    "sg:address":"94-673 Kupuohi St",
    "sg:city":"Waipahu",
    "sg:classifiers":[
        {
            "category":"Restaurant",
            "type":"Food & Drink"
        }
    ],
    "sg:menulink":"http://www.allmenus.com/hi/ewa/104851-taco-del-mar/menu/",
    "sg:phone":"+1 808 676 8226",
    "sg:postcode":"96797",
    "sg:province":"HI",
    "sg:tags":[
        "mexican"
    ],
    "wof:name":"Taco Del Mar",
    "wof:placetype":"venue"
},
  "geometry": {"coordinates":[-158.032859,21.387722],"type":"Point"}
}