{
  "type": "Feature",
  "properties": {
    "iso:country":"US",
    "sg:address":"1354 Kuhio Hwy",
    "sg:city":"Kapaa",
    "sg:classifiers":[
        {
            "category":"Home & Garden",
            "subcategory":"Building Materials",
            "type":"Retail Goods"
        }
    ],
    "sg:phone":"+1 808 823 8655",
    "sg:postcode":"96746",
    "sg:province":"HI",
    "sg:tags":[
        "furniture",
        "accessory"
    ],
    "wof:name":"Marvin L Dye",
    "wof:placetype":"venue"
},
  "geometry": {"coordinates":[-159.318468,22.075824],"type":"Point"}
}