{
  "type": "Feature",
  "properties": {
    "iso:country":"US",
    "sg:address":"867 Ahua St",
    "sg:city":"Honolulu",
    "sg:classifiers":[
        {
            "category":"Manufacturing",
            "subcategory":"Metals",
            "type":"Manufacturing & Wholesale Goods"
        }
    ],
    "sg:phone":"+1 808 834 2500",
    "sg:postcode":"96819",
    "sg:province":"HI",
    "sg:tags":[
        "steel",
        "galvanized",
        "mfg"
    ],
    "wof:name":"Atlas Steel Corp",
    "wof:placetype":"venue"
},
  "geometry": {"coordinates":[-157.89635899999999,21.339892],"type":"Point"}
}