{
  "type": "Feature",
  "properties": {
    "iso:country":"US",
    "sg:address":"2424 Kalakaua Ave",
    "sg:city":"Honolulu",
    "sg:classifiers":[
        {
            "category":"Travel",
            "subcategory":"Campground",
            "type":"Entertainment"
        }
    ],
    "sg:phone":"+1 808 922 8222",
    "sg:postcode":"96815",
    "sg:province":"HI",
    "sg:tags":[
        "trailer"
    ],
    "wof:name":"KOA Gallery Inc",
    "wof:placetype":"venue"
},
  "geometry": {"coordinates":[-157.825332,21.275918],"type":"Point"}
}