{
  "type": "Feature",
  "properties": {
    "iso:country":"US",
    "sg:address":"210 Kauoha Way",
    "sg:city":"Ewa Beach",
    "sg:classifiers":[
        {
            "category":"Building & Trades",
            "subcategory":"Construction",
            "type":"Services"
        }
    ],
    "sg:phone":"+1 808 685 4200",
    "sg:postcode":"96706",
    "sg:province":"HI",
    "sg:tags":[
        "tile",
        "dealer"
    ],
    "wof:name":"Tile Man",
    "wof:placetype":"venue"
},
  "geometry": {"coordinates":[-158.01865699999999,21.335111],"type":"Point"}
}