{
  "type": "Feature",
  "properties": {
    "iso:country":"US",
    "sg:address":"211 Pali Momi St",
    "sg:city":"Aiea",
    "sg:classifiers":[
        {
            "category":"Building & Trades",
            "subcategory":"Construction",
            "type":"Services"
        }
    ],
    "sg:phone":"+1 808 487 1425",
    "sg:postcode":"96701",
    "sg:province":"HI",
    "sg:tags":[
        "house",
        "contractor"
    ],
    "wof:name":"Wong Construction",
    "wof:placetype":"venue"
},
  "geometry": {"coordinates":[-157.93754200000001,21.383234],"type":"Point"}
}