{
  "type": "Feature",
  "properties": {
    "iso:country":"US",
    "sg:address":"791 Farrington Hwy",
    "sg:city":"Waianae",
    "sg:classifiers":[
        {
            "category":"Retail",
            "subcategory":"Repair Shop",
            "type":"Services"
        }
    ],
    "sg:phone":"+1 808 696 9421",
    "sg:postcode":"96792",
    "sg:province":"HI",
    "sg:tags":[
        "hardware",
        "electrical"
    ],
    "wof:name":"Aarons Key & Safe",
    "wof:placetype":"venue"
},
  "geometry": {"coordinates":[-158.17733999999999,21.407131],"type":"Point"}
}