{
  "type": "Feature",
  "properties": {
    "addr:full":"1189 Maunakea St Honolulu HI 96817",
    "addr:housenumber":"1189",
    "addr:postcode":"96817",
    "addr:street":"Maunakea St",
    "iso:country":"US",
    "sg:address":"1189 Maunakea St",
    "sg:city":"Honolulu",
    "sg:classifiers":[
        {
            "category":"Shopping",
            "subcategory":"Florist",
            "type":"Retail Goods"
        }
    ],
    "sg:phone":"+1 808 537 2373",
    "sg:postcode":"96817",
    "sg:province":"HI",
    "sg:tags":[
        "lei",
        "flower"
    ],
    "sg:website":"www.flowerleis.net",
    "wof:name":"Maunakea Street Florist",
    "wof:placetype":"venue"
},
  "geometry": {"coordinates":[-157.861942,21.312738],"type":"Point"}
}