{
  "type": "Feature",
  "properties": {
    "iso:country":"US",
    "sg:address":"407 Coral St",
    "sg:city":"Honolulu",
    "sg:classifiers":[
        {
            "category":"Retail",
            "subcategory":"Auto Rental",
            "type":"Services"
        }
    ],
    "sg:phone":"+1 808 596 7867",
    "sg:postcode":"96813",
    "sg:province":"HI",
    "sg:tags":[
        "truck"
    ],
    "wof:name":"Storage Roon The",
    "wof:placetype":"venue"
},
  "geometry": {"coordinates":[-157.85928799999999,21.299021],"type":"Point"}
}