{
  "type": "Feature",
  "properties": {
    "addr:full":"1888 Kalakaua Ave Honolulu HI 96815",
    "addr:housenumber":"1888",
    "addr:postcode":"96815",
    "addr:street":"Kalakaua Ave",
    "iso:country":"US",
    "sg:address":"1888 Kalakaua Ave",
    "sg:city":"Honolulu",
    "sg:classifiers":[
        {
            "category":"Shopping",
            "subcategory":"Bicycles & Sporting Goods",
            "type":"Retail Goods"
        }
    ],
    "sg:phone":"+1 808 979 4978",
    "sg:postcode":"96815",
    "sg:province":"HI",
    "sg:tags":[
        "surfboard"
    ],
    "wof:name":"Wave Riding Vehicles",
    "wof:placetype":"venue"
},
  "geometry": {"coordinates":[-157.83378400000001,21.287325],"type":"Point"}
}