{
  "type": "Feature",
  "properties": {
    "iso:country":"US",
    "sg:address":"1450 Alani St",
    "sg:city":"Honolulu",
    "sg:classifiers":[
        {
            "category":"Food & Beverages",
            "subcategory":"Candy",
            "type":"Retail Goods"
        }
    ],
    "sg:phone":"+1 808 949 7200",
    "sg:postcode":"96817",
    "sg:province":"HI",
    "sg:tags":[
        "confectionery"
    ],
    "wof:name":"Crack Seed Center",
    "wof:placetype":"venue"
},
  "geometry": {"coordinates":[-157.866152,21.334201],"type":"Point"}
}