{
  "type": "Feature",
  "properties": {
    "iso:country":"US",
    "sg:address":"2606 Aaliamanu Pl",
    "sg:city":"Honolulu",
    "sg:classifiers":[
        {
            "category":"Wholesale",
            "subcategory":"Groceries",
            "type":"Manufacturing & Wholesale Goods"
        }
    ],
    "sg:phone":"+1 808 533 6656",
    "sg:postcode":"96813",
    "sg:province":"HI",
    "sg:tags":[
        "general"
    ],
    "wof:name":"Lam Brokerage Co",
    "wof:placetype":"venue"
},
  "geometry": {"coordinates":[-157.83191299999999,21.31585],"type":"Point"}
}