{
  "type": "Feature",
  "properties": {
    "addr:full":"70 Kaahumanu Ave Kahului HI 96732",
    "addr:housenumber":"70",
    "addr:postcode":"96732",
    "addr:street":"Kaahumanu Ave",
    "iso:country":"US",
    "sg:address":"70 Kaahumanu Ave",
    "sg:city":"Kahului",
    "sg:classifiers":[
        {
            "category":"Shopping",
            "subcategory":"Pharmacy",
            "type":"Retail Goods"
        },
        {
            "category":"Retail",
            "subcategory":"Photofinishing",
            "type":"Services"
        }
    ],
    "sg:phone":"+1 808 877 0041",
    "sg:postcode":"96732",
    "sg:province":"HI",
    "sg:tags":[
        "photo",
        "finishing"
    ],
    "wof:name":"Longs Drug",
    "wof:placetype":"venue"
},
  "geometry": {"coordinates":[-156.469236,20.890628],"type":"Point"}
}