{
  "type": "Feature",
  "properties": {
    "iso:country":"US",
    "sg:address":"811 Kaumana Dr",
    "sg:city":"Hilo",
    "sg:classifiers":[
        {
            "category":"Manufacturing",
            "subcategory":"Lumber",
            "type":"Manufacturing & Wholesale Goods"
        }
    ],
    "sg:phone":"+1 808 934 0502",
    "sg:postcode":"96720",
    "sg:province":"HI",
    "sg:tags":[
        "forester"
    ],
    "wof:name":"Resource Management",
    "wof:placetype":"venue"
},
  "geometry": {"coordinates":[-155.11494999999999,19.698877],"type":"Point"}
}