{
  "type": "Feature",
  "properties": {
    "iso:country":"US",
    "sg:address":"1733 Kahai St",
    "sg:city":"Honolulu",
    "sg:classifiers":[
        {
            "category":"Retail",
            "subcategory":"Auto Repair",
            "type":"Services"
        }
    ],
    "sg:phone":"+1 808 841 5009",
    "sg:postcode":"96819",
    "sg:province":"HI",
    "sg:tags":[
        "automotive",
        "station",
        "gasoline",
        "general"
    ],
    "wof:name":"Tagami Auto Service Ltd",
    "wof:placetype":"venue"
},
  "geometry": {"coordinates":[-157.88530700000001,21.323556],"type":"Point"}
}