{
  "type": "Feature",
  "properties": {
    "addr:full":"4180 Rice St Lihue HI 96766",
    "addr:housenumber":"4180",
    "addr:postcode":"96766",
    "addr:street":"Rice St",
    "iso:country":"US",
    "sg:address":"4180 Rice St",
    "sg:city":"Lihue",
    "sg:classifiers":[
        {
            "category":"Government",
            "subcategory":"Court House",
            "type":"Public Place"
        },
        {
            "category":"Government",
            "subcategory":"Office",
            "type":"Public Place"
        }
    ],
    "sg:phone":"+1 808 241 3811",
    "sg:postcode":"96766",
    "sg:province":"HI",
    "sg:tags":[
        "state",
        "resource"
    ],
    "wof:name":"Child Support Enforcement Agcy",
    "wof:placetype":"venue"
},
  "geometry": {"coordinates":[-159.36213900000001,21.970412],"type":"Point"}
}