{
  "type": "Feature",
  "properties": {
    "iso:country":"US",
    "sg:address":"1325 Halawa Valley St",
    "sg:city":"Aiea",
    "sg:classifiers":[
        {
            "category":"Manufacturing",
            "subcategory":"Food",
            "type":"Manufacturing & Wholesale Goods"
        }
    ],
    "sg:phone":"+1 808 484 1777",
    "sg:postcode":"96701",
    "sg:province":"HI",
    "sg:tags":[
        "bottler"
    ],
    "sg:website":"www.pepsi.com",
    "wof:name":"Pepsi-Cola Hawaii",
    "wof:placetype":"venue"
},
  "geometry": {"coordinates":[-157.90556900000001,21.373939],"type":"Point"}
}