{
  "type": "Feature",
  "properties": {
    "addr:full":"3903 Pili Pl Honolulu HI 96816",
    "addr:housenumber":"3903",
    "addr:postcode":"96816",
    "addr:street":"Pili Pl",
    "iso:country":"US",
    "sg:address":"3903 Pili Pl",
    "sg:city":"Honolulu",
    "sg:classifiers":[
        {
            "category":"Professional",
            "subcategory":"Art Services",
            "type":"Services"
        }
    ],
    "sg:phone":"+1 808 848 4040",
    "sg:postcode":"96816",
    "sg:province":"HI",
    "sg:tags":[
        "agency",
        "photographic"
    ],
    "wof:name":"Honolulu Photo Agency",
    "wof:placetype":"venue"
},
  "geometry": {"coordinates":[-157.787251,21.289631],"type":"Point"}
}