{
  "type": "Feature",
  "properties": {
    "iso:country":"US",
    "sg:address":"1946 Young St",
    "sg:city":"Honolulu",
    "sg:classifiers":[
        {
            "category":"Professional",
            "subcategory":"Research",
            "type":"Services"
        }
    ],
    "sg:phone":"+1 808 949 2208",
    "sg:postcode":"96826",
    "sg:province":"HI",
    "sg:tags":[
        "biomedical",
        "lab",
        "engineer"
    ],
    "wof:name":"Cellular Bio Engineering Inc",
    "wof:placetype":"venue"
},
  "geometry": {"coordinates":[-157.830545,21.296078],"type":"Point"}
}