{
  "type": "Feature",
  "properties": {
    "iso:country":"US",
    "sg:address":"3030 Hibiscus Dr",
    "sg:city":"Honolulu",
    "sg:classifiers":[
        {
            "category":"Education",
            "subcategory":"Dance Studio",
            "type":"Public Place"
        }
    ],
    "sg:phone":"+1 808 923 0446",
    "sg:postcode":"96815",
    "sg:province":"HI",
    "sg:tags":[
        "instruction",
        "dancing"
    ],
    "wof:name":"Square & Round Dance Fdrtn",
    "wof:placetype":"venue"
},
  "geometry": {"coordinates":[-157.81688199999999,21.259414],"type":"Point"}
}