{
  "type": "Feature",
  "properties": {
    "iso:country":"US",
    "sg:address":"5706 Hanama Pl",
    "sg:city":"Kailua Kona",
    "sg:classifiers":[
        {
            "category":"Health Services",
            "subcategory":"Doctor",
            "type":"Services"
        }
    ],
    "sg:phone":"+1 808 329 0080",
    "sg:postcode":"96740",
    "sg:province":"HI",
    "wof:name":"Holguin Rick DDS Msd",
    "wof:placetype":"venue"
},
  "geometry": {"coordinates":[-155.991782,19.640168],"type":"Point"}
}