{
  "type": "Feature",
  "properties": {
    "iso:country":"US",
    "sg:address":"249 Lunalilo Home Rd",
    "sg:city":"Honolulu",
    "sg:classifiers":[
        {
            "category":"Education",
            "subcategory":"Library",
            "type":"Public Place"
        }
    ],
    "sg:phone":"+1 808 397 5833",
    "sg:postcode":"96825",
    "sg:province":"HI",
    "wof:name":"Hawaii Kai Public Library",
    "wof:placetype":"venue"
},
  "geometry": {"coordinates":[-157.70454699999999,21.276125],"type":"Point"}
}