{
  "type": "Feature",
  "properties": {
    "iso:country":"US",
    "sg:address":"321 N Kuakini St",
    "sg:city":"Honolulu",
    "sg:classifiers":[
        {
            "category":"Health Services",
            "subcategory":"Doctor",
            "type":"Services"
        }
    ],
    "sg:phone":"+1 808 521 1818",
    "sg:postcode":"96817",
    "sg:province":"HI",
    "sg:tags":[
        "physician",
        "surgeon"
    ],
    "wof:name":"Roland C K Ng Inc",
    "wof:placetype":"venue"
},
  "geometry": {"coordinates":[-157.85658900000001,21.322489],"type":"Point"}
}