{
  "type": "Feature",
  "properties": {
    "iso:country":"US",
    "sg:address":"151 Kaiulani Ave",
    "sg:city":"Honolulu",
    "sg:classifiers":[
        {
            "category":"Shopping",
            "subcategory":"Clothing, Apparel, & Fashions",
            "type":"Retail Goods"
        }
    ],
    "sg:phone":"+1 808 971 6666",
    "sg:postcode":"96815",
    "sg:province":"HI",
    "sg:tags":[
        "shirt"
    ],
    "wof:name":"Crazy Shirts Inc",
    "wof:placetype":"venue"
},
  "geometry": {"coordinates":[-157.82422,21.277326],"type":"Point"}
}