{
  "type": "Feature",
  "properties": {
    "iso:country":"US",
    "sg:address":"1645 Dole St",
    "sg:city":"Honolulu",
    "sg:classifiers":[
        {
            "category":"Banks & Credit Unions",
            "subcategory":"Investment Brokerage",
            "type":"Services"
        }
    ],
    "sg:phone":"+1 808 946 1667",
    "sg:postcode":"96822",
    "sg:province":"HI",
    "sg:tags":[
        "merchant",
        "banking"
    ],
    "wof:name":"International Finance Group",
    "wof:placetype":"venue"
},
  "geometry": {"coordinates":[-157.83293,21.301589],"type":"Point"}
}