{
  "type": "Feature",
  "properties": {
    "addr:full":"317 Lehua St Hilo HI 96720",
    "addr:housenumber":"317",
    "addr:postcode":"96720",
    "addr:street":"Lehua St",
    "iso:country":"US",
    "sg:address":"317 Lehua St",
    "sg:city":"Hilo",
    "sg:classifiers":[
        {
            "category":"Social Services",
            "subcategory":"Child Care",
            "type":"Services"
        }
    ],
    "sg:phone":"+1 808 934 0150",
    "sg:postcode":"96720",
    "sg:province":"HI",
    "wof:name":"Paradise Preschool",
    "wof:placetype":"venue"
},
  "geometry": {"coordinates":[-155.09025500000001,19.730357],"type":"Point"}
}