{
  "type": "Feature",
  "properties": {
    "iso:country":"US",
    "sg:address":"274 Waianuenue Ave",
    "sg:city":"Hilo",
    "sg:classifiers":[
        {
            "category":"Insurance",
            "subcategory":"Insurance Agent",
            "type":"Services"
        }
    ],
    "sg:phone":"+1 808 935 4455",
    "sg:postcode":"96720",
    "sg:province":"HI",
    "wof:name":"State Farm Insurance",
    "wof:placetype":"venue"
},
  "geometry": {"coordinates":[-155.090339,19.724564],"type":"Point"}
}