{
  "type": "Feature",
  "properties": {
    "addr:full":"193 Farrington Hwy Waipahu HI 96797",
    "addr:housenumber":"193",
    "addr:postcode":"96797",
    "addr:street":"Farrington Hwy",
    "iso:country":"US",
    "sg:address":"193 Farrington Hwy",
    "sg:city":"Waipahu",
    "sg:classifiers":[
        {
            "category":"Autos & Motor Vehicles",
            "subcategory":"Auto Supplies",
            "type":"Retail Goods"
        }
    ],
    "sg:phone":"+1 808 678 8669",
    "sg:postcode":"96797",
    "sg:province":"HI",
    "sg:tags":[
        "automobile",
        "parts"
    ],
    "wof:name":"Checker Auto Parts 1731",
    "wof:placetype":"venue"
},
  "geometry": {"coordinates":[-158.02307099999999,21.377841],"type":"Point"}
}