{
  "type": "Feature",
  "properties": {
    "iso:country":"US",
    "sg:address":"2161 N School St",
    "sg:city":"Honolulu",
    "sg:classifiers":[
        {
            "category":"Wholesale",
            "subcategory":"Non-durable Goods",
            "type":"Manufacturing & Wholesale Goods"
        }
    ],
    "sg:phone":"+1 808 848 4825",
    "sg:postcode":"96819",
    "sg:province":"HI",
    "sg:tags":[
        "fabric"
    ],
    "wof:name":"June Fabrics Co Inc",
    "wof:placetype":"venue"
},
  "geometry": {"coordinates":[-157.87338299999999,21.339473],"type":"Point"}
}