{
  "type": "Feature",
  "properties": {
    "iso:country":"US",
    "sg:address":"211 Leihua St",
    "sg:city":"Waianae",
    "sg:classifiers":[
        {
            "category":"Personal",
            "type":"Services"
        }
    ],
    "sg:phone":"+1 808 696 9914",
    "sg:postcode":"96792",
    "sg:province":"HI",
    "sg:tags":[
        "home",
        "maintenance",
        "improvement"
    ],
    "wof:name":"E & T Home Improvement & Maint",
    "wof:placetype":"venue"
},
  "geometry": {"coordinates":[-158.18018000000001,21.437303],"type":"Point"}
}