{
  "type": "Feature",
  "properties": {
    "iso:country":"US",
    "sg:address":"2020 S King St",
    "sg:city":"Honolulu",
    "sg:classifiers":[
        {
            "category":"Real Estate",
            "subcategory":"Architect",
            "type":"Services"
        }
    ],
    "sg:phone":"+1 808 949 1601",
    "sg:postcode":"96826",
    "sg:province":"HI",
    "sg:website":"www.pacarchitects.com",
    "wof:name":"Pacific Architects Inc",
    "wof:placetype":"venue"
},
  "geometry": {"coordinates":[-157.829376,21.294698],"type":"Point"}
}