{
  "type": "Feature",
  "properties": {
    "iso:country":"US",
    "sg:address":"1682 Nahele St",
    "sg:city":"Aiea",
    "sg:classifiers":[
        {
            "category":"Wholesale",
            "subcategory":"Electrical",
            "type":"Manufacturing & Wholesale Goods"
        }
    ],
    "sg:phone":"+1 808 488 7170",
    "sg:postcode":"96701",
    "sg:province":"HI",
    "sg:tags":[
        "alarm",
        "burglar",
        "system"
    ],
    "wof:name":"Ideal Home Improvements",
    "wof:placetype":"venue"
},
  "geometry": {"coordinates":[-157.946361,21.404577],"type":"Point"}
}