{
  "type": "Feature",
  "properties": {
    "addr:full":"412 Iliwahi Loop Kailua HI 96734",
    "addr:housenumber":"412",
    "addr:postcode":"96734",
    "addr:street":"Iliwahi Loop",
    "iso:country":"US",
    "sg:address":"412 Iliwahi Loop",
    "sg:city":"Kailua",
    "sg:classifiers":[
        {
            "category":"Professional",
            "subcategory":"Management & Consulting",
            "type":"Services"
        }
    ],
    "sg:phone":"+1 808 254 3363",
    "sg:postcode":"96734",
    "sg:province":"HI",
    "sg:tags":[
        "business"
    ],
    "wof:name":"Bill Huntoon Inc",
    "wof:placetype":"venue"
},
  "geometry": {"coordinates":[-157.75303500000001,21.417359],"type":"Point"}
}