{
  "type": "Feature",
  "properties": {
    "iso:country":"US",
    "sg:address":"43 Oneawa St",
    "sg:city":"Kailua",
    "sg:classifiers":[
        {
            "category":"Organizations",
            "subcategory":"Religious Organization",
            "type":"Services"
        }
    ],
    "sg:phone":"+1 808 261 5975",
    "sg:postcode":"96734",
    "sg:province":"HI",
    "sg:tags":[
        "church"
    ],
    "sg:website":"www.newhope-windward.org",
    "wof:name":"New Hope Windward Christian Fe",
    "wof:placetype":"venue"
},
  "geometry": {"coordinates":[-157.74433099999999,21.395335],"type":"Point"}
}