{
  "type": "Feature",
  "properties": {
    "addr:full":"789 Papipi Rd Ewa Beach HI 96706",
    "addr:housenumber":"789",
    "addr:postcode":"96706",
    "addr:street":"Papipi Rd",
    "iso:country":"US",
    "sg:address":"789 Papipi Rd",
    "sg:city":"Ewa Beach",
    "sg:classifiers":[
        {
            "category":"Personal",
            "subcategory":"Barber",
            "type":"Services"
        }
    ],
    "sg:phone":"+1 808 689 0700",
    "sg:postcode":"96706",
    "sg:province":"HI",
    "wof:name":"Hair Hut",
    "wof:placetype":"venue"
},
  "geometry": {"coordinates":[-158.013398,21.315948],"type":"Point"}
}