{
  "type": "Feature",
  "properties": {
    "addr:full":"735 Iwilei Rd Honolulu HI 96817",
    "addr:housenumber":"735",
    "addr:postcode":"96817",
    "addr:street":"Iwilei Rd",
    "iso:country":"US",
    "sg:address":"735 Iwilei Rd",
    "sg:city":"Honolulu",
    "sg:classifiers":[
        {
            "category":"Cinema",
            "subcategory":"Movie Theater",
            "type":"Entertainment"
        }
    ],
    "sg:phone":"+1 808 526 3456",
    "sg:postcode":"96817",
    "sg:province":"HI",
    "wof:name":"Signature Theatres",
    "wof:placetype":"venue"
},
  "geometry": {"coordinates":[-157.87059400000001,21.316112],"type":"Point"}
}