{
  "type": "Feature",
  "properties": {
    "iso:country":"US",
    "sg:address":"4471 Honoapiilani Hwy",
    "sg:city":"Lahaina",
    "sg:classifiers":[
        {
            "category":"Real Estate",
            "subcategory":"Real Estate Agent",
            "type":"Services"
        }
    ],
    "sg:phone":"+1 808 669 5455",
    "sg:postcode":"96761",
    "sg:province":"HI",
    "wof:name":"Nobles Hawaii Real Estate",
    "wof:placetype":"venue"
},
  "geometry": {"coordinates":[-156.67583400000001,20.975451],"type":"Point"}
}