{
  "type": "Feature",
  "properties": {
    "addr:full":"28 Hana Hwy Paia HI 96779",
    "addr:housenumber":"28",
    "addr:postcode":"96779",
    "addr:street":"Hana Hwy",
    "iso:country":"US",
    "sg:address":"28 Hana Hwy",
    "sg:city":"Paia",
    "sg:classifiers":[
        {
            "category":"Social Services",
            "type":"Services"
        }
    ],
    "sg:phone":"+1 808 579 8354",
    "sg:postcode":"96779",
    "sg:province":"HI",
    "sg:tags":[
        "youth",
        "organization",
        "center"
    ],
    "wof:name":"Paia Youth & Culture Ctr",
    "wof:placetype":"venue"
},
  "geometry": {"coordinates":[-156.388105,20.913197],"type":"Point"}
}