{
  "type": "Feature",
  "properties": {
    "iso:country":"US",
    "sg:address":"534 Olive Ave",
    "sg:city":"Wahiawa",
    "sg:classifiers":[
        {
            "category":"Bars & Pubs",
            "type":"Food & Drink"
        }
    ],
    "sg:phone":"+1 808 621 6944",
    "sg:postcode":"96786",
    "sg:province":"HI",
    "sg:tags":[
        "lounge",
        "cocktail"
    ],
    "wof:name":"Rosa's Ice Tee",
    "wof:placetype":"venue"
},
  "geometry": {"coordinates":[-158.028955,21.494642],"type":"Point"}
}