{
  "type": "Feature",
  "properties": {
    "addr:full":"1491 S King St Honolulu HI 96814",
    "addr:housenumber":"1491",
    "addr:postcode":"96814",
    "addr:street":"S King St",
    "iso:country":"US",
    "sg:address":"1491 S King St",
    "sg:city":"Honolulu",
    "sg:classifiers":[
        {
            "category":"Education",
            "subcategory":"Dance Studio",
            "type":"Public Place"
        }
    ],
    "sg:phone":"+1 808 946 8885",
    "sg:postcode":"96814",
    "sg:province":"HI",
    "sg:tags":[
        "instruction",
        "dancing"
    ],
    "wof:name":"Traditional Korean Dance Inst",
    "wof:placetype":"venue"
},
  "geometry": {"coordinates":[-157.83703499999999,21.297351],"type":"Point"}
}