{
  "type": "Feature",
  "properties": {
    "iso:country":"US",
    "sg:address":"2973 Kele St",
    "sg:city":"Lihue",
    "sg:classifiers":[
        {
            "category":"Banks & Credit Unions",
            "subcategory":"Bank",
            "type":"Services"
        }
    ],
    "sg:phone":"+1 808 245 2712",
    "sg:postcode":"96766",
    "sg:province":"HI",
    "wof:name":"Lihue Credit Union",
    "wof:placetype":"venue"
},
  "geometry": {"coordinates":[-159.369291,21.974849],"type":"Point"}
}