{
  "type": "Feature",
  "properties": {
    "iso:country":"US",
    "sg:address":"4400 Kalanianaole Hwy",
    "sg:city":"Honolulu",
    "sg:classifiers":[
        {
            "category":"Manufacturing",
            "subcategory":"Food",
            "type":"Manufacturing & Wholesale Goods"
        }
    ],
    "sg:phone":"+1 808 235 5171",
    "sg:postcode":"96821",
    "sg:province":"HI",
    "sg:tags":[
        "bakery",
        "prod",
        "cookie"
    ],
    "wof:name":"Love's Bakery",
    "wof:placetype":"venue"
},
  "geometry": {"coordinates":[-157.780869,21.277948],"type":"Point"}
}