{
  "type": "Feature",
  "properties": {
    "iso:country":"US",
    "sg:address":"4244 Kilauea Rd",
    "sg:city":"Kilauea",
    "sg:classifiers":[
        {
            "category":"Shopping",
            "subcategory":"Music",
            "type":"Retail Goods"
        },
        {
            "category":"Cinema",
            "subcategory":"Movie Rental",
            "type":"Entertainment"
        }
    ],
    "sg:phone":"+1 808 828 0128",
    "sg:postcode":"96754",
    "sg:province":"HI",
    "sg:tags":[
        "leasing",
        "video",
        "disc",
        "tape"
    ],
    "wof:name":"Kilauea Video",
    "wof:placetype":"venue"
},
  "geometry": {"coordinates":[-159.40809200000001,22.211078],"type":"Point"}
}