{
  "type": "Feature",
  "properties": {
    "addr:full":"3814 Hanapepe Rd Hanapepe HI 96716",
    "addr:housenumber":"3814",
    "addr:postcode":"96716",
    "addr:street":"Hanapepe Rd",
    "iso:country":"US",
    "sg:address":"3814 Hanapepe Rd",
    "sg:city":"Hanapepe",
    "sg:classifiers":[
        {
            "category":"Arts & Performance",
            "subcategory":"Theater",
            "type":"Entertainment"
        }
    ],
    "sg:phone":"+1 808 335 0712",
    "sg:postcode":"96716",
    "sg:province":"HI",
    "sg:tags":[
        "television",
        "program",
        "producer"
    ],
    "wof:name":"Storybook Theatre Of Hawaii",
    "wof:placetype":"venue"
},
  "geometry": {"coordinates":[-159.58631,21.911359],"type":"Point"}
}