{
  "type": "Feature",
  "properties": {
    "iso:country":"US",
    "sg:address":"1200 Ala Moana Blvd",
    "sg:city":"Honolulu",
    "sg:classifiers":[
        {
            "category":"Shopping",
            "subcategory":"Gifts & Souvenirs",
            "type":"Retail Goods"
        }
    ],
    "sg:phone":"+1 808 593 2133",
    "sg:postcode":"96814",
    "sg:province":"HI",
    "sg:tags":[
        "shop"
    ],
    "sg:website":"www.hawaiianaccessories.com",
    "wof:name":"Hawaiian Accessories Inc",
    "wof:placetype":"venue"
},
  "geometry": {"coordinates":[-157.848668,21.291408],"type":"Point"}
}