{
  "type": "Feature",
  "properties": {
    "iso:country":"US",
    "sg:address":"1400 Auina Rd",
    "sg:city":"Pahoa",
    "sg:classifiers":[
        {
            "category":"Farming",
            "subcategory":"Nursery",
            "type":"Manufacturing & Wholesale Goods"
        }
    ],
    "sg:phone":"+1 808 965 9299",
    "sg:postcode":"96778",
    "sg:province":"HI",
    "sg:tags":[
        "greenhouse"
    ],
    "wof:name":"Pacific Paradise Orchids",
    "wof:placetype":"venue"
},
  "geometry": {"coordinates":[-154.95093,19.512075],"type":"Point"}
}