{
  "type": "Feature",
  "properties": {
    "addr:full":"515 Ukee St Waipahu HI 96797",
    "addr:housenumber":"515",
    "addr:postcode":"96797",
    "addr:street":"Ukee St",
    "iso:country":"US",
    "sg:address":"515 Ukee St",
    "sg:city":"Waipahu",
    "sg:classifiers":[
        {
            "category":"Professional",
            "subcategory":"Business Services",
            "type":"Services"
        },
        {
            "category":"Manufacturing",
            "subcategory":"Printing",
            "type":"Manufacturing & Wholesale Goods"
        }
    ],
    "sg:phone":"+1 808 678 3010",
    "sg:postcode":"96797",
    "sg:province":"HI",
    "sg:tags":[
        "multimedia"
    ],
    "wof:name":"Excite Media Group LLC",
    "wof:placetype":"venue"
},
  "geometry": {"coordinates":[-158.00488899999999,21.420438],"type":"Point"}
}