{
  "type": "Feature",
  "properties": {
    "iso:country":"US",
    "sg:address":"360 Kamanelo Pl",
    "sg:city":"Hilo",
    "sg:classifiers":[
        {
            "category":"Wholesale",
            "subcategory":"Dairy",
            "type":"Manufacturing & Wholesale Goods"
        }
    ],
    "sg:phone":"+1 808 959 5959",
    "sg:postcode":"96720",
    "sg:province":"HI",
    "sg:tags":[
        "frozen",
        "dessert",
        "ice",
        "cream"
    ],
    "wof:name":"Hilo Homemade Ice Cream",
    "wof:placetype":"venue"
},
  "geometry": {"coordinates":[-155.08739199999999,19.677127],"type":"Point"}
}