{
  "type": "Feature",
  "properties": {
    "iso:country":"US",
    "sg:address":"405 N Kuakini St",
    "sg:city":"Honolulu",
    "sg:classifiers":[
        {
            "category":"Health Services",
            "subcategory":"Doctor",
            "type":"Services"
        }
    ],
    "sg:phone":"+1 808 440 1141",
    "sg:postcode":"96817",
    "sg:province":"HI",
    "sg:tags":[
        "physician",
        "surgeon"
    ],
    "wof:name":"Yoshio Futatsugi MD",
    "wof:placetype":"venue"
},
  "geometry": {"coordinates":[-157.85683499999999,21.322754],"type":"Point"}
}