{
  "type": "Feature",
  "properties": {
    "iso:country":"US",
    "sg:address":"456 Kamehameha Hwy",
    "sg:city":"Waialua",
    "sg:classifiers":[
        {
            "category":"Shopping",
            "subcategory":"Bicycles & Sporting Goods",
            "type":"Retail Goods"
        }
    ],
    "sg:phone":"+1 808 637 7946",
    "sg:postcode":"96712",
    "sg:province":"HI",
    "sg:tags":[
        "equipment",
        "diver",
        "supply"
    ],
    "wof:name":"Flippers Scuba",
    "wof:placetype":"venue"
},
  "geometry": {"coordinates":[-158.10504800000001,21.581061],"type":"Point"}
}