{
  "type": "Feature",
  "properties": {
    "addr:full":"1005 Moanalua Rd Aiea HI 96701",
    "addr:housenumber":"1005",
    "addr:postcode":"96701",
    "addr:street":"Moanalua Rd",
    "iso:country":"US",
    "sg:address":"1005 Moanalua Rd",
    "sg:city":"Aiea",
    "sg:classifiers":[
        {
            "category":"Shopping",
            "subcategory":"Gifts & Souvenirs",
            "type":"Retail Goods"
        }
    ],
    "sg:phone":"+1 808 484 0226",
    "sg:postcode":"96701",
    "sg:province":"HI",
    "sg:tags":[
        "shop"
    ],
    "wof:name":"Spencer Gifts",
    "wof:placetype":"venue"
},
  "geometry": {"coordinates":[-157.94079500000001,21.385893],"type":"Point"}
}