{
  "type": "Feature",
  "properties": {
    "iso:country":"US",
    "sg:address":"595 Kupuohi St",
    "sg:city":"Waipahu",
    "sg:classifiers":[
        {
            "category":"Insurance",
            "subcategory":"Insurance Agent",
            "type":"Services"
        }
    ],
    "sg:phone":"+1 808 533 2444",
    "sg:postcode":"96797",
    "sg:province":"HI",
    "wof:name":"AIG Hawaii",
    "wof:placetype":"venue"
},
  "geometry": {"coordinates":[-158.032805,21.393183],"type":"Point"}
}