{
  "type": "Feature",
  "properties": {
    "iso:country":"US",
    "sg:address":"1440 Ward Ave",
    "sg:city":"Honolulu",
    "sg:classifiers":[
        {
            "category":"Real Estate",
            "subcategory":"Real Estate Operator",
            "type":"Services"
        }
    ],
    "sg:phone":"+1 808 533 4048",
    "sg:postcode":"96822",
    "sg:province":"HI",
    "sg:tags":[
        "condominium"
    ],
    "wof:name":"Aoao Ward Villa",
    "wof:placetype":"venue"
},
  "geometry": {"coordinates":[-157.84806599999999,21.307318],"type":"Point"}
}