{
  "type": "Feature",
  "properties": {
    "addr:full":"811 Cedar St Honolulu HI 96814",
    "addr:housenumber":"811",
    "addr:postcode":"96814",
    "addr:street":"Cedar St",
    "iso:country":"US",
    "sg:address":"811 Cedar St",
    "sg:city":"Honolulu",
    "sg:classifiers":[
        {
            "category":"Manufacturing",
            "subcategory":"Printing",
            "type":"Manufacturing & Wholesale Goods"
        }
    ],
    "sg:phone":"+1 808 593 8088",
    "sg:postcode":"96814",
    "sg:province":"HI",
    "sg:tags":[
        "commercial",
        "offset"
    ],
    "wof:name":"Budget Color Litho Inc",
    "wof:placetype":"venue"
},
  "geometry": {"coordinates":[-157.842376,21.297731],"type":"Point"}
}