{
  "type": "Feature",
  "properties": {
    "iso:country":"US",
    "sg:address":"339 Molokai Hema St",
    "sg:city":"Kahului",
    "sg:classifiers":[
        {
            "category":"Wholesale",
            "subcategory":"Office Equipment",
            "type":"Manufacturing & Wholesale Goods"
        }
    ],
    "sg:phone":"+1 800 272 2566",
    "sg:postcode":"96732",
    "sg:province":"HI",
    "wof:name":"Monroe Savin Corp",
    "wof:placetype":"venue"
},
  "geometry": {"coordinates":[-156.47194200000001,20.881134],"type":"Point"}
}