{
  "type": "Feature",
  "properties": {
    "iso:country":"US",
    "sg:address":"290 Ailana Pl",
    "sg:city":"Kihei",
    "sg:classifiers":[
        {
            "category":"Shopping",
            "type":"Retail Goods"
        }
    ],
    "sg:phone":"+1 808 873 7522",
    "sg:postcode":"96753",
    "sg:province":"HI",
    "sg:tags":[
        "merchandise"
    ],
    "wof:name":"Tekworx Inc",
    "wof:placetype":"venue"
},
  "geometry": {"coordinates":[-156.45331999999999,20.781617],"type":"Point"}
}