{
  "type": "Feature",
  "properties": {
    "iso:country":"US",
    "sg:address":"1022 Akoko St",
    "sg:city":"Honolulu",
    "sg:classifiers":[
        {
            "category":"Wholesale",
            "subcategory":"Office Equipment",
            "type":"Manufacturing & Wholesale Goods"
        },
        {
            "category":"Shopping",
            "type":"Retail Goods"
        }
    ],
    "sg:phone":"+1 808 589 1986",
    "sg:postcode":"96814",
    "sg:province":"HI",
    "sg:tags":[
        "repair",
        "business",
        "supply",
        "register",
        "cash",
        "machine"
    ],
    "wof:name":"Cash Registers Systems Inc",
    "wof:placetype":"venue"
},
  "geometry": {"coordinates":[-157.841688,21.299915],"type":"Point"}
}