{
  "type": "Feature",
  "properties": {
    "iso:country":"US",
    "sg:address":"505 Ulukanu St",
    "sg:city":"Kailua",
    "sg:classifiers":[
        {
            "category":"Professional",
            "subcategory":"Management & Consulting",
            "type":"Services"
        }
    ],
    "sg:phone":"+1 808 263 4610",
    "sg:postcode":"96734",
    "sg:province":"HI",
    "sg:tags":[
        "business"
    ],
    "wof:name":"Today The World",
    "wof:placetype":"venue"
},
  "geometry": {"coordinates":[-157.755246,21.378477],"type":"Point"}
}