{
  "type": "Feature",
  "properties": {
    "iso:country":"US",
    "sg:address":"1971 Alaeloa St",
    "sg:city":"Honolulu",
    "sg:classifiers":[
        {
            "category":"Professional",
            "type":"Services"
        }
    ],
    "sg:phone":"+1 808 754 1991",
    "sg:postcode":"96821",
    "sg:province":"HI",
    "wof:name":"Charles Mattoch Design",
    "wof:placetype":"venue"
},
  "geometry": {"coordinates":[-157.777253,21.291342],"type":"Point"}
}