{
  "type": "Feature",
  "properties": {
    "iso:country":"US",
    "sg:address":"760 Copp Rd",
    "sg:city":"Kula",
    "sg:classifiers":[
        {
            "category":"Shopping",
            "subcategory":"Florist",
            "type":"Retail Goods"
        }
    ],
    "sg:phone":"+1 808 661 1111",
    "sg:postcode":"96790",
    "sg:province":"HI",
    "sg:tags":[
        "tropical",
        "video"
    ],
    "wof:name":"Maui Floral",
    "wof:placetype":"venue"
},
  "geometry": {"coordinates":[-156.31743900000001,20.750508],"type":"Point"}
}