{
  "type": "Feature",
  "properties": {
    "addr:full":"153 Alamaha St Kahului HI 96732",
    "addr:housenumber":"153",
    "addr:postcode":"96732",
    "addr:street":"Alamaha St",
    "iso:country":"US",
    "sg:address":"153 Alamaha St",
    "sg:city":"Kahului",
    "sg:classifiers":[
        {
            "category":"Home & Garden",
            "subcategory":"Building Materials",
            "type":"Retail Goods"
        },
        {
            "category":"Retail",
            "subcategory":"Auto Repair",
            "type":"Services"
        }
    ],
    "sg:phone":"+1 808 871 7921",
    "sg:postcode":"96732",
    "sg:province":"HI",
    "sg:tags":[
        "plate",
        "window",
        "replacement",
        "glass",
        "automotive"
    ],
    "wof:name":"Ace Auto Glass Inc",
    "wof:placetype":"venue"
},
  "geometry": {"coordinates":[-156.46223000000001,20.88941],"type":"Point"}
}