{
  "type": "Feature",
  "properties": {
    "iso:country":"US",
    "sg:address":"1467 S King St",
    "sg:city":"Honolulu",
    "sg:classifiers":[
        {
            "category":"Food & Beverages",
            "subcategory":"Fruits & Vegetables",
            "type":"Retail Goods"
        }
    ],
    "sg:phone":"+1 808 949 2251",
    "sg:postcode":"96814",
    "sg:province":"HI",
    "sg:tags":[
        "produce"
    ],
    "wof:name":"Cookie's Crackseed Store",
    "wof:placetype":"venue"
},
  "geometry": {"coordinates":[-157.83970099999999,21.298239],"type":"Point"}
}