{
  "type": "Feature",
  "properties": {
    "addr:full":"120 W Kane St Kahului HI 96732",
    "addr:housenumber":"120",
    "addr:postcode":"96732",
    "addr:street":"W Kane St",
    "iso:country":"US",
    "sg:address":"120 W Kane St",
    "sg:city":"Kahului",
    "sg:classifiers":[
        {
            "category":"Manufacturing",
            "subcategory":"Food",
            "type":"Manufacturing & Wholesale Goods"
        }
    ],
    "sg:phone":"+1 808 877 0044",
    "sg:postcode":"96732",
    "sg:province":"HI",
    "sg:tags":[
        "product",
        "manufacturer"
    ],
    "wof:name":"Maui Cattle Co LLC",
    "wof:placetype":"venue"
},
  "geometry": {"coordinates":[-156.46893299999999,20.886276],"type":"Point"}
}