{
  "type": "Feature",
  "properties": {
    "addr:full":"25 Holua Way Wahiawa HI 96786",
    "addr:housenumber":"25",
    "addr:postcode":"96786",
    "addr:street":"Holua Way",
    "iso:country":"US",
    "sg:address":"25 Holua Way",
    "sg:city":"Wahiawa",
    "sg:classifiers":[
        {
            "category":"Utilities",
            "subcategory":"Telephone",
            "type":"Services"
        }
    ],
    "sg:phone":"+1 808 622 0333",
    "sg:postcode":"96786",
    "sg:province":"HI",
    "sg:tags":[
        "messaging",
        "voice",
        "equipment"
    ],
    "wof:name":"Affordable Computer Svc",
    "wof:placetype":"venue"
},
  "geometry": {"coordinates":[-158.00286199999999,21.504952],"type":"Point"}
}