{
  "type": "Feature",
  "properties": {
    "iso:country":"US",
    "sg:address":"820 Kaheka St",
    "sg:city":"Honolulu",
    "sg:classifiers":[
        {
            "category":"Shopping",
            "subcategory":"Books",
            "type":"Retail Goods"
        }
    ],
    "sg:phone":"+1 808 946 8099",
    "sg:postcode":"96814",
    "sg:province":"HI",
    "sg:tags":[
        "dealer"
    ],
    "wof:name":"A-Back Hawaii",
    "wof:placetype":"venue"
},
  "geometry": {"coordinates":[-157.83951099999999,21.292787],"type":"Point"}
}