{
  "type": "Feature",
  "properties": {
    "iso:country":"US",
    "sg:address":"3357 Maunaloa Ave",
    "sg:city":"Honolulu",
    "sg:classifiers":[
        {
            "category":"Retail",
            "subcategory":"Auto Repair",
            "type":"Services"
        }
    ],
    "sg:phone":"+1 808 732 0219",
    "sg:postcode":"96816",
    "sg:province":"HI",
    "sg:tags":[
        "body"
    ],
    "wof:name":"Unique Unlimited",
    "wof:placetype":"venue"
},
  "geometry": {"coordinates":[-157.80723399999999,21.278705],"type":"Point"}
}