{
  "type": "Feature",
  "properties": {
    "iso:country":"US",
    "sg:address":"93 Makaweli St",
    "sg:city":"Honolulu",
    "sg:classifiers":[
        {
            "category":"Professional",
            "type":"Services"
        }
    ],
    "sg:phone":"+1 808 395 6834",
    "sg:postcode":"96825",
    "sg:province":"HI",
    "sg:tags":[
        "establishment"
    ],
    "wof:name":"Elena's Collection Inc",
    "wof:placetype":"venue"
},
  "geometry": {"coordinates":[-157.706613,21.270421],"type":"Point"}
}