{
  "type": "Feature",
  "properties": {
    "iso:country":"US",
    "sg:address":"1631 S Beretania St",
    "sg:city":"Honolulu",
    "sg:classifiers":[
        {
            "category":"Organizations",
            "subcategory":"Religious Organization",
            "type":"Services"
        }
    ],
    "sg:phone":"+1 808 973 0150",
    "sg:postcode":"96826",
    "sg:province":"HI",
    "sg:tags":[
        "church"
    ],
    "wof:name":"Shinshiu Kyokai Mission Hawaii",
    "wof:placetype":"venue"
},
  "geometry": {"coordinates":[-157.833257,21.297873],"type":"Point"}
}