{
  "type": "Feature",
  "properties": {
    "iso:country":"US",
    "sg:address":"3785 Lower Honoapiilani Rd",
    "sg:city":"Lahaina",
    "sg:classifiers":[
        {
            "category":"Personal",
            "type":"Services"
        }
    ],
    "sg:phone":"+1 808 665 0251",
    "sg:postcode":"96761",
    "sg:province":"HI",
    "sg:tags":[
        "consultant",
        "wedding"
    ],
    "wof:name":"Maltese Dreams",
    "wof:placetype":"venue"
},
  "geometry": {"coordinates":[-156.686532,20.962617],"type":"Point"}
}