{
  "type": "Feature",
  "properties": {
    "iso:country":"US",
    "sg:address":"1314 S King St",
    "sg:city":"Honolulu",
    "sg:classifiers":[
        {
            "category":"Professional",
            "type":"Services"
        }
    ],
    "sg:phone":"+1 808 589 1661",
    "sg:postcode":"96814",
    "sg:province":"HI",
    "sg:tags":[
        "establishment"
    ],
    "wof:name":"Shalem International",
    "wof:placetype":"venue"
},
  "geometry": {"coordinates":[-157.840979,21.298817],"type":"Point"}
}