{
  "type": "Feature",
  "properties": {
    "iso:country":"US",
    "sg:address":"1550 Kamehameha Hwy",
    "sg:city":"Wahiawa",
    "sg:classifiers":[
        {
            "category":"Shopping",
            "subcategory":"Gifts & Souvenirs",
            "type":"Retail Goods"
        }
    ],
    "sg:phone":"+1 808 622 1017",
    "sg:postcode":"96786",
    "sg:province":"HI",
    "wof:name":"Alohashells Hawaii",
    "wof:placetype":"venue"
},
  "geometry": {"coordinates":[-158.03943200000001,21.527503],"type":"Point"}
}