{
  "type": "Feature",
  "properties": {
    "addr:full":"152 N Pauahi St Honolulu HI 96817",
    "addr:housenumber":"152",
    "addr:postcode":"96817",
    "addr:street":"N Pauahi St",
    "iso:country":"US",
    "sg:address":"152 N Pauahi St",
    "sg:city":"Honolulu",
    "sg:classifiers":[
        {
            "category":"Restaurant",
            "type":"Food & Drink"
        }
    ],
    "sg:phone":"+1 808 536 0502",
    "sg:postcode":"96817",
    "sg:province":"HI",
    "wof:name":"Pauahi Fast Food Cafe",
    "wof:placetype":"venue"
},
  "geometry": {"coordinates":[-157.86241100000001,21.313254],"type":"Point"}
}