{
  "type": "Feature",
  "properties": {
    "iso:country":"US",
    "sg:address":"83 Kaniela St",
    "sg:city":"Wailuku",
    "sg:classifiers":[
        {
            "category":"Manufacturing",
            "subcategory":"Printing",
            "type":"Manufacturing & Wholesale Goods"
        }
    ],
    "sg:phone":"+1 808 244 5800",
    "sg:postcode":"96793",
    "sg:province":"HI",
    "sg:tags":[
        "screen"
    ],
    "wof:name":"R C Printing",
    "wof:placetype":"venue"
},
  "geometry": {"coordinates":[-156.50198800000001,20.893888],"type":"Point"}
}