{
  "type": "Feature",
  "properties": {
    "addr:full":"1019 Farrington Hwy Waialua HI 96791",
    "addr:housenumber":"1019",
    "addr:postcode":"96791",
    "addr:street":"Farrington Hwy",
    "iso:country":"US",
    "sg:address":"1019 Farrington Hwy",
    "sg:city":"Waialua",
    "sg:classifiers":[
        {
            "category":"Building & Trades",
            "subcategory":"Plumbing",
            "type":"Services"
        }
    ],
    "sg:phone":"+1 808 637 6445",
    "sg:postcode":"96791",
    "sg:province":"HI",
    "sg:tags":[
        "septic"
    ],
    "wof:name":"Water Tech",
    "wof:placetype":"venue"
},
  "geometry": {"coordinates":[-158.20056600000001,21.580965],"type":"Point"}
}