{
  "type": "Feature",
  "properties": {
    "iso:country":"US",
    "sg:address":"535 Ward Ave",
    "sg:city":"Honolulu",
    "sg:classifiers":[
        {
            "category":"Food & Beverages",
            "subcategory":"Specialty",
            "type":"Retail Goods"
        },
        {
            "category":"Wholesale",
            "subcategory":"Non-durable Goods",
            "type":"Manufacturing & Wholesale Goods"
        }
    ],
    "sg:phone":"+1 808 591 9944",
    "sg:postcode":"96814",
    "sg:province":"HI",
    "sg:tags":[
        "health",
        "merchandise",
        "diet"
    ],
    "wof:name":"Naturally Pet",
    "wof:placetype":"venue"
},
  "geometry": {"coordinates":[-157.85314500000001,21.2983],"type":"Point"}
}