{
  "type": "Feature",
  "properties": {
    "iso:country":"US",
    "sg:address":"459 Patterson Rd",
    "sg:city":"Honolulu",
    "sg:classifiers":[
        {
            "category":"Government",
            "subcategory":"Office",
            "type":"Public Place"
        }
    ],
    "sg:phone":"+1 808 433 1912",
    "sg:postcode":"96819",
    "sg:province":"HI",
    "sg:tags":[
        "administrative",
        "program",
        "health"
    ],
    "wof:name":"Pacific E-Halth Innovation Ctr",
    "wof:placetype":"venue"
},
  "geometry": {"coordinates":[-157.888792,21.361079],"type":"Point"}
}