{
  "type": "Feature",
  "properties": {
    "iso:country":"US",
    "sg:address":"390 Komohana St",
    "sg:city":"Kapolei",
    "sg:classifiers":[
        {
            "category":"Building & Trades",
            "subcategory":"Construction",
            "type":"Services"
        }
    ],
    "sg:phone":"+1 808 682 1331",
    "sg:postcode":"96707",
    "sg:province":"HI",
    "sg:tags":[
        "steel",
        "structural",
        "contractor"
    ],
    "wof:name":"S & M Welding Co LTD",
    "wof:placetype":"venue"
},
  "geometry": {"coordinates":[-158.09580099999999,21.305557],"type":"Point"}
}