{
  "type": "Feature",
  "properties": {
    "addr:full":"530 S King St Honolulu HI 96813",
    "addr:housenumber":"530",
    "addr:postcode":"96813",
    "addr:street":"S King St",
    "iso:country":"US",
    "sg:address":"530 S King St",
    "sg:city":"Honolulu",
    "sg:classifiers":[
        {
            "category":"Government",
            "subcategory":"Office",
            "type":"Public Place"
        }
    ],
    "sg:phone":"+1 808 523 4331",
    "sg:postcode":"96813",
    "sg:province":"HI",
    "sg:tags":[
        "village"
    ],
    "sg:website":"www.honolulu.gov",
    "wof:name":"Honolulu Managing Director Ofc",
    "wof:placetype":"venue"
},
  "geometry": {"coordinates":[-157.85774000000001,21.304976],"type":"Point"}
}