{
  "type": "Feature",
  "properties": {
    "addr:full":"1605 Ulupii Pl Kailua HI 96734",
    "addr:housenumber":"1605",
    "addr:postcode":"96734",
    "addr:street":"Ulupii Pl",
    "iso:country":"US",
    "sg:address":"1605 Ulupii Pl",
    "sg:city":"Kailua",
    "sg:classifiers":[
        {
            "category":"Professional",
            "subcategory":"Business Services",
            "type":"Services"
        },
        {
            "category":"Shopping",
            "subcategory":"Music",
            "type":"Retail Goods"
        }
    ],
    "sg:phone":"+1 808 263 7670",
    "sg:postcode":"96734",
    "sg:province":"HI",
    "sg:tags":[
        "recording",
        "studio"
    ],
    "wof:name":"Sma'Kine Recording Studio",
    "wof:placetype":"venue"
},
  "geometry": {"coordinates":[-157.757519,21.375594],"type":"Point"}
}