{
  "type": "Feature",
  "properties": {
    "iso:country":"US",
    "sg:address":"720 Iwilei Rd",
    "sg:city":"Honolulu",
    "sg:classifiers":[
        {
            "category":"Shopping",
            "subcategory":"Computers & Home Electronics",
            "type":"Retail Goods"
        }
    ],
    "sg:phone":"+1 808 566 7906",
    "sg:postcode":"96817",
    "sg:province":"HI",
    "sg:tags":[
        "equipment",
        "electronic",
        "supply"
    ],
    "wof:name":"Pro Tech Electronics Systems",
    "wof:placetype":"venue"
},
  "geometry": {"coordinates":[-157.870375,21.316358],"type":"Point"}
}