{
  "type": "Feature",
  "properties": {
    "iso:country":"US",
    "sg:address":"508 Uluhala St",
    "sg:city":"Kailua",
    "sg:classifiers":[
        {
            "category":"Manufacturing",
            "subcategory":"Printing",
            "type":"Manufacturing & Wholesale Goods"
        }
    ],
    "sg:phone":"+1 808 261 0320",
    "sg:postcode":"96734",
    "sg:province":"HI",
    "sg:tags":[
        "team",
        "screen",
        "uniform",
        "sport",
        "custom"
    ],
    "wof:name":"Treasure Tees",
    "wof:placetype":"venue"
},
  "geometry": {"coordinates":[-157.75586200000001,21.377807],"type":"Point"}
}