{
  "type": "Feature",
  "properties": {
    "addr:full":"1325 Nuuanu Ave Honolulu HI 96817",
    "addr:housenumber":"1325",
    "addr:postcode":"96817",
    "addr:street":"Nuuanu Ave",
    "iso:country":"US",
    "sg:address":"1325 Nuuanu Ave",
    "sg:city":"Honolulu",
    "sg:classifiers":[
        {
            "category":"Organizations",
            "subcategory":"Labor Organization",
            "type":"Services"
        }
    ],
    "sg:phone":"+1 808 550 8823",
    "sg:postcode":"96817",
    "sg:province":"HI",
    "wof:name":"Public Employees Mgmt Assn-Hi",
    "wof:placetype":"venue"
},
  "geometry": {"coordinates":[-157.85799900000001,21.314096],"type":"Point"}
}