{
  "type": "Feature",
  "properties": {
    "iso:country":"US",
    "sg:address":"2137 W Vineyard St",
    "sg:city":"Wailuku",
    "sg:classifiers":[
        {
            "category":"Professional",
            "subcategory":"Lawyer & Legal Services",
            "type":"Services"
        }
    ],
    "sg:phone":"+1 808 244 9676",
    "sg:postcode":"96793",
    "sg:province":"HI",
    "wof:name":"Desjardins Mimi Law Office of",
    "wof:placetype":"venue"
},
  "geometry": {"coordinates":[-156.510435,20.890285],"type":"Point"}
}