{
  "type": "Feature",
  "properties": {
    "addr:full":"3834 Paki Ave Honolulu HI 96815",
    "addr:housenumber":"3834",
    "addr:postcode":"96815",
    "addr:street":"Paki Ave",
    "iso:country":"US",
    "sg:address":"3834 Paki Ave",
    "sg:city":"Honolulu",
    "sg:classifiers":[
        {
            "category":"Professional",
            "type":"Services"
        }
    ],
    "sg:phone":"+1 808 922 3777",
    "sg:postcode":"96815",
    "sg:province":"HI",
    "wof:name":"United States Amateur Box",
    "wof:placetype":"venue"
},
  "geometry": {"coordinates":[-157.817216,21.265431],"type":"Point"}
}