{
  "type": "Feature",
  "properties": {
    "iso:country":"US",
    "sg:address":"1270 Hunekai St",
    "sg:city":"Kapolei",
    "sg:classifiers":[
        {
            "category":"Professional",
            "subcategory":"Management & Consulting",
            "type":"Services"
        }
    ],
    "sg:phone":"+1 808 471 8604",
    "sg:postcode":"96707",
    "sg:province":"HI",
    "sg:tags":[
        "business"
    ],
    "wof:name":"Harmony Woodworks",
    "wof:placetype":"venue"
},
  "geometry": {"coordinates":[-158.083054,21.368469],"type":"Point"}
}