{
  "type": "Feature",
  "properties": {
    "addr:full":"4820 Kanalani St Kailua Kona HI 96740",
    "addr:housenumber":"4820",
    "addr:postcode":"96740",
    "addr:street":"Kanalani St",
    "iso:country":"US",
    "sg:address":"4820 Kanalani St",
    "sg:city":"Kailua Kona",
    "sg:classifiers":[
        {
            "category":"Retail",
            "subcategory":"Repair Shop",
            "type":"Services"
        },
        {
            "category":"Autos & Motor Vehicles",
            "subcategory":"Auto Supplies",
            "type":"Retail Goods"
        }
    ],
    "sg:phone":"+1 808 331 0770",
    "sg:postcode":"96740",
    "sg:province":"HI",
    "sg:tags":[
        "four",
        "wheel",
        "drive",
        "accessory"
    ],
    "wof:name":"Island Performance & Repair",
    "wof:placetype":"venue"
},
  "geometry": {"coordinates":[-156.01952,19.68461],"type":"Point"}
}