{
  "type": "Feature",
  "properties": {
    "iso:country":"US",
    "sg:address":"225 Queen St",
    "sg:city":"Honolulu",
    "sg:classifiers":[
        {
            "category":"Professional",
            "type":"Services"
        }
    ],
    "sg:phone":"+1 808 537 3163",
    "sg:postcode":"96813",
    "sg:province":"HI",
    "sg:tags":[
        "establishment"
    ],
    "wof:name":"MAGBA Inc",
    "wof:placetype":"venue"
},
  "geometry": {"coordinates":[-157.86174600000001,21.306326],"type":"Point"}
}