{
  "type": "Feature",
  "properties": {
    "iso:country":"US",
    "sg:address":"2827 Waimano Home Rd",
    "sg:city":"Pearl City",
    "sg:classifiers":[
        {
            "category":"Health Services",
            "subcategory":"Nursing And Care Facility",
            "type":"Services"
        },
        {
            "category":"Health Services",
            "subcategory":"Clinic",
            "type":"Services"
        }
    ],
    "sg:phone":"+1 808 454 0511",
    "sg:postcode":"96782",
    "sg:province":"HI",
    "sg:tags":[
        "agency",
        "welfare"
    ],
    "wof:name":"Home & Community Svc Of Hawaii",
    "wof:placetype":"venue"
},
  "geometry": {"coordinates":[-157.941001,21.42184],"type":"Point"}
}