{
  "type": "Feature",
  "properties": {
    "iso:country":"US",
    "sg:address":"1 Aloha Tower Dr",
    "sg:city":"Honolulu",
    "sg:classifiers":[
        {
            "category":"Shopping",
            "subcategory":"Discount & Variety Stores",
            "type":"Retail Goods"
        }
    ],
    "sg:phone":"+1 808 528 1212",
    "sg:postcode":"96813",
    "sg:province":"HI",
    "sg:tags":[
        "hula",
        "supply"
    ],
    "wof:name":"Island Hula Studio",
    "wof:placetype":"venue"
},
  "geometry": {"coordinates":[-157.86456699999999,21.306433],"type":"Point"}
}