{
  "type": "Feature",
  "properties": {
    "iso:country":"US",
    "sg:address":"3434 Waialae Ave",
    "sg:city":"Honolulu",
    "sg:classifiers":[
        {
            "category":"Personal",
            "subcategory":"Beauty Salon",
            "type":"Services"
        }
    ],
    "sg:phone":"+1 808 732 5822",
    "sg:postcode":"96816",
    "sg:province":"HI",
    "sg:tags":[
        "shop"
    ],
    "wof:name":"Jean's Beauty Salon",
    "wof:placetype":"venue"
},
  "geometry": {"coordinates":[-157.802997,21.284896],"type":"Point"}
}