{
  "type": "Feature",
  "properties": {
    "addr:full":"1100 Ward Ave Honolulu HI 96814",
    "addr:housenumber":"1100",
    "addr:postcode":"96814",
    "addr:street":"Ward Ave",
    "iso:country":"US",
    "sg:address":"1100 Ward Ave",
    "sg:city":"Honolulu",
    "sg:classifiers":[
        {
            "category":"Insurance",
            "subcategory":"Insurance Agent",
            "type":"Services"
        }
    ],
    "sg:phone":"+1 808 527 7648",
    "sg:postcode":"96814",
    "sg:province":"HI",
    "wof:name":"Roy S Imai",
    "wof:placetype":"venue"
},
  "geometry": {"coordinates":[-157.84943999999999,21.303834],"type":"Point"}
}