{
  "type": "Feature",
  "properties": {
    "addr:full":"6258 Koko Olua Pl Kailua Kona HI 96740",
    "addr:housenumber":"6258",
    "addr:postcode":"96740",
    "addr:street":"Koko Olua Pl",
    "iso:country":"US",
    "sg:address":"6258 Koko Olua Pl",
    "sg:city":"Kailua Kona",
    "sg:classifiers":[
        {
            "category":"Shopping",
            "subcategory":"Clothing, Apparel, & Fashions",
            "type":"Retail Goods"
        }
    ],
    "sg:phone":"+1 808 329 0709",
    "sg:postcode":"96740",
    "sg:province":"HI",
    "wof:name":"CJ S Bargain Beachwear",
    "wof:placetype":"venue"
},
  "geometry": {"coordinates":[-155.96963600000001,19.613575],"type":"Point"}
}