{
  "type": "Feature",
  "properties": {
    "addr:full":"131 Wailea Ike Pl Kihei HI 96753",
    "addr:housenumber":"131",
    "addr:postcode":"96753",
    "addr:street":"Wailea Ike Pl",
    "iso:country":"US",
    "sg:address":"131 Wailea Ike Pl",
    "sg:city":"Kihei",
    "sg:classifiers":[
        {
            "category":"Restaurant",
            "type":"Food & Drink"
        }
    ],
    "sg:phone":"+1 808 875 7767",
    "sg:postcode":"96753",
    "sg:province":"HI",
    "sg:tags":[
        "eating"
    ],
    "wof:name":"Joe's Bar & Grill",
    "wof:placetype":"venue"
},
  "geometry": {"coordinates":[-156.43724,20.687734],"type":"Point"}
}