{
  "type": "Feature",
  "properties": {
    "addr:full":"1405 N King St Honolulu HI 96817",
    "addr:housenumber":"1405",
    "addr:postcode":"96817",
    "addr:street":"N King St",
    "iso:country":"US",
    "sg:address":"1405 N King St",
    "sg:city":"Honolulu",
    "sg:classifiers":[
        {
            "category":"Real Estate",
            "subcategory":"Developer",
            "type":"Services"
        },
        {
            "category":"Real Estate",
            "subcategory":"Real Estate Agent",
            "type":"Services"
        }
    ],
    "sg:phone":"+1 808 845 9554",
    "sg:postcode":"96817",
    "sg:province":"HI",
    "wof:name":"Century Group Realtors",
    "wof:placetype":"venue"
},
  "geometry": {"coordinates":[-157.87210300000001,21.328814],"type":"Point"}
}