{
  "type": "Feature",
  "properties": {
    "iso:country":"US",
    "sg:address":"3508 Kepuhi St",
    "sg:city":"Honolulu",
    "sg:classifiers":[
        {
            "category":"Retail",
            "subcategory":"Portrait Studio",
            "type":"Services"
        }
    ],
    "sg:phone":"+1 808 734 1018",
    "sg:postcode":"96815",
    "sg:province":"HI",
    "sg:tags":[
        "photo"
    ],
    "wof:name":"Sunny Moments Photography LLC",
    "wof:placetype":"venue"
},
  "geometry": {"coordinates":[-157.805894,21.271008],"type":"Point"}
}