{
  "type": "Feature",
  "properties": {
    "iso:country":"US",
    "sg:address":"1269 Iwaena St",
    "sg:city":"Aiea",
    "sg:classifiers":[
        {
            "category":"Restaurant",
            "type":"Food & Drink"
        }
    ],
    "sg:phone":"+1 808 486 9322",
    "sg:postcode":"96701",
    "sg:province":"HI",
    "wof:name":"Sunwest Restaurant Concepts",
    "wof:placetype":"venue"
},
  "geometry": {"coordinates":[-157.90964500000001,21.37791],"type":"Point"}
}