{
  "type": "Feature",
  "properties": {
    "iso:country":"US",
    "sg:address":"3750 Wailea Alanui Dr",
    "sg:city":"Kihei",
    "sg:classifiers":[
        {
            "category":"Museum",
            "type":"Entertainment"
        }
    ],
    "sg:phone":"+1 808 879 0092",
    "sg:postcode":"96753",
    "sg:province":"HI",
    "sg:tags":[
        "gallery"
    ],
    "wof:name":"Ventri 505 Inc",
    "wof:placetype":"venue"
},
  "geometry": {"coordinates":[-156.439267,20.686522],"type":"Point"}
}