{
  "type": "Feature",
  "properties": {
    "iso:country":"US",
    "sg:address":"1018 Kapahulu Ave",
    "sg:city":"Honolulu",
    "sg:classifiers":[
        {
            "category":"Restaurant",
            "type":"Food & Drink"
        }
    ],
    "sg:phone":"+1 808 735 4455",
    "sg:postcode":"96816",
    "sg:province":"HI",
    "sg:tags":[
        "eating"
    ],
    "wof:name":"Mr Ojisan Restaurant",
    "wof:placetype":"venue"
},
  "geometry": {"coordinates":[-157.813343,21.286239],"type":"Point"}
}