{
  "type": "Feature",
  "properties": {
    "iso:country":"US",
    "sg:address":"831 Kuhio Hwy",
    "sg:city":"Kapaa",
    "sg:classifiers":[
        {
            "category":"Restaurant",
            "type":"Food & Drink"
        }
    ],
    "sg:phone":"+1 808 822 0013",
    "sg:postcode":"96746",
    "sg:province":"HI",
    "wof:name":"A Pacific Cafe-Kauai",
    "wof:placetype":"venue"
},
  "geometry": {"coordinates":[-159.32040699999999,22.061321],"type":"Point"}
}