{
  "type": "Feature",
  "properties": {
    "addr:full":"443 Kalewa St Honolulu HI 96819",
    "addr:housenumber":"443",
    "addr:postcode":"96819",
    "addr:street":"Kalewa St",
    "iso:country":"US",
    "sg:address":"443 Kalewa St",
    "sg:city":"Honolulu",
    "sg:classifiers":[
        {
            "category":"Restaurant",
            "type":"Food & Drink"
        }
    ],
    "sg:phone":"+1 808 833 5447",
    "sg:postcode":"96819",
    "sg:province":"HI",
    "wof:name":"Driver's Diner",
    "wof:placetype":"venue"
},
  "geometry": {"coordinates":[-157.900825,21.328438],"type":"Point"}
}