{
  "type": "Feature",
  "properties": {
    "addr:full":"247 Lewers St Honolulu HI 96815",
    "addr:housenumber":"247",
    "addr:postcode":"96815",
    "addr:street":"Lewers St",
    "iso:country":"US",
    "sg:address":"247 Lewers St",
    "sg:city":"Honolulu",
    "sg:classifiers":[
        {
            "category":"Wholesale",
            "subcategory":"Non-durable Goods",
            "type":"Manufacturing & Wholesale Goods"
        }
    ],
    "sg:phone":"+1 808 971 2910",
    "sg:postcode":"96815",
    "sg:province":"HI",
    "wof:name":"Waikiki Trader",
    "wof:placetype":"venue"
},
  "geometry": {"coordinates":[-157.83066500000001,21.279347],"type":"Point"}
}