{
  "type": "Feature",
  "properties": {
    "iso:country":"US",
    "sg:address":"201 Merchant St",
    "sg:city":"Honolulu",
    "sg:classifiers":[
        {
            "category":"Professional",
            "subcategory":"Management & Consulting",
            "type":"Services"
        }
    ],
    "sg:phone":"+1 808 545 4246",
    "sg:postcode":"96813",
    "sg:province":"HI",
    "wof:name":"PM Realty Group LP",
    "wof:placetype":"venue"
},
  "geometry": {"coordinates":[-157.86066299999999,21.306805],"type":"Point"}
}