{
  "type": "Feature",
  "properties": {
    "iso:country":"US",
    "sg:address":"875 Komohana St",
    "sg:city":"Hilo",
    "sg:classifiers":[
        {
            "category":"Government",
            "subcategory":"Office",
            "type":"Public Place"
        }
    ],
    "sg:phone":"+1 808 959 9155",
    "sg:postcode":"96720",
    "sg:province":"HI",
    "sg:tags":[
        "agricultural",
        "regulation",
        "marketing"
    ],
    "wof:name":"U of H Co Op Extension Service",
    "wof:placetype":"venue"
},
  "geometry": {"coordinates":[-155.09105400000001,19.701249],"type":"Point"}
}