{
  "type": "Feature",
  "properties": {
    "iso:country":"US",
    "sg:address":"5936 Mamalahoa Hwy",
    "sg:city":"Holualoa",
    "sg:classifiers":[
        {
            "category":"Manufacturing",
            "subcategory":"Wood Products",
            "type":"Manufacturing & Wholesale Goods"
        }
    ],
    "sg:phone":"+1 808 324 1590",
    "sg:postcode":"96725",
    "sg:province":"HI",
    "sg:tags":[
        "picture",
        "frame"
    ],
    "wof:name":"Country Frame Shop & Gallery",
    "wof:placetype":"venue"
},
  "geometry": {"coordinates":[-155.94912600000001,19.620059],"type":"Point"}
}