{
  "type": "Feature",
  "properties": {
    "addr:full":"2414 Gardenia St Honolulu HI 96816",
    "addr:housenumber":"2414",
    "addr:postcode":"96816",
    "addr:street":"Gardenia St",
    "iso:country":"US",
    "sg:address":"2414 Gardenia St",
    "sg:city":"Honolulu",
    "sg:classifiers":[
        {
            "category":"Professional",
            "subcategory":"Employment Agencies",
            "type":"Services"
        }
    ],
    "sg:phone":"+1 808 739 9271",
    "sg:postcode":"96816",
    "sg:province":"HI",
    "wof:name":"Accommodations Search Hawaii",
    "wof:placetype":"venue"
},
  "geometry": {"coordinates":[-157.79001,21.308642],"type":"Point"}
}