{
  "type": "Feature",
  "properties": {
    "addr:full":"1751 Koikoi St Wahiawa HI 96786",
    "addr:housenumber":"1751",
    "addr:postcode":"96786",
    "addr:street":"Koikoi St",
    "iso:country":"US",
    "sg:address":"1751 Koikoi St",
    "sg:city":"Wahiawa",
    "sg:classifiers":[
        {
            "category":"Social Services",
            "subcategory":"Child Care",
            "type":"Services"
        }
    ],
    "sg:phone":"+1 808 429 5388",
    "sg:postcode":"96786",
    "sg:province":"HI",
    "sg:tags":[
        "day"
    ],
    "wof:name":"Neo Computer Lrng & PC Repr",
    "wof:placetype":"venue"
},
  "geometry": {"coordinates":[-158.00518500000001,21.502548],"type":"Point"}
}