{
  "type": "Feature",
  "properties": {
    "iso:country":"US",
    "sg:address":"3765 Lower Honoapiilani Rd",
    "sg:city":"Lahaina",
    "sg:classifiers":[
        {
            "category":"Real Estate",
            "subcategory":"Real Estate Operator",
            "type":"Services"
        },
        {
            "category":"Organizations",
            "subcategory":"Community Association",
            "type":"Services"
        }
    ],
    "sg:phone":"+1 808 669 8223",
    "sg:postcode":"96761",
    "sg:province":"HI",
    "sg:tags":[
        "condominium"
    ],
    "sg:website":"www.makanisands.com",
    "wof:name":"Makani Sands",
    "wof:placetype":"venue"
},
  "geometry": {"coordinates":[-156.68657899999999,20.962258],"type":"Point"}
}