{
  "type": "Feature",
  "properties": {
    "iso:country":"US",
    "sg:address":"2005 Mokuhau Rd",
    "sg:city":"Wailuku",
    "sg:classifiers":[
        {
            "category":"Social Services",
            "type":"Services"
        }
    ],
    "sg:phone":"+1 808 986 0700",
    "sg:postcode":"96793",
    "sg:province":"HI",
    "sg:tags":[
        "organization",
        "welfare"
    ],
    "wof:name":"Neighborhood Place Of Wailuku",
    "wof:placetype":"venue"
},
  "geometry": {"coordinates":[-156.50849299999999,20.896562],"type":"Point"}
}