{
  "type": "Feature",
  "properties": {
    "addr:full":"19 Kealakaha Dr Aiea HI 96701",
    "addr:housenumber":"19",
    "addr:postcode":"96701",
    "addr:street":"Kealakaha Dr",
    "iso:country":"US",
    "sg:address":"19 Kealakaha Dr",
    "sg:city":"Aiea",
    "sg:classifiers":[
        {
            "category":"Professional",
            "subcategory":"Computer Services",
            "type":"Services"
        }
    ],
    "sg:phone":"+1 808 487 8371",
    "sg:postcode":"96701",
    "sg:province":"HI",
    "wof:name":"Computer Talk",
    "wof:placetype":"venue"
},
  "geometry": {"coordinates":[-157.91895299999999,21.386607],"type":"Point"}
}