{
  "type": "Feature",
  "properties": {
    "iso:country":"US",
    "sg:address":"5610 Alapa St",
    "sg:city":"Kailua Kona",
    "sg:classifiers":[
        {
            "category":"Professional",
            "type":"Services"
        }
    ],
    "sg:phone":"+1 808 329 4039",
    "sg:postcode":"96740",
    "sg:province":"HI",
    "sg:tags":[
        "establishment"
    ],
    "wof:name":"Roberts Central Laupahoehoe",
    "wof:placetype":"venue"
},
  "geometry": {"coordinates":[-155.99935400000001,19.646042],"type":"Point"}
}