{
  "type": "Feature",
  "properties": {
    "iso:country":"US",
    "sg:address":"565 Kamehameha Hwy",
    "sg:city":"Kahuku",
    "sg:classifiers":[
        {
            "category":"Social Services",
            "type":"Services"
        }
    ],
    "sg:phone":"+1 808 232 2319",
    "sg:postcode":"96731",
    "sg:province":"HI",
    "sg:tags":[
        "youth",
        "organization",
        "center"
    ],
    "wof:name":"Malama Youth Ctr",
    "wof:placetype":"venue"
},
  "geometry": {"coordinates":[-157.95185599999999,21.677707],"type":"Point"}
}