{
  "type": "Feature",
  "properties": {
    "addr:full":"236 Moanalua Rd Aiea HI 96701",
    "addr:housenumber":"236",
    "addr:postcode":"96701",
    "addr:street":"Moanalua Rd",
    "iso:country":"US",
    "sg:address":"236 Moanalua Rd",
    "sg:city":"Aiea",
    "sg:classifiers":[
        {
            "category":"Food & Beverages",
            "subcategory":"Groceries & Convenience Stores",
            "type":"Retail Goods"
        }
    ],
    "sg:phone":"+1 808 488 3723",
    "sg:postcode":"96701",
    "sg:province":"HI",
    "sg:tags":[
        "grocer"
    ],
    "wof:name":"Circle K",
    "wof:placetype":"venue"
},
  "geometry": {"coordinates":[-157.930826,21.377528],"type":"Point"}
}