{
  "type": "Feature",
  "properties": {
    "iso:country":"US",
    "sg:address":"1477 Kalanianaole Ave",
    "sg:city":"Hilo",
    "sg:classifiers":[
        {
            "category":"Manufacturing",
            "subcategory":"Food",
            "type":"Manufacturing & Wholesale Goods"
        }
    ],
    "sg:phone":"+1 808 933 9399",
    "sg:postcode":"96720",
    "sg:province":"HI",
    "sg:tags":[
        "frozen",
        "dessert",
        "ice",
        "cream"
    ],
    "wof:name":"Kai Trans Inc",
    "wof:placetype":"venue"
},
  "geometry": {"coordinates":[-155.036092,19.734998],"type":"Point"}
}