{
  "type": "Feature",
  "properties": {
    "addr:full":"1126 Koko Head Ave Honolulu HI 96816",
    "addr:housenumber":"1126",
    "addr:postcode":"96816",
    "addr:street":"Koko Head Ave",
    "iso:country":"US",
    "sg:address":"1126 Koko Head Ave",
    "sg:city":"Honolulu",
    "sg:classifiers":[
        {
            "category":"Real Estate",
            "subcategory":"Real Estate Agent",
            "type":"Services"
        }
    ],
    "sg:phone":"+1 808 735 7888",
    "sg:postcode":"96816",
    "sg:province":"HI",
    "sg:website":"www.c21allislands.com",
    "wof:name":"All Islands",
    "wof:placetype":"venue"
},
  "geometry": {"coordinates":[-157.79877500000001,21.280687],"type":"Point"}
}