{
  "type": "Feature",
  "properties": {
    "addr:full":"725 Kapiolani Blvd Honolulu HI 96813",
    "addr:housenumber":"725",
    "addr:postcode":"96813",
    "addr:street":"Kapiolani Blvd",
    "iso:country":"US",
    "sg:address":"725 Kapiolani Blvd",
    "sg:city":"Honolulu",
    "sg:classifiers":[
        {
            "category":"Travel",
            "subcategory":"Travel Agent",
            "type":"Entertainment"
        }
    ],
    "sg:phone":"+1 808 591 8988",
    "sg:postcode":"96813",
    "sg:province":"HI",
    "sg:tags":[
        "agency",
        "bureau"
    ],
    "sg:website":"www.dragontours.com",
    "wof:name":"Dragon Hawaii Inc",
    "wof:placetype":"venue"
},
  "geometry": {"coordinates":[-157.85470000000001,21.301593],"type":"Point"}
}