{
  "type": "Feature",
  "properties": {
    "addr:full":"1050 Ala Moana Blvd Honolulu HI 96814",
    "addr:housenumber":"1050",
    "addr:postcode":"96814",
    "addr:street":"Ala Moana Blvd",
    "iso:country":"US",
    "sg:address":"1050 Ala Moana Blvd",
    "sg:city":"Honolulu",
    "sg:classifiers":[
        {
            "category":"Shopping",
            "subcategory":"Books",
            "type":"Retail Goods"
        }
    ],
    "sg:phone":"+1 808 596 8890",
    "sg:postcode":"96814",
    "sg:province":"HI",
    "sg:tags":[
        "dealer"
    ],
    "sg:website":"www.honolulu.logosbookstores.com",
    "wof:name":"Logos Bookstore of Hawaii",
    "wof:placetype":"venue"
},
  "geometry": {"coordinates":[-157.855999,21.294406],"type":"Point"}
}