{
  "type": "Feature",
  "properties": {
    "iso:country":"US",
    "sg:address":"91 Fort Weaver Rd",
    "sg:city":"Ewa Beach",
    "sg:classifiers":[
        {
            "category":"Food & Beverages",
            "subcategory":"Groceries & Convenience Stores",
            "type":"Retail Goods"
        }
    ],
    "sg:phone":"+1 808 681 5711",
    "sg:postcode":"96706",
    "sg:province":"HI",
    "wof:name":"7-Eleven",
    "wof:placetype":"venue"
},
  "geometry": {"coordinates":[-157.994182,21.314652],"type":"Point"}
}