{
  "type": "Feature",
  "properties": {
    "addr:full":"7486 Mamalahoa Hwy Kealakekua HI 96750",
    "addr:housenumber":"7486",
    "addr:postcode":"96750",
    "addr:street":"Mamalahoa Hwy",
    "iso:country":"US",
    "sg:address":"7486 Mamalahoa Hwy",
    "sg:city":"Kealakekua",
    "sg:classifiers":[
        {
            "category":"Retail",
            "subcategory":"Laundry & Dry Cleaning",
            "type":"Services"
        }
    ],
    "sg:phone":"+1 808 322 2929",
    "sg:postcode":"96750",
    "sg:province":"HI",
    "wof:name":"K C Washerette",
    "wof:placetype":"venue"
},
  "geometry": {"coordinates":[-155.927482,19.533969],"type":"Point"}
}