{
  "type": "Feature",
  "properties": {
    "iso:country":"US",
    "sg:address":"723 Kuahao Pl",
    "sg:city":"Pearl City",
    "sg:classifiers":[
        {
            "category":"Wholesale",
            "subcategory":"Sporting Goods",
            "type":"Manufacturing & Wholesale Goods"
        }
    ],
    "sg:phone":"+1 808 488 0024",
    "sg:postcode":"96782",
    "sg:province":"HI",
    "sg:tags":[
        "surfboard"
    ],
    "wof:name":"Surftech",
    "wof:placetype":"venue"
},
  "geometry": {"coordinates":[-157.955354,21.392213],"type":"Point"}
}