{
  "type": "Feature",
  "properties": {
    "iso:country":"US",
    "sg:address":"74 Malulani St",
    "sg:city":"Kaneohe",
    "sg:classifiers":[
        {
            "category":"Building & Trades",
            "subcategory":"Construction",
            "type":"Services"
        }
    ],
    "sg:phone":"+1 808 235 2767",
    "sg:postcode":"96744",
    "sg:province":"HI",
    "sg:tags":[
        "house",
        "nonresidential"
    ],
    "wof:name":"G T Industries & Distributors",
    "wof:placetype":"venue"
},
  "geometry": {"coordinates":[-157.77966699999999,21.408633],"type":"Point"}
}