{
  "type": "Feature",
  "properties": {
    "addr:full":"870 4th St Pearl City HI 96782",
    "addr:housenumber":"870",
    "addr:postcode":"96782",
    "addr:street":"4Th St",
    "iso:country":"US",
    "sg:address":"870 4th St",
    "sg:city":"Pearl City",
    "sg:classifiers":[
        {
            "category":"Government",
            "subcategory":"Court House",
            "type":"Public Place"
        }
    ],
    "sg:phone":"+1 808 454 5488",
    "sg:postcode":"96782",
    "sg:province":"HI",
    "sg:tags":[
        "state"
    ],
    "wof:name":"District Court",
    "wof:placetype":"venue"
},
  "geometry": {"coordinates":[-157.96959699999999,21.392547],"type":"Point"}
}