{
  "type": "Feature",
  "properties": {
    "iso:country":"US",
    "sg:address":"117 Nanakuli Ave",
    "sg:city":"Waianae",
    "sg:classifiers":[
        {
            "category":"Organizations",
            "subcategory":"Religious Organization",
            "type":"Services"
        }
    ],
    "sg:phone":"+1 808 668 1927",
    "sg:postcode":"96792",
    "sg:province":"HI",
    "sg:tags":[
        "church"
    ],
    "wof:name":"Ka Mana Ho'Ola Hou Aka Rsrrctn",
    "wof:placetype":"venue"
},
  "geometry": {"coordinates":[-158.141516,21.37939],"type":"Point"}
}