{
  "type": "Feature",
  "properties": {
    "iso:country":"US",
    "sg:address":"884 W Mokuea Pl",
    "sg:city":"Kahului",
    "sg:classifiers":[
        {
            "category":"Retail",
            "subcategory":"Auto Rental",
            "type":"Services"
        }
    ],
    "sg:phone":"+1 808 871 7575",
    "sg:postcode":"96732",
    "sg:province":"HI",
    "sg:tags":[
        "passenger",
        "car"
    ],
    "wof:name":"Avis Rent A Car Systems Inc",
    "wof:placetype":"venue"
},
  "geometry": {"coordinates":[-156.44101900000001,20.894279],"type":"Point"}
}