{
  "type": "Feature",
  "properties": {
    "iso:country":"US",
    "sg:address":"1920 Ala Moana Blvd",
    "sg:city":"Honolulu",
    "sg:classifiers":[
        {
            "category":"Retail",
            "subcategory":"Animal Services",
            "type":"Services"
        }
    ],
    "sg:phone":"+1 808 946 2787",
    "sg:postcode":"96815",
    "sg:province":"HI",
    "wof:name":"Poochs Potti",
    "wof:placetype":"venue"
},
  "geometry": {"coordinates":[-157.83406299999999,21.285616],"type":"Point"}
}