{
  "type": "Feature",
  "properties": {
    "iso:country":"US",
    "sg:address":"16 S Market St",
    "sg:city":"Wailuku",
    "sg:classifiers":[
        {
            "category":"Building & Trades",
            "subcategory":"Landscaping Services",
            "type":"Services"
        }
    ],
    "sg:phone":"+1 808 242 0863",
    "sg:postcode":"96793",
    "sg:province":"HI",
    "sg:tags":[
        "landscape",
        "contractor"
    ],
    "wof:name":"SGS Maui Inc",
    "wof:placetype":"venue"
},
  "geometry": {"coordinates":[-156.50403499999999,20.890232],"type":"Point"}
}