{
  "type": "Feature",
  "properties": {
    "iso:country":"US",
    "sg:address":"5625 Pia St",
    "sg:city":"Honolulu",
    "sg:classifiers":[
        {
            "category":"Wholesale",
            "subcategory":"Sporting Goods",
            "type":"Manufacturing & Wholesale Goods"
        }
    ],
    "sg:phone":"+1 808 373 4916",
    "sg:postcode":"96821",
    "sg:province":"HI",
    "sg:tags":[
        "equipment",
        "golf",
        "supply"
    ],
    "wof:name":"G K Enterprises",
    "wof:placetype":"venue"
},
  "geometry": {"coordinates":[-157.737426,21.282716],"type":"Point"}
}