{
  "type": "Feature",
  "properties": {
    "addr:full":"580 Kamehameha Hwy Haleiwa HI 96712",
    "addr:housenumber":"580",
    "addr:postcode":"96712",
    "addr:street":"Kamehameha Hwy",
    "iso:country":"US",
    "sg:address":"580 Kamehameha Hwy",
    "sg:city":"Haleiwa",
    "sg:classifiers":[
        {
            "category":"Autos & Motor Vehicles",
            "subcategory":"Fuel & Gas Station",
            "type":"Retail Goods"
        }
    ],
    "sg:phone":"+1 808 637 9611",
    "sg:postcode":"96712",
    "sg:province":"HI",
    "sg:tags":[
        "oil"
    ],
    "wof:name":"TESORO Gas Express",
    "wof:placetype":"venue"
},
  "geometry": {"coordinates":[-158.102958,21.595542],"type":"Point"}
}