{
  "type": "Feature",
  "properties": {
    "addr:full":"909 Halekauwila St Honolulu HI 96814",
    "addr:housenumber":"909",
    "addr:postcode":"96814",
    "addr:street":"Halekauwila St",
    "iso:country":"US",
    "sg:address":"909 Halekauwila St",
    "sg:city":"Honolulu",
    "sg:classifiers":[
        {
            "category":"Arts & Performance",
            "subcategory":"Theater",
            "type":"Entertainment"
        }
    ],
    "sg:phone":"+1 808 596 8923",
    "sg:postcode":"96814",
    "sg:province":"HI",
    "sg:tags":[
        "entertainer"
    ],
    "wof:name":"Exotic Nights",
    "wof:placetype":"venue"
},
  "geometry": {"coordinates":[-157.85556800000001,21.296714],"type":"Point"}
}