{
  "type": "Feature",
  "properties": {
    "iso:country":"US",
    "sg:address":"1100 Ward Ave",
    "sg:city":"Honolulu",
    "sg:classifiers":[
        {
            "category":"Banks & Credit Unions",
            "subcategory":"Bank",
            "type":"Services"
        }
    ],
    "sg:phone":"+1 808 545 1000",
    "sg:postcode":"96814",
    "sg:province":"HI",
    "sg:tags":[
        "loan",
        "real estate"
    ],
    "wof:name":"Island Community Lending",
    "wof:placetype":"venue"
},
  "geometry": {"coordinates":[-157.84943999999999,21.303834],"type":"Point"}
}