{
  "type": "Feature",
  "properties": {
    "iso:country":"US",
    "sg:address":"449 Kapahulu Ave",
    "sg:city":"Honolulu",
    "sg:classifiers":[
        {
            "category":"Personal",
            "type":"Services"
        }
    ],
    "sg:phone":"+1 808 738 5244",
    "sg:postcode":"96815",
    "sg:province":"HI",
    "sg:tags":[
        "therapist",
        "massage"
    ],
    "wof:name":"Aloha Lomilomi",
    "wof:placetype":"venue"
},
  "geometry": {"coordinates":[-157.81520399999999,21.27565],"type":"Point"}
}