{
  "type": "Feature",
  "properties": {
    "iso:country":"US",
    "sg:address":"650 Ainapo St",
    "sg:city":"Honolulu",
    "sg:classifiers":[
        {
            "category":"Professional",
            "subcategory":"Engineering",
            "type":"Services"
        }
    ],
    "sg:phone":"+1 808 395 2175",
    "sg:postcode":"96825",
    "sg:province":"HI",
    "wof:name":"Dans Pineapple Salsa",
    "wof:placetype":"venue"
},
  "geometry": {"coordinates":[-157.71097499999999,21.297473],"type":"Point"}
}