{
  "type": "Feature",
  "properties": {
    "iso:country":"US",
    "sg:address":"1230 Kulawai St",
    "sg:city":"Aiea",
    "sg:classifiers":[
        {
            "category":"Professional",
            "subcategory":"Management & Consulting",
            "type":"Services"
        }
    ],
    "sg:phone":"+1 808 488 4458",
    "sg:postcode":"96701",
    "sg:province":"HI",
    "wof:name":"Groundwork Corp",
    "wof:placetype":"venue"
},
  "geometry": {"coordinates":[-157.91993500000001,21.391046],"type":"Point"}
}