{
  "type": "Feature",
  "properties": {
    "addr:full":"1319 Punahou St Honolulu HI 96826",
    "addr:housenumber":"1319",
    "addr:postcode":"96826",
    "addr:street":"Punahou St",
    "iso:country":"US",
    "sg:address":"1319 Punahou St",
    "sg:city":"Honolulu",
    "sg:classifiers":[
        {
            "category":"Health Services",
            "subcategory":"Doctor",
            "type":"Services"
        }
    ],
    "sg:phone":"+1 808 951 8455",
    "sg:postcode":"96826",
    "sg:province":"HI",
    "sg:tags":[
        "medical"
    ],
    "wof:name":"Kaji Devonna M MD Faap",
    "wof:placetype":"venue"
},
  "geometry": {"coordinates":[-157.834698,21.299511],"type":"Point"}
}