{
  "type": "Feature",
  "properties": {
    "addr:full":"1748 Dillingham Blvd Honolulu HI 96819",
    "addr:housenumber":"1748",
    "addr:postcode":"96819",
    "addr:street":"Dillingham Blvd",
    "iso:country":"US",
    "sg:address":"1748 Dillingham Blvd",
    "sg:city":"Honolulu",
    "sg:classifiers":[
        {
            "category":"Health Services",
            "subcategory":"Doctor",
            "type":"Services"
        }
    ],
    "sg:phone":"+1 808 848 0880",
    "sg:postcode":"96819",
    "sg:province":"HI",
    "sg:tags":[
        "physician",
        "surgeon",
        "pediatrician"
    ],
    "wof:name":"Edgar T De La Cruz MD Inc",
    "wof:placetype":"venue"
},
  "geometry": {"coordinates":[-157.88067799999999,21.328009],"type":"Point"}
}