{
  "type": "Feature",
  "properties": {
    "iso:country":"US",
    "sg:address":"2920 Ala Ilima St",
    "sg:city":"Honolulu",
    "sg:classifiers":[
        {
            "category":"Personal",
            "type":"Services"
        }
    ],
    "sg:phone":"+1 808 391 3435",
    "sg:postcode":"96818",
    "sg:province":"HI",
    "sg:tags":[
        "interpreter",
        "escort"
    ],
    "wof:name":"Richard C Lee",
    "wof:placetype":"venue"
},
  "geometry": {"coordinates":[-157.90552700000001,21.345409],"type":"Point"}
}