{
  "type": "Feature",
  "properties": {
    "iso:country":"US",
    "sg:address":"1145 12th Ave",
    "sg:city":"Honolulu",
    "sg:classifiers":[
        {
            "category":"Personal",
            "subcategory":"Shoe Repair & Shine",
            "type":"Services"
        }
    ],
    "sg:phone":"+1 808 737 1715",
    "sg:postcode":"96816",
    "sg:province":"HI",
    "sg:tags":[
        "repairing",
        "parlor",
        "boot"
    ],
    "wof:name":"Tam's Shoe Repair Shop",
    "wof:placetype":"venue"
},
  "geometry": {"coordinates":[-157.79914400000001,21.281899],"type":"Point"}
}