{
  "type": "Feature",
  "properties": {
    "addr:full":"5699 Kopiko St Kailua Kona HI 96740",
    "addr:housenumber":"5699",
    "addr:postcode":"96740",
    "addr:street":"Kopiko St",
    "iso:country":"US",
    "sg:address":"5699 Kopiko St",
    "sg:city":"Kailua Kona",
    "sg:classifiers":[
        {
            "category":"Sports & Exercise",
            "subcategory":"Gym",
            "type":"Entertainment"
        }
    ],
    "sg:phone":"+1 808 327 0066",
    "sg:postcode":"96740",
    "sg:province":"HI",
    "sg:tags":[
        "gymnasium"
    ],
    "wof:name":"Fitzone",
    "wof:placetype":"venue"
},
  "geometry": {"coordinates":[-155.99527,19.643179],"type":"Point"}
}