{
  "type": "Feature",
  "properties": {
    "iso:country":"US",
    "sg:address":"2611 Ala Wai Blvd",
    "sg:city":"Honolulu",
    "sg:classifiers":[
        {
            "category":"Professional",
            "subcategory":"Advertising",
            "type":"Services"
        }
    ],
    "sg:phone":"+1 808 922 2090",
    "sg:postcode":"96815",
    "sg:province":"HI",
    "sg:tags":[
        "counselor"
    ],
    "wof:name":"Ocean Vast Media",
    "wof:placetype":"venue"
},
  "geometry": {"coordinates":[-157.81828899999999,21.275063],"type":"Point"}
}