{
  "type": "Feature",
  "properties": {
    "iso:country":"US",
    "sg:address":"333 Aoloa St",
    "sg:city":"Kailua",
    "sg:classifiers":[
        {
            "category":"Real Estate",
            "subcategory":"Real Estate Agent",
            "type":"Services"
        }
    ],
    "sg:phone":"+1 808 263 4280",
    "sg:postcode":"96734",
    "sg:province":"HI",
    "wof:name":"Touchstone Properties Ltd",
    "wof:placetype":"venue"
},
  "geometry": {"coordinates":[-157.737346,21.391779],"type":"Point"}
}