{
  "type": "Feature",
  "properties": {
    "iso:country":"US",
    "sg:address":"69 Kuuala St",
    "sg:city":"Kailua",
    "sg:classifiers":[
        {
            "category":"Professional",
            "subcategory":"Accounting & Tax Preparation",
            "type":"Services"
        }
    ],
    "sg:phone":"+1 808 261 6242",
    "sg:postcode":"96734",
    "sg:province":"HI",
    "wof:name":"Olga Waterhouse",
    "wof:placetype":"venue"
},
  "geometry": {"coordinates":[-157.734486,21.397947],"type":"Point"}
}