{
  "type": "Feature",
  "properties": {
    "addr:full":"5577 Kauhola St Kailua Kona HI 96740",
    "addr:housenumber":"5577",
    "addr:postcode":"96740",
    "addr:street":"Kauhola St",
    "iso:country":"US",
    "sg:address":"5577 Kauhola St",
    "sg:city":"Kailua Kona",
    "sg:classifiers":[
        {
            "category":"Real Estate",
            "subcategory":"Real Estate Agent",
            "type":"Services"
        }
    ],
    "sg:phone":"+1 808 329 1157",
    "sg:postcode":"96740",
    "sg:province":"HI",
    "wof:name":"Pueo Real Estate Svc Unlimited",
    "wof:placetype":"venue"
},
  "geometry": {"coordinates":[-156.01957300000001,19.688679],"type":"Point"}
}