{
  "type": "Feature",
  "properties": {
    "iso:country":"US",
    "sg:address":"75 N King St",
    "sg:city":"Honolulu",
    "sg:classifiers":[
        {
            "category":"Wholesale",
            "subcategory":"Non-durable Goods",
            "type":"Manufacturing & Wholesale Goods"
        }
    ],
    "sg:phone":"+1 808 524 3344",
    "sg:postcode":"96817",
    "sg:province":"HI",
    "sg:tags":[
        "international",
        "company",
        "trade"
    ],
    "wof:name":"Concord Center",
    "wof:placetype":"venue"
},
  "geometry": {"coordinates":[-157.863587,21.311576],"type":"Point"}
}