{
  "type": "Feature",
  "properties": {
    "addr:full":"270 Aapueo Pkwy Makawao HI 96768",
    "addr:housenumber":"270",
    "addr:postcode":"96768",
    "addr:street":"Aapueo Pkwy",
    "iso:country":"US",
    "sg:address":"270 Aapueo Pkwy",
    "sg:city":"Makawao",
    "sg:classifiers":[
        {
            "category":"Education",
            "subcategory":"School",
            "type":"Public Place"
        }
    ],
    "sg:phone":"+1 808 573 7000",
    "sg:postcode":"96768",
    "sg:province":"HI",
    "wof:name":"Kamehameha High School",
    "wof:placetype":"venue"
},
  "geometry": {"coordinates":[-156.33374800000001,20.82658],"type":"Point"}
}