{
  "type": "Feature",
  "properties": {
    "addr:full":"6655 Mamalahoa Hwy Holualoa HI 96725",
    "addr:postcode":"6655;96725",
    "addr:street":"Mamalahoa Hwy",
    "iso:country":"US",
    "sg:address":"6655 Mamalahoa Hwy",
    "sg:city":"Holualoa",
    "sg:classifiers":[
        {
            "category":"Real Estate",
            "subcategory":"Real Estate Agent",
            "type":"Services"
        }
    ],
    "sg:phone":"+1 808 322 6521",
    "sg:postcode":"96725",
    "sg:province":"HI",
    "wof:name":"Hosley Realty Co",
    "wof:placetype":"venue"
},
  "geometry": {"coordinates":[-155.943389,19.57421],"type":"Point"}
}