{
  "type": "Feature",
  "properties": {
    "iso:country":"US",
    "sg:address":"560 N Nimitz Hwy",
    "sg:city":"Honolulu",
    "sg:classifiers":[
        {
            "category":"Communications",
            "subcategory":"Radio Station",
            "type":"Services"
        }
    ],
    "sg:phone":"+1 808 533 0065",
    "sg:postcode":"96817",
    "sg:province":"HI",
    "sg:tags":[
        "company",
        "broadcasting"
    ],
    "wof:name":"Salem Communications",
    "wof:placetype":"venue"
},
  "geometry": {"coordinates":[-157.87003300000001,21.313861],"type":"Point"}
}