{
  "type": "Feature",
  "properties": {
    "iso:country":"US",
    "sg:address":"221 Piikea Ave",
    "sg:city":"Kihei",
    "sg:classifiers":[
        {
            "category":"Health Services",
            "subcategory":"Doctor",
            "type":"Services"
        }
    ],
    "sg:phone":"+1 808 874 8554",
    "sg:postcode":"96753",
    "sg:province":"HI",
    "sg:tags":[
        "physician",
        "surgeon"
    ],
    "wof:name":"Howard G Barbarosh Inc",
    "wof:placetype":"venue"
},
  "geometry": {"coordinates":[-156.45328900000001,20.750503],"type":"Point"}
}