{
  "type": "Feature",
  "properties": {
    "addr:full":"900 Fort Street Ml Honolulu HI 96813",
    "addr:housenumber":"900",
    "addr:postcode":"96813",
    "addr:street":"Fort Street",
    "iso:country":"US",
    "sg:address":"900 Fort Street Ml",
    "sg:city":"Honolulu",
    "sg:classifiers":[
        {
            "category":"Professional",
            "subcategory":"Lawyer & Legal Services",
            "type":"Services"
        }
    ],
    "sg:phone":"+1 808 538 7677",
    "sg:postcode":"96813",
    "sg:province":"HI",
    "wof:name":"John H PRC PC",
    "wof:placetype":"venue"
},
  "geometry": {"coordinates":[-157.862101,21.309186],"type":"Point"}
}