{
  "type": "Feature",
  "properties": {
    "addr:full":"932 Ward Ave Honolulu HI 96814",
    "addr:housenumber":"932",
    "addr:postcode":"96814",
    "addr:street":"Ward Ave",
    "iso:country":"US",
    "sg:address":"932 Ward Ave",
    "sg:city":"Honolulu",
    "sg:classifiers":[
        {
            "category":"Health Services",
            "subcategory":"Doctor",
            "type":"Services"
        }
    ],
    "sg:phone":"+1 808 535 5555",
    "sg:postcode":"96814",
    "sg:province":"HI",
    "sg:tags":[
        "clinic"
    ],
    "wof:name":"Manakai O'Malama",
    "wof:placetype":"venue"
},
  "geometry": {"coordinates":[-157.852138,21.299672],"type":"Point"}
}