{
  "type": "Feature",
  "properties": {
    "iso:country":"US",
    "sg:address":"450 Koauka Loop",
    "sg:city":"Aiea",
    "sg:classifiers":[
        {
            "category":"Real Estate",
            "subcategory":"Real Estate Agent",
            "type":"Services"
        }
    ],
    "sg:phone":"+1 808 488 0111",
    "sg:postcode":"96701",
    "sg:province":"HI",
    "wof:name":"Highlander",
    "wof:placetype":"venue"
},
  "geometry": {"coordinates":[-157.93681799999999,21.385857],"type":"Point"}
}