{
  "type": "Feature",
  "properties": {
    "iso:country":"US",
    "sg:address":"3181 Mamane St",
    "sg:city":"Honokaa",
    "sg:classifiers":[
        {
            "category":"Shopping",
            "subcategory":"Computers & Home Electronics",
            "type":"Retail Goods"
        }
    ],
    "sg:phone":"+1 808 936 1133",
    "sg:postcode":"96727",
    "sg:province":"HI",
    "sg:tags":[
        "television",
        "radio"
    ],
    "wof:name":"Brent & Val's TV & Appliance",
    "wof:placetype":"venue"
},
  "geometry": {"coordinates":[-155.45152200000001,20.070553],"type":"Point"}
}