{
  "type": "Feature",
  "properties": {
    "addr:full":"1522 Makaloa St Honolulu HI 96814",
    "addr:housenumber":"1522",
    "addr:postcode":"96814",
    "addr:street":"Makaloa St",
    "iso:country":"US",
    "sg:address":"1522 Makaloa St",
    "sg:city":"Honolulu",
    "sg:classifiers":[
        {
            "category":"Organizations",
            "subcategory":"Religious Organization",
            "type":"Services"
        }
    ],
    "sg:phone":"+1 808 942 0854",
    "sg:postcode":"96814",
    "sg:province":"HI",
    "sg:tags":[
        "church"
    ],
    "wof:name":"Full Gospel Church Of Oahu",
    "wof:placetype":"venue"
},
  "geometry": {"coordinates":[-157.841262,21.293484],"type":"Point"}
}