{
  "type": "Feature",
  "properties": {
    "iso:country":"US",
    "sg:address":"915 Farrington Hwy",
    "sg:city":"Waianae",
    "sg:classifiers":[
        {
            "category":"Personal",
            "subcategory":"Beauty Salon",
            "type":"Services"
        }
    ],
    "sg:phone":"+1 808 696 3631",
    "sg:postcode":"96792",
    "sg:province":"HI",
    "sg:tags":[
        "shop"
    ],
    "wof:name":"Jack & Jill Hair Styles",
    "wof:placetype":"venue"
},
  "geometry": {"coordinates":[-158.17689799999999,21.404442],"type":"Point"}
}