{
  "type": "Feature",
  "properties": {
    "addr:full":"3030 Pualei Cir Honolulu HI 96815",
    "addr:housenumber":"3030",
    "addr:postcode":"96815",
    "addr:street":"Pualei Cir",
    "iso:country":"US",
    "sg:address":"3030 Pualei Cir",
    "sg:city":"Honolulu",
    "sg:classifiers":[
        {
            "category":"Utilities",
            "subcategory":"Telephone",
            "type":"Services"
        }
    ],
    "sg:phone":"+1 808 926 8774",
    "sg:postcode":"96815",
    "sg:province":"HI",
    "sg:tags":[
        "camera",
        "internet"
    ],
    "wof:name":"Keikicam",
    "wof:placetype":"venue"
},
  "geometry": {"coordinates":[-157.81475800000001,21.266753],"type":"Point"}
}