{
  "type": "Feature",
  "properties": {
    "iso:country":"US",
    "sg:address":"157 Kipapa Dr",
    "sg:city":"Mililani",
    "sg:classifiers":[
        {
            "category":"Building & Trades",
            "subcategory":"Construction",
            "type":"Services"
        }
    ],
    "sg:phone":"+1 808 623 1603",
    "sg:postcode":"96789",
    "sg:province":"HI",
    "sg:tags":[
        "plastering",
        "business",
        "coping",
        "contractor",
        "tiling",
        "pool",
        "swimming"
    ],
    "wof:name":"Poolpride",
    "wof:placetype":"venue"
},
  "geometry": {"coordinates":[-158.01548099999999,21.460262],"type":"Point"}
}