{
  "type": "Feature",
  "properties": {
    "iso:country":"US",
    "sg:address":"103 S High St",
    "sg:city":"Wailuku",
    "sg:classifiers":[
        {
            "category":"Social Services",
            "subcategory":"Child Care",
            "type":"Services"
        }
    ],
    "sg:phone":"+1 808 244 5676",
    "sg:postcode":"96793",
    "sg:province":"HI",
    "sg:tags":[
        "kindergarten",
        "academic",
        "school"
    ],
    "wof:name":"Punana Leo O Maui",
    "wof:placetype":"venue"
},
  "geometry": {"coordinates":[-156.50774999999999,20.889806],"type":"Point"}
}