{
  "type": "Feature",
  "properties": {
    "iso:country":"US",
    "sg:address":"202 Merchant St",
    "sg:city":"Honolulu",
    "sg:classifiers":[
        {
            "category":"Food & Beverages",
            "subcategory":"Groceries & Convenience Stores",
            "type":"Retail Goods"
        },
        {
            "category":"Food & Beverages",
            "subcategory":"Fruits & Vegetables",
            "type":"Retail Goods"
        }
    ],
    "sg:phone":"+1 808 533 4687",
    "sg:postcode":"96813",
    "sg:province":"HI",
    "sg:tags":[
        "produce"
    ],
    "wof:name":"Alakea Produce Market",
    "wof:placetype":"venue"
},
  "geometry": {"coordinates":[-157.86063200000001,21.306876],"type":"Point"}
}