{
  "type": "Feature",
  "properties": {
    "iso:country":"US",
    "sg:address":"3250 Kalihiwai Rd",
    "sg:city":"Kilauea",
    "sg:classifiers":[
        {
            "category":"Professional",
            "type":"Services"
        }
    ],
    "sg:phone":"+1 808 826 0222",
    "sg:postcode":"96754",
    "sg:province":"HI",
    "sg:tags":[
        "establishment"
    ],
    "wof:name":"Clarum Corp",
    "wof:placetype":"venue"
},
  "geometry": {"coordinates":[-159.43480299999999,22.214515],"type":"Point"}
}