{
  "type": "Feature",
  "properties": {
    "iso:country":"US",
    "sg:address":"335 Merchant St",
    "sg:city":"Honolulu",
    "sg:classifiers":[
        {
            "category":"Government",
            "subcategory":"Court House",
            "type":"Public Place"
        }
    ],
    "sg:phone":"+1 808 548 6500",
    "sg:postcode":"96813",
    "sg:province":"HI",
    "sg:tags":[
        "state",
        "appeal"
    ],
    "wof:name":"Intermediate Court of Appeals",
    "wof:placetype":"venue"
},
  "geometry": {"coordinates":[-157.860196,21.306217],"type":"Point"}
}