{
  "type": "Feature",
  "properties": {
    "iso:country":"US",
    "sg:address":"899 Iwaena St",
    "sg:city":"Aiea",
    "sg:classifiers":[
        {
            "category":"Retail",
            "subcategory":"Laundry & Dry Cleaning",
            "type":"Services"
        }
    ],
    "sg:phone":"+1 808 484 5010",
    "sg:postcode":"96701",
    "sg:province":"HI",
    "sg:tags":[
        "linen",
        "supply"
    ],
    "wof:name":"Courtesy Linen Svc",
    "wof:placetype":"venue"
},
  "geometry": {"coordinates":[-157.910346,21.376671],"type":"Point"}
}