{
  "type": "Feature",
  "properties": {
    "iso:country":"US",
    "sg:address":"111 N King St",
    "sg:city":"Honolulu",
    "sg:classifiers":[
        {
            "category":"Manufacturing",
            "subcategory":"Printing",
            "type":"Manufacturing & Wholesale Goods"
        }
    ],
    "sg:phone":"+1 808 534 1688",
    "sg:postcode":"96817",
    "sg:province":"HI",
    "sg:tags":[
        "commercial"
    ],
    "wof:name":"PCAS Printing & Design",
    "wof:placetype":"venue"
},
  "geometry": {"coordinates":[-157.86386200000001,21.31238],"type":"Point"}
}