{
  "type": "Feature",
  "properties": {
    "iso:country":"US",
    "sg:address":"1300 Pali Hwy",
    "sg:city":"Honolulu",
    "sg:classifiers":[
        {
            "category":"Health Services",
            "subcategory":"Doctor",
            "type":"Services"
        }
    ],
    "sg:phone":"+1 808 524 2461",
    "sg:postcode":"96813",
    "sg:province":"HI",
    "sg:tags":[
        "medical"
    ],
    "wof:name":"Ritt Chong MD",
    "wof:placetype":"venue"
},
  "geometry": {"coordinates":[-157.85689500000001,21.312374],"type":"Point"}
}