{
  "type": "Feature",
  "properties": {
    "iso:country":"US",
    "sg:address":"521 Kamehameha Hwy",
    "sg:city":"Haleiwa",
    "sg:classifiers":[
        {
            "category":"Retail",
            "subcategory":"Portrait Studio",
            "type":"Services"
        }
    ],
    "sg:phone":"+1 808 637 6696",
    "sg:postcode":"96712",
    "sg:province":"HI",
    "sg:tags":[
        "photographer"
    ],
    "wof:name":"Jon Mozo LTD",
    "wof:placetype":"venue"
},
  "geometry": {"coordinates":[-158.05631399999999,21.659459],"type":"Point"}
}