{
  "type": "Feature",
  "properties": {
    "iso:country":"US",
    "sg:address":"388 Ponahawai St",
    "sg:city":"Hilo",
    "sg:classifiers":[
        {
            "category":"Real Estate",
            "subcategory":"Developer",
            "type":"Services"
        }
    ],
    "sg:phone":"+1 808 961 6051",
    "sg:postcode":"96720",
    "sg:province":"HI",
    "sg:tags":[
        "cemetery"
    ],
    "wof:name":"Homelani Memorial Park Inc",
    "wof:placetype":"venue"
},
  "geometry": {"coordinates":[-155.089789,19.718127],"type":"Point"}
}