{
  "type": "Feature",
  "properties": {
    "iso:country":"US",
    "sg:address":"2430 Campus Rd",
    "sg:city":"Honolulu",
    "sg:classifiers":[
        {
            "category":"Organizations",
            "subcategory":"Non-profit Organization",
            "type":"Services"
        }
    ],
    "sg:phone":"+1 808 956 5640",
    "sg:postcode":"96822",
    "sg:province":"HI",
    "sg:tags":[
        "social"
    ],
    "wof:name":"Psychscial Rhblttion Univ Hawa",
    "wof:placetype":"venue"
},
  "geometry": {"coordinates":[-157.81933599999999,21.299428],"type":"Point"}
}