{
  "type": "Feature",
  "properties": {
    "addr:full":"333 S Mokapu St Kahului HI 96732",
    "addr:housenumber":"333",
    "addr:postcode":"96732",
    "addr:street":"S Mokapu St",
    "iso:country":"US",
    "sg:address":"333 S Mokapu St",
    "sg:city":"Kahului",
    "sg:classifiers":[
        {
            "category":"Professional",
            "subcategory":"Secretarial Services",
            "type":"Services"
        }
    ],
    "sg:phone":"+1 808 877 0432",
    "sg:postcode":"96732",
    "sg:province":"HI",
    "sg:tags":[
        "reporting"
    ],
    "wof:name":"Element Pictures LLC",
    "wof:placetype":"venue"
},
  "geometry": {"coordinates":[-156.468087,20.871789],"type":"Point"}
}