{
  "type": "Feature",
  "properties": {
    "addr:full":"101 Aupuni St Hilo HI 96720",
    "addr:housenumber":"101",
    "addr:postcode":"96720",
    "addr:street":"Aupuni St",
    "iso:country":"US",
    "sg:address":"101 Aupuni St",
    "sg:city":"Hilo",
    "sg:classifiers":[
        {
            "category":"Government",
            "subcategory":"Office",
            "type":"Public Place"
        }
    ],
    "sg:phone":"+1 808 933 8898",
    "sg:postcode":"96720",
    "sg:province":"HI",
    "sg:tags":[
        "state",
        "resource"
    ],
    "wof:name":"Welfare Fraud Investigations",
    "wof:placetype":"venue"
},
  "geometry": {"coordinates":[-155.077651,19.718284],"type":"Point"}
}