{
  "type": "Feature",
  "properties": {
    "iso:country":"US",
    "sg:address":"744 Kaima Pl",
    "sg:city":"Hilo",
    "sg:classifiers":[
        {
            "category":"Food & Beverages",
            "subcategory":"Groceries & Convenience Stores",
            "type":"Retail Goods"
        }
    ],
    "sg:phone":"+1 808 969 6639",
    "sg:postcode":"96720",
    "sg:province":"HI",
    "wof:name":"Shell",
    "wof:placetype":"venue"
},
  "geometry": {"coordinates":[-155.08806300000001,19.672033],"type":"Point"}
}