{
  "type": "Feature",
  "properties": {
    "addr:full":"370 Aloha Kona Dr Kailua Kona HI 96740",
    "addr:housenumber":"370",
    "addr:postcode":"96740",
    "addr:street":"Aloha Kona Dr",
    "iso:country":"US",
    "sg:address":"370 Aloha Kona Dr",
    "sg:city":"Kailua Kona",
    "sg:classifiers":[
        {
            "category":"Professional",
            "subcategory":"Research",
            "type":"Services"
        }
    ],
    "sg:phone":"+1 808 989 0637",
    "sg:postcode":"96740",
    "sg:province":"HI",
    "sg:tags":[
        "nonphysical",
        "commercial"
    ],
    "wof:name":"Darnall & Assoc Inc",
    "wof:placetype":"venue"
},
  "geometry": {"coordinates":[-155.96875299999999,19.640122],"type":"Point"}
}