{
  "type": "Feature",
  "properties": {
    "iso:country":"US",
    "sg:address":"420 Ward Ave",
    "sg:city":"Honolulu",
    "sg:classifiers":[
        {
            "category":"Professional",
            "subcategory":"Research",
            "type":"Services"
        }
    ],
    "sg:phone":"+1 808 593 2211",
    "sg:postcode":"96814",
    "sg:province":"HI",
    "sg:tags":[
        "biological",
        "noncommercial",
        "organization"
    ],
    "wof:name":"Dolphin Institute",
    "wof:placetype":"venue"
},
  "geometry": {"coordinates":[-157.854285,21.297544],"type":"Point"}
}