{
  "type": "Feature",
  "properties": {
    "addr:full":"4374 Kukui Grove St Lihue HI 96766",
    "addr:postcode":"4374;96766",
    "addr:street":"Kukui Grove St",
    "iso:country":"US",
    "sg:address":"4374 Kukui Grove St",
    "sg:city":"Lihue",
    "sg:classifiers":[
        {
            "category":"Health Services",
            "subcategory":"Health Practitioner",
            "type":"Services"
        }
    ],
    "sg:phone":"+1 808 246 0011",
    "sg:postcode":"96766",
    "sg:province":"HI",
    "sg:tags":[
        "psychologist"
    ],
    "wof:name":"Minnie Boggs Eiko PHD",
    "wof:placetype":"venue"
},
  "geometry": {"coordinates":[-159.37674000000001,21.970905],"type":"Point"}
}