{
  "type": "Feature",
  "properties": {
    "iso:country":"US",
    "sg:address":"3180 Koapaka St",
    "sg:city":"Honolulu",
    "sg:classifiers":[
        {
            "category":"Shopping",
            "subcategory":"Bicycles & Sporting Goods",
            "type":"Retail Goods"
        }
    ],
    "sg:phone":"+1 808 833 8731",
    "sg:postcode":"96819",
    "sg:province":"HI",
    "wof:name":"Island Archer",
    "wof:placetype":"venue"
},
  "geometry": {"coordinates":[-157.91054500000001,21.335361],"type":"Point"}
}