{
  "type": "Feature",
  "properties": {
    "iso:country":"US",
    "sg:address":"4211 Waialae Ave",
    "sg:city":"Honolulu",
    "sg:classifiers":[
        {
            "category":"Restaurant",
            "type":"Food & Drink"
        }
    ],
    "sg:phone":"+1 808 735 6889",
    "sg:postcode":"96816",
    "sg:province":"HI",
    "wof:name":"Ba-Le Sandwich Shop",
    "wof:placetype":"venue"
},
  "geometry": {"coordinates":[-157.78477100000001,21.278289],"type":"Point"}
}