{
  "type": "Feature",
  "properties": {
    "iso:country":"US",
    "sg:address":"1032 Lower Main St",
    "sg:city":"Wailuku",
    "sg:classifiers":[
        {
            "category":"Food & Beverages",
            "subcategory":"Liquor & Beverages",
            "type":"Retail Goods"
        }
    ],
    "sg:phone":"+1 808 242 5046",
    "sg:postcode":"96793",
    "sg:province":"HI",
    "sg:tags":[
        "alcoholic"
    ],
    "wof:name":"Aloha Liquor Etc Inc",
    "wof:placetype":"venue"
},
  "geometry": {"coordinates":[-156.48897500000001,20.899753],"type":"Point"}
}