{
  "type": "Feature",
  "properties": {
    "addr:full":"1146 12th Ave Honolulu HI 96816",
    "addr:housenumber":"1146",
    "addr:postcode":"96816",
    "addr:street":"12Th Ave",
    "iso:country":"US",
    "sg:address":"1146 12th Ave",
    "sg:city":"Honolulu",
    "sg:classifiers":[
        {
            "category":"Restaurant",
            "type":"Food & Drink"
        }
    ],
    "sg:phone":"+1 808 734 1337",
    "sg:postcode":"96816",
    "sg:province":"HI",
    "sg:tags":[
        "eating"
    ],
    "wof:name":"Duk Kee Chinese Restaurant Inc",
    "wof:placetype":"venue"
},
  "geometry": {"coordinates":[-157.79929300000001,21.28194],"type":"Point"}
}