{
  "type": "Feature",
  "properties": {
    "addr:full":"609 Keaahala Rd Kaneohe HI 96744",
    "addr:housenumber":"609",
    "addr:postcode":"96744",
    "addr:street":"Keaahala Rd",
    "iso:country":"US",
    "sg:address":"609 Keaahala Rd",
    "sg:city":"Kaneohe",
    "sg:classifiers":[
        {
            "category":"Building & Trades",
            "subcategory":"Construction",
            "type":"Services"
        }
    ],
    "sg:phone":"+1 808 841 8700",
    "sg:postcode":"96744",
    "sg:province":"HI",
    "sg:tags":[
        "glass",
        "work",
        "glazing"
    ],
    "wof:name":"Action Glass and Aluminum Inc",
    "wof:placetype":"venue"
},
  "geometry": {"coordinates":[-157.80809600000001,21.410808],"type":"Point"}
}