{
  "type": "Feature",
  "properties": {
    "iso:country":"US",
    "sg:address":"982 Moekahi St",
    "sg:city":"Waianae",
    "sg:classifiers":[
        {
            "category":"Home & Garden",
            "subcategory":"Building Materials",
            "type":"Retail Goods"
        },
        {
            "category":"Retail",
            "subcategory":"Repair Shop",
            "type":"Services"
        }
    ],
    "sg:phone":"+1 808 696 5396",
    "sg:postcode":"96792",
    "sg:province":"HI",
    "sg:tags":[
        "door"
    ],
    "wof:name":"Dan's Commercial Door Svc",
    "wof:placetype":"venue"
},
  "geometry": {"coordinates":[-158.17997099999999,21.439122],"type":"Point"}
}