{
  "type": "Feature",
  "properties": {
    "iso:country":"US",
    "sg:address":"2385 Waimano Home Rd",
    "sg:city":"Pearl City",
    "sg:classifiers":[
        {
            "category":"Education",
            "subcategory":"School",
            "type":"Public Place"
        }
    ],
    "sg:phone":"+1 808 453 1400",
    "sg:postcode":"96782",
    "sg:province":"HI",
    "sg:tags":[
        "academic",
        "special"
    ],
    "wof:name":"Special Education Ctr-Hawaii",
    "wof:placetype":"venue"
},
  "geometry": {"coordinates":[-157.95491699999999,21.415598],"type":"Point"}
}