{
  "type": "Feature",
  "properties": {
    "iso:country":"US",
    "sg:address":"2155 Kalakaua Ave",
    "sg:city":"Honolulu",
    "sg:classifiers":[
        {
            "category":"Travel",
            "subcategory":"Hotels & Motels",
            "type":"Entertainment"
        },
        {
            "category":"Professional",
            "subcategory":"Management & Consulting",
            "type":"Services"
        }
    ],
    "sg:phone":"+1 808 926 5900",
    "sg:postcode":"96815",
    "sg:province":"HI",
    "sg:tags":[
        "resort"
    ],
    "wof:name":"Marc Resorts Hawaii",
    "wof:placetype":"venue"
},
  "geometry": {"coordinates":[-157.83001400000001,21.28034],"type":"Point"}
}