{
  "type": "Feature",
  "properties": {
    "addr:full":"2332 Kalakaua Ave Honolulu HI 96815",
    "addr:housenumber":"2332",
    "addr:postcode":"96815",
    "addr:street":"Kalakaua Ave",
    "iso:country":"US",
    "sg:address":"2332 Kalakaua Ave",
    "sg:city":"Honolulu",
    "sg:classifiers":[
        {
            "category":"Shopping",
            "subcategory":"Clothing, Apparel, & Fashions",
            "type":"Retail Goods"
        }
    ],
    "sg:phone":"+1 808 922 4791",
    "sg:postcode":"96815",
    "sg:province":"HI",
    "sg:tags":[
        "screen",
        "printed",
        "t"
    ],
    "wof:name":"Crazy Shirts",
    "wof:placetype":"venue"
},
  "geometry": {"coordinates":[-157.82660300000001,21.277138],"type":"Point"}
}