{
  "type": "Feature",
  "properties": {
    "addr:full":"641 Mua St Kahului HI 96732",
    "addr:housenumber":"641",
    "addr:postcode":"96732",
    "addr:street":"Mua St",
    "iso:country":"US",
    "sg:address":"641 Mua St",
    "sg:city":"Kahului",
    "sg:classifiers":[
        {
            "category":"Government",
            "subcategory":"Office",
            "type":"Public Place"
        }
    ],
    "sg:phone":"+1 808 873 3560",
    "sg:postcode":"96732",
    "sg:province":"HI",
    "sg:tags":[
        "administrative",
        "program",
        "health"
    ],
    "wof:name":"State Hawaii Health Department",
    "wof:placetype":"venue"
},
  "geometry": {"coordinates":[-156.44634400000001,20.890942],"type":"Point"}
}