{
  "type": "Feature",
  "properties": {
    "iso:country":"US",
    "sg:address":"230 Hoea Rd",
    "sg:city":"Kapaau",
    "sg:classifiers":[
        {
            "category":"Wholesale",
            "subcategory":"Poultry",
            "type":"Manufacturing & Wholesale Goods"
        }
    ],
    "sg:phone":"+1 808 889 5976",
    "sg:postcode":"96719",
    "sg:province":"HI",
    "sg:tags":[
        "eggs"
    ],
    "wof:name":"Big Island Poultry Inc",
    "wof:placetype":"venue"
},
  "geometry": {"coordinates":[-155.82818499999999,20.255817],"type":"Point"}
}