{
  "type": "Feature",
  "properties": {
    "addr:full":"6600 Kalanianaole Hwy Honolulu HI 96825",
    "addr:postcode":"6600;96825",
    "addr:street":"Kalanianaole Hwy",
    "iso:country":"US",
    "sg:address":"6600 Kalanianaole Hwy",
    "sg:city":"Honolulu",
    "sg:classifiers":[
        {
            "category":"Banks & Credit Unions",
            "subcategory":"Bank",
            "type":"Services"
        }
    ],
    "sg:phone":"+1 808 394 5252",
    "sg:postcode":"96825",
    "sg:province":"HI",
    "sg:tags":[
        "escrow"
    ],
    "sg:website":"www.tghawaii.com",
    "wof:name":"Title Guaranty Escrow Svc",
    "wof:placetype":"venue"
},
  "geometry": {"coordinates":[-157.71704700000001,21.284382],"type":"Point"}
}