{
  "type": "Feature",
  "properties": {
    "iso:country":"US",
    "sg:address":"930 Kekaulike St",
    "sg:city":"Honolulu",
    "sg:classifiers":[
        {
            "category":"Bars & Pubs",
            "type":"Food & Drink"
        }
    ],
    "sg:phone":"+1 808 537 3710",
    "sg:postcode":"96817",
    "sg:province":"HI",
    "sg:tags":[
        "lounge",
        "cocktail"
    ],
    "wof:name":"Snack Minato",
    "wof:placetype":"venue"
},
  "geometry": {"coordinates":[-157.86468400000001,21.312213],"type":"Point"}
}