{
  "type": "Feature",
  "properties": {
    "iso:country":"US",
    "sg:address":"3784 Pohoiki Rd",
    "sg:city":"Pahoa",
    "sg:classifiers":[
        {
            "category":"Building & Trades",
            "subcategory":"Construction",
            "type":"Services"
        }
    ],
    "sg:phone":"+1 808 965 9855",
    "sg:postcode":"96778",
    "sg:province":"HI",
    "sg:tags":[
        "steel",
        "erectors"
    ],
    "wof:name":"Steel Erectors Inc",
    "wof:placetype":"venue"
},
  "geometry": {"coordinates":[-154.901726,19.479774],"type":"Point"}
}