{
  "type": "Feature",
  "properties": {
    "iso:country":"US",
    "sg:address":"2122 Kaliawa St",
    "sg:city":"Honolulu",
    "sg:classifiers":[
        {
            "category":"Retail",
            "subcategory":"Auto Repair",
            "type":"Services"
        }
    ],
    "sg:phone":"+1 808 841 6141",
    "sg:postcode":"96819",
    "sg:province":"HI",
    "sg:tags":[
        "repairing",
        "automobile"
    ],
    "wof:name":"Pride Auto Repair",
    "wof:placetype":"venue"
},
  "geometry": {"coordinates":[-157.88977600000001,21.324229],"type":"Point"}
}