{
  "type": "Feature",
  "properties": {
    "iso:country":"US",
    "sg:address":"7284 Kauhako St",
    "sg:city":"Honolulu",
    "sg:classifiers":[
        {
            "category":"Building & Trades",
            "subcategory":"Electrical",
            "type":"Services"
        }
    ],
    "sg:phone":"+1 808 393 2434",
    "sg:postcode":"96825",
    "sg:province":"HI",
    "sg:tags":[
        "electrical",
        "contractor"
    ],
    "wof:name":"Schenks Specialized Services",
    "wof:placetype":"venue"
},
  "geometry": {"coordinates":[-157.70021600000001,21.278032],"type":"Point"}
}