{
  "type": "Feature",
  "properties": {
    "iso:country":"US",
    "sg:address":"240 Kehepue Loop",
    "sg:city":"Mililani",
    "sg:classifiers":[
        {
            "category":"Real Estate",
            "subcategory":"Real Estate Agent",
            "type":"Services"
        }
    ],
    "sg:phone":"+1 808 625 0520",
    "sg:postcode":"96789",
    "sg:province":"HI",
    "sg:tags":[
        "appraiser"
    ],
    "wof:name":"Gene A Castagnetti",
    "wof:placetype":"venue"
},
  "geometry": {"coordinates":[-158.019338,21.451375],"type":"Point"}
}