{
  "type": "Feature",
  "properties": {
    "iso:country":"US",
    "sg:address":"1702 Kewalo St",
    "sg:city":"Honolulu",
    "sg:classifiers":[
        {
            "category":"Health Services",
            "subcategory":"Doctor",
            "type":"Services"
        }
    ],
    "sg:phone":"+1 808 538 8792",
    "sg:postcode":"96822",
    "sg:province":"HI",
    "sg:tags":[
        "medical"
    ],
    "wof:name":"Chen Yen Wang NP Inc",
    "wof:placetype":"venue"
},
  "geometry": {"coordinates":[-157.835477,21.307895],"type":"Point"}
}