{
  "type": "Feature",
  "properties": {
    "addr:full":"1458 Hoomahie Loop Pearl City HI 96782",
    "addr:housenumber":"1458",
    "addr:postcode":"96782",
    "addr:street":"Hoomahie Loop",
    "iso:country":"US",
    "sg:address":"1458 Hoomahie Loop",
    "sg:city":"Pearl City",
    "sg:classifiers":[
        {
            "category":"Retail",
            "subcategory":"Laundry & Dry Cleaning",
            "type":"Services"
        }
    ],
    "sg:phone":"+1 808 455 6174",
    "sg:postcode":"96782",
    "sg:province":"HI",
    "sg:tags":[
        "cleaners",
        "rug",
        "carpet"
    ],
    "wof:name":"Bears Carpet Care",
    "wof:placetype":"venue"
},
  "geometry": {"coordinates":[-157.95409599999999,21.40221],"type":"Point"}
}