{
  "type": "Feature",
  "properties": {
    "iso:country":"US",
    "sg:address":"950 Kaaholo St",
    "sg:city":"Waipahu",
    "sg:classifiers":[
        {
            "category":"Professional",
            "type":"Services"
        }
    ],
    "sg:phone":"+1 808 438 2293",
    "sg:postcode":"96797",
    "sg:province":"HI",
    "wof:name":"Windelina M Govina",
    "wof:placetype":"venue"
},
  "geometry": {"coordinates":[-158.02052499999999,21.395175],"type":"Point"}
}