{
  "type": "Feature",
  "properties": {
    "iso:country":"US",
    "sg:address":"631 Moana St",
    "sg:city":"Laie",
    "sg:classifiers":[
        {
            "category":"Travel",
            "subcategory":"Campground",
            "type":"Entertainment"
        }
    ],
    "sg:phone":"+1 808 293 8800",
    "sg:postcode":"96762",
    "sg:province":"HI",
    "sg:tags":[
        "camp"
    ],
    "wof:name":"Hawaii Seaside Sports Camp",
    "wof:placetype":"venue"
},
  "geometry": {"coordinates":[-157.927471,21.649406],"type":"Point"}
}