{
  "type": "Feature",
  "properties": {
    "iso:country":"US",
    "sg:address":"441 Walina St",
    "sg:city":"Honolulu",
    "sg:classifiers":[
        {
            "category":"Real Estate",
            "subcategory":"Real Estate Operator",
            "type":"Services"
        }
    ],
    "sg:phone":"+1 808 922 1052",
    "sg:postcode":"96815",
    "sg:province":"HI",
    "sg:tags":[
        "apartment"
    ],
    "wof:name":"441 Walina St LLC",
    "wof:placetype":"venue"
},
  "geometry": {"coordinates":[-157.82411500000001,21.279192],"type":"Point"}
}