{
  "type": "Feature",
  "properties": {
    "addr:full":"5045 Huaala Pl Kailua Kona HI 96740",
    "addr:housenumber":"5045",
    "addr:postcode":"96740",
    "addr:street":"Huaala Pl",
    "iso:country":"US",
    "sg:address":"5045 Huaala Pl",
    "sg:city":"Kailua Kona",
    "sg:classifiers":[
        {
            "category":"Organizations",
            "subcategory":"Membership Organization",
            "type":"Services"
        }
    ],
    "sg:phone":"+1 808 329 0559",
    "sg:postcode":"96740",
    "sg:province":"HI",
    "wof:name":"Salvation Army",
    "wof:placetype":"venue"
},
  "geometry": {"coordinates":[-155.98109099999999,19.672081],"type":"Point"}
}