{
  "type": "Feature",
  "properties": {
    "addr:full":"263 Kula Hwy Kula HI 96790",
    "addr:housenumber":"263",
    "addr:postcode":"96790",
    "addr:street":"Kula Hwy",
    "iso:country":"US",
    "sg:address":"263 Kula Hwy",
    "sg:city":"Kula",
    "sg:classifiers":[
        {
            "category":"Manufacturing",
            "subcategory":"Wood Products",
            "type":"Manufacturing & Wholesale Goods"
        }
    ],
    "sg:phone":"+1 808 878 2803",
    "sg:postcode":"96790",
    "sg:province":"HI",
    "sg:tags":[
        "mfg"
    ],
    "wof:name":"Pamjen Capital Inc",
    "wof:placetype":"venue"
},
  "geometry": {"coordinates":[-156.32725199999999,20.802699],"type":"Point"}
}