{
  "type": "Feature",
  "properties": {
    "iso:country":"US",
    "sg:address":"5483 Kaiwi St",
    "sg:city":"Kailua Kona",
    "sg:classifiers":[
        {
            "category":"Retail",
            "subcategory":"Auto Repair",
            "type":"Services"
        }
    ],
    "sg:phone":"+1 808 329 9599",
    "sg:postcode":"96740",
    "sg:province":"HI",
    "sg:tags":[
        "repairing",
        "automobile",
        "transmission"
    ],
    "wof:name":"Auto Transmission Systems",
    "wof:placetype":"venue"
},
  "geometry": {"coordinates":[-156.00081399999999,19.645721],"type":"Point"}
}