{
  "type": "Feature",
  "properties": {
    "iso:country":"US",
    "sg:address":"680 Iwilei Rd",
    "sg:city":"Honolulu",
    "sg:classifiers":[
        {
            "category":"Insurance",
            "subcategory":"Insurance Agent",
            "type":"Services"
        }
    ],
    "sg:phone":"+1 808 532 2888",
    "sg:postcode":"96817",
    "sg:province":"HI",
    "sg:tags":[
        "agency"
    ],
    "sg:website":"www.mutualunderwriters.com",
    "wof:name":"Mutual Underwriters",
    "wof:placetype":"venue"
},
  "geometry": {"coordinates":[-157.86953500000001,21.316097],"type":"Point"}
}