{
  "type": "Feature",
  "properties": {
    "iso:country":"US",
    "sg:address":"247 Hololani St",
    "sg:city":"Makawao",
    "sg:classifiers":[
        {
            "category":"Building & Trades",
            "subcategory":"Construction",
            "type":"Services"
        }
    ],
    "sg:phone":"+1 808 572 6970",
    "sg:postcode":"96768",
    "sg:province":"HI",
    "sg:tags":[
        "contractor"
    ],
    "wof:name":"F R Garcia Construction",
    "wof:placetype":"venue"
},
  "geometry": {"coordinates":[-156.35174799999999,20.840238],"type":"Point"}
}