{
  "type": "Feature",
  "properties": {
    "addr:full":"1100 Alakea St Honolulu HI 96813",
    "addr:housenumber":"1100",
    "addr:postcode":"96813",
    "addr:street":"Alakea St",
    "iso:country":"US",
    "sg:address":"1100 Alakea St",
    "sg:city":"Honolulu",
    "sg:classifiers":[
        {
            "category":"Shopping",
            "subcategory":"Computers & Home Electronics",
            "type":"Retail Goods"
        }
    ],
    "sg:phone":"+1 808 524 3111",
    "sg:postcode":"96813",
    "sg:province":"HI",
    "sg:tags":[
        "equipment",
        "dealer"
    ],
    "sg:website":"www.datacare.net",
    "wof:name":"Data Care Technologies",
    "wof:placetype":"venue"
},
  "geometry": {"coordinates":[-157.85816299999999,21.309891],"type":"Point"}
}