{
  "type": "Feature",
  "properties": {
    "addr:full":"2600 S King St Honolulu HI 96826",
    "addr:housenumber":"2600",
    "addr:postcode":"96826",
    "addr:street":"S King St",
    "iso:country":"US",
    "sg:address":"2600 S King St",
    "sg:city":"Honolulu",
    "sg:classifiers":[
        {
            "category":"Education",
            "subcategory":"Dance Studio",
            "type":"Public Place"
        }
    ],
    "sg:phone":"+1 808 951 4268",
    "sg:postcode":"96826",
    "sg:province":"HI",
    "sg:tags":[
        "instruction",
        "dancing"
    ],
    "wof:name":"Kamaka Kukona Designs",
    "wof:placetype":"venue"
},
  "geometry": {"coordinates":[-157.820875,21.291331],"type":"Point"}
}