{
  "type": "Feature",
  "properties": {
    "iso:country":"US",
    "sg:address":"1521 S King St",
    "sg:city":"Honolulu",
    "sg:classifiers":[
        {
            "category":"Personal",
            "type":"Services"
        }
    ],
    "sg:phone":"+1 808 791 4264",
    "sg:postcode":"96826",
    "sg:province":"HI",
    "sg:tags":[
        "therapist",
        "massage"
    ],
    "wof:name":"Aina Natural Therapies",
    "wof:placetype":"venue"
},
  "geometry": {"coordinates":[-157.83695800000001,21.297247],"type":"Point"}
}