{
  "type": "Feature",
  "properties": {
    "addr:full":"1046 Iwaena St Aiea HI 96701",
    "addr:housenumber":"1046",
    "addr:postcode":"96701",
    "addr:street":"Iwaena St",
    "iso:country":"US",
    "sg:address":"1046 Iwaena St",
    "sg:city":"Aiea",
    "sg:classifiers":[
        {
            "category":"Food & Beverages",
            "subcategory":"Specialty",
            "type":"Retail Goods"
        }
    ],
    "sg:phone":"+1 808 488 0096",
    "sg:postcode":"96701",
    "sg:province":"HI",
    "sg:tags":[
        "health",
        "diet"
    ],
    "wof:name":"Vitacorp International",
    "wof:placetype":"venue"
},
  "geometry": {"coordinates":[-157.91216,21.374631],"type":"Point"}
}