{
  "type": "Feature",
  "properties": {
    "addr:full":"3823 Lower Honoapiilani Rd Lahaina HI 96761",
    "addr:housenumber":"3823",
    "addr:postcode":"96761",
    "addr:street":"Lower Honoapiilani Rd",
    "iso:country":"US",
    "sg:address":"3823 Lower Honoapiilani Rd",
    "sg:city":"Lahaina",
    "sg:classifiers":[
        {
            "category":"Real Estate",
            "subcategory":"Real Estate Agent",
            "type":"Services"
        },
        {
            "category":"Real Estate",
            "subcategory":"Real Estate Operator",
            "type":"Services"
        }
    ],
    "sg:phone":"+1 808 669 0525",
    "sg:postcode":"96761",
    "sg:province":"HI",
    "sg:tags":[
        "condominium"
    ],
    "wof:name":"Nai'a Properties Vacation Rntl",
    "wof:placetype":"venue"
},
  "geometry": {"coordinates":[-156.686105,20.964065],"type":"Point"}
}