{
  "type": "Feature",
  "properties": {
    "iso:country":"US",
    "sg:address":"41 Ohiaku St",
    "sg:city":"Aiea",
    "sg:classifiers":[
        {
            "category":"Building & Trades",
            "subcategory":"Landscaping Services",
            "type":"Services"
        }
    ],
    "sg:phone":"+1 808 478 3795",
    "sg:postcode":"96701",
    "sg:province":"HI",
    "sg:tags":[
        "lawn",
        "maintenance",
        "grounds"
    ],
    "wof:name":"Abbar Yard Svc",
    "wof:placetype":"venue"
},
  "geometry": {"coordinates":[-157.93416199999999,21.364532],"type":"Point"}
}