{
  "type": "Feature",
  "properties": {
    "iso:country":"US",
    "sg:address":"1174 Waimanu St",
    "sg:city":"Honolulu",
    "sg:classifiers":[
        {
            "category":"Education",
            "subcategory":"Special Training",
            "type":"Public Place"
        }
    ],
    "sg:phone":"+1 808 596 8300",
    "sg:postcode":"96814",
    "sg:province":"HI",
    "sg:tags":[
        "instruction",
        "speaking"
    ],
    "wof:name":"American Academy Of Film & TV",
    "wof:placetype":"venue"
},
  "geometry": {"coordinates":[-157.849917,21.29464],"type":"Point"}
}