{
  "type": "Feature",
  "properties": {
    "addr:full":"345 Queen St Honolulu HI 96813",
    "addr:housenumber":"345",
    "addr:postcode":"96813",
    "addr:street":"Queen St",
    "iso:country":"US",
    "sg:address":"345 Queen St",
    "sg:city":"Honolulu",
    "sg:classifiers":[
        {
            "category":"Banks & Credit Unions",
            "subcategory":"Financial Services",
            "type":"Services"
        }
    ],
    "sg:phone":"+1 808 791 6810",
    "sg:postcode":"96813",
    "sg:province":"HI",
    "sg:tags":[
        "except",
        "real estate",
        "operator",
        "property",
        "investor"
    ],
    "wof:name":"Acapital Corporation",
    "wof:placetype":"venue"
},
  "geometry": {"coordinates":[-157.8612,21.305716],"type":"Point"}
}