{
  "type": "Feature",
  "properties": {
    "addr:full":"529 Mokauea St Honolulu HI 96819",
    "addr:housenumber":"529",
    "addr:postcode":"96819",
    "addr:street":"Mokauea St",
    "iso:country":"US",
    "sg:address":"529 Mokauea St",
    "sg:city":"Honolulu",
    "sg:classifiers":[
        {
            "category":"Travel",
            "subcategory":"Travel Agent",
            "type":"Entertainment"
        }
    ],
    "sg:phone":"+1 808 845 2793",
    "sg:postcode":"96819",
    "sg:province":"HI",
    "sg:tags":[
        "agency"
    ],
    "wof:name":"Guieb Travel Agency",
    "wof:placetype":"venue"
},
  "geometry": {"coordinates":[-157.881146,21.328197],"type":"Point"}
}