{
  "type": "Feature",
  "properties": {
    "iso:country":"US",
    "sg:address":"53 Lunalilo St",
    "sg:city":"Wailuku",
    "sg:classifiers":[
        {
            "category":"Wholesale",
            "subcategory":"Groceries",
            "type":"Manufacturing & Wholesale Goods"
        }
    ],
    "sg:phone":"+1 808 244 9153",
    "sg:postcode":"96793",
    "sg:province":"HI",
    "wof:name":"Quality Groceries Inc",
    "wof:placetype":"venue"
},
  "geometry": {"coordinates":[-156.493728,20.890143],"type":"Point"}
}