{
  "type": "Feature",
  "properties": {
    "iso:country":"US",
    "sg:address":"230 Libby St",
    "sg:city":"Honolulu",
    "sg:classifiers":[
        {
            "category":"Wholesale",
            "subcategory":"Seafood",
            "type":"Manufacturing & Wholesale Goods"
        }
    ],
    "sg:phone":"+1 808 847 2580",
    "sg:postcode":"96819",
    "sg:province":"HI",
    "wof:name":"Wing Sing Seafood Inc",
    "wof:placetype":"venue"
},
  "geometry": {"coordinates":[-157.88274699999999,21.320873],"type":"Point"}
}