{
  "type": "Feature",
  "properties": {
    "iso:country":"US",
    "sg:address":"273 Hui Iwa St",
    "sg:city":"Kaneohe",
    "sg:classifiers":[
        {
            "category":"Professional",
            "subcategory":"Engineering",
            "type":"Services"
        }
    ],
    "sg:phone":"+1 808 239 8206",
    "sg:postcode":"96744",
    "sg:province":"HI",
    "sg:tags":[
        "transportation",
        "engineer"
    ],
    "wof:name":"Rowell Phillip & Assoc",
    "wof:placetype":"venue"
},
  "geometry": {"coordinates":[-157.824366,21.43641],"type":"Point"}
}