{
  "type": "Feature",
  "properties": {
    "iso:country":"US",
    "sg:address":"1001 Kalanianaole Hwy",
    "sg:city":"Kailua",
    "sg:classifiers":[
        {
            "category":"Home & Garden",
            "subcategory":"Garden Supply",
            "type":"Retail Goods"
        }
    ],
    "sg:phone":"+1 808 585 9093",
    "sg:postcode":"96734",
    "sg:province":"HI",
    "sg:tags":[
        "tree"
    ],
    "wof:name":"Oahu Tree Experts Inc",
    "wof:placetype":"venue"
},
  "geometry": {"coordinates":[-157.766818,21.377287],"type":"Point"}
}