{
  "type": "Feature",
  "properties": {
    "addr:full":"99 Aupuni St Hilo HI 96720",
    "addr:housenumber":"99",
    "addr:postcode":"96720",
    "addr:street":"Aupuni St",
    "iso:country":"US",
    "sg:address":"99 Aupuni St",
    "sg:city":"Hilo",
    "sg:classifiers":[
        {
            "category":"Real Estate",
            "subcategory":"Real Estate Agent",
            "type":"Services"
        }
    ],
    "sg:phone":"+1 808 969 1850",
    "sg:postcode":"96720",
    "sg:province":"HI",
    "sg:website":"www.easthawaiirealty.com",
    "wof:name":"Bowman Realty",
    "wof:placetype":"venue"
},
  "geometry": {"coordinates":[-155.07762,19.718255],"type":"Point"}
}