{
  "type": "Feature",
  "properties": {
    "iso:country":"US",
    "sg:address":"920 Ward Ave",
    "sg:city":"Honolulu",
    "sg:classifiers":[
        {
            "category":"Professional",
            "subcategory":"Lawyer & Legal Services",
            "type":"Services"
        }
    ],
    "sg:phone":"+1 808 949 0095",
    "sg:postcode":"96814",
    "sg:province":"HI",
    "sg:tags":[
        "attorney"
    ],
    "wof:name":"Steven HS Wong Offices",
    "wof:placetype":"venue"
},
  "geometry": {"coordinates":[-157.852045,21.299795],"type":"Point"}
}