{
  "type": "Feature",
  "properties": {
    "iso:country":"US",
    "sg:address":"6038 Kolopua St",
    "sg:city":"Kapaa",
    "sg:classifiers":[
        {
            "category":"Health Services",
            "subcategory":"Chiropractor",
            "type":"Services"
        }
    ],
    "sg:phone":"+1 808 822 4893",
    "sg:postcode":"96746",
    "sg:province":"HI",
    "wof:name":"Robert A Zelkovsky DC",
    "wof:placetype":"venue"
},
  "geometry": {"coordinates":[-159.372094,22.05777],"type":"Point"}
}