{
  "type": "Feature",
  "properties": {
    "addr:full":"200 S High St Wailuku HI 96793",
    "addr:housenumber":"200",
    "addr:postcode":"96793",
    "addr:street":"S High St",
    "iso:country":"US",
    "sg:address":"200 S High St",
    "sg:city":"Wailuku",
    "sg:classifiers":[
        {
            "category":"Government",
            "subcategory":"Office",
            "type":"Public Place"
        }
    ],
    "sg:phone":"+1 808 270 7511",
    "sg:postcode":"96793",
    "sg:province":"HI",
    "sg:tags":[
        "county",
        "govt"
    ],
    "wof:name":"Department of Transportation",
    "wof:placetype":"venue"
},
  "geometry": {"coordinates":[-156.50747100000001,20.888755],"type":"Point"}
}