{
  "type": "Feature",
  "properties": {
    "addr:full":"2833 E Manoa Rd Honolulu HI 96822",
    "addr:housenumber":"2833",
    "addr:postcode":"96822",
    "addr:street":"E Manoa Rd",
    "iso:country":"US",
    "sg:address":"2833 E Manoa Rd",
    "sg:city":"Honolulu",
    "sg:classifiers":[
        {
            "category":"Arts & Performance",
            "subcategory":"Theater",
            "type":"Entertainment"
        }
    ],
    "sg:phone":"+1 808 988 6131",
    "sg:postcode":"96822",
    "sg:province":"HI",
    "sg:tags":[
        "live"
    ],
    "sg:website":"www.manoavalleytheatre.com",
    "wof:name":"Manoa Valley Theatre",
    "wof:placetype":"venue"
},
  "geometry": {"coordinates":[-157.80962700000001,21.310058],"type":"Point"}
}