{
  "type": "Feature",
  "properties": {
    "addr:full":"1050 Kaaholo St Waipahu HI 96797",
    "addr:housenumber":"1050",
    "addr:postcode":"96797",
    "addr:street":"Kaaholo St",
    "iso:country":"US",
    "sg:address":"1050 Kaaholo St",
    "sg:city":"Waipahu",
    "sg:classifiers":[
        {
            "category":"Professional",
            "subcategory":"Accounting & Tax Preparation",
            "type":"Services"
        }
    ],
    "sg:phone":"+1 808 676 8351",
    "sg:postcode":"96797",
    "sg:province":"HI",
    "wof:name":"Milagros Beleon",
    "wof:placetype":"venue"
},
  "geometry": {"coordinates":[-158.02340000000001,21.397352],"type":"Point"}
}