{
  "type": "Feature",
  "properties": {
    "iso:country":"US",
    "sg:address":"733 Bishop St",
    "sg:city":"Honolulu",
    "sg:classifiers":[
        {
            "category":"Professional",
            "subcategory":"Accounting & Tax Preparation",
            "type":"Services"
        }
    ],
    "sg:phone":"+1 808 524 0748",
    "sg:postcode":"96813",
    "sg:province":"HI",
    "sg:tags":[
        "accountant"
    ],
    "wof:name":"Pacific Outsourcing Group",
    "wof:placetype":"venue"
},
  "geometry": {"coordinates":[-157.86289500000001,21.307425],"type":"Point"}
}