{
  "type": "Feature",
  "properties": {
    "iso:country":"US",
    "sg:address":"1820 Algaroba St",
    "sg:city":"Honolulu",
    "sg:classifiers":[
        {
            "category":"Building & Trades",
            "subcategory":"Landscaping Services",
            "type":"Services"
        }
    ],
    "sg:phone":"+1 808 942 5553",
    "sg:postcode":"96826",
    "sg:province":"HI",
    "sg:tags":[
        "designer",
        "landscape"
    ],
    "wof:name":"Randal Fujimoto Landscape Arch",
    "wof:placetype":"venue"
},
  "geometry": {"coordinates":[-157.831783,21.294672],"type":"Point"}
}