{
  "type": "Feature",
  "properties": {
    "iso:country":"US",
    "sg:address":"5290 Kalanianaole Hwy",
    "sg:city":"Honolulu",
    "sg:classifiers":[
        {
            "category":"Professional",
            "subcategory":"Business Services",
            "type":"Services"
        }
    ],
    "sg:phone":"+1 808 373 4593",
    "sg:postcode":"96821",
    "sg:province":"HI",
    "sg:tags":[
        "consulting"
    ],
    "wof:name":"Esteem",
    "wof:placetype":"venue"
},
  "geometry": {"coordinates":[-157.750789,21.278394],"type":"Point"}
}