{
  "type": "Feature",
  "properties": {
    "iso:country":"US",
    "sg:address":"2703 Puu Hoolai St",
    "sg:city":"Kihei",
    "sg:classifiers":[
        {
            "category":"Professional",
            "subcategory":"Art Services",
            "type":"Services"
        }
    ],
    "sg:phone":"+1 808 873 0626",
    "sg:postcode":"96753",
    "sg:province":"HI",
    "sg:tags":[
        "graphic",
        "designer"
    ],
    "wof:name":"Rebelo Design",
    "wof:placetype":"venue"
},
  "geometry": {"coordinates":[-156.43884800000001,20.712033],"type":"Point"}
}