{
  "type": "Feature",
  "properties": {
    "iso:country":"US",
    "sg:address":"220 S King St",
    "sg:city":"Honolulu",
    "sg:classifiers":[
        {
            "category":"Professional",
            "subcategory":"Lawyer & Legal Services",
            "type":"Services"
        }
    ],
    "sg:phone":"+1 808 526 1122",
    "sg:postcode":"96813",
    "sg:province":"HI",
    "sg:tags":[
        "attorney"
    ],
    "wof:name":"Donald R Hidani",
    "wof:placetype":"venue"
},
  "geometry": {"coordinates":[-157.86040600000001,21.307206],"type":"Point"}
}