{
  "type": "Feature",
  "properties": {
    "iso:country":"US",
    "sg:address":"2274 Kolo Rd",
    "sg:city":"Kilauea",
    "sg:classifiers":[
        {
            "category":"Professional",
            "subcategory":"Employment Agencies",
            "type":"Services"
        }
    ],
    "sg:phone":"+1 808 828 1040",
    "sg:postcode":"96754",
    "sg:province":"HI",
    "sg:tags":[
        "leasing"
    ],
    "wof:name":"Employee Leasing Co Of Hawaii",
    "wof:placetype":"venue"
},
  "geometry": {"coordinates":[-159.40006099999999,22.202169],"type":"Point"}
}