{
  "type": "Feature",
  "properties": {
    "iso:country":"US",
    "sg:address":"529 Keaahala Rd",
    "sg:city":"Kaneohe",
    "sg:classifiers":[
        {
            "category":"Recreation",
            "type":"Entertainment"
        }
    ],
    "sg:phone":"+1 808 233 7330",
    "sg:postcode":"96744",
    "sg:province":"HI",
    "sg:tags":[
        "parks"
    ],
    "wof:name":"Kaneohe Community Park",
    "wof:placetype":"venue"
},
  "geometry": {"coordinates":[-157.801389,21.414822],"type":"Point"}
}