{
  "type": "Feature",
  "properties": {
    "addr:full":"3149 N Nimitz Hwy Honolulu HI 96819",
    "addr:housenumber":"3149",
    "addr:postcode":"96819",
    "addr:street":"N Nimitz Hwy",
    "iso:country":"US",
    "sg:address":"3149 N Nimitz Hwy",
    "sg:city":"Honolulu",
    "sg:classifiers":[
        {
            "category":"Retail",
            "subcategory":"Repair Shop",
            "type":"Services"
        }
    ],
    "sg:phone":"+1 808 836 1144",
    "sg:postcode":"96819",
    "sg:province":"HI",
    "sg:tags":[
        "scooter",
        "motorcycle",
        "motor"
    ],
    "wof:name":"South Seas Honda Yamaha BMW",
    "wof:placetype":"venue"
},
  "geometry": {"coordinates":[-157.911382,21.336386],"type":"Point"}
}