{
  "type": "Feature",
  "properties": {
    "iso:country":"US",
    "sg:address":"1441 Kapiolani Blvd",
    "sg:city":"Honolulu",
    "sg:classifiers":[
        {
            "category":"Real Estate",
            "subcategory":"Real Estate Agent",
            "type":"Services"
        }
    ],
    "sg:phone":"+1 808 949 5599",
    "sg:postcode":"96814",
    "sg:province":"HI",
    "wof:name":"Home808",
    "wof:placetype":"venue"
},
  "geometry": {"coordinates":[-157.844087,21.293729],"type":"Point"}
}