{
  "type": "Feature",
  "properties": {
    "iso:country":"US",
    "sg:address":"6379 Kenika Pl",
    "sg:city":"Kailua Kona",
    "sg:classifiers":[
        {
            "category":"Wholesale",
            "subcategory":"Durable Goods & Equipment",
            "type":"Manufacturing & Wholesale Goods"
        }
    ],
    "sg:phone":"+1 808 334 0525",
    "sg:postcode":"96740",
    "sg:province":"HI",
    "sg:tags":[
        "instrument",
        "musical"
    ],
    "sg:website":"www.ukulelesofkona.com",
    "wof:name":"O Kona Ukuleles & Guitars",
    "wof:placetype":"venue"
},
  "geometry": {"coordinates":[-155.96669199999999,19.606425],"type":"Point"}
}