{
  "type": "Feature",
  "properties": {
    "addr:full":"1448 Kemoa Pl Wailuku HI 96793",
    "addr:housenumber":"1448",
    "addr:postcode":"96793",
    "addr:street":"Kemoa Pl",
    "iso:country":"US",
    "sg:address":"1448 Kemoa Pl",
    "sg:city":"Wailuku",
    "sg:classifiers":[
        {
            "category":"Wholesale",
            "subcategory":"Non-durable Goods",
            "type":"Manufacturing & Wholesale Goods"
        }
    ],
    "sg:phone":"+1 808 244 7521",
    "sg:postcode":"96793",
    "sg:province":"HI",
    "wof:name":"Kealailani Inc",
    "wof:placetype":"venue"
},
  "geometry": {"coordinates":[-156.50764100000001,20.857717],"type":"Point"}
}