{
  "type": "Feature",
  "properties": {
    "iso:country":"US",
    "sg:address":"300 Maalaea Rd",
    "sg:city":"Wailuku",
    "sg:classifiers":[
        {
            "category":"Shopping",
            "type":"Retail Goods"
        }
    ],
    "sg:phone":"+1 808 986 8383",
    "sg:postcode":"96793",
    "sg:province":"HI",
    "sg:tags":[
        "candle"
    ],
    "sg:website":"www.mauisoapworks.com",
    "wof:name":"Island Soap & Candle Works",
    "wof:placetype":"venue"
},
  "geometry": {"coordinates":[-156.51091700000001,20.794339],"type":"Point"}
}