{
  "type": "Feature",
  "properties": {
    "iso:country":"US",
    "sg:address":"693 Kawaiahao St",
    "sg:city":"Honolulu",
    "sg:classifiers":[
        {
            "category":"Professional",
            "subcategory":"Business Services",
            "type":"Services"
        }
    ],
    "sg:phone":"+1 808 596 2999",
    "sg:postcode":"96813",
    "sg:province":"HI",
    "sg:tags":[
        "event"
    ],
    "wof:name":"Event House",
    "wof:placetype":"venue"
},
  "geometry": {"coordinates":[-157.85667000000001,21.301748],"type":"Point"}
}