{
  "type": "Feature",
  "properties": {
    "iso:country":"US",
    "sg:address":"120 Farrington Hwy",
    "sg:city":"Waianae",
    "sg:classifiers":[
        {
            "category":"Restaurant",
            "type":"Food & Drink"
        }
    ],
    "sg:phone":"+1 808 696 1333",
    "sg:postcode":"96792",
    "sg:province":"HI",
    "sg:tags":[
        "eating"
    ],
    "wof:name":"Hui On Fast Foods",
    "wof:placetype":"venue"
},
  "geometry": {"coordinates":[-158.17839799999999,21.425252],"type":"Point"}
}