{
  "type": "Feature",
  "properties": {
    "addr:full":"588 Kamehameha Hwy Kaneohe HI 96744",
    "addr:housenumber":"588",
    "addr:postcode":"96744",
    "addr:street":"Kamehameha Hwy",
    "iso:country":"US",
    "sg:address":"588 Kamehameha Hwy",
    "sg:city":"Kaneohe",
    "sg:classifiers":[
        {
            "category":"Communications",
            "subcategory":"Film & Video Production",
            "type":"Services"
        }
    ],
    "sg:phone":"+1 808 247 1037",
    "sg:postcode":"96744",
    "sg:province":"HI",
    "sg:tags":[
        "taping"
    ],
    "wof:name":"Beam Video",
    "wof:placetype":"venue"
},
  "geometry": {"coordinates":[-157.84123299999999,21.459813],"type":"Point"}
}