{
  "type": "Feature",
  "properties": {
    "iso:country":"US",
    "sg:address":"76 Kalanianaole Ave",
    "sg:city":"Hilo",
    "sg:classifiers":[
        {
            "category":"Wholesale",
            "subcategory":"Electrical",
            "type":"Manufacturing & Wholesale Goods"
        }
    ],
    "sg:phone":"+1 808 961 5688",
    "sg:postcode":"96720",
    "sg:province":"HI",
    "sg:tags":[
        "lighting",
        "showroom",
        "fan"
    ],
    "wof:name":"Bay Lighting & Design",
    "wof:placetype":"venue"
},
  "geometry": {"coordinates":[-155.06274400000001,19.723006],"type":"Point"}
}