{
  "type": "Feature",
  "properties": {
    "iso:country":"US",
    "sg:address":"4573 Akialoa Rd",
    "sg:city":"Kekaha",
    "sg:classifiers":[
        {
            "category":"Travel",
            "subcategory":"Travel Agent",
            "type":"Entertainment"
        }
    ],
    "sg:phone":"+1 808 337 9309",
    "sg:postcode":"96752",
    "sg:province":"HI",
    "sg:tags":[
        "tours",
        "promoter"
    ],
    "wof:name":"Kaulana Pali Kai Tours",
    "wof:placetype":"venue"
},
  "geometry": {"coordinates":[-159.72095999999999,21.974249],"type":"Point"}
}