{
  "type": "Feature",
  "properties": {
    "iso:country":"US",
    "sg:address":"1450 Ala Moana Blvd",
    "sg:city":"Honolulu",
    "sg:classifiers":[
        {
            "category":"Shopping",
            "subcategory":"Shoes",
            "type":"Retail Goods"
        }
    ],
    "sg:phone":"+1 808 949 0155",
    "sg:postcode":"96814",
    "sg:province":"HI",
    "sg:tags":[
        "footwear"
    ],
    "sg:website":"www.slippershawaii.com",
    "wof:name":"Slipper House Inc",
    "wof:placetype":"venue"
},
  "geometry": {"coordinates":[-157.84143399999999,21.289059],"type":"Point"}
}