{
  "type": "Feature",
  "properties": {
    "addr:full":"2310 Umi Pl Haiku HI 96708",
    "addr:housenumber":"2310",
    "addr:postcode":"96708",
    "addr:street":"Umi Pl",
    "iso:country":"US",
    "sg:address":"2310 Umi Pl",
    "sg:city":"Haiku",
    "sg:classifiers":[
        {
            "category":"Health Services",
            "subcategory":"Chiropractor",
            "type":"Services"
        },
        {
            "category":"Health Services",
            "subcategory":"Doctor",
            "type":"Services"
        }
    ],
    "sg:phone":"+1 808 575 2328",
    "sg:postcode":"96708",
    "sg:province":"HI",
    "sg:tags":[
        "clinic"
    ],
    "wof:name":"Maui East West Clinic",
    "wof:placetype":"venue"
},
  "geometry": {"coordinates":[-156.330918,20.924253],"type":"Point"}
}