{
  "type": "Feature",
  "properties": {
    "addr:full":"180 Peahi Rd Haiku HI 96708",
    "addr:housenumber":"180",
    "addr:postcode":"96708",
    "addr:street":"Peahi Rd",
    "iso:country":"US",
    "sg:address":"180 Peahi Rd",
    "sg:city":"Haiku",
    "sg:classifiers":[
        {
            "category":"Building & Trades",
            "subcategory":"Electrical",
            "type":"Services"
        }
    ],
    "sg:phone":"+1 808 575 9283",
    "sg:postcode":"96708",
    "sg:province":"HI",
    "sg:tags":[
        "electrical",
        "contractor"
    ],
    "wof:name":"Accurate Electric",
    "wof:placetype":"venue"
},
  "geometry": {"coordinates":[-156.298956,20.918685],"type":"Point"}
}