{
  "type": "Feature",
  "properties": {
    "addr:full":"203 Kam Hwy Wahiawa HI 96717",
    "addr:housenumber":"203",
    "addr:postcode":"96717",
    "addr:street":"Kam Hwy",
    "iso:country":"US",
    "sg:address":"203 Kam Hwy",
    "sg:city":"Wahiawa",
    "sg:classifiers":[
        {
            "category":"Personal",
            "subcategory":"Shoe Repair & Shine",
            "type":"Services"
        }
    ],
    "sg:phone":"+1 808 624 9339",
    "sg:postcode":"96717",
    "sg:province":"HI",
    "sg:tags":[
        "repairing",
        "boot"
    ],
    "wof:name":"ASAP Shine & Repair",
    "wof:placetype":"venue"
},
  "geometry": {"coordinates":[-157.90841599999999,21.606361],"type":"Point"}
}