{
  "type": "Feature",
  "properties": {
    "addr:full":"1347 Kapiolani Blvd Honolulu HI 96814",
    "addr:housenumber":"1347",
    "addr:postcode":"96814",
    "addr:street":"Kapiolani Blvd",
    "iso:country":"US",
    "sg:address":"1347 Kapiolani Blvd",
    "sg:city":"Honolulu",
    "sg:classifiers":[
        {
            "category":"Home & Garden",
            "subcategory":"Furniture",
            "type":"Retail Goods"
        }
    ],
    "sg:phone":"+1 808 951 4700",
    "sg:postcode":"96814",
    "sg:province":"HI",
    "sg:tags":[
        "bed",
        "mattress"
    ],
    "wof:name":"Mattress Outlet",
    "wof:placetype":"venue"
},
  "geometry": {"coordinates":[-157.845708,21.294542],"type":"Point"}
}