{
  "type": "Feature",
  "properties": {
    "iso:country":"US",
    "sg:address":"345 Wanaao Rd",
    "sg:city":"Kailua",
    "sg:classifiers":[
        {
            "category":"Professional",
            "subcategory":"Management & Consulting",
            "type":"Services"
        }
    ],
    "sg:phone":"+1 808 262 6776",
    "sg:postcode":"96734",
    "sg:province":"HI",
    "sg:tags":[
        "marketing",
        "consultant"
    ],
    "wof:name":"Page Marketing Inc",
    "wof:placetype":"venue"
},
  "geometry": {"coordinates":[-157.73372599999999,21.391582],"type":"Point"}
}