{
  "type": "Feature",
  "properties": {
    "iso:country":"US",
    "sg:address":"3700 Kilauea Ave",
    "sg:city":"Honolulu",
    "sg:classifiers":[
        {
            "category":"Professional",
            "subcategory":"Management & Consulting",
            "type":"Services"
        }
    ],
    "sg:phone":"+1 808 732 1270",
    "sg:postcode":"96816",
    "sg:province":"HI",
    "sg:tags":[
        "consultant",
        "financial"
    ],
    "wof:name":"CYM Corp",
    "wof:placetype":"venue"
},
  "geometry": {"coordinates":[-157.80118100000001,21.273757],"type":"Point"}
}