{
  "type": "Feature",
  "properties": {
    "iso:country":"US",
    "sg:address":"594 Kuilioloa Pl",
    "sg:city":"Ewa Beach",
    "sg:classifiers":[
        {
            "category":"Shopping",
            "subcategory":"Clothing, Apparel, & Fashions",
            "type":"Retail Goods"
        }
    ],
    "sg:phone":"+1 808 689 3589",
    "sg:postcode":"96706",
    "sg:province":"HI",
    "wof:name":"GE Ann Hawaii",
    "wof:placetype":"venue"
},
  "geometry": {"coordinates":[-158.007126,21.312539],"type":"Point"}
}