{
  "type": "Feature",
  "properties": {
    "addr:full":"2005 Kalia Rd Honolulu HI 96815",
    "addr:housenumber":"2005",
    "addr:postcode":"96815",
    "addr:street":"Kalia Rd",
    "iso:country":"US",
    "sg:address":"2005 Kalia Rd",
    "sg:city":"Honolulu",
    "sg:classifiers":[
        {
            "category":"Cafe",
            "type":"Food & Drink"
        }
    ],
    "sg:menulink":"http://www.allmenus.com/hi/honolulu/3373-tapa-cafe/menu/",
    "sg:phone":"+1 808 949 4321",
    "sg:postcode":"96815",
    "sg:province":"HI",
    "sg:tags":[
        "american"
    ],
    "wof:name":"Tapa Cafe",
    "wof:placetype":"venue"
},
  "geometry": {"coordinates":[-157.83560199999999,21.284225],"type":"Point"}
}