{
  "type": "Feature",
  "properties": {
    "iso:country":"US",
    "sg:address":"2453 Halenoho Pl",
    "sg:city":"Honolulu",
    "sg:classifiers":[
        {
            "category":"Building & Trades",
            "subcategory":"Plumbing",
            "type":"Services"
        }
    ],
    "sg:phone":"+1 808 739 9287",
    "sg:postcode":"96816",
    "sg:province":"HI",
    "sg:tags":[
        "product",
        "management",
        "energy",
        "system"
    ],
    "wof:name":"MHP Energy Svc",
    "wof:placetype":"venue"
},
  "geometry": {"coordinates":[-157.782016,21.305541],"type":"Point"}
}