{
  "type": "Feature",
  "properties": {
    "iso:country":"US",
    "sg:address":"2851 E Manoa Rd",
    "sg:city":"Honolulu",
    "sg:classifiers":[
        {
            "category":"Health Services",
            "subcategory":"Health Practitioner",
            "type":"Services"
        }
    ],
    "sg:phone":"+1 808 988 6168",
    "sg:postcode":"96822",
    "sg:province":"HI",
    "sg:tags":[
        "psychologist"
    ],
    "wof:name":"Laura M Sturgis PHD",
    "wof:placetype":"venue"
},
  "geometry": {"coordinates":[-157.80966900000001,21.310032],"type":"Point"}
}