{
  "type": "Feature",
  "properties": {
    "addr:city":"Wailuku",
    "addr:full":"688 Nukuwai Pl Wailuku, Hi 96793",
    "addr:house_number":"688",
    "addr:housenumber":"688",
    "addr:phone":"+1 808-242-1560",
    "addr:postcode":"96793",
    "addr:road":"Nukuwai Pl",
    "addr:state":"HI",
    "addr:street":"Nukuwai Pl",
    "iso:country":"US",
    "sg:address":"688 Nukuwai Pl",
    "sg:city":"Wailuku",
    "sg:classifiers":[
        {
            "category":"Recreation",
            "type":"Entertainment"
        }
    ],
    "sg:phone":"+1 808 242 1560",
    "sg:postcode":"96793",
    "sg:province":"HI",
    "sg:tags":[
        "martial",
        "arts",
        "instruction"
    ],
    "wof:airports":[
        102533095,
        102532929
    ],
    "wof:name":"Maui Okinawa Cultural Center",
    "wof:placetype":"venue"
},
  "geometry": {"coordinates":[-156.4863,20.90721],"type":"Point"}
}