{
  "type": "Feature",
  "properties": {
    "iso:country":"US",
    "sg:address":"707 Alakea St",
    "sg:city":"Honolulu",
    "sg:classifiers":[
        {
            "category":"Professional",
            "subcategory":"Management & Consulting",
            "type":"Services"
        }
    ],
    "sg:phone":"+1 808 538 6261",
    "sg:postcode":"96813",
    "sg:province":"HI",
    "sg:tags":[
        "consultant"
    ],
    "wof:name":"Sam Carl & Associates Inc",
    "wof:placetype":"venue"
},
  "geometry": {"coordinates":[-157.86212,21.306754],"type":"Point"}
}