{
  "type": "Feature",
  "properties": {
    "iso:country":"US",
    "sg:address":"340 Haihai St",
    "sg:city":"Hilo",
    "sg:classifiers":[
        {
            "category":"Shopping",
            "subcategory":"Bicycles & Sporting Goods",
            "type":"Retail Goods"
        }
    ],
    "sg:phone":"+1 808 959 9601",
    "sg:postcode":"96720",
    "sg:province":"HI",
    "wof:name":"Acia Rodney Pga",
    "wof:placetype":"venue"
},
  "geometry": {"coordinates":[-155.068479,19.674603],"type":"Point"}
}