{
  "type": "Feature",
  "properties": {
    "addr:full":"236 Akai St Kihei HI 96753",
    "addr:housenumber":"236",
    "addr:postcode":"96753",
    "addr:street":"Akai St",
    "iso:country":"US",
    "sg:address":"236 Akai St",
    "sg:city":"Kihei",
    "sg:classifiers":[
        {
            "category":"Building & Trades",
            "subcategory":"Cleaning & Sanitation",
            "type":"Services"
        }
    ],
    "sg:phone":"+1 808 879 5953",
    "sg:postcode":"96753",
    "sg:province":"HI",
    "wof:name":"Aloha Interior Maintenance",
    "wof:placetype":"venue"
},
  "geometry": {"coordinates":[-156.451401,20.742436],"type":"Point"}
}