{
  "type": "Feature",
  "properties": {
    "iso:country":"US",
    "sg:address":"5 Kawa St",
    "sg:city":"Kaneohe",
    "sg:classifiers":[
        {
            "category":"Organizations",
            "subcategory":"Religious Organization",
            "type":"Services"
        }
    ],
    "sg:phone":"+1 808 247 4851",
    "sg:postcode":"96744",
    "sg:province":"HI",
    "sg:tags":[
        "church"
    ],
    "wof:name":"New Beginning Christian Fellow",
    "wof:placetype":"venue"
},
  "geometry": {"coordinates":[-157.80362199999999,21.419087],"type":"Point"}
}