{
  "type": "Feature",
  "properties": {
    "addr:full":"14 Oopuhue Pl Kaneohe HI 96744",
    "addr:housenumber":"14",
    "addr:postcode":"96744",
    "addr:street":"Oopuhue Pl",
    "iso:country":"US",
    "sg:address":"14 Oopuhue Pl",
    "sg:city":"Kaneohe",
    "sg:classifiers":[
        {
            "category":"Building & Trades",
            "subcategory":"Construction",
            "type":"Services"
        }
    ],
    "sg:phone":"+1 808 235 3956",
    "sg:postcode":"96744",
    "sg:province":"HI",
    "sg:tags":[
        "house"
    ],
    "wof:name":"Home Planning & Drafting",
    "wof:placetype":"venue"
},
  "geometry": {"coordinates":[-157.78654,21.411603],"type":"Point"}
}