{
  "type": "Feature",
  "properties": {
    "iso:country":"US",
    "sg:address":"938 Laaulu St",
    "sg:city":"Ewa Beach",
    "sg:classifiers":[
        {
            "category":"Professional",
            "subcategory":"Business Services",
            "type":"Services"
        }
    ],
    "sg:phone":"+1 808 831 3519",
    "sg:postcode":"96706",
    "sg:province":"HI",
    "wof:name":"Apolonia Devera",
    "wof:placetype":"venue"
},
  "geometry": {"coordinates":[-158.02839299999999,21.338672],"type":"Point"}
}