{
  "type": "Feature",
  "properties": {
    "iso:country":"US",
    "sg:address":"1055 Kuhaulua St",
    "sg:city":"Waipahu",
    "sg:classifiers":[
        {
            "category":"Building & Trades",
            "subcategory":"Construction",
            "type":"Services"
        }
    ],
    "sg:phone":"+1 808 671 1754",
    "sg:postcode":"96797",
    "sg:province":"HI",
    "sg:tags":[
        "acoustical",
        "contractor"
    ],
    "wof:name":"ADLS Acoustical & Insltn",
    "wof:placetype":"venue"
},
  "geometry": {"coordinates":[-158.011426,21.393811],"type":"Point"}
}