{
  "type": "Feature",
  "properties": {
    "iso:country":"US",
    "sg:address":"426 Queen St",
    "sg:city":"Honolulu",
    "sg:classifiers":[
        {
            "category":"Government",
            "subcategory":"Court House",
            "type":"Public Place"
        }
    ],
    "sg:phone":"+1 808 539 4800",
    "sg:postcode":"96813",
    "sg:province":"HI",
    "sg:tags":[
        "state"
    ],
    "wof:name":"Community Service Sentencing",
    "wof:placetype":"venue"
},
  "geometry": {"coordinates":[-157.86000300000001,21.304562],"type":"Point"}
}