{
  "type": "Feature",
  "properties": {
    "addr:full":"77 Mohouli St Hilo HI 96720",
    "addr:housenumber":"77",
    "addr:postcode":"96720",
    "addr:street":"Mohouli St",
    "iso:country":"US",
    "sg:address":"77 Mohouli St",
    "sg:city":"Hilo",
    "sg:classifiers":[
        {
            "category":"Professional",
            "subcategory":"Lawyer & Legal Services",
            "type":"Services"
        }
    ],
    "sg:phone":"+1 808 969 7070",
    "sg:postcode":"96720",
    "sg:province":"HI",
    "sg:tags":[
        "attorney"
    ],
    "wof:name":"J Richard Peterson Law Office",
    "wof:placetype":"venue"
},
  "geometry": {"coordinates":[-155.07959199999999,19.712247],"type":"Point"}
}