{
  "type": "Feature",
  "properties": {
    "addr:full":"308 Noe St Kihei HI 96753",
    "addr:housenumber":"308",
    "addr:postcode":"96753",
    "addr:street":"Noe St",
    "iso:country":"US",
    "sg:address":"308 Noe St",
    "sg:city":"Kihei",
    "sg:classifiers":[
        {
            "category":"Wholesale",
            "subcategory":"Plants",
            "type":"Manufacturing & Wholesale Goods"
        }
    ],
    "sg:phone":"+1 808 879 5074",
    "sg:postcode":"96753",
    "sg:province":"HI",
    "sg:tags":[
        "supply"
    ],
    "wof:name":"Melia Orchids",
    "wof:placetype":"venue"
},
  "geometry": {"coordinates":[-156.44936300000001,20.778173],"type":"Point"}
}