{
  "type": "Feature",
  "properties": {
    "addr:full":"2696 Kilihau St Honolulu HI 96819",
    "addr:housenumber":"2696",
    "addr:postcode":"96819",
    "addr:street":"Kilihau St",
    "iso:country":"US",
    "sg:address":"2696 Kilihau St",
    "sg:city":"Honolulu",
    "sg:classifiers":[
        {
            "category":"Manufacturing",
            "subcategory":"Metals",
            "type":"Manufacturing & Wholesale Goods"
        }
    ],
    "sg:phone":"+1 808 847 2721",
    "sg:postcode":"96819",
    "sg:province":"HI",
    "sg:tags":[
        "gates"
    ],
    "wof:name":"L & M Metal Works",
    "wof:placetype":"venue"
},
  "geometry": {"coordinates":[-157.89537300000001,21.335222],"type":"Point"}
}