{
  "type": "Feature",
  "properties": {
    "iso:country":"US",
    "sg:address":"1159 Kaleo Way",
    "sg:city":"Kapolei",
    "sg:classifiers":[
        {
            "category":"Organizations",
            "subcategory":"Religious Organization",
            "type":"Services"
        }
    ],
    "sg:phone":"+1 808 672 6016",
    "sg:postcode":"96707",
    "sg:province":"HI",
    "sg:tags":[
        "clergy"
    ],
    "wof:name":"Gabriel Guerra",
    "wof:placetype":"venue"
},
  "geometry": {"coordinates":[-158.086679,21.36777],"type":"Point"}
}