{
  "type": "Feature",
  "properties": {
    "iso:country":"US",
    "sg:address":"3175 Elua St",
    "sg:city":"Lihue",
    "sg:classifiers":[
        {
            "category":"Professional",
            "subcategory":"Lawyer & Legal Services",
            "type":"Services"
        }
    ],
    "sg:phone":"+1 808 823 0000",
    "sg:postcode":"96766",
    "sg:province":"HI",
    "sg:tags":[
        "attorney"
    ],
    "wof:name":"Stanton Clay Chapman Crumpton",
    "wof:placetype":"venue"
},
  "geometry": {"coordinates":[-159.366197,21.97938],"type":"Point"}
}