{
  "type": "Feature",
  "properties": {
    "addr:full":"1325 S Kihei Rd Kihei HI 96753",
    "addr:housenumber":"1325",
    "addr:postcode":"96753",
    "addr:street":"S Kihei Rd",
    "iso:country":"US",
    "sg:address":"1325 S Kihei Rd",
    "sg:city":"Kihei",
    "sg:classifiers":[
        {
            "category":"Professional",
            "type":"Services"
        }
    ],
    "sg:phone":"+1 808 875 2310",
    "sg:postcode":"96753",
    "sg:province":"HI",
    "sg:tags":[
        "establishment"
    ],
    "wof:name":"Maui Pacific Ctr",
    "wof:placetype":"venue"
},
  "geometry": {"coordinates":[-156.456119,20.751281],"type":"Point"}
}