{
  "type": "Feature",
  "properties": {
    "iso:country":"US",
    "sg:address":"2883 Kalihiwai Rd",
    "sg:city":"Kilauea",
    "sg:classifiers":[
        {
            "category":"Travel",
            "subcategory":"Hotels & Motels",
            "type":"Entertainment"
        }
    ],
    "sg:phone":"+1 808 828 1341",
    "sg:postcode":"96754",
    "sg:province":"HI",
    "sg:tags":[
        "breakfast",
        "accommodation",
        "bed"
    ],
    "wof:name":"Hale Ho'o Maha",
    "wof:placetype":"venue"
},
  "geometry": {"coordinates":[-159.42094,22.21603],"type":"Point"}
}