{
  "type": "Feature",
  "properties": {
    "iso:country":"US",
    "sg:address":"185 Makaala St",
    "sg:city":"Hilo",
    "sg:classifiers":[
        {
            "category":"Retail",
            "subcategory":"Auto Repair",
            "type":"Services"
        }
    ],
    "sg:phone":"+1 808 935 6838",
    "sg:postcode":"96720",
    "sg:province":"HI",
    "sg:tags":[
        "repairing",
        "body",
        "general",
        "automobile"
    ],
    "wof:name":"Nick's Garage",
    "wof:placetype":"venue"
},
  "geometry": {"coordinates":[-155.06760499999999,19.702911],"type":"Point"}
}