{
  "type": "Feature",
  "properties": {
    "addr:full":"1365 Nuuanu Ave Honolulu HI 96817",
    "addr:housenumber":"1365",
    "addr:postcode":"96817",
    "addr:street":"Nuuanu Ave",
    "iso:country":"US",
    "sg:address":"1365 Nuuanu Ave",
    "sg:city":"Honolulu",
    "sg:classifiers":[
        {
            "category":"Personal",
            "subcategory":"Beauty Salon",
            "type":"Services"
        }
    ],
    "sg:phone":"+1 808 528 1834",
    "sg:postcode":"96817",
    "sg:province":"HI",
    "sg:tags":[
        "shop"
    ],
    "wof:name":"Nuvo Hair Design",
    "wof:placetype":"venue"
},
  "geometry": {"coordinates":[-157.85835900000001,21.313687],"type":"Point"}
}