{
  "type": "Feature",
  "properties": {
    "iso:country":"US",
    "sg:address":"156 Kolekona Pl",
    "sg:city":"Kapaa",
    "sg:classifiers":[
        {
            "category":"Wholesale",
            "subcategory":"Electrical",
            "type":"Manufacturing & Wholesale Goods"
        }
    ],
    "sg:phone":"+1 808 822 3989",
    "sg:postcode":"96746",
    "sg:province":"HI",
    "sg:tags":[
        "lighting",
        "fixture"
    ],
    "wof:name":"Ichikawa Lighting Enterprises",
    "wof:placetype":"venue"
},
  "geometry": {"coordinates":[-159.386652,22.055643],"type":"Point"}
}