{
  "type": "Feature",
  "properties": {
    "iso:country":"US",
    "sg:address":"2031 Waikalani Pl",
    "sg:city":"Mililani",
    "sg:classifiers":[
        {
            "category":"Real Estate",
            "subcategory":"Real Estate Agent",
            "type":"Services"
        },
        {
            "category":"Real Estate",
            "subcategory":"Real Estate Operator",
            "type":"Services"
        }
    ],
    "sg:phone":"+1 808 627 1599",
    "sg:postcode":"96789",
    "sg:province":"HI",
    "sg:tags":[
        "condominium"
    ],
    "wof:name":"Northbrook Condominium",
    "wof:placetype":"venue"
},
  "geometry": {"coordinates":[-158.02247700000001,21.464444],"type":"Point"}
}