{
  "type": "Feature",
  "properties": {
    "addr:full":"284 Pulehuiki Rd Kula HI 96790",
    "addr:housenumber":"284",
    "addr:postcode":"96790",
    "addr:street":"Pulehuiki Rd",
    "iso:country":"US",
    "sg:address":"284 Pulehuiki Rd",
    "sg:city":"Kula",
    "sg:classifiers":[
        {
            "category":"Farming",
            "subcategory":"Farm",
            "type":"Manufacturing & Wholesale Goods"
        }
    ],
    "sg:phone":"+1 808 878 6055",
    "sg:postcode":"96790",
    "sg:province":"HI",
    "sg:tags":[
        "crop",
        "general"
    ],
    "wof:name":"RH Yokote Farm",
    "wof:placetype":"venue"
},
  "geometry": {"coordinates":[-156.308798,20.763423],"type":"Point"}
}