{
  "type": "Feature",
  "properties": {
    "iso:country":"US",
    "sg:address":"2615 S King St",
    "sg:city":"Honolulu",
    "sg:classifiers":[
        {
            "category":"Restaurant",
            "type":"Food & Drink"
        }
    ],
    "sg:phone":"+1 808 944 5562",
    "sg:postcode":"96826",
    "sg:province":"HI",
    "sg:tags":[
        "eating"
    ],
    "wof:name":"Popeyes Chicken & Biscuits",
    "wof:placetype":"venue"
},
  "geometry": {"coordinates":[-157.82127700000001,21.291498],"type":"Point"}
}