{
  "type": "Feature",
  "properties": {
    "iso:country":"US",
    "sg:address":"431 Nahua St",
    "sg:city":"Honolulu",
    "sg:classifiers":[
        {
            "category":"Real Estate",
            "subcategory":"Real Estate Operator",
            "type":"Services"
        },
        {
            "category":"Organizations",
            "subcategory":"Community Association",
            "type":"Services"
        }
    ],
    "sg:phone":"+1 808 923 5978",
    "sg:postcode":"96815",
    "sg:province":"HI",
    "sg:tags":[
        "condominium"
    ],
    "wof:name":"Palms Condominium",
    "wof:placetype":"venue"
},
  "geometry": {"coordinates":[-157.82467800000001,21.279917],"type":"Point"}
}