{
  "type": "Feature",
  "properties": {
    "addr:full":"269 Keawe St Hilo HI 96720",
    "addr:housenumber":"269",
    "addr:postcode":"96720",
    "addr:street":"Keawe St",
    "iso:country":"US",
    "sg:address":"269 Keawe St",
    "sg:city":"Hilo",
    "sg:classifiers":[
        {
            "category":"Personal",
            "type":"Services"
        }
    ],
    "sg:phone":"+1 808 961 2621",
    "sg:postcode":"96720",
    "sg:province":"HI",
    "sg:website":"www.rainbowtattoo.com",
    "wof:name":"Rainbow Falls Tattoo",
    "wof:placetype":"venue"
},
  "geometry": {"coordinates":[-155.08647199999999,19.723692],"type":"Point"}
}