{
  "type": "Feature",
  "properties": {
    "iso:country":"US",
    "sg:address":"1069 Spencer St",
    "sg:city":"Honolulu",
    "sg:classifiers":[
        {
            "category":"Building & Trades",
            "subcategory":"Construction",
            "type":"Services"
        }
    ],
    "sg:phone":"+1 808 543 0179",
    "sg:postcode":"96822",
    "sg:province":"HI",
    "sg:tags":[
        "residential"
    ],
    "wof:name":"Ss Construction",
    "wof:placetype":"venue"
},
  "geometry": {"coordinates":[-157.84449000000001,21.307585],"type":"Point"}
}