{
  "type": "Feature",
  "properties": {
    "iso:country":"US",
    "sg:address":"1726 Mill St",
    "sg:city":"Wailuku",
    "sg:classifiers":[
        {
            "category":"Autos & Motor Vehicles",
            "subcategory":"Automobile Sales",
            "type":"Retail Goods"
        }
    ],
    "sg:phone":"+1 808 244 3766",
    "sg:postcode":"96793",
    "sg:province":"HI",
    "sg:tags":[
        "car",
        "used",
        "dealer"
    ],
    "wof:name":"Furomotors Used Cars",
    "wof:placetype":"venue"
},
  "geometry": {"coordinates":[-156.501622,20.895836],"type":"Point"}
}