{
  "type": "Feature",
  "properties": {
    "addr:full":"266 Auwaiolimu St Honolulu HI 96813",
    "addr:housenumber":"266",
    "addr:postcode":"96813",
    "addr:street":"Auwaiolimu St",
    "iso:country":"US",
    "sg:address":"266 Auwaiolimu St",
    "sg:city":"Honolulu",
    "sg:classifiers":[
        {
            "category":"Professional",
            "type":"Services"
        }
    ],
    "sg:phone":"+1 808 524 5162",
    "sg:postcode":"96813",
    "sg:province":"HI",
    "wof:name":"Seven-Seven-Seven Inc",
    "wof:placetype":"venue"
},
  "geometry": {"coordinates":[-157.84889000000001,21.317747],"type":"Point"}
}