{
  "type": "Feature",
  "properties": {
    "iso:country":"US",
    "sg:address":"2666 Waiomao Rd",
    "sg:city":"Honolulu",
    "sg:classifiers":[
        {
            "category":"Restaurant",
            "type":"Food & Drink"
        }
    ],
    "sg:phone":"+1 808 381 7411",
    "sg:postcode":"96816",
    "sg:province":"HI",
    "sg:tags":[
        "eating"
    ],
    "wof:name":"Kokohead Foods Ltd",
    "wof:placetype":"venue"
},
  "geometry": {"coordinates":[-157.78222099999999,21.308567],"type":"Point"}
}