{
  "type": "Feature",
  "properties": {
    "iso:country":"US",
    "sg:address":"205 Moanalua Rd",
    "sg:city":"Aiea",
    "sg:classifiers":[
        {
            "category":"Personal",
            "subcategory":"Beauty Salon",
            "type":"Services"
        }
    ],
    "sg:phone":"+1 808 486 0222",
    "sg:postcode":"96701",
    "sg:province":"HI",
    "wof:name":"Hair-Tron By Liza",
    "wof:placetype":"venue"
},
  "geometry": {"coordinates":[-157.93097800000001,21.378678],"type":"Point"}
}