{
  "type": "Feature",
  "properties": {
    "iso:country":"US",
    "sg:address":"1050 Bishop St",
    "sg:city":"Honolulu",
    "sg:classifiers":[
        {
            "category":"Professional",
            "type":"Services"
        }
    ],
    "sg:phone":"+1 808 599 4998",
    "sg:postcode":"96813",
    "sg:province":"HI",
    "wof:name":"Integ Business Svcs",
    "wof:placetype":"venue"
},
  "geometry": {"coordinates":[-157.861086,21.308902],"type":"Point"}
}