{
  "type": "Feature",
  "properties": {
    "iso:country":"US",
    "sg:address":"209 Waianae Valley Rd",
    "sg:city":"Waianae",
    "sg:classifiers":[
        {
            "category":"Shopping",
            "subcategory":"Florist",
            "type":"Retail Goods"
        }
    ],
    "sg:phone":"+1 808 696 2810",
    "sg:postcode":"96792",
    "sg:province":"HI",
    "wof:name":"Bobbie's Flowers & Gifts",
    "wof:placetype":"venue"
},
  "geometry": {"coordinates":[-158.18231700000001,21.444466],"type":"Point"}
}