{
  "type": "Feature",
  "properties": {
    "addr:full":"20 Alaloa St Kaneohe HI 96744",
    "addr:housenumber":"20",
    "addr:postcode":"96744",
    "addr:street":"Alaloa St",
    "iso:country":"US",
    "sg:address":"20 Alaloa St",
    "sg:city":"Kaneohe",
    "sg:classifiers":[
        {
            "category":"Retail",
            "subcategory":"Self-service Laundry",
            "type":"Services"
        }
    ],
    "sg:phone":"+1 808 247 2360",
    "sg:postcode":"96744",
    "sg:province":"HI",
    "sg:tags":[
        "coin"
    ],
    "wof:name":"Kaneohe Laundromat",
    "wof:placetype":"venue"
},
  "geometry": {"coordinates":[-157.80612500000001,21.417411],"type":"Point"}
}