{
  "type": "Feature",
  "properties": {
    "addr:full":"5470 Koloa Rd Koloa HI 96756",
    "addr:housenumber":"5470",
    "addr:postcode":"96756",
    "addr:street":"Koloa Rd",
    "iso:country":"US",
    "sg:address":"5470 Koloa Rd",
    "sg:city":"Koloa",
    "sg:classifiers":[
        {
            "category":"Restaurant",
            "type":"Food & Drink"
        }
    ],
    "sg:phone":"+1 808 742 2323",
    "sg:postcode":"96756",
    "sg:province":"HI",
    "wof:name":"Mi Casita",
    "wof:placetype":"venue"
},
  "geometry": {"coordinates":[-159.46408700000001,21.904716],"type":"Point"}
}