{
  "type": "Feature",
  "properties": {
    "iso:country":"US",
    "sg:address":"502 Office Rd",
    "sg:city":"Lahaina",
    "sg:classifiers":[
        {
            "category":"Shopping",
            "subcategory":"Discount & Variety Stores",
            "type":"Retail Goods"
        }
    ],
    "sg:phone":"+1 808 669 6128",
    "sg:postcode":"96761",
    "sg:province":"HI",
    "sg:tags":[
        "general"
    ],
    "wof:name":"Honolua Store",
    "wof:placetype":"venue"
},
  "geometry": {"coordinates":[-156.65348800000001,20.994588],"type":"Point"}
}