{
  "type": "Feature",
  "properties": {
    "iso:country":"US",
    "sg:address":"3390 Waialae Ave",
    "sg:city":"Honolulu",
    "sg:classifiers":[
        {
            "category":"Shopping",
            "subcategory":"Gifts & Souvenirs",
            "type":"Retail Goods"
        }
    ],
    "sg:phone":"+1 808 735 1510",
    "sg:postcode":"96816",
    "sg:province":"HI",
    "sg:tags":[
        "party",
        "supply"
    ],
    "wof:name":"Party Pizzazz",
    "wof:placetype":"venue"
},
  "geometry": {"coordinates":[-157.80440100000001,21.285593],"type":"Point"}
}