{
  "type": "Feature",
  "properties": {
    "addr:full":"269 Papa Pl Kahului HI 96732",
    "addr:housenumber":"269",
    "addr:postcode":"96732",
    "addr:street":"Papa Pl",
    "iso:country":"US",
    "sg:address":"269 Papa Pl",
    "sg:city":"Kahului",
    "sg:classifiers":[
        {
            "category":"Wholesale",
            "subcategory":"Meat",
            "type":"Manufacturing & Wholesale Goods"
        }
    ],
    "sg:phone":"+1 808 242 8882",
    "sg:postcode":"96732",
    "sg:province":"HI",
    "wof:name":"King Food Service",
    "wof:placetype":"venue"
},
  "geometry": {"coordinates":[-156.45742799999999,20.881507],"type":"Point"}
}