{
  "type": "Feature",
  "properties": {
    "addr:full":"120 Hekili St Kailua HI 96734",
    "addr:housenumber":"120",
    "addr:postcode":"96734",
    "addr:street":"Hekili St",
    "iso:country":"US",
    "sg:address":"120 Hekili St",
    "sg:city":"Kailua",
    "sg:classifiers":[
        {
            "category":"Restaurant",
            "type":"Food & Drink"
        }
    ],
    "sg:phone":"+1 808 262 0522",
    "sg:postcode":"96734",
    "sg:province":"HI",
    "sg:tags":[
        "eating"
    ],
    "wof:name":"C&C Fast Food",
    "wof:placetype":"venue"
},
  "geometry": {"coordinates":[-157.74198899999999,21.392199],"type":"Point"}
}