{
  "type": "Feature",
  "properties": {
    "iso:country":"US",
    "sg:address":"1000 Kamehameha Hwy",
    "sg:city":"Pearl City",
    "sg:classifiers":[
        {
            "category":"Shopping",
            "subcategory":"Bicycles & Sporting Goods",
            "type":"Retail Goods"
        }
    ],
    "sg:phone":"+1 808 456 5401",
    "sg:postcode":"96782",
    "sg:province":"HI",
    "sg:tags":[
        "equipment",
        "golf",
        "supply"
    ],
    "wof:name":"Nevada Bob's",
    "wof:placetype":"venue"
},
  "geometry": {"coordinates":[-157.97060999999999,21.394078],"type":"Point"}
}