{
  "type": "Feature",
  "properties": {
    "iso:country":"US",
    "sg:address":"840 Iwaiwa St",
    "sg:city":"Aiea",
    "sg:classifiers":[
        {
            "category":"Food & Beverages",
            "subcategory":"Bakery",
            "type":"Retail Goods"
        }
    ],
    "sg:phone":"+1 808 488 2193",
    "sg:postcode":"96701",
    "sg:province":"HI",
    "sg:tags":[
        "baker"
    ],
    "sg:website":"www.anisbakeshop.com",
    "wof:name":"Ani's Bake Shop",
    "wof:placetype":"venue"
},
  "geometry": {"coordinates":[-157.91485399999999,21.37238],"type":"Point"}
}