{
  "type": "Feature",
  "properties": {
    "iso:country":"US",
    "sg:address":"2470 S King St",
    "sg:city":"Honolulu",
    "sg:classifiers":[
        {
            "category":"Banks & Credit Unions",
            "subcategory":"Bank",
            "type":"Services"
        }
    ],
    "sg:phone":"+1 808 973 2660",
    "sg:postcode":"96826",
    "sg:province":"HI",
    "wof:name":"Bank Of Hawaii",
    "wof:placetype":"venue"
},
  "geometry": {"coordinates":[-157.82381000000001,21.292688],"type":"Point"}
}