{
  "type": "Feature",
  "properties": {
    "addr:full":"1365 Colburn St Honolulu HI 96817",
    "addr:housenumber":"1365",
    "addr:postcode":"96817",
    "addr:street":"Colburn St",
    "iso:country":"US",
    "sg:address":"1365 Colburn St",
    "sg:city":"Honolulu",
    "sg:classifiers":[
        {
            "category":"Wholesale",
            "subcategory":"Medical Equipment & Supplies",
            "type":"Manufacturing & Wholesale Goods"
        }
    ],
    "sg:phone":"+1 808 841 4558",
    "sg:postcode":"96817",
    "sg:province":"HI",
    "sg:tags":[
        "physician",
        "surgeon"
    ],
    "wof:name":"Holden Hospital Supply Inc",
    "wof:placetype":"venue"
},
  "geometry": {"coordinates":[-157.87595099999999,21.322492],"type":"Point"}
}