{
  "type": "Feature",
  "properties": {
    "iso:country":"US",
    "sg:address":"94-799 Lumiaina St",
    "sg:city":"Waipahu",
    "sg:classifiers":[
        {
            "category":"Restaurant",
            "type":"Food & Drink"
        }
    ],
    "sg:menulink":"http://www.allmenus.com/hi/ewa/109785-subway/menu/",
    "sg:phone":"+1 808 676 7879",
    "sg:postcode":"96797",
    "sg:province":"HI",
    "sg:tags":[
        "american",
        "sandwich"
    ],
    "wof:name":"Subway",
    "wof:placetype":"venue"
},
  "geometry": {"coordinates":[-158.00785500000001,21.400529],"type":"Point"}
}