{
  "type": "Feature",
  "properties": {
    "iso:country":"US",
    "sg:address":"801 Moowaa St",
    "sg:city":"Honolulu",
    "sg:classifiers":[
        {
            "category":"Home & Garden",
            "subcategory":"Building Materials",
            "type":"Retail Goods"
        }
    ],
    "sg:phone":"+1 808 841 2159",
    "sg:postcode":"96817",
    "sg:province":"HI",
    "sg:tags":[
        "paint"
    ],
    "wof:name":"ICI Paints",
    "wof:placetype":"venue"
},
  "geometry": {"coordinates":[-157.87312299999999,21.324268],"type":"Point"}
}