{
  "type": "Feature",
  "properties": {
    "addr:full":"540 Kamehameha Hwy Haleiwa HI 96712",
    "addr:housenumber":"540",
    "addr:postcode":"96712",
    "addr:street":"Kamehameha Hwy",
    "iso:country":"US",
    "sg:address":"540 Kamehameha Hwy",
    "sg:city":"Haleiwa",
    "sg:classifiers":[
        {
            "category":"Retail",
            "subcategory":"Auto Repair",
            "type":"Services"
        }
    ],
    "sg:phone":"+1 808 637 9686",
    "sg:postcode":"96712",
    "sg:province":"HI",
    "sg:tags":[
        "wrecker"
    ],
    "wof:name":"Haleiwa Off Road Towing",
    "wof:placetype":"venue"
},
  "geometry": {"coordinates":[-158.057796,21.657723],"type":"Point"}
}