{
  "type": "Feature",
  "properties": {
    "iso:country":"US",
    "sg:address":"2845 Waialae Ave",
    "sg:city":"Honolulu",
    "sg:classifiers":[
        {
            "category":"Wholesale",
            "subcategory":"Durable Goods & Equipment",
            "type":"Manufacturing & Wholesale Goods"
        }
    ],
    "sg:phone":"+1 808 732 7915",
    "sg:postcode":"96826",
    "sg:province":"HI",
    "wof:name":"Rzw Inc",
    "wof:placetype":"venue"
},
  "geometry": {"coordinates":[-157.81483,21.290325],"type":"Point"}
}