{
  "type": "Feature",
  "properties": {
    "iso:country":"US",
    "sg:address":"125 Waiua Way",
    "sg:city":"Aiea",
    "sg:classifiers":[
        {
            "category":"Manufacturing",
            "subcategory":"Retail Goods",
            "type":"Manufacturing & Wholesale Goods"
        }
    ],
    "sg:phone":"+1 808 487 0136",
    "sg:postcode":"96701",
    "sg:province":"HI",
    "sg:tags":[
        "candle",
        "mfg"
    ],
    "wof:name":"Warehouse",
    "wof:placetype":"venue"
},
  "geometry": {"coordinates":[-157.90123399999999,21.375293],"type":"Point"}
}