{
  "type": "Feature",
  "properties": {
    "iso:country":"US",
    "sg:address":"321 Kulalani Dr",
    "sg:city":"Kula",
    "sg:classifiers":[
        {
            "category":"Building & Trades",
            "subcategory":"Construction",
            "type":"Services"
        }
    ],
    "sg:phone":"+1 808 876 0341",
    "sg:postcode":"96790",
    "sg:province":"HI",
    "sg:tags":[
        "contractor"
    ],
    "wof:name":"Ventura Construction Corp",
    "wof:placetype":"venue"
},
  "geometry": {"coordinates":[-156.30953099999999,20.774441],"type":"Point"}
}