{
  "type": "Feature",
  "properties": {
    "addr:full":"1723 Kahai St Honolulu HI 96819",
    "addr:housenumber":"1723",
    "addr:postcode":"96819",
    "addr:street":"Kahai St",
    "iso:country":"US",
    "sg:address":"1723 Kahai St",
    "sg:city":"Honolulu",
    "sg:classifiers":[
        {
            "category":"Manufacturing",
            "subcategory":"Food",
            "type":"Manufacturing & Wholesale Goods"
        }
    ],
    "sg:phone":"+1 808 841 8662",
    "sg:postcode":"96819",
    "sg:province":"HI",
    "sg:tags":[
        "product",
        "pickle",
        "mfg"
    ],
    "wof:name":"Kewalo Pickle Products Inc",
    "wof:placetype":"venue"
},
  "geometry": {"coordinates":[-157.88538399999999,21.323627],"type":"Point"}
}