{
  "type": "Feature",
  "properties": {
    "addr:full":"358 Papa Pl Kahului HI 96732",
    "addr:housenumber":"358",
    "addr:postcode":"96732",
    "addr:street":"Papa Pl",
    "iso:country":"US",
    "sg:address":"358 Papa Pl",
    "sg:city":"Kahului",
    "sg:classifiers":[
        {
            "category":"Professional",
            "subcategory":"Business Services",
            "type":"Services"
        }
    ],
    "sg:phone":"+1 808 877 4699",
    "sg:postcode":"96732",
    "sg:province":"HI",
    "sg:tags":[
        "preparation",
        "tax",
        "return"
    ],
    "wof:name":"Jim Ericson MBA",
    "wof:placetype":"venue"
},
  "geometry": {"coordinates":[-156.45459399999999,20.885223],"type":"Point"}
}