{
  "type": "Feature",
  "properties": {
    "iso:country":"US",
    "sg:address":"495 Kamehameha Hwy",
    "sg:city":"Kaneohe",
    "sg:classifiers":[
        {
            "category":"Education",
            "subcategory":"Special Training",
            "type":"Public Place"
        }
    ],
    "sg:phone":"+1 808 234 7323",
    "sg:postcode":"96744",
    "sg:province":"HI",
    "sg:tags":[
        "tutoring"
    ],
    "wof:name":"Kumon Math & Reading Ctr",
    "wof:placetype":"venue"
},
  "geometry": {"coordinates":[-157.797518,21.395804],"type":"Point"}
}