{
  "type": "Feature",
  "properties": {
    "iso:country":"US",
    "sg:address":"830 Coolidge St",
    "sg:city":"Honolulu",
    "sg:classifiers":[
        {
            "category":"Retail",
            "subcategory":"Veterinary Services",
            "type":"Services"
        }
    ],
    "sg:phone":"+1 808 944 0003",
    "sg:postcode":"96826",
    "sg:province":"HI",
    "wof:name":"Oahu Veterinary House Calls",
    "wof:placetype":"venue"
},
  "geometry": {"coordinates":[-157.825332,21.291511],"type":"Point"}
}