{
  "type": "Feature",
  "properties": {
    "iso:country":"US",
    "sg:address":"935 N King St",
    "sg:city":"Honolulu",
    "sg:classifiers":[
        {
            "category":"Shopping",
            "subcategory":"Clothing, Apparel, & Fashions",
            "type":"Retail Goods"
        }
    ],
    "sg:phone":"+1 808 842 0766",
    "sg:postcode":"96817",
    "sg:province":"HI",
    "wof:name":"Lacef Polynesian Wear",
    "wof:placetype":"venue"
},
  "geometry": {"coordinates":[-157.86803599999999,21.323059],"type":"Point"}
}