{
  "type": "Feature",
  "properties": {
    "addr:full":"30 Hekaha St Aiea HI 96701",
    "addr:housenumber":"30",
    "addr:postcode":"96701",
    "addr:street":"Hekaha St",
    "iso:country":"US",
    "sg:address":"30 Hekaha St",
    "sg:city":"Aiea",
    "sg:classifiers":[
        {
            "category":"Real Estate",
            "subcategory":"Real Estate Agent",
            "type":"Services"
        }
    ],
    "sg:phone":"+1 808 487 1410",
    "sg:postcode":"96701",
    "sg:province":"HI",
    "wof:name":"Assist 2 Sell Buyers & Sellers",
    "wof:placetype":"venue"
},
  "geometry": {"coordinates":[-157.951684,21.384572],"type":"Point"}
}