{
  "type": "Feature",
  "properties": {
    "iso:country":"US",
    "sg:address":"2255 Kuhio Ave",
    "sg:city":"Honolulu",
    "sg:classifiers":[
        {
            "category":"Travel",
            "subcategory":"Hotels & Motels",
            "type":"Entertainment"
        }
    ],
    "sg:phone":"+1 808 921 0362",
    "sg:postcode":"96815",
    "sg:province":"HI",
    "sg:tags":[
        "operation"
    ],
    "wof:name":"Big Beat Hawaii Inc",
    "wof:placetype":"venue"
},
  "geometry": {"coordinates":[-157.82759899999999,21.280633],"type":"Point"}
}