{
  "type": "Feature",
  "properties": {
    "iso:country":"US",
    "sg:address":"111 Kuikahi St",
    "sg:city":"Hilo",
    "sg:classifiers":[
        {
            "category":"Health Services",
            "subcategory":"Doctor",
            "type":"Services"
        }
    ],
    "sg:phone":"+1 808 961 4492",
    "sg:postcode":"96720",
    "sg:province":"HI",
    "sg:tags":[
        "physician",
        "surgeon"
    ],
    "wof:name":"Neurological Center & Pain",
    "wof:placetype":"venue"
},
  "geometry": {"coordinates":[-155.09071800000001,19.766599],"type":"Point"}
}