{
  "type": "Feature",
  "properties": {
    "iso:country":"US",
    "sg:address":"2298 Alahao Pl",
    "sg:city":"Honolulu",
    "sg:classifiers":[
        {
            "category":"Utilities",
            "subcategory":"Refuse",
            "type":"Services"
        }
    ],
    "sg:phone":"+1 808 845 1076",
    "sg:postcode":"96819",
    "sg:province":"HI",
    "sg:tags":[
        "disposal",
        "waste"
    ],
    "wof:name":"Sanitation System",
    "wof:placetype":"venue"
},
  "geometry": {"coordinates":[-157.888431,21.328976],"type":"Point"}
}