{
  "type": "Feature",
  "properties": {
    "iso:country":"US",
    "sg:address":"3269 Poipu Rd",
    "sg:city":"Koloa",
    "sg:classifiers":[
        {
            "category":"Organizations",
            "subcategory":"Religious Organization",
            "type":"Services"
        }
    ],
    "sg:phone":"+1 808 742 9956",
    "sg:postcode":"96756",
    "sg:province":"HI",
    "sg:tags":[
        "church"
    ],
    "wof:name":"Koloa Church",
    "wof:placetype":"venue"
},
  "geometry": {"coordinates":[-159.46634700000001,21.900239],"type":"Point"}
}