{
  "type": "Feature",
  "properties": {
    "iso:country":"US",
    "sg:address":"26 Kamehameha Hwy",
    "sg:city":"Mililani",
    "sg:classifiers":[
        {
            "category":"Restaurant",
            "type":"Food & Drink"
        }
    ],
    "sg:phone":"+1 808 623 2268",
    "sg:postcode":"96789",
    "sg:province":"HI",
    "wof:name":"Mililani Drive Inn",
    "wof:placetype":"venue"
},
  "geometry": {"coordinates":[-158.02090200000001,21.460156],"type":"Point"}
}