{
  "type": "Feature",
  "properties": {
    "addr:full":"175 N Hotel St Honolulu HI 96817",
    "addr:housenumber":"175",
    "addr:postcode":"96817",
    "addr:street":"N Hotel St",
    "iso:country":"US",
    "sg:address":"175 N Hotel St",
    "sg:city":"Honolulu",
    "sg:classifiers":[
        {
            "category":"Manufacturing",
            "subcategory":"Food",
            "type":"Manufacturing & Wholesale Goods"
        },
        {
            "category":"Wholesale",
            "subcategory":"Groceries",
            "type":"Manufacturing & Wholesale Goods"
        }
    ],
    "sg:phone":"+1 808 531 4555",
    "sg:postcode":"96817",
    "sg:province":"HI",
    "sg:tags":[
        "noodle"
    ],
    "wof:name":"Family Rice & Noodle Shop",
    "wof:placetype":"venue"
},
  "geometry": {"coordinates":[-157.863452,21.312982],"type":"Point"}
}