{
  "type": "Feature",
  "properties": {
    "iso:country":"US",
    "sg:address":"1219 Waihona St",
    "sg:city":"Pearl City",
    "sg:classifiers":[
        {
            "category":"Manufacturing",
            "subcategory":"Motor Vehicles & Parts",
            "type":"Manufacturing & Wholesale Goods"
        }
    ],
    "sg:phone":"+1 808 455 3342",
    "sg:postcode":"96782",
    "sg:province":"HI",
    "sg:tags":[
        "body",
        "truck",
        "mfg"
    ],
    "wof:name":"Rainbow Welding & Service Inc",
    "wof:placetype":"venue"
},
  "geometry": {"coordinates":[-157.97331700000001,21.410274],"type":"Point"}
}