{
  "type": "Feature",
  "properties": {
    "addr:full":"677 Ala Moana Blvd Honolulu HI 96813",
    "addr:housenumber":"677",
    "addr:postcode":"96813",
    "addr:street":"Ala Moana Blvd",
    "iso:country":"US",
    "sg:address":"677 Ala Moana Blvd",
    "sg:city":"Honolulu",
    "sg:classifiers":[
        {
            "category":"Organizations",
            "subcategory":"Professional Association",
            "type":"Services"
        }
    ],
    "sg:phone":"+1 808 537 4308",
    "sg:postcode":"96813",
    "sg:province":"HI",
    "sg:tags":[
        "business",
        "trade"
    ],
    "wof:name":"Legislative Center",
    "wof:placetype":"venue"
},
  "geometry": {"coordinates":[-157.86200500000001,21.297705],"type":"Point"}
}