{
  "type": "Feature",
  "properties": {
    "iso:country":"US",
    "sg:address":"41 Ohiaku St",
    "sg:city":"Aiea",
    "sg:classifiers":[
        {
            "category":"Freight",
            "type":"Transportation"
        },
        {
            "category":"Building & Trades",
            "subcategory":"Landscaping Services",
            "type":"Services"
        }
    ],
    "sg:phone":"+1 808 486 3029",
    "sg:postcode":"96701",
    "sg:province":"HI",
    "sg:tags":[
        "operator",
        "trucking",
        "local",
        "landscape",
        "contractor"
    ],
    "wof:name":"Abeuno Landscape Hauling Svcs",
    "wof:placetype":"venue"
},
  "geometry": {"coordinates":[-157.93416199999999,21.364532],"type":"Point"}
}