{
  "type": "Feature",
  "properties": {
    "addr:full":"1926 S Beretania St Honolulu HI 96826",
    "addr:housenumber":"1926",
    "addr:postcode":"96826",
    "addr:street":"S Beretania St",
    "iso:country":"US",
    "sg:address":"1926 S Beretania St",
    "sg:city":"Honolulu",
    "sg:classifiers":[
        {
            "category":"Food & Beverages",
            "subcategory":"Bakery",
            "type":"Retail Goods"
        }
    ],
    "sg:phone":"+1 808 947 8778",
    "sg:postcode":"96826",
    "sg:province":"HI",
    "wof:name":"Champion Malasadas",
    "wof:placetype":"venue"
},
  "geometry": {"coordinates":[-157.82996800000001,21.296844],"type":"Point"}
}