{
  "type": "Feature",
  "properties": {
    "iso:country":"US",
    "sg:address":"2710 S King St",
    "sg:city":"Honolulu",
    "sg:classifiers":[
        {
            "category":"Food & Beverages",
            "subcategory":"Groceries & Convenience Stores",
            "type":"Retail Goods"
        }
    ],
    "sg:phone":"+1 808 946 2073",
    "sg:postcode":"96826",
    "sg:province":"HI",
    "wof:name":"Fukuya Delicatessen",
    "wof:placetype":"venue"
},
  "geometry": {"coordinates":[-157.82171,21.291939],"type":"Point"}
}