{
  "type": "Feature",
  "properties": {
    "iso:country":"US",
    "sg:address":"5116 Poola St",
    "sg:city":"Honolulu",
    "sg:classifiers":[
        {
            "category":"Wholesale",
            "subcategory":"Durable Goods & Equipment",
            "type":"Manufacturing & Wholesale Goods"
        }
    ],
    "sg:phone":"+1 808 373 4666",
    "sg:postcode":"96821",
    "sg:province":"HI",
    "sg:tags":[
        "representative"
    ],
    "wof:name":"Pacific Sales Representatives",
    "wof:placetype":"venue"
},
  "geometry": {"coordinates":[-157.76084399999999,21.282043],"type":"Point"}
}