{
  "type": "Feature",
  "properties": {
    "iso:country":"US",
    "sg:address":"733 Bishop St",
    "sg:city":"Honolulu",
    "sg:classifiers":[
        {
            "category":"Personal",
            "subcategory":"Beauty Salon",
            "type":"Services"
        }
    ],
    "sg:phone":"+1 808 531 9902",
    "sg:postcode":"96813",
    "sg:province":"HI",
    "sg:tags":[
        "shop"
    ],
    "wof:name":"Hair Designer",
    "wof:placetype":"venue"
},
  "geometry": {"coordinates":[-157.86289500000001,21.307425],"type":"Point"}
}