{
  "type": "Feature",
  "properties": {
    "addr:full":"3140 Ualena St Honolulu HI 96819",
    "addr:housenumber":"3140",
    "addr:postcode":"96819",
    "addr:street":"Ualena St",
    "iso:country":"US",
    "sg:address":"3140 Ualena St",
    "sg:city":"Honolulu",
    "sg:classifiers":[
        {
            "category":"Freight",
            "type":"Transportation"
        }
    ],
    "sg:phone":"+1 808 836 2931",
    "sg:postcode":"96819",
    "sg:province":"HI",
    "sg:tags":[
        "warehouse",
        "storage"
    ],
    "sg:website":"www.unicoldcorp.com",
    "wof:name":"Unicold Corp",
    "wof:placetype":"venue"
},
  "geometry": {"coordinates":[-157.911641,21.334181],"type":"Point"}
}