{
  "type": "Feature",
  "properties": {
    "iso:country":"US",
    "sg:address":"3375 Koapaka St",
    "sg:city":"Honolulu",
    "sg:classifiers":[
        {
            "category":"Professional",
            "subcategory":"Management & Consulting",
            "type":"Services"
        }
    ],
    "sg:phone":"+1 808 836 4094",
    "sg:postcode":"96819",
    "sg:province":"HI",
    "sg:tags":[
        "consultant",
        "security",
        "system"
    ],
    "sg:website":"www.istechs.net",
    "wof:name":"Ingrated Security Tech Inc",
    "wof:placetype":"venue"
},
  "geometry": {"coordinates":[-157.91583600000001,21.336026],"type":"Point"}
}