{
  "type": "Feature",
  "properties": {
    "iso:country":"US",
    "sg:address":"350 Ward Ave",
    "sg:city":"Honolulu",
    "sg:classifiers":[
        {
            "category":"Professional",
            "subcategory":"Business Services",
            "type":"Services"
        }
    ],
    "sg:phone":"+1 808 591 9929",
    "sg:postcode":"96814",
    "sg:province":"HI",
    "sg:tags":[
        "credit",
        "card"
    ],
    "wof:name":"I P S Hawaii",
    "wof:placetype":"venue"
},
  "geometry": {"coordinates":[-157.856393,21.296085],"type":"Point"}
}