{
  "type": "Feature",
  "properties": {
    "iso:country":"US",
    "sg:address":"3276 Hoolimalima Pl",
    "sg:city":"Lihue",
    "sg:classifiers":[
        {
            "category":"Retail",
            "subcategory":"Auto Rental",
            "type":"Services"
        }
    ],
    "sg:phone":"+1 808 246 0646",
    "sg:postcode":"96766",
    "sg:province":"HI",
    "sg:tags":[
        "renting",
        "automobile"
    ],
    "sg:website":"www.alamo.com",
    "wof:name":"Alamo Rent-A-Car",
    "wof:placetype":"venue"
},
  "geometry": {"coordinates":[-159.35082800000001,21.979188],"type":"Point"}
}