{
  "type": "Feature",
  "properties": {
    "iso:country":"US",
    "sg:address":"1034 Apuu St",
    "sg:city":"Ewa Beach",
    "sg:classifiers":[
        {
            "category":"Wholesale",
            "subcategory":"Durable Goods & Equipment",
            "type":"Manufacturing & Wholesale Goods"
        }
    ],
    "sg:phone":"+1 808 681 5511",
    "sg:postcode":"96706",
    "sg:province":"HI",
    "sg:tags":[
        "representative",
        "manufacturer"
    ],
    "wof:name":"Select Building Products Hi",
    "wof:placetype":"venue"
},
  "geometry": {"coordinates":[-158.02634,21.359661],"type":"Point"}
}