{
  "type": "Feature",
  "properties": {
    "iso:country":"US",
    "sg:address":"4938 Alani Pl",
    "sg:city":"Kapaa",
    "sg:classifiers":[
        {
            "category":"Real Estate",
            "subcategory":"Real Estate Agent",
            "type":"Services"
        },
        {
            "category":"Professional",
            "subcategory":"Business Services",
            "type":"Services"
        }
    ],
    "sg:phone":"+1 808 822 7876",
    "sg:postcode":"96746",
    "sg:province":"HI",
    "sg:tags":[
        "appraiser"
    ],
    "wof:name":"Garden Island Appraisals Inc",
    "wof:placetype":"venue"
},
  "geometry": {"coordinates":[-159.34130400000001,22.05558],"type":"Point"}
}