{
  "type": "Feature",
  "properties": {
    "addr:full":"2200 Main St Wailuku HI 96793",
    "addr:housenumber":"2200",
    "addr:postcode":"96793",
    "addr:street":"Main St",
    "iso:country":"US",
    "sg:address":"2200 Main St",
    "sg:city":"Wailuku",
    "sg:classifiers":[
        {
            "category":"Professional",
            "subcategory":"Lawyer & Legal Services",
            "type":"Services"
        }
    ],
    "sg:phone":"+1 808 875 8542",
    "sg:postcode":"96793",
    "sg:province":"HI",
    "sg:tags":[
        "attorney"
    ],
    "wof:name":"Kelsey T Kawano",
    "wof:placetype":"venue"
},
  "geometry": {"coordinates":[-156.508725,20.889809],"type":"Point"}
}