{
  "type": "Feature",
  "properties": {
    "iso:country":"US",
    "sg:address":"2875 S King St",
    "sg:city":"Honolulu",
    "sg:classifiers":[
        {
            "category":"Real Estate",
            "subcategory":"Real Estate Agent",
            "type":"Services"
        }
    ],
    "sg:phone":"+1 808 949 6102",
    "sg:postcode":"96826",
    "sg:province":"HI",
    "sg:tags":[
        "manager",
        "property"
    ],
    "wof:name":"Furuya & Furuya Properties",
    "wof:placetype":"venue"
},
  "geometry": {"coordinates":[-157.81627,21.289165],"type":"Point"}
}