{
  "type": "Feature",
  "properties": {
    "addr:full":"29 Hui Iwa Pl Kaneohe HI 96744",
    "addr:housenumber":"29",
    "addr:postcode":"96744",
    "addr:street":"Hui Iwa Pl",
    "iso:country":"US",
    "sg:address":"29 Hui Iwa Pl",
    "sg:city":"Kaneohe",
    "sg:classifiers":[
        {
            "category":"Professional",
            "type":"Services"
        }
    ],
    "sg:phone":"+1 404 509 2690",
    "sg:postcode":"96744",
    "sg:province":"HI",
    "sg:tags":[
        "development",
        "communications",
        "program",
        "health"
    ],
    "wof:name":"Cole Krista Hopkins",
    "wof:placetype":"venue"
},
  "geometry": {"coordinates":[-157.8246,21.439063],"type":"Point"}
}