{
  "type": "Feature",
  "properties": {
    "iso:country":"US",
    "sg:address":"1794 Pahoa Rd",
    "sg:city":"Keaau",
    "sg:classifiers":[
        {
            "category":"Building & Trades",
            "subcategory":"Plumbing",
            "type":"Services"
        }
    ],
    "sg:phone":"+1 808 982 8668",
    "sg:postcode":"96749",
    "sg:province":"HI",
    "sg:tags":[
        "septic"
    ],
    "wof:name":"A & B Septic Svc",
    "wof:placetype":"venue"
},
  "geometry": {"coordinates":[-154.98652799999999,19.554054],"type":"Point"}
}