{
  "type": "Feature",
  "properties": {
    "iso:country":"US",
    "sg:address":"735 Keeaumoku St",
    "sg:city":"Honolulu",
    "sg:classifiers":[
        {
            "category":"Real Estate",
            "subcategory":"Real Estate Operator",
            "type":"Services"
        }
    ],
    "sg:phone":"+1 808 951 1141",
    "sg:postcode":"96814",
    "sg:province":"HI",
    "sg:tags":[
        "owner",
        "property",
        "commercial"
    ],
    "wof:name":"Keeaumoku Group",
    "wof:placetype":"venue"
},
  "geometry": {"coordinates":[-157.84113099999999,21.29612],"type":"Point"}
}