{
  "type": "Feature",
  "properties": {
    "addr:full":"300 Kahelu Ave Mililani HI 96789",
    "addr:housenumber":"300",
    "addr:postcode":"96789",
    "addr:street":"Kahelu Ave",
    "iso:country":"US",
    "sg:address":"300 Kahelu Ave",
    "sg:city":"Mililani",
    "sg:classifiers":[
        {
            "category":"Communications",
            "type":"Services"
        }
    ],
    "sg:phone":"+1 808 623 0154",
    "sg:postcode":"96789",
    "sg:province":"HI",
    "wof:name":"B Bn Communications Div",
    "wof:placetype":"venue"
},
  "geometry": {"coordinates":[-158.02188599999999,21.480084],"type":"Point"}
}