{
  "type": "Feature",
  "properties": {
    "iso:country":"US",
    "sg:address":"1104 Maunakea St",
    "sg:city":"Honolulu",
    "sg:classifiers":[
        {
            "category":"Organizations",
            "subcategory":"Community Association",
            "type":"Services"
        }
    ],
    "sg:phone":"+1 808 533 2311",
    "sg:postcode":"96817",
    "sg:province":"HI",
    "sg:tags":[
        "fraternal"
    ],
    "wof:name":"Wong Kong Har Tong Society",
    "wof:placetype":"venue"
},
  "geometry": {"coordinates":[-157.86222799999999,21.31274],"type":"Point"}
}