{
  "type": "Feature",
  "properties": {
    "iso:country":"US",
    "sg:address":"5 Sand Island Access Rd",
    "sg:city":"Honolulu",
    "sg:classifiers":[
        {
            "category":"Wholesale",
            "subcategory":"Seafood",
            "type":"Manufacturing & Wholesale Goods"
        }
    ],
    "sg:phone":"+1 808 845 5577",
    "sg:postcode":"96819",
    "sg:province":"HI",
    "wof:name":"Wei Chaun Food",
    "wof:placetype":"venue"
},
  "geometry": {"coordinates":[-157.88908699999999,21.316561],"type":"Point"}
}