{
  "type": "Feature",
  "properties": {
    "iso:country":"US",
    "sg:address":"4273 Rice St",
    "sg:city":"Lihue",
    "sg:classifiers":[
        {
            "category":"Organizations",
            "subcategory":"Labor Organization",
            "type":"Services"
        }
    ],
    "sg:phone":"+1 808 245 8423",
    "sg:postcode":"96766",
    "sg:province":"HI",
    "wof:name":"IBEW Local 1186 Inc",
    "wof:placetype":"venue"
},
  "geometry": {"coordinates":[-159.36489499999999,21.972326],"type":"Point"}
}