{
  "type": "Feature",
  "properties": {
    "iso:country":"US",
    "sg:address":"740 Kilauea Ave",
    "sg:city":"Hilo",
    "sg:classifiers":[
        {
            "category":"Health Services",
            "subcategory":"Health Practitioner",
            "type":"Services"
        }
    ],
    "sg:phone":"+1 808 935 5255",
    "sg:postcode":"96720",
    "sg:province":"HI",
    "sg:tags":[
        "specialty",
        "outpatient"
    ],
    "wof:name":"Big Island Physcl Therapy Care",
    "wof:placetype":"venue"
},
  "geometry": {"coordinates":[-155.079373,19.716841],"type":"Point"}
}