{
  "type": "Feature",
  "properties": {
    "addr:full":"1957 Kinoole St Hilo HI 96720",
    "addr:housenumber":"1957",
    "addr:postcode":"96720",
    "addr:street":"Kinoole St",
    "iso:country":"US",
    "sg:address":"1957 Kinoole St",
    "sg:city":"Hilo",
    "sg:classifiers":[
        {
            "category":"Social Services",
            "subcategory":"Child Care",
            "type":"Services"
        }
    ],
    "sg:phone":"+1 808 959 3896",
    "sg:postcode":"96720",
    "sg:province":"HI",
    "wof:name":"Hilo 1 Preschool",
    "wof:placetype":"venue"
},
  "geometry": {"coordinates":[-155.06950800000001,19.690883],"type":"Point"}
}