{
  "type": "Feature",
  "properties": {
    "iso:country":"US",
    "sg:address":"228 William Henry Rd",
    "sg:city":"Kaneohe",
    "sg:classifiers":[
        {
            "category":"Shopping",
            "subcategory":"Bicycles & Sporting Goods",
            "type":"Retail Goods"
        }
    ],
    "sg:phone":"+1 808 247 0756",
    "sg:postcode":"96744",
    "sg:province":"HI",
    "wof:name":"Alfuri Pool Table Recovering",
    "wof:placetype":"venue"
},
  "geometry": {"coordinates":[-157.797157,21.415701],"type":"Point"}
}