{
  "type": "Feature",
  "properties": {
    "iso:country":"US",
    "sg:address":"801 Papipi Rd",
    "sg:city":"Ewa Beach",
    "sg:classifiers":[
        {
            "category":"Shopping",
            "subcategory":"Florist",
            "type":"Retail Goods"
        }
    ],
    "sg:phone":"+1 808 689 8668",
    "sg:postcode":"96706",
    "sg:province":"HI",
    "wof:name":"Ewa Beach Floral & Gifts LLC",
    "wof:placetype":"venue"
},
  "geometry": {"coordinates":[-158.01351099999999,21.315822],"type":"Point"}
}