{
  "type": "Feature",
  "properties": {
    "addr:full":"2500 Kuhio Ave Honolulu HI 96815",
    "addr:housenumber":"2500",
    "addr:postcode":"96815",
    "addr:street":"Kuhio Ave",
    "iso:country":"US",
    "sg:address":"2500 Kuhio Ave",
    "sg:city":"Honolulu",
    "sg:classifiers":[
        {
            "category":"Travel",
            "subcategory":"Travel Agent",
            "type":"Entertainment"
        }
    ],
    "sg:phone":"+1 808 931 6030",
    "sg:postcode":"96815",
    "sg:province":"HI",
    "sg:tags":[
        "tours",
        "promoter"
    ],
    "wof:name":"Cosmos & Globus Tours",
    "wof:placetype":"venue"
},
  "geometry": {"coordinates":[-157.82208600000001,21.275036],"type":"Point"}
}