{
  "type": "Feature",
  "properties": {
    "iso:country":"US",
    "sg:address":"5530 Kuakini Hwy",
    "sg:city":"Kailua Kona",
    "sg:classifiers":[
        {
            "category":"Recreation",
            "type":"Entertainment"
        }
    ],
    "sg:phone":"+1 808 327 3500",
    "sg:postcode":"96740",
    "sg:province":"HI",
    "sg:tags":[
        "pool",
        "swimming"
    ],
    "wof:name":"Kona Community Aquatic Ctr",
    "wof:placetype":"venue"
},
  "geometry": {"coordinates":[-156.004108,19.642511],"type":"Point"}
}