{
  "type": "Feature",
  "properties": {
    "iso:country":"US",
    "sg:address":"725 Kapiolani Blvd",
    "sg:city":"Honolulu",
    "sg:classifiers":[
        {
            "category":"Wholesale",
            "subcategory":"Jewelry",
            "type":"Manufacturing & Wholesale Goods"
        }
    ],
    "sg:phone":"+1 808 589 2188",
    "sg:postcode":"96813",
    "sg:province":"HI",
    "sg:tags":[
        "stone"
    ],
    "wof:name":"B&W Pacific Pearl Co Inc",
    "wof:placetype":"venue"
},
  "geometry": {"coordinates":[-157.85470000000001,21.301593],"type":"Point"}
}