{
  "type": "Feature",
  "properties": {
    "iso:country":"US",
    "sg:address":"1172 Wainiha St",
    "sg:city":"Honolulu",
    "sg:classifiers":[
        {
            "category":"Real Estate",
            "subcategory":"Real Estate Agent",
            "type":"Services"
        },
        {
            "category":"Real Estate",
            "subcategory":"Real Estate Operator",
            "type":"Services"
        }
    ],
    "sg:phone":"+1 808 395 8522",
    "sg:postcode":"96825",
    "sg:province":"HI",
    "sg:tags":[
        "condominium"
    ],
    "wof:name":"Mariners Village III",
    "wof:placetype":"venue"
},
  "geometry": {"coordinates":[-157.68561199999999,21.305645],"type":"Point"}
}