{
  "type": "Feature",
  "properties": {
    "iso:country":"US",
    "sg:address":"2301 Pauoa Rd",
    "sg:city":"Honolulu",
    "sg:classifiers":[
        {
            "category":"Education",
            "subcategory":"School",
            "type":"Public Place"
        }
    ],
    "sg:phone":"+1 808 587 4500",
    "sg:postcode":"96813",
    "sg:province":"HI",
    "sg:tags":[
        "elementary"
    ],
    "wof:name":"Pauoa Elementary School",
    "wof:placetype":"venue"
},
  "geometry": {"coordinates":[-157.84427199999999,21.319247],"type":"Point"}
}