{
  "type": "Feature",
  "properties": {
    "iso:country":"US",
    "sg:address":"205 Aukahi Pl",
    "sg:city":"Kapolei",
    "sg:classifiers":[
        {
            "category":"Professional",
            "subcategory":"Detective & Security Services",
            "type":"Services"
        }
    ],
    "sg:phone":"+1 808 674 8601",
    "sg:postcode":"96707",
    "sg:province":"HI",
    "sg:tags":[
        "investigator"
    ],
    "wof:name":"Transcend Inc",
    "wof:placetype":"venue"
},
  "geometry": {"coordinates":[-158.06167500000001,21.33264],"type":"Point"}
}