{
  "type": "Feature",
  "properties": {
    "iso:country":"US",
    "sg:address":"728 Huikahi St",
    "sg:city":"Pearl City",
    "sg:classifiers":[
        {
            "category":"Home & Garden",
            "subcategory":"Home Furnishings",
            "type":"Retail Goods"
        }
    ],
    "sg:phone":"+1 808 455 3222",
    "sg:postcode":"96782",
    "sg:province":"HI",
    "sg:tags":[
        "blind",
        "mini",
        "vertical",
        "venetian",
        "a",
        "drapery"
    ],
    "wof:name":"Pauls Carpets",
    "wof:placetype":"venue"
},
  "geometry": {"coordinates":[-157.957831,21.405772],"type":"Point"}
}