{
  "type": "Feature",
  "properties": {
    "iso:country":"US",
    "sg:address":"2531 S Kihei Rd",
    "sg:city":"Kihei",
    "sg:classifiers":[
        {
            "category":"Real Estate",
            "subcategory":"Real Estate Agent",
            "type":"Services"
        }
    ],
    "sg:phone":"+1 808 879 3383",
    "sg:postcode":"96753",
    "sg:province":"HI",
    "wof:name":"Ah Enterprises",
    "wof:placetype":"venue"
},
  "geometry": {"coordinates":[-156.446946,20.720645],"type":"Point"}
}