{
  "type": "Feature",
  "properties": {
    "iso:country":"US",
    "sg:address":"1767 Malanai St",
    "sg:city":"Honolulu",
    "sg:classifiers":[
        {
            "category":"Organizations",
            "subcategory":"Religious Organization",
            "type":"Services"
        }
    ],
    "sg:phone":"+1 808 955 7800",
    "sg:postcode":"96826",
    "sg:province":"HI",
    "sg:tags":[
        "synagogue"
    ],
    "wof:name":"Jodo Shinshu Shinrankai Inc",
    "wof:placetype":"venue"
},
  "geometry": {"coordinates":[-157.83588499999999,21.293661],"type":"Point"}
}