{
  "type": "Feature",
  "properties": {
    "iso:country":"US",
    "sg:address":"1913 S Kihei Rd",
    "sg:city":"Kihei",
    "sg:classifiers":[
        {
            "category":"Shopping",
            "subcategory":"Clothing, Apparel, & Fashions",
            "type":"Retail Goods"
        }
    ],
    "sg:phone":"+1 808 875 0303",
    "sg:postcode":"96753",
    "sg:province":"HI",
    "sg:tags":[
        "lingerie"
    ],
    "wof:name":"Love Shack Maui",
    "wof:placetype":"venue"
},
  "geometry": {"coordinates":[-156.45191199999999,20.731397],"type":"Point"}
}