{
  "type": "Feature",
  "properties": {
    "addr:full":"1379 Waihona St Pearl City HI 96782",
    "addr:housenumber":"1379",
    "addr:postcode":"96782",
    "addr:street":"Waihona St",
    "iso:country":"US",
    "sg:address":"1379 Waihona St",
    "sg:city":"Pearl City",
    "sg:classifiers":[
        {
            "category":"Freight",
            "type":"Transportation"
        }
    ],
    "sg:phone":"+1 808 456 6691",
    "sg:postcode":"96782",
    "sg:province":"HI",
    "wof:name":"Royal Hawaiian Express",
    "wof:placetype":"venue"
},
  "geometry": {"coordinates":[-157.971924,21.411911],"type":"Point"}
}