{
  "type": "Feature",
  "properties": {
    "addr:full":"6246 Alii Dr Kailua Kona HI 96740",
    "addr:housenumber":"6246",
    "addr:postcode":"96740",
    "addr:street":"Alii Dr",
    "iso:country":"US",
    "sg:address":"6246 Alii Dr",
    "sg:city":"Kailua Kona",
    "sg:classifiers":[
        {
            "category":"Real Estate",
            "subcategory":"Real Estate Operator",
            "type":"Services"
        }
    ],
    "sg:phone":"+1 808 329 9381",
    "sg:postcode":"96740",
    "sg:province":"HI",
    "sg:tags":[
        "condominium"
    ],
    "sg:website":"www.marcresorts.com",
    "wof:name":"Kona Bali Kai Resort",
    "wof:placetype":"venue"
},
  "geometry": {"coordinates":[-155.976812,19.607543],"type":"Point"}
}