{
  "type": "Feature",
  "properties": {
    "addr:full":"4426 Aku Rd Hanalei HI 96714",
    "addr:housenumber":"4426",
    "addr:postcode":"96714",
    "addr:street":"Aku Rd",
    "iso:country":"US",
    "sg:address":"4426 Aku Rd",
    "sg:city":"Hanalei",
    "sg:classifiers":[
        {
            "category":"Building & Trades",
            "subcategory":"Construction",
            "type":"Services"
        }
    ],
    "sg:phone":"+1 808 651 0781",
    "sg:postcode":"96714",
    "sg:province":"HI",
    "sg:tags":[
        "contractor"
    ],
    "wof:name":"Thompson Ward Construction",
    "wof:placetype":"venue"
},
  "geometry": {"coordinates":[-159.49714,22.205575],"type":"Point"}
}