{
  "type": "Feature",
  "properties": {
    "iso:country":"US",
    "sg:address":"192 Kepue Pl",
    "sg:city":"Waianae",
    "sg:classifiers":[
        {
            "category":"Professional",
            "subcategory":"Computer Services",
            "type":"Services"
        }
    ],
    "sg:phone":"+1 808 695 8691",
    "sg:postcode":"96792",
    "sg:province":"HI",
    "sg:tags":[
        "consultant",
        "system"
    ],
    "wof:name":"WIS Consulting",
    "wof:placetype":"venue"
},
  "geometry": {"coordinates":[-158.214687,21.472544],"type":"Point"}
}