{
  "type": "Feature",
  "properties": {
    "iso:country":"US",
    "sg:address":"123 Puuohalai Pl",
    "sg:city":"Kaneohe",
    "sg:classifiers":[
        {
            "category":"Health Services",
            "subcategory":"Health Practitioner",
            "type":"Services"
        }
    ],
    "sg:phone":"+1 808 739 6222",
    "sg:postcode":"96744",
    "sg:province":"HI",
    "wof:name":"Jeanne S Hoffman PHD",
    "wof:placetype":"venue"
},
  "geometry": {"coordinates":[-157.76784900000001,21.41362],"type":"Point"}
}