{
  "type": "Feature",
  "properties": {
    "iso:country":"US",
    "sg:address":"2203 Makanani Dr",
    "sg:city":"Honolulu",
    "sg:classifiers":[
        {
            "category":"Professional",
            "type":"Services"
        }
    ],
    "sg:phone":"+1 808 843 2422",
    "sg:postcode":"96817",
    "sg:province":"HI",
    "wof:name":"Gateway Construction",
    "wof:placetype":"venue"
},
  "geometry": {"coordinates":[-157.859174,21.333116],"type":"Point"}
}