{
  "type": "Feature",
  "properties": {
    "iso:country":"US",
    "sg:address":"834 Kilani Ave",
    "sg:city":"Wahiawa",
    "sg:classifiers":[
        {
            "category":"Real Estate",
            "subcategory":"Developer",
            "type":"Services"
        }
    ],
    "sg:phone":"+1 808 621 0533",
    "sg:postcode":"96786",
    "sg:province":"HI",
    "wof:name":"Hawaiian American Land Corp",
    "wof:placetype":"venue"
},
  "geometry": {"coordinates":[-158.02681899999999,21.499211],"type":"Point"}
}