{
  "type": "Feature",
  "properties": {
    "iso:country":"US",
    "sg:address":"2526 Pauoa Rd",
    "sg:city":"Honolulu",
    "sg:classifiers":[
        {
            "category":"Wholesale",
            "subcategory":"Construction Materials",
            "type":"Manufacturing & Wholesale Goods"
        }
    ],
    "sg:phone":"+1 808 847 6460",
    "sg:postcode":"96813",
    "sg:province":"HI",
    "wof:name":"R T N Inc",
    "wof:placetype":"venue"
},
  "geometry": {"coordinates":[-157.83802900000001,21.322201],"type":"Point"}
}