{
  "type": "Feature",
  "properties": {
    "iso:country":"US",
    "sg:address":"2780 Kekaa Dr",
    "sg:city":"Lahaina",
    "sg:classifiers":[
        {
            "category":"Shopping",
            "subcategory":"Florist",
            "type":"Retail Goods"
        }
    ],
    "sg:phone":"+1 808 661 3900",
    "sg:postcode":"96761",
    "sg:province":"HI",
    "wof:name":"Ohana Floral Design & Gifts",
    "wof:placetype":"venue"
},
  "geometry": {"coordinates":[-156.693667,20.936335],"type":"Point"}
}