{
  "type": "Feature",
  "properties": {
    "iso:country":"US",
    "sg:address":"1307 Liliha St",
    "sg:city":"Honolulu",
    "sg:classifiers":[
        {
            "category":"Recreation",
            "type":"Entertainment"
        }
    ],
    "sg:phone":"+1 808 550 0449",
    "sg:postcode":"96817",
    "sg:province":"HI",
    "sg:tags":[
        "hall",
        "auditorium"
    ],
    "wof:name":"Kukui Gardens Community Cntr",
    "wof:placetype":"venue"
},
  "geometry": {"coordinates":[-157.862213,21.31976],"type":"Point"}
}