{
  "type": "Feature",
  "properties": {
    "iso:country":"US",
    "sg:address":"352 Halawa Vw Lp",
    "sg:city":"Honolulu",
    "sg:classifiers":[
        {
            "category":"Government",
            "subcategory":"Office",
            "type":"Public Place"
        }
    ],
    "sg:phone":"+1 808 473 6001",
    "sg:postcode":"96818",
    "sg:province":"HI",
    "sg:tags":[
        "national",
        "security"
    ],
    "wof:name":"Commander In Chief PCF Fleet",
    "wof:placetype":"venue"
},
  "geometry": {"coordinates":[-157.906057,21.366528],"type":"Point"}
}