{
  "type": "Feature",
  "properties": {
    "iso:country":"US",
    "sg:address":"919 Ala Moana Blvd",
    "sg:city":"Honolulu",
    "sg:classifiers":[
        {
            "category":"Government",
            "subcategory":"Office",
            "type":"Public Place"
        }
    ],
    "sg:phone":"+1 808 586 4309",
    "sg:postcode":"96814",
    "sg:province":"HI",
    "sg:tags":[
        "state",
        "program"
    ],
    "wof:name":"Clean Water Div",
    "wof:placetype":"venue"
},
  "geometry": {"coordinates":[-157.85803899999999,21.295021],"type":"Point"}
}