{
  "type": "Feature",
  "properties": {
    "iso:country":"US",
    "sg:address":"426 Haona St",
    "sg:city":"Waialua",
    "sg:classifiers":[
        {
            "category":"Building & Trades",
            "subcategory":"Construction",
            "type":"Services"
        }
    ],
    "sg:phone":"+1 808 637 5575",
    "sg:postcode":"96791",
    "sg:province":"HI",
    "sg:tags":[
        "housing",
        "general",
        "for",
        "family",
        "contractor"
    ],
    "wof:name":"Regal Construction Inc",
    "wof:placetype":"venue"
},
  "geometry": {"coordinates":[-158.118078,21.567517],"type":"Point"}
}