{
  "type": "Feature",
  "properties": {
    "addr:full":"545 Kaaahi St Honolulu HI 96817",
    "addr:housenumber":"545",
    "addr:postcode":"96817",
    "addr:street":"Kaaahi St",
    "iso:country":"US",
    "sg:address":"545 Kaaahi St",
    "sg:city":"Honolulu",
    "sg:classifiers":[
        {
            "category":"Retail",
            "subcategory":"Auto Repair",
            "type":"Services"
        }
    ],
    "sg:phone":"+1 808 841 5036",
    "sg:postcode":"96817",
    "sg:province":"HI",
    "sg:tags":[
        "body",
        "automobile",
        "painting"
    ],
    "wof:name":"Nuuanu Auto Co LTD",
    "wof:placetype":"venue"
},
  "geometry": {"coordinates":[-157.866331,21.318327],"type":"Point"}
}