{
  "type": "Feature",
  "properties": {
    "iso:country":"US",
    "sg:address":"265 Keawe St",
    "sg:city":"Hilo",
    "sg:classifiers":[
        {
            "category":"Home & Garden",
            "subcategory":"Furniture",
            "type":"Retail Goods"
        }
    ],
    "sg:phone":"+1 808 933 9866",
    "sg:postcode":"96720",
    "sg:province":"HI",
    "sg:tags":[
        "bedding"
    ],
    "wof:name":"Sha Sha Decor",
    "wof:placetype":"venue"
},
  "geometry": {"coordinates":[-155.08648099999999,19.723705],"type":"Point"}
}