{
  "type": "Feature",
  "properties": {
    "addr:full":"1623 Hoomaike St Pearl City HI 96782",
    "addr:housenumber":"1623",
    "addr:postcode":"96782",
    "addr:street":"Hoomaike St",
    "iso:country":"US",
    "sg:address":"1623 Hoomaike St",
    "sg:city":"Pearl City",
    "sg:classifiers":[
        {
            "category":"Retail",
            "subcategory":"Laundry & Dry Cleaning",
            "type":"Services"
        }
    ],
    "sg:phone":"+1 808 330 8220",
    "sg:postcode":"96782",
    "sg:province":"HI",
    "sg:tags":[
        "professional"
    ],
    "wof:name":"Champion Clean",
    "wof:placetype":"venue"
},
  "geometry": {"coordinates":[-157.952404,21.397556],"type":"Point"}
}