{
  "type": "Feature",
  "properties": {
    "addr:full":"1385 Waihona St Pearl City HI 96782",
    "addr:housenumber":"1385",
    "addr:postcode":"96782",
    "addr:street":"Waihona St",
    "iso:country":"US",
    "sg:address":"1385 Waihona St",
    "sg:city":"Pearl City",
    "sg:classifiers":[
        {
            "category":"Retail",
            "subcategory":"Portrait Studio",
            "type":"Services"
        }
    ],
    "sg:phone":"+1 808 455 6571",
    "sg:postcode":"96782",
    "sg:province":"HI",
    "sg:tags":[
        "photographer"
    ],
    "sg:website":"www.lifetouch.com",
    "wof:name":"Lifetouch",
    "wof:placetype":"venue"
},
  "geometry": {"coordinates":[-157.97204500000001,21.41169],"type":"Point"}
}