{
  "type": "Feature",
  "properties": {
    "addr:full":"265 Aikahi Pl Kailua HI 96734",
    "addr:housenumber":"265",
    "addr:postcode":"96734",
    "addr:street":"Aikahi Pl",
    "iso:country":"US",
    "sg:address":"265 Aikahi Pl",
    "sg:city":"Kailua",
    "sg:classifiers":[
        {
            "category":"Building & Trades",
            "subcategory":"Construction",
            "type":"Services"
        }
    ],
    "sg:phone":"+1 808 254 5428",
    "sg:postcode":"96734",
    "sg:province":"HI",
    "sg:tags":[
        "house"
    ],
    "wof:name":"Lillico Construction Co",
    "wof:placetype":"venue"
},
  "geometry": {"coordinates":[-157.74757399999999,21.423506],"type":"Point"}
}