{
  "type": "Feature",
  "properties": {
    "iso:country":"US",
    "sg:address":"819 Ahua St",
    "sg:city":"Honolulu",
    "sg:classifiers":[
        {
            "category":"Retail",
            "subcategory":"Auto Rental",
            "type":"Services"
        }
    ],
    "sg:phone":"+1 808 848 0844",
    "sg:postcode":"96819",
    "sg:province":"HI",
    "sg:tags":[
        "renting",
        "truck",
        "leasing"
    ],
    "wof:name":"Penske Truck Leasing 5050-10",
    "wof:placetype":"venue"
},
  "geometry": {"coordinates":[-157.89569599999999,21.340759],"type":"Point"}
}