{
  "type": "Feature",
  "properties": {
    "iso:country":"US",
    "sg:address":"2188 Kamehameha Hwy",
    "sg:city":"Honolulu",
    "sg:classifiers":[
        {
            "category":"Building & Trades",
            "subcategory":"Construction",
            "type":"Services"
        }
    ],
    "sg:phone":"+1 808 841 3625",
    "sg:postcode":"96819",
    "sg:province":"HI",
    "sg:tags":[
        "painter"
    ],
    "wof:name":"Hirota Painting Co Inc",
    "wof:placetype":"venue"
},
  "geometry": {"coordinates":[-157.88316,21.330063],"type":"Point"}
}