{
  "type": "Feature",
  "properties": {
    "iso:country":"US",
    "sg:address":"357 Puhawai Rd",
    "sg:city":"Waianae",
    "sg:classifiers":[
        {
            "category":"Shopping",
            "subcategory":"Hobbies, Toys, & Games",
            "type":"Retail Goods"
        }
    ],
    "sg:phone":"+1 808 696 2597",
    "sg:postcode":"96792",
    "sg:province":"HI",
    "sg:tags":[
        "craft"
    ],
    "wof:name":"Iokepas Crafts",
    "wof:placetype":"venue"
},
  "geometry": {"coordinates":[-158.15827200000001,21.44479],"type":"Point"}
}