{
  "type": "Feature",
  "properties": {
    "iso:country":"US",
    "sg:address":"100 Kauna'oa Dr",
    "sg:city":"Kamuela",
    "sg:classifiers":[
        {
            "category":"Museum",
            "type":"Entertainment"
        }
    ],
    "sg:phone":"+1 808 880 3175",
    "sg:postcode":"96743",
    "sg:province":"HI",
    "sg:tags":[
        "gallery"
    ],
    "wof:name":"Amaury Saintgilles Conte",
    "wof:placetype":"venue"
},
  "geometry": {"coordinates":[-155.82114000000001,20.001334],"type":"Point"}
}