{
  "type": "Feature",
  "properties": {
    "addr:full":"1350 Sand Island Pkwy Honolulu HI 96819",
    "addr:housenumber":"1350",
    "addr:postcode":"96819",
    "addr:street":"Sand Island Pkwy",
    "iso:country":"US",
    "sg:address":"1350 Sand Island Pkwy",
    "sg:city":"Honolulu",
    "sg:classifiers":[
        {
            "category":"Government",
            "subcategory":"Office",
            "type":"Public Place"
        }
    ],
    "sg:phone":"+1 808 847 8300",
    "sg:postcode":"96819",
    "sg:province":"HI",
    "sg:tags":[
        "govt",
        "city"
    ],
    "wof:name":"Wastewater Treatment Plant",
    "wof:placetype":"venue"
},
  "geometry": {"coordinates":[-157.876228,21.306362],"type":"Point"}
}