{
  "type": "Feature",
  "properties": {
    "iso:country":"US",
    "sg:address":"1450 Ala Moana Blvd",
    "sg:city":"Honolulu",
    "sg:classifiers":[
        {
            "category":"Autos & Motor Vehicles",
            "subcategory":"Motorcycle Sales",
            "type":"Retail Goods"
        },
        {
            "category":"Shopping",
            "subcategory":"Clothing, Apparel, & Fashions",
            "type":"Retail Goods"
        }
    ],
    "sg:phone":"+1 808 973 2300",
    "sg:postcode":"96814",
    "sg:province":"HI",
    "sg:tags":[
        "t"
    ],
    "wof:name":"Harley Davidson Motor Clothes",
    "wof:placetype":"venue"
},
  "geometry": {"coordinates":[-157.84143399999999,21.289059],"type":"Point"}
}