{
  "type": "Feature",
  "properties": {
    "addr:full":"880 S Beretania St Honolulu HI 96813",
    "addr:housenumber":"880",
    "addr:postcode":"96813",
    "addr:street":"S Beretania St",
    "iso:country":"US",
    "sg:address":"880 S Beretania St",
    "sg:city":"Honolulu",
    "sg:classifiers":[
        {
            "category":"Health Services",
            "subcategory":"Doctor",
            "type":"Services"
        }
    ],
    "sg:phone":"+1 808 536 2261",
    "sg:postcode":"96813",
    "sg:province":"HI",
    "sg:tags":[
        "physician",
        "surgeon"
    ],
    "wof:name":"Pacific Management Svc",
    "wof:placetype":"venue"
},
  "geometry": {"coordinates":[-157.85055,21.304328],"type":"Point"}
}