{
  "type": "Feature",
  "properties": {
    "addr:full":"626 Kealakai St Hilo HI 96720",
    "addr:housenumber":"626",
    "addr:postcode":"96720",
    "addr:street":"Kealakai St",
    "iso:country":"US",
    "sg:address":"626 Kealakai St",
    "sg:city":"Hilo",
    "sg:classifiers":[
        {
            "category":"Wholesale",
            "subcategory":"Farm Supplies",
            "type":"Manufacturing & Wholesale Goods"
        }
    ],
    "sg:phone":"+1 808 959 9135",
    "sg:postcode":"96720",
    "sg:province":"HI",
    "sg:tags":[
        "horticulture"
    ],
    "wof:name":"Nursery Things Inc",
    "wof:placetype":"venue"
},
  "geometry": {"coordinates":[-155.06151,19.657771],"type":"Point"}
}