{
  "type": "Feature",
  "properties": {
    "iso:country":"US",
    "sg:address":"552 Uhiuala St",
    "sg:city":"Kapolei",
    "sg:classifiers":[
        {
            "category":"Manufacturing",
            "subcategory":"Rubber & Plastics",
            "type":"Manufacturing & Wholesale Goods"
        }
    ],
    "sg:phone":"+1 808 672 4336",
    "sg:postcode":"96707",
    "sg:province":"HI",
    "wof:name":"Classic Plastic Shop",
    "wof:placetype":"venue"
},
  "geometry": {"coordinates":[-158.085635,21.34098],"type":"Point"}
}