{
  "type": "Feature",
  "properties": {
    "iso:country":"US",
    "sg:address":"306 Kaeo Pl",
    "sg:city":"Lahaina",
    "sg:classifiers":[
        {
            "category":"Health Services",
            "subcategory":"Clinic",
            "type":"Services"
        }
    ],
    "sg:phone":"+1 808 667 5356",
    "sg:postcode":"96761",
    "sg:province":"HI",
    "sg:tags":[
        "hypnotherapy"
    ],
    "wof:name":"Destiny",
    "wof:placetype":"venue"
},
  "geometry": {"coordinates":[-156.670242,20.864203],"type":"Point"}
}