{
  "type": "Feature",
  "properties": {
    "addr:full":"1151 Mapunapuna St Honolulu HI 96819",
    "addr:housenumber":"1151",
    "addr:postcode":"96819",
    "addr:street":"Mapunapuna St",
    "iso:country":"US",
    "sg:address":"1151 Mapunapuna St",
    "sg:city":"Honolulu",
    "sg:classifiers":[
        {
            "category":"Shopping",
            "subcategory":"Clothing, Apparel, & Fashions",
            "type":"Retail Goods"
        }
    ],
    "sg:phone":"+1 808 836 0701",
    "sg:postcode":"96819",
    "sg:province":"HI",
    "sg:tags":[
        "tailor"
    ],
    "wof:name":"Michael Lani Creations",
    "wof:placetype":"venue"
},
  "geometry": {"coordinates":[-157.896614,21.346632],"type":"Point"}
}