{
  "type": "Feature",
  "properties": {
    "addr:full":"2570 S Beretania St Honolulu HI 96826",
    "addr:housenumber":"2570",
    "addr:postcode":"96826",
    "addr:street":"S Beretania St",
    "iso:country":"US",
    "sg:address":"2570 S Beretania St",
    "sg:city":"Honolulu",
    "sg:classifiers":[
        {
            "category":"Shopping",
            "subcategory":"Gifts & Souvenirs",
            "type":"Retail Goods"
        }
    ],
    "sg:phone":"+1 808 946 2020",
    "sg:postcode":"96826",
    "sg:province":"HI",
    "sg:tags":[
        "indian"
    ],
    "wof:name":"India Market",
    "wof:placetype":"venue"
},
  "geometry": {"coordinates":[-157.82263800000001,21.292579],"type":"Point"}
}