{
  "type": "Feature",
  "properties": {
    "iso:country":"US",
    "sg:address":"1125 Ala Moana Blvd",
    "sg:city":"Honolulu",
    "sg:classifiers":[
        {
            "category":"Government",
            "subcategory":"Office",
            "type":"Public Place"
        }
    ],
    "sg:phone":"+1 808 592 8301",
    "sg:postcode":"96814",
    "sg:province":"HI",
    "sg:tags":[
        "federal"
    ],
    "wof:name":"National Marine Fisheries Svc",
    "wof:placetype":"venue"
},
  "geometry": {"coordinates":[-157.85400200000001,21.29301],"type":"Point"}
}