{
  "type": "Feature",
  "properties": {
    "iso:country":"US",
    "sg:address":"825 Moanalua Rd",
    "sg:city":"Aiea",
    "sg:classifiers":[
        {
            "category":"Social Services",
            "subcategory":"Child Care",
            "type":"Services"
        },
        {
            "category":"Education",
            "subcategory":"School",
            "type":"Public Place"
        }
    ],
    "sg:phone":"+1 808 488 8126",
    "sg:postcode":"96701",
    "sg:province":"HI",
    "wof:name":"Kama'Aina Kids",
    "wof:placetype":"venue"
},
  "geometry": {"coordinates":[-157.914277,21.370068],"type":"Point"}
}