{
  "type": "Feature",
  "properties": {
    "iso:country":"US",
    "sg:address":"239 Keonekai Rd",
    "sg:city":"Kihei",
    "sg:classifiers":[
        {
            "category":"Building & Trades",
            "subcategory":"Construction",
            "type":"Services"
        }
    ],
    "sg:phone":"+1 808 329 4491",
    "sg:postcode":"96753",
    "sg:province":"HI",
    "sg:tags":[
        "contractor"
    ],
    "wof:name":"Mobley Construction",
    "wof:placetype":"venue"
},
  "geometry": {"coordinates":[-156.439503,20.713893],"type":"Point"}
}