{
  "type": "Feature",
  "properties": {
    "iso:country":"US",
    "sg:address":"292 Goodale Ave",
    "sg:city":"Waialua",
    "sg:classifiers":[
        {
            "category":"Personal",
            "subcategory":"Beauty Salon",
            "type":"Services"
        }
    ],
    "sg:phone":"+1 808 637 4944",
    "sg:postcode":"96791",
    "sg:province":"HI",
    "wof:name":"Mr Gem Hairstyling",
    "wof:placetype":"venue"
},
  "geometry": {"coordinates":[-158.12255300000001,21.568774],"type":"Point"}
}