{
  "type": "Feature",
  "properties": {
    "iso:country":"US",
    "sg:address":"300 E Kawili St",
    "sg:city":"Hilo",
    "sg:classifiers":[
        {
            "category":"Autos & Motor Vehicles",
            "subcategory":"Motorcycle Sales",
            "type":"Retail Goods"
        }
    ],
    "sg:phone":"+1 808 935 4997",
    "sg:postcode":"96720",
    "sg:province":"HI",
    "sg:tags":[
        "scooter",
        "boat"
    ],
    "wof:name":"Cycle Sports Hawaii-Hilo",
    "wof:placetype":"venue"
},
  "geometry": {"coordinates":[-155.06768,19.70582],"type":"Point"}
}