{
  "type": "Feature",
  "properties": {
    "iso:country":"US",
    "sg:address":"743 Waiakamilo Rd",
    "sg:city":"Honolulu",
    "sg:classifiers":[
        {
            "category":"Restaurant",
            "type":"Food & Drink"
        }
    ],
    "sg:phone":"+1 808 845 3943",
    "sg:postcode":"96817",
    "sg:province":"HI",
    "sg:tags":[
        "eating"
    ],
    "wof:name":"Megs Drive-In",
    "wof:placetype":"venue"
},
  "geometry": {"coordinates":[-157.873223,21.326742],"type":"Point"}
}