{
  "type": "Feature",
  "properties": {
    "iso:country":"US",
    "sg:address":"38 S Kukui St",
    "sg:city":"Honolulu",
    "sg:classifiers":[
        {
            "category":"Insurance",
            "subcategory":"Insurance Agent",
            "type":"Services"
        }
    ],
    "sg:phone":"+1 808 523 3002",
    "sg:postcode":"96813",
    "sg:province":"HI",
    "wof:name":"Mililani Life Insurance Co LTD",
    "wof:placetype":"venue"
},
  "geometry": {"coordinates":[-157.858125,21.312596],"type":"Point"}
}