{
  "type": "Feature",
  "properties": {
    "iso:country":"US",
    "sg:address":"1333 Mauilani Pkwy",
    "sg:city":"Kahului",
    "sg:classifiers":[
        {
            "category":"Arena",
            "subcategory":"Sports Club",
            "type":"Entertainment"
        }
    ],
    "sg:phone":"+1 808 877 0469",
    "sg:postcode":"96732",
    "sg:province":"HI",
    "sg:tags":[
        "manager",
        "recruiter",
        "promoter"
    ],
    "wof:name":"Kelly Sports & Consulting Inc",
    "wof:placetype":"venue"
},
  "geometry": {"coordinates":[-156.47552300000001,20.870819],"type":"Point"}
}