{
  "type": "Feature",
  "properties": {
    "iso:country":"US",
    "sg:address":"140 Iako Pl",
    "sg:city":"Honolulu",
    "sg:classifiers":[
        {
            "category":"Education",
            "subcategory":"College",
            "type":"Public Place"
        }
    ],
    "sg:phone":"+1 808 838 1435",
    "sg:postcode":"96819",
    "sg:province":"HI",
    "sg:tags":[
        "academic",
        "school"
    ],
    "wof:name":"Embry-Riddle Aeronautical Univ",
    "wof:placetype":"venue"
},
  "geometry": {"coordinates":[-157.91901999999999,21.315074],"type":"Point"}
}