{
  "type": "Feature",
  "properties": {
    "addr:full":"2340 Kalakaua Ave Honolulu HI 96815",
    "addr:housenumber":"2340",
    "addr:postcode":"96815",
    "addr:street":"Kalakaua Ave",
    "iso:country":"US",
    "sg:address":"2340 Kalakaua Ave",
    "sg:city":"Honolulu",
    "sg:classifiers":[
        {
            "category":"Food & Beverages",
            "subcategory":"Groceries & Convenience Stores",
            "type":"Retail Goods"
        }
    ],
    "sg:phone":"+1 808 926 4471",
    "sg:postcode":"96815",
    "sg:province":"HI",
    "sg:tags":[
        "chain"
    ],
    "wof:name":"ABC",
    "wof:placetype":"venue"
},
  "geometry": {"coordinates":[-157.82674299999999,21.277273],"type":"Point"}
}