{
  "type": "Feature",
  "properties": {
    "addr:full":"221 Pau Hana Rd Makawao HI 96768",
    "addr:housenumber":"221",
    "addr:postcode":"96768",
    "addr:street":"Pau Hana Rd",
    "iso:country":"US",
    "sg:address":"221 Pau Hana Rd",
    "sg:city":"Makawao",
    "sg:classifiers":[
        {
            "category":"Health Services",
            "subcategory":"Health Practitioner",
            "type":"Services"
        }
    ],
    "sg:phone":"+1 808 573 6411",
    "sg:postcode":"96768",
    "sg:province":"HI",
    "sg:tags":[
        "psychologist"
    ],
    "wof:name":"Natasha A Vilas PHD",
    "wof:placetype":"venue"
},
  "geometry": {"coordinates":[-156.32716099999999,20.853022],"type":"Point"}
}