{
  "type": "Feature",
  "properties": {
    "iso:country":"US",
    "sg:address":"1552 Mill St",
    "sg:city":"Wailuku",
    "sg:classifiers":[
        {
            "category":"Wholesale",
            "subcategory":"Groceries",
            "type":"Manufacturing & Wholesale Goods"
        }
    ],
    "sg:phone":"+1 808 244 4996",
    "sg:postcode":"96793",
    "sg:province":"HI",
    "sg:tags":[
        "grocer"
    ],
    "wof:name":"Lisa's Snax",
    "wof:placetype":"venue"
},
  "geometry": {"coordinates":[-156.49917199999999,20.897125],"type":"Point"}
}