{
  "type": "Feature",
  "properties": {
    "iso:country":"US",
    "sg:address":"2100 Kawaihae Rd",
    "sg:city":"Kamuela",
    "sg:classifiers":[
        {
            "category":"Building & Trades",
            "subcategory":"Construction",
            "type":"Services"
        }
    ],
    "sg:phone":"+1 808 885 5865",
    "sg:postcode":"96743",
    "sg:province":"HI",
    "sg:tags":[
        "fence",
        "contractor"
    ],
    "wof:name":"Ranch Services",
    "wof:placetype":"venue"
},
  "geometry": {"coordinates":[-155.727281,20.025017],"type":"Point"}
}