{
  "type": "Feature",
  "properties": {
    "iso:country":"US",
    "sg:address":"650 Waikupanaha St",
    "sg:city":"Waimanalo",
    "sg:classifiers":[
        {
            "category":"Wholesale",
            "subcategory":"Groceries",
            "type":"Manufacturing & Wholesale Goods"
        }
    ],
    "sg:phone":"+1 808 259 5114",
    "sg:postcode":"96795",
    "sg:province":"HI",
    "sg:tags":[
        "food",
        "product"
    ],
    "sg:website":"www.sugarnet.com",
    "wof:name":"Plant Research Corp",
    "wof:placetype":"venue"
},
  "geometry": {"coordinates":[-157.723782,21.334405],"type":"Point"}
}