{
  "type": "Feature",
  "properties": {
    "addr:full":"5596 Pawai Pl Kailua Kona HI 96740",
    "addr:housenumber":"5596",
    "addr:postcode":"96740",
    "addr:street":"Pawai Pl",
    "iso:country":"US",
    "sg:address":"5596 Pawai Pl",
    "sg:city":"Kailua Kona",
    "sg:classifiers":[
        {
            "category":"Organizations",
            "subcategory":"Community Association",
            "type":"Services"
        }
    ],
    "sg:phone":"+1 808 329 2616",
    "sg:postcode":"96740",
    "sg:province":"HI",
    "sg:tags":[
        "fraternal"
    ],
    "wof:name":"Elks Lodge",
    "wof:placetype":"venue"
},
  "geometry": {"coordinates":[-155.999334,19.643608],"type":"Point"}
}