{
  "type": "Feature",
  "properties": {
    "addr:full":"1450 Ala Moana Blvd Honolulu HI 96814",
    "addr:housenumber":"1450",
    "addr:postcode":"96814",
    "addr:street":"Ala Moana Blvd",
    "iso:country":"US",
    "sg:address":"1450 Ala Moana Blvd",
    "sg:city":"Honolulu",
    "sg:classifiers":[
        {
            "category":"Shopping",
            "type":"Retail Goods"
        }
    ],
    "sg:phone":"+1 808 946 7222",
    "sg:postcode":"96814",
    "sg:province":"HI",
    "sg:tags":[
        "candle",
        "merchandise"
    ],
    "wof:name":"Illuminations",
    "wof:placetype":"venue"
},
  "geometry": {"coordinates":[-157.84143399999999,21.289059],"type":"Point"}
}