{
  "type": "Feature",
  "properties": {
    "iso:country":"US",
    "sg:address":"229 Waipahu Depot St",
    "sg:city":"Waipahu",
    "sg:classifiers":[
        {
            "category":"Banks & Credit Unions",
            "subcategory":"Bank",
            "type":"Services"
        }
    ],
    "sg:phone":"+1 808 678 8085",
    "sg:postcode":"96797",
    "sg:province":"HI",
    "sg:tags":[
        "mortgage"
    ],
    "wof:name":"Platinum Financial Group",
    "wof:placetype":"venue"
},
  "geometry": {"coordinates":[-158.00647799999999,21.383975],"type":"Point"}
}