{
  "type": "Feature",
  "properties": {
    "addr:full":"735 Kaululena St Mililani HI 96789",
    "addr:housenumber":"735",
    "addr:postcode":"96789",
    "addr:street":"Kaululena St",
    "iso:country":"US",
    "sg:address":"735 Kaululena St",
    "sg:city":"Mililani",
    "sg:classifiers":[
        {
            "category":"Wholesale",
            "subcategory":"Durable Goods & Equipment",
            "type":"Manufacturing & Wholesale Goods"
        }
    ],
    "sg:phone":"+1 808 625 1000",
    "sg:postcode":"96789",
    "sg:province":"HI",
    "sg:tags":[
        "representative",
        "manufacturer"
    ],
    "wof:name":"Orbit Sales",
    "wof:placetype":"venue"
},
  "geometry": {"coordinates":[-158.00219200000001,21.454378],"type":"Point"}
}