{
  "type": "Feature",
  "properties": {
    "iso:country":"US",
    "sg:address":"3555 Puna Rd",
    "sg:city":"Pahoa",
    "sg:classifiers":[
        {
            "category":"Travel",
            "subcategory":"Hotels & Motels",
            "type":"Entertainment"
        }
    ],
    "sg:phone":"+1 808 965 7441",
    "sg:postcode":"96778",
    "sg:province":"HI",
    "sg:tags":[
        "breakfast",
        "accommodation",
        "bed"
    ],
    "wof:name":"Lava Tree Tropic Inn",
    "wof:placetype":"venue"
},
  "geometry": {"coordinates":[-154.90230600000001,19.511889],"type":"Point"}
}