{
  "type": "Feature",
  "properties": {
    "addr:full":"533 Oneawa St Kailua HI 96734",
    "addr:housenumber":"533",
    "addr:postcode":"96734",
    "addr:street":"Oneawa St",
    "iso:country":"US",
    "sg:address":"533 Oneawa St",
    "sg:city":"Kailua",
    "sg:classifiers":[
        {
            "category":"Retail",
            "subcategory":"Auto Repair",
            "type":"Services"
        }
    ],
    "sg:phone":"+1 808 261 3840",
    "sg:postcode":"96734",
    "sg:province":"HI",
    "sg:tags":[
        "general"
    ],
    "wof:name":"Tysons Complete Repair",
    "wof:placetype":"venue"
},
  "geometry": {"coordinates":[-157.74876699999999,21.401638],"type":"Point"}
}