{
  "type": "Feature",
  "properties": {
    "addr:full":"233 Nani Kailua Dr Kailua Kona HI 96740",
    "addr:housenumber":"233",
    "addr:postcode":"96740",
    "addr:street":"Nani Kailua Dr",
    "iso:country":"US",
    "sg:address":"233 Nani Kailua Dr",
    "sg:city":"Kailua Kona",
    "sg:classifiers":[
        {
            "category":"Restaurant",
            "type":"Food & Drink"
        }
    ],
    "sg:phone":"+1 808 327 2161",
    "sg:postcode":"96740",
    "sg:province":"HI",
    "sg:tags":[
        "eating"
    ],
    "wof:name":"Islan Lava Java",
    "wof:placetype":"venue"
},
  "geometry": {"coordinates":[-155.98084600000001,19.636119],"type":"Point"}
}