{
  "type": "Feature",
  "properties": {
    "iso:country":"US",
    "sg:address":"5811 Alii Dr",
    "sg:city":"Kailua Kona",
    "sg:classifiers":[
        {
            "category":"Restaurant",
            "type":"Food & Drink"
        }
    ],
    "sg:phone":"+1 808 327 9494",
    "sg:postcode":"96740",
    "sg:province":"HI",
    "sg:tags":[
        "eating"
    ],
    "wof:name":"Oceans Sports Bar & Grill",
    "wof:placetype":"venue"
},
  "geometry": {"coordinates":[-155.990656,19.635698],"type":"Point"}
}