{
  "type": "Feature",
  "properties": {
    "iso:country":"US",
    "sg:address":"4569 Kukui St",
    "sg:city":"Kapaa",
    "sg:classifiers":[
        {
            "category":"Professional",
            "subcategory":"Accounting & Tax Preparation",
            "type":"Services"
        }
    ],
    "sg:phone":"+1 808 822 7711",
    "sg:postcode":"96746",
    "sg:province":"HI",
    "sg:tags":[
        "accountant"
    ],
    "wof:name":"Hancock & Co Inc",
    "wof:placetype":"venue"
},
  "geometry": {"coordinates":[-159.31963099999999,22.075822],"type":"Point"}
}