{
  "type": "Feature",
  "properties": {
    "addr:full":"107 Lipoa Pl Aiea HI 96701",
    "addr:housenumber":"107",
    "addr:postcode":"96701",
    "addr:street":"Lipoa Pl",
    "iso:country":"US",
    "sg:address":"107 Lipoa Pl",
    "sg:city":"Aiea",
    "sg:classifiers":[
        {
            "category":"Autos & Motor Vehicles",
            "subcategory":"Auto Supplies",
            "type":"Retail Goods"
        },
        {
            "category":"Wholesale",
            "subcategory":"Auto Parts",
            "type":"Manufacturing & Wholesale Goods"
        }
    ],
    "sg:phone":"+1 808 487 1520",
    "sg:postcode":"96701",
    "sg:province":"HI",
    "sg:tags":[
        "radiator"
    ],
    "wof:name":"Kuroda Radiator Inc",
    "wof:placetype":"venue"
},
  "geometry": {"coordinates":[-157.94521,21.381985],"type":"Point"}
}