{
  "type": "Feature",
  "properties": {
    "iso:country":"US",
    "sg:address":"750 Amana St",
    "sg:city":"Honolulu",
    "sg:classifiers":[
        {
            "category":"Real Estate",
            "subcategory":"Real Estate Operator",
            "type":"Services"
        }
    ],
    "sg:phone":"+1 808 941 8043",
    "sg:postcode":"96814",
    "sg:province":"HI",
    "sg:tags":[
        "condominium"
    ],
    "wof:name":"Holiday Village Condominium",
    "wof:placetype":"venue"
},
  "geometry": {"coordinates":[-157.84036,21.294417],"type":"Point"}
}