{
  "type": "Feature",
  "properties": {
    "iso:country":"US",
    "sg:address":"1650 Liholiho St",
    "sg:city":"Honolulu",
    "sg:classifiers":[
        {
            "category":"Travel",
            "subcategory":"Travel Agent",
            "type":"Entertainment"
        }
    ],
    "sg:phone":"+1 808 550 4330",
    "sg:postcode":"96822",
    "sg:province":"HI",
    "sg:tags":[
        "operator",
        "tour"
    ],
    "wof:name":"Jes Tour",
    "wof:placetype":"venue"
},
  "geometry": {"coordinates":[-157.837309,21.307353],"type":"Point"}
}