{
  "type": "Feature",
  "properties": {
    "iso:country":"US",
    "sg:address":"316 Puuhulu Pl",
    "sg:city":"Waianae",
    "sg:classifiers":[
        {
            "category":"Organizations",
            "subcategory":"Religious Organization",
            "type":"Services"
        }
    ],
    "sg:phone":"+1 808 696 4089",
    "sg:postcode":"96792",
    "sg:province":"HI",
    "wof:name":"Mount Kaala Baptist Churc",
    "wof:placetype":"venue"
},
  "geometry": {"coordinates":[-158.15239800000001,21.447714],"type":"Point"}
}