{
  "type": "Feature",
  "properties": {
    "addr:full":"1316 Kaumualii St Honolulu HI 96817",
    "addr:housenumber":"1316",
    "addr:postcode":"96817",
    "addr:street":"Kaumualii St",
    "iso:country":"US",
    "sg:address":"1316 Kaumualii St",
    "sg:city":"Honolulu",
    "sg:classifiers":[
        {
            "category":"Organizations",
            "subcategory":"Religious Organization",
            "type":"Services"
        }
    ],
    "sg:phone":"+1 808 845 4162",
    "sg:postcode":"96817",
    "sg:province":"HI",
    "wof:name":"Light of World Mission",
    "wof:placetype":"venue"
},
  "geometry": {"coordinates":[-157.874742,21.324744],"type":"Point"}
}