{
  "type": "Feature",
  "properties": {
    "iso:country":"US",
    "sg:address":"130 Waikupanaha St",
    "sg:city":"Waimanalo",
    "sg:classifiers":[
        {
            "category":"Farming",
            "subcategory":"Nursery",
            "type":"Manufacturing & Wholesale Goods"
        }
    ],
    "sg:phone":"+1 808 259 8079",
    "sg:postcode":"96795",
    "sg:province":"HI",
    "sg:tags":[
        "greenhouse"
    ],
    "wof:name":"A & K Nursery",
    "wof:placetype":"venue"
},
  "geometry": {"coordinates":[-157.70912799999999,21.330897],"type":"Point"}
}