{
  "type": "Feature",
  "properties": {
    "iso:country":"US",
    "sg:address":"237 Kaliuna St",
    "sg:city":"Waialua",
    "sg:classifiers":[
        {
            "category":"Shopping",
            "type":"Retail Goods"
        }
    ],
    "sg:phone":"+1 808 637 5193",
    "sg:postcode":"96791",
    "sg:province":"HI",
    "sg:tags":[
        "merchandise"
    ],
    "wof:name":"Ibata Masaichi",
    "wof:placetype":"venue"
},
  "geometry": {"coordinates":[-158.126609,21.579873],"type":"Point"}
}