{
  "type": "Feature",
  "properties": {
    "addr:city":"Honolulu",
    "addr:full":"553 South King Street Honolulu, Hi 96813-3002",
    "addr:house_number":"553",
    "addr:housenumber":"553",
    "addr:phone":"+1 808-447-3910",
    "addr:postcode":"96813-3002",
    "addr:road":"South King Street",
    "addr:state":"HI",
    "addr:street":"S King St",
    "iso:country":"US",
    "sg:address":"553 S King St",
    "sg:city":"Honolulu",
    "sg:classifiers":[
        {
            "category":"Museum",
            "type":"Entertainment"
        }
    ],
    "sg:phone":"+1 808 531 0481",
    "sg:postcode":"96813",
    "sg:province":"HI",
    "sg:tags":[
        "gallery"
    ],
    "sg:website":"www.missionhouses.org",
    "wof:airports":[
        102533997
    ],
    "wof:name":"Mission House Museum",
    "wof:placetype":"venue"
},
  "geometry": {"coordinates":[-157.85681,21.30422],"type":"Point"}
}