{
  "type": "Feature",
  "properties": {
    "addr:full":"553 S King St Honolulu HI 96813",
    "addr:housenumber":"553",
    "addr:postcode":"96813",
    "addr:street":"S King St",
    "iso:country":"US",
    "sg:address":"553 S King St",
    "sg:city":"Honolulu",
    "sg:classifiers":[
        {
            "category":"Museum",
            "type":"Entertainment"
        }
    ],
    "sg:phone":"+1 808 531 0481",
    "sg:postcode":"96813",
    "sg:province":"HI",
    "sg:tags":[
        "gallery"
    ],
    "sg:website":"www.missionhouses.org",
    "wof:name":"Mission Houses Museum",
    "wof:placetype":"venue"
},
  "geometry": {"coordinates":[-157.85620399999999,21.303929],"type":"Point"}
}