{
  "type": "Feature",
  "properties": {
    "addr:full":"1120 Makaaloa St Ewa Beach HI 96706",
    "addr:housenumber":"1120",
    "addr:postcode":"96706",
    "addr:street":"Makaaloa St",
    "iso:country":"US",
    "sg:address":"1120 Makaaloa St",
    "sg:city":"Ewa Beach",
    "sg:classifiers":[
        {
            "category":"Professional",
            "type":"Services"
        }
    ],
    "sg:phone":"+1 808 681 4748",
    "sg:postcode":"96706",
    "sg:province":"HI",
    "wof:name":"Page Painted",
    "wof:placetype":"venue"
},
  "geometry": {"coordinates":[-158.028604,21.358797],"type":"Point"}
}