{
  "type": "Feature",
  "properties": {
    "iso:country":"US",
    "sg:address":"65-1259 Kawaihae Rd",
    "sg:city":"Kamuela",
    "sg:classifiers":[
        {
            "category":"Restaurant",
            "type":"Food & Drink"
        }
    ],
    "sg:menulink":"http://www.allmenus.com/hi/south-kohala/3299-daniel-thiebaut-restaurant/menu/",
    "sg:phone":"+1 808 887 2200",
    "sg:postcode":"96743",
    "sg:province":"HI",
    "sg:tags":[
        "wrap",
        "seafood",
        "sandwich",
        "american"
    ],
    "wof:name":"Daniel Thiebaut Restaurant",
    "wof:placetype":"venue"
},
  "geometry": {"coordinates":[-155.67348200000001,20.02205],"type":"Point"}
}