{
  "type": "Feature",
  "properties": {
    "addr:full":"2210 S King St Honolulu HI 96826",
    "addr:housenumber":"2210",
    "addr:postcode":"96826",
    "addr:street":"S King St",
    "iso:country":"US",
    "sg:address":"2210 S King St",
    "sg:city":"Honolulu",
    "sg:classifiers":[
        {
            "category":"Restaurant",
            "type":"Food & Drink"
        }
    ],
    "sg:phone":"+1 808 947 2125",
    "sg:postcode":"96826",
    "sg:province":"HI",
    "sg:tags":[
        "eating"
    ],
    "wof:name":"Yamagen",
    "wof:placetype":"venue"
},
  "geometry": {"coordinates":[-157.827415,21.293984],"type":"Point"}
}