{
  "type": "Feature",
  "properties": {
    "iso:country":"US",
    "sg:address":"2725 Waimano Home Rd",
    "sg:city":"Pearl City",
    "sg:classifiers":[
        {
            "category":"Professional",
            "subcategory":"Testing Lab",
            "type":"Services"
        }
    ],
    "sg:phone":"+1 808 453 6652",
    "sg:postcode":"96782",
    "sg:province":"HI",
    "sg:tags":[
        "laboratory"
    ],
    "wof:name":"Department of Health Hawaii",
    "wof:placetype":"venue"
},
  "geometry": {"coordinates":[-157.94820899999999,21.418107],"type":"Point"}
}