{
  "type": "Feature",
  "properties": {
    "iso:country":"US",
    "sg:address":"375 Hui Iwa St",
    "sg:city":"Kaneohe",
    "sg:classifiers":[
        {
            "category":"Professional",
            "type":"Services"
        }
    ],
    "sg:phone":"+1 808 282 2721",
    "sg:postcode":"96744",
    "sg:province":"HI",
    "wof:name":"Island Rep",
    "wof:placetype":"venue"
},
  "geometry": {"coordinates":[-157.82749799999999,21.437865],"type":"Point"}
}