{
  "type": "Feature",
  "properties": {
    "iso:country":"US",
    "sg:address":"5191 Mamalahoa Hwy",
    "sg:city":"Captain Cook",
    "sg:classifiers":[
        {
            "category":"Manufacturing",
            "subcategory":"Printing",
            "type":"Manufacturing & Wholesale Goods"
        }
    ],
    "sg:phone":"+1 808 328 1880",
    "sg:postcode":"96704",
    "sg:province":"HI",
    "sg:tags":[
        "newspaper"
    ],
    "wof:name":"Hawaii Island Journal",
    "wof:placetype":"venue"
},
  "geometry": {"coordinates":[-155.88095899999999,19.437179],"type":"Point"}
}