{
  "type": "Feature",
  "properties": {
    "iso:country":"US",
    "sg:address":"1951 E West Rd",
    "sg:city":"Honolulu",
    "sg:classifiers":[
        {
            "category":"Shopping",
            "subcategory":"Clothing, Apparel, & Fashions",
            "type":"Retail Goods"
        }
    ],
    "sg:phone":"+1 808 956 7935",
    "sg:postcode":"96822",
    "sg:province":"HI",
    "wof:name":"Uh Office Captial Improvements",
    "wof:placetype":"venue"
},
  "geometry": {"coordinates":[-157.814504,21.300711],"type":"Point"}
}