{
  "type": "Feature",
  "properties": {
    "iso:country":"US",
    "sg:address":"1006 Kapahulu Ave",
    "sg:city":"Honolulu",
    "sg:classifiers":[
        {
            "category":"Restaurant",
            "type":"Food & Drink"
        }
    ],
    "sg:phone":"+1 808 735 2800",
    "sg:postcode":"96816",
    "sg:province":"HI",
    "sg:tags":[
        "japanese"
    ],
    "sg:website":"www.wasabibistro.com",
    "wof:name":"Wasabi Bistro",
    "wof:placetype":"venue"
},
  "geometry": {"coordinates":[-157.81331599999999,21.28635],"type":"Point"}
}