{
  "type": "Feature",
  "properties": {
    "addr:full":"2100 N Nimitz Hwy Honolulu HI 96819",
    "addr:housenumber":"2100",
    "addr:postcode":"96819",
    "addr:street":"N Nimitz Hwy",
    "iso:country":"US",
    "sg:address":"2100 N Nimitz Hwy",
    "sg:city":"Honolulu",
    "sg:classifiers":[
        {
            "category":"Social Services",
            "type":"Services"
        }
    ],
    "sg:phone":"+1 808 536 5006",
    "sg:postcode":"96819",
    "sg:province":"HI",
    "wof:name":"Voluntary Action Center",
    "wof:placetype":"venue"
},
  "geometry": {"coordinates":[-157.88545500000001,21.327022],"type":"Point"}
}