{
  "type": "Feature",
  "properties": {
    "iso:country":"US",
    "sg:address":"254 Kapuahi St",
    "sg:city":"Makawao",
    "sg:classifiers":[
        {
            "category":"Building & Trades",
            "subcategory":"Construction",
            "type":"Services"
        }
    ],
    "sg:phone":"+1 808 572 7061",
    "sg:postcode":"96768",
    "sg:province":"HI",
    "sg:tags":[
        "contractor"
    ],
    "wof:name":"Re Lo Construction Inc",
    "wof:placetype":"venue"
},
  "geometry": {"coordinates":[-156.33096499999999,20.843996],"type":"Point"}
}