{
  "type": "Feature",
  "properties": {
    "addr:full":"93 Luluka Pl Kihei HI 96753",
    "addr:housenumber":"93",
    "addr:postcode":"96753",
    "addr:street":"Luluka Pl",
    "iso:country":"US",
    "sg:address":"93 Luluka Pl",
    "sg:city":"Kihei",
    "sg:classifiers":[
        {
            "category":"Communications",
            "subcategory":"Film & Video Production",
            "type":"Services"
        }
    ],
    "sg:phone":"+1 808 891 2472",
    "sg:postcode":"96753",
    "sg:province":"HI",
    "sg:tags":[
        "motion"
    ],
    "wof:name":"David Creigh Productions",
    "wof:placetype":"venue"
},
  "geometry": {"coordinates":[-156.45790400000001,20.780417],"type":"Point"}
}