{
  "type": "Feature",
  "properties": {
    "addr:full":"1594 Malo St Lahaina HI 96761",
    "addr:housenumber":"1594",
    "addr:postcode":"96761",
    "addr:street":"Malo St",
    "iso:country":"US",
    "sg:address":"1594 Malo St",
    "sg:city":"Lahaina",
    "sg:classifiers":[
        {
            "category":"Organizations",
            "subcategory":"Religious Organization",
            "type":"Services"
        }
    ],
    "sg:phone":"+1 808 661 3529",
    "sg:postcode":"96761",
    "sg:province":"HI",
    "sg:tags":[
        "church"
    ],
    "sg:website":"www.lds.org",
    "wof:name":"Church Of Jesus Christ Of Lds",
    "wof:placetype":"venue"
},
  "geometry": {"coordinates":[-156.68699899999999,20.902643],"type":"Point"}
}