{
  "type": "Feature",
  "properties": {
    "iso:country":"US",
    "sg:address":"42 Baldwin Ave",
    "sg:city":"Paia",
    "sg:classifiers":[
        {
            "category":"Personal",
            "type":"Services"
        }
    ],
    "sg:phone":"+1 808 579 6070",
    "sg:postcode":"96779",
    "sg:province":"HI",
    "sg:tags":[
        "therapist",
        "massage"
    ],
    "wof:name":"Three Treasures Acupuncture",
    "wof:placetype":"venue"
},
  "geometry": {"coordinates":[-156.376721,20.908763],"type":"Point"}
}