{
  "type": "Feature",
  "properties": {
    "iso:country":"US",
    "sg:address":"3015 Alencastre Pl",
    "sg:city":"Honolulu",
    "sg:classifiers":[
        {
            "category":"Travel",
            "subcategory":"Travel Agent",
            "type":"Entertainment"
        }
    ],
    "sg:phone":"+1 808 735 9494",
    "sg:postcode":"96816",
    "sg:province":"HI",
    "sg:tags":[
        "consultant"
    ],
    "wof:name":"Ecoadventure South East Asia",
    "wof:placetype":"venue"
},
  "geometry": {"coordinates":[-157.80303900000001,21.297354],"type":"Point"}
}