{
  "type": "Feature",
  "properties": {
    "addr:full":"2840 Waimano Home Rd Pearl City HI 96782",
    "addr:housenumber":"2840",
    "addr:postcode":"96782",
    "addr:street":"Waimano Home Rd",
    "iso:country":"US",
    "sg:address":"2840 Waimano Home Rd",
    "sg:city":"Pearl City",
    "sg:classifiers":[
        {
            "category":"Organizations",
            "subcategory":"Non-profit Organization",
            "type":"Services"
        },
        {
            "category":"Social Services",
            "subcategory":"Job Training",
            "type":"Services"
        }
    ],
    "sg:phone":"+1 808 455 7847",
    "sg:postcode":"96782",
    "sg:province":"HI",
    "sg:tags":[
        "shop",
        "handicapped",
        "work",
        "for"
    ],
    "wof:name":"Waimano Auxiliary",
    "wof:placetype":"venue"
},
  "geometry": {"coordinates":[-157.94141099999999,21.421687],"type":"Point"}
}