{
  "type": "Feature",
  "properties": {
    "iso:country":"US",
    "sg:address":"801 Moowaa St",
    "sg:city":"Honolulu",
    "sg:classifiers":[
        {
            "category":"Manufacturing",
            "subcategory":"Tools & Machinery",
            "type":"Manufacturing & Wholesale Goods"
        }
    ],
    "sg:phone":"+1 808 832 7473",
    "sg:postcode":"96817",
    "sg:province":"HI",
    "sg:tags":[
        "water",
        "equipment",
        "works",
        "supply"
    ],
    "wof:name":"Familian Northwest",
    "wof:placetype":"venue"
},
  "geometry": {"coordinates":[-157.87312299999999,21.324268],"type":"Point"}
}