{
  "type": "Feature",
  "properties": {
    "iso:country":"US",
    "sg:address":"1108 Fort Street Ml",
    "sg:city":"Honolulu",
    "sg:classifiers":[
        {
            "category":"Professional",
            "subcategory":"Lawyer & Legal Services",
            "type":"Services"
        }
    ],
    "sg:phone":"+1 808 536 2151",
    "sg:postcode":"96813",
    "sg:province":"HI",
    "sg:tags":[
        "attorney"
    ],
    "wof:name":"Chan & Chan",
    "wof:placetype":"venue"
},
  "geometry": {"coordinates":[-157.860715,21.310301],"type":"Point"}
}