{
  "type": "Feature",
  "properties": {
    "iso:country":"US",
    "sg:address":"2211 Kuhio Ave",
    "sg:city":"Honolulu",
    "sg:classifiers":[
        {
            "category":"Restaurant",
            "type":"Food & Drink"
        }
    ],
    "sg:menulink":"http://www.allmenus.com/hi/honolulu/95600-ihop/menu/",
    "sg:phone":"+1 808 921 2400",
    "sg:postcode":"96815",
    "sg:province":"HI",
    "sg:tags":[
        "sandwich",
        "salad",
        "burger",
        "soup",
        "american",
        "steakhouse",
        "wrap"
    ],
    "wof:name":"IHOP",
    "wof:placetype":"venue"
},
  "geometry": {"coordinates":[-157.82826800000001,21.280988],"type":"Point"}
}