{
  "type": "Feature",
  "properties": {
    "addr:full":"828 Lumikuke Loop Waipahu HI 96797",
    "addr:housenumber":"828",
    "addr:postcode":"96797",
    "addr:street":"Lumikuke Loop",
    "iso:country":"US",
    "sg:address":"828 Lumikuke Loop",
    "sg:city":"Waipahu",
    "sg:classifiers":[
        {
            "category":"Social Services",
            "type":"Services"
        }
    ],
    "sg:phone":"+1 808 671 1140",
    "sg:postcode":"96797",
    "sg:province":"HI",
    "wof:name":"F Nieves Binder",
    "wof:placetype":"venue"
},
  "geometry": {"coordinates":[-157.991849,21.406705],"type":"Point"}
}