{
  "type": "Feature",
  "properties": {
    "iso:country":"US",
    "sg:address":"412 Wainaku Ave",
    "sg:city":"Hilo",
    "sg:classifiers":[
        {
            "category":"Arts & Performance",
            "subcategory":"Theater",
            "type":"Entertainment"
        }
    ],
    "sg:phone":"+1 808 935 7778",
    "sg:postcode":"96720",
    "sg:province":"HI",
    "sg:tags":[
        "group"
    ],
    "wof:name":"Hakahilua Ltd",
    "wof:placetype":"venue"
},
  "geometry": {"coordinates":[-155.091601,19.729231],"type":"Point"}
}