{
  "type": "Feature",
  "properties": {
    "addr:full":"1441 Piikoi St Honolulu HI 96822",
    "addr:housenumber":"1441",
    "addr:postcode":"96822",
    "addr:street":"Piikoi St",
    "iso:country":"US",
    "sg:address":"1441 Piikoi St",
    "sg:city":"Honolulu",
    "sg:classifiers":[
        {
            "category":"Wholesale",
            "subcategory":"Jewelry",
            "type":"Manufacturing & Wholesale Goods"
        }
    ],
    "sg:phone":"+1 808 528 4715",
    "sg:postcode":"96822",
    "sg:province":"HI",
    "sg:tags":[
        "stone"
    ],
    "wof:name":"April Enterprises",
    "wof:placetype":"venue"
},
  "geometry": {"coordinates":[-157.841768,21.303986],"type":"Point"}
}