{
  "type": "Feature",
  "properties": {
    "iso:country":"US",
    "sg:address":"250 Alamaha St",
    "sg:city":"Kahului",
    "sg:classifiers":[
        {
            "category":"Personal",
            "subcategory":"Beauty Salon",
            "type":"Services"
        }
    ],
    "sg:phone":"+1 808 871 5644",
    "sg:postcode":"96732",
    "sg:province":"HI",
    "sg:tags":[
        "shop"
    ],
    "wof:name":"Maximillians",
    "wof:placetype":"venue"
},
  "geometry": {"coordinates":[-156.45973499999999,20.887432],"type":"Point"}
}