{
  "type": "Feature",
  "properties": {
    "iso:country":"US",
    "sg:address":"3465 Wela St",
    "sg:city":"Honolulu",
    "sg:classifiers":[
        {
            "category":"Real Estate",
            "subcategory":"Real Estate Agent",
            "type":"Services"
        }
    ],
    "sg:phone":"+1 808 737 1839",
    "sg:postcode":"96815",
    "sg:province":"HI",
    "wof:name":"Betawest Inc",
    "wof:placetype":"venue"
},
  "geometry": {"coordinates":[-157.80616900000001,21.272099],"type":"Point"}
}