{
  "type": "Feature",
  "properties": {
    "iso:country":"US",
    "sg:address":"3125 Akahi St",
    "sg:city":"Lihue",
    "sg:classifiers":[
        {
            "category":"Banks & Credit Unions",
            "subcategory":"Bank",
            "type":"Services"
        }
    ],
    "sg:phone":"+1 808 245 8888",
    "sg:postcode":"96766",
    "sg:province":"HI",
    "sg:tags":[
        "loan",
        "real estate"
    ],
    "sg:website":"www.hawaii-mortgages.com",
    "wof:name":"Millennium Mortgage",
    "wof:placetype":"venue"
},
  "geometry": {"coordinates":[-159.367368,21.97832],"type":"Point"}
}