{
  "type": "Feature",
  "properties": {
    "iso:country":"US",
    "sg:address":"4160 Lower Kula Rd",
    "sg:city":"Kula",
    "sg:classifiers":[
        {
            "category":"Social Services",
            "subcategory":"Child Care",
            "type":"Services"
        }
    ],
    "sg:phone":"+1 808 878 2511",
    "sg:postcode":"96790",
    "sg:province":"HI",
    "sg:tags":[
        "elementary",
        "school",
        "preschool"
    ],
    "sg:website":"www.waldorfmaui.com",
    "wof:name":"Haleakala Waldorf School",
    "wof:placetype":"venue"
},
  "geometry": {"coordinates":[-156.326043,20.765461],"type":"Point"}
}