{
  "type": "Feature",
  "properties": {
    "addr:full":"510 Kamehameha Hwy Laie HI 96762",
    "addr:housenumber":"510",
    "addr:postcode":"96762",
    "addr:street":"Kamehameha Hwy",
    "iso:country":"US",
    "sg:address":"510 Kamehameha Hwy",
    "sg:city":"Laie",
    "sg:classifiers":[
        {
            "category":"Personal",
            "subcategory":"Beauty Salon",
            "type":"Services"
        }
    ],
    "sg:phone":"+1 808 293 8868",
    "sg:postcode":"96762",
    "sg:province":"HI",
    "sg:tags":[
        "manicuring"
    ],
    "wof:name":"Amber Nails",
    "wof:placetype":"venue"
},
  "geometry": {"coordinates":[-157.92125100000001,21.647042],"type":"Point"}
}