{
  "type": "Feature",
  "properties": {
    "addr:full":"625 Kapahulu Ave Honolulu HI 96815",
    "addr:housenumber":"625",
    "addr:postcode":"96815",
    "addr:street":"Kapahulu Ave",
    "iso:country":"US",
    "sg:address":"625 Kapahulu Ave",
    "sg:city":"Honolulu",
    "sg:classifiers":[
        {
            "category":"Coffee & Tea",
            "type":"Food & Drink"
        }
    ],
    "sg:menulink":"http://www.allmenus.com/hi/honolulu/108562-starbucks-coffee/menu/",
    "sg:phone":"+1 808 734 4116",
    "sg:postcode":"96815",
    "sg:province":"HI",
    "sg:tags":[
        "american"
    ],
    "wof:name":"Starbucks Coffee",
    "wof:placetype":"venue"
},
  "geometry": {"coordinates":[-157.813627,21.278854],"type":"Point"}
}