{
  "type": "Feature",
  "properties": {
    "iso:country":"US",
    "sg:address":"221 Makaala St",
    "sg:city":"Hilo",
    "sg:classifiers":[
        {
            "category":"Manufacturing",
            "subcategory":"Printing",
            "type":"Manufacturing & Wholesale Goods"
        }
    ],
    "sg:phone":"+1 808 961 2697",
    "sg:postcode":"96720",
    "sg:province":"HI",
    "sg:tags":[
        "commercial",
        "lithographic"
    ],
    "wof:name":"Big Island Printers",
    "wof:placetype":"venue"
},
  "geometry": {"coordinates":[-155.067598,19.701674],"type":"Point"}
}