{
  "type": "Feature",
  "properties": {
    "iso:country":"US",
    "sg:address":"2061 Kolo Pl",
    "sg:city":"Wailuku",
    "sg:classifiers":[
        {
            "category":"Professional",
            "type":"Services"
        }
    ],
    "sg:phone":"+1 808 244 1813",
    "sg:postcode":"96793",
    "sg:province":"HI",
    "sg:tags":[
        "establishment"
    ],
    "wof:name":"Maui Island Productions",
    "wof:placetype":"venue"
},
  "geometry": {"coordinates":[-156.50711999999999,20.884242],"type":"Point"}
}