{
  "type": "Feature",
  "properties": {
    "iso:country":"US",
    "sg:address":"638 11th Ave",
    "sg:city":"Honolulu",
    "sg:classifiers":[
        {
            "category":"Building & Trades",
            "subcategory":"Landscaping Services",
            "type":"Services"
        }
    ],
    "sg:phone":"+1 808 732 3202",
    "sg:postcode":"96816",
    "sg:province":"HI",
    "sg:tags":[
        "landscape",
        "maintenance"
    ],
    "wof:name":"Csl-Dbe Inc",
    "wof:placetype":"venue"
},
  "geometry": {"coordinates":[-157.80494100000001,21.274791],"type":"Point"}
}