{
  "type": "Feature",
  "properties": {
    "iso:country":"US",
    "sg:address":"764 Makawao Ave",
    "sg:city":"Makawao",
    "sg:classifiers":[
        {
            "category":"Manufacturing",
            "subcategory":"Glass & Minerals",
            "type":"Manufacturing & Wholesale Goods"
        }
    ],
    "sg:phone":"+1 808 573 8981",
    "sg:postcode":"96768",
    "sg:province":"HI",
    "sg:tags":[
        "product",
        "nonmetallic",
        "mfg"
    ],
    "wof:name":"Hawaiian Fantasy",
    "wof:placetype":"venue"
},
  "geometry": {"coordinates":[-156.31927400000001,20.846166],"type":"Point"}
}