{
  "type": "Feature",
  "properties": {
    "iso:country":"US",
    "sg:address":"6480 Puupilo Rd",
    "sg:city":"Kapaa",
    "sg:classifiers":[
        {
            "category":"Shopping",
            "subcategory":"Bicycles & Sporting Goods",
            "type":"Retail Goods"
        }
    ],
    "sg:phone":"+1 808 822 3649",
    "sg:postcode":"96746",
    "sg:province":"HI",
    "wof:name":"Thomas Guns",
    "wof:placetype":"venue"
},
  "geometry": {"coordinates":[-159.38119599999999,22.062764],"type":"Point"}
}