{
  "type": "Feature",
  "properties": {
    "iso:country":"US",
    "sg:address":"3033 Ala Ilima St",
    "sg:city":"Honolulu",
    "sg:classifiers":[
        {
            "category":"Wholesale",
            "subcategory":"Apparel",
            "type":"Manufacturing & Wholesale Goods"
        }
    ],
    "sg:phone":"+1 808 845 0817",
    "sg:postcode":"96818",
    "sg:province":"HI",
    "sg:tags":[
        "clothing"
    ],
    "wof:name":"Jealousie Lingerie Boutique",
    "wof:placetype":"venue"
},
  "geometry": {"coordinates":[-157.90774500000001,21.345132],"type":"Point"}
}