{
  "type": "Feature",
  "properties": {
    "iso:country":"US",
    "sg:address":"1011 California Ave",
    "sg:city":"Wahiawa",
    "sg:classifiers":[
        {
            "category":"Retail",
            "subcategory":"Auto Repair",
            "type":"Services"
        }
    ],
    "sg:phone":"+1 808 622 1678",
    "sg:postcode":"96786",
    "sg:province":"HI",
    "sg:tags":[
        "station",
        "gasoline",
        "general"
    ],
    "wof:name":"Chevron",
    "wof:placetype":"venue"
},
  "geometry": {"coordinates":[-158.02348699999999,21.498391],"type":"Point"}
}