{
  "type": "Feature",
  "properties": {
    "iso:country":"US",
    "sg:address":"1001 Bishop St",
    "sg:city":"Honolulu",
    "sg:classifiers":[
        {
            "category":"Building & Trades",
            "subcategory":"Electrical",
            "type":"Services"
        },
        {
            "category":"Wholesale",
            "subcategory":"Electrical",
            "type":"Manufacturing & Wholesale Goods"
        }
    ],
    "sg:phone":"+1 808 523 1524",
    "sg:postcode":"96813",
    "sg:province":"HI",
    "sg:tags":[
        "equipment",
        "contractor",
        "electric",
        "supply"
    ],
    "wof:name":"Hawaii's Electrical Export Co",
    "wof:placetype":"venue"
},
  "geometry": {"coordinates":[-157.86039400000001,21.30931],"type":"Point"}
}