{
  "type": "Feature",
  "properties": {
    "iso:country":"US",
    "sg:address":"262 Olai St",
    "sg:city":"Kapolei",
    "sg:classifiers":[
        {
            "category":"Home & Garden",
            "subcategory":"Garden Supply",
            "type":"Retail Goods"
        }
    ],
    "sg:phone":"+1 808 682 5113",
    "sg:postcode":"96707",
    "sg:province":"HI",
    "sg:tags":[
        "fertilizer",
        "agricultural",
        "chemical",
        "related"
    ],
    "wof:name":"Pacific AG Sls & Svcs",
    "wof:placetype":"venue"
},
  "geometry": {"coordinates":[-158.09756200000001,21.299599],"type":"Point"}
}