{
  "type": "Feature",
  "properties": {
    "iso:country":"US",
    "sg:address":"275 Waikoloa Beach Dr",
    "sg:city":"Waikoloa",
    "sg:classifiers":[
        {
            "category":"Shopping",
            "subcategory":"Gifts & Souvenirs",
            "type":"Retail Goods"
        }
    ],
    "sg:phone":"+1 808 886 5017",
    "sg:postcode":"96738",
    "sg:province":"HI",
    "sg:tags":[
        "shop"
    ],
    "wof:name":"Lamonts Gift & Sundry Shops",
    "wof:placetype":"venue"
},
  "geometry": {"coordinates":[-155.88396,19.925515],"type":"Point"}
}