{
  "type": "Feature",
  "properties": {
    "iso:country":"US",
    "sg:address":"1316 Kaumualii St",
    "sg:city":"Honolulu",
    "sg:classifiers":[
        {
            "category":"Retail",
            "subcategory":"Auto Repair",
            "type":"Services"
        }
    ],
    "sg:phone":"+1 808 847 6888",
    "sg:postcode":"96817",
    "sg:province":"HI",
    "sg:tags":[
        "automotive"
    ],
    "wof:name":"Fujikami Auto Air Conditioning",
    "wof:placetype":"venue"
},
  "geometry": {"coordinates":[-157.874742,21.324744],"type":"Point"}
}