{
  "type": "Feature",
  "properties": {
    "iso:country":"US",
    "sg:address":"601 Kaulana St",
    "sg:city":"Kahului",
    "sg:classifiers":[
        {
            "category":"Retail",
            "subcategory":"Portrait Studio",
            "type":"Services"
        }
    ],
    "sg:phone":"+1 808 667 6783",
    "sg:postcode":"96732",
    "sg:province":"HI",
    "sg:tags":[
        "photographer"
    ],
    "sg:website":"www.bluephoto.com",
    "wof:name":"Richard Blue Photography",
    "wof:placetype":"venue"
},
  "geometry": {"coordinates":[-156.4787,20.8752],"type":"Point"}
}