{
  "type": "Feature",
  "properties": {
    "addr:full":"1021 Pueo St Honolulu HI 96816",
    "addr:housenumber":"1021",
    "addr:postcode":"96816",
    "addr:street":"Pueo St",
    "iso:country":"US",
    "sg:address":"1021 Pueo St",
    "sg:city":"Honolulu",
    "sg:classifiers":[
        {
            "category":"Arts & Performance",
            "subcategory":"Theater",
            "type":"Entertainment"
        }
    ],
    "sg:phone":"+1 808 735 2088",
    "sg:postcode":"96816",
    "sg:province":"HI",
    "sg:tags":[
        "theatrical"
    ],
    "wof:name":"KIKA Inc",
    "wof:placetype":"venue"
},
  "geometry": {"coordinates":[-157.782949,21.270646],"type":"Point"}
}