{
  "type": "Feature",
  "properties": {
    "iso:country":"US",
    "sg:address":"2005 Kalia Rd",
    "sg:city":"Honolulu",
    "sg:classifiers":[
        {
            "category":"Organizations",
            "subcategory":"Religious Organization",
            "type":"Services"
        }
    ],
    "sg:phone":"+1 808 952 6688",
    "sg:postcode":"96815",
    "sg:province":"HI",
    "sg:tags":[
        "meditation"
    ],
    "wof:name":"Crystal Collection",
    "wof:placetype":"venue"
},
  "geometry": {"coordinates":[-157.834935,21.282814],"type":"Point"}
}