{
  "type": "Feature",
  "properties": {
    "addr:full":"629 Kailua Rd Kailua HI 96734",
    "addr:housenumber":"629",
    "addr:postcode":"96734",
    "addr:street":"Kailua Rd",
    "iso:country":"US",
    "sg:address":"629 Kailua Rd",
    "sg:city":"Kailua",
    "sg:classifiers":[
        {
            "category":"Real Estate",
            "subcategory":"Real Estate Agent",
            "type":"Services"
        }
    ],
    "sg:phone":"+1 808 261 3314",
    "sg:postcode":"96734",
    "sg:province":"HI",
    "sg:tags":[
        "firm",
        "brokerage"
    ],
    "sg:website":"www.cbpacific.com",
    "wof:name":"Coldwell Banker",
    "wof:placetype":"venue"
},
  "geometry": {"coordinates":[-157.741761,21.393841],"type":"Point"}
}