{
  "type": "Feature",
  "properties": {
    "addr:full":"21 Pier Honolulu HI 96819",
    "addr:housenumber":"21",
    "addr:postcode":"96819",
    "addr:street":"Pier",
    "iso:country":"US",
    "sg:address":"21 Pier",
    "sg:city":"Honolulu",
    "sg:classifiers":[
        {
            "category":"Marine",
            "type":"Transportation"
        }
    ],
    "sg:phone":"+1 808 543 9325",
    "sg:postcode":"96819",
    "sg:province":"HI",
    "sg:tags":[
        "towing"
    ],
    "wof:name":"Hawaiian Tug & Barge",
    "wof:placetype":"venue"
},
  "geometry": {"coordinates":[-157.88833700000001,21.315067],"type":"Point"}
}