{
  "type": "Feature",
  "properties": {
    "addr:full":"3950 Kalai Waa St Kihei HI 96753",
    "addr:housenumber":"3950",
    "addr:postcode":"96753",
    "addr:street":"Kalai Waa St",
    "iso:country":"US",
    "sg:address":"3950 Kalai Waa St",
    "sg:city":"Kihei",
    "sg:classifiers":[
        {
            "category":"Recreation",
            "type":"Entertainment"
        }
    ],
    "sg:phone":"+1 808 244 0009",
    "sg:postcode":"96753",
    "sg:province":"HI",
    "sg:tags":[
        "charter",
        "boat"
    ],
    "wof:name":"Fairytale Charters",
    "wof:placetype":"venue"
},
  "geometry": {"coordinates":[-156.432154,20.685602],"type":"Point"}
}