{
  "type": "Feature",
  "properties": {
    "addr:full":"4562 Kukui St Kapaa HI 96746",
    "addr:postcode":"4562;96746",
    "addr:street":"Kukui St",
    "iso:country":"US",
    "sg:address":"4562 Kukui St",
    "sg:city":"Kapaa",
    "sg:classifiers":[
        {
            "category":"Health Services",
            "subcategory":"Doctor",
            "type":"Services"
        }
    ],
    "sg:phone":"+1 808 822 4906",
    "sg:postcode":"96746",
    "sg:province":"HI",
    "sg:tags":[
        "dentist"
    ],
    "wof:name":"Garden Island Ctr-Aesthetic",
    "wof:placetype":"venue"
},
  "geometry": {"coordinates":[-159.31987699999999,22.075914],"type":"Point"}
}