{
  "type": "Feature",
  "properties": {
    "iso:country":"US",
    "sg:address":"941 Lolena St",
    "sg:city":"Honolulu",
    "sg:classifiers":[
        {
            "category":"Professional",
            "subcategory":"Business Services",
            "type":"Services"
        }
    ],
    "sg:phone":"+1 808 595 6793",
    "sg:postcode":"96817",
    "sg:province":"HI",
    "wof:name":"Theodore Su Chong",
    "wof:placetype":"venue"
},
  "geometry": {"coordinates":[-157.85711699999999,21.329653],"type":"Point"}
}