{
  "type": "Feature",
  "properties": {
    "iso:country":"US",
    "sg:address":"714 Kanoelehua Ave",
    "sg:city":"Hilo",
    "sg:classifiers":[
        {
            "category":"Professional",
            "subcategory":"Business Services",
            "type":"Services"
        }
    ],
    "sg:phone":"+1 808 934 7321",
    "sg:postcode":"96720",
    "sg:province":"HI",
    "sg:tags":[
        "lettering",
        "painting",
        "sign"
    ],
    "wof:name":"Hpc Signs",
    "wof:placetype":"venue"
},
  "geometry": {"coordinates":[-155.06439499999999,19.709095],"type":"Point"}
}