{
  "type": "Feature",
  "properties": {
    "iso:country":"US",
    "sg:address":"1035 Mikole St",
    "sg:city":"Honolulu",
    "sg:classifiers":[
        {
            "category":"Building & Trades",
            "subcategory":"Construction",
            "type":"Services"
        }
    ],
    "sg:phone":"+1 808 841 3446",
    "sg:postcode":"96819",
    "sg:province":"HI",
    "sg:tags":[
        "general",
        "commercial",
        "contractor"
    ],
    "wof:name":"Mitsunaga Construction Inc",
    "wof:placetype":"venue"
},
  "geometry": {"coordinates":[-157.872218,21.303235],"type":"Point"}
}