{
  "type": "Feature",
  "properties": {
    "addr:full":"365 Hanakai St Kahului HI 96732",
    "addr:housenumber":"365",
    "addr:postcode":"96732",
    "addr:street":"Hanakai St",
    "iso:country":"US",
    "sg:address":"365 Hanakai St",
    "sg:city":"Kahului",
    "sg:classifiers":[
        {
            "category":"Manufacturing",
            "subcategory":"Metals",
            "type":"Manufacturing & Wholesale Goods"
        }
    ],
    "sg:phone":"+1 808 877 0056",
    "sg:postcode":"96732",
    "sg:province":"HI",
    "sg:tags":[
        "coating"
    ],
    "wof:name":"Gaspro",
    "wof:placetype":"venue"
},
  "geometry": {"coordinates":[-156.456999,20.88657],"type":"Point"}
}