{
  "type": "Feature",
  "properties": {
    "addr:full":"6491 Ono Rd Kailua Kona HI 96740",
    "addr:housenumber":"6491",
    "addr:postcode":"96740",
    "addr:street":"Ono Rd",
    "iso:country":"US",
    "sg:address":"6491 Ono Rd",
    "sg:city":"Kailua Kona",
    "sg:classifiers":[
        {
            "category":"Farming",
            "subcategory":"Fish & Marine Products",
            "type":"Manufacturing & Wholesale Goods"
        }
    ],
    "sg:phone":"+1 808 329 6125",
    "sg:postcode":"96740",
    "sg:province":"HI",
    "sg:tags":[
        "fishing"
    ],
    "wof:name":"H & M Marine Inc",
    "wof:placetype":"venue"
},
  "geometry": {"coordinates":[-155.956909,19.60425],"type":"Point"}
}