{
  "type": "Feature",
  "properties": {
    "iso:country":"US",
    "sg:address":"700 Bishop St",
    "sg:city":"Honolulu",
    "sg:classifiers":[
        {
            "category":"Banks & Credit Unions",
            "subcategory":"Investment Brokerage",
            "type":"Services"
        }
    ],
    "sg:phone":"+1 808 000 1111",
    "sg:postcode":"96813",
    "sg:province":"HI",
    "sg:tags":[
        "stock",
        "bond"
    ],
    "wof:name":"Charles Schwab & Co",
    "wof:placetype":"venue"
},
  "geometry": {"coordinates":[-157.86358000000001,21.307052],"type":"Point"}
}