{
  "type": "Feature",
  "properties": {
    "addr:full":"65 N Beretania St Honolulu HI 96817",
    "addr:housenumber":"65",
    "addr:postcode":"96817",
    "addr:street":"N Beretania St",
    "iso:country":"US",
    "sg:address":"65 N Beretania St",
    "sg:city":"Honolulu",
    "sg:classifiers":[
        {
            "category":"Shopping",
            "subcategory":"Florist",
            "type":"Retail Goods"
        }
    ],
    "sg:phone":"+1 808 521 1595",
    "sg:postcode":"96817",
    "sg:province":"HI",
    "wof:name":"Jenny's Lei Shop",
    "wof:placetype":"venue"
},
  "geometry": {"coordinates":[-157.86109099999999,21.313111],"type":"Point"}
}