{
  "type": "Feature",
  "properties": {
    "iso:country":"US",
    "sg:address":"680 Farrington Hwy",
    "sg:city":"Waipahu",
    "sg:classifiers":[
        {
            "category":"Manufacturing",
            "subcategory":"Printing",
            "type":"Manufacturing & Wholesale Goods"
        }
    ],
    "sg:phone":"+1 808 677 5228",
    "sg:postcode":"96797",
    "sg:province":"HI",
    "sg:tags":[
        "commercial",
        "lithographic"
    ],
    "wof:name":"Waipahu Print Shop",
    "wof:placetype":"venue"
},
  "geometry": {"coordinates":[-158.009253,21.383179],"type":"Point"}
}