{
  "type": "Feature",
  "properties": {
    "iso:country":"US",
    "sg:address":"230 Mikiola Dr",
    "sg:city":"Kaneohe",
    "sg:classifiers":[
        {
            "category":"Building & Trades",
            "subcategory":"Cleaning & Sanitation",
            "type":"Services"
        }
    ],
    "sg:phone":"+1 808 286 7063",
    "sg:postcode":"96744",
    "sg:province":"HI",
    "sg:tags":[
        "maintenance"
    ],
    "wof:name":"Marine Diesel Cleaning Svc",
    "wof:placetype":"venue"
},
  "geometry": {"coordinates":[-157.775316,21.412292],"type":"Point"}
}