{
  "type": "Feature",
  "properties": {
    "addr:full":"5596 Pawai Pl Kailua Kona HI 96740",
    "addr:housenumber":"5596",
    "addr:postcode":"96740",
    "addr:street":"Pawai Pl",
    "iso:country":"US",
    "sg:address":"5596 Pawai Pl",
    "sg:city":"Kailua Kona",
    "sg:classifiers":[
        {
            "category":"Home & Garden",
            "subcategory":"Home Furnishings",
            "type":"Retail Goods"
        }
    ],
    "sg:phone":"+1 808 326 1658",
    "sg:postcode":"96740",
    "sg:province":"HI",
    "sg:tags":[
        "venetian",
        "blind"
    ],
    "wof:name":"Interior Services",
    "wof:placetype":"venue"
},
  "geometry": {"coordinates":[-155.999334,19.643608],"type":"Point"}
}