{
  "type": "Feature",
  "properties": {
    "iso:country":"US",
    "sg:address":"745 Keeaumoku St",
    "sg:city":"Honolulu",
    "sg:classifiers":[
        {
            "category":"Wholesale",
            "subcategory":"Jewelry",
            "type":"Manufacturing & Wholesale Goods"
        }
    ],
    "sg:phone":"+1 808 945 7001",
    "sg:postcode":"96814",
    "sg:province":"HI",
    "wof:name":"J E S Jewelry",
    "wof:placetype":"venue"
},
  "geometry": {"coordinates":[-157.841174,21.296022],"type":"Point"}
}