{
  "type": "Feature",
  "properties": {
    "iso:country":"US",
    "sg:address":"150 Hana Hwy",
    "sg:city":"Kahului",
    "sg:classifiers":[
        {
            "category":"Retail",
            "subcategory":"Repair Shop",
            "type":"Services"
        },
        {
            "category":"Wholesale",
            "subcategory":"Metals & Minerals",
            "type":"Manufacturing & Wholesale Goods"
        }
    ],
    "sg:phone":"+1 808 871 4099",
    "sg:postcode":"96732",
    "sg:province":"HI",
    "sg:tags":[
        "center",
        "welding"
    ],
    "wof:name":"No 9 Welding & Metal Sales",
    "wof:placetype":"venue"
},
  "geometry": {"coordinates":[-156.460005,20.890105],"type":"Point"}
}