{
  "type": "Feature",
  "properties": {
    "iso:country":"US",
    "sg:address":"2062 S King St",
    "sg:city":"Honolulu",
    "sg:classifiers":[
        {
            "category":"Social Services",
            "subcategory":"Child Care",
            "type":"Services"
        }
    ],
    "sg:phone":"+1 808 944 2625",
    "sg:postcode":"96826",
    "sg:province":"HI",
    "sg:tags":[
        "kindergarten",
        "academic",
        "school"
    ],
    "wof:name":"Angels At Play Preschool",
    "wof:placetype":"venue"
},
  "geometry": {"coordinates":[-157.82816099999999,21.294256],"type":"Point"}
}