{
  "type": "Feature",
  "properties": {
    "iso:country":"US",
    "sg:address":"2406 Kalihi St",
    "sg:city":"Honolulu",
    "sg:classifiers":[
        {
            "category":"Food & Beverages",
            "subcategory":"Groceries & Convenience Stores",
            "type":"Retail Goods"
        }
    ],
    "sg:phone":"+1 808 848 5513",
    "sg:postcode":"96819",
    "sg:province":"HI",
    "wof:name":"J and J Market and Kitchenette",
    "wof:placetype":"venue"
},
  "geometry": {"coordinates":[-157.862022,21.345702],"type":"Point"}
}