{
  "type": "Feature",
  "properties": {
    "iso:country":"US",
    "sg:address":"1100 Alakea St",
    "sg:city":"Honolulu",
    "sg:classifiers":[
        {
            "category":"Utilities",
            "subcategory":"Mobile Phone",
            "type":"Services"
        }
    ],
    "sg:phone":"+1 808 522 1470",
    "sg:postcode":"96813",
    "sg:province":"HI",
    "sg:tags":[
        "telephone",
        "cellular"
    ],
    "wof:name":"T-Mobile",
    "wof:placetype":"venue"
},
  "geometry": {"coordinates":[-157.85816299999999,21.309891],"type":"Point"}
}