{
  "type": "Feature",
  "properties": {
    "addr:full":"1258 Young St Honolulu HI 96814",
    "addr:housenumber":"1258",
    "addr:postcode":"96814",
    "addr:street":"Young St",
    "iso:country":"US",
    "sg:address":"1258 Young St",
    "sg:city":"Honolulu",
    "sg:classifiers":[
        {
            "category":"Retail",
            "subcategory":"Repair Shop",
            "type":"Services"
        }
    ],
    "sg:phone":"+1 808 591 2412",
    "sg:postcode":"96814",
    "sg:province":"HI",
    "wof:name":"Pacific Gallery & Frames",
    "wof:placetype":"venue"
},
  "geometry": {"coordinates":[-157.84236999999999,21.300237],"type":"Point"}
}