{
  "type": "Feature",
  "properties": {
    "iso:country":"US",
    "sg:address":"1714 Kapiolani Blvd",
    "sg:city":"Honolulu",
    "sg:classifiers":[
        {
            "category":"Shopping",
            "subcategory":"Clothing, Apparel, & Fashions",
            "type":"Retail Goods"
        }
    ],
    "sg:phone":"+1 808 951 7877",
    "sg:postcode":"96814",
    "sg:province":"HI",
    "sg:tags":[
        "sportswear"
    ],
    "wof:name":"Russ K",
    "wof:placetype":"venue"
},
  "geometry": {"coordinates":[-157.83969400000001,21.291976],"type":"Point"}
}