{
  "type": "Feature",
  "properties": {
    "iso:country":"US",
    "sg:address":"910 Honoapiilani Hwy",
    "sg:city":"Lahaina",
    "sg:classifiers":[
        {
            "category":"Wholesale",
            "subcategory":"Toys & Hobbies",
            "type":"Manufacturing & Wholesale Goods"
        }
    ],
    "sg:phone":"+1 808 667 6229",
    "sg:postcode":"96761",
    "sg:province":"HI",
    "sg:tags":[
        "wholesaler"
    ],
    "wof:name":"Paradise Wholesale",
    "wof:placetype":"venue"
},
  "geometry": {"coordinates":[-156.682331,20.883375],"type":"Point"}
}