{
  "type": "Feature",
  "properties": {
    "iso:country":"US",
    "sg:address":"23 Aina Moi Pl",
    "sg:city":"Kaneohe",
    "sg:classifiers":[
        {
            "category":"Real Estate",
            "subcategory":"Surveying",
            "type":"Services"
        }
    ],
    "sg:phone":"+1 808 247 6621",
    "sg:postcode":"96744",
    "sg:province":"HI",
    "sg:tags":[
        "business"
    ],
    "wof:name":"Technical Field Data Service",
    "wof:placetype":"venue"
},
  "geometry": {"coordinates":[-157.763712,21.424252],"type":"Point"}
}