{
  "type": "Feature",
  "properties": {
    "iso:country":"US",
    "sg:address":"8902 Kalanianaole Hwy",
    "sg:city":"Honolulu",
    "sg:classifiers":[
        {
            "category":"Sports & Exercise",
            "subcategory":"Golf",
            "type":"Entertainment"
        }
    ],
    "sg:phone":"+1 808 395 2358",
    "sg:postcode":"96825",
    "sg:province":"HI",
    "sg:tags":[
        "club",
        "course",
        "membership",
        "public"
    ],
    "wof:name":"Hawaii Kai Golf Course",
    "wof:placetype":"venue"
},
  "geometry": {"coordinates":[-157.663534,21.291493],"type":"Point"}
}