{
  "type": "Feature",
  "properties": {
    "iso:country":"US",
    "sg:address":"567 Kanoelehua Ave",
    "sg:city":"Hilo",
    "sg:classifiers":[
        {
            "category":"Building & Trades",
            "subcategory":"Electrical",
            "type":"Services"
        }
    ],
    "sg:phone":"+1 808 961 3759",
    "sg:postcode":"96720",
    "sg:province":"HI",
    "sg:tags":[
        "electrical",
        "contractor"
    ],
    "wof:name":"Able Electric Inc",
    "wof:placetype":"venue"
},
  "geometry": {"coordinates":[-155.064235,19.71251],"type":"Point"}
}