{
  "type": "Feature",
  "properties": {
    "iso:country":"US",
    "sg:address":"44 Waonahele Pl",
    "sg:city":"Haiku",
    "sg:classifiers":[
        {
            "category":"Farming",
            "subcategory":"Aquatic Farm",
            "type":"Manufacturing & Wholesale Goods"
        }
    ],
    "sg:phone":"+1 808 573 1585",
    "sg:postcode":"96708",
    "sg:province":"HI",
    "sg:tags":[
        "fish",
        "aquaculture",
        "animal"
    ],
    "wof:name":"Brooks Fresh Water Fish Inc",
    "wof:placetype":"venue"
},
  "geometry": {"coordinates":[-156.27024599999999,20.908802],"type":"Point"}
}