{
  "type": "Feature",
  "properties": {
    "iso:country":"US",
    "sg:address":"1916 Young St",
    "sg:city":"Honolulu",
    "sg:classifiers":[
        {
            "category":"Professional",
            "subcategory":"Management & Consulting",
            "type":"Services"
        }
    ],
    "sg:phone":"+1 808 356 0552",
    "sg:postcode":"96826",
    "sg:province":"HI",
    "sg:tags":[
        "consultant",
        "energy",
        "conservation"
    ],
    "wof:name":"Sustainable Resources Group",
    "wof:placetype":"venue"
},
  "geometry": {"coordinates":[-157.83007799999999,21.295898],"type":"Point"}
}