{
  "type": "Feature",
  "properties": {
    "iso:country":"US",
    "sg:address":"195 Ke Nui Rd",
    "sg:city":"Haleiwa",
    "sg:classifiers":[
        {
            "category":"Real Estate",
            "subcategory":"Architect",
            "type":"Services"
        }
    ],
    "sg:phone":"+1 808 638 7983",
    "sg:postcode":"96712",
    "sg:province":"HI",
    "sg:tags":[
        "architectural"
    ],
    "wof:name":"Douglas M Ackerman AIA",
    "wof:placetype":"venue"
},
  "geometry": {"coordinates":[-158.04392999999999,21.67083],"type":"Point"}
}