{
  "type": "Feature",
  "properties": {
    "iso:country":"US",
    "sg:address":"68 N Kaniku Dr",
    "sg:city":"Kamuela",
    "sg:classifiers":[
        {
            "category":"Professional",
            "type":"Services"
        }
    ],
    "sg:phone":"+1 808 885 1558",
    "sg:postcode":"96743",
    "sg:province":"HI",
    "sg:tags":[
        "establishment"
    ],
    "wof:name":"Maryl Group",
    "wof:placetype":"venue"
},
  "geometry": {"coordinates":[-155.85681400000001,19.951237],"type":"Point"}
}