{
  "type": "Feature",
  "properties": {
    "iso:country":"US",
    "sg:address":"1127 Ahikawa St",
    "sg:city":"Kailua Kona",
    "sg:classifiers":[
        {
            "category":"Building & Trades",
            "subcategory":"Construction",
            "type":"Services"
        }
    ],
    "sg:phone":"+1 808 325 5122",
    "sg:postcode":"96740",
    "sg:province":"HI",
    "sg:tags":[
        "house"
    ],
    "wof:name":"American Dream Inc",
    "wof:placetype":"venue"
},
  "geometry": {"coordinates":[-155.988597,19.722749],"type":"Point"}
}