{
  "type": "Feature",
  "properties": {
    "iso:country":"US",
    "sg:address":"1829 Palolo Ave",
    "sg:city":"Honolulu",
    "sg:classifiers":[
        {
            "category":"Food & Beverages",
            "subcategory":"Groceries & Convenience Stores",
            "type":"Retail Goods"
        }
    ],
    "sg:phone":"+1 808 735 7955",
    "sg:postcode":"96816",
    "sg:province":"HI",
    "sg:tags":[
        "grocer"
    ],
    "wof:name":"Keo's Sundry Store",
    "wof:placetype":"venue"
},
  "geometry": {"coordinates":[-157.799172,21.295515],"type":"Point"}
}