{
  "type": "Feature",
  "properties": {
    "addr:full":"2801 Lai Rd Honolulu HI 96816",
    "addr:housenumber":"2801",
    "addr:postcode":"96816",
    "addr:street":"Lai Rd",
    "iso:country":"US",
    "sg:address":"2801 Lai Rd",
    "sg:city":"Honolulu",
    "sg:classifiers":[
        {
            "category":"Personal",
            "subcategory":"Beauty Salon",
            "type":"Services"
        }
    ],
    "sg:phone":"+1 808 739 1779",
    "sg:postcode":"96816",
    "sg:province":"HI",
    "sg:tags":[
        "shop"
    ],
    "wof:name":"Adele C Tamashiro",
    "wof:placetype":"venue"
},
  "geometry": {"coordinates":[-157.78675000000001,21.308509],"type":"Point"}
}