{
  "type": "Feature",
  "properties": {
    "addr:full":"2719 au St Pahoa HI 96778",
    "addr:housenumber":"2719",
    "addr:postcode":"96778",
    "addr:street":"Au St",
    "iso:country":"US",
    "sg:address":"2719 au St",
    "sg:city":"Pahoa",
    "sg:classifiers":[
        {
            "category":"Home & Garden",
            "subcategory":"Building Materials",
            "type":"Retail Goods"
        }
    ],
    "sg:phone":"+1 808 965 7370",
    "sg:postcode":"96778",
    "sg:province":"HI",
    "wof:name":"Steel Hale Enterprises LLC",
    "wof:placetype":"venue"
},
  "geometry": {"coordinates":[-154.91994600000001,19.531456],"type":"Point"}
}