{
  "type": "Feature",
  "properties": {
    "addr:full":"5135 Laipo Rd Kapaa HI 96746",
    "addr:housenumber":"5135",
    "addr:postcode":"96746",
    "addr:street":"Laipo Rd",
    "iso:country":"US",
    "sg:address":"5135 Laipo Rd",
    "sg:city":"Kapaa",
    "sg:classifiers":[
        {
            "category":"Building & Trades",
            "subcategory":"Construction",
            "type":"Services"
        }
    ],
    "sg:phone":"+1 808 823 6412",
    "sg:postcode":"96746",
    "sg:province":"HI",
    "sg:tags":[
        "tile",
        "dealer"
    ],
    "wof:name":"Cudworth Tile",
    "wof:placetype":"venue"
},
  "geometry": {"coordinates":[-159.324918,22.091002],"type":"Point"}
}