{
  "type": "Feature",
  "properties": {
    "iso:country":"US",
    "sg:address":"653 Kamehameha Hwy",
    "sg:city":"Laie",
    "sg:classifiers":[
        {
            "category":"Retail",
            "subcategory":"Laundry & Dry Cleaning",
            "type":"Services"
        }
    ],
    "sg:phone":"+1 808 293 5100",
    "sg:postcode":"96762",
    "sg:province":"HI",
    "sg:tags":[
        "drycleaning",
        "plant"
    ],
    "wof:name":"Fantastique",
    "wof:placetype":"venue"
},
  "geometry": {"coordinates":[-157.92943,21.65345],"type":"Point"}
}