{
  "type": "Feature",
  "properties": {
    "iso:country":"US",
    "sg:address":"7541 Puumahoe Pl",
    "sg:city":"Honolulu",
    "sg:classifiers":[
        {
            "category":"Arts & Performance",
            "subcategory":"Theater",
            "type":"Entertainment"
        }
    ],
    "sg:phone":"+1 808 395 1185",
    "sg:postcode":"96825",
    "sg:province":"HI",
    "sg:tags":[
        "group",
        "business"
    ],
    "wof:name":"Su Hui Huang",
    "wof:placetype":"venue"
},
  "geometry": {"coordinates":[-157.67337599999999,21.30341],"type":"Point"}
}