{
  "type": "Feature",
  "properties": {
    "addr:full":"5001 Haleilio Rd Kapaa HI 96746",
    "addr:housenumber":"5001",
    "addr:postcode":"96746",
    "addr:street":"Haleilio Rd",
    "iso:country":"US",
    "sg:address":"5001 Haleilio Rd",
    "sg:city":"Kapaa",
    "sg:classifiers":[
        {
            "category":"Mining & Drilling",
            "type":"Manufacturing & Wholesale Goods"
        }
    ],
    "sg:phone":"+1 808 823 9017",
    "sg:postcode":"96746",
    "sg:province":"HI",
    "sg:tags":[
        "nonmetallic",
        "mineral"
    ],
    "wof:name":"Dollys White Coral",
    "wof:placetype":"venue"
},
  "geometry": {"coordinates":[-159.34241,22.05884],"type":"Point"}
}