{
  "type": "Feature",
  "properties": {
    "iso:country":"US",
    "sg:address":"4274 Puaole St",
    "sg:city":"Lihue",
    "sg:classifiers":[
        {
            "category":"Travel",
            "subcategory":"Hotels & Motels",
            "type":"Entertainment"
        }
    ],
    "sg:phone":"+1 808 742 2966",
    "sg:postcode":"96766",
    "sg:province":"HI",
    "sg:tags":[
        "breakfast",
        "accommodation",
        "bed"
    ],
    "wof:name":"De Luxe Bed & Breakfast",
    "wof:placetype":"venue"
},
  "geometry": {"coordinates":[-159.361784,21.9748],"type":"Point"}
}