{
  "type": "Feature",
  "properties": {
    "iso:country":"US",
    "sg:address":"634 Pensacola St",
    "sg:city":"Honolulu",
    "sg:classifiers":[
        {
            "category":"Education",
            "subcategory":"Special Training",
            "type":"Public Place"
        }
    ],
    "sg:phone":"+1 808 594 0466",
    "sg:postcode":"96814",
    "sg:province":"HI",
    "sg:tags":[
        "dealing",
        "school",
        "community"
    ],
    "wof:name":"Hawaii Community Educatn Assn",
    "wof:placetype":"venue"
},
  "geometry": {"coordinates":[-157.847442,21.296618],"type":"Point"}
}