{
  "type": "Feature",
  "properties": {
    "iso:country":"US",
    "sg:address":"1914 Makiki Heights Dr",
    "sg:city":"Honolulu",
    "sg:classifiers":[
        {
            "category":"Organizations",
            "subcategory":"Community Association",
            "type":"Services"
        }
    ],
    "sg:phone":"+1 808 949 7256",
    "sg:postcode":"96822",
    "sg:province":"HI",
    "sg:tags":[
        "club"
    ],
    "wof:name":"Daughters-American Revolution",
    "wof:placetype":"venue"
},
  "geometry": {"coordinates":[-157.83232100000001,21.310551],"type":"Point"}
}