{
  "type": "Feature",
  "properties": {
    "iso:country":"US",
    "sg:address":"88 Kanoelehua Ave",
    "sg:city":"Hilo",
    "sg:classifiers":[
        {
            "category":"Restaurant",
            "type":"Food & Drink"
        },
        {
            "category":"Shopping",
            "subcategory":"Gifts & Souvenirs",
            "type":"Retail Goods"
        }
    ],
    "sg:phone":"+1 808 935 9998",
    "sg:postcode":"96720",
    "sg:province":"HI",
    "sg:tags":[
        "basket",
        "dairy",
        "product",
        "eating",
        "parcel"
    ],
    "wof:name":"Goodies Galore",
    "wof:placetype":"venue"
},
  "geometry": {"coordinates":[-155.06426099999999,19.721972],"type":"Point"}
}