{
  "type": "Feature",
  "properties": {
    "iso:country":"US",
    "sg:address":"399 N Market St",
    "sg:city":"Wailuku",
    "sg:classifiers":[
        {
            "category":"Real Estate",
            "subcategory":"Real Estate Operator",
            "type":"Services"
        }
    ],
    "sg:phone":"+1 808 244 4524",
    "sg:postcode":"96793",
    "sg:province":"HI",
    "sg:tags":[
        "building",
        "apartment"
    ],
    "wof:name":"Mokuhau Apts",
    "wof:placetype":"venue"
},
  "geometry": {"coordinates":[-156.50781699999999,20.897019],"type":"Point"}
}