{
  "type": "Feature",
  "properties": {
    "addr:full":"700 Bishop St Honolulu HI 96813",
    "addr:housenumber":"700",
    "addr:postcode":"96813",
    "addr:street":"Bishop St",
    "iso:country":"US",
    "sg:address":"700 Bishop St",
    "sg:city":"Honolulu",
    "sg:classifiers":[
        {
            "category":"Professional",
            "subcategory":"Accounting & Tax Preparation",
            "type":"Services"
        }
    ],
    "sg:phone":"+1 808 526 1040",
    "sg:postcode":"96813",
    "sg:province":"HI",
    "sg:tags":[
        "accountant"
    ],
    "wof:name":"Stephen H Wilson CPA",
    "wof:placetype":"venue"
},
  "geometry": {"coordinates":[-157.86358000000001,21.307052],"type":"Point"}
}