{
  "type": "Feature",
  "properties": {
    "iso:country":"US",
    "sg:address":"3626 Lower Honoapiilani Rd",
    "sg:city":"Lahaina",
    "sg:classifiers":[
        {
            "category":"Professional",
            "subcategory":"Detective & Security Services",
            "type":"Services"
        }
    ],
    "sg:phone":"+1 808 669 4931",
    "sg:postcode":"96761",
    "sg:province":"HI",
    "sg:tags":[
        "guard",
        "patrol"
    ],
    "wof:name":"Condo & Office Protection Svc",
    "wof:placetype":"venue"
},
  "geometry": {"coordinates":[-156.68551600000001,20.955485],"type":"Point"}
}