{
  "type": "Feature",
  "properties": {
    "iso:country":"US",
    "sg:address":"1614 Nuuanu Ave",
    "sg:city":"Honolulu",
    "sg:classifiers":[
        {
            "category":"Organizations",
            "subcategory":"Religious Organization",
            "type":"Services"
        }
    ],
    "sg:phone":"+1 808 533 6758",
    "sg:postcode":"96817",
    "sg:province":"HI",
    "wof:name":"Hawaii Chinese Buddhist Soc",
    "wof:placetype":"venue"
},
  "geometry": {"coordinates":[-157.85548499999999,21.317014],"type":"Point"}
}