{
  "type": "Feature",
  "properties": {
    "addr:full":"2100 Kalakaua Ave Honolulu HI 96815",
    "addr:housenumber":"2100",
    "addr:postcode":"96815",
    "addr:street":"Kalakaua Ave",
    "iso:country":"US",
    "sg:address":"2100 Kalakaua Ave",
    "sg:city":"Honolulu",
    "sg:classifiers":[
        {
            "category":"Shopping",
            "subcategory":"Jewelry",
            "type":"Retail Goods"
        }
    ],
    "sg:phone":"+1 808 926 2600",
    "sg:postcode":"96815",
    "sg:province":"HI",
    "wof:name":"Tiffany",
    "wof:placetype":"venue"
},
  "geometry": {"coordinates":[-157.831008,21.282315],"type":"Point"}
}