{
  "type": "Feature",
  "properties": {
    "iso:country":"US",
    "sg:address":"264 Farrington Hwy",
    "sg:city":"Waipahu",
    "sg:classifiers":[
        {
            "category":"Food & Beverages",
            "subcategory":"Groceries & Convenience Stores",
            "type":"Retail Goods"
        }
    ],
    "sg:phone":"+1 808 677 7667",
    "sg:postcode":"96797",
    "sg:province":"HI",
    "wof:name":"7-Eleven",
    "wof:placetype":"venue"
},
  "geometry": {"coordinates":[-158.017751,21.380731],"type":"Point"}
}