{
  "type": "Feature",
  "properties": {
    "addr:full":"98-1214 Kaahumanu St Pearl City HI 96782",
    "addr:housenumber":"98-1214",
    "addr:postcode":"96782",
    "addr:street":"Kaahumanu St",
    "iso:country":"US",
    "sg:address":"98-1214 Kaahumanu St",
    "sg:city":"Pearl City",
    "sg:classifiers":[
        {
            "category":"Restaurant",
            "type":"Food & Drink"
        }
    ],
    "sg:menulink":"http://www.allmenus.com/hi/ewa/160854-burger-king/menu/",
    "sg:phone":"+1 808 483 9330",
    "sg:postcode":"96782",
    "sg:province":"HI",
    "sg:tags":[
        "burger",
        "american"
    ],
    "wof:name":"Burger King",
    "wof:placetype":"venue"
},
  "geometry": {"coordinates":[-157.95456899999999,21.38758],"type":"Point"}
}