{
  "type": "Feature",
  "properties": {
    "iso:country":"US",
    "sg:address":"1181 Ka Uka Blvd",
    "sg:city":"Waipahu",
    "sg:classifiers":[
        {
            "category":"Wholesale",
            "subcategory":"Plants",
            "type":"Manufacturing & Wholesale Goods"
        }
    ],
    "sg:phone":"+1 808 676 2003",
    "sg:postcode":"96797",
    "sg:province":"HI",
    "sg:tags":[
        "florist",
        "supply"
    ],
    "wof:name":"Mylene's Floral Wholesale",
    "wof:placetype":"venue"
},
  "geometry": {"coordinates":[-158.00254699999999,21.425599],"type":"Point"}
}