{
  "type": "Feature",
  "properties": {
    "iso:country":"US",
    "sg:address":"305 Royal Hawaiian Ave",
    "sg:city":"Honolulu",
    "sg:classifiers":[
        {
            "category":"Wholesale",
            "subcategory":"Jewelry",
            "type":"Manufacturing & Wholesale Goods"
        }
    ],
    "sg:phone":"+1 808 924 9923",
    "sg:postcode":"96815",
    "sg:province":"HI",
    "sg:tags":[
        "stone"
    ],
    "wof:name":"Tuamotu Pearls & Gems Inc",
    "wof:placetype":"venue"
},
  "geometry": {"coordinates":[-157.82860400000001,21.279827],"type":"Point"}
}