{
  "type": "Feature",
  "properties": {
    "iso:country":"US",
    "sg:address":"2011 N King St",
    "sg:city":"Honolulu",
    "sg:classifiers":[
        {
            "category":"Restaurant",
            "type":"Food & Drink"
        }
    ],
    "sg:phone":"+1 808 843 8886",
    "sg:postcode":"96819",
    "sg:province":"HI",
    "sg:tags":[
        "out"
    ],
    "wof:name":"Alvin's Drive Inn II",
    "wof:placetype":"venue"
},
  "geometry": {"coordinates":[-157.87878499999999,21.332673],"type":"Point"}
}