{
  "type": "Feature",
  "properties": {
    "addr:full":"4270 Kilauea Rd Kilauea HI 96754",
    "addr:housenumber":"4270",
    "addr:postcode":"96754",
    "addr:street":"Kilauea Rd",
    "iso:country":"US",
    "sg:address":"4270 Kilauea Rd",
    "sg:city":"Kilauea",
    "sg:classifiers":[
        {
            "category":"Banks & Credit Unions",
            "subcategory":"Bank",
            "type":"Services"
        }
    ],
    "sg:phone":"+1 808 828 6480",
    "sg:postcode":"96754",
    "sg:province":"HI",
    "sg:tags":[
        "loan",
        "real estate"
    ],
    "wof:name":"Pacific International Mortgage",
    "wof:placetype":"venue"
},
  "geometry": {"coordinates":[-159.40812500000001,22.211025],"type":"Point"}
}