{
  "type": "Feature",
  "properties": {
    "addr:full":"3626 Leahi Ave Honolulu HI 96815",
    "addr:housenumber":"3626",
    "addr:postcode":"96815",
    "addr:street":"Leahi Ave",
    "iso:country":"US",
    "sg:address":"3626 Leahi Ave",
    "sg:city":"Honolulu",
    "sg:classifiers":[
        {
            "category":"Real Estate",
            "subcategory":"Architect",
            "type":"Services"
        }
    ],
    "sg:phone":"+1 808 599 5229",
    "sg:postcode":"96815",
    "sg:province":"HI",
    "sg:tags":[
        "architectural"
    ],
    "wof:name":"Design Works",
    "wof:placetype":"venue"
},
  "geometry": {"coordinates":[-157.81509,21.269806],"type":"Point"}
}