{
  "type": "Feature",
  "properties": {
    "iso:country":"US",
    "sg:address":"3536 Harding Ave",
    "sg:city":"Honolulu",
    "sg:classifiers":[
        {
            "category":"Recreation",
            "type":"Entertainment"
        },
        {
            "category":"Organizations",
            "subcategory":"Community Association",
            "type":"Services"
        }
    ],
    "sg:phone":"+1 808 735 1073",
    "sg:postcode":"96816",
    "sg:province":"HI",
    "sg:tags":[
        "club",
        "membership"
    ],
    "wof:name":"Hawaii Rotary Youth Foundation",
    "wof:placetype":"venue"
},
  "geometry": {"coordinates":[-157.80189200000001,21.282254],"type":"Point"}
}