{
  "type": "Feature",
  "properties": {
    "iso:country":"US",
    "sg:address":"1001 Bishop St",
    "sg:city":"Honolulu",
    "sg:classifiers":[
        {
            "category":"Organizations",
            "subcategory":"Labor Organization",
            "type":"Services"
        },
        {
            "category":"Organizations",
            "subcategory":"Professional Association",
            "type":"Services"
        }
    ],
    "sg:phone":"+1 808 528 5557",
    "sg:postcode":"96813",
    "sg:province":"HI",
    "sg:tags":[
        "business",
        "trade"
    ],
    "wof:name":"Pacific Resource Partnership",
    "wof:placetype":"venue"
},
  "geometry": {"coordinates":[-157.86039400000001,21.30931],"type":"Point"}
}