{
  "type": "Feature",
  "properties": {
    "iso:country":"US",
    "sg:address":"1001 Wilder Ave",
    "sg:city":"Honolulu",
    "sg:classifiers":[
        {
            "category":"Health Services",
            "subcategory":"Chiropractor",
            "type":"Services"
        }
    ],
    "sg:phone":"+1 808 942 9461",
    "sg:postcode":"96822",
    "sg:province":"HI",
    "sg:tags":[
        "dental"
    ],
    "wof:name":"Zais Martin H DDS",
    "wof:placetype":"venue"
},
  "geometry": {"coordinates":[-157.84249399999999,21.308452],"type":"Point"}
}