{
  "type": "Feature",
  "properties": {
    "iso:country":"US",
    "sg:address":"940 Moanalua Rd",
    "sg:city":"Aiea",
    "sg:classifiers":[
        {
            "category":"Education",
            "subcategory":"School",
            "type":"Public Place"
        }
    ],
    "sg:phone":"+1 808 483 7210",
    "sg:postcode":"96701",
    "sg:province":"HI",
    "sg:tags":[
        "elementary"
    ],
    "wof:name":"Pearl Ridge Elementary School",
    "wof:placetype":"venue"
},
  "geometry": {"coordinates":[-157.945943,21.38827],"type":"Point"}
}