{
  "type": "Feature",
  "properties": {
    "iso:country":"US",
    "sg:address":"47 Kaahumanu Ave",
    "sg:city":"Kahului",
    "sg:classifiers":[
        {
            "category":"Restaurant",
            "type":"Food & Drink"
        }
    ],
    "sg:phone":"+1 808 573 2684",
    "sg:postcode":"96732",
    "sg:province":"HI",
    "sg:tags":[
        "out"
    ],
    "wof:name":"T J's Oriental Food Mart",
    "wof:placetype":"venue"
},
  "geometry": {"coordinates":[-156.47011900000001,20.890262],"type":"Point"}
}