{
  "type": "Feature",
  "properties": {
    "iso:country":"US",
    "sg:address":"2200 Main St",
    "sg:city":"Wailuku",
    "sg:classifiers":[
        {
            "category":"Banks & Credit Unions",
            "subcategory":"Investment Brokerage",
            "type":"Services"
        }
    ],
    "sg:phone":"+1 808 244 9124",
    "sg:postcode":"96793",
    "sg:province":"HI",
    "sg:tags":[
        "security"
    ],
    "wof:name":"Dean Witter",
    "wof:placetype":"venue"
},
  "geometry": {"coordinates":[-156.508725,20.889809],"type":"Point"}
}