{
  "type": "Feature",
  "properties": {
    "iso:country":"US",
    "sg:address":"30 N Kukui St",
    "sg:city":"Honolulu",
    "sg:classifiers":[
        {
            "category":"Retail",
            "subcategory":"Funeral Services",
            "type":"Services"
        }
    ],
    "sg:phone":"+1 808 538 3877",
    "sg:postcode":"96817",
    "sg:province":"HI",
    "sg:tags":[
        "crematory"
    ],
    "wof:name":"Hosoi Garden Mortuary Inc",
    "wof:placetype":"venue"
},
  "geometry": {"coordinates":[-157.85936000000001,21.314202],"type":"Point"}
}