{
  "type": "Feature",
  "properties": {
    "iso:country":"US",
    "sg:address":"369 N Vineyard Blvd",
    "sg:city":"Honolulu",
    "sg:classifiers":[
        {
            "category":"Travel",
            "subcategory":"Travel Agent",
            "type":"Entertainment"
        }
    ],
    "sg:phone":"+1 808 523 8944",
    "sg:postcode":"96817",
    "sg:province":"HI",
    "sg:tags":[
        "operator",
        "tour"
    ],
    "wof:name":"Top VIP Tours Inc",
    "wof:placetype":"venue"
},
  "geometry": {"coordinates":[-157.86117300000001,21.318435],"type":"Point"}
}