{
  "type": "Feature",
  "properties": {
    "iso:country":"US",
    "sg:address":"2988 Ualena St",
    "sg:city":"Honolulu",
    "sg:classifiers":[
        {
            "category":"Restaurant",
            "type":"Food & Drink"
        }
    ],
    "sg:phone":"+1 808 833 8788",
    "sg:postcode":"96819",
    "sg:province":"HI",
    "wof:name":"Win Hing Food LLC",
    "wof:placetype":"venue"
},
  "geometry": {"coordinates":[-157.90211099999999,21.332956],"type":"Point"}
}