{
  "type": "Feature",
  "properties": {
    "addr:full":"530 Paiea St Honolulu HI 96819",
    "addr:housenumber":"530",
    "addr:postcode":"96819",
    "addr:street":"Paiea St",
    "iso:country":"US",
    "sg:address":"530 Paiea St",
    "sg:city":"Honolulu",
    "sg:classifiers":[
        {
            "category":"Shopping",
            "type":"Retail Goods"
        }
    ],
    "sg:phone":"+1 808 833 5858",
    "sg:postcode":"96819",
    "sg:province":"HI",
    "sg:tags":[
        "awning",
        "canopy",
        "merchandise"
    ],
    "wof:name":"Tent Services Co",
    "wof:placetype":"venue"
},
  "geometry": {"coordinates":[-157.91487699999999,21.335978],"type":"Point"}
}