{
  "type": "Feature",
  "properties": {
    "addr:full":"851 Leilani St Hilo HI 96720",
    "addr:housenumber":"851",
    "addr:postcode":"96720",
    "addr:street":"Leilani St",
    "iso:country":"US",
    "sg:address":"851 Leilani St",
    "sg:city":"Hilo",
    "sg:classifiers":[
        {
            "category":"Wholesale",
            "subcategory":"Seafood",
            "type":"Manufacturing & Wholesale Goods"
        }
    ],
    "sg:phone":"+1 808 960 2322",
    "sg:postcode":"96720",
    "sg:province":"HI",
    "wof:name":"T JS Seafoods",
    "wof:placetype":"venue"
},
  "geometry": {"coordinates":[-155.05883900000001,19.710501],"type":"Point"}
}