{
  "type": "Feature",
  "properties": {
    "addr:full":"820 Mililani St Honolulu HI 96813",
    "addr:housenumber":"820",
    "addr:postcode":"96813",
    "addr:street":"Mililani St",
    "iso:country":"US",
    "sg:address":"820 Mililani St",
    "sg:city":"Honolulu",
    "sg:classifiers":[
        {
            "category":"Banks & Credit Unions",
            "subcategory":"Financial Services",
            "type":"Services"
        }
    ],
    "sg:phone":"+1 808 533 7437",
    "sg:postcode":"96813",
    "sg:province":"HI",
    "sg:tags":[
        "investor"
    ],
    "wof:name":"Investors Finance",
    "wof:placetype":"venue"
},
  "geometry": {"coordinates":[-157.86001899999999,21.305984],"type":"Point"}
}