{
  "type": "Feature",
  "properties": {
    "iso:country":"US",
    "sg:address":"715 S King St",
    "sg:city":"Honolulu",
    "sg:classifiers":[
        {
            "category":"Banks & Credit Unions",
            "subcategory":"Bank",
            "type":"Services"
        }
    ],
    "sg:phone":"+1 808 547 4521",
    "sg:postcode":"96813",
    "sg:province":"HI",
    "sg:tags":[
        "federally",
        "chartered"
    ],
    "wof:name":"Queen's Federal Credit Union",
    "wof:placetype":"venue"
},
  "geometry": {"coordinates":[-157.85395399999999,21.303263],"type":"Point"}
}