{
  "type": "Feature",
  "properties": {
    "iso:country":"US",
    "sg:address":"2318 Lime St",
    "sg:city":"Honolulu",
    "sg:classifiers":[
        {
            "category":"Taxi",
            "type":"Transportation"
        }
    ],
    "sg:phone":"+1 808 226 6668",
    "sg:postcode":"96826",
    "sg:province":"HI",
    "sg:tags":[
        "taxicab"
    ],
    "wof:name":"Johnny Cheng Airport Taxi",
    "wof:placetype":"venue"
},
  "geometry": {"coordinates":[-157.827561,21.288799],"type":"Point"}
}