{
  "type": "Feature",
  "properties": {
    "iso:country":"US",
    "sg:address":"148 18th St",
    "sg:city":"Honolulu",
    "sg:classifiers":[
        {
            "category":"Professional",
            "subcategory":"Business Services",
            "type":"Services"
        }
    ],
    "sg:phone":"+1 808 922 3481",
    "sg:postcode":"96818",
    "sg:province":"HI",
    "sg:tags":[
        "translation"
    ],
    "wof:name":"Jea Translations",
    "wof:placetype":"venue"
},
  "geometry": {"coordinates":[-157.94747000000001,21.343334],"type":"Point"}
}