{
  "type": "Feature",
  "properties": {
    "addr:full":"1226 Kaahumanu St Pearl City HI 96782",
    "addr:housenumber":"1226",
    "addr:postcode":"96782",
    "addr:street":"Kaahumanu St",
    "iso:country":"US",
    "sg:address":"1226 Kaahumanu St",
    "sg:city":"Pearl City",
    "sg:classifiers":[
        {
            "category":"Restaurant",
            "type":"Food & Drink"
        }
    ],
    "sg:phone":"+1 808 487 0091",
    "sg:postcode":"96782",
    "sg:province":"HI",
    "sg:website":"www.gyotakuhawaii.com",
    "wof:name":"Gyotaku",
    "wof:placetype":"venue"
},
  "geometry": {"coordinates":[-157.953596,21.388946],"type":"Point"}
}