{
  "type": "Feature",
  "properties": {
    "addr:full":"1441 Kapiolani Blvd Honolulu HI 96814",
    "addr:housenumber":"1441",
    "addr:postcode":"96814",
    "addr:street":"Kapiolani Blvd",
    "iso:country":"US",
    "sg:address":"1441 Kapiolani Blvd",
    "sg:city":"Honolulu",
    "sg:classifiers":[
        {
            "category":"Personal",
            "subcategory":"Beauty Salon",
            "type":"Services"
        }
    ],
    "sg:phone":"+1 808 946 3838",
    "sg:postcode":"96814",
    "sg:province":"HI",
    "sg:tags":[
        "application",
        "make",
        "cosmetic",
        "facial"
    ],
    "wof:name":"Ampys Day Spa",
    "wof:placetype":"venue"
},
  "geometry": {"coordinates":[-157.844087,21.293729],"type":"Point"}
}