{
  "type": "Feature",
  "properties": {
    "addr:full":"2111 Ahe St Honolulu HI 96816",
    "addr:housenumber":"2111",
    "addr:postcode":"96816",
    "addr:street":"Ahe St",
    "iso:country":"US",
    "sg:address":"2111 Ahe St",
    "sg:city":"Honolulu",
    "sg:classifiers":[
        {
            "category":"Freight",
            "type":"Transportation"
        }
    ],
    "sg:phone":"+1 808 732 8857",
    "sg:postcode":"96816",
    "sg:province":"HI",
    "wof:name":"Ricky Le",
    "wof:placetype":"venue"
},
  "geometry": {"coordinates":[-157.79357300000001,21.30085],"type":"Point"}
}