{
  "type": "Feature",
  "properties": {
    "iso:country":"US",
    "sg:address":"187 Kilauea Ave",
    "sg:city":"Hilo",
    "sg:classifiers":[
        {
            "category":"Food & Beverages",
            "subcategory":"Specialty",
            "type":"Retail Goods"
        }
    ],
    "sg:phone":"+1 808 935 8360",
    "sg:postcode":"96720",
    "sg:province":"HI",
    "sg:tags":[
        "eating"
    ],
    "wof:name":"Kilauea Preserve Center LLC",
    "wof:placetype":"venue"
},
  "geometry": {"coordinates":[-155.08489299999999,19.721653],"type":"Point"}
}