{
  "type": "Feature",
  "properties": {
    "iso:country":"US",
    "sg:address":"712 Kamehameha Hwy",
    "sg:city":"Haleiwa",
    "sg:classifiers":[
        {
            "category":"Restaurant",
            "type":"Food & Drink"
        }
    ],
    "sg:phone":"+1 808 638 8300",
    "sg:postcode":"96712",
    "sg:province":"HI",
    "wof:name":"Sharks Cove Grill",
    "wof:placetype":"venue"
},
  "geometry": {"coordinates":[-158.06254899999999,21.648048],"type":"Point"}
}