{
  "type": "Feature",
  "properties": {
    "iso:country":"US",
    "sg:address":"555 Hahaione St",
    "sg:city":"Honolulu",
    "sg:classifiers":[
        {
            "category":"Building & Trades",
            "subcategory":"Construction",
            "type":"Services"
        }
    ],
    "sg:phone":"+1 808 396 4445",
    "sg:postcode":"96825",
    "sg:province":"HI",
    "sg:tags":[
        "concrete",
        "contractor"
    ],
    "wof:name":"Elastizell Pacific Corporation",
    "wof:placetype":"venue"
},
  "geometry": {"coordinates":[-157.70788400000001,21.29483],"type":"Point"}
}