{
  "type": "Feature",
  "properties": {
    "iso:country":"US",
    "sg:address":"1450 Renton Rd",
    "sg:city":"Ewa Beach",
    "sg:classifiers":[
        {
            "category":"Recreation",
            "type":"Entertainment"
        }
    ],
    "sg:phone":"+1 808 681 6435",
    "sg:postcode":"96706",
    "sg:province":"HI",
    "sg:tags":[
        "parks"
    ],
    "wof:name":"Asing Park",
    "wof:placetype":"venue"
},
  "geometry": {"coordinates":[-158.02644100000001,21.348248],"type":"Point"}
}