{
  "type": "Feature",
  "properties": {
    "iso:country":"US",
    "sg:address":"65 Kaahumanu Ave",
    "sg:city":"Kahului",
    "sg:classifiers":[
        {
            "category":"Restaurant",
            "type":"Food & Drink"
        },
        {
            "category":"Bars & Pubs",
            "type":"Food & Drink"
        }
    ],
    "sg:phone":"+1 808 877 7776",
    "sg:postcode":"96732",
    "sg:province":"HI",
    "sg:tags":[
        "drinking"
    ],
    "wof:name":"Asian Cuisine & Sports Bar",
    "wof:placetype":"venue"
},
  "geometry": {"coordinates":[-156.47038499999999,20.890088],"type":"Point"}
}