{
  "type": "Feature",
  "properties": {
    "addr:full":"7192 Kalanianaole Hwy Honolulu HI 96825",
    "addr:housenumber":"7192",
    "addr:postcode":"96825",
    "addr:street":"Kalanianaole Hwy",
    "iso:country":"US",
    "sg:address":"7192 Kalanianaole Hwy",
    "sg:city":"Honolulu",
    "sg:classifiers":[
        {
            "category":"Shopping",
            "subcategory":"Clothing, Apparel, & Fashions",
            "type":"Retail Goods"
        }
    ],
    "sg:phone":"+1 808 394 9090",
    "sg:postcode":"96825",
    "sg:province":"HI",
    "wof:name":"KOKO Cabana",
    "wof:placetype":"venue"
},
  "geometry": {"coordinates":[-157.70812699999999,21.278837],"type":"Point"}
}