{
  "type": "Feature",
  "properties": {
    "iso:country":"US",
    "sg:address":"94-780 Meheula Pkwy",
    "sg:city":"Mililani",
    "sg:classifiers":[
        {
            "category":"Restaurant",
            "type":"Food & Drink"
        }
    ],
    "sg:menulink":"http://www.allmenus.com/hi/ewa/83577-papa-johns-pizza/menu/",
    "sg:phone":"+1 808 627 7272",
    "sg:postcode":"96789",
    "sg:province":"HI",
    "sg:tags":[
        "american",
        "pizza"
    ],
    "wof:name":"Papa John's Pizza",
    "wof:placetype":"venue"
},
  "geometry": {"coordinates":[-158.02223599999999,21.442022],"type":"Point"}
}