{
  "type": "Feature",
  "properties": {
    "addr:full":"5037 Onipaa St Kailua Kona HI 96740",
    "addr:housenumber":"5037",
    "addr:postcode":"96740",
    "addr:street":"Onipaa St",
    "iso:country":"US",
    "sg:address":"5037 Onipaa St",
    "sg:city":"Kailua Kona",
    "sg:classifiers":[
        {
            "category":"Education",
            "subcategory":"Dance Studio",
            "type":"Public Place"
        }
    ],
    "sg:phone":"+1 808 329 4343",
    "sg:postcode":"96740",
    "sg:province":"HI",
    "sg:tags":[
        "hula",
        "instructions"
    ],
    "wof:name":"Napua's Hula Studio",
    "wof:placetype":"venue"
},
  "geometry": {"coordinates":[-155.985331,19.672249],"type":"Point"}
}