{
  "type": "Feature",
  "properties": {
    "iso:country":"US",
    "sg:address":"781 Hui Ulili St",
    "sg:city":"Kaneohe",
    "sg:classifiers":[
        {
            "category":"Shopping",
            "subcategory":"Beauty & Cosmetics",
            "type":"Retail Goods"
        }
    ],
    "sg:phone":"+1 808 239 7875",
    "sg:postcode":"96744",
    "sg:province":"HI",
    "wof:name":"Mary Kay Cosmetics",
    "wof:placetype":"venue"
},
  "geometry": {"coordinates":[-157.83499599999999,21.441819],"type":"Point"}
}