{
  "type": "Feature",
  "properties": {
    "addr:full":"1251 Heulu St Honolulu HI 96822",
    "addr:housenumber":"1251",
    "addr:postcode":"96822",
    "addr:street":"Heulu St",
    "iso:country":"US",
    "sg:address":"1251 Heulu St",
    "sg:city":"Honolulu",
    "sg:classifiers":[
        {
            "category":"Health Services",
            "subcategory":"Medical Lab",
            "type":"Services"
        }
    ],
    "sg:phone":"+1 808 537 6206",
    "sg:postcode":"96822",
    "sg:province":"HI",
    "sg:tags":[
        "detection",
        "equipment",
        "drug"
    ],
    "wof:name":"Safe-Tec",
    "wof:placetype":"venue"
},
  "geometry": {"coordinates":[-157.83649800000001,21.307127],"type":"Point"}
}