{
  "type": "Feature",
  "properties": {
    "addr:full":"212 Leoku St Waipahu HI 96797",
    "addr:housenumber":"212",
    "addr:postcode":"96797",
    "addr:street":"Leoku St",
    "iso:country":"US",
    "sg:address":"212 Leoku St",
    "sg:city":"Waipahu",
    "sg:classifiers":[
        {
            "category":"Restaurant",
            "type":"Food & Drink"
        }
    ],
    "sg:phone":"+1 808 671 0881",
    "sg:postcode":"96797",
    "sg:province":"HI",
    "wof:name":"Mc Donald's",
    "wof:placetype":"venue"
},
  "geometry": {"coordinates":[-158.02412200000001,21.379076],"type":"Point"}
}