{
  "type": "Feature",
  "properties": {
    "iso:country":"US",
    "sg:address":"565 Farrington Hwy",
    "sg:city":"Kapolei",
    "sg:classifiers":[
        {
            "category":"Restaurant",
            "type":"Food & Drink"
        }
    ],
    "sg:menulink":"http://www.allmenus.com/hi/ewa/83576-papa-johns-pizza/menu/",
    "sg:phone":"+1 808 674 1991",
    "sg:postcode":"96707",
    "sg:province":"HI",
    "sg:tags":[
        "american",
        "pizza"
    ],
    "wof:name":"Papa John's Pizza",
    "wof:placetype":"venue"
},
  "geometry": {"coordinates":[-158.077718,21.338122],"type":"Point"}
}