{
  "type": "Feature",
  "properties": {
    "iso:country":"US",
    "sg:address":"62 Baldwin Ave",
    "sg:city":"Paia",
    "sg:classifiers":[
        {
            "category":"Travel",
            "subcategory":"Travel Agent",
            "type":"Entertainment"
        }
    ],
    "sg:phone":"+1 808 579 8282",
    "sg:postcode":"96779",
    "sg:province":"HI",
    "sg:tags":[
        "agency",
        "bureau"
    ],
    "sg:website":"www.hookipa.com",
    "wof:name":"Ho'Okipa Haven Vacation Svc",
    "wof:placetype":"venue"
},
  "geometry": {"coordinates":[-156.37668500000001,20.908728],"type":"Point"}
}