{
  "type": "Feature",
  "properties": {
    "iso:country":"US",
    "sg:address":"23 Hekaha St",
    "sg:city":"Aiea",
    "sg:classifiers":[
        {
            "category":"Building & Trades",
            "subcategory":"Cleaning & Sanitation",
            "type":"Services"
        }
    ],
    "sg:phone":"+1 808 487 7767",
    "sg:postcode":"96701",
    "sg:province":"HI",
    "sg:tags":[
        "janitor",
        "maintenance"
    ],
    "wof:name":"Accent Management Service Inc",
    "wof:placetype":"venue"
},
  "geometry": {"coordinates":[-157.95149699999999,21.384471],"type":"Point"}
}