{
  "type": "Feature",
  "properties": {
    "addr:full":"56 Hoomalu St Pearl City HI 96782",
    "addr:housenumber":"56",
    "addr:postcode":"96782",
    "addr:street":"Hoomalu St",
    "iso:country":"US",
    "sg:address":"56 Hoomalu St",
    "sg:city":"Pearl City",
    "sg:classifiers":[
        {
            "category":"Professional",
            "subcategory":"Accounting & Tax Preparation",
            "type":"Services"
        }
    ],
    "sg:phone":"+1 808 456 5715",
    "sg:postcode":"96782",
    "sg:province":"HI",
    "wof:name":"Edward A Sunada",
    "wof:placetype":"venue"
},
  "geometry": {"coordinates":[-157.95339999999999,21.405724],"type":"Point"}
}