{
  "type": "Feature",
  "properties": {
    "iso:country":"US",
    "sg:address":"345 Dairy Rd",
    "sg:city":"Kahului",
    "sg:classifiers":[
        {
            "category":"Autos & Motor Vehicles",
            "subcategory":"Fuel & Gas Station",
            "type":"Retail Goods"
        }
    ],
    "sg:phone":"+1 808 877 2806",
    "sg:postcode":"96732",
    "sg:province":"HI",
    "sg:tags":[
        "oil"
    ],
    "wof:name":"Maui Self Svc",
    "wof:placetype":"venue"
},
  "geometry": {"coordinates":[-156.45438999999999,20.882856],"type":"Point"}
}