{
  "type": "Feature",
  "properties": {
    "iso:country":"US",
    "sg:address":"508 Waiakamilo Rd",
    "sg:city":"Honolulu",
    "sg:classifiers":[
        {
            "category":"Bars & Pubs",
            "type":"Food & Drink"
        }
    ],
    "sg:phone":"+1 808 843 1668",
    "sg:postcode":"96817",
    "sg:province":"HI",
    "sg:tags":[
        "lounge",
        "cocktail"
    ],
    "wof:name":"Club Lao Star",
    "wof:placetype":"venue"
},
  "geometry": {"coordinates":[-157.87510599999999,21.324814],"type":"Point"}
}