{
  "type": "Feature",
  "properties": {
    "iso:country":"US",
    "sg:address":"1782 Bougainvillea Loop",
    "sg:city":"Honolulu",
    "sg:classifiers":[
        {
            "category":"Education",
            "subcategory":"Library",
            "type":"Public Place"
        }
    ],
    "sg:phone":"+1 808 833 4851",
    "sg:postcode":"96818",
    "sg:province":"HI",
    "wof:name":"ALIAMANU Library",
    "wof:placetype":"venue"
},
  "geometry": {"coordinates":[-157.916607,21.361697],"type":"Point"}
}