{
  "type": "Feature",
  "properties": {
    "iso:country":"US",
    "sg:address":"855 Front St",
    "sg:city":"Lahaina",
    "sg:classifiers":[
        {
            "category":"Shopping",
            "subcategory":"Jewelry",
            "type":"Retail Goods"
        }
    ],
    "sg:phone":"+1 808 662 0020",
    "sg:postcode":"96761",
    "sg:province":"HI",
    "sg:tags":[
        "jeweler"
    ],
    "wof:name":"Danamir",
    "wof:placetype":"venue"
},
  "geometry": {"coordinates":[-156.683367,20.879206],"type":"Point"}
}