{
  "type": "Feature",
  "properties": {
    "iso:country":"US",
    "sg:address":"435 Atkinson Dr",
    "sg:city":"Honolulu",
    "sg:classifiers":[
        {
            "category":"Banks & Credit Unions",
            "subcategory":"Bank",
            "type":"Services"
        }
    ],
    "sg:phone":"+1 808 946 2435",
    "sg:postcode":"96814",
    "sg:province":"HI",
    "sg:tags":[
        "cashing",
        "check"
    ],
    "wof:name":"Money Mart 2601",
    "wof:placetype":"venue"
},
  "geometry": {"coordinates":[-157.83943300000001,21.289724],"type":"Point"}
}