{
  "type": "Feature",
  "properties": {
    "addr:full":"275 Kaahumanu Ave Kahului HI 96732",
    "addr:housenumber":"275",
    "addr:postcode":"96732",
    "addr:street":"Kaahumanu Ave",
    "iso:country":"US",
    "sg:address":"275 Kaahumanu Ave",
    "sg:city":"Kahului",
    "sg:classifiers":[
        {
            "category":"Personal",
            "subcategory":"Beauty Salon",
            "type":"Services"
        }
    ],
    "sg:phone":"+1 808 871 8848",
    "sg:postcode":"96732",
    "sg:province":"HI",
    "sg:tags":[
        "shop"
    ],
    "wof:name":"Regis Salon",
    "wof:placetype":"venue"
},
  "geometry": {"coordinates":[-156.47732400000001,20.888739],"type":"Point"}
}