{
  "type": "Feature",
  "properties": {
    "iso:country":"US",
    "sg:address":"525 California Ave",
    "sg:city":"Wahiawa",
    "sg:classifiers":[
        {
            "category":"Banks & Credit Unions",
            "subcategory":"Bank",
            "type":"Services"
        }
    ],
    "sg:phone":"+1 808 622 6088",
    "sg:postcode":"96786",
    "sg:province":"HI",
    "sg:tags":[
        "cashing",
        "check"
    ],
    "wof:name":"Advance Til Payday",
    "wof:placetype":"venue"
},
  "geometry": {"coordinates":[-158.029573,21.49594],"type":"Point"}
}