{
  "type": "Feature",
  "properties": {
    "iso:country":"US",
    "sg:address":"4414 Kukui Grove St",
    "sg:city":"Lihue",
    "sg:classifiers":[
        {
            "category":"Health Services",
            "subcategory":"Optometrist",
            "type":"Services"
        }
    ],
    "sg:phone":"+1 808 245 6811",
    "sg:postcode":"96766",
    "sg:province":"HI",
    "wof:name":"Kauai Optometric Ctr",
    "wof:placetype":"venue"
},
  "geometry": {"coordinates":[-159.37709100000001,21.971179],"type":"Point"}
}