{
  "type": "Feature",
  "properties": {
    "iso:country":"US",
    "sg:address":"88 Piikoi St",
    "sg:city":"Honolulu",
    "sg:classifiers":[
        {
            "category":"Real Estate",
            "subcategory":"Real Estate Agent",
            "type":"Services"
        }
    ],
    "sg:phone":"+1 808 593 0709",
    "sg:postcode":"96814",
    "sg:province":"HI",
    "wof:name":"Newtown Realty Inc",
    "wof:placetype":"venue"
},
  "geometry": {"coordinates":[-157.84701200000001,21.293238],"type":"Point"}
}