{
  "type": "Feature",
  "properties": {
    "iso:country":"US",
    "sg:address":"155 Kapalulu Pl",
    "sg:city":"Honolulu",
    "sg:classifiers":[
        {
            "category":"Airline",
            "type":"Transportation"
        }
    ],
    "sg:phone":"+1 808 836 2000",
    "sg:postcode":"96819",
    "sg:province":"HI",
    "sg:tags":[
        "air",
        "ambulance"
    ],
    "sg:website":"www.hiairamb.com",
    "wof:name":"Hawaii Air Ambulance",
    "wof:placetype":"venue"
},
  "geometry": {"coordinates":[-157.91118,21.321128],"type":"Point"}
}