{
  "type": "Feature",
  "properties": {
    "iso:country":"US",
    "sg:address":"2099 Wells St",
    "sg:city":"Wailuku",
    "sg:classifiers":[
        {
            "category":"Health Services",
            "subcategory":"Health Practitioner",
            "type":"Services"
        }
    ],
    "sg:phone":"+1 808 244 6778",
    "sg:postcode":"96793",
    "sg:province":"HI",
    "sg:tags":[
        "acupuncture"
    ],
    "wof:name":"Blue Bamboo Chinese Med Ctr",
    "wof:placetype":"venue"
},
  "geometry": {"coordinates":[-156.505065,20.889799],"type":"Point"}
}