{
  "type": "Feature",
  "properties": {
    "iso:country":"US",
    "sg:address":"693 Front St",
    "sg:city":"Lahaina",
    "sg:classifiers":[
        {
            "category":"Restaurant",
            "type":"Food & Drink"
        }
    ],
    "sg:phone":"+1 808 661 3310",
    "sg:postcode":"96761",
    "sg:province":"HI",
    "sg:tags":[
        "parlor",
        "ice",
        "cream"
    ],
    "wof:name":"Lappert's Ice Cream",
    "wof:placetype":"venue"
},
  "geometry": {"coordinates":[-156.68080499999999,20.876159],"type":"Point"}
}