{
  "type": "Feature",
  "properties": {
    "iso:country":"US",
    "sg:address":"3416 Rice St",
    "sg:city":"Lihue",
    "sg:classifiers":[
        {
            "category":"Shopping",
            "subcategory":"Jewelry",
            "type":"Retail Goods"
        }
    ],
    "sg:phone":"+1 808 246 2699",
    "sg:postcode":"96766",
    "sg:province":"HI",
    "sg:tags":[
        "jeweler"
    ],
    "wof:name":"Maui Divers",
    "wof:placetype":"venue"
},
  "geometry": {"coordinates":[-159.353092,21.960064],"type":"Point"}
}