{
  "type": "Feature",
  "properties": {
    "iso:country":"US",
    "sg:address":"1111 Hala Dr",
    "sg:city":"Honolulu",
    "sg:classifiers":[
        {
            "category":"Social Services",
            "subcategory":"Adult Care",
            "type":"Services"
        }
    ],
    "sg:phone":"+1 808 842 1082",
    "sg:postcode":"96817",
    "sg:province":"HI",
    "sg:tags":[
        "home"
    ],
    "wof:name":"Maluhia Elderly Housing",
    "wof:placetype":"venue"
},
  "geometry": {"coordinates":[-157.860602,21.329848],"type":"Point"}
}