{
  "type": "Feature",
  "properties": {
    "iso:country":"US",
    "sg:address":"83 Uluwehi St",
    "sg:city":"Wahiawa",
    "sg:classifiers":[
        {
            "category":"Organizations",
            "subcategory":"Professional Association",
            "type":"Services"
        }
    ],
    "sg:phone":"+1 808 621 7305",
    "sg:postcode":"96786",
    "sg:province":"HI",
    "wof:name":"Zonta International",
    "wof:placetype":"venue"
},
  "geometry": {"coordinates":[-158.01028299999999,21.500201],"type":"Point"}
}