{
  "type": "Feature",
  "properties": {
    "iso:country":"US",
    "sg:address":"1188 Mamalahoa Hwy",
    "sg:city":"Kamuela",
    "sg:classifiers":[
        {
            "category":"Travel",
            "subcategory":"Travel Agent",
            "type":"Entertainment"
        }
    ],
    "sg:phone":"+1 808 885 6651",
    "sg:postcode":"96743",
    "sg:province":"HI",
    "sg:tags":[
        "agency",
        "bureau"
    ],
    "wof:name":"Kamuela Travel Inc",
    "wof:placetype":"venue"
},
  "geometry": {"coordinates":[-155.669006,20.020564],"type":"Point"}
}