{
  "type": "Feature",
  "properties": {
    "addr:full":"1019 Waimanu St Honolulu HI 96814",
    "addr:housenumber":"1019",
    "addr:postcode":"96814",
    "addr:street":"Waimanu St",
    "iso:country":"US",
    "sg:address":"1019 Waimanu St",
    "sg:city":"Honolulu",
    "sg:classifiers":[
        {
            "category":"Social Services",
            "type":"Services"
        }
    ],
    "sg:phone":"+1 808 988 1000",
    "sg:postcode":"96814",
    "sg:province":"HI",
    "sg:tags":[
        "information",
        "center",
        "diabetes"
    ],
    "wof:name":"Juvenile Diabetes Foundation",
    "wof:placetype":"venue"
},
  "geometry": {"coordinates":[-157.85094599999999,21.29563],"type":"Point"}
}