{
  "type": "Feature",
  "properties": {
    "iso:country":"US",
    "sg:address":"707 Kinoole St",
    "sg:city":"Hilo",
    "sg:classifiers":[
        {
            "category":"Shopping",
            "subcategory":"Florist",
            "type":"Retail Goods"
        }
    ],
    "sg:phone":"+1 808 961 9143",
    "sg:postcode":"96720",
    "sg:province":"HI",
    "sg:tags":[
        "personal",
        "funeral"
    ],
    "wof:name":"Kui & I Florist",
    "wof:placetype":"venue"
},
  "geometry": {"coordinates":[-155.08421999999999,19.717579],"type":"Point"}
}