{
  "type": "Feature",
  "properties": {
    "iso:country":"US",
    "sg:address":"18 Kamehameha Hwy",
    "sg:city":"Kaneohe",
    "sg:classifiers":[
        {
            "category":"Personal",
            "subcategory":"Barber",
            "type":"Services"
        }
    ],
    "sg:phone":"+1 808 235 0679",
    "sg:postcode":"96744",
    "sg:province":"HI",
    "wof:name":"Ginger Barber Shop & Styling",
    "wof:placetype":"venue"
},
  "geometry": {"coordinates":[-157.78264799999999,21.376589],"type":"Point"}
}