{
  "type": "Feature",
  "properties": {
    "iso:country":"US",
    "sg:address":"626 Farrington Hwy",
    "sg:city":"Waianae",
    "sg:classifiers":[
        {
            "category":"Government",
            "subcategory":"Office",
            "type":"Public Place"
        }
    ],
    "sg:phone":"+1 808 697 7121",
    "sg:postcode":"96792",
    "sg:province":"HI",
    "sg:tags":[
        "educational",
        "program",
        "administrative"
    ],
    "wof:name":"Waianae Intermediate School",
    "wof:placetype":"venue"
},
  "geometry": {"coordinates":[-158.19116600000001,21.449944],"type":"Point"}
}