{
  "type": "Feature",
  "properties": {
    "iso:country":"US",
    "sg:address":"677 Ala Moana Blvd",
    "sg:city":"Honolulu",
    "sg:classifiers":[
        {
            "category":"Travel",
            "subcategory":"Travel Agent",
            "type":"Entertainment"
        }
    ],
    "sg:phone":"+1 808 599 5581",
    "sg:postcode":"96813",
    "sg:province":"HI",
    "sg:tags":[
        "passenger",
        "transportation",
        "arrangement"
    ],
    "wof:name":"Transmarine Navigation Corp",
    "wof:placetype":"venue"
},
  "geometry": {"coordinates":[-157.86200500000001,21.297705],"type":"Point"}
}