{
  "type": "Feature",
  "properties": {
    "iso:country":"US",
    "sg:address":"1257 Kilauea Ave",
    "sg:city":"Hilo",
    "sg:classifiers":[
        {
            "category":"Utilities",
            "subcategory":"Cable",
            "type":"Services"
        }
    ],
    "sg:phone":"+1 808 932 2049",
    "sg:postcode":"96720",
    "sg:province":"HI",
    "sg:tags":[
        "television"
    ],
    "wof:name":"Oceanic Time Warner Cable",
    "wof:placetype":"venue"
},
  "geometry": {"coordinates":[-155.07626099999999,19.710175],"type":"Point"}
}