{
  "type": "Feature",
  "properties": {
    "iso:country":"US",
    "sg:address":"5629 Kuakini Hwy",
    "sg:city":"Kailua Kona",
    "sg:classifiers":[
        {
            "category":"Professional",
            "subcategory":"Art Services",
            "type":"Services"
        }
    ],
    "sg:phone":"+1 808 331 8845",
    "sg:postcode":"96740",
    "sg:province":"HI",
    "sg:tags":[
        "graphic",
        "designer"
    ],
    "wof:name":"Active Graphics",
    "wof:placetype":"venue"
},
  "geometry": {"coordinates":[-155.99807300000001,19.642574],"type":"Point"}
}