{
  "type": "Feature",
  "properties": {
    "iso:country":"US",
    "sg:address":"2759 Iolani St",
    "sg:city":"Makawao",
    "sg:classifiers":[
        {
            "category":"Manufacturing",
            "subcategory":"Printing",
            "type":"Manufacturing & Wholesale Goods"
        }
    ],
    "sg:phone":"+1 808 572 3418",
    "sg:postcode":"96768",
    "sg:province":"HI",
    "sg:tags":[
        "commercial"
    ],
    "wof:name":"Birds World",
    "wof:placetype":"venue"
},
  "geometry": {"coordinates":[-156.354119,20.844242],"type":"Point"}
}