{
  "type": "Feature",
  "properties": {
    "iso:country":"US",
    "sg:address":"95 Nakolo Pl",
    "sg:city":"Honolulu",
    "sg:classifiers":[
        {
            "category":"Airline",
            "type":"Transportation"
        }
    ],
    "sg:phone":"+1 808 834 7603",
    "sg:postcode":"96819",
    "sg:province":"HI",
    "sg:tags":[
        "air"
    ],
    "wof:name":"Air Kiribati Agency",
    "wof:placetype":"venue"
},
  "geometry": {"coordinates":[-157.91183599999999,21.319419],"type":"Point"}
}