{
  "type": "Feature",
  "properties": {
    "iso:country":"US",
    "sg:address":"53 N Puunene Ave",
    "sg:city":"Kahului",
    "sg:classifiers":[
        {
            "category":"Professional",
            "subcategory":"Management & Consulting",
            "type":"Services"
        }
    ],
    "sg:phone":"+1 808 871 1568",
    "sg:postcode":"96732",
    "sg:province":"HI",
    "sg:tags":[
        "consultant",
        "medical"
    ],
    "wof:name":"Intracorp",
    "wof:placetype":"venue"
},
  "geometry": {"coordinates":[-156.46781999999999,20.892406],"type":"Point"}
}