{
  "type": "Feature",
  "properties": {
    "iso:country":"US",
    "sg:address":"8722 Paradise Pkwy",
    "sg:city":"Ocean View",
    "sg:classifiers":[
        {
            "category":"Shopping",
            "type":"Retail Goods"
        }
    ],
    "sg:phone":"+1 808 939 7580",
    "sg:postcode":"96737",
    "sg:province":"HI",
    "sg:tags":[
        "candle"
    ],
    "wof:name":"Candleman",
    "wof:placetype":"venue"
},
  "geometry": {"coordinates":[-155.767414,19.096174],"type":"Point"}
}