{
  "type": "Feature",
  "properties": {
    "iso:country":"US",
    "sg:address":"840 Kawaiahao St",
    "sg:city":"Honolulu",
    "sg:classifiers":[
        {
            "category":"Home & Garden",
            "subcategory":"Building Materials",
            "type":"Retail Goods"
        }
    ],
    "sg:phone":"+1 808 591 0505",
    "sg:postcode":"96813",
    "sg:province":"HI",
    "sg:tags":[
        "lumber"
    ],
    "wof:name":"Makoa Mill Inc",
    "wof:placetype":"venue"
},
  "geometry": {"coordinates":[-157.85602,21.300691],"type":"Point"}
}