{
  "type": "Feature",
  "properties": {
    "addr:full":"521 Ala Moana Blvd Honolulu HI 96813",
    "addr:housenumber":"521",
    "addr:postcode":"96813",
    "addr:street":"Ala Moana Blvd",
    "iso:country":"US",
    "sg:address":"521 Ala Moana Blvd",
    "sg:city":"Honolulu",
    "sg:classifiers":[
        {
            "category":"Shopping",
            "subcategory":"Hobbies, Toys, & Games",
            "type":"Retail Goods"
        }
    ],
    "sg:phone":"+1 808 536 4387",
    "sg:postcode":"96813",
    "sg:province":"HI",
    "wof:name":"Jacks Handicraft Ltd",
    "wof:placetype":"venue"
},
  "geometry": {"coordinates":[-157.86303699999999,21.299438],"type":"Point"}
}