{
  "type": "Feature",
  "properties": {
    "iso:country":"US",
    "sg:address":"2927 Mokumoa St",
    "sg:city":"Honolulu",
    "sg:classifiers":[
        {
            "category":"Building & Trades",
            "subcategory":"Construction",
            "type":"Services"
        }
    ],
    "sg:phone":"+1 808 839 2781",
    "sg:postcode":"96819",
    "sg:province":"HI",
    "sg:tags":[
        "contractor"
    ],
    "sg:website":"www.walker-moody.com",
    "wof:name":"Walker-Moody Construction Co",
    "wof:placetype":"venue"
},
  "geometry": {"coordinates":[-157.895906,21.341189],"type":"Point"}
}