{
  "type": "Feature",
  "properties": {
    "addr:full":"2326 Kalihi St Honolulu HI 96819",
    "addr:housenumber":"2326",
    "addr:postcode":"96819",
    "addr:street":"Kalihi St",
    "iso:country":"US",
    "sg:address":"2326 Kalihi St",
    "sg:city":"Honolulu",
    "sg:classifiers":[
        {
            "category":"Food & Beverages",
            "subcategory":"Meat & Fish",
            "type":"Retail Goods"
        }
    ],
    "sg:phone":"+1 808 847 7298",
    "sg:postcode":"96819",
    "sg:province":"HI",
    "wof:name":"Kays Fish Market Inc",
    "wof:placetype":"venue"
},
  "geometry": {"coordinates":[-157.86246199999999,21.345522],"type":"Point"}
}