{
  "type": "Feature",
  "properties": {
    "addr:full":"111 E Puainako St Hilo HI 96720",
    "addr:housenumber":"111",
    "addr:postcode":"96720",
    "addr:street":"E Puainako St",
    "iso:country":"US",
    "sg:address":"111 E Puainako St",
    "sg:city":"Hilo",
    "sg:classifiers":[
        {
            "category":"Restaurant",
            "type":"Food & Drink"
        }
    ],
    "sg:phone":"+1 808 959 6481",
    "sg:postcode":"96720",
    "sg:province":"HI",
    "wof:name":"Mc Donald's",
    "wof:placetype":"venue"
},
  "geometry": {"coordinates":[-155.067306,19.695086],"type":"Point"}
}