{
  "type": "Feature",
  "properties": {
    "addr:full":"1199 Lumipolu St Waipahu HI 96797",
    "addr:housenumber":"1199",
    "addr:postcode":"96797",
    "addr:street":"Lumipolu St",
    "iso:country":"US",
    "sg:address":"1199 Lumipolu St",
    "sg:city":"Waipahu",
    "sg:classifiers":[
        {
            "category":"Building & Trades",
            "subcategory":"Landscaping Services",
            "type":"Services"
        }
    ],
    "sg:phone":"+1 808 671 7453",
    "sg:postcode":"96797",
    "sg:province":"HI",
    "sg:tags":[
        "landscape"
    ],
    "wof:name":"Francisco Alegria",
    "wof:placetype":"venue"
},
  "geometry": {"coordinates":[-157.99100200000001,21.407719],"type":"Point"}
}