{
  "type": "Feature",
  "properties": {
    "iso:country":"US",
    "sg:address":"1649 Kalakaua Ave",
    "sg:city":"Honolulu",
    "sg:classifiers":[
        {
            "category":"Shopping",
            "subcategory":"Clothing, Apparel, & Fashions",
            "type":"Retail Goods"
        }
    ],
    "sg:phone":"+1 808 941 7084",
    "sg:postcode":"96826",
    "sg:province":"HI",
    "sg:tags":[
        "alteration"
    ],
    "wof:name":"Aiko's Custom Taylor & Altrtns",
    "wof:placetype":"venue"
},
  "geometry": {"coordinates":[-157.83688900000001,21.293743],"type":"Point"}
}