{
  "type": "Feature",
  "properties": {
    "iso:country":"US",
    "sg:address":"48 Kapuai Pl",
    "sg:city":"Haleiwa",
    "sg:classifiers":[
        {
            "category":"Professional",
            "subcategory":"Art Services",
            "type":"Services"
        }
    ],
    "sg:phone":"+1 808 638 7719",
    "sg:postcode":"96712",
    "sg:province":"HI",
    "sg:tags":[
        "graphic",
        "design"
    ],
    "wof:name":"A Stroke of Pen",
    "wof:placetype":"venue"
},
  "geometry": {"coordinates":[-158.03568799999999,21.679579],"type":"Point"}
}