{
  "type": "Feature",
  "properties": {
    "iso:country":"US",
    "sg:address":"824 Hiliu Pl",
    "sg:city":"Aiea",
    "sg:classifiers":[
        {
            "category":"Wholesale",
            "subcategory":"Sporting Goods",
            "type":"Manufacturing & Wholesale Goods"
        }
    ],
    "sg:phone":"+1 808 488 0058",
    "sg:postcode":"96701",
    "sg:province":"HI",
    "wof:name":"International Logo Design Co",
    "wof:placetype":"venue"
},
  "geometry": {"coordinates":[-157.93077,21.403243],"type":"Point"}
}