{
  "type": "Feature",
  "properties": {
    "iso:country":"US",
    "sg:address":"7394 Mamalahoa Hwy",
    "sg:city":"Kealakekua",
    "sg:classifiers":[
        {
            "category":"Food & Beverages",
            "subcategory":"Bakery",
            "type":"Retail Goods"
        }
    ],
    "sg:phone":"+1 808 322 3688",
    "sg:postcode":"96750",
    "sg:province":"HI",
    "sg:tags":[
        "baker"
    ],
    "wof:name":"Standard Bakery Inc",
    "wof:placetype":"venue"
},
  "geometry": {"coordinates":[-155.92884699999999,19.539509],"type":"Point"}
}