{
  "type": "Feature",
  "properties": {
    "iso:country":"US",
    "sg:address":"1093 Makamaka St",
    "sg:city":"Kailua Kona",
    "sg:classifiers":[
        {
            "category":"Building & Trades",
            "subcategory":"Cleaning & Sanitation",
            "type":"Services"
        }
    ],
    "sg:phone":"+1 808 960 8688",
    "sg:postcode":"96740",
    "sg:province":"HI",
    "sg:tags":[
        "window"
    ],
    "wof:name":"Aloha Window Cleaning",
    "wof:placetype":"venue"
},
  "geometry": {"coordinates":[-156.01585,19.72326],"type":"Point"}
}