{
  "type": "Feature",
  "properties": {
    "iso:country":"US",
    "sg:address":"1010 S King St",
    "sg:city":"Honolulu",
    "sg:classifiers":[
        {
            "category":"Personal",
            "subcategory":"Beauty Salon",
            "type":"Services"
        }
    ],
    "sg:phone":"+1 808 721 8322",
    "sg:postcode":"96814",
    "sg:province":"HI",
    "sg:tags":[
        "manicuring"
    ],
    "wof:name":"A Pedicure Haven",
    "wof:placetype":"venue"
},
  "geometry": {"coordinates":[-157.845823,21.300537],"type":"Point"}
}