{
  "type": "Feature",
  "properties": {
    "iso:country":"US",
    "sg:address":"300 Ohukai Rd",
    "sg:city":"Kihei",
    "sg:classifiers":[
        {
            "category":"Banks & Credit Unions",
            "subcategory":"Bank",
            "type":"Services"
        }
    ],
    "sg:phone":"+1 808 875 0770",
    "sg:postcode":"96753",
    "sg:province":"HI",
    "sg:tags":[
        "loan",
        "real estate"
    ],
    "wof:name":"Mortgage Store",
    "wof:placetype":"venue"
},
  "geometry": {"coordinates":[-156.454159,20.775451],"type":"Point"}
}