{
  "type": "Feature",
  "properties": {
    "addr:full":"2619 S Kihei Rd Kihei HI 96753",
    "addr:housenumber":"2619",
    "addr:postcode":"96753",
    "addr:street":"S Kihei Rd",
    "iso:country":"US",
    "sg:address":"2619 S Kihei Rd",
    "sg:city":"Kihei",
    "sg:classifiers":[
        {
            "category":"Real Estate",
            "subcategory":"Real Estate Agent",
            "type":"Services"
        }
    ],
    "sg:phone":"+1 808 879 8111",
    "sg:postcode":"96753",
    "sg:province":"HI",
    "sg:tags":[
        "broker"
    ],
    "wof:name":"Villiers Real Estate Inc",
    "wof:placetype":"venue"
},
  "geometry": {"coordinates":[-156.445436,20.713402],"type":"Point"}
}