{
  "type": "Feature",
  "properties": {
    "iso:country":"US",
    "sg:address":"1247 Kaahumanu St",
    "sg:city":"Aiea",
    "sg:classifiers":[
        {
            "category":"Professional",
            "subcategory":"Management & Consulting",
            "type":"Services"
        }
    ],
    "sg:phone":"+1 808 487 1585",
    "sg:postcode":"96701",
    "sg:province":"HI",
    "sg:tags":[
        "consultant"
    ],
    "wof:name":"Ergonomic Consultants - Hawaii",
    "wof:placetype":"venue"
},
  "geometry": {"coordinates":[-157.953833,21.388047],"type":"Point"}
}