{
  "type": "Feature",
  "properties": {
    "addr:full":"1165 Makamae St Kaneohe HI 96744",
    "addr:housenumber":"1165",
    "addr:postcode":"96744",
    "addr:street":"Makamae St",
    "iso:country":"US",
    "sg:address":"1165 Makamae St",
    "sg:city":"Kaneohe",
    "sg:classifiers":[
        {
            "category":"Wholesale",
            "subcategory":"Electrical",
            "type":"Manufacturing & Wholesale Goods"
        }
    ],
    "sg:phone":"+1 808 247 2076",
    "sg:postcode":"96744",
    "sg:province":"HI",
    "sg:tags":[
        "fire",
        "equipment",
        "protection"
    ],
    "wof:name":"SRG Fire Svc",
    "wof:placetype":"venue"
},
  "geometry": {"coordinates":[-157.79848899999999,21.420682],"type":"Point"}
}