{
  "type": "Feature",
  "properties": {
    "iso:country":"US",
    "sg:address":"423 Kamakee St",
    "sg:city":"Honolulu",
    "sg:classifiers":[
        {
            "category":"Organizations",
            "subcategory":"Religious Organization",
            "type":"Services"
        }
    ],
    "sg:phone":"+1 808 592 2300",
    "sg:postcode":"96814",
    "sg:province":"HI",
    "wof:name":"His Highest Praise Honolulu",
    "wof:placetype":"venue"
},
  "geometry": {"coordinates":[-157.850731,21.29523],"type":"Point"}
}