{
  "type": "Feature",
  "properties": {
    "iso:country":"US",
    "sg:address":"1064 Kuhaulua St",
    "sg:city":"Waipahu",
    "sg:classifiers":[
        {
            "category":"Building & Trades",
            "subcategory":"Landscaping Services",
            "type":"Services"
        }
    ],
    "sg:phone":"+1 808 677 7175",
    "sg:postcode":"96797",
    "sg:province":"HI",
    "sg:tags":[
        "landscape",
        "contractor"
    ],
    "wof:name":"Cfc Landscaping & Mntnc Svc",
    "wof:placetype":"venue"
},
  "geometry": {"coordinates":[-158.01112699999999,21.393976],"type":"Point"}
}