{
  "type": "Feature",
  "properties": {
    "iso:country":"US",
    "sg:address":"84 Kamehameha Hwy",
    "sg:city":"Aiea",
    "sg:classifiers":[
        {
            "category":"Professional",
            "subcategory":"Accounting & Tax Preparation",
            "type":"Services"
        }
    ],
    "sg:phone":"+1 808 484 4808",
    "sg:postcode":"96701",
    "sg:province":"HI",
    "sg:tags":[
        "return",
        "filing"
    ],
    "wof:name":"Sybil Nosaka",
    "wof:placetype":"venue"
},
  "geometry": {"coordinates":[-157.94782699999999,21.384302],"type":"Point"}
}