{
  "type": "Feature",
  "properties": {
    "addr:full":"2511 S Kihei Rd Kihei HI 96753",
    "addr:housenumber":"2511",
    "addr:postcode":"96753",
    "addr:street":"S Kihei Rd",
    "iso:country":"US",
    "sg:address":"2511 S Kihei Rd",
    "sg:city":"Kihei",
    "sg:classifiers":[
        {
            "category":"Restaurant",
            "type":"Food & Drink"
        }
    ],
    "sg:phone":"+1 808 879 9330",
    "sg:postcode":"96753",
    "sg:province":"HI",
    "wof:name":"Greek Bistro",
    "wof:placetype":"venue"
},
  "geometry": {"coordinates":[-156.44684899999999,20.720141],"type":"Point"}
}