{
  "type": "Feature",
  "properties": {
    "addr:full":"4348 Laui St Kailua Kona HI 96740",
    "addr:housenumber":"4348",
    "addr:postcode":"96740",
    "addr:street":"Laui St",
    "iso:country":"US",
    "sg:address":"4348 Laui St",
    "sg:city":"Kailua Kona",
    "sg:classifiers":[
        {
            "category":"Farming",
            "subcategory":"Nursery",
            "type":"Manufacturing & Wholesale Goods"
        }
    ],
    "sg:phone":"+1 808 329 6770",
    "sg:postcode":"96740",
    "sg:province":"HI",
    "sg:tags":[
        "ornamental"
    ],
    "wof:name":"Tropical Breeze Orchid Farm Tr",
    "wof:placetype":"venue"
},
  "geometry": {"coordinates":[-156.02634,19.72555],"type":"Point"}
}