{
  "type": "Feature",
  "properties": {
    "iso:country":"US",
    "sg:address":"208 Hoewaa Pl",
    "sg:city":"Kapolei",
    "sg:classifiers":[
        {
            "category":"Shopping",
            "type":"Retail Goods"
        }
    ],
    "sg:phone":"+1 808 674 2021",
    "sg:postcode":"96707",
    "sg:province":"HI",
    "sg:tags":[
        "merchandise"
    ],
    "wof:name":"Ruff Marlena",
    "wof:placetype":"venue"
},
  "geometry": {"coordinates":[-158.05964599999999,21.335398],"type":"Point"}
}