{
  "type": "Feature",
  "properties": {
    "addr:full":"401 Waiakamilo Rd Honolulu HI 96817",
    "addr:housenumber":"401",
    "addr:postcode":"96817",
    "addr:street":"Waiakamilo Rd",
    "iso:country":"US",
    "sg:address":"401 Waiakamilo Rd",
    "sg:city":"Honolulu",
    "sg:classifiers":[
        {
            "category":"Organizations",
            "subcategory":"Religious Organization",
            "type":"Services"
        }
    ],
    "sg:phone":"+1 808 845 2455",
    "sg:postcode":"96817",
    "sg:province":"HI",
    "sg:tags":[
        "church"
    ],
    "sg:website":"www.superiorliving.org",
    "wof:name":"Pacific Revival Ctr",
    "wof:placetype":"venue"
},
  "geometry": {"coordinates":[-157.87635,21.323254],"type":"Point"}
}