{
  "type": "Feature",
  "properties": {
    "addr:full":"229 Kaulike Dr Pearl City HI 96782",
    "addr:housenumber":"229",
    "addr:postcode":"96782",
    "addr:street":"Kaulike Dr",
    "iso:country":"US",
    "sg:address":"229 Kaulike Dr",
    "sg:city":"Pearl City",
    "sg:classifiers":[
        {
            "category":"Retail",
            "subcategory":"Laundry & Dry Cleaning",
            "type":"Services"
        }
    ],
    "sg:phone":"+1 808 486 3100",
    "sg:postcode":"96782",
    "sg:province":"HI",
    "sg:tags":[
        "cleaners",
        "rug",
        "carpet"
    ],
    "wof:name":"Fibre-Pro",
    "wof:placetype":"venue"
},
  "geometry": {"coordinates":[-157.956479,21.390333],"type":"Point"}
}