{
  "type": "Feature",
  "properties": {
    "addr:full":"2815 Kaihikapu St Honolulu HI 96819",
    "addr:housenumber":"2815",
    "addr:postcode":"96819",
    "addr:street":"Kaihikapu St",
    "iso:country":"US",
    "sg:address":"2815 Kaihikapu St",
    "sg:city":"Honolulu",
    "sg:classifiers":[
        {
            "category":"Building & Trades",
            "subcategory":"Construction",
            "type":"Services"
        }
    ],
    "sg:phone":"+1 808 836 6288",
    "sg:postcode":"96819",
    "sg:province":"HI",
    "sg:tags":[
        "home",
        "builder"
    ],
    "wof:name":"Island Cedar Source",
    "wof:placetype":"venue"
},
  "geometry": {"coordinates":[-157.89974900000001,21.340513],"type":"Point"}
}