{
  "type": "Feature",
  "properties": {
    "iso:country":"US",
    "sg:address":"1360 S Beretania St",
    "sg:city":"Honolulu",
    "sg:classifiers":[
        {
            "category":"Professional",
            "subcategory":"Accounting & Tax Preparation",
            "type":"Services"
        }
    ],
    "sg:phone":"+1 808 538 3232",
    "sg:postcode":"96814",
    "sg:province":"HI",
    "sg:tags":[
        "billing"
    ],
    "wof:name":"Professional Management Group",
    "wof:placetype":"venue"
},
  "geometry": {"coordinates":[-157.83967200000001,21.30038],"type":"Point"}
}