{
  "type": "Feature",
  "properties": {
    "addr:full":"128 Palakamana St Waianae HI 96792",
    "addr:housenumber":"128",
    "addr:postcode":"96792",
    "addr:street":"Palakamana St",
    "iso:country":"US",
    "sg:address":"128 Palakamana St",
    "sg:city":"Waianae",
    "sg:classifiers":[
        {
            "category":"Building & Trades",
            "subcategory":"Equipment Rental",
            "type":"Services"
        }
    ],
    "sg:phone":"+1 808 696 4522",
    "sg:postcode":"96792",
    "sg:province":"HI",
    "sg:tags":[
        "party",
        "supply"
    ],
    "wof:name":"Ko's Party Rentals",
    "wof:placetype":"venue"
},
  "geometry": {"coordinates":[-158.175588,21.417696],"type":"Point"}
}