{
  "type": "Feature",
  "properties": {
    "iso:country":"US",
    "sg:address":"55 Ulumalu Rd",
    "sg:city":"Haiku",
    "sg:classifiers":[
        {
            "category":"Professional",
            "subcategory":"Employment Agencies",
            "type":"Services"
        }
    ],
    "sg:phone":"+1 808 573 6107",
    "sg:postcode":"96708",
    "sg:province":"HI",
    "sg:tags":[
        "modeling"
    ],
    "wof:name":"Hawaii Sports Models",
    "wof:placetype":"venue"
},
  "geometry": {"coordinates":[-156.28876299999999,20.924945],"type":"Point"}
}