{
  "type": "Feature",
  "properties": {
    "addr:full":"104 Haili St Hilo HI 96720",
    "addr:housenumber":"104",
    "addr:postcode":"96720",
    "addr:street":"Haili St",
    "iso:country":"US",
    "sg:address":"104 Haili St",
    "sg:city":"Hilo",
    "sg:classifiers":[
        {
            "category":"Personal",
            "subcategory":"Beauty Salon",
            "type":"Services"
        }
    ],
    "sg:phone":"+1 808 934 8771",
    "sg:postcode":"96720",
    "sg:province":"HI",
    "sg:tags":[
        "shop"
    ],
    "wof:name":"Headline News",
    "wof:placetype":"venue"
},
  "geometry": {"coordinates":[-155.08689699999999,19.724142],"type":"Point"}
}