{
  "type": "Feature",
  "properties": {
    "iso:country":"US",
    "sg:address":"674 Kainalu Pl",
    "sg:city":"Wailuku",
    "sg:classifiers":[
        {
            "category":"Building & Trades",
            "subcategory":"Landscaping Services",
            "type":"Services"
        }
    ],
    "sg:phone":"+1 808 244 1426",
    "sg:postcode":"96793",
    "sg:province":"HI",
    "wof:name":"Maui Lawn & Landscape LLC",
    "wof:placetype":"venue"
},
  "geometry": {"coordinates":[-156.48350400000001,20.903943],"type":"Point"}
}