{
  "type": "Feature",
  "properties": {
    "iso:country":"US",
    "sg:address":"823 California Ave",
    "sg:city":"Wahiawa",
    "sg:classifiers":[
        {
            "category":"Restaurant",
            "type":"Food & Drink"
        }
    ],
    "sg:phone":"+1 808 622 6688",
    "sg:postcode":"96786",
    "sg:province":"HI",
    "sg:tags":[
        "eating"
    ],
    "wof:name":"Wok & Grill Express",
    "wof:placetype":"venue"
},
  "geometry": {"coordinates":[-158.02632500000001,21.497263],"type":"Point"}
}