{
  "type": "Feature",
  "properties": {
    "iso:country":"US",
    "sg:address":"271 Pupukoae St",
    "sg:city":"Waipahu",
    "sg:classifiers":[
        {
            "category":"Retail",
            "subcategory":"Laundry & Dry Cleaning",
            "type":"Services"
        }
    ],
    "sg:phone":"+1 808 676 9175",
    "sg:postcode":"96797",
    "sg:province":"HI",
    "wof:name":"Art & Ron Cleaning & Maintenan",
    "wof:placetype":"venue"
},
  "geometry": {"coordinates":[-158.01921200000001,21.38334],"type":"Point"}
}