{
  "type": "Feature",
  "properties": {
    "iso:country":"US",
    "sg:address":"702 Manawahine Pl",
    "sg:city":"Mililani",
    "sg:classifiers":[
        {
            "category":"Professional",
            "subcategory":"Business Services",
            "type":"Services"
        },
        {
            "category":"Building & Trades",
            "subcategory":"Construction",
            "type":"Services"
        }
    ],
    "sg:phone":"+1 808 625 2236",
    "sg:postcode":"96789",
    "sg:province":"HI",
    "sg:tags":[
        "coping",
        "plastering",
        "tiling",
        "pool",
        "swimming"
    ],
    "wof:name":"Blu Eel Pool & Spa Service",
    "wof:placetype":"venue"
},
  "geometry": {"coordinates":[-158.02667700000001,21.436132],"type":"Point"}
}