{
  "type": "Feature",
  "properties": {
    "addr:full":"810 Kokomo Rd Haiku HI 96708",
    "addr:postcode":"96708",
    "addr:street":"810 Kokomo Rd",
    "iso:country":"US",
    "sg:address":"810 Kokomo Rd",
    "sg:city":"Haiku",
    "sg:classifiers":[
        {
            "category":"Retail",
            "subcategory":"Repair Shop",
            "type":"Services"
        }
    ],
    "sg:phone":"+1 808 575 9432",
    "sg:postcode":"96708",
    "sg:province":"HI",
    "sg:tags":[
        "upholsterer"
    ],
    "wof:name":"Sew On-N-Sew Forth",
    "wof:placetype":"venue"
},
  "geometry": {"coordinates":[-156.31251399999999,20.880446],"type":"Point"}
}