{
  "type": "Feature",
  "properties": {
    "iso:country":"US",
    "sg:address":"1778 Ala Moana Blvd",
    "sg:city":"Honolulu",
    "sg:classifiers":[
        {
            "category":"Health Services",
            "subcategory":"Doctor",
            "type":"Services"
        }
    ],
    "sg:phone":"+1 808 941 3307",
    "sg:postcode":"96815",
    "sg:province":"HI",
    "sg:tags":[
        "clinic"
    ],
    "wof:name":"Discovery Bay Medical Clinic",
    "wof:placetype":"venue"
},
  "geometry": {"coordinates":[-157.83809199999999,21.28498],"type":"Point"}
}