{
  "type": "Feature",
  "properties": {
    "iso:country":"US",
    "sg:address":"1006 Awawamalu St",
    "sg:city":"Honolulu",
    "sg:classifiers":[
        {
            "category":"Professional",
            "subcategory":"Accounting & Tax Preparation",
            "type":"Services"
        }
    ],
    "sg:phone":"+1 808 395 3045",
    "sg:postcode":"96825",
    "sg:province":"HI",
    "sg:tags":[
        "bookkeeping",
        "general"
    ],
    "wof:name":"Blake Bookkeeping Inc",
    "wof:placetype":"venue"
},
  "geometry": {"coordinates":[-157.68508,21.305654],"type":"Point"}
}