{
  "type": "Feature",
  "properties": {
    "iso:country":"US",
    "sg:address":"1993 S Kihei Rd",
    "sg:city":"Kihei",
    "sg:classifiers":[
        {
            "category":"Retail",
            "subcategory":"Laundry & Dry Cleaning",
            "type":"Services"
        }
    ],
    "sg:phone":"+1 808 875 7799",
    "sg:postcode":"96753",
    "sg:province":"HI",
    "sg:tags":[
        "cleaners",
        "rug",
        "carpet"
    ],
    "wof:name":"Aloha Carpet Cleaners",
    "wof:placetype":"venue"
},
  "geometry": {"coordinates":[-156.45172600000001,20.730935],"type":"Point"}
}