{
  "type": "Feature",
  "properties": {
    "iso:country":"US",
    "sg:address":"1173 Iwaena St",
    "sg:city":"Aiea",
    "sg:classifiers":[
        {
            "category":"Building & Trades",
            "subcategory":"Plumbing",
            "type":"Services"
        }
    ],
    "sg:phone":"+1 808 926 2999",
    "sg:postcode":"96701",
    "sg:province":"HI",
    "sg:tags":[
        "plumbing",
        "contractor"
    ],
    "wof:name":"Mr Rooter",
    "wof:placetype":"venue"
},
  "geometry": {"coordinates":[-157.908637,21.379362],"type":"Point"}
}