{
  "type": "Feature",
  "properties": {
    "addr:full":"441 Hoopala St Kaneohe HI 96744",
    "addr:housenumber":"441",
    "addr:postcode":"96744",
    "addr:street":"Hoopala St",
    "iso:country":"US",
    "sg:address":"441 Hoopala St",
    "sg:city":"Kaneohe",
    "sg:classifiers":[
        {
            "category":"Health Services",
            "subcategory":"Health Practitioner",
            "type":"Services"
        }
    ],
    "sg:phone":"+1 808 239 8255",
    "sg:postcode":"96744",
    "sg:province":"HI",
    "wof:name":"Oliveira Berry Jill",
    "wof:placetype":"venue"
},
  "geometry": {"coordinates":[-157.837501,21.445572],"type":"Point"}
}