{
  "type": "Feature",
  "properties": {
    "addr:full":"1649 Kalakaua Ave Honolulu HI 96826",
    "addr:housenumber":"1649",
    "addr:postcode":"96826",
    "addr:street":"Kalakaua Ave",
    "iso:country":"US",
    "sg:address":"1649 Kalakaua Ave",
    "sg:city":"Honolulu",
    "sg:classifiers":[
        {
            "category":"Social Services",
            "subcategory":"Child Care",
            "type":"Services"
        }
    ],
    "sg:phone":"+1 808 942 3595",
    "sg:postcode":"96826",
    "sg:province":"HI",
    "sg:tags":[
        "day"
    ],
    "wof:name":"Easy Computer Learning CT",
    "wof:placetype":"venue"
},
  "geometry": {"coordinates":[-157.83688900000001,21.293743],"type":"Point"}
}