{
  "type": "Feature",
  "properties": {
    "iso:country":"US",
    "sg:address":"525 Cummins St",
    "sg:city":"Honolulu",
    "sg:classifiers":[
        {
            "category":"Wholesale",
            "subcategory":"Durable Goods & Equipment",
            "type":"Manufacturing & Wholesale Goods"
        }
    ],
    "sg:phone":"+1 808 597 8099",
    "sg:postcode":"96814",
    "sg:province":"HI",
    "sg:tags":[
        "importer"
    ],
    "wof:name":"Maiden Limited",
    "wof:placetype":"venue"
},
  "geometry": {"coordinates":[-157.85198700000001,21.296945],"type":"Point"}
}