{
  "type": "Feature",
  "properties": {
    "iso:country":"US",
    "sg:address":"117 Aikahi Loop",
    "sg:city":"Kailua",
    "sg:classifiers":[
        {
            "category":"Shopping",
            "type":"Retail Goods"
        }
    ],
    "sg:phone":"+1 808 254 6880",
    "sg:postcode":"96734",
    "sg:province":"HI",
    "sg:tags":[
        "merchandise"
    ],
    "wof:name":"Laura Crewe",
    "wof:placetype":"venue"
},
  "geometry": {"coordinates":[-157.74917099999999,21.428087],"type":"Point"}
}