{
  "type": "Feature",
  "properties": {
    "addr:full":"1510 Kamehameha Hwy Wahiawa HI 96786",
    "addr:housenumber":"1510",
    "addr:postcode":"96786",
    "addr:street":"Kamehameha Hwy",
    "iso:country":"US",
    "sg:address":"1510 Kamehameha Hwy",
    "sg:city":"Wahiawa",
    "sg:classifiers":[
        {
            "category":"Organizations",
            "subcategory":"Community Association",
            "type":"Services"
        }
    ],
    "sg:phone":"+1 808 622 3929",
    "sg:postcode":"96786",
    "sg:province":"HI",
    "sg:tags":[
        "social"
    ],
    "wof:name":"Anuenue Hale",
    "wof:placetype":"venue"
},
  "geometry": {"coordinates":[-158.041831,21.534975],"type":"Point"}
}