{
  "type": "Feature",
  "properties": {
    "iso:country":"US",
    "sg:address":"614 Cooke St",
    "sg:city":"Honolulu",
    "sg:classifiers":[
        {
            "category":"Shopping",
            "subcategory":"Computers & Home Electronics",
            "type":"Retail Goods"
        }
    ],
    "sg:phone":"+1 808 593 2070",
    "sg:postcode":"96813",
    "sg:province":"HI",
    "sg:tags":[
        "system"
    ],
    "wof:name":"At Home Theater Of Hawaii",
    "wof:placetype":"venue"
},
  "geometry": {"coordinates":[-157.85728399999999,21.29985],"type":"Point"}
}