{
  "type": "Feature",
  "properties": {
    "addr:full":"3060 Eiwa St Lihue HI 96766",
    "addr:housenumber":"3060",
    "addr:postcode":"96766",
    "addr:street":"Eiwa St",
    "iso:country":"US",
    "sg:address":"3060 Eiwa St",
    "sg:city":"Lihue",
    "sg:classifiers":[
        {
            "category":"Government",
            "subcategory":"Office",
            "type":"Public Place"
        }
    ],
    "sg:phone":"+1 808 274 3300",
    "sg:postcode":"96766",
    "sg:province":"HI",
    "sg:tags":[
        "state",
        "resource"
    ],
    "wof:name":"Human Services Dept",
    "wof:placetype":"venue"
},
  "geometry": {"coordinates":[-159.36749399999999,21.976093],"type":"Point"}
}