{
  "type": "Feature",
  "properties": {
    "iso:country":"US",
    "sg:address":"625 Iliaina St",
    "sg:city":"Kailua",
    "sg:classifiers":[
        {
            "category":"Professional",
            "subcategory":"Management & Consulting",
            "type":"Services"
        }
    ],
    "sg:phone":"+1 808 254 3834",
    "sg:postcode":"96734",
    "sg:province":"HI",
    "sg:tags":[
        "consultant",
        "business"
    ],
    "wof:name":"Nancy Deeley & Assoc",
    "wof:placetype":"venue"
},
  "geometry": {"coordinates":[-157.755753,21.410182],"type":"Point"}
}