{
  "type": "Feature",
  "properties": {
    "addr:full":"1230 Waiua Pl Aiea HI 96701",
    "addr:housenumber":"1230",
    "addr:postcode":"96701",
    "addr:street":"Waiua Pl",
    "iso:country":"US",
    "sg:address":"1230 Waiua Pl",
    "sg:city":"Aiea",
    "sg:classifiers":[
        {
            "category":"Wholesale",
            "subcategory":"Machinery & Supplies",
            "type":"Manufacturing & Wholesale Goods"
        }
    ],
    "sg:phone":"+1 808 841 8063",
    "sg:postcode":"96701",
    "sg:province":"HI",
    "sg:tags":[
        "vacuum",
        "janitorial",
        "system",
        "cleaning"
    ],
    "wof:name":"Schubert Sanitary Supply",
    "wof:placetype":"venue"
},
  "geometry": {"coordinates":[-157.905418,21.373683],"type":"Point"}
}