{
  "type": "Feature",
  "properties": {
    "addr:full":"2752 Woodlawn Dr Honolulu HI 96822",
    "addr:housenumber":"2752",
    "addr:postcode":"96822",
    "addr:street":"Woodlawn Dr",
    "iso:country":"US",
    "sg:address":"2752 Woodlawn Dr",
    "sg:city":"Honolulu",
    "sg:classifiers":[
        {
            "category":"Real Estate",
            "subcategory":"Real Estate Agent",
            "type":"Services"
        }
    ],
    "sg:phone":"+1 808 988 2102",
    "sg:postcode":"96822",
    "sg:province":"HI",
    "wof:name":"Century 21",
    "wof:placetype":"venue"
},
  "geometry": {"coordinates":[-157.810046,21.307362],"type":"Point"}
}