{
  "type": "Feature",
  "properties": {
    "iso:country":"US",
    "sg:address":"930 Kaheka St",
    "sg:city":"Honolulu",
    "sg:classifiers":[
        {
            "category":"Restaurant",
            "type":"Food & Drink"
        }
    ],
    "sg:phone":"+1 808 946 2991",
    "sg:postcode":"96814",
    "sg:province":"HI",
    "sg:tags":[
        "eating"
    ],
    "wof:name":"Suekko",
    "wof:placetype":"venue"
},
  "geometry": {"coordinates":[-157.83902,21.295577],"type":"Point"}
}