{
  "type": "Feature",
  "properties": {
    "addr:full":"966 Kaheka St Honolulu HI 96814",
    "addr:housenumber":"966",
    "addr:postcode":"96814",
    "addr:street":"Kaheka St",
    "iso:country":"US",
    "sg:address":"966 Kaheka St",
    "sg:city":"Honolulu",
    "sg:classifiers":[
        {
            "category":"Shopping",
            "subcategory":"Pharmacy",
            "type":"Retail Goods"
        }
    ],
    "sg:phone":"+1 808 945 7875",
    "sg:postcode":"96814",
    "sg:province":"HI",
    "sg:tags":[
        "drug",
        "store"
    ],
    "wof:name":"City Pharmacies Inc",
    "wof:placetype":"venue"
},
  "geometry": {"coordinates":[-157.838223,21.297459],"type":"Point"}
}