{
  "type": "Feature",
  "properties": {
    "iso:country":"US",
    "sg:address":"25 Noolu St",
    "sg:city":"Kihei",
    "sg:classifiers":[
        {
            "category":"Building & Trades",
            "subcategory":"Landscaping Services",
            "type":"Services"
        }
    ],
    "sg:phone":"+1 808 874 1847",
    "sg:postcode":"96753",
    "sg:province":"HI",
    "sg:tags":[
        "landscape",
        "contractor"
    ],
    "wof:name":"Maui Turf Landscaping Inc",
    "wof:placetype":"venue"
},
  "geometry": {"coordinates":[-156.45029700000001,20.757738],"type":"Point"}
}