{
  "type": "Feature",
  "properties": {
    "addr:full":"436 Hihimanu St Waimanalo HI 96795",
    "addr:housenumber":"436",
    "addr:postcode":"96795",
    "addr:street":"Hihimanu St",
    "iso:country":"US",
    "sg:address":"436 Hihimanu St",
    "sg:city":"Waimanalo",
    "sg:classifiers":[
        {
            "category":"Wholesale",
            "subcategory":"Plants",
            "type":"Manufacturing & Wholesale Goods"
        }
    ],
    "sg:phone":"+1 808 259 7295",
    "sg:postcode":"96795",
    "sg:province":"HI",
    "sg:tags":[
        "nursery",
        "tree",
        "supply"
    ],
    "wof:name":"Hawaiian Sunshine Nursery Inc",
    "wof:placetype":"venue"
},
  "geometry": {"coordinates":[-157.71610200000001,21.341407],"type":"Point"}
}