{
  "type": "Feature",
  "properties": {
    "iso:country":"US",
    "sg:address":"3521 Nuuanu Pali Dr",
    "sg:city":"Honolulu",
    "sg:classifiers":[
        {
            "category":"Real Estate",
            "subcategory":"Real Estate Operator",
            "type":"Services"
        }
    ],
    "sg:phone":"+1 808 599 6229",
    "sg:postcode":"96817",
    "sg:province":"HI",
    "sg:tags":[
        "property",
        "lessor"
    ],
    "wof:name":"Kamuela Associates LLC",
    "wof:placetype":"venue"
},
  "geometry": {"coordinates":[-157.83143699999999,21.342286],"type":"Point"}
}