{
  "type": "Feature",
  "properties": {
    "iso:country":"US",
    "sg:address":"1016 Komo Mai Dr",
    "sg:city":"Aiea",
    "sg:classifiers":[
        {
            "category":"Education",
            "subcategory":"School",
            "type":"Public Place"
        }
    ],
    "sg:phone":"+1 808 524 0846",
    "sg:postcode":"96701",
    "sg:province":"HI",
    "wof:name":"Calvary Chapel Christian",
    "wof:placetype":"venue"
},
  "geometry": {"coordinates":[-157.948599,21.401034],"type":"Point"}
}