{
  "type": "Feature",
  "properties": {
    "addr:full":"146 Hekili St Kailua HI 96734",
    "addr:housenumber":"146",
    "addr:postcode":"96734",
    "addr:street":"Hekili St",
    "iso:country":"US",
    "sg:address":"146 Hekili St",
    "sg:city":"Kailua",
    "sg:classifiers":[
        {
            "category":"Health Services",
            "subcategory":"Nursing And Care Facility",
            "type":"Services"
        },
        {
            "category":"Health Services",
            "subcategory":"Health Practitioner",
            "type":"Services"
        }
    ],
    "sg:phone":"+1 808 261 7676",
    "sg:postcode":"96734",
    "sg:province":"HI",
    "sg:tags":[
        "nurse",
        "skilled",
        "registry"
    ],
    "wof:name":"Specialized Nursing Svc Inc",
    "wof:placetype":"venue"
},
  "geometry": {"coordinates":[-157.743504,21.392444],"type":"Point"}
}