{
  "type": "Feature",
  "properties": {
    "addr:full":"207 Kamehameha Hwy Hauula HI 96717",
    "addr:housenumber":"207",
    "addr:postcode":"96717",
    "addr:street":"Kamehameha Hwy",
    "iso:country":"US",
    "sg:address":"207 Kamehameha Hwy",
    "sg:city":"Hauula",
    "sg:classifiers":[
        {
            "category":"Farming",
            "subcategory":"Farm",
            "type":"Manufacturing & Wholesale Goods"
        }
    ],
    "sg:phone":"+1 808 531 8181",
    "sg:postcode":"96717",
    "sg:province":"HI",
    "wof:name":"Koolau Agricultural Co LTD",
    "wof:placetype":"venue"
},
  "geometry": {"coordinates":[-157.91330500000001,21.615413],"type":"Point"}
}