{
  "type": "Feature",
  "properties": {
    "iso:country":"US",
    "sg:address":"319 Wyllie St",
    "sg:city":"Honolulu",
    "sg:classifiers":[
        {
            "category":"Education",
            "subcategory":"School",
            "type":"Public Place"
        }
    ],
    "sg:phone":"+1 808 595 5400",
    "sg:postcode":"96817",
    "sg:province":"HI",
    "wof:name":"Maemae School",
    "wof:placetype":"venue"
},
  "geometry": {"coordinates":[-157.847264,21.328903],"type":"Point"}
}