{
  "type": "Feature",
  "properties": {
    "iso:country":"US",
    "sg:address":"129 Poailani Cir",
    "sg:city":"Waipahu",
    "sg:classifiers":[
        {
            "category":"Personal",
            "subcategory":"Adult",
            "type":"Services"
        }
    ],
    "sg:phone":"+1 808 671 6543",
    "sg:postcode":"96797",
    "sg:province":"HI",
    "wof:name":"Dating Evaresto",
    "wof:placetype":"venue"
},
  "geometry": {"coordinates":[-157.99492499999999,21.385613],"type":"Point"}
}