{
  "type": "Feature",
  "properties": {
    "iso:country":"US",
    "sg:address":"1312 Kuhio Hwy",
    "sg:city":"Kapaa",
    "sg:classifiers":[
        {
            "category":"Manufacturing",
            "subcategory":"Apparel",
            "type":"Manufacturing & Wholesale Goods"
        }
    ],
    "sg:phone":"+1 808 822 3513",
    "sg:postcode":"96746",
    "sg:province":"HI",
    "wof:name":"Ho Dondi",
    "wof:placetype":"venue"
},
  "geometry": {"coordinates":[-159.31877399999999,22.074698],"type":"Point"}
}