{
  "type": "Feature",
  "properties": {
    "addr:full":"235 Nene St Hilo HI 96720",
    "addr:housenumber":"235",
    "addr:postcode":"96720",
    "addr:street":"Nene St",
    "iso:country":"US",
    "sg:address":"235 Nene St",
    "sg:city":"Hilo",
    "sg:classifiers":[
        {
            "category":"Professional",
            "subcategory":"Detective & Security Services",
            "type":"Services"
        }
    ],
    "sg:phone":"+1 808 969 1743",
    "sg:postcode":"96720",
    "sg:province":"HI",
    "sg:tags":[
        "investigator"
    ],
    "wof:name":"Legal Eyes Investigative Svc",
    "wof:placetype":"venue"
},
  "geometry": {"coordinates":[-155.01874100000001,19.731008],"type":"Point"}
}