{
  "type": "Feature",
  "properties": {
    "iso:country":"US",
    "sg:address":"1020 Keolu Dr",
    "sg:city":"Kailua",
    "sg:classifiers":[
        {
            "category":"Restaurant",
            "type":"Food & Drink"
        }
    ],
    "sg:menulink":"http://www.allmenus.com/hi/koolaupoko/92282-l--l-hawaiian-bbq/menu/",
    "sg:phone":"+1 808 262 4411",
    "sg:postcode":"96734",
    "sg:province":"HI",
    "sg:tags":[
        "barbecue",
        "american",
        "hawaiian"
    ],
    "wof:name":"L & L Hawaiian BBQ",
    "wof:placetype":"venue"
},
  "geometry": {"coordinates":[-157.72924,21.378043],"type":"Point"}
}