{
  "type": "Feature",
  "properties": {
    "iso:country":"US",
    "sg:address":"253 Oneawa St",
    "sg:city":"Kailua",
    "sg:classifiers":[
        {
            "category":"Building & Trades",
            "subcategory":"Landscaping Services",
            "type":"Services"
        }
    ],
    "sg:phone":"+1 808 262 3898",
    "sg:postcode":"96734",
    "sg:province":"HI",
    "sg:tags":[
        "landscape"
    ],
    "wof:name":"Expressive Landscaping Inc",
    "wof:placetype":"venue"
},
  "geometry": {"coordinates":[-157.746274,21.397153],"type":"Point"}
}