{
  "type": "Feature",
  "properties": {
    "addr:full":"1107 S King St Honolulu HI 96814",
    "addr:housenumber":"1107",
    "addr:postcode":"96814",
    "addr:street":"S King St",
    "iso:country":"US",
    "sg:address":"1107 S King St",
    "sg:city":"Honolulu",
    "sg:classifiers":[
        {
            "category":"Retail",
            "subcategory":"Portrait Studio",
            "type":"Services"
        }
    ],
    "sg:phone":"+1 808 596 0440",
    "sg:postcode":"96814",
    "sg:province":"HI",
    "sg:tags":[
        "photographic"
    ],
    "wof:name":"House of Photography Inc",
    "wof:placetype":"venue"
},
  "geometry": {"coordinates":[-157.84419299999999,21.299807],"type":"Point"}
}