{
  "type": "Feature",
  "properties": {
    "iso:country":"US",
    "sg:address":"4714 Opukea St",
    "sg:city":"Lihue",
    "sg:classifiers":[
        {
            "category":"Organizations",
            "subcategory":"Professional Association",
            "type":"Services"
        }
    ],
    "sg:phone":"+1 808 246 8878",
    "sg:postcode":"96766",
    "sg:province":"HI",
    "wof:name":"Hui O Hanamaulu Community Ctr",
    "wof:placetype":"venue"
},
  "geometry": {"coordinates":[-159.361876,21.995045],"type":"Point"}
}