{
  "type": "Feature",
  "properties": {
    "iso:country":"US",
    "sg:address":"159 Hualalai Rd",
    "sg:city":"Kailua Kona",
    "sg:classifiers":[
        {
            "category":"Banks & Credit Unions",
            "subcategory":"Investment Brokerage",
            "type":"Services"
        }
    ],
    "sg:phone":"+1 808 331 6209",
    "sg:postcode":"96740",
    "sg:province":"HI",
    "sg:tags":[
        "consultant",
        "planning",
        "financial"
    ],
    "wof:name":"XCU Capital Corp Inc",
    "wof:placetype":"venue"
},
  "geometry": {"coordinates":[-155.99233100000001,19.63766],"type":"Point"}
}