{
  "type": "Feature",
  "properties": {
    "iso:country":"US",
    "sg:address":"1055 Lauae St",
    "sg:city":"Mililani",
    "sg:classifiers":[
        {
            "category":"Recreation",
            "type":"Entertainment"
        }
    ],
    "sg:phone":"+1 808 626 2807",
    "sg:postcode":"96789",
    "sg:province":"HI",
    "sg:tags":[
        "martial",
        "arts",
        "instruction"
    ],
    "wof:name":"Hawaiian Kajukenbo Assn",
    "wof:placetype":"venue"
},
  "geometry": {"coordinates":[-157.996399,21.467845],"type":"Point"}
}