{
  "type": "Feature",
  "properties": {
    "addr:full":"1027 Henry St Kailua Kona HI 96740",
    "addr:housenumber":"1027",
    "addr:postcode":"96740",
    "addr:street":"Henry St",
    "iso:country":"US",
    "sg:address":"1027 Henry St",
    "sg:city":"Kailua Kona",
    "sg:classifiers":[
        {
            "category":"Restaurant",
            "type":"Food & Drink"
        }
    ],
    "sg:phone":"+1 808 329 4822",
    "sg:postcode":"96740",
    "sg:province":"HI",
    "wof:name":"Subway Sandwiches & Salads",
    "wof:placetype":"venue"
},
  "geometry": {"coordinates":[-155.98869400000001,19.648122],"type":"Point"}
}