{
  "type": "Feature",
  "properties": {
    "addr:full":"1535 Colburn St Honolulu HI 96817",
    "addr:housenumber":"1535",
    "addr:postcode":"96817",
    "addr:street":"Colburn St",
    "iso:country":"US",
    "sg:address":"1535 Colburn St",
    "sg:city":"Honolulu",
    "sg:classifiers":[
        {
            "category":"Wholesale",
            "subcategory":"Seafood",
            "type":"Manufacturing & Wholesale Goods"
        }
    ],
    "sg:phone":"+1 808 842 3474",
    "sg:postcode":"96817",
    "sg:province":"HI",
    "sg:website":"www.norpacexport.com",
    "wof:name":"Norpac Fisheries Export",
    "wof:placetype":"venue"
},
  "geometry": {"coordinates":[-157.87661299999999,21.323387],"type":"Point"}
}