{
  "type": "Feature",
  "properties": {
    "addr:full":"3291 Elima St Lihue HI 96766",
    "addr:housenumber":"3291",
    "addr:postcode":"96766",
    "addr:street":"Elima St",
    "iso:country":"US",
    "sg:address":"3291 Elima St",
    "sg:city":"Lihue",
    "sg:classifiers":[
        {
            "category":"Building & Trades",
            "subcategory":"Construction",
            "type":"Services"
        }
    ],
    "sg:phone":"+1 808 632 0063",
    "sg:postcode":"96766",
    "sg:province":"HI",
    "sg:tags":[
        "painter"
    ],
    "wof:name":"M & H Painting",
    "wof:placetype":"venue"
},
  "geometry": {"coordinates":[-159.36755299999999,21.985372],"type":"Point"}
}