{
  "type": "Feature",
  "properties": {
    "iso:country":"US",
    "sg:address":"350 N School St",
    "sg:city":"Honolulu",
    "sg:classifiers":[
        {
            "category":"Autos & Motor Vehicles",
            "subcategory":"Fuel & Gas Station",
            "type":"Retail Goods"
        }
    ],
    "sg:phone":"+1 808 533 6327",
    "sg:postcode":"96817",
    "sg:province":"HI",
    "sg:tags":[
        "oil"
    ],
    "wof:name":"Lance Goya Auto Svc",
    "wof:placetype":"venue"
},
  "geometry": {"coordinates":[-157.85985199999999,21.321553],"type":"Point"}
}