{
  "type": "Feature",
  "properties": {
    "iso:country":"US",
    "sg:address":"257 Hakupokano Loop",
    "sg:city":"Mililani",
    "sg:classifiers":[
        {
            "category":"Professional",
            "subcategory":"Business Services",
            "type":"Services"
        }
    ],
    "sg:phone":"+1 808 456 4044",
    "sg:postcode":"96789",
    "sg:province":"HI",
    "wof:name":"Eagle Interiors",
    "wof:placetype":"venue"
},
  "geometry": {"coordinates":[-158.01807400000001,21.453778],"type":"Point"}
}