{
  "type": "Feature",
  "properties": {
    "iso:country":"US",
    "sg:address":"2841 Kaonawai Pl",
    "sg:city":"Honolulu",
    "sg:classifiers":[
        {
            "category":"Insurance",
            "subcategory":"Insurance Agent",
            "type":"Services"
        }
    ],
    "sg:phone":"+1 808 988 7011",
    "sg:postcode":"96822",
    "sg:province":"HI",
    "wof:name":"State Farm Insurance",
    "wof:placetype":"venue"
},
  "geometry": {"coordinates":[-157.81000700000001,21.31001],"type":"Point"}
}