{
  "type": "Feature",
  "properties": {
    "iso:country":"US",
    "sg:address":"2633 S King St",
    "sg:city":"Honolulu",
    "sg:classifiers":[
        {
            "category":"Personal",
            "subcategory":"Barber",
            "type":"Services"
        }
    ],
    "sg:phone":"+1 808 941 4408",
    "sg:postcode":"96826",
    "sg:province":"HI",
    "wof:name":"Sunae Barber Shop-Hair Styling",
    "wof:placetype":"venue"
},
  "geometry": {"coordinates":[-157.821764,21.291795],"type":"Point"}
}