{
  "type": "Feature",
  "properties": {
    "addr:full":"5311 Apo Dr Honolulu HI 96821",
    "addr:housenumber":"5311",
    "addr:postcode":"96821",
    "addr:street":"Apo Dr",
    "iso:country":"US",
    "sg:address":"5311 Apo Dr",
    "sg:city":"Honolulu",
    "sg:classifiers":[
        {
            "category":"Organizations",
            "subcategory":"Religious Organization",
            "type":"Services"
        }
    ],
    "sg:phone":"+1 808 373 3850",
    "sg:postcode":"96821",
    "sg:province":"HI",
    "wof:name":"Sisters of St Joseph of",
    "wof:placetype":"venue"
},
  "geometry": {"coordinates":[-157.75454300000001,21.282029],"type":"Point"}
}