{
  "type": "Feature",
  "properties": {
    "iso:country":"US",
    "sg:address":"615 Piikoi St",
    "sg:city":"Honolulu",
    "sg:classifiers":[
        {
            "category":"Organizations",
            "subcategory":"Non-profit Organization",
            "type":"Services"
        },
        {
            "category":"Real Estate",
            "subcategory":"Real Estate Operator",
            "type":"Services"
        }
    ],
    "sg:phone":"+1 808 594 4700",
    "sg:postcode":"96814",
    "sg:province":"HI",
    "sg:tags":[
        "property",
        "lessor"
    ],
    "wof:name":"Emma Queen Foundation",
    "wof:placetype":"venue"
},
  "geometry": {"coordinates":[-157.84610599999999,21.295074],"type":"Point"}
}