{
  "type": "Feature",
  "properties": {
    "iso:country":"US",
    "sg:address":"3483 Weliweli Rd",
    "sg:city":"Koloa",
    "sg:classifiers":[
        {
            "category":"Real Estate",
            "subcategory":"Real Estate Agent",
            "type":"Services"
        }
    ],
    "sg:phone":"+1 808 742 0022",
    "sg:postcode":"96756",
    "sg:province":"HI",
    "sg:tags":[
        "sharing"
    ],
    "wof:name":"All Islands Timeshare Resales",
    "wof:placetype":"venue"
},
  "geometry": {"coordinates":[-159.46234200000001,21.902928],"type":"Point"}
}