{
  "type": "Feature",
  "properties": {
    "iso:country":"US",
    "sg:address":"1857 S King St",
    "sg:city":"Honolulu",
    "sg:classifiers":[
        {
            "category":"Shopping",
            "subcategory":"Stationery & Office Supplies",
            "type":"Retail Goods"
        }
    ],
    "sg:phone":"+1 808 946 8968",
    "sg:postcode":"96826",
    "sg:province":"HI",
    "sg:tags":[
        "repairing",
        "pencil",
        "pen",
        "printing",
        "commercial"
    ],
    "wof:name":"Honolulu Pen Shop",
    "wof:placetype":"venue"
},
  "geometry": {"coordinates":[-157.83223100000001,21.295573],"type":"Point"}
}