{
  "type": "Feature",
  "properties": {
    "iso:country":"US",
    "sg:address":"3745 Waipio Rd",
    "sg:city":"Honokaa",
    "sg:classifiers":[
        {
            "category":"Food & Beverages",
            "subcategory":"Groceries & Convenience Stores",
            "type":"Retail Goods"
        }
    ],
    "sg:phone":"+1 808 775 0666",
    "sg:postcode":"96727",
    "sg:province":"HI",
    "sg:tags":[
        "alcoholic"
    ],
    "wof:name":"K K Super Mart Inc",
    "wof:placetype":"venue"
},
  "geometry": {"coordinates":[-155.47053600000001,20.079548],"type":"Point"}
}