{
  "type": "Feature",
  "properties": {
    "iso:country":"US",
    "sg:address":"4920 Honoapiilani Hwy",
    "sg:city":"Lahaina",
    "sg:classifiers":[
        {
            "category":"Food & Beverages",
            "subcategory":"Specialty",
            "type":"Retail Goods"
        }
    ],
    "sg:phone":"+1 808 669 5377",
    "sg:postcode":"96761",
    "sg:province":"HI",
    "sg:tags":[
        "flower",
        "health"
    ],
    "wof:name":"Galaxy Inc",
    "wof:placetype":"venue"
},
  "geometry": {"coordinates":[-156.67274399999999,20.986252],"type":"Point"}
}