{
  "type": "Feature",
  "properties": {
    "iso:country":"US",
    "sg:address":"1121 Rycroft St",
    "sg:city":"Honolulu",
    "sg:classifiers":[
        {
            "category":"Wholesale",
            "subcategory":"Electrical",
            "type":"Manufacturing & Wholesale Goods"
        }
    ],
    "sg:phone":"+1 808 597 8775",
    "sg:postcode":"96814",
    "sg:province":"HI",
    "sg:tags":[
        "alarm",
        "burglar",
        "system"
    ],
    "wof:name":"Island Wireless Alarm",
    "wof:placetype":"venue"
},
  "geometry": {"coordinates":[-157.84622200000001,21.297983],"type":"Point"}
}