{
  "type": "Feature",
  "properties": {
    "iso:country":"US",
    "sg:address":"7107 Pilaa Pl",
    "sg:city":"Honolulu",
    "sg:classifiers":[
        {
            "category":"Building & Trades",
            "subcategory":"Construction",
            "type":"Services"
        }
    ],
    "sg:phone":"+1 808 395 1760",
    "sg:postcode":"96825",
    "sg:province":"HI",
    "sg:tags":[
        "house"
    ],
    "wof:name":"Brian Hepton Contractor",
    "wof:placetype":"venue"
},
  "geometry": {"coordinates":[-157.70686499999999,21.276922],"type":"Point"}
}