{
  "type": "Feature",
  "properties": {
    "iso:country":"US",
    "sg:address":"3577 Pinao St",
    "sg:city":"Honolulu",
    "sg:classifiers":[
        {
            "category":"Communications",
            "subcategory":"Film & Video Production",
            "type":"Services"
        }
    ],
    "sg:phone":"+1 808 778 3459",
    "sg:postcode":"96822",
    "sg:province":"HI",
    "sg:tags":[
        "taping"
    ],
    "wof:name":"Amakua Video",
    "wof:placetype":"venue"
},
  "geometry": {"coordinates":[-157.800894,21.324816],"type":"Point"}
}