{
  "type": "Feature",
  "properties": {
    "iso:country":"US",
    "sg:address":"2646 Kilihau St",
    "sg:city":"Honolulu",
    "sg:classifiers":[
        {
            "category":"Professional",
            "subcategory":"Management & Consulting",
            "type":"Services"
        }
    ],
    "sg:phone":"+1 808 836 2355",
    "sg:postcode":"96819",
    "sg:province":"HI",
    "sg:tags":[
        "operations",
        "environmental",
        "maintenance",
        "facility"
    ],
    "wof:name":"Cdc",
    "wof:placetype":"venue"
},
  "geometry": {"coordinates":[-157.896377,21.33538],"type":"Point"}
}