{
  "type": "Feature",
  "properties": {
    "iso:country":"US",
    "sg:address":"567 Ohohia St",
    "sg:city":"Honolulu",
    "sg:classifiers":[
        {
            "category":"Banks & Credit Unions",
            "subcategory":"Bank",
            "type":"Services"
        }
    ],
    "sg:phone":"+1 808 836 2091",
    "sg:postcode":"96819",
    "sg:province":"HI",
    "sg:tags":[
        "personal",
        "institution"
    ],
    "wof:name":"Associates Financial",
    "wof:placetype":"venue"
},
  "geometry": {"coordinates":[-157.907467,21.335711],"type":"Point"}
}