{
  "type": "Feature",
  "properties": {
    "addr:full":"201 Papa Pl Kahului HI 96732",
    "addr:housenumber":"201",
    "addr:postcode":"96732",
    "addr:street":"Papa Pl",
    "iso:country":"US",
    "sg:address":"201 Papa Pl",
    "sg:city":"Kahului",
    "sg:classifiers":[
        {
            "category":"Home & Garden",
            "subcategory":"Garden Supply",
            "type":"Retail Goods"
        }
    ],
    "sg:phone":"+1 808 871 2622",
    "sg:postcode":"96732",
    "sg:province":"HI",
    "sg:tags":[
        "supp",
        "farm"
    ],
    "wof:name":"United Agri Products",
    "wof:placetype":"venue"
},
  "geometry": {"coordinates":[-156.45648,20.882773],"type":"Point"}
}