{
  "type": "Feature",
  "properties": {
    "iso:country":"US",
    "sg:address":"13 N Kaniku Dr",
    "sg:city":"Kamuela",
    "sg:classifiers":[
        {
            "category":"Professional",
            "type":"Services"
        }
    ],
    "sg:phone":"+1 808 885 5949",
    "sg:postcode":"96743",
    "sg:province":"HI",
    "sg:tags":[
        "establishment"
    ],
    "wof:name":"MLP Estates Inc",
    "wof:placetype":"venue"
},
  "geometry": {"coordinates":[-155.85605899999999,19.941601],"type":"Point"}
}