{
  "type": "Feature",
  "properties": {
    "iso:country":"US",
    "sg:address":"1050 12th Ave",
    "sg:city":"Honolulu",
    "sg:classifiers":[
        {
            "category":"Professional",
            "subcategory":"Accounting & Tax Preparation",
            "type":"Services"
        }
    ],
    "sg:phone":"+1 808 737 8961",
    "sg:postcode":"96816",
    "sg:province":"HI",
    "sg:tags":[
        "bookkeeping",
        "general"
    ],
    "wof:name":"1050 Inc",
    "wof:placetype":"venue"
},
  "geometry": {"coordinates":[-157.79983999999999,21.280998],"type":"Point"}
}