{
  "type": "Feature",
  "properties": {
    "iso:country":"US",
    "sg:address":"1920 E Vineyard St",
    "sg:city":"Wailuku",
    "sg:classifiers":[
        {
            "category":"Personal",
            "subcategory":"Beauty Salon",
            "type":"Services"
        }
    ],
    "sg:phone":"+1 808 244 5636",
    "sg:postcode":"96793",
    "sg:province":"HI",
    "sg:tags":[
        "shop"
    ],
    "wof:name":"The Salon Executives Inc",
    "wof:placetype":"venue"
},
  "geometry": {"coordinates":[-156.504312,20.893237],"type":"Point"}
}