{
  "type": "Feature",
  "properties": {
    "iso:country":"US",
    "sg:address":"1151 Punchbowl St",
    "sg:city":"Honolulu",
    "sg:classifiers":[
        {
            "category":"Government",
            "subcategory":"Office",
            "type":"Public Place"
        }
    ],
    "sg:phone":"+1 808 587 0316",
    "sg:postcode":"96813",
    "sg:province":"HI",
    "sg:tags":[
        "state",
        "maintenance",
        "grounds"
    ],
    "wof:name":"Civic Center Complex Unit",
    "wof:placetype":"venue"
},
  "geometry": {"coordinates":[-157.85716400000001,21.305576],"type":"Point"}
}