{
  "type": "Feature",
  "properties": {
    "iso:country":"US",
    "sg:address":"228 Hoohana St",
    "sg:city":"Kahului",
    "sg:classifiers":[
        {
            "category":"Local Transit",
            "type":"Transportation"
        }
    ],
    "sg:phone":"+1 808 872 3700",
    "sg:postcode":"96732",
    "sg:province":"HI",
    "sg:tags":[
        "seeing",
        "tour",
        "sight"
    ],
    "wof:name":"Travel Plaza Transportation",
    "wof:placetype":"venue"
},
  "geometry": {"coordinates":[-156.46318299999999,20.886712],"type":"Point"}
}