{
  "type": "Feature",
  "properties": {
    "iso:country":"US",
    "sg:address":"1099 Waimano Home Rd",
    "sg:city":"Pearl City",
    "sg:classifiers":[
        {
            "category":"Retail",
            "subcategory":"Car Wash",
            "type":"Services"
        }
    ],
    "sg:phone":"+1 808 456 2099",
    "sg:postcode":"96782",
    "sg:province":"HI",
    "sg:tags":[
        "carwash"
    ],
    "wof:name":"20 20 Auto Detailing LLC",
    "wof:placetype":"venue"
},
  "geometry": {"coordinates":[-157.97024300000001,21.393874],"type":"Point"}
}