{
  "type": "Feature",
  "properties": {
    "addr:full":"275 Waikoloa Beach Dr Waikoloa HI 96738",
    "addr:housenumber":"275",
    "addr:postcode":"96738",
    "addr:street":"Waikoloa Beach Dr",
    "iso:country":"US",
    "sg:address":"275 Waikoloa Beach Dr",
    "sg:city":"Waikoloa",
    "sg:classifiers":[
        {
            "category":"Organizations",
            "subcategory":"Community Association",
            "type":"Services"
        }
    ],
    "sg:phone":"+1 808 886 4915",
    "sg:postcode":"96738",
    "sg:province":"HI",
    "sg:tags":[
        "resort",
        "destination"
    ],
    "wof:name":"Kohala Coast Resort Assn",
    "wof:placetype":"venue"
},
  "geometry": {"coordinates":[-155.88396,19.925515],"type":"Point"}
}