{
  "type": "Feature",
  "properties": {
    "iso:country":"US",
    "sg:address":"1019 Pensacola St",
    "sg:city":"Honolulu",
    "sg:classifiers":[
        {
            "category":"Personal",
            "subcategory":"Beauty Salon",
            "type":"Services"
        }
    ],
    "sg:phone":"+1 808 596 8254",
    "sg:postcode":"96814",
    "sg:province":"HI",
    "wof:name":"Hair One",
    "wof:placetype":"venue"
},
  "geometry": {"coordinates":[-157.84540200000001,21.30115],"type":"Point"}
}