{
  "type": "Feature",
  "properties": {
    "iso:country":"US",
    "sg:address":"150 Hana Hwy",
    "sg:city":"Kahului",
    "sg:classifiers":[
        {
            "category":"Professional",
            "subcategory":"Detective & Security Services",
            "type":"Services"
        },
        {
            "category":"Wholesale",
            "subcategory":"Electrical",
            "type":"Manufacturing & Wholesale Goods"
        }
    ],
    "sg:phone":"+1 808 242 8200",
    "sg:postcode":"96732",
    "sg:province":"HI",
    "sg:tags":[
        "burglar",
        "car",
        "alarm",
        "system",
        "contractor",
        "re"
    ],
    "wof:name":"Sotos Safe & Sound Alarm Co",
    "wof:placetype":"venue"
},
  "geometry": {"coordinates":[-156.460005,20.890105],"type":"Point"}
}