{
  "type": "Feature",
  "properties": {
    "iso:country":"US",
    "sg:address":"529 Kamehameha Hwy",
    "sg:city":"Haleiwa",
    "sg:classifiers":[
        {
            "category":"Organizations",
            "subcategory":"Community Association",
            "type":"Services"
        }
    ],
    "sg:phone":"+1 808 637 2211",
    "sg:postcode":"96712",
    "sg:province":"HI",
    "sg:tags":[
        "environmental",
        "org"
    ],
    "wof:name":"Save The Sea Turtles Intl",
    "wof:placetype":"venue"
},
  "geometry": {"coordinates":[-158.05703800000001,21.658775],"type":"Point"}
}