{
  "type": "Feature",
  "properties": {
    "iso:country":"US",
    "sg:address":"1001 Bishop St",
    "sg:city":"Honolulu",
    "sg:classifiers":[
        {
            "category":"Insurance",
            "subcategory":"Life Insurance",
            "type":"Services"
        }
    ],
    "sg:phone":"+1 808 961 5970",
    "sg:postcode":"96813",
    "sg:province":"HI",
    "sg:tags":[
        "carrier"
    ],
    "wof:name":"Pacific Life Insurance Company",
    "wof:placetype":"venue"
},
  "geometry": {"coordinates":[-157.86039400000001,21.30931],"type":"Point"}
}