{
  "type": "Feature",
  "properties": {
    "iso:country":"US",
    "sg:address":"2015 N King St",
    "sg:city":"Honolulu",
    "sg:classifiers":[
        {
            "category":"Travel",
            "subcategory":"Travel Agent",
            "type":"Entertainment"
        }
    ],
    "sg:phone":"+1 808 841 2841",
    "sg:postcode":"96819",
    "sg:province":"HI",
    "sg:tags":[
        "agency"
    ],
    "wof:name":"Phil American Travel Agency",
    "wof:placetype":"venue"
},
  "geometry": {"coordinates":[-157.87875600000001,21.33262],"type":"Point"}
}