{
  "type": "Feature",
  "properties": {
    "iso:country":"US",
    "sg:address":"522 Kuaaina Way",
    "sg:city":"Kailua",
    "sg:classifiers":[
        {
            "category":"Education",
            "subcategory":"Special Training",
            "type":"Public Place"
        },
        {
            "category":"Organizations",
            "subcategory":"Community Association",
            "type":"Services"
        }
    ],
    "sg:phone":"+1 808 262 5279",
    "sg:postcode":"96734",
    "sg:province":"HI",
    "sg:tags":[
        "educational",
        "cooperative"
    ],
    "wof:name":"Amitabha Educational Center",
    "wof:placetype":"venue"
},
  "geometry": {"coordinates":[-157.748526,21.400616],"type":"Point"}
}