{
  "type": "Feature",
  "properties": {
    "addr:full":"1250 Punchbowl St Honolulu HI 96813",
    "addr:housenumber":"1250",
    "addr:postcode":"96813",
    "addr:street":"Punchbowl St",
    "iso:country":"US",
    "sg:address":"1250 Punchbowl St",
    "sg:city":"Honolulu",
    "sg:classifiers":[
        {
            "category":"Government",
            "subcategory":"Office",
            "type":"Public Place"
        }
    ],
    "sg:phone":"+1 808 586 4583",
    "sg:postcode":"96813",
    "sg:province":"HI",
    "sg:tags":[
        "state",
        "health"
    ],
    "wof:name":"Developmental Disabilities",
    "wof:placetype":"venue"
},
  "geometry": {"coordinates":[-157.85499899999999,21.308379],"type":"Point"}
}