{
  "type": "Feature",
  "properties": {
    "iso:country":"US",
    "sg:address":"22 Hoomalie Pl",
    "sg:city":"Makawao",
    "sg:classifiers":[
        {
            "category":"Building & Trades",
            "subcategory":"Plumbing",
            "type":"Services"
        }
    ],
    "sg:phone":"+1 808 573 5793",
    "sg:postcode":"96768",
    "sg:province":"HI",
    "sg:tags":[
        "contractor"
    ],
    "wof:name":"Perfect Plumbing Co",
    "wof:placetype":"venue"
},
  "geometry": {"coordinates":[-156.342602,20.865997],"type":"Point"}
}