{
  "type": "Feature",
  "properties": {
    "addr:full":"655 Keeaumoku St Honolulu HI 96814",
    "addr:housenumber":"655",
    "addr:postcode":"96814",
    "addr:street":"Keeaumoku St",
    "iso:country":"US",
    "sg:address":"655 Keeaumoku St",
    "sg:city":"Honolulu",
    "sg:classifiers":[
        {
            "category":"Banks & Credit Unions",
            "subcategory":"Financial Services",
            "type":"Services"
        }
    ],
    "sg:phone":"+1 808 923 8600",
    "sg:postcode":"96814",
    "sg:province":"HI",
    "sg:tags":[
        "investor"
    ],
    "wof:name":"Aloha Resort Inc",
    "wof:placetype":"venue"
},
  "geometry": {"coordinates":[-157.84186399999999,21.294325],"type":"Point"}
}