{
  "type": "Feature",
  "properties": {
    "addr:full":"1653 Waiaka St Kamuela HI 96743",
    "addr:housenumber":"1653",
    "addr:postcode":"96743",
    "addr:street":"Waiaka St",
    "iso:country":"US",
    "sg:address":"1653 Waiaka St",
    "sg:city":"Kamuela",
    "sg:classifiers":[
        {
            "category":"Health Services",
            "subcategory":"Medical Lab",
            "type":"Services"
        }
    ],
    "sg:phone":"+1 808 885 0563",
    "sg:postcode":"96743",
    "sg:province":"HI",
    "sg:tags":[
        "laboratory"
    ],
    "wof:name":"Kamuela Ceramic Studio",
    "wof:placetype":"venue"
},
  "geometry": {"coordinates":[-155.701402,20.027684],"type":"Point"}
}