{
  "type": "Feature",
  "properties": {
    "addr:full":"1579 Molehu Dr Honolulu HI 96818",
    "addr:housenumber":"1579",
    "addr:postcode":"96818",
    "addr:street":"Molehu Dr",
    "iso:country":"US",
    "sg:address":"1579 Molehu Dr",
    "sg:city":"Honolulu",
    "sg:classifiers":[
        {
            "category":"Building & Trades",
            "subcategory":"Construction",
            "type":"Services"
        }
    ],
    "sg:phone":"+1 808 422 0902",
    "sg:postcode":"96818",
    "sg:province":"HI",
    "sg:tags":[
        "concrete",
        "contractor"
    ],
    "wof:name":"Arnold S Flooring",
    "wof:placetype":"venue"
},
  "geometry": {"coordinates":[-157.92117099999999,21.362593],"type":"Point"}
}