{
  "type": "Feature",
  "properties": {
    "iso:country":"US",
    "sg:address":"720 Iwilei Rd",
    "sg:city":"Honolulu",
    "sg:classifiers":[
        {
            "category":"Wholesale",
            "subcategory":"Apparel",
            "type":"Manufacturing & Wholesale Goods"
        }
    ],
    "sg:phone":"+1 808 585 6456",
    "sg:postcode":"96817",
    "sg:province":"HI",
    "sg:tags":[
        "clothing"
    ],
    "wof:name":"Winnie Fashion Inc",
    "wof:placetype":"venue"
},
  "geometry": {"coordinates":[-157.870375,21.316358],"type":"Point"}
}