{
  "type": "Feature",
  "properties": {
    "iso:country":"US",
    "sg:address":"1610 Kanunu St",
    "sg:city":"Honolulu",
    "sg:classifiers":[
        {
            "category":"Real Estate",
            "subcategory":"Real Estate Agent",
            "type":"Services"
        },
        {
            "category":"Real Estate",
            "subcategory":"Real Estate Operator",
            "type":"Services"
        }
    ],
    "sg:phone":"+1 808 941 6977",
    "sg:postcode":"96814",
    "sg:province":"HI",
    "sg:tags":[
        "condominium"
    ],
    "wof:name":"Aoao Kapiolani Towers",
    "wof:placetype":"venue"
},
  "geometry": {"coordinates":[-157.83823000000001,21.294173],"type":"Point"}
}