{
  "type": "Feature",
  "properties": {
    "iso:country":"US",
    "sg:address":"705 S King St",
    "sg:city":"Honolulu",
    "sg:classifiers":[
        {
            "category":"Banks & Credit Unions",
            "subcategory":"Bank",
            "type":"Services"
        }
    ],
    "sg:phone":"+1 808 550 0007",
    "sg:postcode":"96813",
    "sg:province":"HI",
    "sg:tags":[
        "mortgage",
        "loan",
        "broker",
        "real estate"
    ],
    "sg:website":"www.pacificcoastmortgage.com",
    "wof:name":"Pacific Coast Mortgage Corp",
    "wof:placetype":"venue"
},
  "geometry": {"coordinates":[-157.853588,21.303124],"type":"Point"}
}