{
  "type": "Feature",
  "properties": {
    "iso:country":"US",
    "sg:address":"198 Loaa St",
    "sg:city":"Waipahu",
    "sg:classifiers":[
        {
            "category":"Professional",
            "subcategory":"Management & Consulting",
            "type":"Services"
        }
    ],
    "sg:phone":"+1 808 677 8501",
    "sg:postcode":"96797",
    "sg:province":"HI",
    "sg:tags":[
        "retail",
        "direct",
        "sales"
    ],
    "wof:name":"Shirley H Alos",
    "wof:placetype":"venue"
},
  "geometry": {"coordinates":[-158.02448200000001,21.383186],"type":"Point"}
}