{
  "type": "Feature",
  "properties": {
    "iso:country":"US",
    "sg:address":"970 N Kalaheo Ave",
    "sg:city":"Kailua",
    "sg:classifiers":[
        {
            "category":"Real Estate",
            "subcategory":"Real Estate Agent",
            "type":"Services"
        },
        {
            "category":"Banks & Credit Unions",
            "subcategory":"Financial Services",
            "type":"Services"
        }
    ],
    "sg:phone":"+1 808 254 6300",
    "sg:postcode":"96734",
    "sg:province":"HI",
    "sg:tags":[
        "loan",
        "investor",
        "broker"
    ],
    "wof:name":"Capital Research Group Inc",
    "wof:placetype":"venue"
},
  "geometry": {"coordinates":[-157.74768700000001,21.419617],"type":"Point"}
}