{
  "type": "Feature",
  "properties": {
    "iso:country":"US",
    "sg:address":"2335 Kalakaua Ave",
    "sg:city":"Honolulu",
    "sg:classifiers":[
        {
            "category":"Professional",
            "type":"Services"
        }
    ],
    "sg:phone":"+1 808 922 0055",
    "sg:postcode":"96815",
    "sg:province":"HI",
    "sg:tags":[
        "establishment"
    ],
    "sg:website":"www.dooney.com",
    "wof:name":"Dooney & Bourke",
    "wof:placetype":"venue"
},
  "geometry": {"coordinates":[-157.826742,21.277063],"type":"Point"}
}