{
  "type": "Feature",
  "properties": {
    "iso:country":"US",
    "sg:address":"4370 Kukui Grove St",
    "sg:city":"Lihue",
    "sg:classifiers":[
        {
            "category":"Insurance",
            "subcategory":"Insurance Agent",
            "type":"Services"
        },
        {
            "category":"Banks & Credit Unions",
            "subcategory":"Bank",
            "type":"Services"
        }
    ],
    "sg:phone":"+1 808 245 6975",
    "sg:postcode":"96766",
    "sg:province":"HI",
    "sg:tags":[
        "escrow"
    ],
    "wof:name":"Security Title Corporation",
    "wof:placetype":"venue"
},
  "geometry": {"coordinates":[-159.37670700000001,21.970876],"type":"Point"}
}