{
  "type": "Feature",
  "properties": {
    "iso:country":"US",
    "sg:address":"753 21st Ave",
    "sg:city":"Honolulu",
    "sg:classifiers":[
        {
            "category":"Professional",
            "subcategory":"Advertising",
            "type":"Services"
        }
    ],
    "sg:phone":"+1 808 734 2170",
    "sg:postcode":"96816",
    "sg:province":"HI",
    "sg:tags":[
        "counselor"
    ],
    "wof:name":"Media Management Svc",
    "wof:placetype":"venue"
},
  "geometry": {"coordinates":[-157.79369199999999,21.270787],"type":"Point"}
}