{
  "type": "Feature",
  "properties": {
    "iso:country":"US",
    "sg:address":"2310 Kuhio Ave",
    "sg:city":"Honolulu",
    "sg:classifiers":[
        {
            "category":"Shopping",
            "subcategory":"Musical Instruments",
            "type":"Retail Goods"
        }
    ],
    "sg:phone":"+1 808 926 6199",
    "sg:postcode":"96815",
    "sg:province":"HI",
    "wof:name":"Da Ukulele",
    "wof:placetype":"venue"
},
  "geometry": {"coordinates":[-157.82587100000001,21.279329],"type":"Point"}
}