{
  "type": "Feature",
  "properties": {
    "iso:country":"US",
    "sg:address":"923 15th Ave",
    "sg:city":"Honolulu",
    "sg:classifiers":[
        {
            "category":"Real Estate",
            "subcategory":"Real Estate Operator",
            "type":"Services"
        }
    ],
    "sg:phone":"+1 808 734 1031",
    "sg:postcode":"96816",
    "sg:province":"HI",
    "sg:tags":[
        "building",
        "apartment"
    ],
    "wof:name":"Yamaguchi Family Par",
    "wof:placetype":"venue"
},
  "geometry": {"coordinates":[-157.79702900000001,21.277188],"type":"Point"}
}