{
  "type": "Feature",
  "properties": {
    "addr:full":"2011 S King St Honolulu HI 96826",
    "addr:housenumber":"2011",
    "addr:postcode":"96826",
    "addr:street":"S King St",
    "iso:country":"US",
    "sg:address":"2011 S King St",
    "sg:city":"Honolulu",
    "sg:classifiers":[
        {
            "category":"Autos & Motor Vehicles",
            "subcategory":"Motorcycle Sales",
            "type":"Retail Goods"
        }
    ],
    "sg:phone":"+1 808 943 1868",
    "sg:postcode":"96826",
    "sg:province":"HI",
    "sg:tags":[
        "moped"
    ],
    "wof:name":"Botek Moped",
    "wof:placetype":"venue"
},
  "geometry": {"coordinates":[-157.82910799999999,21.294443],"type":"Point"}
}