{
  "type": "Feature",
  "properties": {
    "iso:country":"US",
    "sg:address":"2199 Kahookele St",
    "sg:city":"Wailuku",
    "sg:classifiers":[
        {
            "category":"Travel",
            "subcategory":"Hotels & Motels",
            "type":"Entertainment"
        }
    ],
    "sg:phone":"+1 808 244 5897",
    "sg:postcode":"96793",
    "sg:province":"HI",
    "sg:tags":[
        "operation"
    ],
    "sg:website":"www.mauiinn.com",
    "wof:name":"Old Wailuku Inn LTD",
    "wof:placetype":"venue"
},
  "geometry": {"coordinates":[-156.507958,20.885583],"type":"Point"}
}