{
  "type": "Feature",
  "properties": {
    "iso:country":"US",
    "sg:address":"401 Cooke St",
    "sg:city":"Honolulu",
    "sg:classifiers":[
        {
            "category":"Retail",
            "subcategory":"Repair Shop",
            "type":"Services"
        }
    ],
    "sg:phone":"+1 808 593 9114",
    "sg:postcode":"96813",
    "sg:province":"HI",
    "sg:tags":[
        "key"
    ],
    "wof:name":"Aloha Key & Awards",
    "wof:placetype":"venue"
},
  "geometry": {"coordinates":[-157.858587,21.298379],"type":"Point"}
}