{
  "type": "Feature",
  "properties": {
    "iso:country":"US",
    "sg:address":"521 Ala Moana Blvd",
    "sg:city":"Honolulu",
    "sg:classifiers":[
        {
            "category":"Wholesale",
            "subcategory":"Jewelry",
            "type":"Manufacturing & Wholesale Goods"
        }
    ],
    "sg:phone":"+1 808 536 5652",
    "sg:postcode":"96813",
    "sg:province":"HI",
    "sg:tags":[
        "stone"
    ],
    "wof:name":"Dynasty Gems Inc",
    "wof:placetype":"venue"
},
  "geometry": {"coordinates":[-157.86303699999999,21.299438],"type":"Point"}
}