{
  "type": "Feature",
  "properties": {
    "iso:country":"US",
    "sg:address":"365 Kahuanani St",
    "sg:city":"Waipahu",
    "sg:classifiers":[
        {
            "category":"Professional",
            "subcategory":"Business Services",
            "type":"Services"
        }
    ],
    "sg:phone":"+1 808 677 7125",
    "sg:postcode":"96797",
    "sg:province":"HI",
    "wof:name":"A Peace of Hawaii",
    "wof:placetype":"venue"
},
  "geometry": {"coordinates":[-157.99855299999999,21.392961],"type":"Point"}
}