{
  "type": "Feature",
  "properties": {
    "iso:country":"US",
    "sg:address":"2958 Ualena St",
    "sg:city":"Honolulu",
    "sg:classifiers":[
        {
            "category":"Home & Garden",
            "subcategory":"Furniture",
            "type":"Retail Goods"
        }
    ],
    "sg:phone":"+1 808 837 7828",
    "sg:postcode":"96819",
    "sg:province":"HI",
    "wof:name":"Alexander Brothers LTD",
    "wof:placetype":"venue"
},
  "geometry": {"coordinates":[-157.90302600000001,21.333046],"type":"Point"}
}