{
  "type": "Feature",
  "properties": {
    "iso:country":"US",
    "sg:address":"2216 Hillcrest St",
    "sg:city":"Honolulu",
    "sg:classifiers":[
        {
            "category":"Shopping",
            "subcategory":"Clothing, Apparel, & Fashions",
            "type":"Retail Goods"
        }
    ],
    "sg:phone":"+1 808 845 9005",
    "sg:postcode":"96817",
    "sg:province":"HI",
    "sg:tags":[
        "sportswear"
    ],
    "wof:name":"New World Fashions Co",
    "wof:placetype":"venue"
},
  "geometry": {"coordinates":[-157.85946799999999,21.335288],"type":"Point"}
}