{
  "type": "Feature",
  "properties": {
    "iso:country":"US",
    "sg:address":"4370 Kukui Grove St",
    "sg:city":"Lihue",
    "sg:classifiers":[
        {
            "category":"Sports & Exercise",
            "subcategory":"Gym",
            "type":"Entertainment"
        }
    ],
    "sg:phone":"+1 808 245 5381",
    "sg:postcode":"96766",
    "sg:province":"HI",
    "sg:tags":[
        "club",
        "health"
    ],
    "wof:name":"Kauai Athletic Club",
    "wof:placetype":"venue"
},
  "geometry": {"coordinates":[-159.37670700000001,21.970876],"type":"Point"}
}