{
  "type": "Feature",
  "properties": {
    "iso:country":"US",
    "sg:address":"2800 Woodlawn Dr",
    "sg:city":"Honolulu",
    "sg:classifiers":[
        {
            "category":"Professional",
            "subcategory":"Research",
            "type":"Services"
        }
    ],
    "sg:phone":"+1 808 539 3961",
    "sg:postcode":"96822",
    "sg:province":"HI",
    "sg:tags":[
        "consultation"
    ],
    "wof:name":"John J Steffen",
    "wof:placetype":"venue"
},
  "geometry": {"coordinates":[-157.80744899999999,21.309085],"type":"Point"}
}