{
  "type": "Feature",
  "properties": {
    "iso:country":"US",
    "sg:address":"3830 Hanapepe Rd",
    "sg:city":"Hanapepe",
    "sg:classifiers":[
        {
            "category":"Restaurant",
            "type":"Food & Drink"
        }
    ],
    "sg:phone":"+1 808 335 5011",
    "sg:postcode":"96716",
    "sg:province":"HI",
    "wof:name":"Hanapepe Cafe & Espresso",
    "wof:placetype":"venue"
},
  "geometry": {"coordinates":[-159.58633699999999,21.91121],"type":"Point"}
}