{
  "type": "Feature",
  "properties": {
    "addr:full":"415 Prospect St Honolulu HI 96813",
    "addr:housenumber":"415",
    "addr:postcode":"96813",
    "addr:street":"Prospect St",
    "iso:country":"US",
    "sg:address":"415 Prospect St",
    "sg:city":"Honolulu",
    "sg:classifiers":[
        {
            "category":"Retail",
            "subcategory":"Laundry & Dry Cleaning",
            "type":"Services"
        }
    ],
    "sg:phone":"+1 808 531 9992",
    "sg:postcode":"96813",
    "sg:province":"HI",
    "wof:name":"Carpet Cleaner Springer LLC",
    "wof:placetype":"venue"
},
  "geometry": {"coordinates":[-157.85048499999999,21.312103],"type":"Point"}
}