{
  "type": "Feature",
  "properties": {
    "iso:country":"US",
    "sg:address":"688 Farrington Hwy",
    "sg:city":"Waipahu",
    "sg:classifiers":[
        {
            "category":"Home & Garden",
            "subcategory":"Furniture",
            "type":"Retail Goods"
        }
    ],
    "sg:phone":"+1 808 677 3291",
    "sg:postcode":"96797",
    "sg:province":"HI",
    "sg:tags":[
        "household",
        "appliance"
    ],
    "wof:name":"Mid-Town Radio",
    "wof:placetype":"venue"
},
  "geometry": {"coordinates":[-158.009479,21.383066],"type":"Point"}
}