{
  "type": "Feature",
  "properties": {
    "iso:country":"US",
    "sg:address":"25 Holua Way",
    "sg:city":"Wahiawa",
    "sg:classifiers":[
        {
            "category":"Social Services",
            "type":"Services"
        }
    ],
    "sg:phone":"+1 808 621 7731",
    "sg:postcode":"96786",
    "sg:province":"HI",
    "wof:name":"Soccer Assoc For Youth",
    "wof:placetype":"venue"
},
  "geometry": {"coordinates":[-158.00286199999999,21.504952],"type":"Point"}
}