{
  "type": "Feature",
  "properties": {
    "iso:country":"US",
    "sg:address":"238 Ohiohi Pl",
    "sg:city":"Waianae",
    "sg:classifiers":[
        {
            "category":"Professional",
            "subcategory":"Accounting & Tax Preparation",
            "type":"Services"
        }
    ],
    "sg:phone":"+1 808 696 6359",
    "sg:postcode":"96792",
    "sg:province":"HI",
    "sg:tags":[
        "return",
        "filing"
    ],
    "wof:name":"Liahona Tax & Bookkeeping Svc",
    "wof:placetype":"venue"
},
  "geometry": {"coordinates":[-158.17514499999999,21.425202],"type":"Point"}
}