{
  "type": "Feature",
  "properties": {
    "iso:country":"US",
    "sg:address":"125 Terrace Cir",
    "sg:city":"Hilo",
    "sg:classifiers":[
        {
            "category":"Shopping",
            "type":"Retail Goods"
        }
    ],
    "sg:phone":"+1 808 934 9399",
    "sg:postcode":"96720",
    "sg:province":"HI",
    "sg:tags":[
        "merchandise"
    ],
    "wof:name":"Water Man",
    "wof:placetype":"venue"
},
  "geometry": {"coordinates":[-155.11966799999999,19.701346],"type":"Point"}
}