{
  "type": "Feature",
  "properties": {
    "addr:full":"85 Walker Ave Wahiawa HI 96786",
    "addr:housenumber":"85",
    "addr:postcode":"96786",
    "addr:street":"Walker Ave",
    "iso:country":"US",
    "sg:address":"85 Walker Ave",
    "sg:city":"Wahiawa",
    "sg:classifiers":[
        {
            "category":"Personal",
            "subcategory":"Barber",
            "type":"Services"
        }
    ],
    "sg:phone":"+1 808 621 7786",
    "sg:postcode":"96786",
    "sg:province":"HI",
    "sg:tags":[
        "shop"
    ],
    "wof:name":"Y H Barber Shop",
    "wof:placetype":"venue"
},
  "geometry": {"coordinates":[-158.028538,21.49523],"type":"Point"}
}