{
  "type": "Feature",
  "properties": {
    "iso:country":"US",
    "sg:address":"4618 Kilauea Ave",
    "sg:city":"Honolulu",
    "sg:classifiers":[
        {
            "category":"Restaurant",
            "type":"Food & Drink"
        }
    ],
    "sg:menulink":"http://www.allmenus.com/hi/honolulu/92308-l--l-hawaiian-bbq/menu/",
    "sg:phone":"+1 808 732 4042",
    "sg:postcode":"96816",
    "sg:province":"HI",
    "sg:tags":[
        "barbecue",
        "american",
        "hawaiian"
    ],
    "wof:name":"L & L Hawaiian BBQ",
    "wof:placetype":"venue"
},
  "geometry": {"coordinates":[-157.78576000000001,21.275325],"type":"Point"}
}