{
  "type": "Feature",
  "properties": {
    "addr:full":"1122 Mikole St Honolulu HI 96819",
    "addr:housenumber":"1122",
    "addr:postcode":"96819",
    "addr:street":"Mikole St",
    "iso:country":"US",
    "sg:address":"1122 Mikole St",
    "sg:city":"Honolulu",
    "sg:classifiers":[
        {
            "category":"Freight",
            "type":"Transportation"
        }
    ],
    "sg:phone":"+1 808 845 7775",
    "sg:postcode":"96819",
    "sg:province":"HI",
    "sg:tags":[
        "arrangement"
    ],
    "wof:name":"Island Customs Brokers",
    "wof:placetype":"venue"
},
  "geometry": {"coordinates":[-157.87455,21.303651],"type":"Point"}
}