{
  "type": "Feature",
  "properties": {
    "addr:full":"388 Nihoa St Kahului HI 96732",
    "addr:housenumber":"388",
    "addr:postcode":"96732",
    "addr:street":"Nihoa St",
    "iso:country":"US",
    "sg:address":"388 Nihoa St",
    "sg:city":"Kahului",
    "sg:classifiers":[
        {
            "category":"Freight",
            "type":"Transportation"
        }
    ],
    "sg:phone":"+1 808 249 8737",
    "sg:postcode":"96732",
    "sg:province":"HI",
    "sg:tags":[
        "hauling",
        "trucking"
    ],
    "wof:name":"S Funes Equipment Inc",
    "wof:placetype":"venue"
},
  "geometry": {"coordinates":[-156.48355900000001,20.900025],"type":"Point"}
}