{
  "type": "Feature",
  "properties": {
    "iso:country":"US",
    "sg:address":"19 N Kainalu Dr",
    "sg:city":"Kailua",
    "sg:classifiers":[
        {
            "category":"Building & Trades",
            "subcategory":"Construction",
            "type":"Services"
        }
    ],
    "sg:phone":"+1 808 261 2235",
    "sg:postcode":"96734",
    "sg:province":"HI",
    "sg:tags":[
        "remodeling"
    ],
    "wof:name":"Kan Builders",
    "wof:placetype":"venue"
},
  "geometry": {"coordinates":[-157.73942700000001,21.397228],"type":"Point"}
}