{
  "type": "Feature",
  "properties": {
    "addr:full":"2159 Kinoole St Hilo HI 96720",
    "addr:housenumber":"2159",
    "addr:postcode":"96720",
    "addr:street":"Kinoole St",
    "iso:country":"US",
    "sg:address":"2159 Kinoole St",
    "sg:city":"Hilo",
    "sg:classifiers":[
        {
            "category":"Building & Trades",
            "subcategory":"Construction",
            "type":"Services"
        }
    ],
    "sg:phone":"+1 808 959 5848",
    "sg:postcode":"96720",
    "sg:province":"HI",
    "sg:tags":[
        "contractor"
    ],
    "wof:name":"C & S Construction Co",
    "wof:placetype":"venue"
},
  "geometry": {"coordinates":[-155.06909400000001,19.685701],"type":"Point"}
}