{
  "type": "Feature",
  "properties": {
    "iso:country":"US",
    "sg:address":"3569 Waialae Ave",
    "sg:city":"Honolulu",
    "sg:classifiers":[
        {
            "category":"Restaurant",
            "type":"Food & Drink"
        }
    ],
    "sg:phone":"+1 808 738 8855",
    "sg:postcode":"96816",
    "sg:province":"HI",
    "sg:tags":[
        "eating"
    ],
    "wof:name":"Big City Diner Inc",
    "wof:placetype":"venue"
},
  "geometry": {"coordinates":[-157.79959400000001,21.282968],"type":"Point"}
}