{
  "type": "Feature",
  "properties": {
    "iso:country":"US",
    "sg:address":"318 Haiku Rd",
    "sg:city":"Kaneohe",
    "sg:classifiers":[
        {
            "category":"Banks & Credit Unions",
            "subcategory":"Bank",
            "type":"Services"
        }
    ],
    "sg:phone":"+1 808 236 3848",
    "sg:postcode":"96744",
    "sg:province":"HI",
    "sg:tags":[
        "mortgage"
    ],
    "wof:name":"Mortgage Savings of Hawaii",
    "wof:placetype":"venue"
},
  "geometry": {"coordinates":[-157.81574599999999,21.415046],"type":"Point"}
}