{
  "type": "Feature",
  "properties": {
    "iso:country":"US",
    "sg:address":"2636 Peter St",
    "sg:city":"Honolulu",
    "sg:classifiers":[
        {
            "category":"Professional",
            "subcategory":"Accounting & Tax Preparation",
            "type":"Services"
        }
    ],
    "sg:phone":"+1 808 732 4400",
    "sg:postcode":"96816",
    "sg:province":"HI",
    "sg:tags":[
        "bookkeeping",
        "general"
    ],
    "wof:name":"Abbie's Affordable Payroll",
    "wof:placetype":"venue"
},
  "geometry": {"coordinates":[-157.79972000000001,21.302919],"type":"Point"}
}