{
  "type": "Feature",
  "properties": {
    "iso:country":"US",
    "sg:address":"591 Kailua Rd",
    "sg:city":"Kailua",
    "sg:classifiers":[
        {
            "category":"Shopping",
            "subcategory":"Pharmacy",
            "type":"Retail Goods"
        }
    ],
    "sg:phone":"+1 808 261 8537",
    "sg:postcode":"96734",
    "sg:province":"HI",
    "sg:tags":[
        "drug",
        "store",
        "variety"
    ],
    "wof:name":"Longs Drug Store",
    "wof:placetype":"venue"
},
  "geometry": {"coordinates":[-157.74267699999999,21.394127],"type":"Point"}
}