{
  "type": "Feature",
  "properties": {
    "iso:country":"US",
    "sg:address":"421 Kalanikoa St",
    "sg:city":"Hilo",
    "sg:classifiers":[
        {
            "category":"Wholesale",
            "subcategory":"Farm Supplies",
            "type":"Manufacturing & Wholesale Goods"
        }
    ],
    "sg:phone":"+1 808 961 0376",
    "sg:postcode":"96720",
    "sg:province":"HI",
    "wof:name":"Big Island Game Fowl & Farm",
    "wof:placetype":"venue"
},
  "geometry": {"coordinates":[-155.06568200000001,19.71604],"type":"Point"}
}