{
  "type": "Feature",
  "properties": {
    "addr:full":"6393 Mamalahoa Hwy Kealakekua HI 96750",
    "addr:postcode":"6393;96750",
    "addr:street":"Mamalahoa Hwy",
    "iso:country":"US",
    "sg:address":"6393 Mamalahoa Hwy",
    "sg:city":"Kealakekua",
    "sg:classifiers":[
        {
            "category":"Building & Trades",
            "subcategory":"Pest Control",
            "type":"Services"
        }
    ],
    "sg:phone":"+1 808 323 3844",
    "sg:postcode":"96750",
    "sg:province":"HI",
    "sg:website":"www.hawaiifumigation.com",
    "wof:name":"Hawaii Fumigation & Pest Cntrl",
    "wof:placetype":"venue"
},
  "geometry": {"coordinates":[-155.92441700000001,19.528824],"type":"Point"}
}