{
  "type": "Feature",
  "properties": {
    "iso:country":"US",
    "sg:address":"658 Paopua Loop",
    "sg:city":"Kailua",
    "sg:classifiers":[
        {
            "category":"Professional",
            "subcategory":"Business Services",
            "type":"Services"
        }
    ],
    "sg:phone":"+1 808 261 7571",
    "sg:postcode":"96734",
    "sg:province":"HI",
    "sg:tags":[
        "preparation",
        "tax",
        "return"
    ],
    "wof:name":"Alan Kimball Consultant",
    "wof:placetype":"venue"
},
  "geometry": {"coordinates":[-157.728523,21.383464],"type":"Point"}
}