{
  "type": "Feature",
  "properties": {
    "iso:country":"US",
    "sg:address":"369 Nene St",
    "sg:city":"Hilo",
    "sg:classifiers":[
        {
            "category":"Travel",
            "subcategory":"Hotels & Motels",
            "type":"Entertainment"
        }
    ],
    "sg:phone":"+1 808 934 8040",
    "sg:postcode":"96720",
    "sg:province":"HI",
    "sg:tags":[
        "breakfast",
        "accommodation",
        "bed"
    ],
    "wof:name":"At The Beach With Friends",
    "wof:placetype":"venue"
},
  "geometry": {"coordinates":[-155.01655400000001,19.731868],"type":"Point"}
}