{
  "type": "Feature",
  "properties": {
    "addr:full":"2230 Liliha St Honolulu HI 96817",
    "addr:housenumber":"2230",
    "addr:postcode":"96817",
    "addr:street":"Liliha St",
    "iso:country":"US",
    "sg:address":"2230 Liliha St",
    "sg:city":"Honolulu",
    "sg:classifiers":[
        {
            "category":"Education",
            "subcategory":"Library",
            "type":"Public Place"
        }
    ],
    "sg:phone":"+1 808 547 6481",
    "sg:postcode":"96817",
    "sg:province":"HI",
    "sg:tags":[
        "special",
        "interest"
    ],
    "wof:name":"St Francis Med Ctr Med Library",
    "wof:placetype":"venue"
},
  "geometry": {"coordinates":[-157.85174900000001,21.328647],"type":"Point"}
}