{
  "type": "Feature",
  "properties": {
    "iso:country":"US",
    "sg:address":"1079 Moanalua Rd",
    "sg:city":"Aiea",
    "sg:classifiers":[
        {
            "category":"Health Services",
            "subcategory":"Doctor",
            "type":"Services"
        }
    ],
    "sg:phone":"+1 808 486 8630",
    "sg:postcode":"96701",
    "sg:province":"HI",
    "sg:tags":[
        "physician",
        "surgeon",
        "medical"
    ],
    "wof:name":"Ramin C Jamm MD",
    "wof:placetype":"venue"
},
  "geometry": {"coordinates":[-157.937757,21.383942],"type":"Point"}
}