{
  "type": "Feature",
  "properties": {
    "iso:country":"US",
    "sg:address":"2130 Farrington Hwy",
    "sg:city":"Waianae",
    "sg:classifiers":[
        {
            "category":"Food & Beverages",
            "subcategory":"Groceries & Convenience Stores",
            "type":"Retail Goods"
        }
    ],
    "sg:phone":"+1 808 668 1515",
    "sg:postcode":"96792",
    "sg:province":"HI",
    "wof:name":"Fastop Convenience Store 11",
    "wof:placetype":"venue"
},
  "geometry": {"coordinates":[-158.14870300000001,21.384568],"type":"Point"}
}