{
  "type": "Feature",
  "properties": {
    "addr:full":"52 Mango Pl Wahiawa HI 96786",
    "addr:housenumber":"52",
    "addr:postcode":"96786",
    "addr:street":"Mango Pl",
    "iso:country":"US",
    "sg:address":"52 Mango Pl",
    "sg:city":"Wahiawa",
    "sg:classifiers":[
        {
            "category":"Real Estate",
            "subcategory":"Real Estate Agent",
            "type":"Services"
        }
    ],
    "sg:phone":"+1 808 621 4707",
    "sg:postcode":"96786",
    "sg:province":"HI",
    "wof:name":"Almazan & Assoc Realty",
    "wof:placetype":"venue"
},
  "geometry": {"coordinates":[-158.02825300000001,21.497252],"type":"Point"}
}