{
  "type": "Feature",
  "properties": {
    "iso:country":"US",
    "sg:address":"2224 Ahaniu Pl",
    "sg:city":"Honolulu",
    "sg:classifiers":[
        {
            "category":"Professional",
            "type":"Services"
        }
    ],
    "sg:phone":"+1 808 737 1436",
    "sg:postcode":"96821",
    "sg:province":"HI",
    "sg:tags":[
        "establishment"
    ],
    "wof:name":"Jennetics International LTD",
    "wof:placetype":"venue"
},
  "geometry": {"coordinates":[-157.776814,21.296458],"type":"Point"}
}