{
  "type": "Feature",
  "properties": {
    "iso:country":"US",
    "sg:address":"45 Apalapani Ln",
    "sg:city":"Haiku",
    "sg:classifiers":[
        {
            "category":"Shopping",
            "subcategory":"Jewelry",
            "type":"Retail Goods"
        }
    ],
    "sg:phone":"+1 808 575 2391",
    "sg:postcode":"96708",
    "sg:province":"HI",
    "sg:tags":[
        "store",
        "gold",
        "silver"
    ],
    "wof:name":"REA Studio",
    "wof:placetype":"venue"
},
  "geometry": {"coordinates":[-156.30148199999999,20.896904],"type":"Point"}
}