{
  "type": "Feature",
  "properties": {
    "addr:full":"1029 Puuwai St Honolulu HI 96819",
    "addr:housenumber":"1029",
    "addr:postcode":"96819",
    "addr:street":"Puuwai St",
    "iso:country":"US",
    "sg:address":"1029 Puuwai St",
    "sg:city":"Honolulu",
    "sg:classifiers":[
        {
            "category":"Building & Trades",
            "subcategory":"Construction",
            "type":"Services"
        }
    ],
    "sg:phone":"+1 808 841 3327",
    "sg:postcode":"96819",
    "sg:province":"HI",
    "sg:tags":[
        "contractor"
    ],
    "wof:name":"Walter Y Arakaki Inc",
    "wof:placetype":"venue"
},
  "geometry": {"coordinates":[-157.87184400000001,21.302148],"type":"Point"}
}