{
  "type": "Feature",
  "properties": {
    "iso:country":"US",
    "sg:address":"2335 Kalakaua Ave",
    "sg:city":"Honolulu",
    "sg:classifiers":[
        {
            "category":"Restaurant",
            "type":"Food & Drink"
        }
    ],
    "sg:menulink":"http://www.allmenus.com/hi/honolulu/3392-dukes-canoe-club-waikiki/menu/",
    "sg:phone":"+1 808 922 2268",
    "sg:postcode":"96815",
    "sg:province":"HI",
    "sg:tags":[
        "seafood",
        "american"
    ],
    "wof:name":"Duke's Canoe Club Waikiki",
    "wof:placetype":"venue"
},
  "geometry": {"coordinates":[-157.82704000000001,21.277285],"type":"Point"}
}