{
  "type": "Feature",
  "properties": {
    "iso:country":"US",
    "sg:address":"1833 Kalakaua Ave",
    "sg:city":"Honolulu",
    "sg:classifiers":[
        {
            "category":"Professional",
            "subcategory":"Advertising",
            "type":"Services"
        }
    ],
    "sg:phone":"+1 808 945 2338",
    "sg:postcode":"96815",
    "sg:province":"HI",
    "sg:tags":[
        "counselor"
    ],
    "wof:name":"Rojas Advertising-Design",
    "wof:placetype":"venue"
},
  "geometry": {"coordinates":[-157.834372,21.288059],"type":"Point"}
}