{
  "type": "Feature",
  "properties": {
    "iso:country":"US",
    "sg:address":"408 N Kuakini St",
    "sg:city":"Honolulu",
    "sg:classifiers":[
        {
            "category":"Professional",
            "subcategory":"Management & Consulting",
            "type":"Services"
        }
    ],
    "sg:phone":"+1 808 526 1774",
    "sg:postcode":"96817",
    "sg:province":"HI",
    "sg:tags":[
        "food",
        "facility"
    ],
    "wof:name":"Mizo & Assoc",
    "wof:placetype":"venue"
},
  "geometry": {"coordinates":[-157.85667599999999,21.322798],"type":"Point"}
}