{
  "type": "Feature",
  "properties": {
    "addr:full":"120 Lilipuna Rd Kaneohe HI 96744",
    "addr:housenumber":"120",
    "addr:postcode":"96744",
    "addr:street":"Lilipuna Rd",
    "iso:country":"US",
    "sg:address":"120 Lilipuna Rd",
    "sg:city":"Kaneohe",
    "sg:classifiers":[
        {
            "category":"Manufacturing",
            "subcategory":"Rubber & Plastics",
            "type":"Manufacturing & Wholesale Goods"
        }
    ],
    "sg:phone":"+1 808 927 1085",
    "sg:postcode":"96744",
    "sg:province":"HI",
    "sg:tags":[
        "product",
        "metal",
        "mfg"
    ],
    "wof:name":"R S Services",
    "wof:placetype":"venue"
},
  "geometry": {"coordinates":[-157.79157699999999,21.420808],"type":"Point"}
}