{
  "type": "Feature",
  "properties": {
    "addr:full":"6372 Mamalahoa Hwy Kealakekua HI 96750",
    "addr:postcode":"6372;96750",
    "addr:street":"Mamalahoa Hwy",
    "iso:country":"US",
    "sg:address":"6372 Mamalahoa Hwy",
    "sg:city":"Kealakekua",
    "sg:classifiers":[
        {
            "category":"Restaurant",
            "type":"Food & Drink"
        }
    ],
    "sg:phone":"+1 808 323 2595",
    "sg:postcode":"96750",
    "sg:province":"HI",
    "wof:name":"Uncle Inbea's Steak House",
    "wof:placetype":"venue"
},
  "geometry": {"coordinates":[-155.924645,19.529136],"type":"Point"}
}