{
  "type": "Feature",
  "properties": {
    "iso:country":"US",
    "sg:address":"1810 University Ave",
    "sg:city":"Honolulu",
    "sg:classifiers":[
        {
            "category":"Organizations",
            "subcategory":"Non-profit Organization",
            "type":"Services"
        }
    ],
    "sg:phone":"+1 808 778 0315",
    "sg:postcode":"96822",
    "sg:province":"HI",
    "sg:tags":[
        "health",
        "mental",
        "social"
    ],
    "wof:name":"Hoomau Pono",
    "wof:placetype":"venue"
},
  "geometry": {"coordinates":[-157.82119399999999,21.299943],"type":"Point"}
}