{
  "type": "Feature",
  "properties": {
    "addr:full":"810 Kokomo Rd Haiku HI 96708",
    "addr:postcode":"96708",
    "addr:street":"810 Kokomo Rd",
    "iso:country":"US",
    "sg:address":"810 Kokomo Rd",
    "sg:city":"Haiku",
    "sg:classifiers":[
        {
            "category":"Home & Garden",
            "subcategory":"Furniture",
            "type":"Retail Goods"
        }
    ],
    "sg:phone":"+1 808 575 7678",
    "sg:postcode":"96708",
    "sg:province":"HI",
    "sg:tags":[
        "builder",
        "custom"
    ],
    "sg:website":"www.fogelvik.com",
    "wof:name":"Fogelvik Furniture",
    "wof:placetype":"venue"
},
  "geometry": {"coordinates":[-156.31251399999999,20.880446],"type":"Point"}
}