{
  "type": "Feature",
  "properties": {
    "iso:country":"US",
    "sg:address":"101 N Kihei Rd",
    "sg:city":"Kihei",
    "sg:classifiers":[
        {
            "category":"Personal",
            "type":"Services"
        }
    ],
    "sg:phone":"+1 808 891 8526",
    "sg:postcode":"96753",
    "sg:province":"HI",
    "sg:tags":[
        "consultant",
        "wedding"
    ],
    "wof:name":"Paradise Maui",
    "wof:placetype":"venue"
},
  "geometry": {"coordinates":[-156.47124199999999,20.788474],"type":"Point"}
}