{
  "type": "Feature",
  "properties": {
    "iso:country":"US",
    "sg:address":"1136 California Ave",
    "sg:city":"Wahiawa",
    "sg:classifiers":[
        {
            "category":"Government",
            "subcategory":"Office",
            "type":"Public Place"
        }
    ],
    "sg:phone":"+1 808 622 6421",
    "sg:postcode":"96786",
    "sg:province":"HI",
    "sg:tags":[
        "educational",
        "program",
        "administrative"
    ],
    "wof:name":"State of Hawaii",
    "wof:placetype":"venue"
},
  "geometry": {"coordinates":[-158.02146500000001,21.499788],"type":"Point"}
}