{
  "type": "Feature",
  "properties": {
    "iso:country":"US",
    "sg:address":"45 N Kamehameha Hwy",
    "sg:city":"Wahiawa",
    "sg:classifiers":[
        {
            "category":"Organizations",
            "subcategory":"Religious Organization",
            "type":"Services"
        }
    ],
    "sg:phone":"+1 808 621 1528",
    "sg:postcode":"96786",
    "sg:province":"HI",
    "sg:tags":[
        "church"
    ],
    "wof:name":"Wahiawa Regional Ctr",
    "wof:placetype":"venue"
},
  "geometry": {"coordinates":[-158.029967,21.496601],"type":"Point"}
}