{
  "type": "Feature",
  "properties": {
    "iso:country":"US",
    "sg:address":"5677 Lawehana St",
    "sg:city":"Kailua Kona",
    "sg:classifiers":[
        {
            "category":"Wholesale",
            "subcategory":"Seafood",
            "type":"Manufacturing & Wholesale Goods"
        }
    ],
    "sg:phone":"+1 808 331 2100",
    "sg:postcode":"96740",
    "sg:province":"HI",
    "wof:name":"Fresh Island Fish Co Inc",
    "wof:placetype":"venue"
},
  "geometry": {"coordinates":[-156.019263,19.684581],"type":"Point"}
}