{
  "type": "Feature",
  "properties": {
    "iso:country":"US",
    "sg:address":"808 Ahua St",
    "sg:city":"Honolulu",
    "sg:classifiers":[
        {
            "category":"Shopping",
            "subcategory":"Clothing, Apparel, & Fashions",
            "type":"Retail Goods"
        }
    ],
    "sg:phone":"+1 808 222 2932",
    "sg:postcode":"96819",
    "sg:province":"HI",
    "sg:tags":[
        "maternity"
    ],
    "wof:name":"Bloom & Blossoms",
    "wof:placetype":"venue"
},
  "geometry": {"coordinates":[-157.89572699999999,21.341019],"type":"Point"}
}