{
  "type": "Feature",
  "properties": {
    "iso:country":"US",
    "sg:address":"740 Kinalau Pl",
    "sg:city":"Honolulu",
    "sg:classifiers":[
        {
            "category":"Government",
            "subcategory":"Office",
            "type":"Public Place"
        }
    ],
    "sg:phone":"+1 808 527 6988",
    "sg:postcode":"96813",
    "sg:province":"HI",
    "sg:tags":[
        "city",
        "program"
    ],
    "wof:name":"Honolulu Transportation Dept",
    "wof:placetype":"venue"
},
  "geometry": {"coordinates":[-157.850371,21.306153],"type":"Point"}
}