{
  "type": "Feature",
  "properties": {
    "iso:country":"US",
    "sg:address":"5744 Alii Dr",
    "sg:city":"Kailua Kona",
    "sg:classifiers":[
        {
            "category":"Shopping",
            "subcategory":"Gifts & Souvenirs",
            "type":"Retail Goods"
        }
    ],
    "sg:phone":"+1 808 329 4348",
    "sg:postcode":"96740",
    "sg:province":"HI",
    "wof:name":"Tropical Art Glass",
    "wof:placetype":"venue"
},
  "geometry": {"coordinates":[-155.99330599999999,19.638125],"type":"Point"}
}