{
  "type": "Feature",
  "properties": {
    "iso:country":"US",
    "sg:address":"2248 Jennie St",
    "sg:city":"Honolulu",
    "sg:classifiers":[
        {
            "category":"Professional",
            "type":"Services"
        }
    ],
    "sg:phone":"+1 808 373 2742",
    "sg:postcode":"96819",
    "sg:province":"HI",
    "wof:name":"Le & Van Inc",
    "wof:placetype":"venue"
},
  "geometry": {"coordinates":[-157.86559199999999,21.346035],"type":"Point"}
}