{
  "type": "Feature",
  "properties": {
    "addr:full":"1643 9th Ave Honolulu HI 96816",
    "addr:housenumber":"1643",
    "addr:postcode":"96816",
    "addr:street":"9Th Ave",
    "iso:country":"US",
    "sg:address":"1643 9th Ave",
    "sg:city":"Honolulu",
    "sg:classifiers":[
        {
            "category":"Building & Trades",
            "subcategory":"Equipment Rental",
            "type":"Services"
        }
    ],
    "sg:phone":"+1 808 735 3719",
    "sg:postcode":"96816",
    "sg:province":"HI",
    "sg:tags":[
        "yard",
        "store"
    ],
    "wof:name":"Local Lifts Inc",
    "wof:placetype":"venue"
},
  "geometry": {"coordinates":[-157.79734099999999,21.292796],"type":"Point"}
}