{
  "type": "Feature",
  "properties": {
    "addr:full":"1011 Waianuenue Ave Hilo HI 96720",
    "addr:housenumber":"1011",
    "addr:postcode":"96720",
    "addr:street":"Waianuenue Ave",
    "iso:country":"US",
    "sg:address":"1011 Waianuenue Ave",
    "sg:city":"Hilo",
    "sg:classifiers":[
        {
            "category":"Health Services",
            "subcategory":"Nursing And Care Facility",
            "type":"Services"
        }
    ],
    "sg:phone":"+1 808 969 1733",
    "sg:postcode":"96720",
    "sg:province":"HI",
    "sg:tags":[
        "home"
    ],
    "sg:website":"www.hospiceofhilo.org",
    "wof:name":"Hospice Of Hilo",
    "wof:placetype":"venue"
},
  "geometry": {"coordinates":[-155.10566700000001,19.716982],"type":"Point"}
}