{
  "type": "Feature",
  "properties": {
    "iso:country":"US",
    "sg:address":"3040 Umi St",
    "sg:city":"Lihue",
    "sg:classifiers":[
        {
            "category":"Health Services",
            "subcategory":"Nursing And Care Facility",
            "type":"Services"
        }
    ],
    "sg:phone":"+1 808 241 3387",
    "sg:postcode":"96766",
    "sg:province":"HI",
    "sg:tags":[
        "skilled"
    ],
    "wof:name":"Kawaii Public Health Nursing",
    "wof:placetype":"venue"
},
  "geometry": {"coordinates":[-159.36615900000001,21.975347],"type":"Point"}
}