{
  "type": "Feature",
  "properties": {
    "iso:country":"US",
    "sg:address":"1504 Lanikuhana Ave",
    "sg:city":"Mililani",
    "sg:classifiers":[
        {
            "category":"Retail",
            "subcategory":"Auto Repair",
            "type":"Services"
        }
    ],
    "sg:phone":"+1 808 625 5465",
    "sg:postcode":"96789",
    "sg:province":"HI",
    "sg:tags":[
        "general"
    ],
    "wof:name":"Blizzard Auto A/C LLC",
    "wof:placetype":"venue"
},
  "geometry": {"coordinates":[-158.006348,21.445592],"type":"Point"}
}