{
  "type": "Feature",
  "properties": {
    "iso:country":"US",
    "sg:address":"346 Waianuenue Ave",
    "sg:city":"Hilo",
    "sg:classifiers":[
        {
            "category":"Health Services",
            "subcategory":"Doctor",
            "type":"Services"
        }
    ],
    "sg:phone":"+1 808 961 9040",
    "sg:postcode":"96720",
    "sg:province":"HI",
    "sg:tags":[
        "physician",
        "surgeon"
    ],
    "wof:name":"Robert S Shapiro MD",
    "wof:placetype":"venue"
},
  "geometry": {"coordinates":[-155.09096,19.724147],"type":"Point"}
}