{
  "type": "Feature",
  "properties": {
    "iso:country":"US",
    "sg:address":"941 Halawa Valley St",
    "sg:city":"Aiea",
    "sg:classifiers":[
        {
            "category":"Restaurant",
            "type":"Food & Drink"
        }
    ],
    "sg:phone":"+1 808 487 2016",
    "sg:postcode":"96701",
    "sg:province":"HI",
    "sg:tags":[
        "eating"
    ],
    "wof:name":"Henry Sandoval",
    "wof:placetype":"venue"
},
  "geometry": {"coordinates":[-157.908208,21.373271],"type":"Point"}
}