{
  "type": "Feature",
  "properties": {
    "addr:full":"690 Pohukaina St Honolulu HI 96813",
    "addr:housenumber":"690",
    "addr:postcode":"96813",
    "addr:street":"Pohukaina St",
    "iso:country":"US",
    "sg:address":"690 Pohukaina St",
    "sg:city":"Honolulu",
    "sg:classifiers":[
        {
            "category":"Government",
            "subcategory":"Office",
            "type":"Public Place"
        }
    ],
    "sg:phone":"+1 808 537 6381",
    "sg:postcode":"96813",
    "sg:province":"HI",
    "wof:name":"Centralized Processing",
    "wof:placetype":"venue"
},
  "geometry": {"coordinates":[-157.859838,21.299923],"type":"Point"}
}