{
  "type": "Feature",
  "properties": {
    "addr:full":"3203 Winam Ave Honolulu HI 96816",
    "addr:housenumber":"3203",
    "addr:postcode":"96816",
    "addr:street":"Winam Ave",
    "iso:country":"US",
    "sg:address":"3203 Winam Ave",
    "sg:city":"Honolulu",
    "sg:classifiers":[
        {
            "category":"Local Transit",
            "type":"Transportation"
        }
    ],
    "sg:phone":"+1 808 226 8944",
    "sg:postcode":"96816",
    "sg:province":"HI",
    "sg:tags":[
        "limousine"
    ],
    "wof:name":"Ali Limousine",
    "wof:placetype":"venue"
},
  "geometry": {"coordinates":[-157.81310099999999,21.280704],"type":"Point"}
}