{
  "type": "Feature",
  "properties": {
    "iso:country":"US",
    "sg:address":"232 Hui Akikiki Pl",
    "sg:city":"Kaneohe",
    "sg:classifiers":[
        {
            "category":"Shopping",
            "subcategory":"Catalog Store",
            "type":"Retail Goods"
        }
    ],
    "sg:phone":"+1 808 239 4128",
    "sg:postcode":"96744",
    "sg:province":"HI",
    "sg:tags":[
        "mail",
        "house"
    ],
    "wof:name":"Hoala Hawaii",
    "wof:placetype":"venue"
},
  "geometry": {"coordinates":[-157.82509899999999,21.437079],"type":"Point"}
}