{
  "type": "Feature",
  "properties": {
    "iso:country":"US",
    "sg:address":"2752 Woodlawn Dr",
    "sg:city":"Honolulu",
    "sg:classifiers":[
        {
            "category":"Banks & Credit Unions",
            "subcategory":"Bank",
            "type":"Services"
        }
    ],
    "sg:phone":"+1 808 988 9194",
    "sg:postcode":"96822",
    "sg:province":"HI",
    "sg:tags":[
        "broker",
        "mortgage"
    ],
    "wof:name":"USA Mortgage Corporation",
    "wof:placetype":"venue"
},
  "geometry": {"coordinates":[-157.810046,21.307362],"type":"Point"}
}