{
  "type": "Feature",
  "properties": {
    "iso:country":"US",
    "sg:address":"67 Kaneohe Bay Dr",
    "sg:city":"Kaneohe",
    "sg:classifiers":[
        {
            "category":"Professional",
            "subcategory":"Computer Services",
            "type":"Services"
        }
    ],
    "sg:phone":"+1 808 234 1288",
    "sg:postcode":"96744",
    "sg:province":"HI",
    "sg:tags":[
        "repair"
    ],
    "wof:name":"Hawaii Publishers",
    "wof:placetype":"venue"
},
  "geometry": {"coordinates":[-157.777615,21.410712],"type":"Point"}
}