{
  "type": "Feature",
  "properties": {
    "addr:full":"5039 Queen Kaahumanu Hwy Kailua Kona HI 96740",
    "addr:housenumber":"5039",
    "addr:postcode":"96740",
    "addr:street":"Queen Kaahumanu Hwy",
    "iso:country":"US",
    "sg:address":"5039 Queen Kaahumanu Hwy",
    "sg:city":"Kailua Kona",
    "sg:classifiers":[
        {
            "category":"Building & Trades",
            "subcategory":"Construction",
            "type":"Services"
        }
    ],
    "sg:phone":"+1 808 327 6555",
    "sg:postcode":"96740",
    "sg:province":"HI",
    "sg:tags":[
        "granite",
        "stone",
        "contractor"
    ],
    "wof:name":"Stoneworks LLC",
    "wof:placetype":"venue"
},
  "geometry": {"coordinates":[-155.98992699999999,19.644722],"type":"Point"}
}