{
  "type": "Feature",
  "properties": {
    "iso:country":"US",
    "sg:address":"1146 Ala Kapua St",
    "sg:city":"Kailua Kona",
    "sg:classifiers":[
        {
            "category":"Restaurant",
            "type":"Food & Drink"
        }
    ],
    "sg:phone":"+1 808 935 7880",
    "sg:postcode":"96740",
    "sg:province":"HI",
    "sg:tags":[
        "eating"
    ],
    "wof:name":"Restaurant Satsuki",
    "wof:placetype":"venue"
},
  "geometry": {"coordinates":[-156.009117,19.719817],"type":"Point"}
}