{
  "type": "Feature",
  "properties": {
    "addr:full":"4958 Kiwi St Kailua Kona HI 96740",
    "addr:housenumber":"4958",
    "addr:postcode":"96740",
    "addr:street":"Kiwi St",
    "iso:country":"US",
    "sg:address":"4958 Kiwi St",
    "sg:city":"Kailua Kona",
    "sg:classifiers":[
        {
            "category":"Building & Trades",
            "subcategory":"Landscaping Services",
            "type":"Services"
        }
    ],
    "sg:phone":"+1 808 329 8644",
    "sg:postcode":"96740",
    "sg:province":"HI",
    "sg:tags":[
        "landscape",
        "contractor"
    ],
    "wof:name":"Orchid Isle Landscaping Co",
    "wof:placetype":"venue"
},
  "geometry": {"coordinates":[-155.982561,19.678338],"type":"Point"}
}