{
  "type": "Feature",
  "properties": {
    "iso:country":"US",
    "sg:address":"60 S Wakea Ave",
    "sg:city":"Kahului",
    "sg:classifiers":[
        {
            "category":"Retail",
            "subcategory":"Car Wash",
            "type":"Services"
        }
    ],
    "sg:phone":"+1 808 893 0751",
    "sg:postcode":"96732",
    "sg:province":"HI",
    "sg:tags":[
        "polishing",
        "washing"
    ],
    "wof:name":"Bodashes Auto Detailing",
    "wof:placetype":"venue"
},
  "geometry": {"coordinates":[-156.47848999999999,20.886734],"type":"Point"}
}