{
  "type": "Feature",
  "properties": {
    "addr:full":"2335 Kalakaua Ave Honolulu HI 96815",
    "addr:housenumber":"2335",
    "addr:postcode":"96815",
    "addr:street":"Kalakaua Ave",
    "iso:country":"US",
    "sg:address":"2335 Kalakaua Ave",
    "sg:city":"Honolulu",
    "sg:classifiers":[
        {
            "category":"Shopping",
            "subcategory":"Luggage & Leather Goods",
            "type":"Retail Goods"
        }
    ],
    "sg:phone":"+1 808 923 0549",
    "sg:postcode":"96815",
    "sg:province":"HI",
    "sg:website":"www.coach.com",
    "wof:name":"Coach Store",
    "wof:placetype":"venue"
},
  "geometry": {"coordinates":[-157.826742,21.277063],"type":"Point"}
}