{
  "type": "Feature",
  "properties": {
    "iso:country":"US",
    "sg:address":"3075 Waialae Ave",
    "sg:city":"Honolulu",
    "sg:classifiers":[
        {
            "category":"Autos & Motor Vehicles",
            "subcategory":"Fuel & Gas Station",
            "type":"Retail Goods"
        }
    ],
    "sg:phone":"+1 808 734 2288",
    "sg:postcode":"96816",
    "sg:province":"HI",
    "sg:tags":[
        "oil"
    ],
    "wof:name":"St Louis Shell Svc",
    "wof:placetype":"venue"
},
  "geometry": {"coordinates":[-157.81093200000001,21.288748],"type":"Point"}
}