{
  "type": "Feature",
  "properties": {
    "iso:country":"US",
    "sg:address":"3430 Maunaloa Ave",
    "sg:city":"Honolulu",
    "sg:classifiers":[
        {
            "category":"Education",
            "subcategory":"Special Training",
            "type":"Public Place"
        }
    ],
    "sg:phone":"+1 808 734 7323",
    "sg:postcode":"96816",
    "sg:province":"HI",
    "sg:tags":[
        "tutoring"
    ],
    "wof:name":"Kumon USA",
    "wof:placetype":"venue"
},
  "geometry": {"coordinates":[-157.80710400000001,21.27872],"type":"Point"}
}