{
  "type": "Feature",
  "properties": {
    "addr:full":"323 Alae Rd Kula HI 96790",
    "addr:housenumber":"323",
    "addr:postcode":"96790",
    "addr:street":"Alae Rd",
    "iso:country":"US",
    "sg:address":"323 Alae Rd",
    "sg:city":"Kula",
    "sg:classifiers":[
        {
            "category":"Building & Trades",
            "subcategory":"Construction",
            "type":"Services"
        }
    ],
    "sg:phone":"+1 808 878 6938",
    "sg:postcode":"96790",
    "sg:province":"HI",
    "sg:tags":[
        "tile",
        "dealer"
    ],
    "wof:name":"Outer Island Tile",
    "wof:placetype":"venue"
},
  "geometry": {"coordinates":[-156.323081,20.747176],"type":"Point"}
}