{
  "type": "Feature",
  "properties": {
    "addr:full":"4521 Lower Honoapiilani Rd Lahaina HI 96761",
    "addr:housenumber":"4521",
    "addr:postcode":"96761",
    "addr:street":"Lower Honoapiilani Rd",
    "iso:country":"US",
    "sg:address":"4521 Lower Honoapiilani Rd",
    "sg:city":"Lahaina",
    "sg:classifiers":[
        {
            "category":"Organizations",
            "subcategory":"Professional Association",
            "type":"Services"
        }
    ],
    "sg:phone":"+1 808 669 6505",
    "sg:postcode":"96761",
    "sg:province":"HI",
    "wof:name":"Kahana Outrigger Assn",
    "wof:placetype":"venue"
},
  "geometry": {"coordinates":[-156.677603,20.975488],"type":"Point"}
}