{
  "type": "Feature",
  "properties": {
    "addr:full":"524 Mahoe St Waipahu HI 96797",
    "addr:housenumber":"524",
    "addr:postcode":"96797",
    "addr:street":"Mahoe St",
    "iso:country":"US",
    "sg:address":"524 Mahoe St",
    "sg:city":"Waipahu",
    "sg:classifiers":[
        {
            "category":"Arts & Performance",
            "subcategory":"Theater",
            "type":"Entertainment"
        }
    ],
    "sg:phone":"+1 808 671 8537",
    "sg:postcode":"96797",
    "sg:province":"HI",
    "sg:tags":[
        "group"
    ],
    "wof:name":"So Far",
    "wof:placetype":"venue"
},
  "geometry": {"coordinates":[-158.003657,21.395551],"type":"Point"}
}