{
  "type": "Feature",
  "properties": {
    "addr:full":"1002 Waieli St Honolulu HI 96821",
    "addr:housenumber":"1002",
    "addr:postcode":"96821",
    "addr:street":"Waieli St",
    "iso:country":"US",
    "sg:address":"1002 Waieli St",
    "sg:city":"Honolulu",
    "sg:classifiers":[
        {
            "category":"Health Services",
            "subcategory":"Clinic",
            "type":"Services"
        }
    ],
    "sg:phone":"+1 808 382 7632",
    "sg:postcode":"96821",
    "sg:province":"HI",
    "wof:name":"Pacific Medical Concepts",
    "wof:placetype":"venue"
},
  "geometry": {"coordinates":[-157.775724,21.275407],"type":"Point"}
}