{
  "type": "Feature",
  "properties": {
    "iso:country":"US",
    "sg:address":"372 Waiehu Beach Rd",
    "sg:city":"Wailuku",
    "sg:classifiers":[
        {
            "category":"Food & Beverages",
            "subcategory":"Groceries & Convenience Stores",
            "type":"Retail Goods"
        }
    ],
    "sg:phone":"+1 808 244 2323",
    "sg:postcode":"96793",
    "sg:province":"HI",
    "wof:name":"Tom's Mini Mart",
    "wof:placetype":"venue"
},
  "geometry": {"coordinates":[-156.48447200000001,20.904892],"type":"Point"}
}