{
  "type": "Feature",
  "properties": {
    "addr:full":"20 Puukani Pl Kailua HI 96734",
    "addr:housenumber":"20",
    "addr:postcode":"96734",
    "addr:street":"Puukani Pl",
    "iso:country":"US",
    "sg:address":"20 Puukani Pl",
    "sg:city":"Kailua",
    "sg:classifiers":[
        {
            "category":"Real Estate",
            "subcategory":"Architect",
            "type":"Services"
        }
    ],
    "sg:phone":"+1 808 261 6524",
    "sg:postcode":"96734",
    "sg:province":"HI",
    "wof:name":"Gary Canner",
    "wof:placetype":"venue"
},
  "geometry": {"coordinates":[-157.73102,21.397958],"type":"Point"}
}