{
  "type": "Feature",
  "properties": {
    "addr:full":"515 S Kihei Rd Kihei HI 96753",
    "addr:housenumber":"515",
    "addr:postcode":"96753",
    "addr:street":"S Kihei Rd",
    "iso:country":"US",
    "sg:address":"515 S Kihei Rd",
    "sg:city":"Kihei",
    "sg:classifiers":[
        {
            "category":"Food & Beverages",
            "subcategory":"Groceries & Convenience Stores",
            "type":"Retail Goods"
        },
        {
            "category":"Real Estate",
            "subcategory":"Real Estate Operator",
            "type":"Services"
        }
    ],
    "sg:phone":"+1 808 879 7800",
    "sg:postcode":"96753",
    "sg:province":"HI",
    "sg:tags":[
        "ope",
        "condominium"
    ],
    "wof:name":"Maui Beach Resort",
    "wof:placetype":"venue"
},
  "geometry": {"coordinates":[-156.46072699999999,20.773105],"type":"Point"}
}