{
  "type": "Feature",
  "properties": {
    "addr:full":"5210 Likini St Honolulu HI 96818",
    "addr:housenumber":"5210",
    "addr:postcode":"96818",
    "addr:street":"Likini St",
    "iso:country":"US",
    "sg:address":"5210 Likini St",
    "sg:city":"Honolulu",
    "sg:classifiers":[
        {
            "category":"Building & Trades",
            "subcategory":"Electrical",
            "type":"Services"
        }
    ],
    "sg:phone":"+1 808 839 5211",
    "sg:postcode":"96818",
    "sg:province":"HI",
    "sg:tags":[
        "electrical",
        "contractor"
    ],
    "wof:name":"Nakada Electric",
    "wof:placetype":"venue"
},
  "geometry": {"coordinates":[-157.90633299999999,21.346282],"type":"Point"}
}