{
  "type": "Feature",
  "properties": {
    "iso:country":"US",
    "sg:address":"793 Halawa Heights Rd",
    "sg:city":"Aiea",
    "sg:classifiers":[
        {
            "category":"Food & Beverages",
            "subcategory":"Groceries & Convenience Stores",
            "type":"Retail Goods"
        }
    ],
    "sg:phone":"+1 808 488 8754",
    "sg:postcode":"96701",
    "sg:province":"HI",
    "sg:tags":[
        "grocer"
    ],
    "wof:name":"Halawa Heights Market Inc",
    "wof:placetype":"venue"
},
  "geometry": {"coordinates":[-157.91497899999999,21.37967],"type":"Point"}
}