{
  "type": "Feature",
  "properties": {
    "iso:country":"US",
    "sg:address":"227 Wehena Pl",
    "sg:city":"Waipahu",
    "sg:classifiers":[
        {
            "category":"Professional",
            "subcategory":"Research",
            "type":"Services"
        }
    ],
    "sg:phone":"+1 808 677 8554",
    "sg:postcode":"96797",
    "sg:province":"HI",
    "wof:name":"Patsy A Goding",
    "wof:placetype":"venue"
},
  "geometry": {"coordinates":[-158.00192100000001,21.401766],"type":"Point"}
}