{
  "type": "Feature",
  "properties": {
    "addr:full":"497 Ilima St Honokaa HI 96727",
    "addr:housenumber":"497",
    "addr:postcode":"96727",
    "addr:street":"Ilima St",
    "iso:country":"US",
    "sg:address":"497 Ilima St",
    "sg:city":"Honokaa",
    "sg:classifiers":[
        {
            "category":"Health Services",
            "subcategory":"Doctor",
            "type":"Services"
        }
    ],
    "sg:phone":"+1 808 775 0624",
    "sg:postcode":"96727",
    "sg:province":"HI",
    "sg:tags":[
        "dentist"
    ],
    "wof:name":"Edmund W O Akioka DDS",
    "wof:placetype":"venue"
},
  "geometry": {"coordinates":[-155.46299099999999,20.079687],"type":"Point"}
}