{
  "type": "Feature",
  "properties": {
    "iso:country":"US",
    "sg:address":"248 Olomea Pl",
    "sg:city":"Kailua Kona",
    "sg:classifiers":[
        {
            "category":"Wholesale",
            "subcategory":"Groceries",
            "type":"Manufacturing & Wholesale Goods"
        }
    ],
    "sg:phone":"+1 808 329 2348",
    "sg:postcode":"96740",
    "sg:province":"HI",
    "sg:tags":[
        "tea",
        "coffee"
    ],
    "wof:name":"Puunani Coffee Co",
    "wof:placetype":"venue"
},
  "geometry": {"coordinates":[-155.971632,19.616023],"type":"Point"}
}