{
  "type": "Feature",
  "properties": {
    "addr:full":"91 Sand Island Access Rd Honolulu HI 96819",
    "addr:housenumber":"91",
    "addr:postcode":"96819",
    "addr:street":"Sand Island Access Rd",
    "iso:country":"US",
    "sg:address":"91 Sand Island Access Rd",
    "sg:city":"Honolulu",
    "sg:classifiers":[
        {
            "category":"Government",
            "subcategory":"Post Office",
            "type":"Public Place"
        }
    ],
    "sg:phone":"+1 808 832 0046",
    "sg:postcode":"96819",
    "sg:province":"HI",
    "wof:name":"US Post Office",
    "wof:placetype":"venue"
},
  "geometry": {"coordinates":[-157.89149,21.32262],"type":"Point"}
}