{
  "type": "Feature",
  "properties": {
    "iso:country":"US",
    "sg:address":"330 Hoohana St",
    "sg:city":"Kahului",
    "sg:classifiers":[
        {
            "category":"Retail",
            "subcategory":"Auto Repair",
            "type":"Services"
        }
    ],
    "sg:phone":"+1 808 871 7676",
    "sg:postcode":"96732",
    "sg:province":"HI",
    "sg:tags":[
        "repairing",
        "automobile"
    ],
    "wof:name":"Big Al's V'W' Auto Svc",
    "wof:placetype":"venue"
},
  "geometry": {"coordinates":[-156.461174,20.883571],"type":"Point"}
}