{
  "type": "Feature",
  "properties": {
    "iso:country":"US",
    "sg:address":"2435 Kaanapali Pkwy",
    "sg:city":"Lahaina",
    "sg:classifiers":[
        {
            "category":"Restaurant",
            "type":"Food & Drink"
        }
    ],
    "sg:phone":"+1 808 667 5377",
    "sg:postcode":"96761",
    "sg:province":"HI",
    "sg:tags":[
        "parlor",
        "ice",
        "cream"
    ],
    "wof:name":"Haagen-Dazs Ice Cream",
    "wof:placetype":"venue"
},
  "geometry": {"coordinates":[-156.69540599999999,20.924222],"type":"Point"}
}