{
  "type": "Feature",
  "properties": {
    "iso:country":"US",
    "sg:address":"4151 Momi St",
    "sg:city":"Kilauea",
    "sg:classifiers":[
        {
            "category":"Professional",
            "subcategory":"Business Services",
            "type":"Services"
        },
        {
            "category":"Shopping",
            "subcategory":"Clothing, Apparel, & Fashions",
            "type":"Retail Goods"
        }
    ],
    "sg:phone":"+1 808 828 1638",
    "sg:postcode":"96754",
    "sg:province":"HI",
    "sg:tags":[
        "woman",
        "embroidery"
    ],
    "wof:name":"Laurie J's Custom Fashions",
    "wof:placetype":"venue"
},
  "geometry": {"coordinates":[-159.40385000000001,22.21071],"type":"Point"}
}