{
  "type": "Feature",
  "properties": {
    "addr:full":"1520 Liliha St Honolulu HI 96817",
    "addr:housenumber":"1520",
    "addr:postcode":"96817",
    "addr:street":"Liliha St",
    "iso:country":"US",
    "sg:address":"1520 Liliha St",
    "sg:city":"Honolulu",
    "sg:classifiers":[
        {
            "category":"Health Services",
            "subcategory":"Doctor",
            "type":"Services"
        }
    ],
    "sg:phone":"+1 808 524 8344",
    "sg:postcode":"96817",
    "sg:province":"HI",
    "sg:tags":[
        "dentist"
    ],
    "wof:name":"Todays Dental",
    "wof:placetype":"venue"
},
  "geometry": {"coordinates":[-157.860365,21.32138],"type":"Point"}
}