{
  "type": "Feature",
  "properties": {
    "iso:country":"US",
    "sg:address":"445 Kalamauka Rd",
    "sg:city":"Holualoa",
    "sg:classifiers":[
        {
            "category":"Professional",
            "subcategory":"Business Services",
            "type":"Services"
        }
    ],
    "sg:phone":"+1 808 324 7907",
    "sg:postcode":"96725",
    "sg:province":"HI",
    "sg:tags":[
        "translator",
        "interpreter"
    ],
    "wof:name":"Kona Wisteria Inc",
    "wof:placetype":"venue"
},
  "geometry": {"coordinates":[-155.953722,19.606445],"type":"Point"}
}