{
  "type": "Feature",
  "properties": {
    "iso:country":"US",
    "sg:address":"555 Kaukahi St",
    "sg:city":"Kihei",
    "sg:classifiers":[
        {
            "category":"Travel",
            "subcategory":"Hotels & Motels",
            "type":"Entertainment"
        }
    ],
    "sg:phone":"+1 808 874 0500",
    "sg:postcode":"96753",
    "sg:province":"HI",
    "sg:tags":[
        "operation",
        "eating",
        "drinking"
    ],
    "wof:name":"Diamond Resort Hawaii Corp",
    "wof:placetype":"venue"
},
  "geometry": {"coordinates":[-156.43335999999999,20.675774],"type":"Point"}
}