{
  "type": "Feature",
  "properties": {
    "iso:country":"US",
    "sg:address":"905 Makahiki Way",
    "sg:city":"Honolulu",
    "sg:classifiers":[
        {
            "category":"Recreation",
            "type":"Entertainment"
        },
        {
            "category":"Arena",
            "subcategory":"Sports Club",
            "type":"Entertainment"
        }
    ],
    "sg:phone":"+1 808 973 7247",
    "sg:postcode":"96826",
    "sg:province":"HI",
    "sg:tags":[
        "professional",
        "baseball",
        "winter",
        "league"
    ],
    "wof:name":"Hawaii Winter Baseball League",
    "wof:placetype":"venue"
},
  "geometry": {"coordinates":[-157.827642,21.292961],"type":"Point"}
}