{
  "type": "Feature",
  "properties": {
    "addr:full":"1716 Ala Amoamo St Honolulu HI 96819",
    "addr:housenumber":"1716",
    "addr:postcode":"96819",
    "addr:street":"Ala Amoamo St",
    "iso:country":"US",
    "sg:address":"1716 Ala Amoamo St",
    "sg:city":"Honolulu",
    "sg:classifiers":[
        {
            "category":"Professional",
            "subcategory":"Business Services",
            "type":"Services"
        }
    ],
    "sg:phone":"+1 808 945 5613",
    "sg:postcode":"96819",
    "sg:province":"HI",
    "wof:name":"Leslie J Lum",
    "wof:placetype":"venue"
},
  "geometry": {"coordinates":[-157.88312999999999,21.355274],"type":"Point"}
}