{
  "type": "Feature",
  "properties": {
    "iso:country":"US",
    "sg:address":"500 Iao Valley Rd",
    "sg:city":"Wailuku",
    "sg:classifiers":[
        {
            "category":"Manufacturing",
            "subcategory":"Food",
            "type":"Manufacturing & Wholesale Goods"
        },
        {
            "category":"Wholesale",
            "subcategory":"Groceries",
            "type":"Manufacturing & Wholesale Goods"
        }
    ],
    "sg:phone":"+1 808 242 0741",
    "sg:postcode":"96793",
    "sg:province":"HI",
    "sg:tags":[
        "baker",
        "product",
        "mfg"
    ],
    "wof:name":"Nancy Brown's Bread",
    "wof:placetype":"venue"
},
  "geometry": {"coordinates":[-156.527457,20.88309],"type":"Point"}
}