{
  "type": "Feature",
  "properties": {
    "addr:full":"2860 Lower Kula Rd Kula HI 96790",
    "addr:postcode":"2860;96790",
    "addr:street":"Lower Kula Rd",
    "iso:country":"US",
    "sg:address":"2860 Lower Kula Rd",
    "sg:city":"Kula",
    "sg:classifiers":[
        {
            "category":"Professional",
            "subcategory":"Accounting & Tax Preparation",
            "type":"Services"
        }
    ],
    "sg:phone":"+1 808 878 2703",
    "sg:postcode":"96790",
    "sg:province":"HI",
    "sg:tags":[
        "bookkeeping",
        "general"
    ],
    "wof:name":"Excel Bookkeeping Svc",
    "wof:placetype":"venue"
},
  "geometry": {"coordinates":[-156.32653199999999,20.783292],"type":"Point"}
}