{
  "type": "Feature",
  "properties": {
    "iso:country":"US",
    "sg:address":"3269 Koapaka St",
    "sg:city":"Honolulu",
    "sg:classifiers":[
        {
            "category":"Wholesale",
            "subcategory":"Machinery & Supplies",
            "type":"Manufacturing & Wholesale Goods"
        },
        {
            "category":"Wholesale",
            "subcategory":"Electrical",
            "type":"Manufacturing & Wholesale Goods"
        }
    ],
    "sg:phone":"+1 808 836 1371",
    "sg:postcode":"96819",
    "sg:province":"HI",
    "sg:tags":[
        "transmission",
        "equipment",
        "industrial",
        "power",
        "bearing"
    ],
    "wof:name":"Kaman Industrial Tech Corp",
    "wof:placetype":"venue"
},
  "geometry": {"coordinates":[-157.90828999999999,21.334893],"type":"Point"}
}