{
  "type": "Feature",
  "properties": {
    "iso:country":"US",
    "sg:address":"2377 Saint Louis Dr",
    "sg:city":"Honolulu",
    "sg:classifiers":[
        {
            "category":"Professional",
            "subcategory":"Management & Consulting",
            "type":"Services"
        }
    ],
    "sg:phone":"+1 808 783 2314",
    "sg:postcode":"96816",
    "sg:province":"HI",
    "sg:tags":[
        "meeting"
    ],
    "wof:name":"Donna Ching",
    "wof:placetype":"venue"
},
  "geometry": {"coordinates":[-157.80226999999999,21.301337],"type":"Point"}
}