{
  "type": "Feature",
  "properties": {
    "iso:country":"US",
    "sg:address":"430 Kele St",
    "sg:city":"Kahului",
    "sg:classifiers":[
        {
            "category":"Building & Trades",
            "subcategory":"Equipment Rental",
            "type":"Services"
        }
    ],
    "sg:phone":"+1 808 871 8887",
    "sg:postcode":"96732",
    "sg:province":"HI",
    "sg:tags":[
        "yard"
    ],
    "wof:name":"Rent-A-Center",
    "wof:placetype":"venue"
},
  "geometry": {"coordinates":[-156.45299600000001,20.886813],"type":"Point"}
}