{
  "type": "Feature",
  "properties": {
    "iso:country":"US",
    "sg:address":"95 Mahalani St",
    "sg:city":"Wailuku",
    "sg:classifiers":[
        {
            "category":"Organizations",
            "subcategory":"Professional Association",
            "type":"Services"
        }
    ],
    "sg:phone":"+1 808 244 5553",
    "sg:postcode":"96793",
    "sg:province":"HI",
    "wof:name":"American Cancer Society",
    "wof:placetype":"venue"
},
  "geometry": {"coordinates":[-156.49069900000001,20.888108],"type":"Point"}
}