{
  "type": "Feature",
  "properties": {
    "addr:full":"325 Ewa Beach Rd Ewa Beach HI 96706",
    "addr:housenumber":"325",
    "addr:postcode":"96706",
    "addr:street":"Ewa Beach Rd",
    "iso:country":"US",
    "sg:address":"325 Ewa Beach Rd",
    "sg:city":"Ewa Beach",
    "sg:classifiers":[
        {
            "category":"Local Transit",
            "type":"Transportation"
        }
    ],
    "sg:phone":"+1 808 484 7700",
    "sg:postcode":"96706",
    "sg:province":"HI",
    "wof:name":"Dispatch Office",
    "wof:placetype":"venue"
},
  "geometry": {"coordinates":[-157.994182,21.314652],"type":"Point"}
}