{
  "type": "Feature",
  "properties": {
    "iso:country":"US",
    "sg:address":"3440 Leahi Ave",
    "sg:city":"Honolulu",
    "sg:classifiers":[
        {
            "category":"Education",
            "subcategory":"School",
            "type":"Public Place"
        }
    ],
    "sg:phone":"+1 808 733 4999",
    "sg:postcode":"96815",
    "sg:province":"HI",
    "sg:tags":[
        "academic",
        "special"
    ],
    "sg:website":"www.hcdb.k12.hi.us",
    "wof:name":"Hawaii Center-Deaf & Blind",
    "wof:placetype":"venue"
},
  "geometry": {"coordinates":[-157.81589500000001,21.273202],"type":"Point"}
}