{
  "type": "Feature",
  "properties": {
    "iso:country":"US",
    "sg:address":"622 11th Ave",
    "sg:city":"Honolulu",
    "sg:classifiers":[
        {
            "category":"Professional",
            "type":"Services"
        }
    ],
    "sg:phone":"+1 808 734 8407",
    "sg:postcode":"96816",
    "sg:province":"HI",
    "wof:name":"Aloha Shuttle Service LLC",
    "wof:placetype":"venue"
},
  "geometry": {"coordinates":[-157.804802,21.275047],"type":"Point"}
}