{
  "type": "Feature",
  "properties": {
    "iso:country":"US",
    "sg:address":"4455 Rice St",
    "sg:city":"Lihue",
    "sg:classifiers":[
        {
            "category":"Banks & Credit Unions",
            "subcategory":"Bank",
            "type":"Services"
        }
    ],
    "sg:phone":"+1 808 245 6761",
    "sg:postcode":"96766",
    "sg:province":"HI",
    "wof:name":"Bank Of Hawaii",
    "wof:placetype":"venue"
},
  "geometry": {"coordinates":[-159.36928900000001,21.97503],"type":"Point"}
}