{
  "type": "Feature",
  "properties": {
    "iso:country":"US",
    "sg:address":"4010 Lower Kula Rd",
    "sg:city":"Kula",
    "sg:classifiers":[
        {
            "category":"Shopping",
            "type":"Retail Goods"
        }
    ],
    "sg:phone":"+1 808 878 2090",
    "sg:postcode":"96790",
    "sg:province":"HI",
    "sg:tags":[
        "awning",
        "canopy"
    ],
    "wof:name":"Maui Canvas Ctr",
    "wof:placetype":"venue"
},
  "geometry": {"coordinates":[-156.327539,20.766988],"type":"Point"}
}