{
  "type": "Feature",
  "properties": {
    "iso:country":"US",
    "sg:address":"109 Kainana Pl",
    "sg:city":"Kula",
    "sg:classifiers":[
        {
            "category":"Retail",
            "subcategory":"Portrait Studio",
            "type":"Services"
        }
    ],
    "sg:phone":"+1 808 244 1113",
    "sg:postcode":"96790",
    "sg:province":"HI",
    "sg:tags":[
        "photographer"
    ],
    "sg:website":"www.ctpmaui.com",
    "wof:name":"Creative Touch Photography",
    "wof:placetype":"venue"
},
  "geometry": {"coordinates":[-156.33066500000001,20.763952],"type":"Point"}
}