{
  "type": "Feature",
  "properties": {
    "iso:country":"US",
    "sg:address":"30 Aulike St",
    "sg:city":"Kailua",
    "sg:classifiers":[
        {
            "category":"Health Services",
            "subcategory":"Doctor",
            "type":"Services"
        }
    ],
    "sg:phone":"+1 808 262 5666",
    "sg:postcode":"96734",
    "sg:province":"HI",
    "wof:name":"Kim Howard Y B DDS Inc",
    "wof:placetype":"venue"
},
  "geometry": {"coordinates":[-157.742919,21.396638],"type":"Point"}
}