{
  "type": "Feature",
  "properties": {
    "iso:country":"US",
    "sg:address":"1159 Gulick Ave",
    "sg:city":"Honolulu",
    "sg:classifiers":[
        {
            "category":"Organizations",
            "subcategory":"Religious Organization",
            "type":"Services"
        }
    ],
    "sg:phone":"+1 808 841 8451",
    "sg:postcode":"96819",
    "sg:province":"HI",
    "sg:tags":[
        "church"
    ],
    "wof:name":"Hawaiian Pentecostal Full",
    "wof:placetype":"venue"
},
  "geometry": {"coordinates":[-157.87704099999999,21.334581],"type":"Point"}
}