{
  "type": "Feature",
  "properties": {
    "iso:country":"US",
    "sg:address":"2375 Kuhio Ave",
    "sg:city":"Honolulu",
    "sg:classifiers":[
        {
            "category":"Restaurant",
            "type":"Food & Drink"
        }
    ],
    "sg:phone":"+1 808 922 9888",
    "sg:postcode":"96815",
    "sg:province":"HI",
    "sg:tags":[
        "eating"
    ],
    "wof:name":"Keoni By Keo's",
    "wof:placetype":"venue"
},
  "geometry": {"coordinates":[-157.825672,21.279038],"type":"Point"}
}