{
  "type": "Feature",
  "properties": {
    "addr:full":"1430 Kona St Honolulu HI 96814",
    "addr:housenumber":"1430",
    "addr:postcode":"96814",
    "addr:street":"Kona St",
    "iso:country":"US",
    "sg:address":"1430 Kona St",
    "sg:city":"Honolulu",
    "sg:classifiers":[
        {
            "category":"Personal",
            "subcategory":"Beauty Salon",
            "type":"Services"
        }
    ],
    "sg:phone":"+1 808 947 4294",
    "sg:postcode":"96814",
    "sg:province":"HI",
    "sg:tags":[
        "shop"
    ],
    "wof:name":"Joseph Anthony Hair Salon",
    "wof:placetype":"venue"
},
  "geometry": {"coordinates":[-157.84341499999999,21.292549],"type":"Point"}
}