{
  "type": "Feature",
  "properties": {
    "addr:full":"878 Front St Lahaina HI 96761",
    "addr:housenumber":"878",
    "addr:postcode":"96761",
    "addr:street":"Front St",
    "iso:country":"US",
    "sg:address":"878 Front St",
    "sg:city":"Lahaina",
    "sg:classifiers":[
        {
            "category":"Shopping",
            "type":"Retail Goods"
        }
    ],
    "sg:phone":"+1 808 661 3377",
    "sg:postcode":"96761",
    "sg:province":"HI",
    "sg:tags":[
        "art",
        "gallery",
        "dealer"
    ],
    "wof:name":"Hager Collection",
    "wof:placetype":"venue"
},
  "geometry": {"coordinates":[-156.683865,20.880109],"type":"Point"}
}