{
  "type": "Feature",
  "properties": {
    "iso:country":"US",
    "sg:address":"3133 Waialae Ave",
    "sg:city":"Honolulu",
    "sg:classifiers":[
        {
            "category":"Real Estate",
            "subcategory":"Real Estate Agent",
            "type":"Services"
        }
    ],
    "sg:phone":"+1 808 735 1273",
    "sg:postcode":"96816",
    "sg:province":"HI",
    "wof:name":"Joseph C Leonardo and Company",
    "wof:placetype":"venue"
},
  "geometry": {"coordinates":[-157.80931000000001,21.287941],"type":"Point"}
}