{
  "type": "Feature",
  "properties": {
    "addr:full":"2199 Kalia Rd Honolulu HI 96815",
    "addr:housenumber":"2199",
    "addr:postcode":"96815",
    "addr:street":"Kalia Rd",
    "iso:country":"US",
    "sg:address":"2199 Kalia Rd",
    "sg:city":"Honolulu",
    "sg:classifiers":[
        {
            "category":"Shopping",
            "subcategory":"Clothing, Apparel, & Fashions",
            "type":"Retail Goods"
        }
    ],
    "sg:phone":"+1 808 923 8893",
    "sg:postcode":"96815",
    "sg:province":"HI",
    "sg:tags":[
        "item",
        "boutique"
    ],
    "wof:name":"Philippe Charriol",
    "wof:placetype":"venue"
},
  "geometry": {"coordinates":[-157.83091200000001,21.277772],"type":"Point"}
}