{
  "type": "Feature",
  "properties": {
    "addr:full":"148 Kaiulani Ave Honolulu HI 96815",
    "addr:postcode":"96815",
    "addr:street":"Kaiulani Ave",
    "iso:country":"US",
    "sg:address":"148 Kaiulani Ave",
    "sg:city":"Honolulu",
    "sg:classifiers":[
        {
            "category":"Retail",
            "subcategory":"Auto Rental",
            "type":"Services"
        }
    ],
    "sg:phone":"+1 808 971 3700",
    "sg:postcode":"96815",
    "sg:province":"HI",
    "sg:tags":[
        "renting",
        "automobile"
    ],
    "wof:name":"Avis Rent A Car",
    "wof:placetype":"venue"
},
  "geometry": {"coordinates":[-157.82545400000001,21.276988],"type":"Point"}
}