{
  "type": "Feature",
  "properties": {
    "iso:country":"US",
    "sg:address":"1007 Puia St",
    "sg:city":"Waipahu",
    "sg:classifiers":[
        {
            "category":"Building & Trades",
            "subcategory":"Construction",
            "type":"Services"
        }
    ],
    "sg:phone":"+1 808 677 7969",
    "sg:postcode":"96797",
    "sg:province":"HI",
    "sg:tags":[
        "residential",
        "commercial"
    ],
    "wof:name":"Sapigao Construction",
    "wof:placetype":"venue"
},
  "geometry": {"coordinates":[-158.02147400000001,21.399729],"type":"Point"}
}