{
  "type": "Feature",
  "properties": {
    "iso:country":"US",
    "sg:address":"2805 Ualena St",
    "sg:city":"Honolulu",
    "sg:classifiers":[
        {
            "category":"Autos & Motor Vehicles",
            "subcategory":"Fuel & Gas Station",
            "type":"Retail Goods"
        }
    ],
    "sg:phone":"+1 808 836 8662",
    "sg:postcode":"96819",
    "sg:province":"HI",
    "sg:tags":[
        "oil"
    ],
    "wof:name":"Airport Shell Station",
    "wof:placetype":"venue"
},
  "geometry": {"coordinates":[-157.907813,21.333465],"type":"Point"}
}