{
  "type": "Feature",
  "properties": {
    "iso:country":"US",
    "sg:address":"55 Merchant St",
    "sg:city":"Honolulu",
    "sg:classifiers":[
        {
            "category":"Banks & Credit Unions",
            "subcategory":"Investment Brokerage",
            "type":"Services"
        }
    ],
    "sg:phone":"+1 808 545 1522",
    "sg:postcode":"96813",
    "sg:province":"HI",
    "sg:tags":[
        "security"
    ],
    "sg:website":"www.eabuck.com",
    "wof:name":"H Beck Inc",
    "wof:placetype":"venue"
},
  "geometry": {"coordinates":[-157.86303699999999,21.309004],"type":"Point"}
}