{
  "type": "Feature",
  "properties": {
    "iso:country":"US",
    "sg:address":"1717 Ala Wai Blvd",
    "sg:city":"Honolulu",
    "sg:classifiers":[
        {
            "category":"Building & Trades",
            "subcategory":"Construction",
            "type":"Services"
        }
    ],
    "sg:phone":"+1 808 949 7587",
    "sg:postcode":"96815",
    "sg:province":"HI",
    "sg:tags":[
        "general",
        "work",
        "remodeling",
        "carpentry"
    ],
    "wof:name":"Raymonds Remodeling",
    "wof:placetype":"venue"
},
  "geometry": {"coordinates":[-157.83576600000001,21.288231],"type":"Point"}
}