{
  "type": "Feature",
  "properties": {
    "iso:country":"US",
    "sg:address":"3663 Baldwin Ave",
    "sg:city":"Makawao",
    "sg:classifiers":[
        {
            "category":"Shopping",
            "subcategory":"Clothing, Apparel, & Fashions",
            "type":"Retail Goods"
        }
    ],
    "sg:phone":"+1 808 572 9576",
    "sg:postcode":"96768",
    "sg:province":"HI",
    "sg:tags":[
        "boutique",
        "accessory"
    ],
    "wof:name":"Insync",
    "wof:placetype":"venue"
},
  "geometry": {"coordinates":[-156.31089700000001,20.854801],"type":"Point"}
}