{
  "type": "Feature",
  "properties": {
    "addr:full":"520 Kamoku St Honolulu HI 96826",
    "addr:housenumber":"520",
    "addr:postcode":"96826",
    "addr:street":"Kamoku St",
    "iso:country":"US",
    "sg:address":"520 Kamoku St",
    "sg:city":"Honolulu",
    "sg:classifiers":[
        {
            "category":"Organizations",
            "subcategory":"Community Association",
            "type":"Services"
        }
    ],
    "sg:phone":"+1 808 946 0272",
    "sg:postcode":"96826",
    "sg:province":"HI",
    "sg:tags":[
        "military"
    ],
    "wof:name":"100th Infantry Battalion Vets",
    "wof:placetype":"venue"
},
  "geometry": {"coordinates":[-157.825537,21.285728],"type":"Point"}
}