{
  "type": "Feature",
  "properties": {
    "addr:full":"1333 Kaeleku St Honolulu HI 96825",
    "addr:housenumber":"1333",
    "addr:postcode":"96825",
    "addr:street":"Kaeleku St",
    "iso:country":"US",
    "sg:address":"1333 Kaeleku St",
    "sg:city":"Honolulu",
    "sg:classifiers":[
        {
            "category":"Manufacturing",
            "subcategory":"Textiles",
            "type":"Manufacturing & Wholesale Goods"
        }
    ],
    "sg:phone":"+1 808 396 9963",
    "sg:postcode":"96825",
    "sg:province":"HI",
    "sg:tags":[
        "swimwear",
        "sportswear",
        "mfg"
    ],
    "wof:name":"Honey Girl LLC",
    "wof:placetype":"venue"
},
  "geometry": {"coordinates":[-157.67060799999999,21.303103],"type":"Point"}
}