{
  "type": "Feature",
  "properties": {
    "iso:country":"US",
    "sg:address":"821 Kalihi St",
    "sg:city":"Honolulu",
    "sg:classifiers":[
        {
            "category":"Education",
            "subcategory":"School",
            "type":"Public Place"
        }
    ],
    "sg:phone":"+1 808 832 3130",
    "sg:postcode":"96819",
    "sg:province":"HI",
    "sg:tags":[
        "middle"
    ],
    "wof:name":"Kalaukaua Intermediate School",
    "wof:placetype":"venue"
},
  "geometry": {"coordinates":[-157.876768,21.329732],"type":"Point"}
}