{
  "type": "Feature",
  "properties": {
    "addr:full":"377 Keahole St Honolulu HI 96825",
    "addr:housenumber":"377",
    "addr:postcode":"96825",
    "addr:street":"Keahole St",
    "iso:country":"US",
    "sg:address":"377 Keahole St",
    "sg:city":"Honolulu",
    "sg:classifiers":[
        {
            "category":"Personal",
            "subcategory":"Beauty Salon",
            "type":"Services"
        }
    ],
    "sg:phone":"+1 808 394 9111",
    "sg:postcode":"96825",
    "sg:province":"HI",
    "wof:name":"Regis Salons",
    "wof:placetype":"venue"
},
  "geometry": {"coordinates":[-157.70769200000001,21.285752],"type":"Point"}
}