{
  "type": "Feature",
  "properties": {
    "iso:country":"US",
    "sg:address":"360 Puuikena Dr",
    "sg:city":"Honolulu",
    "sg:classifiers":[
        {
            "category":"Banks & Credit Unions",
            "subcategory":"Financial Services",
            "type":"Services"
        }
    ],
    "sg:phone":"+1 808 377 7115",
    "sg:postcode":"96821",
    "sg:province":"HI",
    "sg:tags":[
        "trust"
    ],
    "wof:name":"Elaine L Chang Trust",
    "wof:placetype":"venue"
},
  "geometry": {"coordinates":[-157.746105,21.283498],"type":"Point"}
}