{
  "type": "Feature",
  "properties": {
    "addr:full":"2301 Kalakaua Ave Honolulu HI 96815",
    "addr:housenumber":"2301",
    "addr:postcode":"96815",
    "addr:street":"Kalakaua Ave",
    "iso:country":"US",
    "sg:address":"2301 Kalakaua Ave",
    "sg:city":"Honolulu",
    "sg:classifiers":[
        {
            "category":"Shopping",
            "subcategory":"Bicycles & Sporting Goods",
            "type":"Retail Goods"
        }
    ],
    "sg:phone":"+1 808 924 8870",
    "sg:postcode":"96815",
    "sg:province":"HI",
    "sg:tags":[
        "athletic",
        "footwear"
    ],
    "wof:name":"Royal Sports Center Inc",
    "wof:placetype":"venue"
},
  "geometry": {"coordinates":[-157.82606999999999,21.276543],"type":"Point"}
}