{
  "type": "Feature",
  "properties": {
    "addr:full":"2301 Kalakaua Ave Honolulu HI 96815",
    "addr:housenumber":"2301",
    "addr:postcode":"96815",
    "addr:street":"Kalakaua Ave",
    "iso:country":"US",
    "sg:address":"2301 Kalakaua Ave",
    "sg:city":"Honolulu",
    "sg:classifiers":[
        {
            "category":"Manufacturing",
            "subcategory":"Paper Products",
            "type":"Manufacturing & Wholesale Goods"
        },
        {
            "category":"Shopping",
            "subcategory":"Beauty & Cosmetics",
            "type":"Retail Goods"
        }
    ],
    "sg:phone":"+1 808 926 6960",
    "sg:postcode":"96815",
    "sg:province":"HI",
    "sg:tags":[
        "bag",
        "merchandise"
    ],
    "wof:name":"G B C Boxes & Packaging",
    "wof:placetype":"venue"
},
  "geometry": {"coordinates":[-157.82606999999999,21.276543],"type":"Point"}
}