{
  "type": "Feature",
  "properties": {
    "iso:country":"US",
    "sg:address":"5254 Waihou St",
    "sg:city":"Honolulu",
    "sg:classifiers":[
        {
            "category":"Real Estate",
            "subcategory":"Real Estate Operator",
            "type":"Services"
        }
    ],
    "sg:phone":"+1 808 373 1677",
    "sg:postcode":"96821",
    "sg:province":"HI",
    "sg:tags":[
        "building",
        "apartment"
    ],
    "wof:name":"Tom Building",
    "wof:placetype":"venue"
},
  "geometry": {"coordinates":[-157.755503,21.285215],"type":"Point"}
}