{
  "type": "Feature",
  "properties": {
    "iso:country":"US",
    "sg:address":"2250 Kalakaua Ave",
    "sg:city":"Honolulu",
    "sg:classifiers":[
        {
            "category":"Shopping",
            "subcategory":"Clothing, Apparel, & Fashions",
            "type":"Retail Goods"
        }
    ],
    "sg:phone":"+1 808 922 6988",
    "sg:postcode":"96815",
    "sg:province":"HI",
    "sg:tags":[
        "logo",
        "sport"
    ],
    "wof:name":"Plaza Sports",
    "wof:placetype":"venue"
},
  "geometry": {"coordinates":[-157.828868,21.279143],"type":"Point"}
}