{
  "type": "Feature",
  "properties": {
    "addr:full":"6005 Kalemakapii St Kapolei HI 96707",
    "addr:housenumber":"6005",
    "addr:postcode":"96707",
    "addr:street":"Kalemakapii St",
    "iso:country":"US",
    "sg:address":"6005 Kalemakapii St",
    "sg:city":"Kapolei",
    "sg:classifiers":[
        {
            "category":"Professional",
            "subcategory":"Accounting & Tax Preparation",
            "type":"Services"
        }
    ],
    "sg:phone":"+1 808 672 6584",
    "sg:postcode":"96707",
    "sg:province":"HI",
    "sg:tags":[
        "bookkeeping",
        "general"
    ],
    "wof:name":"Tashiro Accounting Svc Inc",
    "wof:placetype":"venue"
},
  "geometry": {"coordinates":[-158.090373,21.366833],"type":"Point"}
}