{
  "type": "Feature",
  "properties": {
    "addr:full":"2809 Kaihikapu St Honolulu HI 96819",
    "addr:housenumber":"2809",
    "addr:postcode":"96819",
    "addr:street":"Kaihikapu St",
    "iso:country":"US",
    "sg:address":"2809 Kaihikapu St",
    "sg:city":"Honolulu",
    "sg:classifiers":[
        {
            "category":"Wholesale",
            "subcategory":"Auto Parts",
            "type":"Manufacturing & Wholesale Goods"
        }
    ],
    "sg:phone":"+1 808 834 7757",
    "sg:postcode":"96819",
    "sg:province":"HI",
    "sg:tags":[
        "distributor"
    ],
    "wof:name":"Pacific Jobbers Warehouse Inc",
    "wof:placetype":"venue"
},
  "geometry": {"coordinates":[-157.89987600000001,21.340572],"type":"Point"}
}