{
  "type": "Feature",
  "properties": {
    "iso:country":"US",
    "sg:address":"8221 Kekaha Rd",
    "sg:city":"Kekaha",
    "sg:classifiers":[
        {
            "category":"Manufacturing",
            "subcategory":"Watercraft",
            "type":"Manufacturing & Wholesale Goods"
        }
    ],
    "sg:phone":"+1 808 337 9641",
    "sg:postcode":"96752",
    "sg:province":"HI",
    "sg:tags":[
        "boat"
    ],
    "sg:website":"www.hawaiiancats.com",
    "wof:name":"Hi Tech Fiberglass",
    "wof:placetype":"venue"
},
  "geometry": {"coordinates":[-159.71314000000001,21.97058],"type":"Point"}
}