{
  "type": "Feature",
  "properties": {
    "iso:country":"US",
    "sg:address":"120 Pauahi St",
    "sg:city":"Hilo",
    "sg:classifiers":[
        {
            "category":"Government",
            "subcategory":"Office",
            "type":"Public Place"
        }
    ],
    "sg:phone":"+1 808 959 0669",
    "sg:postcode":"96720",
    "sg:province":"HI",
    "sg:tags":[
        "state",
        "agency",
        "child",
        "care"
    ],
    "wof:name":"Child Care Licensing Chld Svcs",
    "wof:placetype":"venue"
},
  "geometry": {"coordinates":[-155.07871499999999,19.721482],"type":"Point"}
}