{
  "type": "Feature",
  "properties": {
    "iso:country":"US",
    "sg:address":"555 Farrington Hwy",
    "sg:city":"Kapolei",
    "sg:classifiers":[
        {
            "category":"Restaurant",
            "type":"Food & Drink"
        }
    ],
    "sg:menulink":"http://www.allmenus.com/hi/ewa/160829-burger-king/menu/",
    "sg:phone":"+1 808 674 9651",
    "sg:postcode":"96707",
    "sg:province":"HI",
    "sg:tags":[
        "burger",
        "american"
    ],
    "wof:name":"Burger King",
    "wof:placetype":"venue"
},
  "geometry": {"coordinates":[-158.07853700000001,21.33777],"type":"Point"}
}