{
  "type": "Feature",
  "properties": {
    "addr:full":"1642 Home Rule St Honolulu HI 96819",
    "addr:housenumber":"1642",
    "addr:postcode":"96819",
    "addr:street":"Home Rule St",
    "iso:country":"US",
    "sg:address":"1642 Home Rule St",
    "sg:city":"Honolulu",
    "sg:classifiers":[
        {
            "category":"Retail",
            "subcategory":"Auto Repair",
            "type":"Services"
        }
    ],
    "sg:phone":"+1 808 351 5751",
    "sg:postcode":"96819",
    "sg:province":"HI",
    "sg:tags":[
        "body",
        "automobile",
        "painting"
    ],
    "wof:name":"Sid's Body Works",
    "wof:placetype":"venue"
},
  "geometry": {"coordinates":[-157.882361,21.323031],"type":"Point"}
}