{
  "type": "Feature",
  "properties": {
    "iso:country":"US",
    "sg:address":"3350 Lower Honoapiilani Rd",
    "sg:city":"Lahaina",
    "sg:classifiers":[
        {
            "category":"Shopping",
            "subcategory":"Clothing, Apparel, & Fashions",
            "type":"Retail Goods"
        }
    ],
    "sg:phone":"+1 808 661 5554",
    "sg:postcode":"96761",
    "sg:province":"HI",
    "wof:name":"Leola's Family Fun Wear",
    "wof:placetype":"venue"
},
  "geometry": {"coordinates":[-156.68757299999999,20.946002],"type":"Point"}
}