{
  "type": "Feature",
  "properties": {
    "addr:full":"1249 Meheula Pkwy Mililani HI 96789",
    "addr:housenumber":"1249",
    "addr:postcode":"96789",
    "addr:street":"Meheula Pkwy",
    "iso:country":"US",
    "sg:address":"1249 Meheula Pkwy",
    "sg:city":"Mililani",
    "sg:classifiers":[
        {
            "category":"Health Services",
            "subcategory":"Doctor",
            "type":"Services"
        }
    ],
    "sg:phone":"+1 808 625 4444",
    "sg:postcode":"96789",
    "sg:province":"HI",
    "sg:tags":[
        "medical"
    ],
    "wof:name":"Steven Y Orimoto MD",
    "wof:placetype":"venue"
},
  "geometry": {"coordinates":[-158.007576,21.455167],"type":"Point"}
}