{
  "type": "Feature",
  "properties": {
    "addr:full":"1965 Kamehameha Ave Hilo HI 96720",
    "addr:housenumber":"1965",
    "addr:postcode":"96720",
    "addr:street":"Kamehameha Ave",
    "iso:country":"US",
    "sg:address":"1965 Kamehameha Ave",
    "sg:city":"Hilo",
    "sg:classifiers":[
        {
            "category":"Wholesale",
            "subcategory":"Groceries",
            "type":"Manufacturing & Wholesale Goods"
        }
    ],
    "sg:phone":"+1 808 935 8537",
    "sg:postcode":"96720",
    "sg:province":"HI",
    "sg:tags":[
        "general"
    ],
    "wof:name":"Susisan Company",
    "wof:placetype":"venue"
},
  "geometry": {"coordinates":[-155.058898,19.722657],"type":"Point"}
}