{
  "type": "Feature",
  "properties": {
    "iso:country":"US",
    "sg:address":"457 Hui Iwa St",
    "sg:city":"Kaneohe",
    "sg:classifiers":[
        {
            "category":"Government",
            "subcategory":"Fire Station",
            "type":"Public Place"
        }
    ],
    "sg:phone":"+1 808 239 7169",
    "sg:postcode":"96744",
    "sg:province":"HI",
    "sg:tags":[
        "protection"
    ],
    "wof:name":"Fire Protection Services Inc",
    "wof:placetype":"venue"
},
  "geometry": {"coordinates":[-157.82957200000001,21.437438],"type":"Point"}
}