{
  "type": "Feature",
  "properties": {
    "iso:country":"US",
    "sg:address":"1060 Young St",
    "sg:city":"Honolulu",
    "sg:classifiers":[
        {
            "category":"Health Services",
            "subcategory":"Doctor",
            "type":"Services"
        }
    ],
    "sg:phone":"+1 808 531 9757",
    "sg:postcode":"96814",
    "sg:province":"HI",
    "wof:name":"Loo Harrison DMD",
    "wof:placetype":"venue"
},
  "geometry": {"coordinates":[-157.84755100000001,21.302193],"type":"Point"}
}