{
  "type": "Feature",
  "properties": {
    "iso:country":"US",
    "sg:address":"79 Leokane St",
    "sg:city":"Waipahu",
    "sg:classifiers":[
        {
            "category":"Building & Trades",
            "subcategory":"Construction",
            "type":"Services"
        }
    ],
    "sg:phone":"+1 808 677 5050",
    "sg:postcode":"96797",
    "sg:province":"HI",
    "sg:tags":[
        "installation",
        "manufacturer"
    ],
    "wof:name":"Custom Countertops Inc",
    "wof:placetype":"venue"
},
  "geometry": {"coordinates":[-158.02002300000001,21.375177],"type":"Point"}
}