{
  "type": "Feature",
  "properties": {
    "iso:country":"US",
    "sg:address":"945 Halawa Valley St",
    "sg:city":"Aiea",
    "sg:classifiers":[
        {
            "category":"Government",
            "subcategory":"Office",
            "type":"Public Place"
        }
    ],
    "sg:phone":"+1 808 483 2535",
    "sg:postcode":"96701",
    "sg:province":"HI",
    "sg:tags":[
        "state",
        "program",
        "health"
    ],
    "wof:name":"Environmental Health Svc Div",
    "wof:placetype":"venue"
},
  "geometry": {"coordinates":[-157.90556900000001,21.373939],"type":"Point"}
}