{
  "type": "Feature",
  "properties": {
    "addr:full":"1476 S Kihei Rd Kihei HI 96753",
    "addr:housenumber":"1476",
    "addr:postcode":"96753",
    "addr:street":"S Kihei Rd",
    "iso:country":"US",
    "sg:address":"1476 S Kihei Rd",
    "sg:city":"Kihei",
    "sg:classifiers":[
        {
            "category":"Retail",
            "subcategory":"Veterinary Services",
            "type":"Services"
        }
    ],
    "sg:phone":"+1 808 879 5777",
    "sg:postcode":"96753",
    "sg:province":"HI",
    "sg:tags":[
        "veterinarian"
    ],
    "wof:name":"Kihei Veterinary Clinic",
    "wof:placetype":"venue"
},
  "geometry": {"coordinates":[-156.454657,20.744084],"type":"Point"}
}