{
  "type": "Feature",
  "properties": {
    "addr:full":"7192 Kalanianaole Hwy Honolulu HI 96825",
    "addr:housenumber":"7192",
    "addr:postcode":"96825",
    "addr:street":"Kalanianaole Hwy",
    "iso:country":"US",
    "sg:address":"7192 Kalanianaole Hwy",
    "sg:city":"Honolulu",
    "sg:classifiers":[
        {
            "category":"Recreation",
            "type":"Entertainment"
        }
    ],
    "sg:phone":"+1 808 396 8838",
    "sg:postcode":"96825",
    "sg:province":"HI",
    "sg:tags":[
        "instruction",
        "yoga"
    ],
    "wof:name":"Bikram Yoga Hawaii Kai",
    "wof:placetype":"venue"
},
  "geometry": {"coordinates":[-157.70812699999999,21.278837],"type":"Point"}
}