{
  "type": "Feature",
  "properties": {
    "iso:country":"US",
    "sg:address":"3908 Lawehana St",
    "sg:city":"Lihue",
    "sg:classifiers":[
        {
            "category":"Professional",
            "subcategory":"Business Services",
            "type":"Services"
        }
    ],
    "sg:phone":"+1 808 246 6232",
    "sg:postcode":"96766",
    "sg:province":"HI",
    "wof:name":"Emiteria U Songcuan",
    "wof:placetype":"venue"
},
  "geometry": {"coordinates":[-159.356572,21.991343],"type":"Point"}
}