{
  "type": "Feature",
  "properties": {
    "iso:country":"US",
    "sg:address":"900 Fort Street Ml",
    "sg:city":"Honolulu",
    "sg:classifiers":[
        {
            "category":"Professional",
            "subcategory":"Employment Agencies",
            "type":"Services"
        }
    ],
    "sg:phone":"+1 808 523 3313",
    "sg:postcode":"96813",
    "sg:province":"HI",
    "sg:tags":[
        "temporary",
        "help"
    ],
    "wof:name":"Olsten",
    "wof:placetype":"venue"
},
  "geometry": {"coordinates":[-157.862101,21.309186],"type":"Point"}
}