{
  "type": "Feature",
  "properties": {
    "iso:country":"US",
    "sg:address":"5819 Alii Dr",
    "sg:city":"Kailua Kona",
    "sg:classifiers":[
        {
            "category":"Real Estate",
            "subcategory":"Real Estate Agent",
            "type":"Services"
        }
    ],
    "sg:phone":"+1 808 326 7220",
    "sg:postcode":"96740",
    "sg:province":"HI",
    "wof:name":"Island Riders",
    "wof:placetype":"venue"
},
  "geometry": {"coordinates":[-155.98994400000001,19.634735],"type":"Point"}
}