{
  "type": "Feature",
  "properties": {
    "iso:country":"US",
    "sg:address":"555 University Ave",
    "sg:city":"Honolulu",
    "sg:classifiers":[
        {
            "category":"Professional",
            "type":"Services"
        }
    ],
    "sg:phone":"+1 808 228 7629",
    "sg:postcode":"96826",
    "sg:province":"HI",
    "sg:tags":[
        "science",
        "engineering",
        "marine",
        "consulting",
        "coastal"
    ],
    "wof:name":"Physalia Ocean Scnces Intl Inc",
    "wof:placetype":"venue"
},
  "geometry": {"coordinates":[-157.826717,21.286616],"type":"Point"}
}