{
  "type": "Feature",
  "properties": {
    "iso:country":"US",
    "sg:address":"4911 Nonou Rd",
    "sg:city":"Kapaa",
    "sg:classifiers":[
        {
            "category":"Professional",
            "type":"Services"
        }
    ],
    "sg:phone":"+1 808 828 2005",
    "sg:postcode":"96746",
    "sg:province":"HI",
    "sg:tags":[
        "establishment"
    ],
    "wof:name":"U Turn",
    "wof:placetype":"venue"
},
  "geometry": {"coordinates":[-159.34266199999999,22.053701],"type":"Point"}
}