{
  "type": "Feature",
  "properties": {
    "addr:full":"147 W Kinai Pl Hilo HI 96720",
    "addr:housenumber":"147",
    "addr:postcode":"96720",
    "addr:street":"W Kinai Pl",
    "iso:country":"US",
    "sg:address":"147 W Kinai Pl",
    "sg:city":"Hilo",
    "sg:classifiers":[
        {
            "category":"Building & Trades",
            "subcategory":"Landscaping Services",
            "type":"Services"
        }
    ],
    "sg:phone":"+1 808 959 3073",
    "sg:postcode":"96720",
    "sg:province":"HI",
    "wof:name":"Design Landscape",
    "wof:placetype":"venue"
},
  "geometry": {"coordinates":[-155.06249399999999,19.67852],"type":"Point"}
}