{
  "type": "Feature",
  "properties": {
    "iso:country":"US",
    "sg:address":"2139 Fort Weaver Rd",
    "sg:city":"Ewa Beach",
    "sg:classifiers":[
        {
            "category":"Shopping",
            "subcategory":"Pharmacy",
            "type":"Retail Goods"
        }
    ],
    "sg:phone":"+1 808 676 3333",
    "sg:postcode":"96706",
    "sg:province":"HI",
    "wof:name":"Pharma Care",
    "wof:placetype":"venue"
},
  "geometry": {"coordinates":[-158.02632199999999,21.36867],"type":"Point"}
}