{
  "type": "Feature",
  "properties": {
    "iso:country":"US",
    "sg:address":"111 Sand Island Access Rd",
    "sg:city":"Honolulu",
    "sg:classifiers":[
        {
            "category":"Manufacturing",
            "subcategory":"Apparel",
            "type":"Manufacturing & Wholesale Goods"
        }
    ],
    "sg:phone":"+1 808 848 0881",
    "sg:postcode":"96819",
    "sg:province":"HI",
    "wof:name":"Minh T-Shirt",
    "wof:placetype":"venue"
},
  "geometry": {"coordinates":[-157.89026799999999,21.324297],"type":"Point"}
}