{
  "type": "Feature",
  "properties": {
    "addr:full":"9888 Waimea Rd Waimea HI 96796",
    "addr:housenumber":"9888",
    "addr:postcode":"96796",
    "addr:street":"Waimea Rd",
    "iso:country":"US",
    "sg:address":"9888 Waimea Rd",
    "sg:city":"Waimea",
    "sg:classifiers":[
        {
            "category":"Local Transit",
            "type":"Transportation"
        }
    ],
    "sg:phone":"+1 808 338 1868",
    "sg:postcode":"96796",
    "sg:province":"HI",
    "sg:tags":[
        "ambulance"
    ],
    "wof:name":"American Medical Response",
    "wof:placetype":"venue"
},
  "geometry": {"coordinates":[-159.66760600000001,21.955199],"type":"Point"}
}