{
  "type": "Feature",
  "properties": {
    "iso:country":"US",
    "sg:address":"449 Hoene Pl",
    "sg:city":"Kaneohe",
    "sg:classifiers":[
        {
            "category":"Professional",
            "subcategory":"Accounting & Tax Preparation",
            "type":"Services"
        }
    ],
    "sg:phone":"+1 808 235 3401",
    "sg:postcode":"96744",
    "sg:province":"HI",
    "sg:tags":[
        "computer",
        "related"
    ],
    "wof:name":"Neil Freeman Consultants",
    "wof:placetype":"venue"
},
  "geometry": {"coordinates":[-157.79881700000001,21.407314],"type":"Point"}
}