{
  "type": "Feature",
  "properties": {
    "addr:full":"707 Hui Ulili St Kaneohe HI 96744",
    "addr:housenumber":"707",
    "addr:postcode":"96744",
    "addr:street":"Hui Ulili St",
    "iso:country":"US",
    "sg:address":"707 Hui Ulili St",
    "sg:city":"Kaneohe",
    "sg:classifiers":[
        {
            "category":"Recreation",
            "type":"Entertainment"
        }
    ],
    "sg:phone":"+1 808 348 3292",
    "sg:postcode":"96744",
    "sg:province":"HI",
    "sg:tags":[
        "sport"
    ],
    "wof:name":"Quentin Redmon",
    "wof:placetype":"venue"
},
  "geometry": {"coordinates":[-157.83690799999999,21.434823],"type":"Point"}
}