{
  "type": "Feature",
  "properties": {
    "iso:country":"US",
    "sg:address":"157 N King St",
    "sg:city":"Honolulu",
    "sg:classifiers":[
        {
            "category":"Food & Beverages",
            "subcategory":"Meat & Fish",
            "type":"Retail Goods"
        }
    ],
    "sg:phone":"+1 808 533 0577",
    "sg:postcode":"96817",
    "sg:province":"HI",
    "wof:name":"Chun's Meat Market",
    "wof:placetype":"venue"
},
  "geometry": {"coordinates":[-157.86422899999999,21.312782],"type":"Point"}
}