{
  "type": "Feature",
  "properties": {
    "iso:country":"US",
    "sg:address":"8663 Kaumualii Hwy",
    "sg:city":"Kekaha",
    "sg:classifiers":[
        {
            "category":"Travel",
            "subcategory":"Hotels & Motels",
            "type":"Entertainment"
        }
    ],
    "sg:phone":"+1 808 337 9113",
    "sg:postcode":"96752",
    "sg:province":"HI",
    "sg:tags":[
        "breakfast",
        "accommodation",
        "bed"
    ],
    "wof:name":"Ole Kamaole's Beach House",
    "wof:placetype":"venue"
},
  "geometry": {"coordinates":[-159.70396099999999,21.960823],"type":"Point"}
}