{
  "type": "Feature",
  "properties": {
    "iso:country":"US",
    "sg:address":"215 Railroad Ave",
    "sg:city":"Hilo",
    "sg:classifiers":[
        {
            "category":"Recreation",
            "type":"Entertainment"
        }
    ],
    "sg:phone":"+1 808 934 0642",
    "sg:postcode":"96720",
    "sg:province":"HI",
    "sg:tags":[
        "instruction",
        "gymnastic"
    ],
    "wof:name":"Pacific Gymnastics",
    "wof:placetype":"venue"
},
  "geometry": {"coordinates":[-155.05984900000001,19.70368],"type":"Point"}
}