{
  "type": "Feature",
  "properties": {
    "iso:country":"US",
    "sg:address":"689 Old Mokapu Rd",
    "sg:city":"Kailua",
    "sg:classifiers":[
        {
            "category":"Building & Trades",
            "subcategory":"Construction",
            "type":"Services"
        }
    ],
    "sg:phone":"+1 808 254 2270",
    "sg:postcode":"96734",
    "sg:province":"HI",
    "sg:tags":[
        "repairing",
        "remodeling",
        "contractor"
    ],
    "wof:name":"Merit Sales",
    "wof:placetype":"venue"
},
  "geometry": {"coordinates":[-157.742875,21.427073],"type":"Point"}
}