{
  "type": "Feature",
  "properties": {
    "iso:country":"US",
    "sg:address":"302 California Ave",
    "sg:city":"Wahiawa",
    "sg:classifiers":[
        {
            "category":"Health Services",
            "subcategory":"Health Practitioner",
            "type":"Services"
        }
    ],
    "sg:phone":"+1 808 621 7878",
    "sg:postcode":"96786",
    "sg:province":"HI",
    "wof:name":"Dana Zichittella PHD",
    "wof:placetype":"venue"
},
  "geometry": {"coordinates":[-158.031858,21.49517],"type":"Point"}
}