{
  "type": "Feature",
  "properties": {
    "addr:full":"1026 Nuuanu Ave Honolulu HI 96817",
    "addr:housenumber":"1026",
    "addr:postcode":"96817",
    "addr:street":"Nuuanu Ave",
    "iso:country":"US",
    "sg:address":"1026 Nuuanu Ave",
    "sg:city":"Honolulu",
    "sg:classifiers":[
        {
            "category":"Professional",
            "subcategory":"Lawyer & Legal Services",
            "type":"Services"
        }
    ],
    "sg:phone":"+1 808 523 6936",
    "sg:postcode":"96817",
    "sg:province":"HI",
    "sg:tags":[
        "attorney"
    ],
    "sg:website":"www.manasoftware.com",
    "wof:name":"Edward JSF Smith Law Offices",
    "wof:placetype":"venue"
},
  "geometry": {"coordinates":[-157.86230499999999,21.310973],"type":"Point"}
}