{
  "type": "Feature",
  "properties": {
    "addr:full":"247 Kalihi St Honolulu HI 96819",
    "addr:housenumber":"247",
    "addr:postcode":"96819",
    "addr:street":"Kalihi St",
    "iso:country":"US",
    "sg:address":"247 Kalihi St",
    "sg:city":"Honolulu",
    "sg:classifiers":[
        {
            "category":"Real Estate",
            "subcategory":"Architect",
            "type":"Services"
        }
    ],
    "sg:phone":"+1 808 841 4478",
    "sg:postcode":"96819",
    "sg:province":"HI",
    "sg:tags":[
        "architectural"
    ],
    "wof:name":"Design Perspective",
    "wof:placetype":"venue"
},
  "geometry": {"coordinates":[-157.883534,21.322653],"type":"Point"}
}