{
  "type": "Feature",
  "properties": {
    "iso:country":"US",
    "sg:address":"1820 Colburn St",
    "sg:city":"Honolulu",
    "sg:classifiers":[
        {
            "category":"Building & Trades",
            "subcategory":"Plumbing",
            "type":"Services"
        }
    ],
    "sg:phone":"+1 808 845 4112",
    "sg:postcode":"96819",
    "sg:province":"HI",
    "sg:tags":[
        "plumbing",
        "contractor"
    ],
    "wof:name":"Commercial Plumbing Inc",
    "wof:placetype":"venue"
},
  "geometry": {"coordinates":[-157.88063700000001,21.32701],"type":"Point"}
}