{
  "type": "Feature",
  "properties": {
    "addr:full":"1 Kamehameha Hwy Kaneohe HI 96744",
    "addr:housenumber":"1",
    "addr:postcode":"96744",
    "addr:street":"Kamehameha Hwy",
    "iso:country":"US",
    "sg:address":"1 Kamehameha Hwy",
    "sg:city":"Kaneohe",
    "sg:classifiers":[
        {
            "category":"Health Services",
            "subcategory":"Chiropractor",
            "type":"Services"
        }
    ],
    "sg:phone":"+1 808 234 5535",
    "sg:postcode":"96744",
    "sg:province":"HI",
    "wof:name":"Bernard C Abbadessa DC",
    "wof:placetype":"venue"
},
  "geometry": {"coordinates":[-157.80304699999999,21.420068],"type":"Point"}
}