{
  "type": "Feature",
  "properties": {
    "addr:full":"1412 Middle St Honolulu HI 96819",
    "addr:housenumber":"1412",
    "addr:postcode":"96819",
    "addr:street":"Middle St",
    "iso:country":"US",
    "sg:address":"1412 Middle St",
    "sg:city":"Honolulu",
    "sg:classifiers":[
        {
            "category":"Shopping",
            "subcategory":"Used Merchandise",
            "type":"Retail Goods"
        }
    ],
    "sg:phone":"+1 808 841 7999",
    "sg:postcode":"96819",
    "sg:province":"HI",
    "wof:name":"Shafter Pawn",
    "wof:placetype":"venue"
},
  "geometry": {"coordinates":[-157.87857500000001,21.342142],"type":"Point"}
}