{
  "type": "Feature",
  "properties": {
    "addr:full":"250 Puako Beach Dr Kamuela HI 96743",
    "addr:housenumber":"250",
    "addr:postcode":"96743",
    "addr:street":"Puako Beach Dr",
    "iso:country":"US",
    "sg:address":"250 Puako Beach Dr",
    "sg:city":"Kamuela",
    "sg:classifiers":[
        {
            "category":"Museum",
            "type":"Entertainment"
        }
    ],
    "sg:phone":"+1 808 886 5533",
    "sg:postcode":"96743",
    "sg:province":"HI",
    "sg:tags":[
        "gallery"
    ],
    "wof:name":"Dolphin Gallery",
    "wof:placetype":"venue"
},
  "geometry": {"coordinates":[-155.84809000000001,19.9673],"type":"Point"}
}