{
  "type": "Feature",
  "properties": {
    "iso:country":"US",
    "sg:address":"147 S Puunene Ave",
    "sg:city":"Kahului",
    "sg:classifiers":[
        {
            "category":"Autos & Motor Vehicles",
            "subcategory":"Fuel & Gas Station",
            "type":"Retail Goods"
        }
    ],
    "sg:phone":"+1 808 871 4202",
    "sg:postcode":"96732",
    "sg:province":"HI",
    "sg:tags":[
        "oil"
    ],
    "wof:name":"J's Shell Inc",
    "wof:placetype":"venue"
},
  "geometry": {"coordinates":[-156.46557899999999,20.887445],"type":"Point"}
}