{
  "type": "Feature",
  "properties": {
    "iso:country":"US",
    "sg:address":"2982 Kress St",
    "sg:city":"Lihue",
    "sg:classifiers":[
        {
            "category":"Restaurant",
            "type":"Food & Drink"
        }
    ],
    "sg:phone":"+1 808 245 2921",
    "sg:postcode":"96766",
    "sg:province":"HI",
    "wof:name":"Lihue Barbecue Inn",
    "wof:placetype":"venue"
},
  "geometry": {"coordinates":[-159.36550399999999,21.972167],"type":"Point"}
}