{
  "type": "Feature",
  "properties": {
    "addr:full":"501 Sumner St Honolulu HI 96817",
    "addr:housenumber":"501",
    "addr:postcode":"96817",
    "addr:street":"Sumner St",
    "iso:country":"US",
    "sg:address":"501 Sumner St",
    "sg:city":"Honolulu",
    "sg:classifiers":[
        {
            "category":"Wholesale",
            "subcategory":"Apparel",
            "type":"Manufacturing & Wholesale Goods"
        }
    ],
    "sg:phone":"+1 808 537 6937",
    "sg:postcode":"96817",
    "sg:province":"HI",
    "sg:tags":[
        "piece"
    ],
    "wof:name":"Forever Florals Nani Makana",
    "wof:placetype":"venue"
},
  "geometry": {"coordinates":[-157.868596,21.318077],"type":"Point"}
}