{
  "type": "Feature",
  "properties": {
    "iso:country":"US",
    "sg:address":"1720 Ala Moana Blvd",
    "sg:city":"Honolulu",
    "sg:classifiers":[
        {
            "category":"Real Estate",
            "subcategory":"Architect",
            "type":"Services"
        }
    ],
    "sg:phone":"+1 808 942 3823",
    "sg:postcode":"96815",
    "sg:province":"HI",
    "wof:name":"Allen Ng & Assoc Architect",
    "wof:placetype":"venue"
},
  "geometry": {"coordinates":[-157.83979600000001,21.287012],"type":"Point"}
}