{
  "type": "Feature",
  "properties": {
    "iso:country":"US",
    "sg:address":"825 Front St",
    "sg:city":"Lahaina",
    "sg:classifiers":[
        {
            "category":"Recreation",
            "type":"Entertainment"
        }
    ],
    "sg:phone":"+1 808 661 8221",
    "sg:postcode":"96761",
    "sg:province":"HI",
    "sg:tags":[
        "ticket"
    ],
    "wof:name":"Lahaina Ticket Co",
    "wof:placetype":"venue"
},
  "geometry": {"coordinates":[-156.68284199999999,20.878597],"type":"Point"}
}