{
  "type": "Feature",
  "properties": {
    "iso:country":"US",
    "sg:address":"4770 Kanalani St",
    "sg:city":"Kailua Kona",
    "sg:classifiers":[
        {
            "category":"Building & Trades",
            "subcategory":"Construction",
            "type":"Services"
        }
    ],
    "sg:phone":"+1 808 326 5452",
    "sg:postcode":"96740",
    "sg:province":"HI",
    "sg:tags":[
        "woodworker"
    ],
    "wof:name":"Matthew J D'Avella Woodworking",
    "wof:placetype":"venue"
},
  "geometry": {"coordinates":[-156.02123499999999,19.69007],"type":"Point"}
}