{
  "type": "Feature",
  "properties": {
    "iso:country":"US",
    "sg:address":"174 Wailua Rd",
    "sg:city":"Kapaa",
    "sg:classifiers":[
        {
            "category":"Ferry",
            "type":"Transportation"
        }
    ],
    "sg:phone":"+1 808 821 6892",
    "sg:postcode":"96746",
    "sg:province":"HI",
    "sg:tags":[
        "excursion",
        "boat"
    ],
    "wof:name":"Smiths Motor Boat Service",
    "wof:placetype":"venue"
},
  "geometry": {"coordinates":[-159.33604199999999,22.047186],"type":"Point"}
}