{
  "type": "Feature",
  "properties": {
    "iso:country":"US",
    "sg:address":"198 N King St",
    "sg:city":"Honolulu",
    "sg:classifiers":[
        {
            "category":"Restaurant",
            "type":"Food & Drink"
        }
    ],
    "sg:phone":"+1 808 531 1185",
    "sg:postcode":"96817",
    "sg:province":"HI",
    "wof:name":"Golden River Restaurant",
    "wof:placetype":"venue"
},
  "geometry": {"coordinates":[-157.86419900000001,21.313015],"type":"Point"}
}