{
  "type": "Feature",
  "properties": {
    "iso:country":"US",
    "sg:address":"205 Lewers St",
    "sg:city":"Honolulu",
    "sg:classifiers":[
        {
            "category":"Travel",
            "subcategory":"Travel Agent",
            "type":"Entertainment"
        }
    ],
    "sg:phone":"+1 808 923 8687",
    "sg:postcode":"96815",
    "sg:province":"HI",
    "sg:tags":[
        "transportation"
    ],
    "wof:name":"Island World Tickets & Tours",
    "wof:placetype":"venue"
},
  "geometry": {"coordinates":[-157.83126899999999,21.278753],"type":"Point"}
}