{
  "type": "Feature",
  "properties": {
    "addr:full":"1325 S Kihei Rd Kihei HI 96753",
    "addr:housenumber":"1325",
    "addr:postcode":"96753",
    "addr:street":"S Kihei Rd",
    "iso:country":"US",
    "sg:address":"1325 S Kihei Rd",
    "sg:city":"Kihei",
    "sg:classifiers":[
        {
            "category":"Retail",
            "subcategory":"Laundry & Dry Cleaning",
            "type":"Services"
        }
    ],
    "sg:phone":"+1 808 874 9141",
    "sg:postcode":"96753",
    "sg:province":"HI",
    "wof:name":"Kihei Carpet Cleaning Inc",
    "wof:placetype":"venue"
},
  "geometry": {"coordinates":[-156.456119,20.751281],"type":"Point"}
}