{
  "type": "Feature",
  "properties": {
    "iso:country":"US",
    "sg:address":"391 Nui St",
    "sg:city":"Mililani",
    "sg:classifiers":[
        {
            "category":"Professional",
            "subcategory":"Management & Consulting",
            "type":"Services"
        }
    ],
    "sg:phone":"+1 808 230 4528",
    "sg:postcode":"96789",
    "sg:province":"HI",
    "sg:tags":[
        "technical",
        "support",
        "public"
    ],
    "wof:name":"Warren N Ah Loo",
    "wof:placetype":"venue"
},
  "geometry": {"coordinates":[-158.025756,21.433732],"type":"Point"}
}