{
  "type": "Feature",
  "properties": {
    "iso:country":"US",
    "sg:address":"745 Fort Street Ml",
    "sg:city":"Honolulu",
    "sg:classifiers":[
        {
            "category":"Professional",
            "subcategory":"Management & Consulting",
            "type":"Services"
        }
    ],
    "sg:phone":"+1 808 533 0528",
    "sg:postcode":"96813",
    "sg:province":"HI",
    "wof:name":"Bc Inc",
    "wof:placetype":"venue"
},
  "geometry": {"coordinates":[-157.863764,21.308151],"type":"Point"}
}