{
  "type": "Feature",
  "properties": {
    "iso:country":"US",
    "sg:address":"428 Mokuola St",
    "sg:city":"Waipahu",
    "sg:classifiers":[
        {
            "category":"Insurance",
            "subcategory":"Insurance Agent",
            "type":"Services"
        }
    ],
    "sg:phone":"+1 808 678 1200",
    "sg:postcode":"96797",
    "sg:province":"HI",
    "wof:name":"Waipio Insurance LLC",
    "wof:placetype":"venue"
},
  "geometry": {"coordinates":[-158.00586200000001,21.387495],"type":"Point"}
}