{
  "type": "Feature",
  "properties": {
    "iso:country":"US",
    "sg:address":"2965 Mokumoa St",
    "sg:city":"Honolulu",
    "sg:classifiers":[
        {
            "category":"Wholesale",
            "subcategory":"Electrical",
            "type":"Manufacturing & Wholesale Goods"
        }
    ],
    "sg:phone":"+1 808 839 4594",
    "sg:postcode":"96819",
    "sg:province":"HI",
    "sg:tags":[
        "lighting",
        "fixture"
    ],
    "wof:name":"Island Lighting Co Inc",
    "wof:placetype":"venue"
},
  "geometry": {"coordinates":[-157.899711,21.342766],"type":"Point"}
}