{
  "type": "Feature",
  "properties": {
    "iso:country":"US",
    "sg:address":"841 Bishop St",
    "sg:city":"Honolulu",
    "sg:classifiers":[
        {
            "category":"Professional",
            "subcategory":"Accounting & Tax Preparation",
            "type":"Services"
        }
    ],
    "sg:phone":"+1 808 521 5051",
    "sg:postcode":"96813",
    "sg:province":"HI",
    "sg:tags":[
        "accountant"
    ],
    "wof:name":"Gilbert Leong & Gregory Lee",
    "wof:placetype":"venue"
},
  "geometry": {"coordinates":[-157.86240799999999,21.307771],"type":"Point"}
}