{
  "type": "Feature",
  "properties": {
    "addr:full":"3523 Hookupu St Pahoa HI 96778",
    "addr:housenumber":"3523",
    "addr:postcode":"96778",
    "addr:street":"Hookupu St",
    "iso:country":"US",
    "sg:address":"3523 Hookupu St",
    "sg:city":"Pahoa",
    "sg:classifiers":[
        {
            "category":"Food & Beverages",
            "subcategory":"Specialty",
            "type":"Retail Goods"
        }
    ],
    "sg:phone":"+1 808 965 9195",
    "sg:postcode":"96778",
    "sg:province":"HI",
    "wof:name":"Forerunners Hawaii",
    "wof:placetype":"venue"
},
  "geometry": {"coordinates":[-154.903831,19.460719],"type":"Point"}
}