{
  "type": "Feature",
  "properties": {
    "iso:country":"US",
    "sg:address":"2600 Kaumualii Hwy",
    "sg:city":"Lihue",
    "sg:classifiers":[
        {
            "category":"Shopping",
            "subcategory":"Jewelry",
            "type":"Retail Goods"
        }
    ],
    "sg:phone":"+1 808 246 0888",
    "sg:postcode":"96766",
    "sg:province":"HI",
    "wof:name":"Prestige Jewelers",
    "wof:placetype":"venue"
},
  "geometry": {"coordinates":[-159.38431700000001,21.970843],"type":"Point"}
}