{
  "type": "Feature",
  "properties": {
    "addr:full":"225 Queen St Honolulu HI 96813",
    "addr:housenumber":"225",
    "addr:postcode":"96813",
    "addr:street":"Queen St",
    "iso:country":"US",
    "sg:address":"225 Queen St",
    "sg:city":"Honolulu",
    "sg:classifiers":[
        {
            "category":"Banks & Credit Unions",
            "subcategory":"Bank",
            "type":"Services"
        }
    ],
    "sg:phone":"+1 808 522 0915",
    "sg:postcode":"96813",
    "sg:province":"HI",
    "sg:tags":[
        "loan",
        "real estate"
    ],
    "wof:name":"Pinnacle Funding Group",
    "wof:placetype":"venue"
},
  "geometry": {"coordinates":[-157.86174600000001,21.306326],"type":"Point"}
}