{
  "type": "Feature",
  "properties": {
    "iso:country":"US",
    "sg:address":"575 Keolu Dr",
    "sg:city":"Kailua",
    "sg:classifiers":[
        {
            "category":"Building & Trades",
            "subcategory":"Construction",
            "type":"Services"
        }
    ],
    "sg:phone":"+1 808 262 0848",
    "sg:postcode":"96734",
    "sg:province":"HI",
    "sg:tags":[
        "contractor",
        "work",
        "carpentry"
    ],
    "wof:name":"R W Almonte Enterprises Inc",
    "wof:placetype":"venue"
},
  "geometry": {"coordinates":[-157.740453,21.382269],"type":"Point"}
}