{
  "type": "Feature",
  "properties": {
    "iso:country":"US",
    "sg:address":"5436 Kawaihau Rd",
    "sg:city":"Kapaa",
    "sg:classifiers":[
        {
            "category":"Personal",
            "type":"Services"
        }
    ],
    "sg:phone":"+1 808 822 0748",
    "sg:postcode":"96746",
    "sg:province":"HI",
    "sg:tags":[
        "wear",
        "formal"
    ],
    "wof:name":"A Formal Affair",
    "wof:placetype":"venue"
},
  "geometry": {"coordinates":[-159.32787400000001,22.096186],"type":"Point"}
}