{
  "type": "Feature",
  "properties": {
    "addr:full":"2646 Kilihau St Honolulu HI 96819",
    "addr:housenumber":"2646",
    "addr:postcode":"96819",
    "addr:street":"Kilihau St",
    "iso:country":"US",
    "sg:address":"2646 Kilihau St",
    "sg:city":"Honolulu",
    "sg:classifiers":[
        {
            "category":"Manufacturing",
            "subcategory":"Chemicals & Compounds",
            "type":"Manufacturing & Wholesale Goods"
        }
    ],
    "sg:phone":"+1 808 839 9088",
    "sg:postcode":"96819",
    "sg:province":"HI",
    "sg:tags":[
        "fertilizer",
        "equipment",
        "electrical",
        "nitrogenous",
        "mfg"
    ],
    "wof:name":"Light Bulbs Plus LLC",
    "wof:placetype":"venue"
},
  "geometry": {"coordinates":[-157.896377,21.33538],"type":"Point"}
}