{
  "type": "Feature",
  "properties": {
    "addr:full":"1256 Hakimo Rd Waianae HI 96792",
    "addr:housenumber":"1256",
    "addr:postcode":"96792",
    "addr:street":"Hakimo Rd",
    "iso:country":"US",
    "sg:address":"1256 Hakimo Rd",
    "sg:city":"Waianae",
    "sg:classifiers":[
        {
            "category":"Farming",
            "subcategory":"Nursery",
            "type":"Manufacturing & Wholesale Goods"
        }
    ],
    "sg:phone":"+1 808 668 2328",
    "sg:postcode":"96792",
    "sg:province":"HI",
    "sg:tags":[
        "plant"
    ],
    "wof:name":"Jerant Brothers",
    "wof:placetype":"venue"
},
  "geometry": {"coordinates":[-158.14041800000001,21.418343],"type":"Point"}
}