{
  "type": "Feature",
  "properties": {
    "addr:full":"1781 Omaopio Rd Kula HI 96790",
    "addr:housenumber":"1781",
    "addr:postcode":"96790",
    "addr:street":"Omaopio Rd",
    "iso:country":"US",
    "sg:address":"1781 Omaopio Rd",
    "sg:city":"Kula",
    "sg:phone":"+1 808 878 2905",
    "sg:postcode":"96790",
    "sg:province":"HI",
    "sg:tags":[
        "farm",
        "field",
        "crop"
    ],
    "wof:name":"Evonuk Farms",
    "wof:placetype":"venue"
},
  "geometry": {"coordinates":[-156.34647899999999,20.805593],"type":"Point"}
}