{
  "type": "Feature",
  "properties": {
    "iso:country":"US",
    "sg:address":"722 9th Ave",
    "sg:city":"Honolulu",
    "sg:classifiers":[
        {
            "category":"Building & Trades",
            "subcategory":"Construction",
            "type":"Services"
        }
    ],
    "sg:phone":"+1 808 734 4376",
    "sg:postcode":"96816",
    "sg:province":"HI",
    "sg:tags":[
        "hanging",
        "contractor"
    ],
    "wof:name":"Blue Sky Productions",
    "wof:placetype":"venue"
},
  "geometry": {"coordinates":[-157.80620999999999,21.277809],"type":"Point"}
}