{
  "type": "Feature",
  "properties": {
    "iso:country":"US",
    "sg:address":"1021 Aeoia St",
    "sg:city":"Ewa Beach",
    "sg:classifiers":[
        {
            "category":"Building & Trades",
            "subcategory":"Construction",
            "type":"Services"
        }
    ],
    "sg:phone":"+1 808 681 5163",
    "sg:postcode":"96706",
    "sg:province":"HI",
    "sg:tags":[
        "masonry",
        "contractor"
    ],
    "wof:name":"E M Masonry",
    "wof:placetype":"venue"
},
  "geometry": {"coordinates":[-158.025609,21.35524],"type":"Point"}
}