{
  "type": "Feature",
  "properties": {
    "iso:country":"US",
    "sg:address":"2290 Alahao Pl",
    "sg:city":"Honolulu",
    "sg:classifiers":[
        {
            "category":"Freight",
            "type":"Transportation"
        }
    ],
    "sg:phone":"+1 808 942 8622",
    "sg:postcode":"96819",
    "sg:province":"HI",
    "sg:tags":[
        "operator",
        "local",
        "trucking"
    ],
    "wof:name":"Offroad Express",
    "wof:placetype":"venue"
},
  "geometry": {"coordinates":[-157.88846599999999,21.329084],"type":"Point"}
}