{
  "type": "Feature",
  "properties": {
    "iso:country":"US",
    "sg:address":"1119 Mowai St",
    "sg:city":"Kailua",
    "sg:classifiers":[
        {
            "category":"Home & Garden",
            "subcategory":"Building Materials",
            "type":"Retail Goods"
        }
    ],
    "sg:phone":"+1 808 728 8407",
    "sg:postcode":"96734",
    "sg:province":"HI",
    "sg:tags":[
        "glass",
        "leaded"
    ],
    "wof:name":"Leialoha's Stained Glass",
    "wof:placetype":"venue"
},
  "geometry": {"coordinates":[-157.72645199999999,21.374775],"type":"Point"}
}