{
  "type": "Feature",
  "properties": {
    "iso:country":"US",
    "sg:address":"5759 Kini Loop",
    "sg:city":"Kailua Kona",
    "sg:classifiers":[
        {
            "category":"Health Services",
            "subcategory":"Medical Lab",
            "type":"Services"
        }
    ],
    "sg:phone":"+1 808 326 2548",
    "sg:postcode":"96740",
    "sg:province":"HI",
    "sg:tags":[
        "laboratory"
    ],
    "wof:name":"Diagnostic Lab Services Inc",
    "wof:placetype":"venue"
},
  "geometry": {"coordinates":[-155.978812,19.638748],"type":"Point"}
}