{
  "type": "Feature",
  "properties": {
    "iso:country":"US",
    "sg:address":"5615 Luhia St",
    "sg:city":"Kailua Kona",
    "sg:classifiers":[
        {
            "category":"Shopping",
            "subcategory":"Bicycles & Sporting Goods",
            "type":"Retail Goods"
        }
    ],
    "sg:phone":"+1 808 329 3100",
    "sg:postcode":"96740",
    "sg:province":"HI",
    "wof:name":"Polynesian Paddling Products",
    "wof:placetype":"venue"
},
  "geometry": {"coordinates":[-155.99889999999999,19.647397],"type":"Point"}
}