{
  "type": "Feature",
  "properties": {
    "iso:country":"US",
    "sg:address":"818 Pine St",
    "sg:city":"Honolulu",
    "sg:classifiers":[
        {
            "category":"Travel",
            "subcategory":"Travel Agent",
            "type":"Entertainment"
        }
    ],
    "sg:phone":"+1 808 921 9503",
    "sg:postcode":"96817",
    "sg:province":"HI",
    "sg:tags":[
        "family",
        "bus",
        "agency",
        "tour",
        "operator",
        "sightseeing"
    ],
    "wof:name":"Jtb Overseas Development Corp",
    "wof:placetype":"venue"
},
  "geometry": {"coordinates":[-157.86792600000001,21.317388],"type":"Point"}
}