{
  "type": "Feature",
  "properties": {
    "iso:country":"US",
    "sg:address":"2412 Prince Edward St",
    "sg:city":"Honolulu",
    "sg:classifiers":[
        {
            "category":"Retail",
            "subcategory":"Repair Shop",
            "type":"Services"
        }
    ],
    "sg:phone":"+1 808 924 1676",
    "sg:postcode":"96815",
    "sg:province":"HI",
    "sg:tags":[
        "marine",
        "electric"
    ],
    "wof:name":"Investech Hawaii Inc",
    "wof:placetype":"venue"
},
  "geometry": {"coordinates":[-157.82431199999999,21.276773],"type":"Point"}
}