{
  "type": "Feature",
  "properties": {
    "iso:country":"US",
    "sg:address":"1031 Auahi St",
    "sg:city":"Honolulu",
    "sg:classifiers":[
        {
            "category":"Shopping",
            "subcategory":"Musical Instruments",
            "type":"Retail Goods"
        }
    ],
    "sg:phone":"+1 808 524 5675",
    "sg:postcode":"96814",
    "sg:province":"HI",
    "wof:name":"Yamaha Music Center",
    "wof:placetype":"venue"
},
  "geometry": {"coordinates":[-157.85529099999999,21.29485],"type":"Point"}
}