{
  "type": "Feature",
  "properties": {
    "iso:country":"US",
    "sg:address":"718 Puuhale Rd",
    "sg:city":"Honolulu",
    "sg:classifiers":[
        {
            "category":"Education",
            "subcategory":"Special Training",
            "type":"Public Place"
        }
    ],
    "sg:phone":"+1 808 440 4646",
    "sg:postcode":"96819",
    "sg:province":"HI",
    "sg:tags":[
        "educational"
    ],
    "wof:name":"Ukulele Guild of Hawaii",
    "wof:placetype":"venue"
},
  "geometry": {"coordinates":[-157.881686,21.330602],"type":"Point"}
}