{
  "type": "Feature",
  "properties": {
    "addr:full":"972 Front St Lahaina HI 96761",
    "addr:housenumber":"972",
    "addr:postcode":"96761",
    "addr:street":"Front St",
    "iso:country":"US",
    "sg:address":"972 Front St",
    "sg:city":"Lahaina",
    "sg:classifiers":[
        {
            "category":"Real Estate",
            "subcategory":"Real Estate Operator",
            "type":"Services"
        }
    ],
    "sg:phone":"+1 808 667 9161",
    "sg:postcode":"96761",
    "sg:province":"HI",
    "sg:tags":[
        "mall",
        "shopping",
        "center"
    ],
    "wof:name":"Landing At Lahaina",
    "wof:placetype":"venue"
},
  "geometry": {"coordinates":[-156.684282,20.88088],"type":"Point"}
}