{
  "type": "Feature",
  "properties": {
    "iso:country":"US",
    "sg:address":"111 Hekili St",
    "sg:city":"Kailua",
    "sg:classifiers":[
        {
            "category":"Freight",
            "type":"Transportation"
        }
    ],
    "sg:phone":"+1 808 254 2838",
    "sg:postcode":"96734",
    "sg:province":"HI",
    "sg:tags":[
        "operator",
        "local",
        "trucking"
    ],
    "wof:name":"Wurlitzer Moving Inc",
    "wof:placetype":"venue"
},
  "geometry": {"coordinates":[-157.74148400000001,21.391889],"type":"Point"}
}