{
  "type": "Feature",
  "properties": {
    "addr:full":"6321 Mahuahua Pl Kailua Kona HI 96740",
    "addr:housenumber":"6321",
    "addr:postcode":"96740",
    "addr:street":"Mahuahua Pl",
    "iso:country":"US",
    "sg:address":"6321 Mahuahua Pl",
    "sg:city":"Kailua Kona",
    "sg:classifiers":[
        {
            "category":"Organizations",
            "subcategory":"Religious Organization",
            "type":"Services"
        }
    ],
    "sg:phone":"+1 808 329 5530",
    "sg:postcode":"96740",
    "sg:province":"HI",
    "sg:tags":[
        "church"
    ],
    "wof:name":"Halelewa Baptist Church",
    "wof:placetype":"venue"
},
  "geometry": {"coordinates":[-155.96775099999999,19.610912],"type":"Point"}
}