{
  "type": "Feature",
  "properties": {
    "iso:country":"US",
    "sg:address":"3566 Harding Ave",
    "sg:city":"Honolulu",
    "sg:classifiers":[
        {
            "category":"Food & Beverages",
            "subcategory":"Specialty",
            "type":"Retail Goods"
        }
    ],
    "sg:phone":"+1 808 739 2990",
    "sg:postcode":"96816",
    "sg:province":"HI",
    "sg:tags":[
        "health",
        "store"
    ],
    "wof:name":"Kaimuki Health Market",
    "wof:placetype":"venue"
},
  "geometry": {"coordinates":[-157.800164,21.281376],"type":"Point"}
}