{
  "type": "Feature",
  "properties": {
    "addr:full":"650 Iwilei Rd Honolulu HI 96817",
    "addr:housenumber":"650",
    "addr:postcode":"96817",
    "addr:street":"Iwilei Rd",
    "iso:country":"US",
    "sg:address":"650 Iwilei Rd",
    "sg:city":"Honolulu",
    "sg:classifiers":[
        {
            "category":"Sports & Exercise",
            "subcategory":"Gym",
            "type":"Entertainment"
        }
    ],
    "sg:phone":"+1 808 525 5688",
    "sg:postcode":"96817",
    "sg:province":"HI",
    "sg:tags":[
        "club",
        "health",
        "studio",
        "gymnasium"
    ],
    "wof:name":"Curves For Women",
    "wof:placetype":"venue"
},
  "geometry": {"coordinates":[-157.86893800000001,21.315966],"type":"Point"}
}