{
  "type": "Feature",
  "properties": {
    "iso:country":"US",
    "sg:address":"560 N Nimitz Hwy",
    "sg:city":"Honolulu",
    "sg:classifiers":[
        {
            "category":"Professional",
            "type":"Services"
        },
        {
            "category":"Professional",
            "subcategory":"Advertising",
            "type":"Services"
        }
    ],
    "sg:phone":"+1 808 521 1821",
    "sg:postcode":"96817",
    "sg:province":"HI",
    "sg:tags":[
        "establishment"
    ],
    "sg:website":"www.viacomoutdoor.com",
    "wof:name":"Hawaii Malls Inc",
    "wof:placetype":"venue"
},
  "geometry": {"coordinates":[-157.87003300000001,21.313861],"type":"Point"}
}