{
  "type": "Feature",
  "properties": {
    "iso:country":"US",
    "sg:address":"888 S King St",
    "sg:city":"Honolulu",
    "sg:classifiers":[
        {
            "category":"Home & Garden",
            "subcategory":"Furniture",
            "type":"Retail Goods"
        },
        {
            "category":"Health Services",
            "subcategory":"Doctor",
            "type":"Services"
        }
    ],
    "sg:phone":"+1 808 522 4448",
    "sg:postcode":"96813",
    "sg:province":"HI",
    "sg:tags":[
        "physician",
        "surgeon",
        "medical"
    ],
    "wof:name":"Sleep Disorders Ctr Of Pacific",
    "wof:placetype":"venue"
},
  "geometry": {"coordinates":[-157.85018099999999,21.302004],"type":"Point"}
}