{
  "type": "Feature",
  "properties": {
    "iso:country":"US",
    "sg:address":"1330 Pali Hwy",
    "sg:city":"Honolulu",
    "sg:classifiers":[
        {
            "category":"Shopping",
            "subcategory":"Pharmacy",
            "type":"Retail Goods"
        }
    ],
    "sg:phone":"+1 808 536 7302",
    "sg:postcode":"96813",
    "sg:province":"HI",
    "wof:name":"Longs Drug",
    "wof:placetype":"venue"
},
  "geometry": {"coordinates":[-157.85759300000001,21.311605],"type":"Point"}
}