{
  "type": "Feature",
  "properties": {
    "iso:country":"US",
    "sg:address":"1100 Ward Ave",
    "sg:city":"Honolulu",
    "sg:classifiers":[
        {
            "category":"Professional",
            "subcategory":"Computer Services",
            "type":"Services"
        }
    ],
    "sg:phone":"+1 808 545 1822",
    "sg:postcode":"96814",
    "sg:province":"HI",
    "sg:tags":[
        "development",
        "consulting"
    ],
    "wof:name":"Lang Group The",
    "wof:placetype":"venue"
},
  "geometry": {"coordinates":[-157.84943999999999,21.303834],"type":"Point"}
}