{
  "type": "Feature",
  "properties": {
    "addr:full":"11 Arizona Memorial Rd Honolulu HI 96818",
    "addr:housenumber":"11",
    "addr:postcode":"96818",
    "addr:street":"Arizona Memorial Rd",
    "iso:country":"US",
    "sg:address":"11 Arizona Memorial Rd",
    "sg:city":"Honolulu",
    "sg:classifiers":[
        {
            "category":"Museum",
            "type":"Entertainment"
        }
    ],
    "sg:phone":"+1 808 423 1341",
    "sg:postcode":"96818",
    "sg:province":"HI",
    "sg:tags":[
        "military",
        "park",
        "history"
    ],
    "sg:website":"www.bowfin.org",
    "wof:name":"USS Bowfin Submarine Museum Pk",
    "wof:placetype":"venue"
},
  "geometry": {"coordinates":[-157.937793,21.364353],"type":"Point"}
}