{
  "type": "Feature",
  "properties": {
    "iso:country":"US",
    "sg:address":"1508 Palolo Ave",
    "sg:city":"Honolulu",
    "sg:classifiers":[
        {
            "category":"Travel",
            "subcategory":"Hotels & Motels",
            "type":"Entertainment"
        }
    ],
    "sg:phone":"+1 808 735 1813",
    "sg:postcode":"96816",
    "sg:province":"HI",
    "sg:tags":[
        "operation"
    ],
    "wof:name":"18 Drive Inn",
    "wof:placetype":"venue"
},
  "geometry": {"coordinates":[-157.80240699999999,21.2909],"type":"Point"}
}