{
  "type": "Feature",
  "properties": {
    "addr:full":"758 Kapahulu Ave Honolulu HI 96816",
    "addr:housenumber":"758",
    "addr:postcode":"96816",
    "addr:street":"Kapahulu Ave",
    "iso:country":"US",
    "sg:address":"758 Kapahulu Ave",
    "sg:city":"Honolulu",
    "sg:classifiers":[
        {
            "category":"Recreation",
            "type":"Entertainment"
        }
    ],
    "sg:phone":"+1 808 561 5938",
    "sg:postcode":"96816",
    "sg:province":"HI",
    "wof:name":"AAA Watersports",
    "wof:placetype":"venue"
},
  "geometry": {"coordinates":[-157.81423799999999,21.281293],"type":"Point"}
}