{
  "type": "Feature",
  "properties": {
    "iso:country":"US",
    "sg:address":"516 Kinoole St",
    "sg:city":"Hilo",
    "sg:classifiers":[
        {
            "category":"Manufacturing",
            "subcategory":"Printing",
            "type":"Manufacturing & Wholesale Goods"
        }
    ],
    "sg:phone":"+1 808 969 1151",
    "sg:postcode":"96720",
    "sg:province":"HI",
    "sg:tags":[
        "commercial"
    ],
    "wof:name":"Hilo Printers LTD",
    "wof:placetype":"venue"
},
  "geometry": {"coordinates":[-155.08596800000001,19.720232],"type":"Point"}
}