{
  "type": "Feature",
  "properties": {
    "iso:country":"US",
    "sg:address":"209 Moanalua Rd",
    "sg:city":"Aiea",
    "sg:classifiers":[
        {
            "category":"Personal",
            "subcategory":"Beauty Salon",
            "type":"Services"
        }
    ],
    "sg:phone":"+1 808 487 9144",
    "sg:postcode":"96701",
    "sg:province":"HI",
    "sg:tags":[
        "shop"
    ],
    "wof:name":"Le Nails",
    "wof:placetype":"venue"
},
  "geometry": {"coordinates":[-157.93097599999999,21.378787],"type":"Point"}
}