{
  "type": "Feature",
  "properties": {
    "iso:country":"US",
    "sg:address":"430 N Kalaheo Ave",
    "sg:city":"Kailua",
    "sg:classifiers":[
        {
            "category":"Manufacturing",
            "subcategory":"Chemicals & Compounds",
            "type":"Manufacturing & Wholesale Goods"
        }
    ],
    "sg:phone":"+1 808 262 8443",
    "sg:postcode":"96734",
    "sg:province":"HI",
    "sg:tags":[
        "industrial",
        "gas"
    ],
    "wof:name":"Hawaiian Islands Gas Inc",
    "wof:placetype":"venue"
},
  "geometry": {"coordinates":[-157.74262999999999,21.407244],"type":"Point"}
}