{
  "type": "Feature",
  "properties": {
    "iso:country":"US",
    "sg:address":"1556 Piikoi St",
    "sg:city":"Honolulu",
    "sg:classifiers":[
        {
            "category":"Restaurant",
            "type":"Food & Drink"
        }
    ],
    "sg:phone":"+1 808 952 9980",
    "sg:postcode":"96822",
    "sg:province":"HI",
    "wof:name":"Pearl Vietnamese Bistro",
    "wof:placetype":"venue"
},
  "geometry": {"coordinates":[-157.84068199999999,21.305243],"type":"Point"}
}