{
  "type": "Feature",
  "properties": {
    "iso:country":"US",
    "sg:address":"3108 Olu St",
    "sg:city":"Honolulu",
    "sg:classifiers":[
        {
            "category":"Restaurant",
            "type":"Food & Drink"
        }
    ],
    "sg:phone":"+1 808 734 5573",
    "sg:postcode":"96816",
    "sg:province":"HI",
    "sg:tags":[
        "bar"
    ],
    "wof:name":"Izakaya Nonbei",
    "wof:placetype":"venue"
},
  "geometry": {"coordinates":[-157.81194099999999,21.28256],"type":"Point"}
}