{
  "type": "Feature",
  "properties": {
    "addr:full":"2435 Bingham St Honolulu HI 96826",
    "addr:housenumber":"2435",
    "addr:postcode":"96826",
    "addr:street":"Bingham St",
    "iso:country":"US",
    "sg:address":"2435 Bingham St",
    "sg:city":"Honolulu",
    "sg:classifiers":[
        {
            "category":"Manufacturing",
            "subcategory":"Jewelry",
            "type":"Manufacturing & Wholesale Goods"
        }
    ],
    "sg:phone":"+1 808 941 7087",
    "sg:postcode":"96826",
    "sg:province":"HI",
    "sg:tags":[
        "precious",
        "metal",
        "mfg"
    ],
    "wof:name":"Suzi Shimada",
    "wof:placetype":"venue"
},
  "geometry": {"coordinates":[-157.82233600000001,21.293943],"type":"Point"}
}