{
  "type": "Feature",
  "properties": {
    "addr:full":"501 Hahaione St Honolulu HI 96825",
    "addr:housenumber":"501",
    "addr:postcode":"96825",
    "addr:street":"Hahaione St",
    "iso:country":"US",
    "sg:address":"501 Hahaione St",
    "sg:city":"Honolulu",
    "sg:classifiers":[
        {
            "category":"Banks & Credit Unions",
            "subcategory":"Financial Services",
            "type":"Services"
        }
    ],
    "sg:phone":"+1 808 396 8401",
    "sg:postcode":"96825",
    "sg:province":"HI",
    "sg:tags":[
        "investor"
    ],
    "wof:name":"Kkc Investment Inc",
    "wof:placetype":"venue"
},
  "geometry": {"coordinates":[-157.707955,21.294631],"type":"Point"}
}