{
  "type": "Feature",
  "properties": {
    "addr:full":"2752 Woodlawn Dr Honolulu HI 96822",
    "addr:housenumber":"2752",
    "addr:postcode":"96822",
    "addr:street":"Woodlawn Dr",
    "iso:country":"US",
    "sg:address":"2752 Woodlawn Dr",
    "sg:city":"Honolulu",
    "sg:classifiers":[
        {
            "category":"Restaurant",
            "type":"Food & Drink"
        }
    ],
    "sg:phone":"+1 808 988 1088",
    "sg:postcode":"96822",
    "sg:province":"HI",
    "wof:name":"Pearl's Korean BBQ",
    "wof:placetype":"venue"
},
  "geometry": {"coordinates":[-157.810046,21.307362],"type":"Point"}
}