{
  "type": "Feature",
  "properties": {
    "iso:country":"US",
    "sg:address":"828 Anoi Rd",
    "sg:city":"Kaneohe",
    "sg:classifiers":[
        {
            "category":"Organizations",
            "subcategory":"Professional Association",
            "type":"Services"
        }
    ],
    "sg:phone":"+1 808 233 5656",
    "sg:postcode":"96744",
    "sg:province":"HI",
    "wof:name":"Families For Real",
    "wof:placetype":"venue"
},
  "geometry": {"coordinates":[-157.804474,21.409351],"type":"Point"}
}