{
  "type": "Feature",
  "properties": {
    "iso:country":"US",
    "sg:address":"178 Main St",
    "sg:city":"Honolulu",
    "sg:classifiers":[
        {
            "category":"Government",
            "subcategory":"Office",
            "type":"Public Place"
        }
    ],
    "sg:phone":"+1 808 472 6630",
    "sg:postcode":"96818",
    "sg:province":"HI",
    "sg:tags":[
        "accounting",
        "bookkeeping",
        "finance"
    ],
    "wof:name":"Defense Fin & Accounting Svc",
    "wof:placetype":"venue"
},
  "geometry": {"coordinates":[-157.93526399999999,21.348779],"type":"Point"}
}