{
  "type": "Feature",
  "properties": {
    "addr:full":"1005 Moanalua Rd Aiea HI 96701",
    "addr:housenumber":"1005",
    "addr:postcode":"96701",
    "addr:street":"Moanalua Rd",
    "iso:country":"US",
    "sg:address":"1005 Moanalua Rd",
    "sg:city":"Aiea",
    "sg:classifiers":[
        {
            "category":"Utilities",
            "subcategory":"Telephone",
            "type":"Services"
        }
    ],
    "sg:phone":"+1 808 487 2900",
    "sg:postcode":"96701",
    "sg:province":"HI",
    "sg:tags":[
        "communications"
    ],
    "wof:name":"Hele Net Inc",
    "wof:placetype":"venue"
},
  "geometry": {"coordinates":[-157.94079500000001,21.385893],"type":"Point"}
}