{
  "type": "Feature",
  "properties": {
    "iso:country":"US",
    "sg:address":"336 Eggerking Rd",
    "sg:city":"Kapaa",
    "sg:classifiers":[
        {
            "category":"Building & Trades",
            "subcategory":"Plumbing",
            "type":"Services"
        }
    ],
    "sg:phone":"+1 808 822 4261",
    "sg:postcode":"96746",
    "sg:province":"HI",
    "sg:tags":[
        "plumbing",
        "sheet",
        "ventilation",
        "metal",
        "contractor"
    ],
    "wof:name":"Hideo Tanaka Plumbing Inc",
    "wof:placetype":"venue"
},
  "geometry": {"coordinates":[-159.34002899999999,22.057077],"type":"Point"}
}