{
  "type": "Feature",
  "properties": {
    "iso:country":"US",
    "sg:address":"515 Main St",
    "sg:city":"Honolulu",
    "sg:classifiers":[
        {
            "category":"Organizations",
            "subcategory":"Religious Organization",
            "type":"Services"
        }
    ],
    "sg:phone":"+1 808 422 7033",
    "sg:postcode":"96818",
    "sg:province":"HI",
    "wof:name":"Church of Christ Pharbor",
    "wof:placetype":"venue"
},
  "geometry": {"coordinates":[-157.93610899999999,21.341881],"type":"Point"}
}