{
  "type": "Feature",
  "properties": {
    "iso:country":"US",
    "sg:address":"880 Awa St",
    "sg:city":"Hilo",
    "sg:classifiers":[
        {
            "category":"Wholesale",
            "subcategory":"Plants",
            "type":"Manufacturing & Wholesale Goods"
        }
    ],
    "sg:phone":"+1 808 959 3636",
    "sg:postcode":"96720",
    "sg:province":"HI",
    "sg:tags":[
        "nursery",
        "tree"
    ],
    "wof:name":"H & L Terada Farm",
    "wof:placetype":"venue"
},
  "geometry": {"coordinates":[-155.04478,19.65489],"type":"Point"}
}