{
  "type": "Feature",
  "properties": {
    "addr:full":"2846 S King St Honolulu HI 96826",
    "addr:housenumber":"2846",
    "addr:postcode":"96826",
    "addr:street":"S King St",
    "iso:country":"US",
    "sg:address":"2846 S King St",
    "sg:city":"Honolulu",
    "sg:classifiers":[
        {
            "category":"Retail",
            "subcategory":"Portrait Studio",
            "type":"Services"
        }
    ],
    "sg:phone":"+1 808 945 3686",
    "sg:postcode":"96826",
    "sg:province":"HI",
    "sg:tags":[
        "photographer"
    ],
    "wof:name":"Studio",
    "wof:placetype":"venue"
},
  "geometry": {"coordinates":[-157.81805499999999,21.289872],"type":"Point"}
}