{
  "type": "Feature",
  "properties": {
    "addr:full":"2222 Kaluaopalena St Honolulu HI 96819",
    "addr:housenumber":"2222",
    "addr:postcode":"96819",
    "addr:street":"Kaluaopalena St",
    "iso:country":"US",
    "sg:address":"2222 Kaluaopalena St",
    "sg:city":"Honolulu",
    "sg:classifiers":[
        {
            "category":"Farming",
            "subcategory":"Nursery",
            "type":"Manufacturing & Wholesale Goods"
        }
    ],
    "sg:phone":"+1 808 842 1661",
    "sg:postcode":"96819",
    "sg:province":"HI",
    "sg:tags":[
        "greenhouse"
    ],
    "wof:name":"Floral Resources Hawaii Inc",
    "wof:placetype":"venue"
},
  "geometry": {"coordinates":[-157.884907,21.332184],"type":"Point"}
}