{
  "type": "Feature",
  "properties": {
    "addr:full":"142 Leoleo St Waipahu HI 96797",
    "addr:housenumber":"142",
    "addr:postcode":"96797",
    "addr:street":"Leoleo St",
    "iso:country":"US",
    "sg:address":"142 Leoleo St",
    "sg:city":"Waipahu",
    "sg:classifiers":[
        {
            "category":"Building & Trades",
            "subcategory":"Construction",
            "type":"Services"
        }
    ],
    "sg:phone":"+1 808 671 4002",
    "sg:postcode":"96797",
    "sg:province":"HI",
    "sg:tags":[
        "ventilation",
        "air",
        "conditioning",
        "contractor"
    ],
    "wof:name":"Commercial Sheetmetal Co Inc",
    "wof:placetype":"venue"
},
  "geometry": {"coordinates":[-158.020421,21.376788],"type":"Point"}
}