{
  "type": "Feature",
  "properties": {
    "iso:country":"US",
    "sg:address":"720 Laukapu St",
    "sg:city":"Hilo",
    "sg:classifiers":[
        {
            "category":"Manufacturing",
            "subcategory":"Apparel",
            "type":"Manufacturing & Wholesale Goods"
        }
    ],
    "sg:phone":"+1 808 961 6492",
    "sg:postcode":"96720",
    "sg:province":"HI",
    "sg:tags":[
        "patch"
    ],
    "wof:name":"PACIFIC Image Co",
    "wof:placetype":"venue"
},
  "geometry": {"coordinates":[-155.06727599999999,19.708947],"type":"Point"}
}