{
  "type": "Feature",
  "properties": {
    "iso:country":"US",
    "sg:address":"100 Kanaloa Ave",
    "sg:city":"Kahului",
    "sg:classifiers":[
        {
            "category":"Social Services",
            "type":"Services"
        }
    ],
    "sg:phone":"+1 808 242 4363",
    "sg:postcode":"96732",
    "sg:province":"HI",
    "sg:tags":[
        "youth",
        "organization",
        "center"
    ],
    "wof:name":"Boys & Girls Club Of Maui",
    "wof:placetype":"venue"
},
  "geometry": {"coordinates":[-156.48692,20.8888],"type":"Point"}
}