{
  "type": "Feature",
  "properties": {
    "iso:country":"US",
    "sg:address":"407 Iliwahi Loop",
    "sg:city":"Kailua",
    "sg:classifiers":[
        {
            "category":"Building & Trades",
            "subcategory":"Construction",
            "type":"Services"
        }
    ],
    "sg:phone":"+1 808 263 0222",
    "sg:postcode":"96734",
    "sg:province":"HI",
    "sg:tags":[
        "res",
        "contractor"
    ],
    "wof:name":"Gold Coast Construction",
    "wof:placetype":"venue"
},
  "geometry": {"coordinates":[-157.75327200000001,21.41718],"type":"Point"}
}