{
  "type": "Feature",
  "properties": {
    "addr:full":"12 Kamehameha Hwy Kaneohe HI 96744",
    "addr:housenumber":"12",
    "addr:postcode":"96744",
    "addr:street":"Kamehameha Hwy",
    "iso:country":"US",
    "sg:address":"12 Kamehameha Hwy",
    "sg:city":"Kaneohe",
    "sg:classifiers":[
        {
            "category":"Health Services",
            "subcategory":"Medical Lab",
            "type":"Services"
        }
    ],
    "sg:phone":"+1 808 233 0819",
    "sg:postcode":"96744",
    "sg:province":"HI",
    "sg:tags":[
        "laboratory"
    ],
    "wof:name":"Clinical Labs of Hawaii LLP",
    "wof:placetype":"venue"
},
  "geometry": {"coordinates":[-157.780933,21.374944],"type":"Point"}
}