{
  "type": "Feature",
  "properties": {
    "addr:full":"718 Kanalani Pl Haleiwa HI 96712",
    "addr:housenumber":"718",
    "addr:postcode":"96712",
    "addr:street":"Kanalani Pl",
    "iso:country":"US",
    "sg:address":"718 Kanalani Pl",
    "sg:city":"Haleiwa",
    "sg:classifiers":[
        {
            "category":"Retail",
            "subcategory":"Repair Shop",
            "type":"Services"
        }
    ],
    "sg:phone":"+1 808 429 5387",
    "sg:postcode":"96712",
    "sg:province":"HI",
    "wof:name":"Custom Decor LLC",
    "wof:placetype":"venue"
},
  "geometry": {"coordinates":[-158.03475700000001,21.639574],"type":"Point"}
}