{
  "type": "Feature",
  "properties": {
    "addr:full":"420 S Puunene Ave Kahului HI 96732",
    "addr:housenumber":"420",
    "addr:postcode":"96732",
    "addr:street":"S Puunene Ave",
    "iso:country":"US",
    "sg:address":"420 S Puunene Ave",
    "sg:city":"Kahului",
    "sg:classifiers":[
        {
            "category":"Building & Trades",
            "subcategory":"Construction",
            "type":"Services"
        }
    ],
    "sg:phone":"+1 808 893 0334",
    "sg:postcode":"96732",
    "sg:province":"HI",
    "sg:tags":[
        "home",
        "builder"
    ],
    "wof:name":"Habitat For Humanity",
    "wof:placetype":"venue"
},
  "geometry": {"coordinates":[-156.462806,20.881316],"type":"Point"}
}