{
  "type": "Feature",
  "properties": {
    "iso:country":"US",
    "sg:address":"321 Makaala St",
    "sg:city":"Hilo",
    "sg:classifiers":[
        {
            "category":"Autos & Motor Vehicles",
            "subcategory":"Fuel & Gas Station",
            "type":"Retail Goods"
        }
    ],
    "sg:phone":"+1 808 935 5165",
    "sg:postcode":"96720",
    "sg:province":"HI",
    "sg:tags":[
        "oil"
    ],
    "wof:name":"Waiakea Center Chevron",
    "wof:placetype":"venue"
},
  "geometry": {"coordinates":[-155.06618,19.69926],"type":"Point"}
}