{
  "type": "Feature",
  "properties": {
    "addr:full":"16 Kainehe St Kailua HI 96734",
    "addr:housenumber":"16",
    "addr:postcode":"96734",
    "addr:street":"Kainehe St",
    "iso:country":"US",
    "sg:address":"16 Kainehe St",
    "sg:city":"Kailua",
    "sg:classifiers":[
        {
            "category":"Food & Beverages",
            "subcategory":"Liquor & Beverages",
            "type":"Retail Goods"
        }
    ],
    "sg:phone":"+1 808 262 6388",
    "sg:postcode":"96734",
    "sg:province":"HI",
    "sg:tags":[
        "alcoholic"
    ],
    "wof:name":"Kaineahe Liquor",
    "wof:placetype":"venue"
},
  "geometry": {"coordinates":[-157.745946,21.394687],"type":"Point"}
}