{
  "type": "Feature",
  "properties": {
    "addr:full":"5759 Kuakini Hwy Kailua Kona HI 96740",
    "addr:housenumber":"5759",
    "addr:postcode":"96740",
    "addr:street":"Kuakini Hwy",
    "iso:country":"US",
    "sg:address":"5759 Kuakini Hwy",
    "sg:city":"Kailua Kona",
    "sg:classifiers":[
        {
            "category":"Professional",
            "subcategory":"Business Services",
            "type":"Services"
        }
    ],
    "sg:phone":"+1 808 329 8885",
    "sg:postcode":"96740",
    "sg:province":"HI",
    "sg:tags":[
        "interior",
        "consultant",
        "design",
        "decorator"
    ],
    "wof:name":"Kitchens & Interiors-Von Hake",
    "wof:placetype":"venue"
},
  "geometry": {"coordinates":[-155.99032700000001,19.638273],"type":"Point"}
}