{
  "type": "Feature",
  "properties": {
    "addr:full":"222 Pohaku Dr Keaau HI 96749",
    "addr:housenumber":"222",
    "addr:postcode":"96749",
    "addr:street":"Pohaku Dr Keaau",
    "iso:country":"US",
    "sg:address":"222 Pohaku Dr",
    "sg:city":"Keaau",
    "sg:classifiers":[
        {
            "category":"Farming",
            "subcategory":"Nursery",
            "type":"Manufacturing & Wholesale Goods"
        }
    ],
    "sg:phone":"+1 808 966 8285",
    "sg:postcode":"96749",
    "sg:province":"HI",
    "sg:tags":[
        "greenhouse"
    ],
    "wof:name":"Yolanda Tabile",
    "wof:placetype":"venue"
},
  "geometry": {"coordinates":[-155.012766,19.580214],"type":"Point"}
}