{
  "type": "Feature",
  "properties": {
    "addr:full":"5491 Mamalahoa Hwy Holualoa HI 96725",
    "addr:housenumber":"5491",
    "addr:postcode":"96725",
    "addr:street":"Mamalahoa Hwy",
    "iso:country":"US",
    "sg:address":"5491 Mamalahoa Hwy",
    "sg:city":"Holualoa",
    "sg:classifiers":[
        {
            "category":"Shopping",
            "subcategory":"Clothing, Apparel, & Fashions",
            "type":"Retail Goods"
        }
    ],
    "sg:phone":"+1 808 324 1508",
    "sg:postcode":"96725",
    "sg:province":"HI",
    "sg:tags":[
        "footwear"
    ],
    "wof:name":"Hg Innovative Network",
    "wof:placetype":"venue"
},
  "geometry": {"coordinates":[-155.95418000000001,19.64783],"type":"Point"}
}