{
  "type": "Feature",
  "properties": {
    "addr:full":"545 Chin Chuck Rd Honomu HI 96710",
    "addr:housenumber":"545",
    "addr:postcode":"96710",
    "addr:street":"Chin Chuck Rd",
    "iso:country":"US",
    "sg:address":"545 Chin Chuck Rd",
    "sg:city":"Honomu",
    "sg:classifiers":[
        {
            "category":"Wholesale",
            "subcategory":"Plants",
            "type":"Manufacturing & Wholesale Goods"
        }
    ],
    "sg:phone":"+1 808 963 6283",
    "sg:postcode":"96710",
    "sg:province":"HI",
    "sg:tags":[
        "nursery",
        "tree"
    ],
    "wof:name":"Manelo Orchards",
    "wof:placetype":"venue"
},
  "geometry": {"coordinates":[-155.15383399999999,19.874196],"type":"Point"}
}