{
  "type": "Feature",
  "properties": {
    "addr:full":"3088 Akahi St Lihue HI 96766",
    "addr:housenumber":"3088",
    "addr:postcode":"96766",
    "addr:street":"Akahi St",
    "iso:country":"US",
    "sg:address":"3088 Akahi St",
    "sg:city":"Lihue",
    "sg:classifiers":[
        {
            "category":"Professional",
            "subcategory":"Accounting & Tax Preparation",
            "type":"Services"
        }
    ],
    "sg:phone":"+1 808 246 8788",
    "sg:postcode":"96766",
    "sg:province":"HI",
    "sg:tags":[
        "bookkeeping",
        "general"
    ],
    "wof:name":"Makena Miyake Inc",
    "wof:placetype":"venue"
},
  "geometry": {"coordinates":[-159.367357,21.977772],"type":"Point"}
}