{
  "type": "Feature",
  "properties": {
    "addr:full":"211 Pali Momi St Aiea HI 96701",
    "addr:housenumber":"211",
    "addr:postcode":"96701",
    "addr:street":"Pali Momi St",
    "iso:country":"US",
    "sg:address":"211 Pali Momi St",
    "sg:city":"Aiea",
    "sg:classifiers":[
        {
            "category":"Manufacturing",
            "subcategory":"Tools & Machinery",
            "type":"Manufacturing & Wholesale Goods"
        }
    ],
    "sg:phone":"+1 808 486 2169",
    "sg:postcode":"96701",
    "sg:province":"HI",
    "sg:tags":[
        "control"
    ],
    "wof:name":"Mesa Energy Systems Inc",
    "wof:placetype":"venue"
},
  "geometry": {"coordinates":[-157.93754200000001,21.383234],"type":"Point"}
}