{
  "type": "Feature",
  "properties": {
    "iso:country":"US",
    "sg:address":"429 Wainaku Ave",
    "sg:city":"Hilo",
    "sg:classifiers":[
        {
            "category":"Organizations",
            "subcategory":"Religious Organization",
            "type":"Services"
        }
    ],
    "sg:phone":"+1 808 935 6401",
    "sg:postcode":"96720",
    "sg:province":"HI",
    "sg:tags":[
        "church"
    ],
    "wof:name":"Berean Bible Church",
    "wof:placetype":"venue"
},
  "geometry": {"coordinates":[-155.091725,19.729136],"type":"Point"}
}