{
  "type": "Feature",
  "properties": {
    "iso:country":"US",
    "sg:address":"2831 Kalihi St",
    "sg:city":"Honolulu",
    "sg:classifiers":[
        {
            "category":"Restaurant",
            "type":"Food & Drink"
        }
    ],
    "sg:phone":"+1 808 842 4711",
    "sg:postcode":"96819",
    "sg:province":"HI",
    "sg:tags":[
        "caterer"
    ],
    "wof:name":"Earl Mc Donald Catering",
    "wof:placetype":"venue"
},
  "geometry": {"coordinates":[-157.85816199999999,21.352248],"type":"Point"}
}