{
  "type": "Feature",
  "properties": {
    "addr:full":"3245 Ala Laulani St Honolulu HI 96818",
    "addr:housenumber":"3245",
    "addr:postcode":"96818",
    "addr:street":"Ala Laulani St",
    "iso:country":"US",
    "sg:address":"3245 Ala Laulani St",
    "sg:city":"Honolulu",
    "sg:classifiers":[
        {
            "category":"Manufacturing",
            "subcategory":"Apparel",
            "type":"Manufacturing & Wholesale Goods"
        }
    ],
    "sg:phone":"+1 808 839 9188",
    "sg:postcode":"96818",
    "sg:province":"HI",
    "sg:tags":[
        "sewing",
        "contractor"
    ],
    "wof:name":"Lucky Hawaii Inc",
    "wof:placetype":"venue"
},
  "geometry": {"coordinates":[-157.91365400000001,21.348804],"type":"Point"}
}