{
  "type": "Feature",
  "properties": {
    "addr:full":"1833 Kalakaua Ave Honolulu HI 96815",
    "addr:housenumber":"1833",
    "addr:postcode":"96815",
    "addr:street":"Kalakaua Ave",
    "iso:country":"US",
    "sg:address":"1833 Kalakaua Ave",
    "sg:city":"Honolulu",
    "sg:classifiers":[
        {
            "category":"Shopping",
            "subcategory":"Department Store",
            "type":"Retail Goods"
        }
    ],
    "sg:phone":"+1 808 955 0877",
    "sg:postcode":"96815",
    "sg:province":"HI",
    "sg:tags":[
        "shop"
    ],
    "wof:name":"Horizon Discount Tours",
    "wof:placetype":"venue"
},
  "geometry": {"coordinates":[-157.834372,21.288059],"type":"Point"}
}