{
  "type": "Feature",
  "properties": {
    "iso:country":"US",
    "sg:address":"1326 Liona St",
    "sg:city":"Honolulu",
    "sg:classifiers":[
        {
            "category":"Retail",
            "subcategory":"Car Wash",
            "type":"Services"
        }
    ],
    "sg:phone":"+1 808 949 0454",
    "sg:postcode":"96814",
    "sg:province":"HI",
    "sg:tags":[
        "automobile",
        "detail",
        "clean"
    ],
    "wof:name":"Yajima Auto Detailing",
    "wof:placetype":"venue"
},
  "geometry": {"coordinates":[-157.841309,21.298051],"type":"Point"}
}