{
  "type": "Feature",
  "properties": {
    "iso:country":"US",
    "sg:address":"495 Hukilike St",
    "sg:city":"Kahului",
    "sg:classifiers":[
        {
            "category":"Professional",
            "subcategory":"Engineering",
            "type":"Services"
        }
    ],
    "sg:phone":"+1 808 877 6501",
    "sg:postcode":"96732",
    "sg:province":"HI",
    "sg:tags":[
        "general",
        "contractor"
    ],
    "wof:name":"Fong Construction Co LTD",
    "wof:placetype":"venue"
},
  "geometry": {"coordinates":[-156.45855399999999,20.882502],"type":"Point"}
}