{
  "type": "Feature",
  "properties": {
    "addr:full":"1727 Democrat St Honolulu HI 96819",
    "addr:housenumber":"1727",
    "addr:postcode":"96819",
    "addr:street":"Democrat St",
    "iso:country":"US",
    "sg:address":"1727 Democrat St",
    "sg:city":"Honolulu",
    "sg:classifiers":[
        {
            "category":"Building & Trades",
            "subcategory":"Construction",
            "type":"Services"
        }
    ],
    "sg:phone":"+1 808 847 0288",
    "sg:postcode":"96819",
    "sg:province":"HI",
    "sg:tags":[
        "resurfacing",
        "laying",
        "refinishing",
        "floor"
    ],
    "wof:name":"Allied Floor Corp",
    "wof:placetype":"venue"
},
  "geometry": {"coordinates":[-157.884872,21.324089],"type":"Point"}
}