{
  "type": "Feature",
  "properties": {
    "iso:country":"US",
    "sg:address":"1637 Makiki St",
    "sg:city":"Honolulu",
    "sg:classifiers":[
        {
            "category":"Professional",
            "subcategory":"Business Services",
            "type":"Services"
        }
    ],
    "sg:phone":"+1 808 942 2026",
    "sg:postcode":"96822",
    "sg:province":"HI",
    "wof:name":"Del Marc Fujita Enterprises LL",
    "wof:placetype":"venue"
},
  "geometry": {"coordinates":[-157.83394799999999,21.304685],"type":"Point"}
}