{
  "type": "Feature",
  "properties": {
    "iso:country":"US",
    "sg:address":"2345 Ala Wai Blvd",
    "sg:city":"Honolulu",
    "sg:classifiers":[
        {
            "category":"Personal",
            "type":"Services"
        }
    ],
    "sg:phone":"+1 808 923 1603",
    "sg:postcode":"96815",
    "sg:province":"HI",
    "sg:tags":[
        "consultant",
        "wedding"
    ],
    "wof:name":"Beau Marriage",
    "wof:placetype":"venue"
},
  "geometry": {"coordinates":[-157.82410899999999,21.280111],"type":"Point"}
}