{
  "type": "Feature",
  "properties": {
    "addr:full":"901 River St Honolulu HI 96817",
    "addr:housenumber":"901",
    "addr:postcode":"96817",
    "addr:street":"River St",
    "iso:country":"US",
    "sg:address":"901 River St",
    "sg:city":"Honolulu",
    "sg:classifiers":[
        {
            "category":"Retail",
            "subcategory":"Laundry & Dry Cleaning",
            "type":"Services"
        },
        {
            "category":"Shopping",
            "subcategory":"Clothing, Apparel, & Fashions",
            "type":"Retail Goods"
        }
    ],
    "sg:phone":"+1 808 550 2776",
    "sg:postcode":"96817",
    "sg:province":"HI",
    "sg:tags":[
        "alteration"
    ],
    "wof:name":"Nikki Alteration",
    "wof:placetype":"venue"
},
  "geometry": {"coordinates":[-157.864227,21.313579],"type":"Point"}
}