{
  "type": "Feature",
  "properties": {
    "addr:full":"2205 Nuna St Honolulu HI 96821",
    "addr:housenumber":"2205",
    "addr:postcode":"96821",
    "addr:street":"Nuna St",
    "iso:country":"US",
    "sg:address":"2205 Nuna St",
    "sg:city":"Honolulu",
    "sg:classifiers":[
        {
            "category":"Wholesale",
            "subcategory":"Non-durable Goods",
            "type":"Manufacturing & Wholesale Goods"
        }
    ],
    "sg:phone":"+1 808 373 5322",
    "sg:postcode":"96821",
    "sg:province":"HI",
    "sg:tags":[
        "gift"
    ],
    "wof:name":"Creative Hawaiian Gifts Inc",
    "wof:placetype":"venue"
},
  "geometry": {"coordinates":[-157.76462900000001,21.295453],"type":"Point"}
}