{
  "type": "Feature",
  "properties": {
    "addr:full":"920 Iwaena St Aiea HI 96701",
    "addr:housenumber":"920",
    "addr:postcode":"96701",
    "addr:street":"Iwaena St",
    "iso:country":"US",
    "sg:address":"920 Iwaena St",
    "sg:city":"Aiea",
    "sg:classifiers":[
        {
            "category":"Wholesale",
            "subcategory":"Electrical",
            "type":"Manufacturing & Wholesale Goods"
        }
    ],
    "sg:phone":"+1 808 487 9891",
    "sg:postcode":"96701",
    "sg:province":"HI",
    "sg:tags":[
        "alarm",
        "burglar",
        "system"
    ],
    "wof:name":"Diversified Security Design",
    "wof:placetype":"venue"
},
  "geometry": {"coordinates":[-157.91070099999999,21.376385],"type":"Point"}
}