{
  "type": "Feature",
  "properties": {
    "addr:full":"4353 Rice St Lihue HI 96766",
    "addr:housenumber":"4353",
    "addr:postcode":"96766",
    "addr:street":"Rice St",
    "iso:country":"US",
    "sg:address":"4353 Rice St",
    "sg:city":"Lihue",
    "sg:classifiers":[
        {
            "category":"Shopping",
            "subcategory":"Used Merchandise",
            "type":"Retail Goods"
        }
    ],
    "sg:phone":"+1 808 245 9397",
    "sg:postcode":"96766",
    "sg:province":"HI",
    "sg:tags":[
        "shop",
        "consignment"
    ],
    "wof:name":"Lifestyles Consignment Btq",
    "wof:placetype":"venue"
},
  "geometry": {"coordinates":[-159.36674400000001,21.973732],"type":"Point"}
}