{
  "type": "Feature",
  "properties": {
    "iso:country":"US",
    "sg:address":"587 Kam Hwy",
    "sg:city":"Laie",
    "sg:classifiers":[
        {
            "category":"Social Services",
            "subcategory":"Adult Care",
            "type":"Services"
        }
    ],
    "sg:phone":"+1 808 293 1163",
    "sg:postcode":"96717",
    "sg:province":"HI",
    "sg:tags":[
        "juvenile"
    ],
    "wof:name":"Aloha Youth Academy",
    "wof:placetype":"venue"
},
  "geometry": {"coordinates":[-157.90805800000001,21.607478],"type":"Point"}
}