{
  "type": "Feature",
  "properties": {
    "iso:country":"US",
    "sg:address":"451 Kapahulu Ave",
    "sg:city":"Honolulu",
    "sg:classifiers":[
        {
            "category":"Shopping",
            "subcategory":"Bicycles & Sporting Goods",
            "type":"Retail Goods"
        }
    ],
    "sg:phone":"+1 808 735 3594",
    "sg:postcode":"96815",
    "sg:province":"HI",
    "sg:website":"www.classicsurfhawaii.com",
    "wof:name":"Classic Surfboards",
    "wof:placetype":"venue"
},
  "geometry": {"coordinates":[-157.81522699999999,21.275609],"type":"Point"}
}