{
  "type": "Feature",
  "properties": {
    "addr:full":"1210 Dillingham Blvd Honolulu HI 96817",
    "addr:housenumber":"1210",
    "addr:postcode":"96817",
    "addr:street":"Dillingham Blvd",
    "iso:country":"US",
    "sg:address":"1210 Dillingham Blvd",
    "sg:city":"Honolulu",
    "sg:classifiers":[
        {
            "category":"Banks & Credit Unions",
            "subcategory":"Bank",
            "type":"Services"
        }
    ],
    "sg:phone":"+1 808 841 0981",
    "sg:postcode":"96817",
    "sg:province":"HI",
    "sg:tags":[
        "personal",
        "institution"
    ],
    "wof:name":"Wells Fargo",
    "wof:placetype":"venue"
},
  "geometry": {"coordinates":[-157.87445700000001,21.322938],"type":"Point"}
}