{
  "type": "Feature",
  "properties": {
    "addr:full":"103 Kalakaua St Hilo HI 96720",
    "addr:housenumber":"103",
    "addr:postcode":"96720",
    "addr:street":"Kalakaua St",
    "iso:country":"US",
    "sg:address":"103 Kalakaua St",
    "sg:city":"Hilo",
    "sg:classifiers":[
        {
            "category":"Health Services",
            "subcategory":"Health Practitioner",
            "type":"Services"
        }
    ],
    "sg:phone":"+1 808 934 7030",
    "sg:postcode":"96720",
    "sg:province":"HI",
    "sg:tags":[
        "acupuncture"
    ],
    "wof:name":"Healing Arts Alliance",
    "wof:placetype":"venue"
},
  "geometry": {"coordinates":[-155.088052,19.724962],"type":"Point"}
}