{
  "type": "Feature",
  "properties": {
    "iso:country":"US",
    "sg:address":"137 Hana Hwy",
    "sg:city":"Paia",
    "sg:classifiers":[
        {
            "category":"Banks & Credit Unions",
            "subcategory":"Bank",
            "type":"Services"
        }
    ],
    "sg:phone":"+1 808 264 3715",
    "sg:postcode":"96779",
    "sg:province":"HI",
    "sg:tags":[
        "loan",
        "broker",
        "mortgage"
    ],
    "wof:name":"International Mortgage LLC",
    "wof:placetype":"venue"
},
  "geometry": {"coordinates":[-156.38543100000001,20.918722],"type":"Point"}
}