{
  "type": "Feature",
  "properties": {
    "addr:full":"1801 Liliha St Honolulu HI 96817",
    "addr:housenumber":"1801",
    "addr:postcode":"96817",
    "addr:street":"Liliha St",
    "iso:country":"US",
    "sg:address":"1801 Liliha St",
    "sg:city":"Honolulu",
    "sg:classifiers":[
        {
            "category":"Shopping",
            "subcategory":"Hobbies, Toys, & Games",
            "type":"Retail Goods"
        }
    ],
    "sg:phone":"+1 808 536 5255",
    "sg:postcode":"96817",
    "sg:province":"HI",
    "sg:website":"www.cbyweddings.com",
    "wof:name":"Creations By You",
    "wof:placetype":"venue"
},
  "geometry": {"coordinates":[-157.85611800000001,21.324603],"type":"Point"}
}