{
  "type": "Feature",
  "properties": {
    "iso:country":"US",
    "sg:address":"560 N Nimitz Hwy",
    "sg:city":"Honolulu",
    "sg:classifiers":[
        {
            "category":"Professional",
            "subcategory":"Lawyer & Legal Services",
            "type":"Services"
        }
    ],
    "sg:phone":"+1 808 524 7900",
    "sg:postcode":"96817",
    "sg:province":"HI",
    "sg:tags":[
        "attorney"
    ],
    "wof:name":"Robinson & Chur",
    "wof:placetype":"venue"
},
  "geometry": {"coordinates":[-157.87003300000001,21.313861],"type":"Point"}
}