{
  "type": "Feature",
  "properties": {
    "iso:country":"US",
    "sg:address":"4264 Halenani St",
    "sg:city":"Lihue",
    "sg:classifiers":[
        {
            "category":"Shopping",
            "type":"Retail Goods"
        }
    ],
    "sg:phone":"+1 808 246 2171",
    "sg:postcode":"96766",
    "sg:province":"HI",
    "sg:tags":[
        "ice"
    ],
    "wof:name":"Island Cubes",
    "wof:placetype":"venue"
},
  "geometry": {"coordinates":[-159.36535599999999,21.971591],"type":"Point"}
}