{
  "type": "Feature",
  "properties": {
    "addr:full":"1742 Lawrence Rd Kailua HI 96734",
    "addr:housenumber":"1742",
    "addr:postcode":"96734",
    "addr:street":"Lawrence Rd",
    "iso:country":"US",
    "sg:address":"1742 Lawrence Rd",
    "sg:city":"Kailua",
    "sg:classifiers":[
        {
            "category":"Manufacturing",
            "subcategory":"Glass & Minerals",
            "type":"Manufacturing & Wholesale Goods"
        }
    ],
    "sg:phone":"+1 808 265 2714",
    "sg:postcode":"96734",
    "sg:province":"HI",
    "sg:tags":[
        "product",
        "mfg"
    ],
    "wof:name":"Imagine That Stained Glass",
    "wof:placetype":"venue"
},
  "geometry": {"coordinates":[-157.74181799999999,21.451321],"type":"Point"}
}