{
  "type": "Feature",
  "properties": {
    "addr:full":"5615 Luhia St Kailua Kona HI 96740",
    "addr:housenumber":"5615",
    "addr:postcode":"96740",
    "addr:street":"Luhia St",
    "iso:country":"US",
    "sg:address":"5615 Luhia St",
    "sg:city":"Kailua Kona",
    "sg:classifiers":[
        {
            "category":"Sports & Exercise",
            "subcategory":"Gym",
            "type":"Entertainment"
        }
    ],
    "sg:phone":"+1 808 329 2444",
    "sg:postcode":"96740",
    "sg:province":"HI",
    "sg:tags":[
        "club",
        "health",
        "studio",
        "gymnasium"
    ],
    "wof:name":"Omega Fitness",
    "wof:placetype":"venue"
},
  "geometry": {"coordinates":[-155.99889999999999,19.647397],"type":"Point"}
}