{
  "type": "Feature",
  "properties": {
    "iso:country":"US",
    "sg:address":"5000 Kahala Ave",
    "sg:city":"Honolulu",
    "sg:classifiers":[
        {
            "category":"Shopping",
            "subcategory":"Clothing, Apparel, & Fashions",
            "type":"Retail Goods"
        }
    ],
    "sg:phone":"+1 808 738 5251",
    "sg:postcode":"96816",
    "sg:province":"HI",
    "sg:tags":[
        "ready",
        "handbag",
        "ac"
    ],
    "wof:name":"Par Excellence",
    "wof:placetype":"venue"
},
  "geometry": {"coordinates":[-157.77631400000001,21.271685],"type":"Point"}
}