{
  "type": "Feature",
  "properties": {
    "addr:full":"5751 Kuakini Hwy Kailua Kona HI 96740",
    "addr:postcode":"5751;96740",
    "addr:street":"Kuakini Hwy",
    "iso:country":"US",
    "sg:address":"5751 Kuakini Hwy",
    "sg:city":"Kailua Kona",
    "sg:classifiers":[
        {
            "category":"Wholesale",
            "subcategory":"Office Equipment",
            "type":"Manufacturing & Wholesale Goods"
        }
    ],
    "sg:phone":"+1 808 326 1169",
    "sg:postcode":"96740",
    "sg:province":"HI",
    "sg:tags":[
        "machine",
        "duplicating",
        "copying"
    ],
    "wof:name":"Kawon Enterprises Inc",
    "wof:placetype":"venue"
},
  "geometry": {"coordinates":[-155.990172,19.637976],"type":"Point"}
}