{
  "type": "Feature",
  "properties": {
    "iso:country":"US",
    "sg:address":"463 Laukapu St",
    "sg:city":"Hilo",
    "sg:classifiers":[
        {
            "category":"Wholesale",
            "subcategory":"Machinery & Supplies",
            "type":"Manufacturing & Wholesale Goods"
        }
    ],
    "sg:phone":"+1 808 935 4833",
    "sg:postcode":"96720",
    "sg:province":"HI",
    "sg:tags":[
        "equipment",
        "construction",
        "contractor"
    ],
    "wof:name":"Mels Equipment and Parts Inc",
    "wof:placetype":"venue"
},
  "geometry": {"coordinates":[-155.06713500000001,19.71512],"type":"Point"}
}