{
  "type": "Feature",
  "properties": {
    "addr:full":"20 Manana St Waimanalo HI 96795",
    "addr:housenumber":"20",
    "addr:postcode":"96795",
    "addr:street":"Manana St",
    "iso:country":"US",
    "sg:address":"20 Manana St",
    "sg:city":"Waimanalo",
    "sg:classifiers":[
        {
            "category":"Real Estate",
            "subcategory":"Real Estate Agent",
            "type":"Services"
        }
    ],
    "sg:phone":"+1 808 259 8811",
    "sg:postcode":"96795",
    "sg:province":"HI",
    "sg:tags":[
        "management"
    ],
    "wof:name":"Sunshine Properties",
    "wof:placetype":"venue"
},
  "geometry": {"coordinates":[-157.69947400000001,21.335476],"type":"Point"}
}