{
  "type": "Feature",
  "properties": {
    "iso:country":"US",
    "sg:address":"115 Aiea Heights Dr",
    "sg:city":"Aiea",
    "sg:classifiers":[
        {
            "category":"Professional",
            "subcategory":"Printing & Photocopies",
            "type":"Services"
        }
    ],
    "sg:phone":"+1 808 486 3819",
    "sg:postcode":"96701",
    "sg:province":"HI",
    "sg:tags":[
        "duplicating",
        "copying"
    ],
    "sg:website":"www.aieacopycenter.com",
    "wof:name":"Aiea Copy Ctr",
    "wof:placetype":"venue"
},
  "geometry": {"coordinates":[-157.929744,21.379439],"type":"Point"}
}