{
  "type": "Feature",
  "properties": {
    "iso:country":"US",
    "sg:address":"2530 Dole St",
    "sg:city":"Honolulu",
    "sg:classifiers":[
        {
            "category":"Education",
            "subcategory":"College",
            "type":"Public Place"
        }
    ],
    "sg:phone":"+1 808 956 8245",
    "sg:postcode":"96822",
    "sg:province":"HI",
    "wof:name":"Credit Prog Outreach College",
    "wof:placetype":"venue"
},
  "geometry": {"coordinates":[-157.81778,21.296772],"type":"Point"}
}