{
  "type": "Feature",
  "properties": {
    "addr:full":"46-056 Kamehameha Hwy Kaneohe HI 96744",
    "addr:housenumber":"46-056",
    "addr:postcode":"96744",
    "addr:street":"Kamehameha Hwy",
    "iso:country":"US",
    "sg:address":"46-056 Kamehameha Hwy",
    "sg:city":"Kaneohe",
    "sg:classifiers":[
        {
            "category":"Restaurant",
            "type":"Food & Drink"
        }
    ],
    "sg:menulink":"http://www.allmenus.com/hi/koolaupoko/103573-ruby-tuesdays/menu/",
    "sg:phone":"+1 808 235 5800",
    "sg:postcode":"96744",
    "sg:province":"HI",
    "sg:tags":[
        "burger",
        "american"
    ],
    "wof:name":"Ruby Tuesdays",
    "wof:placetype":"venue"
},
  "geometry": {"coordinates":[-157.78400199999999,21.378066],"type":"Point"}
}