{
  "type": "Feature",
  "properties": {
    "iso:country":"US",
    "sg:address":"3580 Mamane St",
    "sg:city":"Honokaa",
    "sg:classifiers":[
        {
            "category":"Restaurant",
            "type":"Food & Drink"
        }
    ],
    "sg:phone":"+1 808 775 7236",
    "sg:postcode":"96727",
    "sg:province":"HI",
    "wof:name":"Mamane Bar & Grill",
    "wof:placetype":"venue"
},
  "geometry": {"coordinates":[-155.465745,20.078281],"type":"Point"}
}