{
  "type": "Feature",
  "properties": {
    "iso:country":"US",
    "sg:address":"733 Bishop St",
    "sg:city":"Honolulu",
    "sg:classifiers":[
        {
            "category":"Professional",
            "subcategory":"Research",
            "type":"Services"
        }
    ],
    "sg:phone":"+1 808 585 7439",
    "sg:postcode":"96813",
    "sg:province":"HI",
    "sg:tags":[
        "development",
        "laboratory"
    ],
    "wof:name":"Archinoetics LLC",
    "wof:placetype":"venue"
},
  "geometry": {"coordinates":[-157.86289500000001,21.307425],"type":"Point"}
}