{
  "type": "Feature",
  "properties": {
    "iso:country":"US",
    "sg:address":"757 Kuhio Hwy",
    "sg:city":"Kapaa",
    "sg:classifiers":[
        {
            "category":"Government",
            "subcategory":"Fire Station",
            "type":"Public Place"
        }
    ],
    "sg:phone":"+1 808 822 4381",
    "sg:postcode":"96746",
    "sg:province":"HI",
    "sg:tags":[
        "county",
        "protection"
    ],
    "wof:name":"Kapaa Fire Station",
    "wof:placetype":"venue"
},
  "geometry": {"coordinates":[-159.321699,22.060053],"type":"Point"}
}