{
  "type": "Feature",
  "properties": {
    "iso:country":"US",
    "sg:address":"625 Kunawai Ln",
    "sg:city":"Honolulu",
    "sg:classifiers":[
        {
            "category":"Building & Trades",
            "subcategory":"Pest Control",
            "type":"Services"
        }
    ],
    "sg:phone":"+1 808 839 7338",
    "sg:postcode":"96817",
    "sg:province":"HI",
    "wof:name":"Pro-Tech Termite & Pest Cntrl",
    "wof:placetype":"venue"
},
  "geometry": {"coordinates":[-157.85837000000001,21.327267],"type":"Point"}
}