{
  "type": "Feature",
  "properties": {
    "iso:country":"US",
    "sg:address":"2005 Kalia Rd",
    "sg:city":"Honolulu",
    "sg:classifiers":[
        {
            "category":"Shopping",
            "subcategory":"Jewelry",
            "type":"Retail Goods"
        }
    ],
    "sg:phone":"+1 808 942 4858",
    "sg:postcode":"96815",
    "sg:province":"HI",
    "sg:tags":[
        "jeweler"
    ],
    "sg:website":"www.nahoku.com",
    "wof:name":"Nahoku Jewelry",
    "wof:placetype":"venue"
},
  "geometry": {"coordinates":[-157.834935,21.282814],"type":"Point"}
}