{
  "type": "Feature",
  "properties": {
    "iso:country":"US",
    "sg:address":"1013 Mamalahoa Hwy",
    "sg:city":"Kamuela",
    "sg:classifiers":[
        {
            "category":"Home & Garden",
            "subcategory":"Building Materials",
            "type":"Retail Goods"
        }
    ],
    "sg:phone":"+1 808 326 1616",
    "sg:postcode":"96743",
    "sg:province":"HI",
    "sg:tags":[
        "door"
    ],
    "sg:website":"www.bigislanddoor.com",
    "wof:name":"Raynor Garage Doors-Big Island",
    "wof:placetype":"venue"
},
  "geometry": {"coordinates":[-155.66185300000001,20.02442],"type":"Point"}
}