{
  "type": "Feature",
  "properties": {
    "iso:country":"US",
    "sg:address":"1158 Mamalahoa Hwy",
    "sg:city":"Kamuela",
    "sg:classifiers":[
        {
            "category":"Restaurant",
            "type":"Food & Drink"
        }
    ],
    "sg:phone":"+1 808 885 5552",
    "sg:postcode":"96743",
    "sg:province":"HI",
    "wof:name":"Subway Sandwiches & Salads",
    "wof:placetype":"venue"
},
  "geometry": {"coordinates":[-155.66905,20.02045],"type":"Point"}
}