{
  "type": "Feature",
  "properties": {
    "iso:country":"US",
    "sg:address":"732 Amaumau Pl",
    "sg:city":"Haleiwa",
    "sg:classifiers":[
        {
            "category":"Retail",
            "subcategory":"Self-service Laundry",
            "type":"Services"
        }
    ],
    "sg:phone":"+1 808 638 9138",
    "sg:postcode":"96712",
    "sg:province":"HI",
    "sg:tags":[
        "coin"
    ],
    "wof:name":"Fg Enterprises",
    "wof:placetype":"venue"
},
  "geometry": {"coordinates":[-158.06150099999999,21.647721],"type":"Point"}
}