{
  "type": "Feature",
  "properties": {
    "iso:country":"US",
    "sg:address":"3100 Kuhio Hwy",
    "sg:city":"Lihue",
    "sg:classifiers":[
        {
            "category":"Shopping",
            "subcategory":"Optical Goods",
            "type":"Retail Goods"
        }
    ],
    "sg:phone":"+1 808 246 8855",
    "sg:postcode":"96766",
    "sg:province":"HI",
    "sg:tags":[
        "medical"
    ],
    "wof:name":"Kuwai Eye Care",
    "wof:placetype":"venue"
},
  "geometry": {"coordinates":[-159.36822900000001,21.97868],"type":"Point"}
}