{
  "type": "Feature",
  "properties": {
    "iso:country":"US",
    "sg:address":"1040 Mamalahoa Hwy",
    "sg:city":"Kamuela",
    "sg:classifiers":[
        {
            "category":"Communications",
            "subcategory":"Radio Station",
            "type":"Services"
        }
    ],
    "sg:phone":"+1 808 885 9866",
    "sg:postcode":"96743",
    "sg:province":"HI",
    "sg:tags":[
        "company",
        "broadcasting"
    ],
    "wof:name":"KWYI",
    "wof:placetype":"venue"
},
  "geometry": {"coordinates":[-155.66349500000001,20.024361],"type":"Point"}
}