{
  "type": "Feature",
  "properties": {
    "iso:country":"US",
    "sg:address":"801 Moowaa St",
    "sg:city":"Honolulu",
    "sg:classifiers":[
        {
            "category":"Manufacturing",
            "subcategory":"Printing",
            "type":"Manufacturing & Wholesale Goods"
        }
    ],
    "sg:phone":"+1 808 832 0122",
    "sg:postcode":"96817",
    "sg:province":"HI",
    "sg:tags":[
        "printer"
    ],
    "sg:website":"www.orderprinting.com",
    "wof:name":"BCT",
    "wof:placetype":"venue"
},
  "geometry": {"coordinates":[-157.87312299999999,21.324268],"type":"Point"}
}