{
  "type": "Feature",
  "properties": {
    "iso:country":"US",
    "sg:address":"44 N Market St",
    "sg:city":"Wailuku",
    "sg:classifiers":[
        {
            "category":"Retail",
            "subcategory":"Portrait Studio",
            "type":"Services"
        }
    ],
    "sg:phone":"+1 808 242 8809",
    "sg:postcode":"96793",
    "sg:province":"HI",
    "sg:tags":[
        "photographer",
        "imaging"
    ],
    "wof:name":"Steve Brinkman Photography",
    "wof:placetype":"venue"
},
  "geometry": {"coordinates":[-156.50482099999999,20.89177],"type":"Point"}
}