{
  "type": "Feature",
  "properties": {
    "addr:full":"270 Lewers St Honolulu HI 96815",
    "addr:housenumber":"270",
    "addr:postcode":"96815",
    "addr:street":"Lewers St",
    "iso:country":"US",
    "sg:address":"270 Lewers St",
    "sg:city":"Honolulu",
    "sg:classifiers":[
        {
            "category":"Professional",
            "type":"Services"
        }
    ],
    "sg:phone":"+1 808 923 2681",
    "sg:postcode":"96815",
    "sg:province":"HI",
    "sg:tags":[
        "establishment"
    ],
    "wof:name":"Pipe Dreams Surf Co",
    "wof:placetype":"venue"
},
  "geometry": {"coordinates":[-157.83007900000001,21.279935],"type":"Point"}
}