{
  "type": "Feature",
  "properties": {
    "iso:country":"US",
    "sg:address":"716 Cooke St",
    "sg:city":"Honolulu",
    "sg:classifiers":[
        {
            "category":"Personal",
            "type":"Services"
        },
        {
            "category":"Shopping",
            "subcategory":"Clothing, Apparel, & Fashions",
            "type":"Retail Goods"
        }
    ],
    "sg:phone":"+1 808 947 2696",
    "sg:postcode":"96813",
    "sg:province":"HI",
    "sg:tags":[
        "shop",
        "bridal"
    ],
    "sg:website":"www.masakoformals.com",
    "wof:name":"Masako Formals",
    "wof:placetype":"venue"
},
  "geometry": {"coordinates":[-157.85615000000001,21.300683],"type":"Point"}
}