{
  "type": "Feature",
  "properties": {
    "iso:country":"US",
    "sg:address":"57 Palimalu Dr",
    "sg:city":"Honolulu",
    "sg:classifiers":[
        {
            "category":"Real Estate",
            "subcategory":"Developer",
            "type":"Services"
        }
    ],
    "sg:phone":"+1 808 595 8134",
    "sg:postcode":"96817",
    "sg:province":"HI",
    "wof:name":"Jon Gomes & Associates",
    "wof:placetype":"venue"
},
  "geometry": {"coordinates":[-157.82873900000001,21.344912],"type":"Point"}
}