{
  "type": "Feature",
  "properties": {
    "addr:full":"1790 Bougainvillea Loop Honolulu HI 96818",
    "addr:housenumber":"1790",
    "addr:postcode":"96818",
    "addr:street":"Bougainvillea Loop",
    "iso:country":"US",
    "sg:address":"1790 Bougainvillea Loop",
    "sg:city":"Honolulu",
    "sg:classifiers":[
        {
            "category":"Government",
            "subcategory":"Office",
            "type":"Public Place"
        }
    ],
    "sg:phone":"+1 808 836 4599",
    "sg:postcode":"96818",
    "sg:province":"HI",
    "sg:tags":[
        "federal",
        "security"
    ],
    "wof:name":"US Army Chaplin Office",
    "wof:placetype":"venue"
},
  "geometry": {"coordinates":[-157.916606,21.361709],"type":"Point"}
}