{
  "type": "Feature",
  "properties": {
    "addr:full":"631 Puuluna Pl Kaneohe HI 96744",
    "addr:housenumber":"631",
    "addr:postcode":"96744",
    "addr:street":"Puuluna Pl",
    "iso:country":"US",
    "sg:address":"631 Puuluna Pl",
    "sg:city":"Kaneohe",
    "sg:classifiers":[
        {
            "category":"Retail",
            "subcategory":"Animal Services",
            "type":"Services"
        }
    ],
    "sg:phone":"+1 808 247 7209",
    "sg:postcode":"96744",
    "sg:province":"HI",
    "wof:name":"Pet Purrfection",
    "wof:placetype":"venue"
},
  "geometry": {"coordinates":[-157.79213100000001,21.407135],"type":"Point"}
}