{
  "type": "Feature",
  "properties": {
    "addr:full":"490 Haleiwa Rd Haleiwa HI 96712",
    "addr:housenumber":"490",
    "addr:postcode":"96712",
    "addr:street":"Haleiwa Rd",
    "iso:country":"US",
    "sg:address":"490 Haleiwa Rd",
    "sg:city":"Haleiwa",
    "sg:classifiers":[
        {
            "category":"Organizations",
            "subcategory":"Professional Association",
            "type":"Services"
        }
    ],
    "sg:phone":"+1 808 637 4647",
    "sg:postcode":"96712",
    "sg:province":"HI",
    "wof:name":"Central Oahu Youth Svc Assn",
    "wof:placetype":"venue"
},
  "geometry": {"coordinates":[-158.11349899999999,21.58406],"type":"Point"}
}