{
  "type": "Feature",
  "properties": {
    "iso:country":"US",
    "sg:address":"1102 Lumi St",
    "sg:city":"Waipahu",
    "sg:classifiers":[
        {
            "category":"Food & Beverages",
            "subcategory":"Specialty",
            "type":"Retail Goods"
        }
    ],
    "sg:phone":"+1 808 678 1441",
    "sg:postcode":"96797",
    "sg:province":"HI",
    "sg:tags":[
        "health",
        "diet"
    ],
    "wof:name":"Herbalife Distributor",
    "wof:placetype":"venue"
},
  "geometry": {"coordinates":[-157.994823,21.408301],"type":"Point"}
}