{
  "type": "Feature",
  "properties": {
    "iso:country":"US",
    "sg:address":"2200 Kamehameha Hwy",
    "sg:city":"Honolulu",
    "sg:classifiers":[
        {
            "category":"Banks & Credit Unions",
            "subcategory":"Bank",
            "type":"Services"
        }
    ],
    "sg:phone":"+1 808 845 3905",
    "sg:postcode":"96819",
    "sg:province":"HI",
    "wof:name":"Tesoro Hawaii Fcu",
    "wof:placetype":"venue"
},
  "geometry": {"coordinates":[-157.883002,21.329946],"type":"Point"}
}