{
  "type": "Feature",
  "properties": {
    "iso:country":"US",
    "sg:address":"21 Kalanianaole Ave",
    "sg:city":"Hilo",
    "sg:classifiers":[
        {
            "category":"Shopping",
            "subcategory":"Bicycles & Sporting Goods",
            "type":"Retail Goods"
        }
    ],
    "sg:phone":"+1 808 935 2229",
    "sg:postcode":"96720",
    "sg:province":"HI",
    "sg:tags":[
        "surfboard"
    ],
    "wof:name":"Xtreme Image Inc",
    "wof:placetype":"venue"
},
  "geometry": {"coordinates":[-155.06333000000001,19.72272],"type":"Point"}
}