{
  "type": "Feature",
  "properties": {
    "addr:full":"1001 Bishop St Honolulu HI 96813",
    "addr:housenumber":"1001",
    "addr:postcode":"96813",
    "addr:street":"Bishop St",
    "iso:country":"US",
    "sg:address":"1001 Bishop St",
    "sg:city":"Honolulu",
    "sg:classifiers":[
        {
            "category":"Professional",
            "subcategory":"Accounting & Tax Preparation",
            "type":"Services"
        }
    ],
    "sg:phone":"+1 808 532 9200",
    "sg:postcode":"96813",
    "sg:province":"HI",
    "sg:tags":[
        "accountant"
    ],
    "sg:website":"www.marialowder.com",
    "wof:name":"Maria Lowder Inc",
    "wof:placetype":"venue"
},
  "geometry": {"coordinates":[-157.86039400000001,21.30931],"type":"Point"}
}