{
  "type": "Feature",
  "properties": {
    "iso:country":"US",
    "sg:address":"1580 Hanai Loop",
    "sg:city":"Honolulu",
    "sg:classifiers":[
        {
            "category":"Professional",
            "subcategory":"Employment Agencies",
            "type":"Services"
        }
    ],
    "sg:phone":"+1 808 845 4880",
    "sg:postcode":"96817",
    "sg:province":"HI",
    "sg:tags":[
        "opportunity",
        "help",
        "supply"
    ],
    "wof:name":"Fountain of Success Inc",
    "wof:placetype":"venue"
},
  "geometry": {"coordinates":[-157.86643699999999,21.336392],"type":"Point"}
}