{
  "type": "Feature",
  "properties": {
    "iso:country":"US",
    "sg:address":"114 Lopikane St",
    "sg:city":"Waianae",
    "sg:classifiers":[
        {
            "category":"Autos & Motor Vehicles",
            "subcategory":"Auto Supplies",
            "type":"Retail Goods"
        }
    ],
    "sg:phone":"+1 808 696 4218",
    "sg:postcode":"96792",
    "sg:province":"HI",
    "sg:tags":[
        "automobile",
        "parts"
    ],
    "wof:name":"Leeward Auto Parts Inc",
    "wof:placetype":"venue"
},
  "geometry": {"coordinates":[-158.17621399999999,21.425661],"type":"Point"}
}